Workbook
Name \0: #REF!
Name \0: #REF!
Name \a: #REF!
Name \a: #REF!
Name \B: #REF!
Name \B: #REF!
Name \c: #N/A
Name \D: #REF!
Name \DD: #REF!
Name \E: #REF!
Name \f: #N/A
Name \G: #REF!
Name \H: #REF!
Name \I: #REF!
Name \J: #REF!
Name \K: #REF!
Name \l: #N/A
Name \m: #N/A
Name \N: #REF!
Name \O: #REF!
Name \P: #REF!
Name \q: #N/A
Name \r: #N/A
Name \S: #REF!
Name \t: #N/A
Name \U: #REF!
Name \V: #REF!
Name \w: #N/A
Name \X: #REF!
Name \Z: #REF!
Name _________________________vvv1: {"bbtday",#N/A,FALSE,"ban0930";"banksday",#N/A,FALSE,"ban0930";"compday",#N/A,FALSE,"ban0930"}
Name _________________________vvv1: {"bbtday",#N/A,FALSE,"ban0930";"banksday",#N/A,FALSE,"ban0930";"compday",#N/A,FALSE,"ban0930"}
Name _________________________vvv1: {"bbtday",#N/A,FALSE,"ban0930";"banksday",#N/A,FALSE,"ban0930";"compday",#N/A,FALSE,"ban0930"}
Name _________________________vvv1: {"bbtday",#N/A,FALSE,"ban0930";"banksday",#N/A,FALSE,"ban0930";"compday",#N/A,FALSE,"ban0930"}
Name _________________________x1: {"compweek",#N/A,FALSE,"ban0930";"bankweek",#N/A,FALSE,"ban0930"}
Name _________________________x1: {"compweek",#N/A,FALSE,"ban0930";"bankweek",#N/A,FALSE,"ban0930"}
Name _________________________x1: {"compweek",#N/A,FALSE,"ban0930";"bankweek",#N/A,FALSE,"ban0930"}
Name _________________________x1: {"compweek",#N/A,FALSE,"ban0930";"bankweek",#N/A,FALSE,"ban0930"}
Name _________________________y1: {"bbtday",#N/A,FALSE,"ban0930";"banksday",#N/A,FALSE,"ban0930";"compday",#N/A,FALSE,"ban0930"}
Name _________________________y1: {"bbtday",#N/A,FALSE,"ban0930";"banksday",#N/A,FALSE,"ban0930";"compday",#N/A,FALSE,"ban0930"}
Name _________________________y1: {"bbtday",#N/A,FALSE,"ban0930";"banksday",#N/A,FALSE,"ban0930";"compday",#N/A,FALSE,"ban0930"}
Name _________________________y1: {"bbtday",#N/A,FALSE,"ban0930";"banksday",#N/A,FALSE,"ban0930";"compday",#N/A,FALSE,"ban0930"}
Name ________________________vvv1: {"bbtday",#N/A,FALSE,"ban0930";"banksday",#N/A,FALSE,"ban0930";"compday",#N/A,FALSE,"ban0930"}
Name ________________________vvv1: {"bbtday",#N/A,FALSE,"ban0930";"banksday",#N/A,FALSE,"ban0930";"compday",#N/A,FALSE,"ban0930"}
Name ________________________vvv1: {"bbtday",#N/A,FALSE,"ban0930";"banksday",#N/A,FALSE,"ban0930";"compday",#N/A,FALSE,"ban0930"}
Name ________________________vvv1: {"bbtday",#N/A,FALSE,"ban0930";"banksday",#N/A,FALSE,"ban0930";"compday",#N/A,FALSE,"ban0930"}
Name ________________________x1: {"compweek",#N/A,FALSE,"ban0930";"bankweek",#N/A,FALSE,"ban0930"}
Name ________________________x1: {"compweek",#N/A,FALSE,"ban0930";"bankweek",#N/A,FALSE,"ban0930"}
Name ________________________x1: {"compweek",#N/A,FALSE,"ban0930";"bankweek",#N/A,FALSE,"ban0930"}
Name ________________________x1: {"compweek",#N/A,FALSE,"ban0930";"bankweek",#N/A,FALSE,"ban0930"}
Name ________________________y1: {"bbtday",#N/A,FALSE,"ban0930";"banksday",#N/A,FALSE,"ban0930";"compday",#N/A,FALSE,"ban0930"}
Name ________________________y1: {"bbtday",#N/A,FALSE,"ban0930";"banksday",#N/A,FALSE,"ban0930";"compday",#N/A,FALSE,"ban0930"}
Name ________________________y1: {"bbtday",#N/A,FALSE,"ban0930";"banksday",#N/A,FALSE,"ban0930";"compday",#N/A,FALSE,"ban0930"}
Name ________________________y1: {"bbtday",#N/A,FALSE,"ban0930";"banksday",#N/A,FALSE,"ban0930";"compday",#N/A,FALSE,"ban0930"}
Name _______________________vvv1: {"bbtday",#N/A,FALSE,"ban0930";"banksday",#N/A,FALSE,"ban0930";"compday",#N/A,FALSE,"ban0930"}
Name _______________________vvv1: {"bbtday",#N/A,FALSE,"ban0930";"banksday",#N/A,FALSE,"ban0930";"compday",#N/A,FALSE,"ban0930"}
Name _______________________vvv1: {"bbtday",#N/A,FALSE,"ban0930";"banksday",#N/A,FALSE,"ban0930";"compday",#N/A,FALSE,"ban0930"}
Name _______________________vvv1: {"bbtday",#N/A,FALSE,"ban0930";"banksday",#N/A,FALSE,"ban0930";"compday",#N/A,FALSE,"ban0930"}
Name _______________________x1: {"compweek",#N/A,FALSE,"ban0930";"bankweek",#N/A,FALSE,"ban0930"}
Name _______________________x1: {"compweek",#N/A,FALSE,"ban0930";"bankweek",#N/A,FALSE,"ban0930"}

Sheet Capital Structure
D3: Bingo Industries | L3: DRAFT
D4: Capital Structure | L4: CONFIDENTIAL
D5: Data as of December 31, 2025
D6: (A$ millions)
D8: AUD to USD conversion | E8: 0.7
D9: SOFR / Libor | E9: 0.0434
D10: TLB Hedge % | E10: 0.55
D11: Swap Rate | E11: 0.0524
E13: Face | F13: Leverage | G13: Interest | H13: Effective | I13: Annual | K13: Credit | L13: Trading | P13: Effective | R13: Quarterly | S13: FY'25
D14: Description | E14: Value | F14: (Face) | G14: Rate | H14: Rate(1) | I14: Interest | J14: Maturity | K14: Rating | L14: Price | O14: Spread | P14: Rate | R14: Amort. | S14: Balances
D16: AUD RCF (A$75mm)(2) | E16: 29 | F16: =SUM($E$16:E16)/$E$27 -> 0.28199967 | G16: NA | H16: NA | I16: 0 | J16: 46217 | K16: Caa2/CCC+ | L16: =Pricing!E12 -> 67.75
D17: AUD United Asset Financing | E17: 2.671 | F17: =SUM($E$16:E17)/$E$27 -> 0.30797281 | G17: NA | H17: NA | I17: 0 | J17: 46948 | K17: Caa2/CCC+ | L17: NA
D18: $325 A$mm AUD Term Loan B First Lien (3) | E18: 311 | F18: =SUM($E$16:E18)/$E$27 -> 3.3321762 | G18: 350 | H18: =P18 -> 0.0641 | I18: =H18*E18 -> 19.9351 | J18: 46948 | K18: Caa2/CCC+ | L18: =Pricing!F12 -> 68.5 | O18: =G18/10000 -> 0.035 | P18: =$E$10*$E$11+(1-$E$10)*($E$9+O18) -> 0.0641 | R18: =(2.3*E18)/SUM($E$18:$E$20) -> 0.75853659 | S18: 312.813
D19: $100 A$mm AUD DDTL First Lien | E19: 96 | F19: =SUM($E$16:E19)/$E$27 -> 4.2656923 | G19: 350 | H19: =P19 -> 0.0641 | I19: =H19*E19 -> 6.1536 | J19: 46948 | K19: Caa2/CCC+ | L19: =Pricing!H12 -> 68.5 | O19: =G19/10000 -> 0.035 | P19: =$E$10*$E$11+(1-$E$10)*($E$9+O19) -> 0.0641 | R19: =(2.3*E19)/SUM($E$18:$E$20) -> 0.23414634 | S19: 96.75
D20: $375mm USD Term Loan B First Lien (3) | E20: 536 | F20: =SUM($E$16:E20)/$E$27 -> 9.4778241 | G20: 350 | H20: =P20 -> 0.0641 | I20: =H20*E20 -> 34.3576 | J20: 46948 | K20: Caa2/CCC+ | L20: =Pricing!G12 -> 67.75 | O20: =G20/10000 -> 0.035 | P20: =$E$10*$E$11+(1-$E$10)*($E$9+O20) -> 0.0641 | R20: =(2.3*E20)/SUM($E$18:$E$20) -> 1.3073171 | S20: 360.938
D21: SHL DDTL (A$100mm)(4) | E21: 51.2 | F21: =SUM($E$16:E21)/$E$27 -> 9.9756994 | G21: PIK | H21: 0.13 | I21: 0 | J21: 49188 | K21: Caa2/CCC+ | L21: NA
D22: Total Debt | E22: =SUM(E16:E21) -> 1025.871 | F22: =E22/E27 -> 9.9756994 | I22: =SUM(I16:I21) -> 60.4463 | K22: Caa2/CCC+
D23: Less: Cash and Equivalents(2) | E23: =-E35 -> -52
D24: Net Debt | E24: =SUM(E22:E23) -> 973.871 | F24: =E24/$E$27 -> 9.4700448
D26: Memo:
D27: LTM 2Q'26 Adj EBITDA | E27: =SUM(Historicals!U84:X84) -> 102.837
D29: Current Liquidity
D30: RCF Capacity | E30: 75
D31: Less: Outstanding Borrowings | E31: =-E16 -> -29
D32: Less: Covenant Trigger(5) | E32: -45
D33: RCF Availability (Pre-Covenant Trigger) | E33: =SUM(E30:E32) -> 1
D34: Plus: Remaining SHL DDTL (A$100mm) | E34: 60
D35: Plus: Cash and Equivalents(2) | E35: 52
D36: Total Liquidity | E36: =SUM(E33:E35) -> 113

Sheet Historicals
D3: ='Capital Structure'!D3 -> Bingo Industries | AD3: DRAFT
D4: Spread Financials | AD4: CONFIDENTIAL
D5: Data as of 2Q'26
D6: ($ millions)
D9: Start | F9: 44287 | G9: =EOMONTH(F9,2)+1 -> 44378 | H9: =EOMONTH(G9,2)+1 -> 44470 | I9: =EOMONTH(H9,2)+1 -> 44562 | J9: =EOMONTH(I9,2)+1 -> 44652 | K9: =EOMONTH(J9,2)+1 -> 44743 | L9: =EOMONTH(K9,2)+1 -> 44835 | M9: =EOMONTH(L9,2)+1 -> 44927 | N9: =EOMONTH(M9,2)+1 -> 45017 | ... X9: =EOMONTH(W9,2)+1 -> 45931 | Z9: 44562 | AA9: =EOMONTH(Z9,12) -> 44957 | AB9: =EOMONTH(AA9,12) -> 45322 | AC9: =EOMONTH(AB9,12) -> 45688 | AD9: =EOMONTH(AC9,12) -> 46053
D10: End | F10: =EOMONTH(F9,2) -> 44377 | G10: =EOMONTH(F10,3) -> 44469 | H10: =EOMONTH(G10,3) -> 44561 | I10: =EOMONTH(H10,3) -> 44651 | J10: =EOMONTH(I10,3) -> 44742 | K10: =EOMONTH(J10,3) -> 44834 | L10: =EOMONTH(K10,3) -> 44926 | M10: =EOMONTH(L10,3) -> 45016 | N10: =EOMONTH(M10,3) -> 45107 | ... X10: =EOMONTH(W10,3) -> 46022 | Z10: 44926 | AA10: =EOMONTH(Z10,12) -> 45291 | AB10: =EOMONTH(AA10,12) -> 45657 | AC10: =EOMONTH(AB10,12) -> 46022 | AD10: =EOMONTH(AC10,12) -> 46387
D11: Fiscal Year | F11: 2022 | G11: 2022 | H11: 2022 | I11: 2022 | J11: 2022 | K11: 2023 | L11: 2023 | M11: 2023 | N11: 2023 | O11: 2024 | P11: 2024 | Q11: 2024 | R11: 2024 | S11: 2025 | T11: 2025 | U11: 2025 | V11: 2025 | W11: 2026 | X11: 2026 | Z11: 2022 | AA11: 2023 | AB11: 2024 | AC11: 2025 | AD11: LTM
D12: Quarter | F12: 1Q | G12: 1Q | H12: 2Q | I12: 3Q | J12: 4Q | K12: 1Q | L12: 2Q | M12: 3Q | N12: 4Q | O12: 1Q | P12: 2Q | Q12: 3Q | R12: 4Q | S12: 1Q | T12: 2Q | U12: 3Q | V12: 4Q | W12: 4Q | X12: 4Q
D13: Identifier (Qtr) | F13: =F12&RIGHT(F11,2) -> 1Q22 | G13: =G12&RIGHT(G11,2) -> 1Q22 | H13: =H12&RIGHT(H11,2) -> 2Q22 | I13: =I12&RIGHT(I11,2) -> 3Q22 | J13: =J12&RIGHT(J11,2) -> 4Q22 | K13: =K12&RIGHT(K11,2) -> 1Q23 | L13: =L12&RIGHT(L11,2) -> 2Q23 | M13: =M12&RIGHT(M11,2) -> 3Q23 | ... Y13: =Y12&RIGHT(Y11,2) | Z13: ="FY-"&RIGHT(Z11,2) -> FY-22 | AA13: ="FY-"&RIGHT(AA11,2) -> FY-23 | AB13: ="FY-"&RIGHT(AB11,2) -> FY-24 | AC13: ="FY-"&RIGHT(AC11,2) -> FY-25 | AD13: ="FY-"&RIGHT(AD11,2) -> FY-TM
F15: 4Q21 | G15: 1Q22 | H15: 2Q22 | I15: 3Q22 | J15: 4Q22 | K15: 1Q23 | L15: 2Q23 | M15: 3Q23 | N15: 4Q23 | O15: 1Q24 | P15: 2Q24 | Q15: 3Q24 | R15: 4Q24 | S15: 1Q25 | T15: 2Q25 | U15: 3Q25 | V15: 4Q25 | W15: 1Q26 | X15: 2Q26 | Z15: =Z13 -> FY-22 | AA15: =AA13 -> FY-23 | AB15: =AB13 -> FY-24 | AC15: =AC13 -> FY-25 | AD15: LTM 2Q26
F16: 44377 | G16: 44469 | H16: 44561 | I16: 44651 | J16: 44742 | K16: 44834 | L16: 44926 | M16: 45016 | N16: 45107 | O16: 45199 | P16: 45291 | Q16: 45382 | R16: 45473 | S16: 45565 | T16: 45657 | U16: 45747 | V16: 45838 | W16: =W10 -> 45930 | X16: =X10 -> 46022 | Z16: =J16 -> 44742 | AA16: =N16 -> 45107 | AB16: =R16 -> 45473 | AC16: =V16 -> 45838 | AD16: =X16 -> 46022
C18: x | D18: Income Statement
D20: Revenues
D21: Collections revenue | I21: 49.3 | J21: 54.8 | K21: 66.1 | L21: 70.8 | M21: 72.2 | N21: 74.5 | O21: 85.2 | P21: 77.8 | Q21: 74.8 | R21: 77.5 | S21: 83.8 | T21: 77.9 | AA21: =SUMIF($G$11:$V$11,AA$11,$G21:$V21) -> 283.6 | AB21: =SUMIF($G$11:$V$11,AB$11,$G21:$V21) -> 315.3
D22: Post-Collections revenue | I22: 82.9 | J22: 87.8 | K22: 119.4 | L22: 109.6 | M22: 113.4 | N22: 118.1 | O22: 124.4 | P22: 102.6 | Q22: 102.8 | R22: 115 | S22: 130.1 | T22: 114.5 | AA22: =SUMIF($G$11:$V$11,AA$11,$G22:$V22) -> 460.5 | AB22: =SUMIF($G$11:$V$11,AB$11,$G22:$V22) -> 444.8
D23: Other revenue | I23: 8.6 | J23: 7.9 | K23: 8.9 | L23: 10 | M23: 8.3 | N23: 9.7 | O23: 8.6 | P23: 7.2 | Q23: 6.7 | R23: 4.6 | S23: 4.4 | T23: 3.4 | AA23: =SUMIF($G$11:$V$11,AA$11,$G23:$V23) -> 36.9 | AB23: =SUMIF($G$11:$V$11,AB$11,$G23:$V23) -> 27.1
D24: Eliminations | I24: -26.5 | J24: -15.3 | K24: -33.1 | L24: -34.8 | M24: -31.4 | N24: -34.9 | O24: -35.3 | P24: -31.9 | Q24: -31.2 | R24: -31.9 | S24: -37.9 | T24: -34.3 | AA24: =SUMIF($G$11:$V$11,AA$11,$G24:$V24) -> -134.2 | AB24: =SUMIF($G$11:$V$11,AB$11,$G24:$V24) -> -130.3
D25: Total Revenues | G25: 70.474 | H25: 125.6 | I25: =SUM(I21:I24) -> 114.3 | J25: =SUM(J21:J24) -> 135.2 | K25: =SUM(K21:K24) -> 161.3 | L25: =SUM(L21:L24) -> 155.6 | M25: =SUM(M21:M24) -> 162.5 | N25: =SUM(N21:N24) -> 167.4 | O25: =SUM(O21:O24) -> 182.9 | P25: =SUM(P21:P24) -> 155.7 | ... T25: =SUM(T21:T24) -> 161.5 | U25: 157.698 | V25: =AC25-SUM(S25:U25) -> 176.267 | W25: 144.874 | X25: 138.06 | Z25: =SUMIF($G$11:$S$11,Z$11,$G25:$T25) -> 445.574 | AA25: =SUMIF($G$11:$S$11,AA$11,$G25:$T25) -> 646.8 | AB25: =SUMIF($G$11:$S$11,AB$11,$G25:$T25) -> 656.9 | AC25: 675.865 | AD25: =SUM(U25:X25) -> 616.899
D26: Post-Collections % of Total | I26: =I22/SUM(I21:I22) -> 0.62708018 | J26: =J22/SUM(J21:J22) -> 0.61570827 | K26: =K22/SUM(K21:K22) -> 0.64366577 | L26: =L22/SUM(L21:L22) -> 0.6075388 | M26: =M22/SUM(M21:M22) -> 0.61099138 | N26: =N22/SUM(N21:N22) -> 0.61318795 | O26: =O22/SUM(O21:O22) -> 0.59351145 | P26: =P22/SUM(P21:P22) -> 0.56873614 | ... T26: =T22/SUM(T21:T22) -> 0.59511435 | AG26: =191.3-91.6 -> 99.7
D27: Check: Segment Sum | I27: 114.3 | J27: 135.2 | K27: 161.3 | L27: 155.6 | M27: 162.5 | N27: 167.4 | O27: 182.9 | P27: 155.7 | Q27: 153.1 | R27: 165.2 | S27: 180.4 | T27: 161.5 | W27: 144.874 | X27: 138.06 | AA27: 646.8 | AB27: 656.9 | AC27: 675.865
I28: =I25-I27 -> 0 | J28: =J25-J27 -> 0 | K28: =K25-K27 -> 0 | L28: =L25-L27 -> 0 | M28: =M25-M27 -> 0 | N28: =N25-N27 -> 0 | O28: =O25-O27 -> 0 | P28: =P25-P27 -> 0 | ... T28: =T25-T27 -> 0 | W28: =W25-W27 -> 0 | X28: =X25-X27 -> 0 | AA28: =AA25-AA27 -> 0 | AB28: =AB25-AB27 -> 0 | AC28: =SUM(R28:V28) -> 0
D30: Tipping & Transportation Costs | G30: -27.671 | H30: -48.853 | I30: -46.599 | J30: -61.344 | K30: -71.517 | L30: -62.521 | M30: -70.753 | N30: -76.695 | O30: -74.914 | P30: -63.685 | Q30: -62.419 | R30: -71.246 | S30: -77.513 | T30: -67.586 | U30: -70.76 | V30: -84.672 | W30: -50.818 | X30: -50.318 | Z30: =SUMIF($G$11:$X$11,Z$11,$G30:$X30) -> -184.467 | AA30: =SUMIF($G$11:$X$11,AA$11,$G30:$X30) -> -281.486 | AB30: =SUMIF($G$11:$X$11,AB$11,$G30:$X30) -> -272.264 | AC30: =SUMIF($G$11:$X$11,AC$11,$G30:$X30) -> -300.531 | AD30: =SUM(U30:X30) -> -256.568
D31: Property expenses | G31: -1.389 | H31: -2.774 | I31: -2.513 | J31: -3.433 | K31: -3.461 | L31: -3.71 | M31: -4.089 | N31: -4.224 | O31: -3.644 | P31: -3.628 | Q31: -4.208 | R31: -4.871 | S31: -4.045 | T31: -3.781 | U31: -4.529 | V31: -5.233 | W31: -4.502 | X31: -4.239 | Z31: =SUMIF($G$11:$X$11,Z$11,$G31:$X31) -> -10.109 | AA31: =SUMIF($G$11:$X$11,AA$11,$G31:$X31) -> -15.484 | AB31: =SUMIF($G$11:$X$11,AB$11,$G31:$X31) -> -16.351 | AC31: =SUMIF($G$11:$X$11,AC$11,$G31:$X31) -> -17.588 | AD31: =SUM(U31:X31) -> -18.503
D32: Lender Deck COGS Adjustment | G32: 0 | H32: 0 | I32: 0.733 | J32: 0 | K32: 1.697 | L32: 2.348 | M32: 0.519 | N32: 7.906 | O32: -0.624 | P32: -0.603 | Q32: 0.562 | R32: 2.18 | S32: 0.9 | T32: 1.5 | U32: 0 | V32: -1.1 | W32: 1.6 | X32: 1.2 | Z32: =SUMIF($G$11:$X$11,Z$11,$G32:$X32) -> 0.733 | AA32: =SUMIF($G$11:$X$11,AA$11,$G32:$X32) -> 12.47 | AB32: =SUMIF($G$11:$X$11,AB$11,$G32:$X32) -> 1.515 | AC32: =SUMIF($G$11:$X$11,AC$11,$G32:$X32) -> 1.3 | AD32: =SUM(U32:X32) -> 1.7
D33: Cost of goods sold | G33: =SUM(G30:G32) -> -29.06 | H33: =SUM(H30:H32) -> -51.627 | I33: =SUM(I30:I32) -> -48.379 | J33: =SUM(J30:J32) -> -64.777 | K33: =SUM(K30:K32) -> -73.281 | L33: =SUM(L30:L32) -> -63.883 | M33: =SUM(M30:M32) -> -74.323 | N33: =SUM(N30:N32) -> -73.013 | ... U33: =SUM(U30:U32) -> -75.289 | V33: =AC33-SUM(S33:U33) -> -91.005 | W33: =SUM(W30:W32) -> -53.72 | X33: =SUM(X30:X32) -> -53.357 | Z33: =SUM(Z30:Z32) -> -193.843 | AA33: =SUM(AA30:AA32) -> -284.5 | AB33: =SUM(AB30:AB32) -> -287.1 | AC33: =SUM(AC30:AC32) -> -316.819 | AD33: =SUM(U33:X33) -> -273.371
D35: Gross Profit | G35: =SUM(G33,G25) -> 41.414 | H35: =SUM(H33,H25) -> 73.973 | I35: =SUM(I33,I25) -> 65.921 | J35: =SUM(J33,J25) -> 70.423 | K35: =SUM(K33,K25) -> 88.019 | L35: =SUM(L33,L25) -> 91.717 | M35: =SUM(M33,M25) -> 88.177 | N35: =SUM(N33,N25) -> 94.387 | ... U35: =SUM(U33,U25) -> 82.409 | V35: =AC35-SUM(S35:U35) -> 85.262 | W35: =SUM(W33,W25) -> 91.154 | X35: =SUM(X33,X25) -> 84.703 | Z35: =SUM(Z33,Z25) -> 251.731 | AA35: =SUM(AA33,AA25) -> 362.3 | AB35: =SUM(AB33,AB25) -> 369.8 | AC35: =SUM(AC33,AC25) -> 359.046 | AD35: =SUM(U35:X35) -> 343.528
D36: Check: Lender Deck | G36: 63.907 | H36: =H35 -> 73.973 | I36: 65.921 | J36: =J35 -> 70.423 | K36: 88.019 | L36: 91.717 | M36: 88.177 | N36: 94.387 | O36: 103.718 | P36: 87.784 | Q36: 87.035 | R36: 91.263 | S36: =191.3-91.6 -> 99.7 | T36: 91.6 | U36: =U35 -> 82.409 | V36: 93.1 | W36: =175.9-84.7 -> 91.2 | X36: 84.7 | Z36: =SUMIF($G$11:$S$11,Z$11,$G36:$S36) -> 274.224 | AA36: =SUMIF($G$11:$S$11,AA$11,$G36:$S36) -> 362.3 | AB36: =SUMIF($G$11:$S$11,AB$11,$G36:$S36) -> 369.8 | AC36: =SUM(S36:V36) -> 366.809 | AD36: =SUM(U36:X36) -> 351.409
G37: =G35-G36 -> -22.493 | I37: =I35-I36 -> 0 | K37: =K35-K36 -> 0 | L37: =L35-L36 -> 0 | M37: =M35-M36 -> 0 | N37: =N35-N36 -> 0 | O37: =O35-O36 -> 0 | P37: =P35-P36 -> 0 | Q37: =Q35-Q36 -> 0 | R37: =R35-R36 -> 0 | ... T37: =T35-T36 -> 0.033 | W37: =W35-W36 -> -0.046 | X37: =X35-X36 -> 0.003 | Z37: =Z35-Z36 -> -22.493 | AA37: =AA35-AA36 -> 0 | AB37: =AB35-AB36 -> 0 | AC37: =SUM(R37:V37) -> 0.075
D38: Gross Profit Margin | G38: =G35 / G25 -> 0.58764935 | H38: =H35 / H25 -> 0.58895701 | I38: =I35 / I25 -> 0.57673666 | J38: =J35 / J25 -> 0.52088018 | K38: =K35 / K25 -> 0.54568506 | L38: =L35 / L25 -> 0.58944087 | M38: =M35 / M25 -> 0.54262769 | N38: =N35 / N25 -> 0.5638411 | ... X38: =X35 / X25 -> 0.61352311 | Z38: =Z35 / Z25 -> 0.56495891 | AA38: =AA35 / AA25 -> 0.56014224 | AB38: =AB35 / AB25 -> 0.56294718 | AC38: =AC35 / AC25 -> 0.53123923
D40: Trucks and machinery costs | G40: -4.217 | H40: -10.364 | I40: -8.318 | J40: -8.736 | K40: -10.721 | L40: -11.56 | M40: -12.005 | N40: -11.298 | O40: -11.595 | P40: -11.306 | Q40: -11.433 | R40: -11.841 | S40: -13.411 | T40: -11.538 | U40: -11.76 | V40: -12.206 | W40: -12.601 | X40: -12.166 | Z40: =SUMIF($G$11:$X$11,Z$11,$G40:$X40) -> -31.635 | AA40: =SUMIF($G$11:$X$11,AA$11,$G40:$X40) -> -45.584 | AB40: =SUMIF($G$11:$X$11,AB$11,$G40:$X40) -> -46.175 | AC40: =SUMIF($G$11:$X$11,AC$11,$G40:$X40) -> -48.915 | AD40: =SUM(U40:X40) -> -48.733
D41: Administrative expenses | G41: -0.908 | H41: -1.153 | I41: -1.121 | J41: -3.179 | K41: -0.843 | L41: 0.601 | M41: -1.937 | N41: -9.295 | O41: -3.046 | P41: -2.452 | Q41: -2.959 | R41: 6.322 | S41: -3.322 | T41: -2.864 | U41: -3.056 | V41: -4.424 | W41: -1.924 | X41: -3.124 | Z41: =SUMIF($G$11:$X$11,Z$11,$G41:$X41) -> -6.361 | AA41: =SUMIF($G$11:$X$11,AA$11,$G41:$X41) -> -11.474 | AB41: =SUMIF($G$11:$X$11,AB$11,$G41:$X41) -> -2.135 | AC41: =SUMIF($G$11:$X$11,AC$11,$G41:$X41) -> -13.666 | AD41: =SUM(U41:X41) -> -12.528
D42: Employee benefits expenses | G42: -19.499 | H42: -36.769 | I42: -36.53 | J42: -39.573 | K42: -41.608 | L42: -42.826 | M42: -42.352 | N42: -42.906 | O42: -45.1 | P42: -43.02 | Q42: -42.241 | R42: -46.434 | S42: -46.05 | T42: -45.626 | U42: -42.259 | V42: -43.492 | W42: -43.489 | X42: -40.737 | Z42: =SUMIF($G$11:$X$11,Z$11,$G42:$X42) -> -132.371 | AA42: =SUMIF($G$11:$X$11,AA$11,$G42:$X42) -> -169.692 | AB42: =SUMIF($G$11:$X$11,AB$11,$G42:$X42) -> -176.795 | AC42: =SUMIF($G$11:$X$11,AC$11,$G42:$X42) -> -177.427 | AD42: =SUM(U42:X42) -> -169.977
D43: Interest income | G43: 0.12 | H43: 0.199 | I43: 0.171 | J43: 0.779 | K43: 0.557 | L43: 15.9 | M43: 0.703 | N43: -14.263 | O43: 1.041 | P43: 0.837 | Q43: 0.638 | R43: 0.941 | S43: 0.364 | T43: 0.55 | U43: 0.182 | V43: 0.328 | W43: 0 | X43: 0.129 | Z43: =SUMIF($G$11:$X$11,Z$11,$G43:$X43) -> 1.269 | AA43: =SUMIF($G$11:$X$11,AA$11,$G43:$X43) -> 2.897 | AB43: =SUMIF($G$11:$X$11,AB$11,$G43:$X43) -> 3.457 | AC43: =SUMIF($G$11:$X$11,AC$11,$G43:$X43) -> 1.424 | AD43: =SUM(U43:X43) -> 0.639
D44: Acquisition expenses | G44: -23.4 | H44: -4.922 | I44: -1.205 | J44: -21.451 | K44: -0.162 | L44: 0.081 | M44: 0.08 | N44: 0.001 | O44: 0 | P44: 0 | Q44: 0 | R44: 0 | S44: 0 | T44: 0 | U44: 0 | V44: 0 | W44: 0 | X44: 0 | Z44: =SUMIF($G$11:$X$11,Z$11,$G44:$X44) -> -50.978 | AA44: =SUMIF($G$11:$X$11,AA$11,$G44:$X44) -> -8.6736174e-19 | AB44: =SUMIF($G$11:$X$11,AB$11,$G44:$X44) -> 0 | AC44: =SUMIF($G$11:$X$11,AC$11,$G44:$X44) -> 0 | AD44: =SUM(U44:X44) -> 0
D45: Oth. income/(expenses) | G45: -0.795 | H45: -11.573 | I45: -8.075 | J45: 16.632 | K45: -9.673 | L45: -13.139 | M45: -8.075 | N45: 17.799 | O45: -10.463 | P45: -7.069 | Q45: -4.316 | R45: 8.723 | S45: -9.936 | T45: -5.327 | U45: -0.169 | V45: -10.582 | W45: -6.136 | X45: -6.056 | Z45: =SUMIF($G$11:$X$11,Z$11,$G45:$X45) -> -3.811 | AA45: =SUMIF($G$11:$X$11,AA$11,$G45:$X45) -> -13.088 | AB45: =SUMIF($G$11:$X$11,AB$11,$G45:$X45) -> -13.125 | AC45: =SUMIF($G$11:$X$11,AC$11,$G45:$X45) -> -26.014 | AD45: =SUM(U45:X45) -> -22.943
D46: Lender Deck COGS Adjustment | G46: =-G32 -> 0 | H46: =-H32 -> 0 | I46: =-I32 -> -0.733 | J46: =-J32 -> 0 | K46: =-K32 -> -1.697 | L46: =-L32 -> -2.348 | M46: =-M32 -> -0.519 | N46: =-N32 -> -7.906 | ... X46: =-X32 -> -1.2 | Z46: =SUMIF($G$11:$X$11,Z$11,$G46:$X46) -> -0.733 | AA46: =SUMIF($G$11:$X$11,AA$11,$G46:$X46) -> -12.47 | AB46: =SUMIF($G$11:$X$11,AB$11,$G46:$X46) -> -1.515 | AC46: =SUMIF($G$11:$X$11,AC$11,$G46:$X46) -> -1.3 | AD46: =SUM(U46:X46) -> -1.7
D47: EBITDA | G47: =SUM(G40:G46,G35) -> -7.285 | H47: =SUM(H40:H46,H35) -> 9.391 | I47: =SUM(I40:I46,I35) -> 10.11 | J47: =SUM(J40:J46,J35) -> 14.895 | K47: =SUM(K40:K46,K35) -> 23.872 | L47: =SUM(L40:L46,L35) -> 38.426 | M47: =SUM(M40:M46,M35) -> 24.072 | N47: =SUM(N40:N46,N35) -> 26.519 | ... X47: =SUM(X40:X46,X35) -> 21.549 | Z47: =SUM(Z40:Z46,Z35) -> 27.111 | AA47: =SUM(AA40:AA46,AA35) -> 112.889 | AB47: =SUM(AB40:AB46,AB35) -> 133.512 | AC47: =SUM(AC40:AC46,AC35) -> 93.148 | AD47: =SUM(U47:X47) -> 88.286
D48: EBITDA Margin | G48: =G47 / G25 -> -0.10337146 | H48: =H47 / H25 -> 0.074769108 | I48: =I47 / I25 -> 0.088451444 | J48: =J47 / J25 -> 0.11017012 | K48: =K47 / K25 -> 0.14799752 | L48: =L47 / L25 -> 0.24695373 | M48: =M47 / M25 -> 0.14813538 | N48: =N47 / N25 -> 0.15841697 | ... X48: =X47 / X25 -> 0.15608431 | Z48: =Z47 / Z25 -> 0.060845112 | AA48: =AA47 / AA25 -> 0.17453463 | AB48: =AB47 / AB$25 -> 0.20324555 | AC48: =AC47 / AC25 -> 0.13782042
D50: Impairment Loss on Intangibles | G50: 0 | H50: 0 | I50: 0 | J50: -155 | K50: 0 | L50: 0 | M50: 0 | N50: -385 | O50: 0 | P50: 0 | Q50: 0 | R50: -160 | S50: 0 | T50: 0 | U50: 0 | V50: 0 | X50: 0 | Z50: =SUMIF($G$11:$X$11,Z$11,$G50:$X50) -> -155 | AA50: =SUMIF($G$11:$X$11,AA$11,$G50:$X50) -> -385 | AB50: =SUMIF($G$11:$X$11,AB$11,$G50:$X50) -> -160 | AC50: =SUMIF($G$11:$X$11,AC$11,$G50:$X50) -> 0 | AD50: =SUM(U50:X50) -> 0
D51: Net finance costs | G51: -9.214 | H51: -12.924 | I51: -13.99 | J51: -64.132 | K51: -30.063 | L51: -42.145 | M51: -38.428 | N51: -41.045 | O51: -43.832 | P51: -45.464 | Q51: -46.343 | R51: -47.332 | S51: -48.358 | T51: 9.771 | U51: -25.391 | V51: -22.76 | W51: -21.516 | X51: -20.359 | Z51: =SUMIF($G$11:$X$11,Z$11,$G51:$X51) -> -100.26 | AA51: =SUMIF($G$11:$X$11,AA$11,$G51:$X51) -> -151.681 | AB51: =SUMIF($G$11:$X$11,AB$11,$G51:$X51) -> -182.971 | AC51: =SUMIF($G$11:$X$11,AC$11,$G51:$X51) -> -86.738 | AD51: =SUM(U51:X51) -> -90.026
D52: Depreciation & amortization | G52: -9.96 | H52: -18.533 | I52: -19.817 | J52: -30.294 | K52: -26.456 | L52: -26.075 | M52: -25.29 | N52: -27.747 | O52: -27.113 | P52: -26.685 | Q52: -26.108 | R52: -28.763 | S52: -27.212 | T52: -26.945 | U52: -26.258 | V52: -25.487 | W52: -24.929 | X52: -28.377 | Z52: =SUMIF($G$11:$X$11,Z$11,$G52:$X52) -> -78.604 | AA52: =SUMIF($G$11:$X$11,AA$11,$G52:$X52) -> -105.568 | AB52: =SUMIF($G$11:$X$11,AB$11,$G52:$X52) -> -108.669 | AC52: =SUMIF($G$11:$X$11,AC$11,$G52:$X52) -> -105.902 | AD52: =SUM(U52:X52) -> -105.051
D53: EBT | G53: =SUM(G47,G50:G52) -> -26.459 | H53: =SUM(H47,H50:H52) -> -22.066 | I53: =SUM(I47,I50:I52) -> -23.697 | J53: =SUM(J47,J50:J52) -> -234.531 | K53: =SUM(K47,K50:K52) -> -32.647 | L53: =SUM(L47,L50:L52) -> -29.794 | M53: =SUM(M47,M50:M52) -> -39.646 | N53: =SUM(N47,N50:N52) -> -427.273 | ... X53: =SUM(X47,X50:X52) -> -27.187 | Z53: =Z47+SUM(Z50:Z52) -> -306.753 | AA53: =AA47+SUM(AA50:AA52) -> -529.36 | AB53: =AB47+SUM(AB50:AB52) -> -318.128 | AC53: =AC47+SUM(AC50:AC52) -> -99.492 | AD53: =SUM(U53:X53) -> -106.791
Z54: =SUMIF($G$11:$X$11,Z$11,$G54:$X54) -> 0 | AA54: =SUMIF($G$11:$X$11,AA$11,$G54:$X54) -> 0 | AB54: =SUMIF($G$11:$X$11,AB$11,$G54:$X54) -> 0 | AC54: =SUMIF($G$11:$X$11,AC$11,$G54:$X54) -> 0
D55: Income tax expense | G55: 0 | H55: 0 | I55: 0 | J55: 43 | K55: 0 | L55: 0 | M55: 7.122 | N55: 60.634 | O55: 2.762 | P55: 7.661 | Q55: 5.753 | R55: 94.989 | S55: 5.144 | T55: 6.29 | U55: 8.705 | V55: 0.987 | W55: 3.526 | X55: 9.281 | Z55: =SUMIF($G$11:$X$11,Z$11,$G55:$X55) -> 43 | AA55: =SUMIF($G$11:$X$11,AA$11,$G55:$X55) -> 67.756 | AB55: =SUMIF($G$11:$X$11,AB$11,$G55:$X55) -> 111.165 | AC55: =SUMIF($G$11:$X$11,AC$11,$G55:$X55) -> 21.126 | AD55: =SUM(U55:X55) -> 22.499
D56: Comprehensive Net Income (Loss) | G56: =SUM(G53:G55) -> -26.459 | H56: =SUM(H53:H55) -> -22.066 | I56: =SUM(I53:I55) -> -23.697 | J56: =SUM(J53:J55) -> -191.531 | K56: =SUM(K53:K55) -> -32.647 | L56: =SUM(L53:L55) -> -29.794 | M56: =SUM(M53:M55) -> -32.524 | N56: =SUM(N53:N55) -> -366.639 | ... U56: =SUM(U53:U55) -> -17.597 | V56: =AC56-SUM(S56:U56) -> -31.274 | W56: =SUM(W53:W55) -> -17.515 | X56: =SUM(X53:X55) -> -17.906 | Z56: =SUM(Z53:Z55) -> -263.753 | AA56: =SUM(AA53:AA55) -> -461.604 | AB56: =SUM(AB53:AB55) -> -206.963 | AC56: =SUM(AC53:AC55) -> -78.366 | AD56: =SUM(U56:X56) -> -84.292
D58: Net fair value loss on cash flow hedges | G58: 0 | H58: 8.189 | I58: 0 | J58: 41.551 | K58: 0 | L58: -0.597 | M58: 0 | N58: 0 | O58: 0 | P58: 1.12 | Q58: 0 | R58: 0 | S58: 0 | T58: -9.164 | U58: 0 | V58: -12.109 | W58: 2.25 | X58: -9.056 | Z58: =SUMIF($G$11:$X$11,Z$11,$G58:$X58) -> 49.74 | AA58: =SUMIF($G$11:$X$11,AA$11,$G58:$X58) -> -0.597 | AB58: =SUMIF($G$11:$X$11,AB$11,$G58:$X58) -> 1.12 | AC58: =SUMIF($G$11:$X$11,AC$11,$G58:$X58) -> -21.273 | AD58: =SUM(U58:X58) -> -18.915
D59: Income tax relating to these items | G59: 0 | H59: -2.457 | I59: 0 | J59: -14.922 | K59: 0 | L59: 0 | M59: 0 | N59: 0 | O59: 0 | P59: -10.216 | Q59: 0 | R59: 0 | S59: 0 | T59: 2.749 | U59: 0 | V59: 3.633 | W59: -0.675 | X59: 2.846 | Z59: =SUMIF($G$11:$X$11,Z$11,$G59:$X59) -> -17.379 | AA59: =SUMIF($G$11:$X$11,AA$11,$G59:$X59) -> 0 | AB59: =SUMIF($G$11:$X$11,AB$11,$G59:$X59) -> -10.216 | AC59: =SUMIF($G$11:$X$11,AC$11,$G59:$X59) -> 6.382 | AD59: =SUM(U59:X59) -> 5.804
D60: Net Income (Loss) | G60: =SUM(G56:G59) -> -26.459 | H60: =SUM(H56:H59) -> -16.334 | I60: =SUM(I56:I59) -> -23.697 | J60: =SUM(J56:J59) -> -164.902 | K60: =SUM(K56:K59) -> -32.647 | L60: =SUM(L56:L59) -> -30.391 | M60: =SUM(M56:M59) -> -32.524 | N60: =SUM(N56:N59) -> -366.639 | ... U60: =SUM(U56:U59) -> -17.597 | V60: =AC60-SUM(S60:U60) -> -39.75 | W60: =SUM(W56:W59) -> -15.94 | X60: =SUM(X56:X59) -> -24.116 | Z60: =SUM(Z56:Z59) -> -231.392 | AA60: =SUM(AA56:AA59) -> -462.201 | AB60: =SUM(AB56:AB59) -> -216.059 | AC60: =SUM(AC56:AC59) -> -93.257 | AD60: =SUM(U60:X60) -> -97.403
D61: Check: Lender Deck | G61: -26.459 | H61: -16.288 | I61: -23.975 | J61: =Z61-SUM(G61:I61) -> -163.366 | K61: -32.753 | L61: -29.769 | M61: -32.624 | N61: -367.263 | O61: -33.002 | P61: -48.147 | Q61: -40.73 | R61: -94.106 | S61: -43.961 | T61: 8.082 | U61: -17.597 | W61: -15.762 | X61: -24.116 | Z61: -230.088 | AA61: =SUMIF($G$11:$S$11,AA$11,$G61:$S61) -> -462.409 | AB61: =SUMIF($G$11:$S$11,AB$11,$G61:$S61) -> -215.985 | AC61: =-93.257 -> -93.257 | AD61: =SUM(U61:X61) -> -57.475
G62: =G60-G61 -> 0 | H62: =H60-H61 -> -0.046 | I62: =I60-I61 -> 0.278 | J62: =J60-J61 -> -1.536 | K62: =K60-K61 -> 0.106 | L62: =L60-L61 -> -0.622 | M62: =M60-M61 -> 0.1 | N62: =N60-N61 -> 0.624 | ... U62: =U60-U61 -> 0 | W62: =W60-W61 -> -0.178 | X62: =X60-X61 -> 0 | Z62: =Z60-Z61 -> -1.304 | AA62: =AA60-AA61 -> 0.208 | AB62: =AB60-AB61 -> -0.074 | AC62: =AC60-AC61 -> 0
D64: Recycle and Resource Operations Pty Ltd (RRO) EBITDA | G64: =G47 -> -7.285 | H64: =H47 -> 9.391 | I64: =I47 -> 10.11 | J64: =J47 -> 14.895 | K64: =K47 -> 23.872 | L64: =L47 -> 38.426 | M64: =M47 -> 24.072 | N64: =N47 -> 26.519 | ... X64: =X47 -> 21.549 | Z64: =SUMIF($G$11:$X$11,Z$11,$G64:$X64) -> 27.111 | AA64: =SUMIF($G$11:$X$11,AA$11,$G64:$X64) -> 112.889 | AB64: =SUMIF($G$11:$X$11,AB$11,$G64:$X64) -> 133.512 | AC64: =SUMIF($G$11:$X$11,AC$11,$G64:$X64) -> 93.148 | AD64: =SUM(U64:X64) -> 88.286
D65: Adjustments
D67: Patons Lane (start-up and rectification costs) | G67: 0 | H67: 0 | I67: 0 | J67: 0 | K67: 0 | L67: 0 | M67: 0 | N67: 0 | O67: 0 | P67: 0 | Q67: 0 | R67: 0 | S67: 0.7 | T67: 0.5 | U67: 0.3 | V67: -0.1 | W67: 0 | Z67: =SUMIF($G$11:$X$11,Z$11,$G67:$X67) -> 0 | AA67: =SUMIF($G$11:$X$11,AA$11,$G67:$X67) -> 0 | AB67: =SUMIF($G$11:$X$11,AB$11,$G67:$X67) -> 0 | AC67: =SUMIF($G$11:$X$11,AC$11,$G67:$X67) -> 1.4 | AD67: =SUM(U67:X67) -> 0.2
D68: Holding company costs | G68: 0 | H68: 0 | I68: 0 | J68: 0 | K68: 0 | L68: 0 | M68: 0 | N68: -1 | O68: 0 | P68: -0.6 | Q68: 0 | R68: -0.5 | S68: -0.3 | T68: -1.4 | U68: -0.3 | V68: 0 | W68: -0.2 | Z68: =SUMIF($G$11:$X$11,Z$11,$G68:$X68) -> 0 | AA68: =SUMIF($G$11:$X$11,AA$11,$G68:$X68) -> -1 | AB68: =SUMIF($G$11:$X$11,AB$11,$G68:$X68) -> -1.1 | AC68: =SUMIF($G$11:$X$11,AC$11,$G68:$X68) -> -2 | AD68: =SUM(U68:X68) -> -0.5
D69: United Integration cost | G69: 0 | H69: 0 | I69: 0 | J69: 0 | K69: 0.4 | L69: 0.2 | M69: 0.6 | N69: -1.2 | O69: 0 | P69: 0.1 | Q69: 0 | R69: -0.1 | S69: 0 | T69: 0 | U69: 0 | V69: 0 | W69: 0 | Z69: =SUMIF($G$11:$X$11,Z$11,$G69:$X69) -> 0 | AA69: =SUMIF($G$11:$X$11,AA$11,$G69:$X69) -> 0 | AB69: =SUMIF($G$11:$X$11,AB$11,$G69:$X69) -> 0 | AC69: =SUMIF($G$11:$X$11,AC$11,$G69:$X69) -> 0 | AD69: =SUM(U69:X69) -> 0
D70: Historical IPO Costs | G70: 0 | H70: 0 | I70: 0 | J70: 0 | K70: 0.2 | L70: -0.2 | M70: 0 | N70: 0 | O70: 0 | P70: 0 | Q70: 0 | R70: 0 | S70: 0 | T70: 0 | U70: 0 | V70: 0 | W70: 0 | Z70: =SUMIF($G$11:$X$11,Z$11,$G70:$X70) -> 0 | AA70: =SUMIF($G$11:$X$11,AA$11,$G70:$X70) -> 0 | AB70: =SUMIF($G$11:$X$11,AB$11,$G70:$X70) -> 0 | AC70: =SUMIF($G$11:$X$11,AC$11,$G70:$X70) -> 0 | AD70: =SUM(U70:X70) -> 0
D71: Acquisition Pure Costs | G71: 1.75 | H71: 1.75 | I71: -0.2 | J71: 1.2 | K71: 0.3 | L71: 0.1 | M71: -0.4 | N71: 0.1 | O71: 0 | P71: -0.2 | Q71: 0 | R71: 1 | S71: 0 | T71: 0 | U71: 0 | V71: 0 | W71: 0 | Z71: =SUMIF($G$11:$X$11,Z$11,$G71:$X71) -> 4.5 | AA71: =SUMIF($G$11:$X$11,AA$11,$G71:$X71) -> 0.1 | AB71: =SUMIF($G$11:$X$11,AB$11,$G71:$X71) -> 0.8 | AC71: =SUMIF($G$11:$X$11,AC$11,$G71:$X71) -> 0 | AD71: =SUM(U71:X71) -> 0
D72: Bingo P&L Pre - Acquisition | G72: -19.6 | H72: -19.6 | I72: 0 | J72: -4.4 | K72: 0 | L72: 0 | M72: 0 | N72: 0 | O72: 0 | P72: 0 | Q72: 0 | R72: 0 | S72: 0 | T72: 0 | U72: 0 | V72: 0 | W72: 0 | Z72: =SUMIF($G$11:$X$11,Z$11,$G72:$X72) -> -43.6 | AA72: =SUMIF($G$11:$X$11,AA$11,$G72:$X72) -> 0 | AB72: =SUMIF($G$11:$X$11,AB$11,$G72:$X72) -> 0 | AC72: =SUMIF($G$11:$X$11,AC$11,$G72:$X72) -> 0 | AD72: =SUM(U72:X72) -> 0
D73: EPA Matter | G73: 0 | H73: 0 | I73: 0 | J73: 0 | K73: 0 | L73: 0 | M73: 0 | N73: 0 | O73: 0 | P73: 0 | Q73: 0 | R73: -14.4 | S73: 0 | T73: 0 | U73: 0 | V73: 0 | W73: 0 | Z73: =SUMIF($G$11:$X$11,Z$11,$G73:$X73) -> 0 | AA73: =SUMIF($G$11:$X$11,AA$11,$G73:$X73) -> 0 | AB73: =SUMIF($G$11:$X$11,AB$11,$G73:$X73) -> -14.4 | AC73: =SUMIF($G$11:$X$11,AC$11,$G73:$X73) -> 0 | AD73: =SUM(U73:X73) -> 0
D74: RRH + RRP | G74: -0.2 | H74: -0.2 | I74: -0.3 | J74: -0.3 | K74: -0.3 | L74: -0.2 | M74: -0.2 | N74: 0.7 | O74: -0.2 | P74: 0.2 | Q74: -0.3 | R74: 0.3 | S74: 0 | T74: 0 | U74: 0 | V74: 0 | W74: 0 | Z74: =SUMIF($G$11:$X$11,Z$11,$G74:$X74) -> -1 | AA74: =SUMIF($G$11:$X$11,AA$11,$G74:$X74) -> 0 | AB74: =SUMIF($G$11:$X$11,AB$11,$G74:$X74) -> 0 | AC74: =SUMIF($G$11:$X$11,AC$11,$G74:$X74) -> 0 | AD74: =SUM(U74:X74) -> 0
D75: Jordan corporate defence costs | G75: 38.4 | H75: 26.4 | I75: 0.1 | J75: -64.9 | K75: 0.7 | L75: 3.1 | M75: 0.7 | N75: -1.1 | O75: 0 | P75: 0 | Q75: 0.5 | R75: -0.5 | S75: 0 | T75: 0 | U75: 0 | V75: 0 | W75: 0 | Z75: =SUMIF($G$11:$X$11,Z$11,$G75:$X75) -> 0 | AA75: =SUMIF($G$11:$X$11,AA$11,$G75:$X75) -> 3.4 | AB75: =SUMIF($G$11:$X$11,AB$11,$G75:$X75) -> 0 | AC75: =SUMIF($G$11:$X$11,AC$11,$G75:$X75) -> 0 | AD75: =SUM(U75:X75) -> 0
D76: MPC2 Rectification cost | G76: 2.55 | H76: 2.55 | I76: 3.5 | J76: 4.4 | K76: 0 | L76: 0 | M76: 1.3 | N76: 1 | O76: 0 | P76: 0 | Q76: 0 | R76: 0 | S76: 0 | T76: 0 | U76: 0 | V76: 0 | W76: 0 | Z76: =SUMIF($G$11:$X$11,Z$11,$G76:$X76) -> 13 | AA76: =SUMIF($G$11:$X$11,AA$11,$G76:$X76) -> 2.3 | AB76: =SUMIF($G$11:$X$11,AB$11,$G76:$X76) -> 0 | AC76: =SUMIF($G$11:$X$11,AC$11,$G76:$X76) -> 0 | AD76: =SUM(U76:X76) -> 0
D77: ACCC litigation costs | G77: 0.55 | H77: 0.55 | I77: -0.2 | J77: 0.5 | K77: 0.3 | L77: 0.5 | M77: 0.5 | N77: 1.2 | O77: 0 | P77: 1.9 | Q77: 0 | R77: -9.6 | S77: 0 | T77: 0 | U77: 0 | V77: 0 | W77: 0 | Z77: =SUMIF($G$11:$X$11,Z$11,$G77:$X77) -> 1.4 | AA77: =SUMIF($G$11:$X$11,AA$11,$G77:$X77) -> 2.5 | AB77: =SUMIF($G$11:$X$11,AB$11,$G77:$X77) -> -7.7 | AC77: =SUMIF($G$11:$X$11,AC$11,$G77:$X77) -> 0 | AD77: =SUM(U77:X77) -> 0
D78: Bingo Corporate Defense Costs | G78: 0 | H78: 0 | I78: 0 | J78: 69.8 | K78: 0 | L78: 0 | M78: 0 | N78: 0 | O78: 0 | P78: 0 | Q78: 0 | R78: 0 | S78: 0 | T78: 0 | U78: 0 | V78: 0 | W78: 0 | Z78: =SUMIF($G$11:$X$11,Z$11,$G78:$X78) -> 69.8 | AA78: =SUMIF($G$11:$X$11,AA$11,$G78:$X78) -> 0 | AB78: =SUMIF($G$11:$X$11,AB$11,$G78:$X78) -> 0 | AC78: =SUMIF($G$11:$X$11,AC$11,$G78:$X78) -> 0 | AD78: =SUM(U78:X78) -> 0
D79: Finance Transformation | I79: 0 | J79: 0 | K79: 0 | L79: 0 | M79: 0 | N79: 0 | O79: 0 | P79: 0 | Q79: 0 | R79: 0 | S79: 0 | T79: 1.2 | U79: 2.7 | V79: 1.2 | W79: 0 | Z79: =SUMIF($G$11:$X$11,Z$11,$G79:$X79) -> 0 | AA79: =SUMIF($G$11:$X$11,AA$11,$G79:$X79) -> 0 | AB79: =SUMIF($G$11:$X$11,AB$11,$G79:$X79) -> 0 | AC79: =SUMIF($G$11:$X$11,AC$11,$G79:$X79) -> 5.1 | AD79: =SUM(U79:X79) -> 3.9
D80: Shareholder loan | G80: 0 | H80: 0 | I80: 0 | J80: 0 | K80: 0 | L80: 0 | M80: 0 | N80: 0 | O80: 0 | P80: 0 | Q80: 0 | R80: 1 | S80: 0.1 | T80: 1.6 | U80: 0 | V80: 0 | W80: 0 | Z80: =SUMIF($G$11:$X$11,Z$11,$G80:$X80) -> 0 | AA80: =SUMIF($G$11:$X$11,AA$11,$G80:$X80) -> 0 | AB80: =SUMIF($G$11:$X$11,AB$11,$G80:$X80) -> 1 | AC80: =SUMIF($G$11:$X$11,AC$11,$G80:$X80) -> 1.7 | AD80: =SUM(U80:X80) -> 0
D81: Others | G81: 0 | H81: 0 | I81: 0 | J81: 0 | K81: 0 | L81: 0.8 | M81: 0.2 | N81: 4.7 | O81: 0.5 | P81: 0.8 | Q81: 0.4 | R81: -1.9 | S81: 0 | T81: 0.2 | U81: 0 | V81: 8 | W81: 0.8 | Z81: =SUMIF($G$11:$X$11,Z$11,$G81:$X81) -> 0 | AA81: =SUMIF($G$11:$X$11,AA$11,$G81:$X81) -> 5.7 | AB81: =SUMIF($G$11:$X$11,AB$11,$G81:$X81) -> -0.2 | AC81: =SUMIF($G$11:$X$11,AC$11,$G81:$X81) -> 8.2 | AD81: =SUM(U81:X81) -> 8.8
D82: Software expenses | G82: 0 | H82: 0 | I82: 0 | J82: 0 | K82: 1 | L82: 1.5 | M82: 1.4 | N82: 1.6 | O82: 1.5 | P82: 0.9 | Q82: 1 | R82: 0.9 | S82: 0.6 | T82: 1.5 | U82: 0.5 | V82: 0.5 | W82: 0.3 | Z82: =SUMIF($G$11:$X$11,Z$11,$G82:$X82) -> 0 | AA82: =SUMIF($G$11:$X$11,AA$11,$G82:$X82) -> 5.5 | AB82: =SUMIF($G$11:$X$11,AB$11,$G82:$X82) -> 4.3 | AC82: =SUMIF($G$11:$X$11,AC$11,$G82:$X82) -> 3.1 | AD82: =SUM(U82:X82) -> 1.3
D83: Payroll review | G83: 0 | H83: 0 | I83: 0 | J83: 0 | K83: 0 | L83: 0 | M83: 0 | N83: 0 | O83: 0 | P83: 0 | Q83: 0 | R83: 2.7 | S83: 0.5 | T83: 0.9 | U83: -0.3 | V83: -0.7 | W83: 0 | Z83: =SUMIF($G$11:$X$11,Z$11,$G83:$X83) -> 0 | AA83: =SUMIF($G$11:$X$11,AA$11,$G83:$X83) -> 0 | AB83: =SUMIF($G$11:$X$11,AB$11,$G83:$X83) -> 2.7 | AC83: =SUMIF($G$11:$X$11,AC$11,$G83:$X83) -> 0.4 | AD83: =SUM(U83:X83) -> -1
D84: Adjusted EBITDA | G84: =SUM(G64:G83) -> 16.165 | H84: =SUM(H64:H83) -> 20.841 | I84: =SUM(I64:I83) -> 13.01 | J84: =SUM(J64:J83) -> 21.195 | K84: =SUM(K64:K83) -> 26.472 | L84: =SUM(L64:L83) -> 44.226 | M84: =SUM(M64:M83) -> 28.172 | N84: =SUM(N64:N83) -> 32.519 | ... W84: =SUM(W64:W83) -> 26.304 | X84: 23.4 | Z84: =SUM(Z64:Z83) -> 71.211 | AA84: =SUM(AA64:AA83) -> 131.389 | AB84: =SUM(AB64:AB83) -> 118.912 | AC84: =SUM(AC64:AC83) -> 111.048 | AD84: =SUM(U84:X84) -> 102.837
D85: Check: Lender Deck | G85: =G98 -> 16.1 | H85: =H98 -> 21.2 | I85: 12.9 | J85: 20.1 | K85: 26.4 | L85: 43.7 | M85: 28.12 | N85: 33 | O85: 37 | P85: 28.5 | Q85: 27.6 | R85: 26.6 | S85: 28 | U85: 28.2 | W85: 26.5 | Z85: =SUMIF($G$11:$S$11,Z$11,$G85:$S85) -> 70.3 | AA85: =SUMIF($G$11:$S$11,AA$11,$G85:$S85) -> 131.22 | AB85: =SUMIF($G$11:$S$11,AB$11,$G85:$S85) -> 119.7 | AC85: 111
G86: =G84-G85 -> 0.065 | H86: =H84-H85 -> -0.359 | I86: =I84-I85 -> 0.11 | J86: =J84-J85 -> 1.095 | K86: =K84-K85 -> 0.072 | L86: =L84-L85 -> 0.526 | M86: =M84-M85 -> 0.052 | N86: =N84-N85 -> -0.481 | ... S86: =S84-S85 -> 0.087 | U86: =U84-U85 -> 0.047 | W86: =W84-W85 -> -0.196 | Z86: =Z84-Z85 -> 0.911 | AA86: =AA84-AA85 -> 0.169 | AB86: =AB84-AB85 -> -0.788 | AC86: =AC84-AC85 -> 0.048
D87: Adj. EBITDA Margin | G87: =G84 / G$25 -> 0.22937537 | H87: =H84 / H$25 -> 0.16593153 | I87: =I84 / I$25 -> 0.11382327 | J87: =J84 / J$25 -> 0.15676775 | K87: =K84 / K$25 -> 0.16411655 | L87: =L84 / L$25 -> 0.28422879 | M87: =M84 / M$25 -> 0.17336615 | N87: =N84 / N$25 -> 0.19425926 | ... X87: =X84 / X$25 -> 0.16949153 | Z87: =Z84 / Z$25 -> 0.15981857 | AA87: =AA84 / AA$25 -> 0.20313698 | AB87: =AB84 / AB$25 -> 0.18101994 | AC87: =AC84 / AC$25 -> 0.164305 | AD87: =AD84 / AD$25 -> 0.1666999
D89: Note: EBITDA Adj. Bucketing
D90: Litigation Costs | I90: =SUM(I73:I78) -> 3.1 | J90: =SUM(J73:J78) -> 9.5 | K90: =SUM(K73:K78) -> 0.7 | L90: =SUM(L73:L78) -> 3.4 | M90: =SUM(M73:M78) -> 2.3 | N90: =SUM(N73:N78) -> 1.8 | O90: =SUM(O73:O78) -> -0.2 | P90: =SUM(P73:P78) -> 2.1 | ... W90: =SUM(W73:W78) -> 0 | Z90: =SUMIF($G$11:$X$11,Z$11,$G90:$X90) -> 12.6 | AA90: =SUMIF($G$11:$X$11,AA$11,$G90:$X90) -> 8.2 | AB90: =SUMIF($G$11:$X$11,AB$11,$G90:$X90) -> -22.1 | AC90: =SUMIF($G$11:$X$11,AC$11,$G90:$X90) -> 0 | AD90: =SUM(U90:X90) -> 0
D91: Other Costs | I91: =SUM(I79:I83,I70) -> 0 | J91: =SUM(J79:J83,J70) -> 0 | K91: =SUM(K79:K83,K70) -> 1.2 | L91: =SUM(L79:L83,L70) -> 2.1 | M91: =SUM(M79:M83,M70) -> 1.6 | N91: =SUM(N79:N83,N70) -> 6.3 | O91: =SUM(O79:O83,O70) -> 2 | P91: =SUM(P79:P83,P70) -> 1.7 | ... W91: =SUM(W79:W83,W70) -> 1.1 | Z91: =SUMIF($G$11:$X$11,Z$11,$G91:$X91) -> 0 | AA91: =SUMIF($G$11:$X$11,AA$11,$G91:$X91) -> 11.2 | AB91: =SUMIF($G$11:$X$11,AB$11,$G91:$X91) -> 7.8 | AC91: =SUMIF($G$11:$X$11,AC$11,$G91:$X91) -> 18.5 | AD91: =SUM(U91:X91) -> 13
D92: Acquisition Costs | I92: =SUM(I71:I72,I67:I69) -> -0.2 | J92: =SUM(J71:J72,J67:J69) -> -3.2 | K92: =SUM(K71:K72,K67:K69) -> 0.7 | L92: =SUM(L71:L72,L67:L69) -> 0.3 | M92: =SUM(M71:M72,M67:M69) -> 0.2 | N92: =SUM(N71:N72,N67:N69) -> -2.1 | O92: =SUM(O71:O72,O67:O69) -> 0 | P92: =SUM(P71:P72,P67:P69) -> -0.7 | ... W92: =SUM(W71:W72,W67:W69) -> -0.2 | Z92: =SUMIF($G$11:$X$11,Z$11,$G92:$X92) -> -3.4 | AA92: =SUMIF($G$11:$X$11,AA$11,$G92:$X92) -> -0.9 | AB92: =SUMIF($G$11:$X$11,AB$11,$G92:$X92) -> -0.3 | AC92: =SUMIF($G$11:$X$11,AC$11,$G92:$X92) -> -0.6 | AD92: =SUM(U92:X92) -> -0.3
D94: Additional Segment Info: EBITDA Share
D95: Collections Underlying EBITDA | G95: 2.2 | H95: 0 | I95: -0.5 | J95: 1.7 | K95: 1.3 | L95: =0.4-K95 -> -0.9 | M95: -0.8 | N95: -0.1 | O95: 1.4 | P95: -1.3 | Q95: -2 | R95: -2.1 | S95: -0.2 | Z95: =SUMIF($G$11:$X$11,Z$11,$G95:$X95) -> 3.4 | AA95: =SUMIF($G$11:$X$11,AA$11,$G95:$X95) -> -0.5 | AB95: =SUMIF($G$11:$X$11,AB$11,$G95:$X95) -> -4 | AC95: =SUMIF($G$11:$X$11,AC$11,$G95:$X95) -> -0.2 | AD95: =SUM(U95:X95) -> 0
D96: Post-Collections Underlying EBITDA | G96: 13.9 | H96: =34.7-G96 -> 20.8 | I96: 13.1 | J96: 18.8 | K96: 24.4 | L96: =49-K96 -> 24.6 | M96: 27.3 | N96: 29.9 | O96: 36.9 | P96: 24.7 | Q96: 30 | R96: 28.6 | S96: 30.3 | Z96: =SUMIF($G$11:$X$11,Z$11,$G96:$X96) -> 66.6 | AA96: =SUMIF($G$11:$X$11,AA$11,$G96:$X96) -> 106.2 | AB96: =SUMIF($G$11:$X$11,AB$11,$G96:$X96) -> 120.2 | AC96: =SUMIF($G$11:$X$11,AC$11,$G96:$X96) -> 30.3 | AD96: =SUM(U96:X96) -> 0
D97: Other Underlying EBITDA | G97: 0 | H97: 0.4 | I97: 0.3 | J97: -0.5 | K97: 0.7 | L97: =21.8-K97 -> 21.1 | M97: 1.6 | N97: 0.6 | O97: -1.3 | P97: 5.1 | Q97: -0.3 | R97: 0 | S97: -2 | Z97: =SUMIF($G$11:$X$11,Z$11,$G97:$X97) -> 0.2 | AA97: =SUMIF($G$11:$X$11,AA$11,$G97:$X97) -> 24 | AB97: =SUMIF($G$11:$X$11,AB$11,$G97:$X97) -> 3.5 | AC97: =SUMIF($G$11:$X$11,AC$11,$G97:$X97) -> -2 | AD97: =SUM(U97:X97) -> 0
D98: BINGO Underlying EBITDA | G98: =SUM(G95:G97) -> 16.1 | H98: =SUM(H95:H97) -> 21.2 | I98: =SUM(I95:I97) -> 12.9 | J98: =SUM(J95:J97) -> 20 | K98: =SUM(K95:K97) -> 26.4 | L98: =SUM(L95:L97) -> 44.8 | M98: =SUM(M95:M97) -> 28.1 | N98: 30.4 | O98: 37 | P98: 28.5 | Q98: 27.7 | R98: 26.5 | S98: =SUM(S95:S97) -> 28.1 | Z98: =SUM(Z95:Z97) -> 70.2 | AA98: =SUM(AA95:AA97) -> 129.7 | AB98: =SUM(AB95:AB97) -> 119.7 | AC98: =SUM(AC95:AC97) -> 28.1 | AD98: =SUM(U98:X98) -> 0
D99: Check: Lender Deck | G99: =G84 -> 16.165 | H99: =H84 -> 20.841 | I99: =I84 -> 13.01 | J99: =J84 -> 21.195 | K99: =K84 -> 26.472 | L99: =L84 -> 44.226 | M99: =M84 -> 28.172 | N99: =N84 -> 32.519 | ... S99: =S84 -> 28.087 | Z99: =Z84 -> 71.211 | AA99: =AA84 -> 131.389 | AB99: =AB84 -> 118.912 | AC99: =AC84 -> 111.048
G100: =G98-G99 -> -0.065 | H100: =H98-H99 -> 0.359 | I100: =I98-I99 -> -0.11 | J100: =J98-J99 -> -1.195 | K100: =K98-K99 -> -0.072 | L100: =L98-L99 -> 0.574 | M100: =M98-M99 -> -0.072 | N100: =N98-N99 -> -2.119 | ... S100: =S98-S99 -> 0.013 | Z100: =Z98-Z99 -> -1.011 | AA100: =AA98-AA99 -> -1.689 | AB100: =AB98-AB99 -> 0.788 | AC100: =SUM(R100:V100) -> 0.819
Z101: =Z98 / Z$25 -> 0.15754959 | AA101: =AA98 / AA$25 -> 0.20052566 | AB101: =AB98 / AB$25 -> 0.18221952 | AC101: =AC98 / AC$25 -> 0.04157635
C102: x | D102: Balance Sheet
D104: Assets
D105: Cash and cash equivalents | F105: 42.824 | G105: 154.772 | H105: 137.694 | I105: 185.134 | J105: 180.504 | K105: 88.031 | L105: 80.616 | M105: 100.999 | N105: 113.373 | O105: 73.672 | P105: 56.265 | Q105: 17.884 | R105: 44.365 | S105: 16.892 | T105: 21.146 | U105: 12.751 | V105: 16.708 | W105: 14.582 | X105: 38.074 | Z105: =J105 -> 180.504 | AA105: =N105 -> 113.373 | AB105: =R105 -> 44.365 | AC105: =V105 -> 16.708 | AD105: =X105 -> 38.074
D106: Trade and other receivables | F106: 79.625 | G106: 70.379 | H106: 70.023 | I106: 78.709 | J106: 82.833 | K106: 119.311 | L106: 105.228 | M106: 109.339 | N106: 156.269 | O106: 171.646 | P106: 180.458 | Q106: 195.275 | R106: 237.203 | S106: 244.697 | T106: 250.46 | U106: 251.633 | V106: 226.221 | W106: 208.715 | X106: 215.106 | Z106: =J106 -> 82.833 | AA106: =N106 -> 156.269 | AB106: =R106 -> 237.203 | AC106: =V106 -> 226.221 | AD106: =X106 -> 215.106
D107: Contract assets | F107: 0.465 | G107: 0.474 | H107: 0.472 | I107: 0.551 | J107: 0.532 | K107: 0.629 | L107: 0.572 | M107: 0.633 | N107: 0.62 | O107: 0.629 | P107: 0.636 | Q107: 0.607 | R107: 0.6 | S107: 0.654 | T107: 0.654 | U107: 0.654 | V107: 0.912 | W107: 0.911 | X107: 0.903 | Z107: =J107 -> 0.532 | AA107: =N107 -> 0.62 | AB107: =R107 -> 0.6 | AC107: =V107 -> 0.912 | AD107: =X107 -> 0.903
D108: Inventories | F108: 6.611 | G108: 8.027 | H108: 10.388 | I108: 9.946 | J108: 12.218 | K108: 10.47 | L108: 11.6 | M108: 13.135 | N108: 12.516 | O108: 13.783 | P108: 12.898 | Q108: 11.791 | R108: 12.217 | S108: 10.762 | T108: 9.917 | U108: 10.623 | V108: 10.105 | W108: 9.397 | X108: 8.784 | Z108: =J108 -> 12.218 | AA108: =N108 -> 12.516 | AB108: =R108 -> 12.217 | AC108: =V108 -> 10.105 | AD108: =X108 -> 8.784
D109: Other assets | F109: 6.01 | G109: 17.881 | H109: 17.961 | I109: 21.314 | J109: 30.283 | K109: 37.321 | L109: 45.802 | M109: 44.433 | N109: 41.655 | O109: 48.26 | P109: 42.087 | Q109: 43.684 | R109: 42.058 | S109: 53.14 | T109: 52.337 | U109: 49.576 | V109: 35.002 | W109: 90.422 | X109: 46.183 | Z109: =J109 -> 30.283 | AA109: =N109 -> 41.655 | AB109: =R109 -> 42.058 | AC109: =V109 -> 35.002 | AD109: =X109 -> 46.183
D110: Income tax receivable | F110: 0 | G110: 0 | H110: 1.613 | I110: 1.311 | J110: 0 | K110: 0 | L110: 0 | M110: 0 | N110: 0 | O110: 0 | P110: 0 | Q110: 0 | R110: 0.057 | S110: 0.208 | T110: 0.208 | U110: 0.208 | V110: 0 | W110: 0 | X110: 0 | Z110: =J110 -> 0 | AA110: =N110 -> 0 | AB110: =R110 -> 0.057 | AC110: =V110 -> 0 | AD110: =X110 -> 0
D111: Assets classified as held-for-sale | F111: 0 | G111: 0 | H111: 0 | I111: 0 | J111: 0 | K111: 0 | L111: 19.591 | M111: 0 | N111: 0 | O111: 0 | P111: 0 | Q111: 0 | R111: 91.554 | S111: 83.318 | T111: 85.96 | U111: 37.04 | V111: 36.838 | W111: 0 | X111: 0 | Z111: =J111 -> 0 | AA111: =N111 -> 0 | AB111: =R111 -> 91.554 | AC111: =V111 -> 36.838 | AD111: =X111 -> 0
D112: Total current assets | F112: =SUM(F105:F111) -> 135.535 | G112: =SUM(G105:G111) -> 251.533 | H112: =SUM(H105:H111) -> 238.151 | I112: =SUM(I105:I111) -> 296.965 | J112: =SUM(J105:J111) -> 306.37 | K112: =SUM(K105:K111) -> 255.762 | L112: =SUM(L105:L111) -> 263.409 | M112: =SUM(M105:M111) -> 268.539 | ... X112: =SUM(X105:X111) -> 309.05 | Z112: =J112 -> 306.37 | AA112: =N112 -> 324.433 | AB112: =R112 -> 428.054 | AC112: =V112 -> 325.786 | AD112: =X112 -> 309.05
D114: Property, plant and equipment | F114: 858.763 | G114: 868.336 | H114: 879.674 | I114: 889.106 | J114: 981.011 | K114: 1005.514 | L114: 988.966 | M114: 981.239 | N114: 985.09 | O114: 979.542 | P114: 979.22 | Q114: 982.468 | R114: 897.316 | S114: 889.343 | T114: 883.815 | U114: 878.978 | V114: 871.445 | W114: 897.4 | X114: 884.437 | Z114: =J114 -> 981.011 | AA114: =N114 -> 985.09 | AB114: =R114 -> 897.316 | AC114: =V114 -> 871.445 | AD114: =X114 -> 884.437
D115: Right-of-use assets | F115: 38.205 | G115: 45.372 | H115: 45.49 | I115: 45.39 | J115: 61.568 | K115: 63.855 | L115: 64.567 | M115: 64.487 | N115: 62.981 | O115: 61.103 | P115: 58.212 | Q115: 56.305 | R115: 61.615 | S115: 58.847 | T115: 56.188 | U115: 53.169 | V115: 64.543 | W115: 60.435 | X115: 57.278 | Z115: =J115 -> 61.568 | AA115: =N115 -> 62.981 | AB115: =R115 -> 61.615 | AC115: =V115 -> 64.543 | AD115: =X115 -> 57.278
D116: Intangible assets | F116: 477.415 | G116: 1901.497 | H116: 1899.526 | I116: 1898.023 | J116: 1849.411 | K116: 1843.178 | L116: 1838.057 | M116: 1831.401 | N116: 1451.507 | O116: 1443.694 | P116: 1437.418 | Q116: 1430.457 | R116: 1262.968 | S116: 1255.552 | T116: 1247.23 | U116: 1239.318 | V116: 1237.126 | W116: 1231.208 | X116: 1222.593 | Z116: =J116 -> 1849.411 | AA116: =N116 -> 1451.507 | AB116: =R116 -> 1262.968 | AC116: =V116 -> 1237.126 | AD116: =X116 -> 1222.593
D117: Other assets | F117: 4.141 | G117: 4.088 | H117: 30.185 | I117: 28.673 | J117: 80.907 | K117: 80.765 | L117: 79.189 | M117: 79.045 | N117: 84.642 | O117: 84.491 | P117: 58.663 | Q117: 58.509 | R117: 73.256 | S117: 73.095 | T117: 100.497 | U117: 100.37 | V117: =62.769 + 22.487 -> 85.256 | W117: =23.162+2.144 -> 25.306 | X117: =24.658+2.091 -> 26.749 | Z117: =J117 -> 80.907 | AA117: =N117 -> 84.642 | AB117: =R117 -> 73.256 | AC117: =V117 -> 85.256 | AD117: =X117 -> 26.749
D118: Total Assets | F118: =SUM(F112:F117) -> 1514.059 | G118: =SUM(G112:G117) -> 3070.826 | H118: =SUM(H112:H117) -> 3093.026 | I118: =SUM(I112:I117) -> 3158.157 | J118: =SUM(J112:J117) -> 3279.267 | K118: =SUM(K112:K117) -> 3249.074 | L118: =SUM(L112:L117) -> 3234.188 | M118: =SUM(M112:M117) -> 3224.711 | ... X118: =SUM(X112:X117) -> 2500.107 | Z118: =J118 -> 3279.267 | AA118: =N118 -> 2908.653 | AB118: =R118 -> 2723.209 | AC118: =V118 -> 2584.156 | AD118: =X118 -> 2500.107
...

Sheet O1
D3: ='Capital Structure'!D3 -> Bingo Industries | K3: DRAFT
D4: Income Statement Output | K4: CONFIDENTIAL
D5: Data as of 2Q'26
D6: ($ millions)
F7: Year Ended | J7: Quarter Ended
F8: 2023 | G8: =F8+1 -> 2024 | H8: =G8+1 -> 2025 | I8: LTM | J8: =Historicals!T15 -> 2Q25 | K8: =Historicals!X15 -> 2Q26
F9: =Historicals!$AA$16 -> 45107 | G9: =Historicals!$AB$16 -> 45473 | H9: =Historicals!$AC$16 -> 45838 | I9: =Historicals!$AD$16 -> 46022 | J9: =Historicals!$T$16 -> 45657 | K9: =Historicals!$X$16 -> 46022
D11: Revenues
D12: Collections revenue | F12: =INDEX(Historicals!$Z$21:$AD$92,MATCH($D12,Historicals!$D$21:$D$92,0),MATCH(F$8,Historicals!$Z$11:$AD$11,0)) -> 283.6 | G12: =INDEX(Historicals!$Z$21:$AD$92,MATCH($D12,Historicals!$D$21:$D$92,0),MATCH(G$8,Historicals!$Z$11:$AD$11,0)) -> 315.3 | J12: =INDEX(Historicals!$F$21:$X$92,MATCH($D16,Historicals!$D$21:$D$92,0),MATCH(J$8,Historicals!$F$15:$X$15,0)) -> 161.5
D13: Post-Collections revenue | F13: =INDEX(Historicals!$Z$21:$AD$92,MATCH($D13,Historicals!$D$21:$D$92,0),MATCH(F$8,Historicals!$Z$11:$AD$11,0)) -> 460.5 | G13: =INDEX(Historicals!$Z$21:$AD$92,MATCH($D13,Historicals!$D$21:$D$92,0),MATCH(G$8,Historicals!$Z$11:$AD$11,0)) -> 444.8 | J13: =INDEX(Historicals!$F$21:$X$92,MATCH($D13,Historicals!$D$21:$D$92,0),MATCH(J$8,Historicals!$F$15:$X$15,0)) -> 114.5
D14: Other revenue | F14: =INDEX(Historicals!$Z$21:$AD$92,MATCH($D14,Historicals!$D$21:$D$92,0),MATCH(F$8,Historicals!$Z$11:$AD$11,0)) -> 36.9 | G14: =INDEX(Historicals!$Z$21:$AD$92,MATCH($D14,Historicals!$D$21:$D$92,0),MATCH(G$8,Historicals!$Z$11:$AD$11,0)) -> 27.1 | J14: =INDEX(Historicals!$F$21:$X$92,MATCH($D14,Historicals!$D$21:$D$92,0),MATCH(J$8,Historicals!$F$15:$X$15,0)) -> 3.4
D15: Eliminations | F15: =INDEX(Historicals!$Z$21:$AD$92,MATCH($D15,Historicals!$D$21:$D$92,0),MATCH(F$8,Historicals!$Z$11:$AD$11,0)) -> -134.2 | G15: =INDEX(Historicals!$Z$21:$AD$92,MATCH($D15,Historicals!$D$21:$D$92,0),MATCH(G$8,Historicals!$Z$11:$AD$11,0)) -> -130.3 | J15: =INDEX(Historicals!$F$21:$X$92,MATCH($D15,Historicals!$D$21:$D$92,0),MATCH(J$8,Historicals!$F$15:$X$15,0)) -> -34.3
D16: Total Revenues | F16: =INDEX(Historicals!$Z$21:$AD$92,MATCH($D16,Historicals!$D$21:$D$92,0),MATCH(F$8,Historicals!$Z$11:$AD$11,0)) -> 646.8 | G16: =INDEX(Historicals!$Z$21:$AD$92,MATCH($D16,Historicals!$D$21:$D$92,0),MATCH(G$8,Historicals!$Z$11:$AD$11,0)) -> 656.9 | H16: =INDEX(Historicals!$Z$21:$AD$92,MATCH($D16,Historicals!$D$21:$D$92,0),MATCH(H$8,Historicals!$Z$11:$AD$11,0)) -> 675.865 | I16: =INDEX(Historicals!$Z$21:$AD$92,MATCH($D16,Historicals!$D$21:$D$92,0),MATCH(I$8,Historicals!$Z$11:$AD$11,0)) -> 616.899 | J16: =INDEX(Historicals!$F$21:$X$92,MATCH($D16,Historicals!$D$21:$D$92,0),MATCH(J$8,Historicals!$F$15:$X$15,0)) -> 161.5 | K16: =INDEX(Historicals!$F$21:$X$92,MATCH($D16,Historicals!$D$21:$D$92,0),MATCH(K$8,Historicals!$F$15:$X$15,0)) -> 138.06
D17: Cost of goods sold | F17: =INDEX(Historicals!$Z$21:$AD$92,MATCH($D17,Historicals!$D$21:$D$92,0),MATCH(F$8,Historicals!$Z$11:$AD$11,0)) -> -284.5 | G17: =INDEX(Historicals!$Z$21:$AD$92,MATCH($D17,Historicals!$D$21:$D$92,0),MATCH(G$8,Historicals!$Z$11:$AD$11,0)) -> -287.1 | H17: =INDEX(Historicals!$Z$21:$AD$92,MATCH($D17,Historicals!$D$21:$D$92,0),MATCH(H$8,Historicals!$Z$11:$AD$11,0)) -> -316.819 | I17: =INDEX(Historicals!$Z$21:$AD$92,MATCH($D17,Historicals!$D$21:$D$92,0),MATCH(I$8,Historicals!$Z$11:$AD$11,0)) -> -273.371 | J17: =INDEX(Historicals!$F$21:$X$92,MATCH($D17,Historicals!$D$21:$D$92,0),MATCH(J$8,Historicals!$F$15:$X$15,0)) -> -69.867 | K17: =INDEX(Historicals!$F$21:$X$92,MATCH($D17,Historicals!$D$21:$D$92,0),MATCH(K$8,Historicals!$F$15:$X$15,0)) -> -53.357
D18: Gross profit | F18: =INDEX(Historicals!$Z$21:$AD$92,MATCH($D18,Historicals!$D$21:$D$92,0),MATCH(F$8,Historicals!$Z$11:$AD$11,0)) -> 362.3 | G18: =INDEX(Historicals!$Z$21:$AD$92,MATCH($D18,Historicals!$D$21:$D$92,0),MATCH(G$8,Historicals!$Z$11:$AD$11,0)) -> 369.8 | H18: =INDEX(Historicals!$Z$21:$AD$92,MATCH($D18,Historicals!$D$21:$D$92,0),MATCH(H$8,Historicals!$Z$11:$AD$11,0)) -> 359.046 | I18: =INDEX(Historicals!$Z$21:$AD$92,MATCH($D18,Historicals!$D$21:$D$92,0),MATCH(I$8,Historicals!$Z$11:$AD$11,0)) -> 343.528 | J18: =INDEX(Historicals!$F$21:$X$92,MATCH($D18,Historicals!$D$21:$D$92,0),MATCH(J$8,Historicals!$F$15:$X$15,0)) -> 91.633 | K18: =INDEX(Historicals!$F$21:$X$92,MATCH($D18,Historicals!$D$21:$D$92,0),MATCH(K$8,Historicals!$F$15:$X$15,0)) -> 84.703
D19: Check: | F19: =ROUND(SUM(F16:F17,-F18),1) -> 0 | G19: =ROUND(SUM(G16:G17,-G18),1) -> 0 | H19: =ROUND(SUM(H16:H17,-H18),1) -> 0 | I19: =ROUND(SUM(I16:I17,-I18),1) -> 0 | J19: =ROUND(SUM(J16:J17,-J18),1) -> 0 | K19: =ROUND(SUM(K16:K17,-K18),1) -> 0
D21: Interest income | F21: =INDEX(Historicals!$Z$21:$AD$92,MATCH($D21,Historicals!$D$21:$D$92,0),MATCH(F$8,Historicals!$Z$11:$AD$11,0)) -> 2.897 | G21: =INDEX(Historicals!$Z$21:$AD$92,MATCH($D21,Historicals!$D$21:$D$92,0),MATCH(G$8,Historicals!$Z$11:$AD$11,0)) -> 3.457 | H21: =INDEX(Historicals!$Z$21:$AD$92,MATCH($D21,Historicals!$D$21:$D$92,0),MATCH(H$8,Historicals!$Z$11:$AD$11,0)) -> 1.424 | I21: =INDEX(Historicals!$Z$21:$AD$92,MATCH($D21,Historicals!$D$21:$D$92,0),MATCH(I$8,Historicals!$Z$11:$AD$11,0)) -> 0.639 | J21: =INDEX(Historicals!$F$21:$X$92,MATCH($D21,Historicals!$D$21:$D$92,0),MATCH(J$8,Historicals!$F$15:$X$15,0)) -> 0.55 | K21: =INDEX(Historicals!$F$21:$X$92,MATCH($D21,Historicals!$D$21:$D$92,0),MATCH(K$8,Historicals!$F$15:$X$15,0)) -> 0.129
D22: Employee benefits expenses | F22: =INDEX(Historicals!$Z$21:$AD$92,MATCH($D22,Historicals!$D$21:$D$92,0),MATCH(F$8,Historicals!$Z$11:$AD$11,0)) -> -169.692 | G22: =INDEX(Historicals!$Z$21:$AD$92,MATCH($D22,Historicals!$D$21:$D$92,0),MATCH(G$8,Historicals!$Z$11:$AD$11,0)) -> -176.795 | H22: =INDEX(Historicals!$Z$21:$AD$92,MATCH($D22,Historicals!$D$21:$D$92,0),MATCH(H$8,Historicals!$Z$11:$AD$11,0)) -> -177.427 | I22: =INDEX(Historicals!$Z$21:$AD$92,MATCH($D22,Historicals!$D$21:$D$92,0),MATCH(I$8,Historicals!$Z$11:$AD$11,0)) -> -169.977 | J22: =INDEX(Historicals!$F$21:$X$92,MATCH($D22,Historicals!$D$21:$D$92,0),MATCH(J$8,Historicals!$F$15:$X$15,0)) -> -45.626 | K22: =INDEX(Historicals!$F$21:$X$92,MATCH($D22,Historicals!$D$21:$D$92,0),MATCH(K$8,Historicals!$F$15:$X$15,0)) -> -40.737
D23: Trucks and machinery costs | F23: =INDEX(Historicals!$Z$21:$AD$92,MATCH($D23,Historicals!$D$21:$D$92,0),MATCH(F$8,Historicals!$Z$11:$AD$11,0)) -> -45.584 | G23: =INDEX(Historicals!$Z$21:$AD$92,MATCH($D23,Historicals!$D$21:$D$92,0),MATCH(G$8,Historicals!$Z$11:$AD$11,0)) -> -46.175 | H23: =INDEX(Historicals!$Z$21:$AD$92,MATCH($D23,Historicals!$D$21:$D$92,0),MATCH(H$8,Historicals!$Z$11:$AD$11,0)) -> -48.915 | I23: =INDEX(Historicals!$Z$21:$AD$92,MATCH($D23,Historicals!$D$21:$D$92,0),MATCH(I$8,Historicals!$Z$11:$AD$11,0)) -> -48.733 | J23: =INDEX(Historicals!$F$21:$X$92,MATCH($D23,Historicals!$D$21:$D$92,0),MATCH(J$8,Historicals!$F$15:$X$15,0)) -> -11.538 | K23: =INDEX(Historicals!$F$21:$X$92,MATCH($D23,Historicals!$D$21:$D$92,0),MATCH(K$8,Historicals!$F$15:$X$15,0)) -> -12.166
D24: Administrative expenses | F24: =INDEX(Historicals!$Z$21:$AD$92,MATCH($D24,Historicals!$D$21:$D$92,0),MATCH(F$8,Historicals!$Z$11:$AD$11,0)) -> -11.474 | G24: =INDEX(Historicals!$Z$21:$AD$92,MATCH($D24,Historicals!$D$21:$D$92,0),MATCH(G$8,Historicals!$Z$11:$AD$11,0)) -> -2.135 | H24: =INDEX(Historicals!$Z$21:$AD$92,MATCH($D24,Historicals!$D$21:$D$92,0),MATCH(H$8,Historicals!$Z$11:$AD$11,0)) -> -13.666 | I24: =INDEX(Historicals!$Z$21:$AD$92,MATCH($D24,Historicals!$D$21:$D$92,0),MATCH(I$8,Historicals!$Z$11:$AD$11,0)) -> -12.528 | J24: =INDEX(Historicals!$F$21:$X$92,MATCH($D24,Historicals!$D$21:$D$92,0),MATCH(J$8,Historicals!$F$15:$X$15,0)) -> -2.864 | K24: =INDEX(Historicals!$F$21:$X$92,MATCH($D24,Historicals!$D$21:$D$92,0),MATCH(K$8,Historicals!$F$15:$X$15,0)) -> -3.124
D25: Acquisition expenses | F25: =INDEX(Historicals!$Z$21:$AD$92,MATCH($D25,Historicals!$D$21:$D$92,0),MATCH(F$8,Historicals!$Z$11:$AD$11,0)) -> -8.6736174e-19 | G25: =INDEX(Historicals!$Z$21:$AD$92,MATCH($D25,Historicals!$D$21:$D$92,0),MATCH(G$8,Historicals!$Z$11:$AD$11,0)) -> 0 | H25: =INDEX(Historicals!$Z$21:$AD$92,MATCH($D25,Historicals!$D$21:$D$92,0),MATCH(H$8,Historicals!$Z$11:$AD$11,0)) -> 0 | I25: =INDEX(Historicals!$Z$21:$AD$92,MATCH($D25,Historicals!$D$21:$D$92,0),MATCH(I$8,Historicals!$Z$11:$AD$11,0)) -> 0 | J25: =INDEX(Historicals!$F$21:$X$92,MATCH($D25,Historicals!$D$21:$D$92,0),MATCH(J$8,Historicals!$F$15:$X$15,0)) -> 0 | K25: =INDEX(Historicals!$F$21:$X$92,MATCH($D25,Historicals!$D$21:$D$92,0),MATCH(K$8,Historicals!$F$15:$X$15,0)) -> 0
D26: Oth. income/(expenses) | F26: =INDEX(Historicals!$Z$21:$AD$84,MATCH($D26,Historicals!$D$21:$D$84,0),MATCH(F$8,Historicals!$Z$11:$AD$11,0)) -INDEX(Historicals!$Z$21:$AD$84,MATCH("Lender Deck COGS Adjustment",Historicals!$D$21:$D$84,0),MATCH(F$8,Historicals!$Z$11:$AD$11,0)) -> -25.558 | G26: =INDEX(Historicals!$Z$21:$AD$84,MATCH($D26,Historicals!$D$21:$D$84,0),MATCH(G$8,Historicals!$Z$11:$AD$11,0)) -INDEX(Historicals!$Z$21:$AD$84,MATCH("Lender Deck COGS Adjustment",Historicals!$D$21:$D$84,0),MATCH(G$8,Historicals!$Z$11:$AD$11,0)) -> -14.64 | H26: =INDEX(Historicals!$Z$21:$AD$84,MATCH($D26,Historicals!$D$21:$D$84,0),MATCH(H$8,Historicals!$Z$11:$AD$11,0)) -INDEX(Historicals!$Z$21:$AD$84,MATCH("Lender Deck COGS Adjustment",Historicals!$D$21:$D$84,0),MATCH(H$8,Historicals!$Z$11:$AD$11,0)) -> -27.314 | I26: =INDEX(Historicals!$Z$21:$AD$84,MATCH($D26,Historicals!$D$21:$D$84,0),MATCH(I$8,Historicals!$Z$11:$AD$11,0)) -INDEX(Historicals!$Z$21:$AD$84,MATCH("Lender Deck COGS Adjustment",Historicals!$D$21:$D$84,0),MATCH(I$8,Historicals!$Z$11:$AD$11,0)) -> -24.643 | J26: =INDEX(Historicals!$F$21:$X$84,MATCH($D26,Historicals!$D$21:$D$84,0),MATCH(J$8,Historicals!$F$15:$X$15,0)) -INDEX(Historicals!$F$21:$X$84,MATCH("Lender Deck COGS Adjustment",Historicals!$D$21:$D$84,0),MATCH(J$8,Historicals!$F$15:$X$15,0)) -> -6.827 | K26: =INDEX(Historicals!$F$21:$X$84,MATCH($D26,Historicals!$D$21:$D$84,0),MATCH(K$8,Historicals!$F$15:$X$15,0)) -INDEX(Historicals!$F$21:$X$84,MATCH("Lender Deck COGS Adjustment",Historicals!$D$21:$D$84,0),MATCH(K$8,Historicals!$F$15:$X$15,0)) -> -7.256
D27: EBITDA | F27: =INDEX(Historicals!$Z$21:$AD$92,MATCH($D27,Historicals!$D$21:$D$92,0),MATCH(F$8,Historicals!$Z$11:$AD$11,0)) -> 112.889 | G27: =INDEX(Historicals!$Z$21:$AD$92,MATCH($D27,Historicals!$D$21:$D$92,0),MATCH(G$8,Historicals!$Z$11:$AD$11,0)) -> 133.512 | H27: =INDEX(Historicals!$Z$21:$AD$92,MATCH($D27,Historicals!$D$21:$D$92,0),MATCH(H$8,Historicals!$Z$11:$AD$11,0)) -> 93.148 | I27: =INDEX(Historicals!$Z$21:$AD$92,MATCH($D27,Historicals!$D$21:$D$92,0),MATCH(I$8,Historicals!$Z$11:$AD$11,0)) -> 88.286 | J27: =INDEX(Historicals!$F$21:$X$92,MATCH($D27,Historicals!$D$21:$D$92,0),MATCH(J$8,Historicals!$F$15:$X$15,0)) -> 25.328 | K27: =INDEX(Historicals!$F$21:$X$92,MATCH($D27,Historicals!$D$21:$D$92,0),MATCH(K$8,Historicals!$F$15:$X$15,0)) -> 21.549
D28: Check: | F28: =ROUND(SUM(F21:F26,F18,-F27),0) -> 0 | G28: =ROUND(SUM(G21:G26,G18,-G27),0) -> 0 | H28: =ROUND(SUM(H21:H26,H18,-H27),0) -> 0 | I28: =ROUND(SUM(I21:I26,I18,-I27),0) -> 0 | J28: =ROUND(SUM(J21:J26,J18,-J27),0) -> 0 | K28: =ROUND(SUM(K21:K26,K18,-K27),0) -> 0
D30: Acquisition Costs | F30: =INDEX(Historicals!$Z$21:$AD$92,MATCH($D30,Historicals!$D$21:$D$92,0),MATCH(F$8,Historicals!$Z$11:$AD$11,0)) -> -0.9 | G30: =INDEX(Historicals!$Z$21:$AD$92,MATCH($D30,Historicals!$D$21:$D$92,0),MATCH(G$8,Historicals!$Z$11:$AD$11,0)) -> -0.3 | H30: =INDEX(Historicals!$Z$21:$AD$92,MATCH($D30,Historicals!$D$21:$D$92,0),MATCH(H$8,Historicals!$Z$11:$AD$11,0)) -> -0.6 | J30: =INDEX(Historicals!$F$21:$X$92,MATCH($D30,Historicals!$D$21:$D$92,0),MATCH(J$8,Historicals!$F$15:$X$15,0)) -> -0.9
D31: Litigation costs | F31: =INDEX(Historicals!$Z$21:$AD$92,MATCH($D31,Historicals!$D$21:$D$92,0),MATCH(F$8,Historicals!$Z$11:$AD$11,0)) -> 8.2 | G31: =INDEX(Historicals!$Z$21:$AD$92,MATCH($D31,Historicals!$D$21:$D$92,0),MATCH(G$8,Historicals!$Z$11:$AD$11,0)) -> -22.1 | H31: =INDEX(Historicals!$Z$21:$AD$92,MATCH($D31,Historicals!$D$21:$D$92,0),MATCH(H$8,Historicals!$Z$11:$AD$11,0)) -> 0 | J31: =INDEX(Historicals!$F$21:$X$92,MATCH($D31,Historicals!$D$21:$D$92,0),MATCH(J$8,Historicals!$F$15:$X$15,0)) -> 0
D32: Other Costs | F32: =INDEX(Historicals!$Z$21:$AD$92,MATCH($D32,Historicals!$D$21:$D$92,0),MATCH(F$8,Historicals!$Z$11:$AD$11,0)) -> 11.2 | G32: =INDEX(Historicals!$Z$21:$AD$92,MATCH($D32,Historicals!$D$21:$D$92,0),MATCH(G$8,Historicals!$Z$11:$AD$11,0)) -> 7.8 | H32: =INDEX(Historicals!$Z$21:$AD$92,MATCH($D32,Historicals!$D$21:$D$92,0),MATCH(H$8,Historicals!$Z$11:$AD$11,0)) -> 18.5 | J32: =INDEX(Historicals!$F$21:$X$92,MATCH($D32,Historicals!$D$21:$D$92,0),MATCH(J$8,Historicals!$F$15:$X$15,0)) -> 5.4
D33: Adjusted EBITDA | F33: =INDEX(Historicals!$Z$21:$AD$92,MATCH($D33,Historicals!$D$21:$D$92,0),MATCH(F$8,Historicals!$Z$11:$AD$11,0)) -> 131.389 | G33: =INDEX(Historicals!$Z$21:$AD$92,MATCH($D33,Historicals!$D$21:$D$92,0),MATCH(G$8,Historicals!$Z$11:$AD$11,0)) -> 118.912 | H33: =INDEX(Historicals!$Z$21:$AD$92,MATCH($D33,Historicals!$D$21:$D$92,0),MATCH(H$8,Historicals!$Z$11:$AD$11,0)) -> 111.048 | I33: =INDEX(Historicals!$Z$21:$AD$92,MATCH($D33,Historicals!$D$21:$D$92,0),MATCH(I$8,Historicals!$Z$11:$AD$11,0)) -> 102.837 | J33: =INDEX(Historicals!$F$21:$X$92,MATCH($D33,Historicals!$D$21:$D$92,0),MATCH(J$8,Historicals!$F$15:$X$15,0)) -> 29.828 | K33: =INDEX(Historicals!$F$21:$X$92,MATCH($D33,Historicals!$D$21:$D$92,0),MATCH(K$8,Historicals!$F$15:$X$15,0)) -> 23.4
D34: Check: | F34: =ROUND(SUM(F30:F32,F27,-F33),0) -> 0 | G34: =ROUND(SUM(G30:G32,G27,-G33),0) -> 0 | H34: =ROUND(SUM(H30:H32,H27,-H33),0) -> 0 | J34: =ROUND(SUM(J30:J32,J27,-J33),0) -> 0
D36: Free Cash Flow Build
D37: Reported EBITDA | F37: =INDEX(Historicals!$Z$284:$AD$292,MATCH($D37,Historicals!$D$284:$D$292,0),MATCH(F$8,Historicals!$Z$11:$AD$11,0)) -> 112.889 | G37: =INDEX(Historicals!$Z$284:$AD$292,MATCH($D37,Historicals!$D$284:$D$292,0),MATCH(G$8,Historicals!$Z$11:$AD$11,0)) -> 133.512 | H37: =INDEX(Historicals!$Z$284:$AD$292,MATCH($D37,Historicals!$D$284:$D$292,0),MATCH(H$8,Historicals!$Z$11:$AD$11,0)) -> 93.148 | I37: =INDEX(Historicals!$Z$284:$AD$292,MATCH($D37,Historicals!$D$284:$D$292,0),MATCH(I$8,Historicals!$Z$11:$AD$11,0)) -> 88.286 | J37: =INDEX(Historicals!$F$284:$X$292,MATCH($D37,Historicals!$D$284:$D$292,0),MATCH(J$8,Historicals!$F$15:$X$15,0)) -> 25.328 | K37: =INDEX(Historicals!$F$284:$X$292,MATCH($D37,Historicals!$D$284:$D$292,0),MATCH(K$8,Historicals!$F$15:$X$15,0)) -> 21.549
D38: Est. Change in NWC | F38: =INDEX(Historicals!$Z$284:$AD$292,MATCH($D38,Historicals!$D$284:$D$292,0),MATCH(F$8,Historicals!$Z$11:$AD$11,0)) -> 6.2528 | G38: =INDEX(Historicals!$Z$284:$AD$292,MATCH($D38,Historicals!$D$284:$D$292,0),MATCH(G$8,Historicals!$Z$11:$AD$11,0)) -> 11.2678 | H38: =INDEX(Historicals!$Z$284:$AD$292,MATCH($D38,Historicals!$D$284:$D$292,0),MATCH(H$8,Historicals!$Z$11:$AD$11,0)) -> 12.5904 | I38: =INDEX(Historicals!$Z$284:$AD$292,MATCH($D38,Historicals!$D$284:$D$292,0),MATCH(I$8,Historicals!$Z$11:$AD$11,0)) -> 45.5605 | J38: =INDEX(Historicals!$F$284:$X$292,MATCH($D38,Historicals!$D$284:$D$292,0),MATCH(J$8,Historicals!$F$15:$X$15,0)) -> -12.76405 | K38: =INDEX(Historicals!$F$284:$X$292,MATCH($D38,Historicals!$D$284:$D$292,0),MATCH(K$8,Historicals!$F$15:$X$15,0)) -> -1.324
D39: Est. Capex in NWC | F39: =INDEX(Historicals!$Z$284:$AD$292,MATCH($D39,Historicals!$D$284:$D$292,0),MATCH(F$8,Historicals!$Z$11:$AD$11,0)) -> -35.4548 | G39: =INDEX(Historicals!$Z$284:$AD$292,MATCH($D39,Historicals!$D$284:$D$292,0),MATCH(G$8,Historicals!$Z$11:$AD$11,0)) -> -35.4548 | H39: =INDEX(Historicals!$Z$284:$AD$292,MATCH($D39,Historicals!$D$284:$D$292,0),MATCH(H$8,Historicals!$Z$11:$AD$11,0)) -> -17.7274 | I39: =INDEX(Historicals!$Z$284:$AD$292,MATCH($D39,Historicals!$D$284:$D$292,0),MATCH(I$8,Historicals!$Z$11:$AD$11,0)) -> -2.8421709e-14 | J39: =INDEX(Historicals!$F$284:$X$292,MATCH($D39,Historicals!$D$284:$D$292,0),MATCH(J$8,Historicals!$F$15:$X$15,0)) -> -8.8637 | K39: =INDEX(Historicals!$F$284:$X$292,MATCH($D39,Historicals!$D$284:$D$292,0),MATCH(K$8,Historicals!$F$15:$X$15,0)) -> 0
D40: Reported Capital Expenditures | F40: =INDEX(Historicals!$Z$284:$AD$292,MATCH($D40,Historicals!$D$284:$D$292,0),MATCH(F$8,Historicals!$Z$11:$AD$11,0)) -> -85.428 | G40: =INDEX(Historicals!$Z$284:$AD$292,MATCH($D40,Historicals!$D$284:$D$292,0),MATCH(G$8,Historicals!$Z$11:$AD$11,0)) -> -73.773 | H40: =INDEX(Historicals!$Z$284:$AD$292,MATCH($D40,Historicals!$D$284:$D$292,0),MATCH(H$8,Historicals!$Z$11:$AD$11,0)) -> -42.043 | I40: =INDEX(Historicals!$Z$284:$AD$292,MATCH($D40,Historicals!$D$284:$D$292,0),MATCH(I$8,Historicals!$Z$11:$AD$11,0)) -> -23.31 | J40: =INDEX(Historicals!$F$284:$X$292,MATCH($D40,Historicals!$D$284:$D$292,0),MATCH(J$8,Historicals!$F$15:$X$15,0)) -> -10.519 | K40: =INDEX(Historicals!$F$284:$X$292,MATCH($D40,Historicals!$D$284:$D$292,0),MATCH(K$8,Historicals!$F$15:$X$15,0)) -> -3.588
D41: One-Time Items | F41: =INDEX(Historicals!$Z$284:$AD$292,MATCH($D41,Historicals!$D$284:$D$292,0),MATCH(F$8,Historicals!$Z$11:$AD$11,0)) -> 11.343 | G41: =INDEX(Historicals!$Z$284:$AD$292,MATCH($D41,Historicals!$D$284:$D$292,0),MATCH(G$8,Historicals!$Z$11:$AD$11,0)) -> -11.607 | H41: =INDEX(Historicals!$Z$284:$AD$292,MATCH($D41,Historicals!$D$284:$D$292,0),MATCH(H$8,Historicals!$Z$11:$AD$11,0)) -> -25.344 | I41: =INDEX(Historicals!$Z$284:$AD$292,MATCH($D41,Historicals!$D$284:$D$292,0),MATCH(I$8,Historicals!$Z$11:$AD$11,0)) -> -48.4255 | J41: =INDEX(Historicals!$F$284:$X$292,MATCH($D41,Historicals!$D$284:$D$292,0),MATCH(J$8,Historicals!$F$15:$X$15,0)) -> -0.42225 | K41: =INDEX(Historicals!$F$284:$X$292,MATCH($D41,Historicals!$D$284:$D$292,0),MATCH(K$8,Historicals!$F$15:$X$15,0)) -> -4.157
D42: Unlevered Free Cash Flow | F42: =INDEX(Historicals!$Z$284:$AD$292,MATCH($D42,Historicals!$D$284:$D$292,0),MATCH(F$8,Historicals!$Z$11:$AD$11,0)) -> 9.602 | G42: =INDEX(Historicals!$Z$284:$AD$292,MATCH($D42,Historicals!$D$284:$D$292,0),MATCH(G$8,Historicals!$Z$11:$AD$11,0)) -> 23.945 | H42: =INDEX(Historicals!$Z$284:$AD$292,MATCH($D42,Historicals!$D$284:$D$292,0),MATCH(H$8,Historicals!$Z$11:$AD$11,0)) -> 20.624 | I42: =INDEX(Historicals!$Z$284:$AD$292,MATCH($D42,Historicals!$D$284:$D$292,0),MATCH(I$8,Historicals!$Z$11:$AD$11,0)) -> 62.111 | J42: =INDEX(Historicals!$F$284:$X$292,MATCH($D42,Historicals!$D$284:$D$292,0),MATCH(J$8,Historicals!$F$15:$X$15,0)) -> -7.241 | K42: =INDEX(Historicals!$F$284:$X$292,MATCH($D42,Historicals!$D$284:$D$292,0),MATCH(K$8,Historicals!$F$15:$X$15,0)) -> 12.48
D43: Check: | F43: =ROUND(SUM(F37:F41,-F42),0) -> 0 | G43: =ROUND(SUM(G37:G41,-G42),0) -> 0 | H43: =ROUND(SUM(H37:H41,-H42),0) -> 0 | I43: =ROUND(SUM(I37:I41,-I42),0) -> 0 | J43: =ROUND(SUM(J37:J41,-J42),0) -> 0 | K43: =ROUND(SUM(K37:K41,-K42),0) -> 0
D45: Less: Interest Expense (incl. leases) | F45: =INDEX(Historicals!$Z$284:$AD$292,MATCH($D45,Historicals!$D$284:$D$292,0),MATCH(F$8,Historicals!$Z$11:$AD$11,0)) -> -61.787 | G45: =INDEX(Historicals!$Z$284:$AD$292,MATCH($D45,Historicals!$D$284:$D$292,0),MATCH(G$8,Historicals!$Z$11:$AD$11,0)) -> -66.85 | H45: =INDEX(Historicals!$Z$284:$AD$292,MATCH($D45,Historicals!$D$284:$D$292,0),MATCH(H$8,Historicals!$Z$11:$AD$11,0)) -> -61.049 | I45: =INDEX(Historicals!$Z$284:$AD$292,MATCH($D45,Historicals!$D$284:$D$292,0),MATCH(I$8,Historicals!$Z$11:$AD$11,0)) -> -56.246 | J45: =INDEX(Historicals!$F$284:$X$292,MATCH($D45,Historicals!$D$284:$D$292,0),MATCH(J$8,Historicals!$F$15:$X$15,0)) -> -16.868 | K45: =INDEX(Historicals!$F$284:$X$292,MATCH($D45,Historicals!$D$284:$D$292,0),MATCH(K$8,Historicals!$F$15:$X$15,0)) -> -14.815
D46: Less: Mandatory Debt Repayments | F46: =INDEX(Historicals!$Z$284:$AD$292,MATCH($D46,Historicals!$D$284:$D$292,0),MATCH(F$8,Historicals!$Z$11:$AD$11,0)) -> -9.2 | G46: =INDEX(Historicals!$Z$284:$AD$292,MATCH($D46,Historicals!$D$284:$D$292,0),MATCH(G$8,Historicals!$Z$11:$AD$11,0)) -> -9.2 | H46: =INDEX(Historicals!$Z$284:$AD$292,MATCH($D46,Historicals!$D$284:$D$292,0),MATCH(H$8,Historicals!$Z$11:$AD$11,0)) -> -9.2 | I46: =INDEX(Historicals!$Z$284:$AD$292,MATCH($D46,Historicals!$D$284:$D$292,0),MATCH(I$8,Historicals!$Z$11:$AD$11,0)) -> -9.2 | J46: =INDEX(Historicals!$F$284:$X$292,MATCH($D46,Historicals!$D$284:$D$292,0),MATCH(J$8,Historicals!$F$15:$X$15,0)) -> -2.3 | K46: =INDEX(Historicals!$F$284:$X$292,MATCH($D46,Historicals!$D$284:$D$292,0),MATCH(K$8,Historicals!$F$15:$X$15,0)) -> -2.3
D47: Levered Free Cash Flow | F47: =INDEX(Historicals!$Z$284:$AD$292,MATCH($D47,Historicals!$D$284:$D$292,0),MATCH(F$8,Historicals!$Z$11:$AD$11,0)) -> -61.385 | G47: =INDEX(Historicals!$Z$284:$AD$292,MATCH($D47,Historicals!$D$284:$D$292,0),MATCH(G$8,Historicals!$Z$11:$AD$11,0)) -> -52.105 | H47: =INDEX(Historicals!$Z$284:$AD$292,MATCH($D47,Historicals!$D$284:$D$292,0),MATCH(H$8,Historicals!$Z$11:$AD$11,0)) -> -49.625 | I47: =INDEX(Historicals!$Z$284:$AD$292,MATCH($D47,Historicals!$D$284:$D$292,0),MATCH(I$8,Historicals!$Z$11:$AD$11,0)) -> -3.335 | J47: =INDEX(Historicals!$F$284:$X$292,MATCH($D47,Historicals!$D$284:$D$292,0),MATCH(J$8,Historicals!$F$15:$X$15,0)) -> -26.409 | K47: =INDEX(Historicals!$F$284:$X$292,MATCH($D47,Historicals!$D$284:$D$292,0),MATCH(K$8,Historicals!$F$15:$X$15,0)) -> -4.635
D48: Check: | F48: =ROUND(SUM(F45:F46,F42,-F47),0) -> 0 | G48: =ROUND(SUM(G45:G46,G42,-G47),0) -> 0 | H48: =ROUND(SUM(H45:H46,H42,-H47),0) -> 0 | I48: =ROUND(SUM(I45:I46,I42,-I47),0) -> 0 | J48: =ROUND(SUM(J45:J46,J42,-J47),0) -> 0 | K48: =ROUND(SUM(K45:K46,K42,-K47),0) -> 0
D50: Memo Items:
D51: Revenue Growth | G51: =G16/F16-1 -> 0.015615337 | H51: =H16/G16-1 -> 0.028870452
D52: Gross Margin | F52: =F18/F16 -> 0.56014224 | G52: =G18/G16 -> 0.56294718 | H52: =H18/H16 -> 0.53123923 | I52: =I18/I16 -> 0.55686263 | J52: =J18/J16 -> 0.567387 | K52: =K18/K16 -> 0.61352311
D53: EBITDA Margin | F53: =F27/F16 -> 0.17453463 | G53: =G27/G16 -> 0.20324555 | H53: =H27/H16 -> 0.13782042 | I53: =I27/I16 -> 0.14311257 | J53: =J27/J16 -> 0.15682972 | K53: =K27/K16 -> 0.15608431
D54: Adj. EBITDA Margin | F54: =F33/F16 -> 0.20313698 | G54: =G33/G16 -> 0.18101994 | H54: =H33/H16 -> 0.164305 | I54: NA | J54: =J33/J16 -> 0.1846935 | K54: NA
D55: Change in NWC as a % of Revenue | F55: =F38/F16 -> 0.0096672851 | G55: =G38/G16 -> 0.017152991 | H55: =H38/H16 -> 0.018628572 | I55: =I38/I16 -> 0.073854067 | J55: =J38/J16 -> -0.079034365 | K55: =K38/K16 -> -0.0095900333
D56: Capex as a % of Revenue | F56: =-F40/F16 -> 0.13207792 | G56: =-G40/G16 -> 0.11230476 | H56: =-H40/H16 -> 0.06220621 | I56: =-I40/I16 -> 0.037785764 | J56: =-J40/J16 -> 0.065133127 | K56: =-K40/K16 -> 0.025988701
S90: 2Q24 | T90: 3Q24
S91: {=INDEX(F42:N42,0,MATCH(S90,F11:H11,0))} -> #N/A | T91: {=INDEX(F42:N42,0,MATCH(T90,F11:J11,0))} -> #N/A
D101: Liquidity Profile & Covenant Restrictions

Sheet O2
D3: ='Capital Structure'!D3 -> Bingo Industries | K3: DRAFT
D4: Statement of Cash Flows Output | K4: CONFIDENTIAL
D5: Data as of 2Q'26
D6: ($ millions)
F7: Year Ended | J7: Quarter Ended
F8: 2023 | G8: =F8+1 -> 2024 | H8: =G8+1 -> 2025 | I8: LTM | J8: ='O1'!J8 -> 2Q25 | K8: ='O1'!K8 -> 2Q26
F9: =Historicals!$AA$16 -> 45107 | G9: =Historicals!$AB$16 -> 45473 | H9: =Historicals!$AC$16 -> 45838 | I9: =Historicals!$AD$16 -> 46022 | J9: =Historicals!$T$16 -> 45657 | K9: =Historicals!$X$16 -> 46022
D11: Net Income (Loss) | F11: =Historicals!AA60 -> -462.201 | G11: =Historicals!AB60 -> -216.059 | H11: =Historicals!AC60 -> -93.257 | I11: =Historicals!AD60 -> -97.403 | J11: =Historicals!T60 -> 8.029 | K11: =Historicals!X60 -> -24.116
D13: Cash Flows From Operations
D14: Plus: Depreciation and amortization | F14: =-Historicals!AA52 -> 105.568 | G14: =-Historicals!AB52 -> 108.669 | H14: =-Historicals!AC52 -> 105.902 | I14: =-Historicals!AD52 -> 105.051 | J14: =-Historicals!T52 -> 26.945 | K14: =-Historicals!X52 -> 28.377
D15: Plus: Financing Costs | F15: =-Historicals!AA51 -> 151.681 | G15: =-Historicals!AB51 -> 182.971 | H15: =-Historicals!AC51 -> 86.738 | I15: =-Historicals!AD51 -> 90.026 | J15: =-Historicals!T51 -> -9.771 | K15: =-Historicals!X51 -> 20.359
D16: Plus: Impairment Expense | F16: =-Historicals!AA50 -> 385 | G16: =-Historicals!AB50 -> 160 | H16: =-Historicals!AC50 -> 0 | I16: =-Historicals!AD50 -> 0 | J16: =-Historicals!T50 -> 0 | K16: =-Historicals!X50 -> 0
D17: Less: Non-Cash Tax Benefits | F17: =-Historicals!AA55 -> -67.756 | G17: =-Historicals!AB55 -> -111.165 | H17: =-Historicals!AC55 -> -21.126 | I17: =-Historicals!AD55 -> -22.499 | J17: =-Historicals!T55 -> -6.29 | K17: =-Historicals!X55 -> -9.281
D18: Less: Gain on Fair Value Hedges, net of tax | F18: =SUM(Historicals!AA58:AA59) -> -0.597 | G18: =SUM(Historicals!AB58:AB59) -> -9.096 | H18: =SUM(Historicals!AC58:AC59) -> -14.891 | I18: =SUM(Historicals!AD58:AD59) -> -13.111 | J18: =SUM(Historicals!T58:T59) -> -6.415 | K18: =SUM(Historicals!X58:X59) -> -6.21
D19: Other Cash items | F19: =F26-SUM(F11,F14:F18,F21:F25) -> -22.9178 | G19: =G26-SUM(G11,G14:G18,G21:G25) -> -28.8698 | H19: =H26-SUM(H11,H14:H18,H21:H25) -> -13.2894 | I19: =I26-SUM(I11,I14:I18,I21:I25) -> -28.5945 | J19: =J26-SUM(J11,J14:J18,J21:J25) -> 3.68305 | K19: =K26-SUM(K11,K14:K18,K21:K25) -> 7.555
D20: Decrease (increase) in:
D21: Adj. Trade and other receivables | F21: =Historicals!AA235 -> -21.129 | G21: =Historicals!AB235 -> -8.65 | H21: =Historicals!AC235 -> 6.943 | I21: =Historicals!AD235 -> 39.7255 | J21: =Historicals!T235 -> -6.77275 | K21: =Historicals!X235 -> -6.391
D22: Inventories | F22: =Historicals!Z259-Historicals!AA259 -> -0.298 | G22: =Historicals!AA259-Historicals!AB259 -> 0.299 | H22: =Historicals!AB259-Historicals!AC259 -> 2.112 | I22: =Historicals!T259-Historicals!AD259 -> 1.133 | J22: =Historicals!U259-Historicals!T259 -> 0.706 | K22: =Historicals!V259-Historicals!X259 -> 1.321
D23: Adj. Other Assets (ex. Derivative Assets) | F23: =Historicals!AA247 -> 2.708 | G23: =Historicals!AB247 -> -1.687 | H23: =Historicals!AC247 -> -20.633 | I23: =Historicals!AD247 -> 5.002 | J23: =Historicals!T247 -> 0.401 | K23: =Historicals!X247 -> 10.585
D24: Increase (decrease) in:
D25: Adj. Trade and other payables | F25: =Historicals!AA255 -> 24.9718 | G25: =Historicals!AB255 -> 21.3058 | H25: =Historicals!AC255 -> 24.1684 | I25: =Historicals!AD255 -> 6.091 | J25: =Historicals!T255 -> -7.2373 | K25: =Historicals!X255 -> -6.131
D26: Net cash flows provided by (used in) operating activities | F26: =Historicals!AA162 -> 95.03 | G26: =Historicals!AB162 -> 97.718 | H26: =Historicals!AC162 -> 62.667 | I26: =Historicals!AD162 -> 85.421 | J26: =Historicals!T162 -> 3.278 | K26: =Historicals!X162 -> 16.068
D27: Check: | F27: =ROUND(SUM(F11:F25,-F26),1) -> 0 | G27: =ROUND(SUM(G11:G25,-G26),1) -> 0 | H27: =ROUND(SUM(H11:H25,-H26),1) -> 0 | I27: =ROUND(SUM(I11:I25,-I26),1) -> 0 | J27: =ROUND(SUM(J11:J25,-J26),1) -> 0 | K27: =ROUND(SUM(K11:K25,-K26),1) -> 0
D29: Cash Flows From Investing
D30: Purchase of property, plant and equipment | F30: =INDEX(Historicals!$Z$159:$AD$195,MATCH($D30,Historicals!$D$159:$D$195,0),MATCH(F$8,Historicals!$Z$11:$AD$11,0)) -> -85.428 | G30: =INDEX(Historicals!$Z$159:$AD$195,MATCH($D30,Historicals!$D$159:$D$195,0),MATCH(G$8,Historicals!$Z$11:$AD$11,0)) -> -73.773 | H30: =INDEX(Historicals!$Z$159:$AD$195,MATCH($D30,Historicals!$D$159:$D$195,0),MATCH(H$8,Historicals!$Z$11:$AD$11,0)) -> -42.043 | I30: =INDEX(Historicals!$Z$159:$AD$195,MATCH($D30,Historicals!$D$159:$D$195,0),MATCH(I$8,Historicals!$Z$11:$AD$11,0)) -> -23.31 | J30: =INDEX(Historicals!$F$159:$X$195,MATCH($D30,Historicals!$D$159:$D$195,0),MATCH(J$8,Historicals!$F$15:$X$15,0)) -> -10.519 | K30: =INDEX(Historicals!$F$159:$X$195,MATCH($D30,Historicals!$D$159:$D$195,0),MATCH(K$8,Historicals!$F$15:$X$15,0)) -> -3.588
D31: Purchase of business | F31: =INDEX(Historicals!$Z$159:$AD$195,MATCH($D31,Historicals!$D$159:$D$195,0),MATCH(F$8,Historicals!$Z$11:$AD$11,0)) -> -21.482 | G31: =INDEX(Historicals!$Z$159:$AD$195,MATCH($D31,Historicals!$D$159:$D$195,0),MATCH(G$8,Historicals!$Z$11:$AD$11,0)) -> -3.607 | H31: =INDEX(Historicals!$Z$159:$AD$195,MATCH($D31,Historicals!$D$159:$D$195,0),MATCH(H$8,Historicals!$Z$11:$AD$11,0)) -> 0 | I31: =INDEX(Historicals!$Z$159:$AD$195,MATCH($D31,Historicals!$D$159:$D$195,0),MATCH(I$8,Historicals!$Z$11:$AD$11,0)) -> 0 | J31: =INDEX(Historicals!$F$159:$X$195,MATCH($D31,Historicals!$D$159:$D$195,0),MATCH(J$8,Historicals!$F$15:$X$15,0)) -> 0 | K31: =INDEX(Historicals!$F$159:$X$195,MATCH($D31,Historicals!$D$159:$D$195,0),MATCH(K$8,Historicals!$F$15:$X$15,0)) -> 0
D32: Purchase of intangible assets | F32: =INDEX(Historicals!$Z$159:$AD$195,MATCH($D32,Historicals!$D$159:$D$195,0),MATCH(F$8,Historicals!$Z$11:$AD$11,0)) -> -7.961 | G32: =INDEX(Historicals!$Z$159:$AD$195,MATCH($D32,Historicals!$D$159:$D$195,0),MATCH(G$8,Historicals!$Z$11:$AD$11,0)) -> -5.876 | H32: =INDEX(Historicals!$Z$159:$AD$195,MATCH($D32,Historicals!$D$159:$D$195,0),MATCH(H$8,Historicals!$Z$11:$AD$11,0)) -> -3.371 | I32: =INDEX(Historicals!$Z$159:$AD$195,MATCH($D32,Historicals!$D$159:$D$195,0),MATCH(I$8,Historicals!$Z$11:$AD$11,0)) -> -2.45 | J32: =INDEX(Historicals!$F$159:$X$195,MATCH($D32,Historicals!$D$159:$D$195,0),MATCH(J$8,Historicals!$F$15:$X$15,0)) -> -0.308 | K32: =INDEX(Historicals!$F$159:$X$195,MATCH($D32,Historicals!$D$159:$D$195,0),MATCH(K$8,Historicals!$F$15:$X$15,0)) -> -0.052
D33: Payments for Land Option | F33: =INDEX(Historicals!$Z$159:$AD$195,MATCH($D33,Historicals!$D$159:$D$195,0),MATCH(F$8,Historicals!$Z$11:$AD$11,0)) -> 0 | G33: =INDEX(Historicals!$Z$159:$AD$195,MATCH($D33,Historicals!$D$159:$D$195,0),MATCH(G$8,Historicals!$Z$11:$AD$11,0)) -> 0 | H33: =INDEX(Historicals!$Z$159:$AD$195,MATCH($D33,Historicals!$D$159:$D$195,0),MATCH(H$8,Historicals!$Z$11:$AD$11,0)) -> -103.39 | I33: =INDEX(Historicals!$Z$159:$AD$195,MATCH($D33,Historicals!$D$159:$D$195,0),MATCH(I$8,Historicals!$Z$11:$AD$11,0)) -> -103.39 | J33: =INDEX(Historicals!$F$159:$X$195,MATCH($D33,Historicals!$D$159:$D$195,0),MATCH(J$8,Historicals!$F$15:$X$15,0)) -> 0 | K33: =INDEX(Historicals!$F$159:$X$195,MATCH($D33,Historicals!$D$159:$D$195,0),MATCH(K$8,Historicals!$F$15:$X$15,0)) -> 0
D34: Proceeds from Disposal of Assets Held For Sale | F34: =INDEX(Historicals!$Z$159:$AD$195,MATCH($D34,Historicals!$D$159:$D$195,0),MATCH(F$8,Historicals!$Z$11:$AD$11,0)) -> 0 | G34: =INDEX(Historicals!$Z$159:$AD$195,MATCH($D34,Historicals!$D$159:$D$195,0),MATCH(G$8,Historicals!$Z$11:$AD$11,0)) -> 0 | H34: =INDEX(Historicals!$Z$159:$AD$195,MATCH($D34,Historicals!$D$159:$D$195,0),MATCH(H$8,Historicals!$Z$11:$AD$11,0)) -> 64.049 | I34: =INDEX(Historicals!$Z$159:$AD$195,MATCH($D34,Historicals!$D$159:$D$195,0),MATCH(I$8,Historicals!$Z$11:$AD$11,0)) -> 64.049 | J34: =INDEX(Historicals!$F$159:$X$195,MATCH($D34,Historicals!$D$159:$D$195,0),MATCH(J$8,Historicals!$F$15:$X$15,0)) -> 0 | K34: =INDEX(Historicals!$F$159:$X$195,MATCH($D34,Historicals!$D$159:$D$195,0),MATCH(K$8,Historicals!$F$15:$X$15,0)) -> 0
D35: Proceeds from sale of non-current assets | F35: =INDEX(Historicals!$Z$159:$AD$195,MATCH($D35,Historicals!$D$159:$D$195,0),MATCH(F$8,Historicals!$Z$11:$AD$11,0)) -> 40.724 | G35: =INDEX(Historicals!$Z$159:$AD$195,MATCH($D35,Historicals!$D$159:$D$195,0),MATCH(G$8,Historicals!$Z$11:$AD$11,0)) -> 1.415 | H35: =INDEX(Historicals!$Z$159:$AD$195,MATCH($D35,Historicals!$D$159:$D$195,0),MATCH(H$8,Historicals!$Z$11:$AD$11,0)) -> 2.549 | I35: =INDEX(Historicals!$Z$159:$AD$195,MATCH($D35,Historicals!$D$159:$D$195,0),MATCH(I$8,Historicals!$Z$11:$AD$11,0)) -> -9.95 | J35: =INDEX(Historicals!$F$159:$X$195,MATCH($D35,Historicals!$D$159:$D$195,0),MATCH(J$8,Historicals!$F$15:$X$15,0)) -> 3.119 | K35: =INDEX(Historicals!$F$159:$X$195,MATCH($D35,Historicals!$D$159:$D$195,0),MATCH(K$8,Historicals!$F$15:$X$15,0)) -> 0
D36: Deposites at call for bank guarantees | F36: =INDEX(Historicals!$Z$159:$AD$195,MATCH($D36,Historicals!$D$159:$D$195,0),MATCH(F$8,Historicals!$Z$11:$AD$11,0)) -> 0 | G36: =INDEX(Historicals!$Z$159:$AD$195,MATCH($D36,Historicals!$D$159:$D$195,0),MATCH(G$8,Historicals!$Z$11:$AD$11,0)) -> 0 | H36: =INDEX(Historicals!$Z$159:$AD$195,MATCH($D36,Historicals!$D$159:$D$195,0),MATCH(H$8,Historicals!$Z$11:$AD$11,0)) -> -0.914 | I36: =INDEX(Historicals!$Z$159:$AD$195,MATCH($D36,Historicals!$D$159:$D$195,0),MATCH(I$8,Historicals!$Z$11:$AD$11,0)) -> -0.914 | J36: =INDEX(Historicals!$F$159:$X$195,MATCH($D36,Historicals!$D$159:$D$195,0),MATCH(J$8,Historicals!$F$15:$X$15,0)) -> 0 | K36: =INDEX(Historicals!$F$159:$X$195,MATCH($D36,Historicals!$D$159:$D$195,0),MATCH(K$8,Historicals!$F$15:$X$15,0)) -> 0
D37: Interest received | F37: =INDEX(Historicals!$Z$159:$AD$195,MATCH($D37,Historicals!$D$159:$D$195,0),MATCH(F$8,Historicals!$Z$11:$AD$11,0)) -> 3.02 | G37: =INDEX(Historicals!$Z$159:$AD$195,MATCH($D37,Historicals!$D$159:$D$195,0),MATCH(G$8,Historicals!$Z$11:$AD$11,0)) -> 3.457 | H37: =INDEX(Historicals!$Z$159:$AD$195,MATCH($D37,Historicals!$D$159:$D$195,0),MATCH(H$8,Historicals!$Z$11:$AD$11,0)) -> 1.424 | I37: =INDEX(Historicals!$Z$159:$AD$195,MATCH($D37,Historicals!$D$159:$D$195,0),MATCH(I$8,Historicals!$Z$11:$AD$11,0)) -> 0.967 | J37: =INDEX(Historicals!$F$159:$X$195,MATCH($D37,Historicals!$D$159:$D$195,0),MATCH(J$8,Historicals!$F$15:$X$15,0)) -> 0.55 | K37: =INDEX(Historicals!$F$159:$X$195,MATCH($D37,Historicals!$D$159:$D$195,0),MATCH(K$8,Historicals!$F$15:$X$15,0)) -> 0.129
D38: Net cash flows provided by (used in) investing activities | F38: =INDEX(Historicals!$Z$159:$AD$195,MATCH($D38,Historicals!$D$159:$D$195,0),MATCH(F$8,Historicals!$Z$11:$AD$11,0)) -> -71.127 | G38: =INDEX(Historicals!$Z$159:$AD$195,MATCH($D38,Historicals!$D$159:$D$195,0),MATCH(G$8,Historicals!$Z$11:$AD$11,0)) -> -78.384 | H38: =INDEX(Historicals!$Z$159:$AD$195,MATCH($D38,Historicals!$D$159:$D$195,0),MATCH(H$8,Historicals!$Z$11:$AD$11,0)) -> -81.696 | I38: =INDEX(Historicals!$Z$159:$AD$195,MATCH($D38,Historicals!$D$159:$D$195,0),MATCH(I$8,Historicals!$Z$11:$AD$11,0)) -> -74.998 | J38: =INDEX(Historicals!$F$159:$X$195,MATCH($D38,Historicals!$D$159:$D$195,0),MATCH(J$8,Historicals!$F$15:$X$15,0)) -> -7.158 | K38: =INDEX(Historicals!$F$159:$X$195,MATCH($D38,Historicals!$D$159:$D$195,0),MATCH(K$8,Historicals!$F$15:$X$15,0)) -> -3.511
D39: Check: | F39: =ROUND(SUM(F30:F37,-F38),1) -> 0 | G39: =ROUND(SUM(G30:G37,-G38),1) -> 0 | H39: =ROUND(SUM(H30:H37,-H38),1) -> 0 | I39: =ROUND(SUM(I30:I37,-I38),1) -> 0 | J39: =ROUND(SUM(J30:J37,-J38),1) -> 0 | K39: =ROUND(SUM(K30:K37,-K38),1) -> 0
D41: Cash Flows From Financing
D42: Proceeds from share issue | F42: =INDEX(Historicals!$Z$159:$AD$195,MATCH($D42,Historicals!$D$159:$D$195,0),MATCH(F$8,Historicals!$Z$11:$AD$11,0)) -> 0 | G42: =INDEX(Historicals!$Z$159:$AD$195,MATCH($D42,Historicals!$D$159:$D$195,0),MATCH(G$8,Historicals!$Z$11:$AD$11,0)) -> 0 | H42: =INDEX(Historicals!$Z$159:$AD$195,MATCH($D42,Historicals!$D$159:$D$195,0),MATCH(H$8,Historicals!$Z$11:$AD$11,0)) -> 0 | I42: =INDEX(Historicals!$Z$159:$AD$195,MATCH($D42,Historicals!$D$159:$D$195,0),MATCH(I$8,Historicals!$Z$11:$AD$11,0)) -> 0 | J42: =INDEX(Historicals!$F$159:$X$195,MATCH($D42,Historicals!$D$159:$D$195,0),MATCH(J$8,Historicals!$F$15:$X$15,0)) -> 0 | K42: =INDEX(Historicals!$F$159:$X$195,MATCH($D42,Historicals!$D$159:$D$195,0),MATCH(K$8,Historicals!$F$15:$X$15,0)) -> 0
D43: (Repayment of) / proceeds from related party loan | F43: =INDEX(Historicals!$Z$159:$AD$195,MATCH($D43,Historicals!$D$159:$D$195,0),MATCH(F$8,Historicals!$Z$11:$AD$11,0)) -> -8.868 | G43: =INDEX(Historicals!$Z$159:$AD$195,MATCH($D43,Historicals!$D$159:$D$195,0),MATCH(G$8,Historicals!$Z$11:$AD$11,0)) -> -1.724 | H43: =INDEX(Historicals!$Z$159:$AD$195,MATCH($D43,Historicals!$D$159:$D$195,0),MATCH(H$8,Historicals!$Z$11:$AD$11,0)) -> 40 | I43: =INDEX(Historicals!$Z$159:$AD$195,MATCH($D43,Historicals!$D$159:$D$195,0),MATCH(I$8,Historicals!$Z$11:$AD$11,0)) -> 45.501 | J43: =INDEX(Historicals!$F$159:$X$195,MATCH($D43,Historicals!$D$159:$D$195,0),MATCH(J$8,Historicals!$F$15:$X$15,0)) -> 0.101 | K43: =INDEX(Historicals!$F$159:$X$195,MATCH($D43,Historicals!$D$159:$D$195,0),MATCH(K$8,Historicals!$F$15:$X$15,0)) -> -0.18
D44: (Repayment of) / proceeds from borrowing | F44: =INDEX(Historicals!$Z$159:$AD$195,MATCH($D44,Historicals!$D$159:$D$195,0),MATCH(F$8,Historicals!$Z$11:$AD$11,0)) -> -11.943 | G44: =INDEX(Historicals!$Z$159:$AD$195,MATCH($D44,Historicals!$D$159:$D$195,0),MATCH(G$8,Historicals!$Z$11:$AD$11,0)) -> -11.077 | H44: =INDEX(Historicals!$Z$159:$AD$195,MATCH($D44,Historicals!$D$159:$D$195,0),MATCH(H$8,Historicals!$Z$11:$AD$11,0)) -> 28.076 | I44: =INDEX(Historicals!$Z$159:$AD$195,MATCH($D44,Historicals!$D$159:$D$195,0),MATCH(I$8,Historicals!$Z$11:$AD$11,0)) -> 4.004 | J44: =INDEX(Historicals!$F$159:$X$195,MATCH($D44,Historicals!$D$159:$D$195,0),MATCH(J$8,Historicals!$F$15:$X$15,0)) -> 27.39 | K44: =INDEX(Historicals!$F$159:$X$195,MATCH($D44,Historicals!$D$159:$D$195,0),MATCH(K$8,Historicals!$F$15:$X$15,0)) -> -2.648
D45: Principal payment for lease liabilities | F45: =INDEX(Historicals!$Z$159:$AD$195,MATCH($D45,Historicals!$D$159:$D$195,0),MATCH(F$8,Historicals!$Z$11:$AD$11,0)) -> -8.436 | G45: =INDEX(Historicals!$Z$159:$AD$195,MATCH($D45,Historicals!$D$159:$D$195,0),MATCH(G$8,Historicals!$Z$11:$AD$11,0)) -> -8.691 | H45: =INDEX(Historicals!$Z$159:$AD$195,MATCH($D45,Historicals!$D$159:$D$195,0),MATCH(H$8,Historicals!$Z$11:$AD$11,0)) -> -14.929 | I45: =INDEX(Historicals!$Z$159:$AD$195,MATCH($D45,Historicals!$D$159:$D$195,0),MATCH(I$8,Historicals!$Z$11:$AD$11,0)) -> -18.237 | J45: =INDEX(Historicals!$F$159:$X$195,MATCH($D45,Historicals!$D$159:$D$195,0),MATCH(J$8,Historicals!$F$15:$X$15,0)) -> -2.487 | K45: =INDEX(Historicals!$F$159:$X$195,MATCH($D45,Historicals!$D$159:$D$195,0),MATCH(K$8,Historicals!$F$15:$X$15,0)) -> -3.631
D46: Debt raising cost | F46: =INDEX(Historicals!$Z$159:$AD$195,MATCH($D46,Historicals!$D$159:$D$195,0),MATCH(F$8,Historicals!$Z$11:$AD$11,0)) -> 0 | G46: =INDEX(Historicals!$Z$159:$AD$195,MATCH($D46,Historicals!$D$159:$D$195,0),MATCH(G$8,Historicals!$Z$11:$AD$11,0)) -> 0 | H46: =INDEX(Historicals!$Z$159:$AD$195,MATCH($D46,Historicals!$D$159:$D$195,0),MATCH(H$8,Historicals!$Z$11:$AD$11,0)) -> 0 | I46: =INDEX(Historicals!$Z$159:$AD$195,MATCH($D46,Historicals!$D$159:$D$195,0),MATCH(I$8,Historicals!$Z$11:$AD$11,0)) -> 0 | J46: =INDEX(Historicals!$F$159:$X$195,MATCH($D46,Historicals!$D$159:$D$195,0),MATCH(J$8,Historicals!$F$15:$X$15,0)) -> 0 | K46: =INDEX(Historicals!$F$159:$X$195,MATCH($D46,Historicals!$D$159:$D$195,0),MATCH(K$8,Historicals!$F$15:$X$15,0)) -> 0
D47: Finance costs paid | F47: =INDEX(Historicals!$Z$159:$AD$195,MATCH($D47,Historicals!$D$159:$D$195,0),MATCH(F$8,Historicals!$Z$11:$AD$11,0)) -> -61.787 | G47: =INDEX(Historicals!$Z$159:$AD$195,MATCH($D47,Historicals!$D$159:$D$195,0),MATCH(G$8,Historicals!$Z$11:$AD$11,0)) -> -66.85 | H47: =INDEX(Historicals!$Z$159:$AD$195,MATCH($D47,Historicals!$D$159:$D$195,0),MATCH(H$8,Historicals!$Z$11:$AD$11,0)) -> -61.049 | I47: =INDEX(Historicals!$Z$159:$AD$195,MATCH($D47,Historicals!$D$159:$D$195,0),MATCH(I$8,Historicals!$Z$11:$AD$11,0)) -> -56.246 | J47: =INDEX(Historicals!$F$159:$X$195,MATCH($D47,Historicals!$D$159:$D$195,0),MATCH(J$8,Historicals!$F$15:$X$15,0)) -> -16.868 | K47: =INDEX(Historicals!$F$159:$X$195,MATCH($D47,Historicals!$D$159:$D$195,0),MATCH(K$8,Historicals!$F$15:$X$15,0)) -> -14.815
D48: Payment of Capitalized Borrowing Costs | F48: =INDEX(Historicals!$Z$159:$AD$195,MATCH($D48,Historicals!$D$159:$D$195,0),MATCH(F$8,Historicals!$Z$11:$AD$11,0)) -> 0 | G48: =INDEX(Historicals!$Z$159:$AD$195,MATCH($D48,Historicals!$D$159:$D$195,0),MATCH(G$8,Historicals!$Z$11:$AD$11,0)) -> 0 | H48: =INDEX(Historicals!$Z$159:$AD$195,MATCH($D48,Historicals!$D$159:$D$195,0),MATCH(H$8,Historicals!$Z$11:$AD$11,0)) -> -0.726 | I48: =INDEX(Historicals!$Z$159:$AD$195,MATCH($D48,Historicals!$D$159:$D$195,0),MATCH(I$8,Historicals!$Z$11:$AD$11,0)) -> -0.726 | J48: =INDEX(Historicals!$F$159:$X$195,MATCH($D48,Historicals!$D$159:$D$195,0),MATCH(J$8,Historicals!$F$15:$X$15,0)) -> 0 | K48: =INDEX(Historicals!$F$159:$X$195,MATCH($D48,Historicals!$D$159:$D$195,0),MATCH(K$8,Historicals!$F$15:$X$15,0)) -> 0
D49: Settlement of Derivative Assets | F49: =INDEX(Historicals!$Z$159:$AD$195,MATCH($D49,Historicals!$D$159:$D$195,0),MATCH(F$8,Historicals!$Z$11:$AD$11,0)) -> 0 | G49: =INDEX(Historicals!$Z$159:$AD$195,MATCH($D49,Historicals!$D$159:$D$195,0),MATCH(G$8,Historicals!$Z$11:$AD$11,0)) -> 0 | H49: =INDEX(Historicals!$Z$159:$AD$195,MATCH($D49,Historicals!$D$159:$D$195,0),MATCH(H$8,Historicals!$Z$11:$AD$11,0)) -> 0 | I49: =INDEX(Historicals!$Z$159:$AD$195,MATCH($D49,Historicals!$D$159:$D$195,0),MATCH(I$8,Historicals!$Z$11:$AD$11,0)) -> 32.211 | J49: =INDEX(Historicals!$F$159:$X$195,MATCH($D49,Historicals!$D$159:$D$195,0),MATCH(J$8,Historicals!$F$15:$X$15,0)) -> 0 | K49: =INDEX(Historicals!$F$159:$X$195,MATCH($D49,Historicals!$D$159:$D$195,0),MATCH(K$8,Historicals!$F$15:$X$15,0)) -> 32.211
D50: Net cash flows provided by (used in) financing activities | F50: =INDEX(Historicals!$Z$159:$AD$195,MATCH($D50,Historicals!$D$159:$D$195,0),MATCH(F$8,Historicals!$Z$11:$AD$11,0)) -> -91.034 | G50: =INDEX(Historicals!$Z$159:$AD$195,MATCH($D50,Historicals!$D$159:$D$195,0),MATCH(G$8,Historicals!$Z$11:$AD$11,0)) -> -88.342 | H50: =INDEX(Historicals!$Z$159:$AD$195,MATCH($D50,Historicals!$D$159:$D$195,0),MATCH(H$8,Historicals!$Z$11:$AD$11,0)) -> -8.628 | I50: =INDEX(Historicals!$Z$159:$AD$195,MATCH($D50,Historicals!$D$159:$D$195,0),MATCH(I$8,Historicals!$Z$11:$AD$11,0)) -> 6.507 | J50: =INDEX(Historicals!$F$159:$X$195,MATCH($D50,Historicals!$D$159:$D$195,0),MATCH(J$8,Historicals!$F$15:$X$15,0)) -> 8.136 | K50: =INDEX(Historicals!$F$159:$X$195,MATCH($D50,Historicals!$D$159:$D$195,0),MATCH(K$8,Historicals!$F$15:$X$15,0)) -> 10.937
D51: Check: | F51: =ROUND(SUM(F42:F49,-F50),1) -> 0 | G51: =ROUND(SUM(G42:G49,-G50),1) -> 0 | H51: =ROUND(SUM(H42:H49,-H50),1) -> 0 | I51: =ROUND(SUM(I42:I49,-I50),1) -> 0 | J51: =ROUND(SUM(J42:J49,-J50),1) -> 0 | K51: =ROUND(SUM(K42:K49,-K50),1) -> 0
D53: Total Change in Cash | F53: =SUM(F26,F38,F50) -> -67.131 | G53: =SUM(G26,G38,G50) -> -69.008 | H53: =SUM(H26,H38,H50) -> -27.657 | I53: =SUM(I26,I38,I50) -> 16.93 | J53: =SUM(J26,J38,J50) -> 4.256 | K53: =SUM(K26,K38,K50) -> 23.494
D55: Cash at the beginning of the period | F55: =Historicals!AA193 -> 180.504 | G55: =F56 -> 113.373 | H55: =G56 -> 44.365 | I55: =Historicals!T105 -> 21.146 | J55: =Historicals!S105 -> 16.892 | K55: =Historicals!W105 -> 14.582
D56: Cash at the end of the period | F56: =SUM(F53,F55) -> 113.373 | G56: =SUM(G53,G55) -> 44.365 | H56: =SUM(H53,H55) -> 16.708 | I56: =SUM(I53,I55) -> 38.076 | J56: =SUM(J53,J55) -> 21.148 | K56: =SUM(K53,K55) -> 38.076
D57: Check: | F57: =ROUND(F56-Historicals!AA105,0) -> 0 | G57: =ROUND(G56-Historicals!AB105,0) -> 0 | H57: =ROUND(H56-Historicals!AC105,0) -> 0 | I57: =ROUND(I56-Historicals!AD105,0) -> 0 | J57: =ROUND(J56-Historicals!T105,0) -> 0 | K57: =ROUND(K56-Historicals!X105,0) -> 0

Sheet O3
D3: ='Capital Structure'!D3 -> Bingo Industries | G3: DRAFT | K3: =D3 -> Bingo Industries | L3: DRAFT
D4: Charts - Situation Overview | G4: CONFIDENTIAL | K4: Charts - Company Overview | L4: CONFIDENTIAL
D5: Data as of 2Q'26 | K5: Data as of 2Q'26
D6: ($ millions) | K6: ($ millions)
B8: x | D8: Total Revenue & Gross Margin | (A$ Millions) | K8: Revenue (A$ Millions)
B17: x | D17: Adjusted EBITDA Breakdown | (A$ Millions) | K17: Reported EBITDA (A$ Millions)
B26: x | D26: Cumulative Levered Free Cash Flow | (A$ Millions)
K28: Levered Free Cash Flow (A$ Millions)
B34: x | D34: Liquidity Profile | (A$ Millions)
B42: x | D42: Revolving Facility Balance | (A$ Millions)
B50: x | D50: Covenant Adj. EBITDA Headroom | (A$ Millions)
B57: x | D57: Segment Revenues | (A$ Millions)
B67: x | D67: Throughput & Recovery
B76: x | D76: Productivity & Uptime

Sheet Pricing
D3: Bingo Industries | H3: DRAFT
D4: Pricing | H4: CONFIDENTIAL
D5: Data as of March 2, 2026
D6: (A$ millions)
D8: Pulled from Debtwire
E10: AUD 75m RCF | F10: AUD 325m Term Loan B First Lien | G10: USD 375m Term Loan B First Lien | H10: AUD 100m SHL Facility
D11: Date | E11: Price | F11: Price | G11: Price
D12: 46100 | E12: 67.75 | F12: 68.5 | G12: 67.75 | H12: 68.5
D13: 46099 | E13: 67.75 | F13: 68.5 | G13: 67.75 | H13: 68.5
D14: 46098 | E14: 67.75 | F14: 68.5 | G14: 67.88 | H14: 68.5
D15: 46097 | E15: 67.75 | F15: 68.5 | G15: 67.88 | H15: 68.5
D16: 46094 | E16: 67.75 | F16: 68.5 | G16: 68.88 | H16: 68.5
D17: 46093 | E17: 67.75 | F17: 68.5 | G17: 68.13 | H17: 68.5
D18: 46092 | E18: 67.75 | F18: 68.5 | G18: 69.2 | H18: 68.5
D19: 46091 | E19: 67.75 | F19: 68.5 | G19: 69.8 | H19: 68.5
D20: 46090 | E20: 67.75 | F20: 68.5 | G20: 68.63 | H20: 68.5
D21: 46087 | E21: 67.75 | F21: 68.5 | G21: 68.66 | H21: 68.5
D22: 46086 | E22: 67.75 | F22: 68.5 | G22: 68.72 | H22: 68.5
D23: 46085 | E23: 67.75 | F23: 68.5 | G23: 69.06 | H23: 68.5
... D278: 45726 | E278: 71.73 | F278: 74.67 | G278: 76.96 | H278: 76.96
D279: 45723 | E279: 70.58 | F279: 74.67 | G279: 76.82
D280: 45722 | E280: 69.41 | F280: 73.5 | G280: 77
D281: 45721 | E281: 70.41 | F281: 74.5 | G281: 76.25
D282: 45720 | E282: 70.91 | F282: 75 | G282: 75.96
D283: 45719 | E283: 70.91 | F283: 75 | G283: 75.79
D284: 45716 | E284: 70.91 | F284: 75 | G284: 75.54
D285: 45715 | E285: 69.75 | F285: 73.83 | G285: 75.11
D286: 45714 | E286: 69.75 | F286: 73.83 | G286: 75.07
D287: 45713 | E287: 69.75 | F287: 73.83 | G287: 75.07
D288: 45712 | E288: 69.75 | F288: 73.83 | G288: 75.07
D289: 45709 | E289: 69.16 | F289: 73.25 | G289: 75.07
D290: 45708 | E290: 69.16 | F290: 73.25 | G290: 75.04
... D861: 44909 | E861: 83.41 | F861: 87.5 | G861: 91.42
D862: 44908 | G862: 91.42
D863: 44907 | G863: 91.42
D864: 44904 | G864: 91.42
D865: 44903 | G865: 91.42
D866: 44902 | G866: 91.42
D867: 44901 | G867: 91.67
D868: 44900 | G868: 91.67
D869: 44897 | G869: 91.67
D870: 44896 | G870: 91.67
D871: 44895 | G871: 91.67
D872: 44894 | G872: 91.67
D873: 44893 | G873: 91.67
... D1233: 44389 | G1233: 100.25

Sheet Sheet1
D3: Bingo Industries | H3: DRAFT
D4: Land Fill Data | H4: CONFIDENTIAL
D5: (A$ millions)
D7: Total Landfill | E7: NSW C&D to Landfill (Marketwide)(1) | F7: -0.17
D8: BINGO Easter Creek(2) | E8: Total Landfill | F8: -0.55
E9: External Volumes Only | F9: -0.69
G14: BINGO Easter Creek
F15: NSW C&D to Landfill (Marketwide) | G15: Total Landfill | H15: External Volumes Only
F16: -0.17 | G16: -0.55 | H16: -0.69
F21: =F14 | G21: =F15 -> NSW C&D to Landfill (Marketwide) | H21: =F16 -> -0.17
F22: =G14 -> BINGO Easter Creek | G22: =G15 -> Total Landfill | H22: =G16 -> -0.55
G23: =H15 -> External Volumes Only | H23: =H16 -> -0.69
