Workbook
Name \0: #REF!
Name \0: #REF!
Name \0: #REF!
Name \a: #REF!
Name \a: #REF!
Name \B: #REF!
Name \B: #REF!
Name \c: #N/A
Name \D: #REF!
Name \DD: #REF!
Name \E: #REF!
Name \f: #N/A
Name \G: #REF!
Name \H: #REF!
Name \I: #REF!
Name \J: #REF!
Name \K: #REF!
Name \l: #N/A
Name \m: #N/A
Name \N: #REF!
Name \O: #REF!
Name \P: #REF!
Name \q: #N/A
Name \r: #N/A
Name \S: #REF!
Name \t: #N/A
Name \U: #REF!
Name \V: #REF!
Name \w: #N/A
Name \X: #REF!
Name \Z: #REF!
Name _________________________vvv1: {"bbtday",#N/A,FALSE,"ban0930";"banksday",#N/A,FALSE,"ban0930";"compday",#N/A,FALSE,"ban0930"}
Name _________________________vvv1: {"bbtday",#N/A,FALSE,"ban0930";"banksday",#N/A,FALSE,"ban0930";"compday",#N/A,FALSE,"ban0930"}
Name _________________________vvv1: {"bbtday",#N/A,FALSE,"ban0930";"banksday",#N/A,FALSE,"ban0930";"compday",#N/A,FALSE,"ban0930"}
Name _________________________x1: {"compweek",#N/A,FALSE,"ban0930";"bankweek",#N/A,FALSE,"ban0930"}
Name _________________________x1: {"compweek",#N/A,FALSE,"ban0930";"bankweek",#N/A,FALSE,"ban0930"}
Name _________________________x1: {"compweek",#N/A,FALSE,"ban0930";"bankweek",#N/A,FALSE,"ban0930"}
Name _________________________y1: {"bbtday",#N/A,FALSE,"ban0930";"banksday",#N/A,FALSE,"ban0930";"compday",#N/A,FALSE,"ban0930"}
Name _________________________y1: {"bbtday",#N/A,FALSE,"ban0930";"banksday",#N/A,FALSE,"ban0930";"compday",#N/A,FALSE,"ban0930"}
Name _________________________y1: {"bbtday",#N/A,FALSE,"ban0930";"banksday",#N/A,FALSE,"ban0930";"compday",#N/A,FALSE,"ban0930"}
Name ________________________vvv1: {"bbtday",#N/A,FALSE,"ban0930";"banksday",#N/A,FALSE,"ban0930";"compday",#N/A,FALSE,"ban0930"}
Name ________________________vvv1: {"bbtday",#N/A,FALSE,"ban0930";"banksday",#N/A,FALSE,"ban0930";"compday",#N/A,FALSE,"ban0930"}
Name ________________________vvv1: {"bbtday",#N/A,FALSE,"ban0930";"banksday",#N/A,FALSE,"ban0930";"compday",#N/A,FALSE,"ban0930"}
Name ________________________x1: {"compweek",#N/A,FALSE,"ban0930";"bankweek",#N/A,FALSE,"ban0930"}
Name ________________________x1: {"compweek",#N/A,FALSE,"ban0930";"bankweek",#N/A,FALSE,"ban0930"}
Name ________________________x1: {"compweek",#N/A,FALSE,"ban0930";"bankweek",#N/A,FALSE,"ban0930"}
Name ________________________y1: {"bbtday",#N/A,FALSE,"ban0930";"banksday",#N/A,FALSE,"ban0930";"compday",#N/A,FALSE,"ban0930"}
Name ________________________y1: {"bbtday",#N/A,FALSE,"ban0930";"banksday",#N/A,FALSE,"ban0930";"compday",#N/A,FALSE,"ban0930"}
Name ________________________y1: {"bbtday",#N/A,FALSE,"ban0930";"banksday",#N/A,FALSE,"ban0930";"compday",#N/A,FALSE,"ban0930"}
Name _______________________vvv1: {"bbtday",#N/A,FALSE,"ban0930";"banksday",#N/A,FALSE,"ban0930";"compday",#N/A,FALSE,"ban0930"}
Name _______________________vvv1: {"bbtday",#N/A,FALSE,"ban0930";"banksday",#N/A,FALSE,"ban0930";"compday",#N/A,FALSE,"ban0930"}
Name _______________________vvv1: {"bbtday",#N/A,FALSE,"ban0930";"banksday",#N/A,FALSE,"ban0930";"compday",#N/A,FALSE,"ban0930"}
Name _______________________x1: {"compweek",#N/A,FALSE,"ban0930";"bankweek",#N/A,FALSE,"ban0930"}
Name _______________________x1: {"compweek",#N/A,FALSE,"ban0930";"bankweek",#N/A,FALSE,"ban0930"}
Name _______________________x1: {"compweek",#N/A,FALSE,"ban0930";"bankweek",#N/A,FALSE,"ban0930"}
Name _______________________y1: {"bbtday",#N/A,FALSE,"ban0930";"banksday",#N/A,FALSE,"ban0930";"compday",#N/A,FALSE,"ban0930"}
Name _______________________y1: {"bbtday",#N/A,FALSE,"ban0930";"banksday",#N/A,FALSE,"ban0930";"compday",#N/A,FALSE,"ban0930"}
Name _______________________y1: {"bbtday",#N/A,FALSE,"ban0930";"banksday",#N/A,FALSE,"ban0930";"compday",#N/A,FALSE,"ban0930"}
Name _____________________vvv1: {"bbtday",#N/A,FALSE,"ban0930";"banksday",#N/A,FALSE,"ban0930";"compday",#N/A,FALSE,"ban0930"}
Name _____________________vvv1: {"bbtday",#N/A,FALSE,"ban0930";"banksday",#N/A,FALSE,"ban0930";"compday",#N/A,FALSE,"ban0930"}

Sheet __snloffice
A1: 允䅁䅁䅍䅁慁䅁䅁兓剂䙁䄸兔䉂䙁䅉睓䙂䙁䅑睑䉂䙁䅁䅁䉁䅁䅁䅆䅁䕁䄴兗呂䕁䅕杏䑂䕁䄸睔䱂䅁䅁䅁䅁䅁䅷䅁ぁ䑁䅙䅍㑁䑁䅙䅁䍁䅁䅁䅁䅁䅁㴽

Sheet Historical Financials
D3: Traeger Pellet Grills | G3: Print Screen | I3: 0 | AJ3: DRAFT
D4: Spread Financials | AJ4: CONFIDENTIAL
D5: Data as of 4Q'25
D7: ($ millions) | F7: 2021 | G7: 2021 | H7: 2021 | I7: 2021 | J7: 2022 | K7: 2022 | L7: 2022 | M7: 2022 | N7: 2023 | O7: 2023 | P7: 2023 | Q7: 2023 | R7: 2024 | S7: 2024 | T7: 2024 | U7: 2024 | V7: 2025 | W7: 2025 | X7: 2025 | Y7: 2025 | AI7: Quarter Ended | BG7: Retail | BH7: 203.217 | BI7: 162.137 | BJ7: 502.884 | BK7: 132.61 | BL7: 135.198 | BM7: =BJ7-SUM(BH7:BI7)+SUM(BK7:BL7) -> 405.338 | BN7: 451.759 | BO7: 121.26 | BP7: =BO7/BO8 -> 1
D8: Line Item | F8: 1Q'21 | G8: 2Q'21 | H8: 3Q'21 | I8: 4Q'21 | J8: 1Q'22 | K8: 2Q'22 | L8: 3Q'22 | M8: 4Q'22 | N8: 1Q'23 | O8: 2Q'23 | P8: 3Q'23 | Q8: 4Q'23 | R8: 1Q'24 | S8: 2Q'24 | T8: 3Q'24 | U8: 4Q'24 | V8: 1Q'25 | W8: 2Q'25 | X8: 3Q'25 | Y8: 4Q'25 | AA8: 2019 | AB8: 2020 | AC8: 2021 | AD8: 2022 | AE8: 2023 | AF8: 2024 | AG8: 2025 | AH8: LTM 3Q'25 | AI8: 4Q'24 | AJ8: 4Q'25 | BH8: =SUM(BH7:BH7) -> 203.217 | BI8: =SUM(BI7:BI7) -> 162.137 | BJ8: =SUM(#REF!) -> #REF! | BK8: =SUM(BK7:BK7) -> 132.61 | BL8: =SUM(BL7:BL7) -> 135.198 | BM8: =SUM(BM7:BM7) -> 405.338 | BN8: =SUM(BN7:BN7) -> 451.759 | BO8: =SUM(BO7:BO7) -> 121.26
F9: 44286 | G9: 44377 | H9: 44469 | I9: 44561 | J9: 44651 | K9: 44742 | L9: 44834 | M9: 44926 | N9: 45016 | O9: 45107 | P9: 45199 | Q9: 45291 | R9: 45382 | S9: 45473 | T9: 45565 | U9: 45657 | V9: 45747 | W9: 45838 | X9: 45930 | Y9: 46022
B11: x | C11: Income Statement
C13: Revenue
D14: Grills | F14: 178.655 | G14: 156.101 | H14: 108.799 | I14: =AC14-SUM(F14:H14) -> 100.645 | J14: 150.431 | K14: 117.68 | L14: 38.994 | M14: 48.333 | N14: 89.738 | O14: 93.133 | P14: 56.573 | Q14: =AE14-SUM(N14:P14) -> 59.902 | R14: 76.819 | S14: 94.971 | T14: 74.931 | U14: =AF14-SUM(R14:T14) -> 77.981 | V14: 86.685 | W14: 74.184 | X14: 76.569 | Y14: =AG14-SUM(V14:X14) -> 60.572 | AB14: 391.047 | AC14: 544.2 | AD14: 355.441 | AE14: 299.346 | AF14: 324.702 | AG14: 298.01 | AH14: =SUM(U14:X14) -> 315.419 | AI14: =U14 -> 77.981 | AJ14: =Y14 -> 60.572 | AM14: =AH14/SUM(Q14:T14)-1 -> 0.028686693 | AN14: =SUM(Q14:T14) -> 306.623
D15: Consumables | F15: 40.813 | G15: 41.178 | H15: 28.029 | I15: =AC15-SUM(F15:H15) -> 26.196 | J15: 39.651 | K15: 42.097 | L15: 25.151 | M15: 24.4 | N15: 30.045 | O15: 34.9 | P15: 25.385 | Q15: =AE15-SUM(N15:P15) -> 24.571 | R15: 32.259 | S15: 33.831 | T15: 22.531 | U15: =AF15-SUM(R15:T15) -> 30.678 | V15: 30.288 | W15: 36.357 | X15: 25.296 | Y15: =AG15-SUM(V15:X15) -> 35.569 | AB15: 120.247 | AC15: 136.216 | AD15: 131.342 | AE15: 114.901 | AF15: 119.299 | AG15: 127.51 | AH15: =SUM(U15:X15) -> 122.619 | AI15: =U15 -> 30.678 | AJ15: =Y15 -> 35.569 | AM15: =AH15/$AH$17 -> 0.21039636
D16: Accessories | F16: 16.105 | G16: 15.743 | H16: 25.19 | I16: =AC16-SUM(F16:H16) -> 48.091 | J16: 33.628 | K16: 40.493 | L16: 29.644 | M16: 65.4 | N16: 33.378 | O16: 43.479 | P16: 35.772 | Q16: =AE16-SUM(N16:P16) -> 79.006 | R16: 35.836 | S16: 39.669 | T16: 24.588 | U16: =AF16-SUM(R16:T16) -> 59.978 | V16: 26.31 | W16: 34.943 | X16: 23.531 | Y16: =AG16-SUM(V16:X16) -> 49.216 | AB16: 34.478 | AC16: 105.129 | AD16: 169.118 | AE16: 191.635 | AF16: 160.071 | AG16: 134 | AH16: =SUM(U16:X16) -> 144.762 | AI16: =U16 -> 59.978 | AJ16: =Y16 -> 49.216 | AM16: =AH16/$AH$17 -> 0.24839053
C17: Total Revenue | F17: =SUM(F14:F16) -> 235.573 | G17: =SUM(G14:G16) -> 213.022 | H17: =SUM(H14:H16) -> 162.018 | I17: =SUM(I14:I16) -> 174.932 | J17: =SUM(J14:J16) -> 223.71 | K17: =SUM(K14:K16) -> 200.27 | L17: =SUM(L14:L16) -> 93.789 | M17: =SUM(M14:M16) -> 138.133 | ... T17: =SUM(T14:T16) -> 122.05 | U17: =AF17-SUM(R17:T17) -> 168.637 | V17: =SUM(V14:V16) -> 143.283 | W17: =SUM(W14:W16) -> 145.484 | X17: =SUM(X14:X16) -> 125.396 | Y17: =SUM(Y14:Y16) -> 145.357 | AA17: 363.319 | AB17: =SUM(AB14:AB16) -> 545.772 | AC17: =SUM(AC14:AC16) -> 785.545 | AD17: =SUM(AD14:AD16) -> 655.901 | AE17: =SUM(AE14:AE16) -> 605.882 | AF17: =SUM(AF14:AF16) -> 604.072 | AG17: =SUM(AG14:AG16) -> 559.52 | AH17: =SUM(U17:X17) -> 582.8 | AI17: =SUM(AI14:AI16) -> 168.637 | AJ17: =SUM(AJ14:AJ16) -> 145.357 | AM17: =AJ17/AI17-1 -> -0.138048
C18: Cost of Revenue | F18: 134.942 | G18: 129.715 | H18: 107.696 | I18: =AC18-SUM(F18:H18) -> 109.481 | J18: 140.145 | K18: 126.764 | L18: 67.81 | M18: 90.524 | N18: 97.738 | O18: 108.181 | P18: 73.064 | Q18: 103.342 | R18: 82.351 | S18: 96.143 | T18: 70.362 | U18: =AF18-SUM(R18:T18) -> 99.747 | V18: 83.824 | W18: 88.483 | X18: 76.85 | Y18: =AG18-SUM(V18:X18) -> 91.017 | AA18: 207.539 | AB18: 310.408 | AC18: 481.834 | AD18: 427.129 | AE18: =382.325 -> 382.325 | AF18: 348.603 | AG18: 340.174 | AH18: =SUM(U18:X18) -> 348.904 | AI18: =U18 -> 99.747 | AJ18: =Y18 -> 91.017
C19: Gross Profit | F19: =F17-F18 -> 100.631 | G19: =G17-G18 -> 83.307 | H19: =H17-H18 -> 54.322 | I19: =I17-I18 -> 65.451 | J19: =J17-J18 -> 83.565 | K19: =K17-K18 -> 73.506 | L19: =L17-L18 -> 25.979 | M19: =M17-M18 -> 47.609 | ... T19: =T17-T18 -> 51.688 | U19: =AF19-SUM(R19:T19) -> 68.89 | V19: =V17-V18 -> 59.459 | W19: =W17-W18 -> 57.001 | X19: =X17-X18 -> 48.546 | Y19: =Y17-Y18 -> 54.34 | AA19: =AA17-AA18 -> 155.78 | AB19: =AB17-AB18 -> 235.364 | AC19: =AC17-AC18 -> 303.711 | AD19: =AD17-AD18 -> 228.772 | AE19: =AE17-AE18 -> 223.557 | AF19: =AF17-AF18 -> 255.469 | AG19: =AG17-AG18 -> 219.346 | AH19: =SUM(U19:X19) -> 233.896 | AI19: =AI17-AI18 -> 68.89 | AJ19: =AJ17-AJ18 -> 54.34 | AM19: =AJ19/AI19-1 -> -0.21120627
D20: Gross Margin | F20: =F19/F17 -> 0.42717544 | G20: =G19/G17 -> 0.39107228 | H20: =H19/H17 -> 0.33528373 | I20: =I19/I17 -> 0.3741511 | J20: =J19/J17 -> 0.37354164 | K20: =K19/K17 -> 0.3670345 | L20: =L19/L17 -> 0.2769941 | M20: =M19/M17 -> 0.34466058 | ... Y20: =Y19/Y17 -> 0.37383821 | AA20: =AA19/AA17 -> 0.42876921 | AB20: =AB19/AB17 -> 0.43124968 | AC20: =AC19/AC17 -> 0.38662457 | AD20: =AD19/AD17 -> 0.34879044 | AE20: =AE19/AE17 -> 0.36897779 | AF20: =AF19/AF17 -> 0.42291151 | AG20: =AG19/AG17 -> 0.39202531 | AH20: =AH19/AH17 -> 0.4013315 | ... AJ20: =AJ19/AJ17 -> 0.37383821
D21: TTM Revenue | J21: =SUM(G17:J17) -> 773.682 | K21: =SUM(H17:K17) -> 760.93 | L21: =SUM(I17:L17) -> 692.701 | M21: =SUM(J17:M17) -> 655.902 | N21: =SUM(K17:N17) -> 585.353 | O21: =SUM(L17:O17) -> 556.595 | P21: =SUM(M17:P17) -> 580.536 | Q21: =SUM(N17:Q17) -> 605.882 | ... Y21: =SUM(V17:Y17) -> 559.52
C23: Operating Expense
D24: Sales and Marketing | F24: 30.851 | G24: 47.269 | H24: 48.519 | I24: =AC24-SUM(F24:H24) -> 38.541 | J24: 33.094 | K24: 43.811 | L24: 25.496 | M24: 28.287 | N24: 22.075 | O24: 27.915 | P24: =25.913 -> 25.913 | Q24: 32.824 | R24: 21.679 | S24: 28.224 | T24: 26.162 | U24: =AF24-SUM(R24:T24) -> 33.591 | V24: 22.21 | W24: 24.779 | X24: 20 | Y24: =AG24-SUM(V24:X24) -> 23.228 | AA24: 66.921 | AB24: 93.69 | AC24: 165.18 | AD24: 130.688 | AE24: =108.727 -> 108.727 | AF24: 109.656 | AG24: 90.217 | AH24: =SUM(U24:X24) -> 100.58 | AI24: =U24 -> 33.591 | AJ24: =Y24 -> 23.228
D25: General and Admin | F25: 13.556 | G25: 24.802 | H25: 75.824 | I25: =AC25-SUM(F25:H25) -> 44.373 | J25: 42.869 | K25: 28.886 | L25: 70.882 | M25: 24.187 | N25: 26.679 | O25: 52.371 | P25: 24.823 | Q25: 25.927 | R25: 32.138 | S25: 30.491 | T25: 24.135 | U25: =AF25-SUM(R25:T25) -> 26.719 | V25: 25.019 | W25: 26.032 | X25: 22.164 | Y25: =AG25-SUM(V25:X25) -> 21.816 | AA25: 45.304 | AB25: 50.243 | AC25: 158.555 | AD25: 166.824 | AE25: =129.8 -> 129.8 | AF25: 113.483 | AG25: 95.031 | AH25: =SUM(U25:X25) -> 99.934 | AI25: =U25 -> 26.719 | AJ25: =Y25 -> 21.816
D26: Amortization of Intangibles | F26: 8.301 | G26: 8.301 | H26: 8.889 | I26: =AC26-SUM(F26:H26) -> 8.888 | J26: 8.889 | K26: 8.888 | L26: 8.889 | M26: 8.888 | N26: 8.889 | O26: 8.888 | P26: 8.889 | Q26: 8.888 | R26: 8.819 | S26: 8.818 | T26: 8.819 | U26: =AF26-SUM(R26:T26) -> 8.818 | V26: 8.818 | W26: 8.816 | X26: 8.813 | Y26: =AG26-SUM(V26:X26) -> 8.813 | AA26: 33.1 | AB26: 32.533 | AC26: 34.379 | AD26: 35.554 | AE26: =35.554 -> 35.554 | AF26: 35.274 | AG26: 35.26 | AH26: =SUM(U26:X26) -> 35.265 | AI26: =U26 -> 8.818 | AJ26: =Y26 -> 8.813
D27: Change in fair value of contingent consideration | F27: 0 | G27: 0 | H27: 2.9 | I27: =AC27-SUM(F27:H27) -> 0.9 | J27: 1.7 | K27: 0.255 | L27: 1.82 | M27: 6.227 | N27: 1.043 | O27: 1.765 | P27: =-2.3 -> -2.3 | Q27: 4.19 | R27: 0 | S27: 0 | T27: 0 | U27: =AF27-SUM(R27:T27) -> 0 | V27: 0 | W27: 0 | X27: 0 | Y27: =AG27-SUM(V27:X27) -> 0 | AA27: 0 | AB27: 0 | AC27: 3.8 | AD27: 10.002 | AE27: =4.698 -> 4.698 | AF27: 0 | AG27: 0 | AH27: =SUM(U27:X27) -> 0 | AI27: =U27 -> 0 | AJ27: =Y27 -> 0
D28: Goodwill impairment | F28: 0 | G28: 0 | H28: 0 | I28: =AC28-SUM(F28:H28) -> 0 | J28: 0 | K28: 111.485 | L28: 110.837 | M28: 0 | N28: 0 | O28: 0 | P28: =0.225 -> 0.225 | Q28: 0 | R28: 0 | S28: 0 | T28: 0 | U28: =AF28-SUM(R28:T28) -> 0 | V28: 0 | W28: 0 | X28: 74.725 | Y28: =AG28-SUM(V28:X28) -> 0 | AA28: 0 | AB28: 0 | AC28: 0 | AD28: 222.322 | AE28: 0 | AF28: 0 | AG28: 74.725 | AH28: =SUM(U28:X28) -> 74.725 | AI28: =U28 -> 0 | AJ28: =Y28 -> 0
D29: Restructuring Charges | F29: 0 | G29: 0 | H29: 0 | I29: =AC29-SUM(F29:H29) -> 0 | J29: 0 | K29: 0 | L29: 8.036 | M29: 1.288 | N29: 0 | O29: 0 | P29: 0 | Q29: 0 | R29: 0 | S29: 0 | U29: =AF29-SUM(R29:T29) -> 0 | W29: 3.468 | X29: 6.204 | Y29: =AG29-SUM(V29:X29) -> 12.168 | AA29: 0 | AB29: 0 | AC29: 0 | AD29: 9.324 | AE29: =0.225 -> 0.225 | AF29: 0 | AG29: 21.84 | AH29: =SUM(U29:X29) -> 9.672 | AI29: =U29 -> 0 | AJ29: =Y29 -> 12.168
C30: Operating Income | F30: =F19-SUM(F24:F29) -> 47.923 | G30: =G19-SUM(G24:G29) -> 2.935 | H30: =H19-SUM(H24:H29) -> -81.81 | I30: =I19-SUM(I24:I29) -> -27.251 | J30: =J19-SUM(J24:J29) -> -2.987 | K30: =K19-SUM(K24:K29) -> -119.819 | L30: =L19-SUM(L24:L29) -> -199.981 | M30: =M19-SUM(M24:M29) -> -21.268 | ... T30: =T19-SUM(T24:T29) -> -7.428 | U30: =AF30-SUM(R30:T30) -> -0.238 | V30: =V19-SUM(V24:V29) -> 3.412 | W30: =W19-SUM(W24:W29) -> -6.094 | X30: =X19-SUM(X24:X29) -> -83.36 | Y30: =Y19-SUM(Y24:Y29) -> -11.685 | AA30: =AA19-SUM(AA24:AA29) -> 10.455 | AB30: =AB19-SUM(AB24:AB29) -> 58.898 | AC30: =AC19-SUM(AC24:AC29) -> -58.203 | AD30: =AD19-SUM(AD24:AD29) -> -345.942 | AE30: =AE19-SUM(AE24:AE29) -> -55.447 | AF30: =AF19-SUM(AF24:AF29) -> -2.944 | AG30: =AG19-SUM(AG24:AG29) -> -97.727 | AH30: =SUM(U30:X30) -> -86.28 | AI30: =AI19-SUM(AI24:AI29) -> -0.238 | AJ30: =AJ19-SUM(AJ24:AJ29) -> -11.685
D31: Interest Expense, Net | F31: -7.812 | G31: -7.877 | H31: -5.704 | I31: =AC31-SUM(F31:H31) -> -5.253 | J31: -5.837 | K31: -7.064 | L31: -7.337 | M31: -7.647 | N31: -10.454 | O31: -7.81 | P31: =-7.517 -> -7.517 | Q31: =-7.867 -> -7.867 | R31: =-8.096 -> -8.096 | S31: -8.678 | T31: -8.534 | U31: =AF31-SUM(R31:T31) -> -8.192 | V31: -7.893 | W31: -8.091 | X31: -7.815 | Y31: =AG31-SUM(V31:X31) -> -7.551 | AA31: -39.462 | AB31: -34.073 | AC31: -26.646 | AD31: -27.885 | AE31: =-31.275 -> -31.275 | AF31: -33.5 | AG31: -31.35 | AH31: =SUM(U31:X31) -> -31.991 | AI31: =U31 -> -8.192 | AJ31: =Y31 -> -7.551
D32: Loss on extinguishment of debt | F32: -0.458 | G32: -1.957 | H32: -3.228 | I32: =AC32-SUM(F32:H32) -> 0.458 | J32: 0.544 | K32: 0 | L32: 0 | M32: 0 | N32: 0 | O32: 0 | P32: 0 | Q32: 0 | R32: 0 | S32: 0 | T32: 0 | U32: =AF32-SUM(R32:T32) -> 0 | V32: 0 | W32: 0 | X32: 0 | Y32: =AG32-SUM(V32:X32) -> 0 | AA32: 0 | AB32: 0 | AC32: -5.185 | AD32: 0 | AE32: 0 | AF32: 0 | AG32: 0 | AH32: =SUM(U32:X32) -> 0 | AI32: =U32 -> 0 | AJ32: =Y32 -> 0
D33: Other Income (expense) | F33: 0 | G33: 1.996 | H33: -0.426 | I33: =AC33-SUM(F33:H33) -> 1.132 | J33: 0 | K33: -5.35 | L33: -3.545 | M33: 1.224 | N33: 21.899 | O33: 5.45 | P33: =1.992 -> 1.992 | Q33: =-3.715 -> -3.715 | R33: 3.676 | S33: 1.281 | T33: -3.964 | U33: =AF33-SUM(R33:T33) -> -0.513 | V33: 2.103 | W33: 6.411 | X33: 1.049 | Y33: =AG33-SUM(V33:X33) -> 0.192 | AA33: -0.462 | AB33: 7.526 | AC33: 2.702 | AD33: -7.127 | AE33: =4.305 -> 4.305 | AF33: 0.48 | AG33: 9.755 | AH33: =SUM(U33:X33) -> 9.05 | AI33: =U33 -> -0.513 | AJ33: =Y33 -> 0.192
C34: Income (Loss) Before Tax | F34: =+F30+SUM(F31:F33) -> 39.653 | G34: =+G30+SUM(G31:G33) -> -4.903 | H34: =+H30+SUM(H31:H33) -> -91.168 | I34: =+I30+SUM(I31:I33) -> -30.914 | J34: =+J30+SUM(J31:J33) -> -8.28 | K34: =+K30+SUM(K31:K33) -> -132.233 | L34: =+L30+SUM(L31:L33) -> -210.863 | M34: =+M30+SUM(M31:M33) -> -27.691 | ... T34: =+T30+SUM(T31:T33) -> -19.926 | U34: =AF34-SUM(R34:T34) -> -8.943 | V34: =+V30+SUM(V31:V33) -> -2.378 | W34: =+W30+SUM(W31:W33) -> -7.774 | X34: =+X30+SUM(X31:X33) -> -90.126 | Y34: =+Y30+SUM(Y31:Y33) -> -19.044 | AA34: =+AA30+SUM(AA31:AA33) -> -29.469 | AB34: =+AB30+SUM(AB31:AB33) -> 32.351 | AC34: =+AC30+SUM(AC31:AC33) -> -87.332 | AD34: =+AD30+SUM(AD31:AD33) -> -380.954 | AE34: =+AE30+SUM(AE31:AE33) -> -82.417 | AF34: =+AF30+SUM(AF31:AF33) -> -35.964 | AG34: =+AG30+SUM(AG31:AG33) -> -119.322 | AH34: =SUM(U34:X34) -> -109.221 | AI34: =+AI30+SUM(AI31:AI33) -> -8.943 | AJ34: =+AJ30+SUM(AJ31:AJ33) -> -19.044
D35: Provision (benefit) for Income Tax | F35: 0.724 | G35: 0.004 | H35: -1.983 | I35: =AC35-SUM(F35:H35) -> 2.744 | J35: 0.152 | K35: 0.046 | L35: -0.225 | M35: 1.213 | N35: 0.164 | O35: 0.198 | P35: =0.852 -> 0.852 | Q35: =0.771 -> 0.771 | R35: 0.19 | S35: -0.024 | T35: -0.137 | U35: =AF35-SUM(R35:T35) -> -1.985 | V35: -1.6 | W35: -0.391 | X35: -0.307 | Y35: =AG35-SUM(V35:X35) -> -1.843 | AA35: 0.124 | AB35: 0.749 | AC35: 1.489 | AD35: 1.186 | AE35: =1.985 -> 1.985 | AF35: -1.956 | AG35: -4.141 | AH35: =SUM(U35:X35) -> -4.283 | AI35: =U35 -> -1.985 | AJ35: =Y35 -> -1.843
C36: Net Income (Loss) | F36: =+F34-F35 -> 38.929 | G36: =+G34-G35 -> -4.907 | H36: =+H34-H35 -> -89.185 | I36: =+I34-I35 -> -33.658 | J36: =+J34-J35 -> -8.432 | K36: =+K34-K35 -> -132.279 | L36: =+L34-L35 -> -210.638 | M36: =+M34-M35 -> -28.904 | ... T36: =+T34-T35 -> -19.789 | U36: =AF36-SUM(R36:T36) -> -6.958 | V36: =+V34-V35 -> -0.778 | W36: =+W34-W35 -> -7.383 | X36: =+X34-X35 -> -89.819 | Y36: =+Y34-Y35 -> -17.201 | AA36: =+AA34-AA35 -> -29.593 | AB36: =+AB34-AB35 -> 31.602 | AC36: =+AC34-AC35 -> -88.821 | AD36: =+AD34-AD35 -> -382.14 | AE36: =+AE34-AE35 -> -84.402 | AF36: =+AF34-AF35 -> -34.008 | AG36: =+AG34-AG35 -> -115.181 | AH36: =SUM(U36:X36) -> -104.938 | AI36: =+AI34-AI35 -> -6.958 | AJ36: =+AJ34-AJ35 -> -17.201
C37: As Reported | F37: 38.929 | G37: -4.907 | H37: -89.185 | I37: =AC37-SUM(F37:H37) -> -33.658 | J37: -8.432 | K37: -132.279 | L37: -210.639 | M37: -28.904 | N37: 8.018 | O37: -30.166 | P37: =-19.261 -> -19.261 | Q37: =-24.045 -> -24.045 | R37: =-4.683 -> -4.683 | S37: -2.578 | T37: -19.789 | U37: -6.958 | V37: -0.778 | W37: -7.384 | X37: -89.819 | Y37: -17.2 | AA37: -29.593 | AB37: 31.602 | AC37: -88.821 | AD37: -382.14 | AE37: =-84.402 -> -84.402 | AF37: -34.008 | AG37: -115.181 | AH37: =SUM(U37:X37) -> -104.939
C38: Check | F38: =F36-F37 -> 0 | G38: =G36-G37 -> -1.0658141e-14 | H38: =H36-H37 -> 0 | I38: =I36-I37 -> 1.6342483e-13 | J38: =J36-J37 -> 3.5527137e-14 | K38: =K36-K37 -> 0 | L38: =L36-L37 -> 0.001 | M38: =M36-M37 -> 0 | ... Y38: =Y36-Y37 -> -0.001 | AB38: =AB36-AB37 -> 2.8421709e-14 | AC38: =AC36-AC37 -> 0 | AD38: =AD36-AD37 -> 0 | AE38: =AE36-AE37 -> 0 | AF38: =AF36-AF37 -> 0 | AG38: =AG36-AG37 -> 0 | AH38: =SUM(U38:X38) -> 0.001
D40: Provision for income taxes | F40: 0.724 | G40: 0.004 | H40: -1.983 | I40: =AC40-SUM(F40:H40) -> 2.744 | J40: 0.152 | K40: 0.046 | L40: -0.225 | M40: 1.213 | N40: 0.164 | O40: 0.198 | P40: =0.852 -> 0.852 | Q40: =0.771 -> 0.771 | R40: 0.19 | S40: -0.024 | T40: -0.137 | U40: -1.985 | V40: -1.6 | W40: -0.391 | X40: -0.307 | Y40: =Y35 -> -1.843 | AB40: 0.749 | AC40: 1.489 | AD40: 1.186 | AE40: =1.985 -> 1.985 | AF40: -1.956 | AG40: =AG35 -> -4.141 | AH40: =SUM(U40:X40) -> -4.283 | AI40: =U40 -> -1.985 | AJ40: =Y40 -> -1.843
D41: Interest expense | F41: 7.812 | G41: 7.877 | H41: 3.977 | I41: =AC41-SUM(F41:H41) -> 6.98 | J41: 5.837 | K41: 7.064 | L41: 7.337 | M41: 7.647 | N41: 10.454 | O41: 7.81 | P41: =7.517 -> 7.517 | Q41: =7.867 -> 7.867 | R41: =8.096 -> 8.096 | S41: 8.678 | T41: 8.534 | U41: 8.192 | V41: 7.893 | W41: 8.091 | X41: 7.815 | Y41: =AG41-SUM(V41:X41) -> 7.551 | AB41: 34.073 | AC41: 26.646 | AD41: 27.885 | AE41: 31.275 | AF41: 33.5 | AG41: 31.35 | AH41: =SUM(U41:X41) -> 31.991 | AI41: =U41 -> 8.192 | AJ41: =Y41 -> 7.551
D42: Depreciation and amortization | F42: 10.699 | G42: 10.74 | H42: 5.704 | I42: =AC42-SUM(F42:H42) -> 20.356 | J42: 13.177 | K42: 14.242 | L42: 14.382 | M42: 14.816 | N42: 14.255 | O42: 14.587 | P42: =14.433 -> 14.433 | Q42: =14.503 -> 14.503 | R42: 14.247 | S42: 13.944 | T42: 13.885 | U42: 14.251 | V42: 14.242 | W42: 13.308 | X42: 13.302 | Y42: =AG42-SUM(V42:X42) -> 13.285 | AB42: 40.968 | AC42: 47.499 | AD42: 56.617 | AE42: =57.778 -> 57.778 | AF42: 56.327 | AG42: 54.137 | AH42: =SUM(U42:X42) -> 55.103 | AI42: =U42 -> 14.251 | AJ42: =Y42 -> 13.285
D43: Other (income) expense | F43: 3.348 | G43: 2.72 | H43: 13.076 | I43: =AC43-SUM(F43:H43) -> -8.626 | J43: 0.674 | K43: 3.401 | L43: 0.021 | M43: -1.629 | N43: -20.307 | O43: -6.529 | P43: =-2.978 -> -2.978 | Q43: =3.276 -> 3.276 | R43: =-3.637 -> -3.637 | S43: -1.863 | T43: 3.875 | U43: 0.011 | V43: -2.411 | W43: -1.747 | X43: -0.467 | Y43: =AG43-SUM(V43:X43) -> -0.468 | AB43: -5.947 | AC43: 10.518 | AD43: 2.466 | AE43: =-5.216 -> -5.216 | AF43: -1.614 | AG43: -5.093 | AH43: =SUM(U43:X43) -> -4.614 | AI43: =U43 -> 0.011 | AJ43: =Y43 -> -0.468
D44: Goodwill impairment | F44: 0 | G44: 0 | H44: 59.21 | I44: =AC44-SUM(F44:H44) -> -59.21 | J44: 0 | K44: 111.485 | L44: 109.757 | M44: 0 | N44: 0 | O44: 0 | P44: 0 | Q44: 0 | R44: 0 | S44: 0 | T44: 0 | U44: 0 | W44: 0 | X44: 74.725 | Y44: =AG44-SUM(V44:X44) -> 0 | AB44: 0 | AC44: 0 | AD44: 222.322 | AE44: 0 | AF44: 0 | AG44: 74.725 | AH44: =SUM(U44:X44) -> 74.725 | AI44: =U44 -> 0 | AJ44: =Y44 -> 0
D45: Restructuring costs | F45: 0 | G45: 0 | H45: 0 | I45: 0 | J45: 0 | K45: 0 | L45: 9.644 | M45: 1.898 | N45: 0 | O45: 0 | P45: =0.225 -> 0.225 | Q45: 0 | R45: 0 | S45: 0 | T45: 0 | U45: 0 | W45: 3.468 | X45: 6.204 | Y45: =AG45-SUM(V45:X45) -> 15.27 | AB45: 0 | AC45: 0 | AD45: 11.542 | AE45: =0.225 -> 0.225 | AF45: 27.901 | AG45: 24.942 | AH45: =SUM(U45:X45) -> 9.672 | AI45: =U45 -> 0 | AJ45: =Y45 -> 15.27
D46: Equity-based compensation | F46: 0.956 | G46: 1.545 | H46: 1.313 | I46: =AC46-SUM(F46:H46) -> 77.298 | J46: 15.483 | K46: 11.951 | L46: 53.254 | M46: 7.01 | N46: 7.943 | O46: 33.036 | P46: =6.201 -> 6.201 | Q46: 6.023 | R46: 10.098 | S46: 7.065 | T46: 5.901 | U46: 4.837 | V46: 5.176 | W46: 3.969 | X46: 3.331 | Y46: =AG46-SUM(V46:X46) -> 2.778 | AB46: 12.81 | AC46: 81.112 | AD46: 87.697 | AE46: =53.203 -> 53.203 | AF46: 1.794 | AG46: 15.254 | AH46: =SUM(U46:X46) -> 17.313 | AI46: =U46 -> 4.837 | AJ46: =Y46 -> 2.778
D47: Non-routine legal expenses | F47: 1.242 | G47: 1.512 | H47: 2.883 | I47: =AC47-SUM(F47:H47) -> 0.706 | J47: 1.919 | K47: 1.051 | L47: 0.788 | M47: -0.745 | N47: 0.233 | O47: 0.248 | P47: 0 | Q47: =0.397 -> 0.397 | R47: 0.103 | S47: 1.6 | T47: 0.079 | U47: 0.013 | V47: 0.008 | W47: 0.01 | X47: 0.005 | Y47: =AG47-SUM(V47:X47) -> 0.002 | AB47: 1.82 | AC47: 6.343 | AD47: 3.012 | AE47: =0.878 -> 0.878 | AF47: 0 | AG47: 0.025 | AH47: =SUM(U47:X47) -> 0.036 | AI47: =U47 -> 0.013 | AJ47: =Y47 -> 0.002
D48: Change in fair value of contingent consideration | F48: 0 | G48: 0 | H48: 2.624 | I48: =AC48-SUM(F48:H48) -> 1.176 | J48: 1.7 | K48: 0.255 | L48: 2.71 | M48: 6.227 | N48: 1.043 | O48: 1.765 | P48: =-2.3 -> -2.3 | Q48: =4.19 -> 4.19 | R48: 0 | S48: 0 | T48: 0 | U48: 0 | W48: 0 | Y48: =AG48-SUM(V48:X48) -> 0 | AB48: 0 | AC48: 3.8 | AD48: 10.002 | AE48: =4.698 -> 4.698 | AF48: 0 | AG48: 0 | AH48: =SUM(U48:X48) -> 0 | AI48: =U48 -> 0 | AJ48: =Y48 -> 0
D49: Offering related expenses | F49: 0.369 | G49: 0.666 | H49: 2.9 | I49: =AC49-SUM(F49:H49) -> -0.21 | J49: 0 | K49: 0 | L49: 0 | M49: 0 | N49: 0 | O49: 0 | P49: 0 | Q49: 0 | R49: 0 | S49: 0 | T49: 0 | U49: 0 | W49: 0 | Y49: =AG49-SUM(V49:X49) -> 0 | AB49: 0 | AC49: 3.725 | AD49: 0 | AE49: =0.669 -> 0.669 | AF49: 0 | AG49: 0 | AH49: =SUM(U49:X49) -> 0 | AI49: =U49 -> 0 | AJ49: =Y49 -> 0
D50: Non-routine start-up costs | F50: 0 | G50: 2.98 | H50: 2.607 | I50: =AC50-SUM(F50:H50) -> 3.314 | J50: 0 | K50: 0 | L50: 0 | M50: 0 | N50: 0 | O50: 0 | P50: 0 | Q50: 0 | R50: 0 | S50: 0 | T50: 0 | U50: 0 | W50: 0 | Y50: =AG50-SUM(V50:X50) -> 0 | AB50: 0 | AC50: 8.901 | AD50: 0 | AE50: 0 | AF50: 0 | AG50: 0 | AH50: =SUM(U50:X50) -> 0 | AI50: =U50 -> 0 | AJ50: =Y50 -> 0
D51: Non-Runtime acquisition expenses | F51: 0 | G51: 0 | H51: 0 | I51: =AC51-SUM(F51:H51) -> 2.624 | J51: 0 | K51: 0 | L51: 0 | M51: 0 | N51: 0 | O51: 0 | P51: 0 | Q51: 0 | R51: 0 | S51: 0 | T51: 0 | U51: 0 | W51: 0 | Y51: =AG51-SUM(V51:X51) -> 0 | AB51: 0 | AC51: 2.624 | AD51: 0 | AE51: 0 | AF51: 0 | AG51: 0 | AH51: =SUM(U51:X51) -> 0 | AI51: =U51 -> 0 | AJ51: =Y51 -> 0
D52: Non-routine refinancing expenses | F52: 0 | G52: 3.895 | H52: 0 | I52: =AC52-SUM(F52:H52) -> 0 | J52: 0 | K52: 0 | L52: 0 | M52: 0 | N52: 0 | O52: 0 | P52: 0 | Q52: 0 | R52: 0 | S52: 0 | T52: 0 | U52: 0 | W52: 0 | Y52: =AG52-SUM(V52:X52) -> 0 | AB52: 0 | AC52: 3.895 | AD52: 0 | AE52: 0 | AF52: 0 | AG52: 0 | AH52: =SUM(U52:X52) -> 0 | AI52: =U52 -> 0 | AJ52: =Y52 -> 0
D53: Other adjustment items | F53: 0 | G53: 0 | H53: 0.972 | I53: =AC53-SUM(F53:H53) -> 0.304 | J53: 0.412 | K53: 0.668 | L53: 0.274 | M53: 0 | N53: 0.143 | O53: 0.526 | P53: 0 | Q53: 0 | R53: 0 | S53: 0 | T53: 0 | U53: 0 | W53: 0 | Y53: =AG53-SUM(V53:X53) -> 0 | AB53: 0 | AC53: 1.276 | AD53: 0.938 | AE53: 0 | AF53: 0 | AG53: 0 | AH53: =SUM(U53:X53) -> 0 | AI53: =U53 -> 0 | AJ53: =Y53 -> 0
D54: Other adjustment items | F54: =SUM(F47:F53) -> 1.611 | G54: =SUM(G47:G53) -> 9.053 | H54: =SUM(H47:H53) -> 11.986 | I54: =SUM(I47:I53) -> 7.914 | J54: =SUM(J47:J53) -> 4.031 | K54: =SUM(K47:K53) -> 1.974 | L54: =SUM(L47:L53) -> 3.772 | M54: =SUM(M47:M53) -> 5.482 | ... U54: =SUM(U47:U53) -> 0.013 | W54: =-5.067 -> -5.067 | X54: -0.982 | Y54: =AG54-SUM(V54:X54) -> 0 | AB54: =SUM(AB47:AB53) -> 1.82 | AC54: =SUM(AC47:AC53) -> 30.564 | AD54: =SUM(AD47:AD53) -> 13.952 | AE54: =SUM(AE47:AE53) -> 6.245 | AF54: =SUM(AF47:AF53) -> 0 | AG54: -6.049 | AH54: =SUM(U54:X54) -> -6.036 | AI54: =U54 -> 0.013 | AJ54: =Y54 -> 0 | BM54: =5.3/21.5 -> 0.24651163
C55: Adjusted EBITDA | F55: =SUM(F54,F40:F46,F36) -> 64.079 | G55: =SUM(G54,G40:G46,G36) -> 27.032 | H55: =SUM(H54,H40:H46,H36) -> 4.098 | I55: =SUM(I54,I40:I46,I36) -> 13.798 | J55: =SUM(J54,J40:J46,J36) -> 30.922 | K55: =SUM(K54,K40:K46,K36) -> 17.884 | L55: =SUM(L54,L40:L46,L36) -> -12.696 | M55: =SUM(M54,M40:M46,M36) -> 7.533 | ... U55: =SUM(U54,U40:U46,U36) -> 18.361 | V55: =SUM(V54,V40:V47,V36) -> 22.53 | W55: =SUM(W54,W40:W47,W36) -> 14.258 | X55: =SUM(X54,X40:X47,X36) -> 13.807 | Y55: =SUM(Y54,Y40:Y47,Y36) -> 19.374 | AB55: =SUM(AB54,AB40:AB46,AB36) -> 116.075 | AC55: =SUM(AC54,AC40:AC46,AC36) -> 109.007 | AD55: =SUM(AD54,AD40:AD46,AD36) -> 41.527 | AE55: =SUM(AE54,AE40:AE46,AE36) -> 61.093 | AF55: =SUM(AF54,AF40:AF46,AF36) -> 81.944 | AG55: =SUM(AG54,AG40:AG47,AG36) -> 69.969 | AH55: =SUM(U55:X55) -> 68.956 | AI55: =SUM(AI54,AI40:AI46,AI36) -> 18.361 | AJ55: =SUM(AJ54,AJ40:AJ46,AJ36) -> 19.372
D56: Margin (% of Revenue) | F56: =F55/F17 -> 0.27201335 | G56: =G55/G17 -> 0.12689769 | H56: =H55/H17 -> 0.025293486 | I56: =I55/I17 -> 0.078876363 | J56: =J55/J17 -> 0.13822359 | K56: =K55/K17 -> 0.089299446 | L56: =L55/L17 -> -0.13536769 | M56: =M55/M17 -> 0.054534398 | ... Y56: =Y55/Y17 -> 0.13328563 | AB56: =AB55/AB17 -> 0.21268039 | AC56: =AC55/AC17 -> 0.13876608 | AD56: =AD55/AD17 -> 0.063312909 | AE56: =AE55/AE17 -> 0.10083317 | AF56: =AF55/AF17 -> 0.1356527 | AG56: =AG55/AG17 -> 0.12505183 | AH56: =AH55/AH17 -> 0.11831846 | AI56: =AI55/AI17 -> 0.10887883 | AJ56: =AJ55/AJ17 -> 0.13327188
D57: TTM Adj. EBITDA | J57: =SUM(G55:J55) -> 75.85 | K57: =SUM(H55:K55) -> 66.702 | L57: =SUM(I55:L55) -> 49.908 | M57: =SUM(J55:M55) -> 43.643 | N57: =SUM(K55:N55) -> 34.667 | O57: =SUM(L55:O55) -> 38.258 | P57: =SUM(M55:P55) -> 55.643 | Q57: =SUM(N55:Q55) -> 61.092 | ... Y57: =SUM(V55:Y55) -> 69.969
C58: As Reported | F58: 64.079 | G58: 27.032 | H58: 4.098 | I58: 13.797 | J58: 30.922 | K58: 17.884 | L58: -12.601 | M58: 7.116 | N58: 21.946 | O58: 21.475 | P58: 4.689 | Q58: 12.982 | R58: 24.414 | S58: 26.822 | T58: 12.348 | U58: 18.361 | V58: 22.53 | W58: 14.257 | X58: 13.807 | Y58: 19.374 | AB58: 116.075 | AC58: 109.007 | AD58: 41.527 | AE58: 61.093 | AF58: 81.944 | AG58: 69.969 | AH58: =SUM(U58:X58) -> 68.955
C59: Check | F59: =F55-F58 -> 0 | G59: =G55-G58 -> 0 | H59: =H55-H58 -> 0 | I59: =I55-I58 -> 0.001 | J59: =J55-J58 -> 3.1974423e-14 | K59: =K55-K58 -> 0 | L59: =L55-L58 -> -0.095 | M59: =M55-M58 -> 0.417 | ... Y59: =Y55-Y58 -> 7.1054274e-14 | AB59: =AB55-AB58 -> 0 | AC59: =AC55-AC58 -> 0 | AD59: =AD55-AD58 -> 0 | AE59: =AE55-AE58 -> 5.6843419e-14 | AF59: =AF55-AF58 -> 0 | AG59: =AG55-AG58 -> 0 | AH59: =SUM(U59:X59) -> 0.001 | AL59: Unwinding Cumulative Reporting
B61: x | C61: Cash Flows | AL61: 2Q21 | AM61: 2Q22 | AN61: 2Q23 | AO61: 2Q24 | AP61: 2Q25 | AQ61: 3Q21 | AR61: 3Q22 | AS61: 3Q23 | AT61: 3Q24 | AU61: 3Q25
C62: Change in NWC
D63: Accounts receivable | F63: =-99.293 -> -99.293 | G63: =AL63-F63 -> 44.128 | H63: =AQ63-SUM(F63:G63) -> 35.973 | I63: =AC63-SUM(F63:H63) -> -7.173 | J63: =-70.383 -> -70.383 | K63: =AM63-J63 -> 51.674 | L63: =AR63-SUM(J63:K63) -> 77.583 | M63: =AD63-SUM(J63:L63) -> -7.822 | N63: =-57.145 -> -57.145 | O63: =AN63-N63 -> 16.166 | P63: =AS63-SUM(N63:O63) -> 31.88 | Q63: =AE63-SUM(N63:P63) -> -8.636 | R63: =-19.11 -> -19.11 | S63: =AO63-R63 -> -10.185 | T63: =AT63-SUM(R63:S63) -> 18.444 | U63: =AF63-SUM(R63:T63) -> -14.545 | V63: -9.627 | W63: =AP63-V63 -> 18.809 | X63: =AU63-SUM(V63:W63) -> -4.533 | Y63: =AG63-SUM(V63:X63) -> -1.499 | AB63: =-30.17 -> -30.17 | AC63: =-26.365 -> -26.365 | AD63: =51.052 -> 51.052 | AE63: =-17.735 -> -17.735 | AF63: -25.396 | AG63: 3.15 | AH63: =SUM(U63:X63) -> -9.896 | AI63: =U63 -> -14.545 | AJ63: =Y63 -> -1.499 | AL63: =-55.165 -> -55.165 | AM63: =-18.709 -> -18.709 | AN63: =-40.979 -> -40.979 | AO63: -29.295 | AP63: 9.182 | AQ63: =-19.192 -> -19.192 | AR63: =58.874 -> 58.874 | AS63: =-9.099 -> -9.099 | AT63: -10.851 | AU63: 4.649
D64: Inventories, net | F64: =-6.697 -> -6.697 | G64: =AL64-F64 -> -10.619 | H64: =AQ64-SUM(F64:G64) -> -23.015 | I64: =AC64-SUM(F64:H64) -> -27.495 | J64: =-18.561 -> -18.561 | K64: =AM64-J64 -> 0.78 | L64: =AR64-SUM(J64:K64) -> 1.05 | M64: =AD64-SUM(J64:L64) -> 4.8 | N64: =21.09 -> 21.09 | O64: =AN64-N64 -> 34.578 | P64: =AS64-SUM(N64:O64) -> -4.088 | Q64: =AE64-SUM(N64:P64) -> 5.715 | R64: =-3.727 -> -3.727 | S64: =AO64-R64 -> 8.867 | T64: =AT64-SUM(R64:S64) -> -14.023 | U64: =AF64-SUM(R64:T64) -> -2.309 | V64: -19.869 | W64: =AP64-V64 -> 11.441 | X64: =AU64-SUM(V64:W64) -> 1.169 | Y64: =AG64-SUM(V64:X64) -> 15.795 | AB64: =-28.979 -> -28.979 | AC64: =-67.826 -> -67.826 | AD64: =-11.931 -> -11.931 | AE64: =57.295 -> 57.295 | AF64: -11.192 | AG64: 8.536 | AH64: =SUM(U64:X64) -> -9.568 | AI64: =U64 -> -2.309 | AJ64: =Y64 -> 15.795 | AL64: =-17.316 -> -17.316 | AM64: =-17.781 -> -17.781 | AN64: =55.668 -> 55.668 | AO64: 5.14 | AP64: -8.428 | AQ64: =-40.331 -> -40.331 | AR64: =-16.731 -> -16.731 | AS64: =51.58 -> 51.58 | AT64: -8.883 | AU64: -7.259
D65: Prepaid expenses and other current assets | F65: =-1.844 -> -1.844 | G65: =AL65-F65 -> 0.424 | H65: =AQ65-SUM(F65:G65) -> -6.059 | I65: =AC65-SUM(F65:H65) -> 1.692 | J65: =1.741 -> 1.741 | K65: =AM65-J65 -> -4.135 | L65: =AR65-SUM(J65:K65) -> -4.724 | M65: =AD65-SUM(J65:L65) -> 4.072 | N65: =-1.214 -> -1.214 | O65: =AN65-N65 -> 0.14 | P65: =AS65-SUM(N65:O65) -> -5.003 | Q65: =AE65-SUM(N65:P65) -> 1.878 | R65: =3.071 -> 3.071 | S65: =AO65-R65 -> 1.685 | T65: =AT65-SUM(R65:S65) -> -2.16 | U65: =AF65-SUM(R65:T65) -> -10.169 | V65: 15.917 | W65: =AP65-V65 -> -1.44 | X65: =AU65-SUM(V65:W65) -> 1.114 | Y65: =AG65-SUM(V65:X65) -> -1.236 | AB65: =-4.311 -> -4.311 | AC65: =-5.787 -> -5.787 | AD65: =-3.046 -> -3.046 | AE65: =-4.199 -> -4.199 | AF65: -7.573 | AG65: 14.355 | AH65: =SUM(U65:X65) -> 5.422 | AI65: =U65 -> -10.169 | AJ65: =Y65 -> -1.236 | AL65: =-1.42 -> -1.42 | AM65: =-2.394 -> -2.394 | AN65: =-1.074 -> -1.074 | AO65: 4.756 | AP65: 14.477 | AQ65: =-7.479 -> -7.479 | AR65: =-7.118 -> -7.118 | AS65: =-6.077 -> -6.077 | AT65: 2.596 | AU65: 15.591
D66: Other non-current assets | F66: 0 | G66: =AL66-F66 -> -0.279 | H66: =AQ66-SUM(F66:G66) -> 0.06 | I66: =AC66-SUM(F66:H66) -> -0.462 | J66: =0.004 -> 0.004 | K66: =AM66-J66 -> 0.019 | L66: =AR66-SUM(J66:K66) -> 0.041 | M66: =AD66-SUM(J66:L66) -> 0.014 | N66: 0.018 | O66: =AN66-N66 -> -0.031 | P66: =AS66-SUM(N66:O66) -> -0.38 | Q66: =AE66-SUM(N66:P66) -> -0.175 | R66: =0.037 -> 0.037 | S66: =AO66-R66 -> 0.037 | T66: =AT66-SUM(R66:S66) -> 0.012 | U66: =AF66-SUM(R66:T66) -> 0.062 | V66: 0.207 | W66: =AP66-V66 -> -0.123 | X66: =AU66-SUM(V66:W66) -> 0.011 | Y66: =AG66-SUM(V66:X66) -> 0.019 | AB66: 0 | AC66: =-0.681 -> -0.681 | AD66: =0.078 -> 0.078 | AE66: =-0.568 -> -0.568 | AF66: 0.148 | AG66: 0.114 | AH66: =SUM(U66:X66) -> 0.157 | AI66: =U66 -> 0.062 | AJ66: =Y66 -> 0.019 | AL66: =-0.279 -> -0.279 | AM66: =0.023 -> 0.023 | AN66: =-0.013 -> -0.013 | AO66: 0.074 | AP66: 0.084 | AQ66: =-0.219 -> -0.219 | AR66: =0.064 -> 0.064 | AS66: =-0.393 -> -0.393 | AT66: 0.086 | AU66: 0.095
D67: Accounts payable and accrued expenses | F67: =26.531 -> 26.531 | G67: =AL67-F67 -> -1.733 | H67: =AQ67-SUM(F67:G67) -> -14.767 | I67: =AC67-SUM(F67:H67) -> 9.151 | J67: =17.638 -> 17.638 | K67: =AM67-J67 -> -36.592 | L67: =AR67-SUM(J67:K67) -> -23.874 | M67: =AD67-SUM(J67:L67) -> 14.617 | N67: =-0.073 -> -0.073 | O67: =AN67-N67 -> -14.081 | P67: =AS67-SUM(N67:O67) -> -1.313 | Q67: =AE67-SUM(N67:P67) -> 17.841 | R67: =-10.651 -> -10.651 | S67: =AO67-R67 -> 9.597 | T67: =AT67-SUM(R67:S67) -> 6.074 | U67: =AF67-SUM(R67:T67) -> 21.962 | V67: -26.319 | W67: =AP67-V67 -> -21.282 | X67: =AU67-SUM(V67:W67) -> 6.161 | Y67: =AG67-SUM(V67:X67) -> 6.262 | AB67: =28.351 -> 28.351 | AC67: =19.182 -> 19.182 | AD67: =-28.211 -> -28.211 | AE67: =2.374 -> 2.374 | AF67: 26.982 | AG67: -35.178 | AH67: =SUM(U67:X67) -> -19.478 | AI67: =U67 -> 21.962 | AJ67: =Y67 -> 6.262 | AL67: =24.798 -> 24.798 | AM67: =-18.954 -> -18.954 | AN67: =-14.154 -> -14.154 | AO67: -1.054 | AP67: -47.601 | AQ67: =10.031 -> 10.031 | AR67: =-42.828 -> -42.828 | AS67: =-15.467 -> -15.467 | AT67: 5.02 | AU67: -41.44
D68: Other non-current liabilities | F68: =0.006 -> 0.006 | G68: =AL68-F68 -> 0.007 | H68: =AQ68-SUM(F68:G68) -> -0.004 | I68: =AC68-SUM(F68:H68) -> -0.875 | J68: 0.012 | K68: =AM68-J68 -> 0.001 | L68: =AR68-SUM(J68:K68) -> 0.009 | M68: =AD68-SUM(J68:L68) -> -1.76 | N68: =-0.293 -> -0.293 | O68: =AN68-N68 -> -0.289 | P68: =AS68-SUM(N68:O68) -> 0.586 | Q68: =AE68-SUM(N68:P68) -> -0.004 | R68: 0 | S68: =AO68-R68 -> 0 | T68: =AT68-SUM(R68:S68) -> 0 | U68: =AF68-SUM(R68:T68) -> 0 | V68: 0 | W68: =AP68-V68 -> 0 | X68: =AU68-SUM(V68:W68) -> 0 | Y68: =AG68-SUM(V68:X68) -> 0 | AB68: =0.017 -> 0.017 | AC68: =-0.866 -> -0.866 | AD68: =-1.738 -> -1.738 | AE68: 0 | AF68: 0 | AG68: 0 | AH68: =SUM(U68:X68) -> 0 | AI68: =U68 -> 0 | AJ68: =Y68 -> 0 | AL68: =0.013 -> 0.013 | AM68: =0.013 -> 0.013 | AN68: =-0.582 -> -0.582 | AP68: 0 | AQ68: =0.009 -> 0.009 | AR68: =0.022 -> 0.022 | AS68: =0.004 -> 0.004 | AT68: 0 | AU68: 0
C69: Total Change in NWC | F69: =SUM(F63:F68) -> -81.297 | G69: =SUM(G63:G68) -> 31.928 | H69: =SUM(H63:H68) -> -7.812 | I69: =SUM(I63:I68) -> -25.162 | J69: =SUM(J63:J68) -> -69.549 | K69: =SUM(K63:K68) -> 11.747 | L69: =SUM(L63:L68) -> 50.085 | M69: =SUM(M63:M68) -> 13.921 | ... Y69: =SUM(Y63:Y68) -> 19.341 | AB69: =SUM(AB63:AB68) -> -35.092 | AC69: =SUM(AC63:AC68) -> -82.343 | AD69: =SUM(AD63:AD68) -> 6.204 | AE69: =SUM(AE63:AE68) -> 37.167 | AF69: =SUM(AF63:AF68) -> -17.031 | AG69: =SUM(AG63:AG68) -> -9.023 | AH69: =SUM(U69:X69) -> -33.363 | AI69: =SUM(AI63:AI68) -> -4.999 | AJ69: =SUM(AJ63:AJ68) -> 19.341 | AL69: =SUM(AL63:AL68) -> -49.369 | AM69: =SUM(AM63:AM68) -> -57.802 | AN69: =SUM(AN63:AN68) -> -1.134 | AO69: =SUM(AO63:AO68) -> -20.379 | AP69: =SUM(AP63:AP68) -> -32.286 | AQ69: =SUM(AQ63:AQ68) -> -57.181 | AR69: =SUM(AR63:AR68) -> -7.717 | AS69: =SUM(AS63:AS68) -> 20.548 | ... AU69: =SUM(AU63:AU68) -> -28.364
D70: Less: Capex | F70: =-4.865 -> -4.865 | G70: =AL70-F70 -> -6.383 | H70: =AQ70-SUM(F70:G70) -> -6.738 | I70: =AC70-SUM(F70:H70) -> -4.493 | J70: =-4.524 -> -4.524 | K70: =AM70-J70 -> -7.898 | L70: =AR70-SUM(J70:K70) -> -2.706 | M70: =AD70-SUM(J70:L70) -> -3.27 | N70: =-2.082 -> -2.082 | O70: =AN70-N70 -> -6.772 | P70: =AS70-SUM(N70:O70) -> -6.824 | Q70: =AE70-SUM(N70:P70) -> -4.268 | R70: =-5.683 -> -5.683 | S70: =AO70-R70 -> -2.051 | T70: =AT70-SUM(R70:S70) -> -2.3 | U70: =AF70-SUM(R70:T70) -> -1.962 | V70: -1.826 | W70: =AP70-V70 -> -2.625 | X70: =AU70-SUM(V70:W70) -> -1.163 | Y70: =AG70-SUM(V70:X70) -> -1.32 | AB70: =-14.127 -> -14.127 | AC70: =-22.479 -> -22.479 | AD70: =-18.398 -> -18.398 | AE70: =-19.946 -> -19.946 | AF70: -11.996 | AG70: -6.934 | AH70: =SUM(U70:X70) -> -7.576 | AI70: =U70 -> -1.962 | AJ70: =Y70 -> -1.32 | AL70: =-11.248 -> -11.248 | AM70: =-12.422 -> -12.422 | AN70: =-8.854 -> -8.854 | AO70: -7.734 | AP70: =-4.451 -> -4.451 | AQ70: =-17.986 -> -17.986 | AR70: =-15.128 -> -15.128 | AS70: =-15.678 -> -15.678 | AT70: -10.034 | AU70: -5.614
C71: Unlevered FCF | F71: =F55+F69+F70 -> -22.083 | G71: =G55+G69+G70 -> 52.577 | H71: =H55+H69+H70 -> -10.452 | I71: =I55+I69+I70 -> -15.857 | J71: =J55+J69+J70 -> -43.151 | K71: =K55+K69+K70 -> 21.733 | L71: =L55+L69+L70 -> 34.683 | M71: =M55+M69+M70 -> 18.184 | ... Y71: =Y55+Y69+Y70 -> 37.395 | AB71: =AB55+AB69+AB70 -> 66.856 | AC71: =AC55+AC69+AC70 -> 4.185 | AD71: =AD55+AD69+AD70 -> 29.333 | AE71: =AE55+AE69+AE70 -> 78.314 | AF71: =AF55+AF69+AF70 -> 52.917 | AG71: =AG55+AG69+AG70 -> 54.012 | AH71: =SUM(U71:X71) -> 28.017 | AI71: =AI55+AI69+AI70 -> 11.4 | AJ71: =AJ55+AJ69+AJ70 -> 37.393
D72: Less: Interest Expense | F72: =F31 -> -7.812 | G72: =G31 -> -7.877 | H72: =H31 -> -5.704 | I72: =I31 -> -5.253 | J72: =J31 -> -5.837 | K72: =K31 -> -7.064 | L72: =L31 -> -7.337 | M72: =M31 -> -7.647 | ... T72: =T31 -> -8.534 | U72: =AF72-SUM(R72:T72) -> -8.192 | V72: =V31 -> -7.893 | W72: =W31 -> -8.091 | X72: =X31 -> -7.815 | Y72: =AG72-SUM(V72:X72) -> -7.551 | AB72: =AB31 -> -34.073 | AC72: =AC31 -> -26.646 | AD72: =AD31 -> -27.885 | AE72: =AE31 -> -31.275 | AF72: =AF31 -> -33.5 | AG72: =AG31 -> -31.35 | AH72: =SUM(U72:X72) -> -31.991 | AI72: =U72 -> -8.192 | AJ72: =Y72 -> -7.551
D73: Less: Mandatory Amortization | F73: =-510*0.0025 -> -1.275 | G73: =-510*0.0025 -> -1.275 | H73: =-510*0.0025 -> -1.275 | I73: =-510*0.0025 -> -1.275 | J73: =-510*0.0025 -> -1.275 | K73: =-510*0.0025 -> -1.275 | L73: =-510*0.0025 -> -1.275 | M73: =-510*0.0025 -> -1.275 | ... T73: =-510*0.0025 -> -1.275 | U73: =AF73-SUM(R73:T73) -> -1.275 | V73: =-510*0.0025 -> -1.275 | W73: =-510*0.0025 -> -1.275 | X73: =-510*0.0025 -> -1.275 | Y73: =AG73-SUM(V73:X73) -> -1.275 | AB73: =-510*0.01 -> -5.1 | AC73: =-510*0.01 -> -5.1 | AD73: =-510*0.01 -> -5.1 | AE73: =-510*0.01 -> -5.1 | AF73: =-510*0.01 -> -5.1 | AG73: =-510*0.01 -> -5.1 | AH73: =SUM(U73:X73) -> -5.1 | AI73: =U73 -> -1.275 | AJ73: =Y73 -> -1.275
C74: Levered FCF | F74: =SUM(F71:F73) -> -31.17 | G74: =SUM(G71:G73) -> 43.425 | H74: =SUM(H71:H73) -> -17.431 | I74: =SUM(I71:I73) -> -22.385 | J74: =SUM(J71:J73) -> -50.263 | K74: =SUM(K71:K73) -> 13.394 | L74: =SUM(L71:L73) -> 26.071 | M74: =SUM(M71:M73) -> 9.262 | ... Y74: =SUM(Y71:Y73) -> 28.569 | AB74: =SUM(AB71:AB73) -> 27.683 | AC74: =SUM(AC71:AC73) -> -27.561 | AD74: =SUM(AD71:AD73) -> -3.652 | AE74: =SUM(AE71:AE73) -> 41.939 | AF74: =SUM(AF71:AF73) -> 14.317 | AG74: =SUM(AG71:AG73) -> 17.562 | AH74: =SUM(U74:X74) -> -9.074 | AI74: =SUM(AI71:AI73) -> 1.933 | AJ74: =SUM(AJ71:AJ73) -> 28.567
C76: Revenue
C77: Total | F77: =F17 -> 235.573 | G77: =G17 -> 213.022 | H77: =H17 -> 162.018 | I77: =I17 -> 174.932 | J77: =J17 -> 223.71 | K77: =K17 -> 200.27 | L77: =L17 -> 93.789 | M77: =M17 -> 138.133 | ... Y77: =Y17 -> 145.357 | AA77: =AA17 -> 363.319 | AB77: =AB17 -> 545.772 | AC77: =AC17 -> 785.545 | AD77: =AD17 -> 655.901 | AE77: =AE17 -> 605.882 | AF77: =AF17 -> 604.072 | AG77: =AG17 -> 559.52 | AH77: =SUM(U77:X77) -> 582.8 | AI77: =AI17 -> 168.637 | AJ77: =AJ17 -> 145.357
D78: YoY Growth Rate | J78: =J77/F77-1 -> -0.050358063 | K78: =K77/G77-1 -> -0.059862362 | L78: =L77/H77-1 -> -0.42111988 | M78: =M77/I77-1 -> -0.21036174 | N78: =N77/J77-1 -> -0.31535917 | O78: =O77/K77-1 -> -0.14359615 | P78: =P77/L77-1 -> 0.25526448 | Q78: =Q77/M77-1 -> 0.18348983 | ... Y78: =Y77/U77-1 -> -0.138048 | AB78: =AB77/AA77-1 -> 0.50218403 | AC78: =AC77/AB77-1 -> 0.43932814 | AD78: =AD77/AC77-1 -> -0.16503701 | AE78: =AE77/AD77-1 -> -0.076259984 | AF78: =AF77/AE77-1 -> -0.0029873804 | AG78: =AG77/AF77-1 -> -0.073752798 | AH78: =AH77/AF77-1 -> -0.035214345 | AJ78: =AJ77/AI77-1 -> -0.138048
C79: FCF Build
C80: Cash Flow From Operations | F80: =-26.544 -> -26.544 | G80: =AL80-F80 -> 42.738 | H80: =AQ80-SUM(F80:G80) -> -17.064 | I80: =AC80-SUM(F80:H80) -> -27.557 | J80: =-46.911 -> -46.911 | K80: =AM80-J80 -> 16.861 | L80: =AR80-SUM(J80:K80) -> 24.049 | M80: =AD80-SUM(J80:L80) -> 11.095 | N80: =-23.59 -> -23.59 | O80: =AN80-N80 -> 49.446 | P80: =AS80-SUM(N80:O80) -> 18.503 | Q80: =AE80-SUM(N80:P80) -> 19.683 | R80: =-12.598 -> -12.598 | S80: =1.269 -> 1.269 | T80: =1.269 -> 1.269 | U80: =1.269 -> 1.269 | V80: =1.269 -> 1.269 | W80: =AP80-V80 -> -3.814 | X80: =AU80-SUM(V80:W80) -> 7.554 | Y80: =AG80-SUM(V80:X80) -> 15.511 | AB80: 46.597 | AC80: =-28.427 -> -28.427 | AD80: =5.094 -> 5.094 | AE80: =64.042 -> 64.042 | AF80: 23.888 | AG80: 20.52 | AH80: =SUM(U80:X80) -> 6.278 | AI80: =U80 -> 1.269 | AJ80: =Y80 -> 15.511 | AL80: =16.194 -> 16.194 | AM80: =-30.05 -> -30.05 | AN80: =25.856 -> 25.856 | AO80: 1.269 | AP80: -2.545 | AQ80: =-0.87 -> -0.87 | AR80: =-6.001 -> -6.001 | AS80: 44.359 | AT80: 16.416 | AU80: 5.009
D81: Less: Capex | F81: =F70 -> -4.865 | G81: =G70 -> -6.383 | H81: =H70 -> -6.738 | I81: =I70 -> -4.493 | J81: =J70 -> -4.524 | K81: =K70 -> -7.898 | L81: =L70 -> -2.706 | M81: =M70 -> -3.27 | ... Y81: =Y70 -> -1.32 | AB81: =AB70 -> -14.127 | AC81: =AC70 -> -22.479 | AD81: =AD70 -> -18.398 | AE81: =AE70 -> -19.946 | AF81: =AF70 -> -11.996 | AG81: =AG70 -> -6.934 | AH81: =SUM(U81:X81) -> -7.576 | AI81: =U81 -> -1.962 | AJ81: =Y81 -> -1.32
C82: FCF | F82: =SUM(F80:F81) -> -31.409 | G82: =SUM(G80:G81) -> 36.355 | H82: =SUM(H80:H81) -> -23.802 | I82: =SUM(I80:I81) -> -32.05 | J82: =SUM(J80:J81) -> -51.435 | K82: =SUM(K80:K81) -> 8.963 | L82: =SUM(L80:L81) -> 21.343 | M82: =SUM(M80:M81) -> 7.825 | ... U82: =SUM(U80:U81) -> -0.693 | V82: =V71 -> -18.987 | W82: =W71 -> 19.038 | X82: =X71 -> 16.566 | Y82: =SUM(Y80:Y81) -> 14.191 | AB82: =SUM(AB80:AB81) -> 32.47 | AC82: =SUM(AC80:AC81) -> -50.906 | AD82: =SUM(AD80:AD81) -> -13.304 | AE82: =SUM(AE80:AE81) -> 44.096 | AF82: =SUM(AF80:AF81) -> 11.892 | AG82: =SUM(AG80:AG81) -> 13.586 | AH82: =SUM(U82:X82) -> 15.924 | AI82: =SUM(AI80:AI81) -> -0.693 | AJ82: =SUM(AJ80:AJ81) -> 14.191

Sheet Capital Structure
D3: Traeger Pellet Grills | S3: DRAFT
D4: Capital Structure | S4: CONFIDENTIAL
D5: Data as of 4Q'25
D6: ($ millions)
D8: Stock Ticker: | F8: NYSE:COOK
D9: Date: | F9: 46086
G11: Principal | H11: Interest | J11: Effective | L11: Credit | M11: Trading | N11: Cash | O11: Cum. | P11: Market | R11: 1 Month SOFR as of 3/5/2026
D12: Description | G12: Amount | H12: Rate | I12: YTM | J12: Rate | K12: Maturity | L12: Rating | M12: Price(1) | N12: Interest | O12: Leverage | P12: Amount | R12: 0.0367223
D14: Revolving Credit Facility ($112.5mm)(2) | G14: 0 | H14: 350 | I14: NA | J14: =$R$12+(H14/10000) -> 0.0717223 | K14: 46202 | L14: NA | M14: NA | N14: =J14*G14 -> 0 | P14: =IF(ISNUMBER(M14),M14*G14/100,G14) -> 0 | R14: 1L TL Hedged Cash Interest
D15: Receivables Financing Agreement | G15: 0 | H15: 200 | I15: NA | J15: =$R$12+(H15/10000) -> 0.0567223 | K15: 46605 | L15: B- | M15: NA | N15: =J15*G15 -> 0 | P15: =IF(ISNUMBER(M15),M15*G15/100,G15) -> 0 | R15: Interest Rate Swap Notional: | S15: 379.2
D16: Delayed Draw Term Loan | G16: 25 | H16: 350 | J16: =$R$12+(H16/10000) -> 0.0717223 | K16: 46933 | L16: B- | M16: 94.43 | N16: =J16*G16 -> 1.7930575 | O16: =SUM($G$14:G16)/$G$22 -> 0.35730109 | P16: =IF(ISNUMBER(M16),M16*G16/100,G16) -> 23.6075 | R16: Interest Rate | S16: 0.0533
D17: 1L Term Loan due 2028(3) | G17: 403.325 | H17: 350 | I17: 0.0991 | J17: =$R$12+(H17/10000) -> 0.0717223 | K17: 46933 | L17: B- | M17: 84.38 | N17: =J17*G17 -> 28.927397 | P17: =IF(ISNUMBER(M17),M17*G17/100,G17) -> 340.32563 | R17: Cash Interest - Hedged | S17: =+S15*S16 -> 20.21136
D18: Total Debt | G18: =SUM(G14,G15,G17) -> 403.325 | N18: =SUM(N14,N15,N17) -> 28.927397 | O18: =G18/$G$22 -> 5.7643385 | P18: =SUM(P14,P15,P17) -> 340.32563 | R18: Remaining TL Balance | S18: =+G17-S15 -> 24.125
D19: Less: Cash and Equivalents | G19: =-G32 -> -19.624 | O19: =G19/G22 -> -0.28046706 | R19: Cash Interest - Unhedged | S19: =+S18*J17 -> 1.7303005
D20: Net Debt | G20: =SUM(G18:G19) -> 383.701 | O20: =+G20/G22 -> 5.4838714 | R20: Total Cash Interest | S20: =+S19+S17 -> 21.94166
D22: Memo: FY'25 Adj. EBITDA | G22: ='O1'!M40 -> 69.969
D23: Market Cap | G23: =_xll.ciqfunctions.udf.CIQ(F8, "IQ_MARKETCAP", F9) -> 105.62807
D26: Liquidity
D27: RCF Capacity | G27: 112.5
D28: Less: Outstanding | G28: =-G14 -> 0
D29: Receivables Financing Agreement Capacity | G29: 30
D30: Less: Outstanding | G30: =-G15 -> 0
D31: Credit Facility Availability | G31: =SUM(G27:G30) -> 142.5
D32: Plus: Cash and Equivalents | G32: 19.624
D33: Less: Min Liquidity Requirement(4) | G33: -42.5
D34: Total Liquidity | G34: =SUM(G31:G33) -> 119.624

Sheet _CIQHiddenCacheSheet
A1: 2 | B1: BAABTAVMT0NBTAFI/////wFQAQAAACNDSVEuTllTRTpDT09LLklRX01BUktFVENBUC4zLzUvMjAyNgEAAABTELtjAgAAAAoxMDUuNjI4MDczAQYAAAAFAAAAATEBAAAACy0xOTAzMzA0OTcwAwAAAAMxNjACAAAABjEwMDA1NAQAAAABMAcAAAAIMy81LzIwMjZKPFwYvn3eCLqEdhi+fd4I

Sheet Liquidity Model
D3: Traeger Pellet Grills | AD3: DRAFT
D4: Liquidity Model | AD4: CONFIDENTIAL
D5: Data as of 1Q25
D6: ($ millions)
E8: Case | F8: 2
E10: Circ | F10: 1 | S10: New Price = 1 + ( % COGS x % Tariff x % Pass-Through)
S11: Tariff Paid % of Revenue = ( % COGS x % Tariff )
E12: Print Screen | F12: 2 | S12: COGS % of Revenue = ( 1 - Assumed Gross Margin % )
E14: PF Switch | F14: 1
E16: Tariff / Margin Assumptions
E18: Traeger Grilling & Accessories Gross Margin | M18: 0.385
E19: Retailer Gross Margin | M19: 0.2
E21: Section 232 Steel Tariff | M21: 0.5
E22: IEEPA Tariff | M22: 0
E23: Section 301 China Tariff | M23: 0.25
E24: Vietnam Tariff | M24: 0
E26: Tariff Pass-Through
E27: Live Case | S27: =CHOOSE($F$8,S28,S29,S30) -> 0.75 | T27: =CHOOSE($F$8,T28,T29,T30) -> 0.75 | U27: =CHOOSE($F$8,U28,U29,U30) -> 0.75 | V27: =CHOOSE($F$8,V28,V29,V30) -> 0.75
D28: 1 | E28: Downside | S28: 0.5 | T28: 0.5 | U28: 0.5 | V28: 0.5
D29: 2 | E29: Base | S29: 0.75 | T29: 0.75 | U29: 0.75 | V29: 0.75
D30: 3 | E30: Upside | S30: 1 | T30: 1 | U30: 1 | V30: 1
E33: Tariffs on Grills
E34: Live Case | S34: =CHOOSE($F$8,S35,S36,S37) -> 0.5 | T34: =CHOOSE($F$8,T35,T36,T37) -> 0.5 | U34: =CHOOSE($F$8,U35,U36,U37) -> 0.5 | V34: =CHOOSE($F$8,V35,V36,V37) -> 0.5
D35: 1 | E35: Downside | K35: 301 Exemption Renewed | S35: =SUM($M$21:$M$22) -> 0.5 | T35: =SUM($M$21:$M$22) -> 0.5 | U35: =SUM($M$21:$M$22) -> 0.5 | V35: =SUM($M$21:$M$22) -> 0.5
D36: 2 | E36: Base | K36: 301 Exemption Renewed | S36: =SUM($M$21:$M$22) -> 0.5 | T36: =SUM($M$21:$M$22) -> 0.5 | U36: =SUM($M$21:$M$22) -> 0.5 | V36: =SUM($M$21:$M$22) -> 0.5
D37: 3 | E37: Upside | K37: 301 Exemption Renewed | S37: =SUM($M$21:$M$22) -> 0.5 | T37: =SUM($M$21:$M$22) -> 0.5 | U37: =SUM($M$21:$M$22) -> 0.5 | V37: =SUM($M$21:$M$22) -> 0.5
E39: Illustrative Gross Margin Build (NO TARIFF)
E40: Revenue - Grills | S40: 100 | T40: 100 | U40: 100 | V40: 100
E41: Less: Cost of Goods Sold - Grills | S41: =-S40*(1-$M$18) -> -61.5 | T41: =-T40*(1-$M$18) -> -61.5 | U41: =-U40*(1-$M$18) -> -61.5 | V41: =-V40*(1-$M$18) -> -61.5
E42: Gross Profit - Grills | S42: =S40+S41 -> 38.5 | T42: =T40+T41 -> 38.5 | U42: =U40+U41 -> 38.5 | V42: =V40+V41 -> 38.5
E43: Gross Profit (%) | S43: =S42/S40 -> 0.385 | T43: =T42/T40 -> 0.385 | U43: =U42/U40 -> 0.385 | V43: =V42/V40 -> 0.385
E45: Illustrative Gross Margin Build (TARIFF)
E46: Revenue - Grills | S46: 100 | T46: 100 | U46: 100 | V46: 100
E47: Plus: Additional Revenue from Price Increases | S47: =-S50*S27 -> 23.0625 | T47: =-T50*T27 -> 23.0625 | U47: =-U50*U27 -> 23.0625 | V47: =-V50*V27 -> 23.0625
E48: Total Revenues (Post Price Increase) | S48: =SUM(S46:S47) -> 123.0625 | T48: =SUM(T46:T47) -> 123.0625 | U48: =SUM(U46:U47) -> 123.0625 | V48: =SUM(V46:V47) -> 123.0625
E49: Less: Cost of Goods Sold - Grills | S49: =-S46*(1-$M$18) -> -61.5 | T49: =-T46*(1-$M$18) -> -61.5 | U49: =-U46*(1-$M$18) -> -61.5 | V49: =-V46*(1-$M$18) -> -61.5
E50: Less: Tariff Due - Grills | S50: =S49*S34 -> -30.75 | T50: =T49*T34 -> -30.75 | U50: =U49*U34 -> -30.75 | V50: =V49*V34 -> -30.75
E51: Gross Profit - Grills (Post Price Increase) | S51: =SUM(S48:S50) -> 30.8125 | T51: =SUM(T48:T50) -> 30.8125 | U51: =SUM(U48:U50) -> 30.8125 | V51: =SUM(V48:V50) -> 30.8125
E52: Gross Profit (%) | S52: =S51/S48 -> 0.2503809 | T52: =T51/T48 -> 0.2503809 | U52: =U51/U48 -> 0.2503809 | V52: =V51/V48 -> 0.2503809
E55: Negative Tariff Impact on Grills GM | S55: =S52-S43 -> -0.1346191 | T55: =T52-T43 -> -0.1346191 | U55: =U52-U43 -> -0.1346191 | V55: =V52-V43 -> -0.1346191
E58: Tariffs on Accessories
E59: Live Case | S59: =CHOOSE($F$8,S60,S61,S62) -> 0 | T59: =CHOOSE($F$8,T60,T61,T62) -> 0 | U59: =CHOOSE($F$8,U60,U61,U62) -> 0 | V59: =CHOOSE($F$8,V60,V61,V62) -> 0
D60: 1 | E60: Downside | K60: 301 Exemption Renewed | L60: 301 Exemption Not Renewed | S60: =$M$24 -> 0 | T60: =$M$24 -> 0 | U60: =$M$24 -> 0 | V60: =$M$24 -> 0
D61: 2 | E61: Base | K61: 301 Exemption Renewed | S61: =$M$24 -> 0 | T61: =$M$24 -> 0 | U61: =$M$24 -> 0 | V61: =$M$24 -> 0
D62: 3 | E62: Upside | K62: 301 Exemption Renewed | S62: =$M$24 -> 0 | T62: =$M$24 -> 0 | U62: =$M$24 -> 0 | V62: =$M$24 -> 0
E64: Illustrative Gross Margin Build (NO TARIFF)
E65: Revenue - Accessories | S65: 100 | T65: 100 | U65: 100 | V65: 100
E66: Less: Cost of Goods Sold - Accessories | S66: =-S65*(1-$M$18) -> -61.5 | T66: =-T65*(1-$M$18) -> -61.5 | U66: =-U65*(1-$M$18) -> -61.5 | V66: =-V65*(1-$M$18) -> -61.5
E67: Gross Profit - Grills | S67: =S65+S66 -> 38.5 | T67: =T65+T66 -> 38.5 | U67: =U65+U66 -> 38.5 | V67: =V65+V66 -> 38.5
E68: Gross Profit (%) | S68: =S67/S65 -> 0.385 | T68: =T67/T65 -> 0.385 | U68: =U67/U65 -> 0.385 | V68: =V67/V65 -> 0.385
E70: Illustrative Gross Margin Build (TARIFF)
E71: Revenue - Accessories | S71: 100 | T71: 100 | U71: 100 | V71: 100
E72: Plus: Additional Revenue from Price Increases | S72: =-S75*S52 -> 0 | T72: =-T75*T52 -> 0 | U72: =-U75*U52 -> 0 | V72: =-V75*V52 -> 0
E73: Total Revenues (Post Price Increase) | S73: =SUM(S71:S72) -> 100 | T73: =SUM(T71:T72) -> 100 | U73: =SUM(U71:U72) -> 100 | V73: =SUM(V71:V72) -> 100
E74: Less: Cost of Goods Sold - Grills | S74: =-S71*(1-$M$18) -> -61.5 | T74: =-T71*(1-$M$18) -> -61.5 | U74: =-U71*(1-$M$18) -> -61.5 | V74: =-V71*(1-$M$18) -> -61.5
E75: Less: Tariff Due - Accessories | S75: =S74*S59 -> 0 | T75: =T74*T59 -> 0 | U75: =U74*U59 -> 0 | V75: =V74*V59 -> 0
E76: Gross Profit - Grills (Post Price Increase) | S76: =SUM(S73:S75) -> 38.5 | T76: =SUM(T73:T75) -> 38.5 | U76: =SUM(U73:U75) -> 38.5 | V76: =SUM(V73:V75) -> 38.5
E77: Gross Profit (%) | S77: =S76/S73 -> 0.385 | T77: =T76/T73 -> 0.385 | U77: =U76/U73 -> 0.385 | V77: =V76/V73 -> 0.385
E80: Negative Tariff Impact on Accessories GM | S80: =S68-S77 -> 0 | T80: =T68-T77 -> 0 | U80: =U68-U77 -> 0 | V80: =V68-V77 -> 0
E82: Gross Margin
E83: Live Case | S83: =S87 -> 0.385 | T83: =T87 -> 0.385 | U83: =U87 -> 0.385 | V83: =V87 -> 0.385
E84: Base | S84: =$M$18 -> 0.385 | T84: =$M$18 -> 0.385 | U84: =$M$18 -> 0.385 | V84: =$M$18 -> 0.385
D85: 1 | E85: Proportional Negative Tariff Impact - Grills (%) | S85: =IF($D85=$F$8,S55*S196/S199,0) -> 0 | T85: =IF($D85=$F$8,T55*T196/T199,0) -> 0 | U85: =IF($D85=$F$8,U55*U196/U199,0) -> 0 | V85: =IF($D85=$F$8,V55*V196/V199,0) -> 0
D86: 1 | E86: Proportional Negative Tariff Impact - Accessories (%) | S86: =IF($D86=$F$8,S80*S198/S199,0) -> 0 | T86: =IF($D86=$F$8,T80*T198/T199,0) -> 0 | U86: =IF($D86=$F$8,U80*U198/U199,0) -> 0 | V86: =IF($D86=$F$8,V80*V198/V199,0) -> 0
E87: Gross Margin | S87: =SUM(S84:S86) -> 0.385 | T87: =SUM(T84:T86) -> 0.385 | U87: =SUM(U84:U86) -> 0.385 | V87: =SUM(V84:V86) -> 0.385
E89: Tariff Impact on Revenue | S89: =S118*S196 -> -9.153936 | T89: =T118*T196 -> -7.8338304 | U89: =Q89 -> 0 | V89: =R89 -> 0
E90: Tariff Impact on Gross margin | S90: =SUM(S85:S86)*S$199 -> 0 | T90: =SUM(T85:T86)*T$199 -> 0 | U90: =SUM(U85:U86)*U$199 -> 0 | V90: =SUM(V85:V86)*V$199 -> 0
E91: Tariif Impact ($) | S91: =SUM(S88:S90) -> -9.153936 | T91: =SUM(T88:T90) -> -7.8338304 | U91: =SUM(U88:U90) -> 0 | V91: =SUM(V88:V90) -> 0
E93: Gross Margin | S93: =CHOOSE($F$8,S94,S95,S96) -> 0.385 | T93: =CHOOSE($F$8,T94,T95,T96) -> 0.385 | U93: =CHOOSE($F$8,U94,U95,U96) -> 0.385 | V93: =CHOOSE($F$8,V94,V95,V96) -> 0.385
D94: 1 | E94: Downside | S94: 0.37 | T94: 0.37 | U94: 0.37 | V94: 0.37
D95: 2 | E95: Base | S95: 0.385 | T95: 0.385 | U95: 0.385 | V95: 0.385
D96: 3 | E96: Upside | S96: 0.4 | T96: 0.4 | U96: 0.4 | V96: 0.4
E98: Revenue Assumptions
E100: Grill Demand Elasticity | M100: =CHOOSE($F$8,M101,M102,M103) -> -1.5
D101: 1 | E101: Downside | M101: -1.5
D102: 2 | E102: Base | M102: -1.5
D103: 3 | E103: Upside | M103: -1.5
D105: Grills - YoY Consumer Price Increase
E106: Live Case | S106: =CHOOSE($F$8,S107,S108,S109) -> 0.1921875 | T106: =CHOOSE($F$8,T107,T108,T109) -> 0.1921875 | U106: =CHOOSE($F$8,U107,U108,U109) -> 0 | V106: =CHOOSE($F$8,V107,V108,V109) -> 0
D107: 1 | E107: Downside | S107: =IF($F$8=$D107,((1+$M$19)+((S$34*(1-$M$18))*S$27))/(1+$M$19)-1,S107) -> 0 | T107: =IF($F$8=$D107,((1+$M$19)+((T$34*(1-$M$18))*T$27))/(1+$M$19)-1,T107) -> 0.128125 | U107: 0 | V107: 0
D108: 2 | E108: Base | S108: =IF($F$8=$D108,((1+$M$19)+((S$34*(1-$M$18))*S$27))/(1+$M$19)-1,S108) -> 0.1921875 | T108: =IF($F$8=$D108,((1+$M$19)+((T$34*(1-$M$18))*T$27))/(1+$M$19)-1,T108) -> 0.1921875 | U108: 0 | V108: 0
D109: 3 | E109: Upside | S109: =IF($F$8=$D109,((1+$M$19)+((S$34*(1-$M$18))*S$27))/(1+$M$19)-1,S109) -> 0.230625 | T109: =IF($F$8=$D109,((1+$M$19)+((T$34*(1-$M$18))*T$27))/(1+$M$19)-1,T109) -> 0.230625 | U109: 0 | V109: 0
D111: Grills - YoY Volumes % Change
E112: Live Case | S112: =CHOOSE($F$8,S113,S114,S115) -> -0.28828125 | T112: =CHOOSE($F$8,T113,T114,T115) -> -0.28828125 | U112: =CHOOSE($F$8,U113,U114,U115) -> 0 | V112: =CHOOSE($F$8,V113,V114,V115) -> 0
D113: 1 | E113: Downside | S113: =S107*$M$100 -> 0 | T113: =T107*$M$100 -> -0.1921875 | U113: =U107*$M$100 -> 0 | V113: =V107*$M$100 -> 0
D114: 2 | E114: Base | S114: =S108*$M$100 -> -0.28828125 | T114: =T108*$M$100 -> -0.28828125 | U114: =U108*$M$100 -> 0 | V114: =V108*$M$100 -> 0
D115: 3 | E115: Upside | S115: =S109*$M$100 -> -0.3459375 | T115: =T109*$M$100 -> -0.3459375 | U115: =U109*$M$100 -> 0 | V115: =V109*$M$100 -> 0
D117: Grills Revenue Growth
E118: Live Case | S118: =CHOOSE($F$8,S119,S120,S121) -> -0.12 | T118: =CHOOSE($F$8,T119,T120,T121) -> -0.12 | U118: =CHOOSE($F$8,U119,U120,U121) -> -0.12 | V118: =CHOOSE($F$8,V119,V120,V121) -> -0.12
D119: 1 | E119: Downside | S119: -0.2 | T119: -0.2 | U119: -0.2 | V119: -0.2
D120: 2 | E120: Base | S120: -0.12 | T120: -0.12 | U120: -0.12 | V120: -0.12
D121: 3 | E121: Upside | S121: =(1+S109)*(1+S115)-1 -> -0.19509434 | T121: =(1+T109)*(1+T115)-1 -> -0.19509434 | U121: =(1+U109)*(1+U115)-1 -> 0 | V121: =(1+V109)*(1+V115)-1 -> 0
D123: Consumables Revenue Growth
E124: Live Case | S124: =CHOOSE($F$8,S125,S126,S127) -> 0 | T124: =CHOOSE($F$8,T125,T126,T127) -> 0 | U124: =CHOOSE($F$8,U125,U126,U127) -> 0 | V124: =CHOOSE($F$8,V125,V126,V127) -> 0
D125: 1 | E125: Downside | S125: 0 | T125: 0 | U125: 0 | V125: 0
D126: 2 | E126: Base | S126: 0 | T126: 0 | U126: 0 | V126: 0
D127: 3 | E127: Upside | S127: 0 | T127: 0 | U127: 0 | V127: 0
E129: Accessories Demand Elasticity | M129: -2
D131: Accessories - Consumer Price Increase
E132: Live Case | S132: =CHOOSE($F$8,S133,S134,S135) -> 0 | T132: =CHOOSE($F$8,T133,T134,T135) -> 0 | U132: =CHOOSE($F$8,U133,U134,U135) -> 0 | V132: =CHOOSE($F$8,V133,V134,V135) -> 0
...

Sheet O1
D3: Traeger Pellet Grills | P3: DRAFT
D4: Historical Financials | P4: CONFIDENTIAL
D5: Data as of 2Q'25
H8: Year Ended | O8: ='Historical Financials'!AI7 -> Quarter Ended
H10: 2020 | I10: 2021 | J10: ='Historical Financials'!AD8 -> 2022 | K10: 2023 | L10: ='Historical Financials'!AF8 -> 2024 | M10: ='Historical Financials'!AG8 -> 2025 | N10: LTM 3Q25 | O10: ='Historical Financials'!AI8 -> 4Q'24 | P10: ='Historical Financials'!AJ8 -> 4Q'25
D12: Revenue
E13: Grills | H13: ='Historical Financials'!AB14 -> 391.047 | I13: ='Historical Financials'!AC14 -> 544.2 | J13: ='Historical Financials'!AD14 -> 355.441 | K13: ='Historical Financials'!AE14 -> 299.346 | L13: ='Historical Financials'!AF14 -> 324.702 | M13: ='Historical Financials'!AG14 -> 298.01 | N13: ='Historical Financials'!AH14 -> 315.419 | O13: ='Historical Financials'!AI14 -> 77.981 | P13: ='Historical Financials'!AJ14 -> 60.572 | R13: =M13/L13-1 -> -0.082204606
E14: Consumables | H14: ='Historical Financials'!AB15 -> 120.247 | I14: ='Historical Financials'!AC15 -> 136.216 | J14: ='Historical Financials'!AD15 -> 131.342 | K14: ='Historical Financials'!AE15 -> 114.901 | L14: ='Historical Financials'!AF15 -> 119.299 | M14: ='Historical Financials'!AG15 -> 127.51 | N14: ='Historical Financials'!AH15 -> 122.619 | O14: ='Historical Financials'!AI15 -> 30.678 | P14: ='Historical Financials'!AJ15 -> 35.569
E15: Accessories | H15: ='Historical Financials'!AB16 -> 34.478 | I15: ='Historical Financials'!AC16 -> 105.129 | J15: ='Historical Financials'!AD16 -> 169.118 | K15: ='Historical Financials'!AE16 -> 191.635 | L15: ='Historical Financials'!AF16 -> 160.071 | M15: ='Historical Financials'!AG16 -> 134 | N15: ='Historical Financials'!AH16 -> 144.762 | O15: ='Historical Financials'!AI16 -> 59.978 | P15: ='Historical Financials'!AJ16 -> 49.216
D16: Total Revenue | H16: ='Historical Financials'!AB17 -> 545.772 | I16: ='Historical Financials'!AC17 -> 785.545 | J16: ='Historical Financials'!AD17 -> 655.901 | K16: ='Historical Financials'!AE17 -> 605.882 | L16: ='Historical Financials'!AF17 -> 604.072 | M16: ='Historical Financials'!AG17 -> 559.52 | N16: ='Historical Financials'!AH17 -> 582.8 | O16: ='Historical Financials'!AI17 -> 168.637 | P16: ='Historical Financials'!AJ17 -> 145.357
E17: Cost of Revenue | H17: ='Historical Financials'!AB18 -> 310.408 | I17: ='Historical Financials'!AC18 -> 481.834 | J17: ='Historical Financials'!AD18 -> 427.129 | K17: ='Historical Financials'!AE18 -> 382.325 | L17: ='Historical Financials'!AF18 -> 348.603 | M17: ='Historical Financials'!AG18 -> 340.174 | N17: ='Historical Financials'!AH18 -> 348.904 | O17: ='Historical Financials'!AI18 -> 99.747 | P17: ='Historical Financials'!AJ18 -> 91.017
D18: Gross Profit | H18: ='Historical Financials'!AB19 -> 235.364 | I18: ='Historical Financials'!AC19 -> 303.711 | J18: ='Historical Financials'!AD19 -> 228.772 | K18: ='Historical Financials'!AE19 -> 223.557 | L18: ='Historical Financials'!AF19 -> 255.469 | M18: ='Historical Financials'!AG19 -> 219.346 | N18: ='Historical Financials'!AH19 -> 233.896 | O18: ='Historical Financials'!AI19 -> 68.89 | P18: ='Historical Financials'!AJ19 -> 54.34
E19: Gross Margin | H19: ='Historical Financials'!AB20 -> 0.43124968 | I19: ='Historical Financials'!AC20 -> 0.38662457 | J19: ='Historical Financials'!AD20 -> 0.34879044 | K19: ='Historical Financials'!AE20 -> 0.36897779 | L19: ='Historical Financials'!AF20 -> 0.42291151 | M19: ='Historical Financials'!AG20 -> 0.39202531 | N19: ='Historical Financials'!AH20 -> 0.4013315 | O19: ='Historical Financials'!AI20 -> 0.40851059 | P19: ='Historical Financials'!AJ20 -> 0.37383821 | AF19: Retail | AG19: 468.452 | AH19: =AG19/SUM($AG$19:$AG$20) -> 0.83723906
D20: Operating Expenses | AF20: DTC | AG20: 91.068 | AH20: =AG20/SUM($AG$19:$AG$20) -> 0.16276094
E21: Sales and Marketing | H21: ='Historical Financials'!AB24 -> 93.69 | I21: ='Historical Financials'!AC24 -> 165.18 | J21: ='Historical Financials'!AD24 -> 130.688 | K21: ='Historical Financials'!AE24 -> 108.727 | L21: ='Historical Financials'!AF24 -> 109.656 | M21: ='Historical Financials'!AG24 -> 90.217 | N21: ='Historical Financials'!AH24 -> 100.58 | O21: ='Historical Financials'!AI24 -> 33.591 | P21: ='Historical Financials'!AJ24 -> 23.228
E22: General and Admin | H22: ='Historical Financials'!AB25 -> 50.243 | I22: ='Historical Financials'!AC25 -> 158.555 | J22: ='Historical Financials'!AD25 -> 166.824 | K22: ='Historical Financials'!AE25 -> 129.8 | L22: ='Historical Financials'!AF25 -> 113.483 | M22: ='Historical Financials'!AG25 -> 95.031 | N22: ='Historical Financials'!AH25 -> 99.934 | O22: ='Historical Financials'!AI25 -> 26.719 | P22: ='Historical Financials'!AJ25 -> 21.816
E23: Amortization of Intangibles | H23: ='Historical Financials'!AB26 -> 32.533 | I23: ='Historical Financials'!AC26 -> 34.379 | J23: ='Historical Financials'!AD26 -> 35.554 | K23: ='Historical Financials'!AE26 -> 35.554 | L23: ='Historical Financials'!AF26 -> 35.274 | M23: ='Historical Financials'!AG26 -> 35.26 | N23: ='Historical Financials'!AH26 -> 35.265 | O23: ='Historical Financials'!AI26 -> 8.818 | P23: ='Historical Financials'!AJ26 -> 8.813 | AK23: Grills | AL23: =M13 -> 298.01
E24: Change in fair value of contingent consideration | H24: ='Historical Financials'!AB27 -> 0 | I24: ='Historical Financials'!AC27 -> 3.8 | J24: ='Historical Financials'!AD27 -> 10.002 | K24: ='Historical Financials'!AE27 -> 4.698 | L24: ='Historical Financials'!AF27 -> 0 | M24: ='Historical Financials'!AG27 -> 0 | N24: ='Historical Financials'!AH27 -> 0 | O24: ='Historical Financials'!AI27 -> 0 | P24: ='Historical Financials'!AJ27 -> 0 | AK24: Consumables | AL24: =M14 -> 127.51
E25: Goodwill impairment | H25: ='Historical Financials'!AB28 -> 0 | I25: ='Historical Financials'!AC28 -> 0 | J25: ='Historical Financials'!AD28 -> 222.322 | K25: ='Historical Financials'!AE28 -> 0 | L25: ='Historical Financials'!AF28 -> 0 | M25: ='Historical Financials'!AG28 -> 74.725 | N25: ='Historical Financials'!AH28 -> 74.725 | O25: ='Historical Financials'!AI28 -> 0 | P25: ='Historical Financials'!AJ28 -> 0 | AK25: Accessories | AL25: =M15 -> 134
E26: Restructuring Charges | H26: ='Historical Financials'!AB29 -> 0 | I26: ='Historical Financials'!AC29 -> 0 | J26: ='Historical Financials'!AD29 -> 9.324 | K26: ='Historical Financials'!AE29 -> 0.225 | L26: ='Historical Financials'!AF29 -> 0 | M26: ='Historical Financials'!AG29 -> 21.84 | N26: ='Historical Financials'!AH29 -> 9.672 | O26: ='Historical Financials'!AI29 -> 0 | P26: ='Historical Financials'!AJ29 -> 12.168 | AK26: Other | AL26: =SUM(AL24:AL25) -> 261.51
D27: Operating Income | H27: ='Historical Financials'!AB30 -> 58.898 | I27: ='Historical Financials'!AC30 -> -58.203 | J27: ='Historical Financials'!AD30 -> -345.942 | K27: ='Historical Financials'!AE30 -> -55.447 | L27: ='Historical Financials'!AF30 -> -2.944 | M27: ='Historical Financials'!AG30 -> -97.727 | N27: ='Historical Financials'!AH30 -> -86.28 | O27: ='Historical Financials'!AI30 -> -0.238 | P27: ='Historical Financials'!AJ30 -> -11.685
E28: Interest Expense, Net | H28: ='Historical Financials'!AB31 -> -34.073 | I28: ='Historical Financials'!AC31 -> -26.646 | J28: ='Historical Financials'!AD31 -> -27.885 | K28: ='Historical Financials'!AE31 -> -31.275 | L28: ='Historical Financials'!AF31 -> -33.5 | M28: ='Historical Financials'!AG31 -> -31.35 | N28: ='Historical Financials'!AH31 -> -31.991 | O28: ='Historical Financials'!AI31 -> -8.192 | P28: ='Historical Financials'!AJ31 -> -7.551
E29: Loss on extinguishment of debt | H29: ='Historical Financials'!AB32 -> 0 | I29: ='Historical Financials'!AC32 -> -5.185 | J29: ='Historical Financials'!AD32 -> 0 | K29: ='Historical Financials'!AE32 -> 0 | L29: ='Historical Financials'!AF32 -> 0 | M29: ='Historical Financials'!AG32 -> 0 | N29: ='Historical Financials'!AH32 -> 0 | O29: ='Historical Financials'!AI32 -> 0 | P29: ='Historical Financials'!AJ32 -> 0
E30: Other Income (expense) | H30: ='Historical Financials'!AB33 -> 7.526 | I30: ='Historical Financials'!AC33 -> 2.702 | J30: ='Historical Financials'!AD33 -> -7.127 | K30: ='Historical Financials'!AE33 -> 4.305 | L30: ='Historical Financials'!AF33 -> 0.48 | M30: ='Historical Financials'!AG33 -> 9.755 | N30: ='Historical Financials'!AH33 -> 9.05 | O30: ='Historical Financials'!AI33 -> -0.513 | P30: ='Historical Financials'!AJ33 -> 0.192
D31: Income (Loss) Before Tax | H31: ='Historical Financials'!AB34 -> 32.351 | I31: ='Historical Financials'!AC34 -> -87.332 | J31: ='Historical Financials'!AD34 -> -380.954 | K31: ='Historical Financials'!AE34 -> -82.417 | L31: ='Historical Financials'!AF34 -> -35.964 | M31: ='Historical Financials'!AG34 -> -119.322 | N31: ='Historical Financials'!AH34 -> -109.221 | O31: ='Historical Financials'!AI34 -> -8.943 | P31: ='Historical Financials'!AJ34 -> -19.044
E32: Provision (benefit) for Income Tax | H32: ='Historical Financials'!AB35 -> 0.749 | I32: ='Historical Financials'!AC35 -> 1.489 | J32: ='Historical Financials'!AD35 -> 1.186 | K32: ='Historical Financials'!AE35 -> 1.985 | L32: ='Historical Financials'!AF35 -> -1.956 | M32: ='Historical Financials'!AG35 -> -4.141 | N32: ='Historical Financials'!AH35 -> -4.283 | O32: ='Historical Financials'!AI35 -> -1.985 | P32: ='Historical Financials'!AJ35 -> -1.843
E33: Interest expense | H33: ='Historical Financials'!AB41 -> 34.073 | I33: ='Historical Financials'!AC41 -> 26.646 | J33: ='Historical Financials'!AD41 -> 27.885 | K33: ='Historical Financials'!AE41 -> 31.275 | L33: ='Historical Financials'!AF41 -> 33.5 | M33: ='Historical Financials'!AG41 -> 31.35 | N33: ='Historical Financials'!AH41 -> 31.991 | O33: ='Historical Financials'!AI41 -> 8.192 | P33: ='Historical Financials'!AJ41 -> 7.551
E34: Depreciation and amortization | H34: ='Historical Financials'!AB42 -> 40.968 | I34: ='Historical Financials'!AC42 -> 47.499 | J34: ='Historical Financials'!AD42 -> 56.617 | K34: ='Historical Financials'!AE42 -> 57.778 | L34: ='Historical Financials'!AF42 -> 56.327 | M34: ='Historical Financials'!AG42 -> 54.137 | N34: ='Historical Financials'!AH42 -> 55.103 | O34: ='Historical Financials'!AI42 -> 14.251 | P34: ='Historical Financials'!AJ42 -> 13.285
E35: Other (income) expense | H35: ='Historical Financials'!AB43 -> -5.947 | I35: ='Historical Financials'!AC43 -> 10.518 | J35: ='Historical Financials'!AD43 -> 2.466 | K35: ='Historical Financials'!AE43 -> -5.216 | L35: ='Historical Financials'!AF43 -> -1.614 | M35: ='Historical Financials'!AG43 -> -5.093 | N35: ='Historical Financials'!AH43 -> -4.614 | O35: ='Historical Financials'!AI43 -> 0.011 | P35: ='Historical Financials'!AJ43 -> -0.468
E36: Goodwill impairment | H36: ='Historical Financials'!AB44 -> 0 | I36: ='Historical Financials'!AC44 -> 0 | J36: ='Historical Financials'!AD44 -> 222.322 | K36: ='Historical Financials'!AE44 -> 0 | L36: ='Historical Financials'!AF44 -> 0 | M36: ='Historical Financials'!AG44 -> 74.725 | N36: ='Historical Financials'!AH44 -> 74.725 | O36: ='Historical Financials'!AI44 -> 0 | P36: ='Historical Financials'!AJ44 -> 0
E37: Restructuring costs | H37: ='Historical Financials'!AB45 -> 0 | I37: ='Historical Financials'!AC45 -> 0 | J37: ='Historical Financials'!AD45 -> 11.542 | K37: ='Historical Financials'!AE45 -> 0.225 | L37: ='Historical Financials'!AF45 -> 27.901 | M37: ='Historical Financials'!AG45 -> 24.942 | N37: ='Historical Financials'!AH45 -> 9.672 | O37: ='Historical Financials'!AI45 -> 0 | P37: ='Historical Financials'!AJ45 -> 15.27
E38: Equity-based compensation | H38: ='Historical Financials'!AB46 -> 12.81 | I38: ='Historical Financials'!AC46 -> 81.112 | J38: ='Historical Financials'!AD46 -> 87.697 | K38: ='Historical Financials'!AE46 -> 53.203 | L38: ='Historical Financials'!AF46 -> 1.794 | M38: ='Historical Financials'!AG46 -> 15.254 | N38: ='Historical Financials'!AH46 -> 17.313 | O38: ='Historical Financials'!AI46 -> 4.837 | P38: ='Historical Financials'!AJ46 -> 2.778
E39: Other adjustment items | H39: ='Historical Financials'!AB47 -> 1.82 | I39: ='Historical Financials'!AC54 -> 30.564 | J39: ='Historical Financials'!AD54 -> 13.952 | K39: ='Historical Financials'!AE54 -> 6.245 | L39: ='Historical Financials'!AF54 -> 0 | M39: ='Historical Financials'!AG54 -> -6.049 | N39: ='Historical Financials'!AH54 -> -6.036 | O39: ='Historical Financials'!AI54 -> 0.013 | P39: ='Historical Financials'!AJ54 -> 0
D40: Adjusted EBITDA | H40: ='Historical Financials'!AB55 -> 116.075 | I40: ='Historical Financials'!AC55 -> 109.007 | J40: ='Historical Financials'!AD55 -> 41.527 | K40: ='Historical Financials'!AE55 -> 61.093 | L40: ='Historical Financials'!AF55 -> 81.944 | M40: ='Historical Financials'!AG55 -> 69.969 | N40: ='Historical Financials'!AH55 -> 68.956 | O40: ='Historical Financials'!AI55 -> 18.361 | P40: ='Historical Financials'!AJ55 -> 19.372
E41: Margin | H41: ='Historical Financials'!AB56 -> 0.21268039 | I41: ='Historical Financials'!AC56 -> 0.13876608 | J41: ='Historical Financials'!AD56 -> 0.063312909 | K41: ='Historical Financials'!AE56 -> 0.10083317 | L41: ='Historical Financials'!AF56 -> 0.1356527 | M41: ='Historical Financials'!AG56 -> 0.12505183 | N41: ='Historical Financials'!AH56 -> 0.11831846 | O41: ='Historical Financials'!AI56 -> 0.10887883 | P41: ='Historical Financials'!AJ56 -> 0.13327188
E42: Less: Change in NWC | H42: ='Historical Financials'!AB69 -> -35.092 | I42: ='Historical Financials'!AC69 -> -82.343 | J42: ='Historical Financials'!AD69 -> 6.204 | K42: ='Historical Financials'!AE69 -> 37.167 | L42: ='Historical Financials'!AF69 -> -17.031 | M42: ='Historical Financials'!AG69 -> -9.023 | N42: ='Historical Financials'!AH69 -> -33.363 | O42: ='Historical Financials'!AI69 -> -4.999 | P42: ='Historical Financials'!AJ69 -> 19.341
E43: Less: Capex | H43: ='Historical Financials'!AB70 -> -14.127 | I43: ='Historical Financials'!AC70 -> -22.479 | J43: ='Historical Financials'!AD70 -> -18.398 | K43: ='Historical Financials'!AE70 -> -19.946 | L43: ='Historical Financials'!AF70 -> -11.996 | M43: ='Historical Financials'!AG70 -> -6.934 | N43: ='Historical Financials'!AH70 -> -7.576 | O43: ='Historical Financials'!AI70 -> -1.962 | P43: ='Historical Financials'!AJ70 -> -1.32
E44: Less: Provision for income tax | H44: =-H32 -> -0.749 | I44: =-I32 -> -1.489 | J44: =-J32 -> -1.186 | K44: =-K32 -> -1.985 | L44: =-L32 -> 1.956 | M44: =-M32 -> 4.141 | N44: =-N32 -> 4.283 | O44: =-O32 -> 1.985 | P44: =-P32 -> 1.843
D45: ='O2'!D31 -> FCF | H45: =H40+SUM(H42:H44) -> 66.107 | I45: =I40+SUM(I42:I44) -> 2.696 | J45: =J40+SUM(J42:J44) -> 28.147 | K45: =K40+SUM(K42:K44) -> 76.329 | L45: =L40+SUM(L42:L44) -> 54.873 | M45: =M40+SUM(M42:M44) -> 58.153 | N45: =N40+SUM(N42:N44) -> 32.3 | O45: =O40+SUM(O42:O44) -> 13.385 | P45: =P40+SUM(P42:P44) -> 39.236
E46: ='Historical Financials'!D72 -> Less: Interest Expense | H46: ='Historical Financials'!AB72 -> -34.073 | I46: ='Historical Financials'!AC72 -> -26.646 | J46: ='Historical Financials'!AD72 -> -27.885 | K46: ='Historical Financials'!AE72 -> -31.275 | L46: ='Historical Financials'!AF72 -> -33.5 | M46: ='Historical Financials'!AG72 -> -31.35 | N46: ='Historical Financials'!AH72 -> -31.991 | O46: ='Historical Financials'!AI72 -> -8.192 | P46: ='Historical Financials'!AJ72 -> -7.551
E47: ='Historical Financials'!D73 -> Less: Mandatory Amortization | H47: ='Historical Financials'!AB73 -> -5.1 | I47: ='Historical Financials'!AC73 -> -5.1 | J47: ='Historical Financials'!AD73 -> -5.1 | K47: ='Historical Financials'!AE73 -> -5.1 | L47: ='Historical Financials'!AF73 -> -5.1 | M47: ='Historical Financials'!AG73 -> -5.1 | N47: ='Historical Financials'!AH73 -> -5.1 | O47: ='Historical Financials'!AI73 -> -1.275 | P47: ='Historical Financials'!AJ73 -> -1.275
D48: Levered Free Cash Flows | H48: =SUM(H45:H47) -> 26.934 | I48: =SUM(I45:I47) -> -29.05 | J48: =SUM(J45:J47) -> -4.838 | K48: =SUM(K45:K47) -> 39.954 | L48: =SUM(L45:L47) -> 16.273 | M48: =SUM(M45:M47) -> 21.703 | N48: =SUM(N45:N47) -> -4.791 | O48: =SUM(O45:O47) -> 3.918 | P48: =SUM(P45:P47) -> 30.41

Sheet O2
D3: Traeger Pellet Grills | P3: DRAFT
D4: Historical Financials | P4: CONFIDENTIAL
D5: Data as of 2Q'25
H8: Year Ended | O8: ='Historical Financials'!AI7 -> Quarter Ended
H10: 2020 | I10: 2021 | J10: ='Historical Financials'!AD8 -> 2022 | K10: 2023 | L10: ='Historical Financials'!AF8 -> 2024 | M10: ='Historical Financials'!AG8 -> 2025 | N10: LTM 3Q25 | O10: ='Historical Financials'!AI8 -> 4Q'24 | P10: ='Historical Financials'!AJ8 -> 4Q'25
D12: Revenue
D13: Grills | H13: ='Historical Financials'!AB14 -> 391.047 | I13: ='Historical Financials'!AC14 -> 544.2 | J13: ='Historical Financials'!AD14 -> 355.441 | K13: ='Historical Financials'!AE14 -> 299.346 | L13: ='Historical Financials'!AF14 -> 324.702 | M13: ='Historical Financials'!AG14 -> 298.01 | N13: ='O1'!N13 -> 315.419 | O13: ='Historical Financials'!AI14 -> 77.981 | P13: ='Historical Financials'!AJ14 -> 60.572
D14: Consumables | H14: ='Historical Financials'!AB15 -> 120.247 | I14: ='Historical Financials'!AC15 -> 136.216 | J14: ='Historical Financials'!AD15 -> 131.342 | K14: ='Historical Financials'!AE15 -> 114.901 | L14: ='Historical Financials'!AF15 -> 119.299 | M14: ='Historical Financials'!AG15 -> 127.51 | N14: ='O1'!N14 -> 122.619 | O14: ='Historical Financials'!AI15 -> 30.678 | P14: ='Historical Financials'!AJ15 -> 35.569
D15: Accessories | H15: ='Historical Financials'!AB16 -> 34.478 | I15: ='Historical Financials'!AC16 -> 105.129 | J15: ='Historical Financials'!AD16 -> 169.118 | K15: ='Historical Financials'!AE16 -> 191.635 | L15: ='Historical Financials'!AF16 -> 160.071 | M15: ='Historical Financials'!AG16 -> 134 | N15: ='O1'!N15 -> 144.762 | O15: ='Historical Financials'!AI16 -> 59.978 | P15: ='Historical Financials'!AJ16 -> 49.216
D16: Total Revenue | H16: ='Historical Financials'!AB17 -> 545.772 | I16: ='Historical Financials'!AC17 -> 785.545 | J16: ='Historical Financials'!AD17 -> 655.901 | K16: ='Historical Financials'!AE17 -> 605.882 | L16: ='Historical Financials'!AF17 -> 604.072 | M16: ='Historical Financials'!AG17 -> 559.52 | N16: ='Historical Financials'!AH17 -> 582.8 | O16: ='Historical Financials'!AI17 -> 168.637 | P16: ='Historical Financials'!AJ17 -> 145.357
D17: YoY Growth | H17: =H16/'Historical Financials'!AA17-1 -> 0.50218403 | I17: =I16/H16-1 -> 0.43932814 | J17: =J16/I16-1 -> -0.16503701 | K17: =K16/J16-1 -> -0.076259984 | L17: =L16/K16-1 -> -0.0029873804 | M17: =M16/L16-1 -> -0.073752798 | N17: =N16/L16-1 -> -0.035214345 | O17: =O16/'Historical Financials'!M17-1 -> 0.22083065 | P17: =P16/O16-1 -> -0.138048
C18: Adjusted EBITDA | D18: Adjusted EBITDA | H18: ='Historical Financials'!AB55 -> 116.075 | I18: ='Historical Financials'!AC55 -> 109.007 | J18: ='Historical Financials'!AD55 -> 41.527 | K18: ='Historical Financials'!AE55 -> 61.093 | L18: ='Historical Financials'!AF55 -> 81.944 | M18: ='Historical Financials'!AG55 -> 69.969 | N18: ='Historical Financials'!AH55 -> 68.956 | O18: ='Historical Financials'!AI55 -> 18.361 | P18: ='Historical Financials'!AJ55 -> 19.372
D19: Margin | H19: =H18/H16 -> 0.21268039 | I19: =I18/I16 -> 0.13876608 | J19: =J18/J16 -> 0.063312909 | K19: =K18/K16 -> 0.10083317 | L19: =L18/L16 -> 0.1356527 | M19: =M18/M16 -> 0.12505183 | N19: =N18/N16 -> 0.11831846 | O19: =O18/O16 -> 0.10887883 | P19: =P18/P16 -> 0.13327188
C20: Change in NWC | D20: Change in NWC
C21: A/R | D21: ='Historical Financials'!D63 -> Accounts receivable | H21: ='Historical Financials'!AB63 -> -30.17 | I21: ='Historical Financials'!AC63 -> -26.365 | J21: ='Historical Financials'!AD63 -> 51.052 | K21: ='Historical Financials'!AE63 -> -17.735 | L21: ='Historical Financials'!AF63 -> -25.396 | M21: ='Historical Financials'!AG63 -> 3.15 | N21: ='Historical Financials'!AH63 -> -9.896 | O21: ='Historical Financials'!AI63 -> -14.545 | P21: ='Historical Financials'!AJ63 -> -1.499
C22: Inventories | D22: ='Historical Financials'!D64 -> Inventories, net | H22: ='Historical Financials'!AB64 -> -28.979 | I22: ='Historical Financials'!AC64 -> -67.826 | J22: ='Historical Financials'!AD64 -> -11.931 | K22: ='Historical Financials'!AE64 -> 57.295 | L22: ='Historical Financials'!AF64 -> -11.192 | M22: ='Historical Financials'!AG64 -> 8.536 | N22: ='Historical Financials'!AH64 -> -9.568 | O22: ='Historical Financials'!AI64 -> -2.309 | P22: ='Historical Financials'!AJ64 -> 15.795
C23: Prepaid expenses | D23: ='Historical Financials'!D65 -> Prepaid expenses and other current assets | H23: ='Historical Financials'!AB65 -> -4.311 | I23: ='Historical Financials'!AC65 -> -5.787 | J23: ='Historical Financials'!AD65 -> -3.046 | K23: ='Historical Financials'!AE65 -> -4.199 | L23: ='Historical Financials'!AF65 -> -7.573 | M23: ='Historical Financials'!AG65 -> 14.355 | N23: ='Historical Financials'!AH65 -> 5.422 | O23: ='Historical Financials'!AI65 -> -10.169 | P23: ='Historical Financials'!AJ65 -> -1.236
C24: Other assets | D24: ='Historical Financials'!D66 -> Other non-current assets | H24: ='Historical Financials'!AB66 -> 0 | I24: ='Historical Financials'!AC66 -> -0.681 | J24: ='Historical Financials'!AD66 -> 0.078 | K24: ='Historical Financials'!AE66 -> -0.568 | L24: ='Historical Financials'!AF66 -> 0.148 | M24: ='Historical Financials'!AG66 -> 0.114 | N24: ='Historical Financials'!AH66 -> 0.157 | O24: ='Historical Financials'!AI66 -> 0.062 | P24: ='Historical Financials'!AJ66 -> 0.019
C25: A/P | D25: ='Historical Financials'!D67 -> Accounts payable and accrued expenses | H25: ='Historical Financials'!AB67 -> 28.351 | I25: ='Historical Financials'!AC67 -> 19.182 | J25: ='Historical Financials'!AD67 -> -28.211 | K25: ='Historical Financials'!AE67 -> 2.374 | L25: ='Historical Financials'!AF67 -> 26.982 | M25: ='Historical Financials'!AG67 -> -35.178 | N25: ='Historical Financials'!AH67 -> -19.478 | O25: ='Historical Financials'!AI67 -> 21.962 | P25: ='Historical Financials'!AJ67 -> 6.262
C26: Other liabilities | D26: ='Historical Financials'!D68 -> Other non-current liabilities | H26: ='Historical Financials'!AB68 -> 0.017 | I26: ='Historical Financials'!AC68 -> -0.866 | J26: ='Historical Financials'!AD68 -> -1.738 | K26: ='Historical Financials'!AE68 -> 0 | L26: ='Historical Financials'!AF68 -> 0 | M26: ='Historical Financials'!AG68 -> 0 | N26: ='Historical Financials'!AH68 -> 0 | O26: ='Historical Financials'!AI68 -> 0 | P26: ='Historical Financials'!AJ68 -> 0
C27: Total Change in NWC | D27: Total Change in NWC | H27: =SUM(H21:H26) -> -35.092 | I27: =SUM(I21:I26) -> -82.343 | J27: =SUM(J21:J26) -> 6.204 | K27: =SUM(K21:K26) -> 37.167 | L27: =SUM(L21:L26) -> -17.031 | M27: =SUM(M21:M26) -> -9.023 | N27: =SUM(N21:N26) -> -33.363 | O27: =SUM(O21:O26) -> -4.999 | P27: =SUM(P21:P26) -> 19.341
E28: Change in NWC Check | H28: ='Historical Financials'!AB69 -> -35.092 | I28: ='Historical Financials'!AC69 -> -82.343 | J28: ='Historical Financials'!AD69 -> 6.204 | K28: ='Historical Financials'!AE69 -> 37.167 | L28: ='Historical Financials'!AF69 -> -17.031 | M28: ='Historical Financials'!AG69 -> -9.023 | N28: ='Historical Financials'!AH69 -> -33.363 | O28: ='Historical Financials'!AI69 -> -4.999 | P28: ='Historical Financials'!AJ69 -> 19.341
C29: Capex | D29: Less: Capex | H29: ='Historical Financials'!AB70 -> -14.127 | I29: ='Historical Financials'!AC70 -> -22.479 | J29: ='Historical Financials'!AD70 -> -18.398 | K29: ='Historical Financials'!AE70 -> -19.946 | L29: ='Historical Financials'!AF70 -> -11.996 | M29: ='Historical Financials'!AG70 -> -6.934 | N29: ='Historical Financials'!AH70 -> -7.576 | O29: ='Historical Financials'!AI70 -> -1.962 | P29: ='Historical Financials'!AJ70 -> -1.32
C30: Income taxes | D30: Less: Provision for income taxes | H30: =-'O1'!H32 -> -0.749 | I30: =-'O1'!I32 -> -1.489 | J30: =-'O1'!J32 -> -1.186 | K30: =-'O1'!K32 -> -1.985 | L30: =-'O1'!L32 -> 1.956 | M30: =-'O1'!M32 -> 4.141 | N30: =-'O1'!N32 -> 4.283 | O30: =-'O1'!O32 -> 1.985 | P30: =-'O1'!P32 -> 1.843
C31: FCF | D31: FCF | H31: =H18+SUM(H27,H29:H30) -> 66.107 | I31: =I18+SUM(I27,I29:I30) -> 2.696 | J31: =J18+SUM(J27,J29:J30) -> 28.147 | K31: =K18+SUM(K27,K29:K30) -> 76.329 | L31: =L18+SUM(L27,L29:L30) -> 54.873 | M31: =M18+SUM(M27,M29:M30) -> 58.153 | N31: =N18+SUM(N27,N29:N30) -> 32.3 | O31: =O18+SUM(O27,O29:O30) -> 13.385 | P31: =P18+SUM(P27,P29:P30) -> 39.236
E32: Less: Interest expense | H32: ='Historical Financials'!AB72 -> -34.073 | I32: ='Historical Financials'!AC72 -> -26.646 | J32: ='Historical Financials'!AD72 -> -27.885 | K32: ='Historical Financials'!AE72 -> -31.275 | L32: ='Historical Financials'!AH72 -> -31.991 | O32: ='Historical Financials'!AI72 -> -8.192 | P32: ='Historical Financials'!AJ72 -> -7.551
E33: Less: Mandatory amortization | H33: ='Historical Financials'!AB73 -> -5.1 | I33: ='Historical Financials'!AC73 -> -5.1 | J33: ='Historical Financials'!AD73 -> -5.1 | K33: ='Historical Financials'!AE73 -> -5.1 | L33: ='Historical Financials'!AH73 -> -5.1 | O33: ='Historical Financials'!AI73 -> -1.275 | P33: ='Historical Financials'!AJ73 -> -1.275
D34: Levered FCF | H34: =SUM(H31:H33) -> 26.934 | I34: =SUM(I31:I33) -> -29.05 | J34: =SUM(J31:J33) -> -4.838 | K34: =SUM(K31:K33) -> 39.954 | L34: =SUM(L31:L33) -> 17.782 | O34: =SUM(O31:O33) -> 3.918 | P34: =SUM(P31:P33) -> 30.41

Sheet O3
D3: Traeger Pellet Grills | O3: DRAFT
D4: Liquidity Model Output | G4: Case | H4: ='Liquidity Model'!F8 -> 2 | J4: Print Screen | K4: 1 | O4: CONFIDENTIAL
D5: Data as of 1Q'25
F6: Actuals | K6: Forecast
F8: 1Q'25 | G8: 2Q'25 | H8: 3Q'25 | I8: 4Q'25 | J8: FY'25 | K8: 1Q'26 | L8: 2Q'26 | M8: 3Q'26 | N8: 4Q'26 | O8: FY'26
D10: Revenue
D11: Grills | F11: ='Liquidity Model'!O196 -> 86.685 | G11: ='Liquidity Model'!P196 -> 74.184 | H11: ='Liquidity Model'!Q196 -> 76.569 | I11: ='Liquidity Model'!R196 -> 60.572 | J11: =SUM(F11:I11) -> 298.01 | K11: ='Liquidity Model'!S196 -> 76.2828 | L11: ='Liquidity Model'!T196 -> 65.28192 | M11: ='Liquidity Model'!U196 -> 67.38072 | N11: ='Liquidity Model'!V196 -> 53.30336 | O11: =SUM(K11:N11) -> 262.2488
D12: Consumables | F12: ='Liquidity Model'!O197 -> 30.288 | G12: ='Liquidity Model'!P197 -> 36.357 | H12: ='Liquidity Model'!Q197 -> 25.296 | I12: ='Liquidity Model'!R197 -> 35.569 | J12: =SUM(F12:I12) -> 127.51 | K12: ='Liquidity Model'!S197 -> 30.288 | L12: ='Liquidity Model'!T197 -> 36.357 | M12: ='Liquidity Model'!U197 -> 25.296 | N12: ='Liquidity Model'!V197 -> 35.569 | O12: =SUM(K12:N12) -> 127.51
D13: Accessories | F13: ='Liquidity Model'!O198 -> 26.31 | G13: ='Liquidity Model'!P198 -> 34.943 | H13: ='Liquidity Model'!Q198 -> 23.531 | I13: ='Liquidity Model'!R198 -> 49.216 | J13: =SUM(F13:I13) -> 134 | K13: ='Liquidity Model'!S198 -> 16.5753 | L13: ='Liquidity Model'!T198 -> 22.01409 | M13: ='Liquidity Model'!U198 -> 14.82453 | N13: ='Liquidity Model'!V198 -> 31.00608 | O13: =SUM(K13:N13) -> 84.42
D14: Total Revenue | F14: ='Liquidity Model'!O199 -> 143.283 | G14: ='Liquidity Model'!P199 -> 145.484 | H14: ='Liquidity Model'!Q199 -> 125.396 | I14: ='Liquidity Model'!R199 -> 145.357 | J14: =SUM(F14:I14) -> 559.52 | K14: ='Liquidity Model'!S199 -> 123.1461 | L14: ='Liquidity Model'!T199 -> 123.65301 | M14: ='Liquidity Model'!U199 -> 107.50125 | N14: ='Liquidity Model'!V199 -> 119.87844 | O14: =SUM(K14:N14) -> 474.1788
D16: Cost of Revenue | F16: ='Liquidity Model'!O200 -> -83.824 | G16: ='Liquidity Model'!P200 -> -88.483 | H16: ='Liquidity Model'!Q200 -> -76.85 | I16: ='Liquidity Model'!R200 -> -91.017 | J16: =SUM(F16:I16) -> -340.174 | K16: ='Liquidity Model'!S200 -> -75.734852 | L16: ='Liquidity Model'!T200 -> -76.046601 | M16: ='Liquidity Model'!U200 -> -66.113269 | N16: ='Liquidity Model'!V200 -> -73.725241 | O16: =SUM(K16:N16) -> -291.61996
D17: Gross Profit | F17: ='Liquidity Model'!O201 -> 59.459 | G17: ='Liquidity Model'!P201 -> 57.001 | H17: ='Liquidity Model'!Q201 -> 48.546 | I17: ='Liquidity Model'!R201 -> 54.34 | J17: =SUM(F17:I17) -> 219.346 | K17: ='Liquidity Model'!S201 -> 47.411248 | L17: ='Liquidity Model'!T201 -> 47.606409 | M17: ='Liquidity Model'!U201 -> 41.387981 | N17: ='Liquidity Model'!V201 -> 46.153199 | O17: =SUM(K17:N17) -> 182.55884
D18: Gross Margin | F18: ='Liquidity Model'!O229 -> 0.41497596 | G18: ='Liquidity Model'!P229 -> 0.39180253 | H18: ='Liquidity Model'!Q229 -> 0.38714154 | I18: ='Liquidity Model'!R229 -> 0.37383821 | J18: =J17/J14 -> 0.39202531 | K18: ='Liquidity Model'!S229 -> 0.385 | L18: ='Liquidity Model'!T229 -> 0.385 | M18: ='Liquidity Model'!U229 -> 0.385 | N18: ='Liquidity Model'!V229 -> 0.385 | O18: =O17/O14 -> 0.385
D20: Operating Expenses
D21: Sales and Marketing | F21: ='Liquidity Model'!O204 -> -22.21 | G21: ='Liquidity Model'!P204 -> -24.779 | H21: ='Liquidity Model'!Q204 -> -20 | I21: ='Liquidity Model'!R204 -> -23.228 | J21: =SUM(F21:I21) -> -90.217 | K21: ='Liquidity Model'!S204 -> -21.988 | L21: ='Liquidity Model'!T204 -> -24.779 | M21: ='Liquidity Model'!U204 -> -20 | N21: ='Liquidity Model'!V204 -> -23.228 | O21: =SUM(K21:N21) -> -89.995
D22: G&A (excl. D&A) | F22: ='Liquidity Model'!O205 -> -10.777 | G22: ='Liquidity Model'!P205 -> -12.724 | H22: ='Liquidity Model'!Q205 -> -8.862 | I22: ='Liquidity Model'!R205 -> -8.531 | J22: =SUM(F22:I22) -> -40.894 | K22: ='Liquidity Model'!S205 -> -8.620227 | L22: ='Liquidity Model'!T205 -> -8.620227 | M22: ='Liquidity Model'!U205 -> -8.620227 | N22: ='Liquidity Model'!V205 -> -8.620227 | O22: =SUM(K22:N22) -> -34.480908
D23: Other Op. Expenses | F23: ='Liquidity Model'!O206 -> -8.818 | G23: ='Liquidity Model'!P206 -> -12.284 | H23: ='Liquidity Model'!Q206 -> -89.742 | I23: ='Liquidity Model'!R206 -> -20.981 | J23: =SUM(F23:I23) -> -131.825 | K23: ='Liquidity Model'!S206 -> -12.31461 | L23: ='Liquidity Model'!T206 -> -12.365301 | M23: ='Liquidity Model'!U206 -> -10.750125 | N23: ='Liquidity Model'!V206 -> -11.987844 | O23: =SUM(K23:N23) -> -47.41788
D24: Operating Income | F24: ='Liquidity Model'!O207 -> 17.654 | G24: ='Liquidity Model'!P207 -> 7.214 | H24: ='Liquidity Model'!Q207 -> -70.058 | I24: ='Liquidity Model'!R207 -> 1.6 | J24: =SUM(F24:I24) -> -43.59 | K24: ='Liquidity Model'!S207 -> 4.4884115 | L24: ='Liquidity Model'!T207 -> 1.8418808 | M24: ='Liquidity Model'!U207 -> 2.0176292 | N24: ='Liquidity Model'!V207 -> 2.3171284 | O24: =SUM(K24:N24) -> 10.66505
D26: Share-based comp. | F26: ='Liquidity Model'!O208 -> 5.176 | G26: ='Liquidity Model'!P208 -> 3.969 | H26: ='Liquidity Model'!Q208 -> 3.331 | I26: ='Liquidity Model'!R208 -> 2.778 | J26: =SUM(F26:I26) -> 15.254 | K26: ='Liquidity Model'!S208 -> 3.694383 | L26: ='Liquidity Model'!T208 -> 3.7095903 | M26: ='Liquidity Model'!U208 -> 3.2250375 | N26: ='Liquidity Model'!V208 -> 3.5963532 | O26: =SUM(K26:N26) -> 14.225364
D27: Other adjustment items(1) | F27: ='Liquidity Model'!O209 -> -0.308 | G27: ='Liquidity Model'!P209 -> 3.065 | H27: ='Liquidity Model'!Q209 -> 80.529 | I27: ='Liquidity Model'!R209 -> 14.994 | J27: =SUM(F27:I27) -> 98.28 | K27: ='Liquidity Model'!S209 -> 7.5 | L27: ='Liquidity Model'!T209 -> 7.5 | M27: ='Liquidity Model'!U209 -> 7.5 | N27: ='Liquidity Model'!V209 -> 7.5 | O27: =SUM(K27:N27) -> 30
D28: Adjusted EBITDA | F28: ='Liquidity Model'!O210 -> 22.522 | G28: ='Liquidity Model'!P210 -> 14.248 | H28: ='Liquidity Model'!Q210 -> 13.802 | I28: ='Liquidity Model'!R210 -> 19.372 | J28: =SUM(F28:I28) -> 69.944 | K28: ='Liquidity Model'!S210 -> 15.682794 | L28: ='Liquidity Model'!T210 -> 13.051471 | M28: ='Liquidity Model'!U210 -> 12.742667 | N28: ='Liquidity Model'!V210 -> 13.413482 | O28: =SUM(K28:N28) -> 54.890414
D29: Adj. EBITDA Margin | F29: ='Liquidity Model'!O230 -> 0.15718543 | G29: ='Liquidity Model'!P230 -> 0.097935168 | H29: ='Liquidity Model'!Q230 -> 0.11006731 | I29: ='Liquidity Model'!R230 -> 0.13327188 | J29: =J28/J14 -> 0.12500715 | K29: ='Liquidity Model'!S230 -> 0.12735113 | L29: ='Liquidity Model'!T230 -> 0.10554916 | M29: ='Liquidity Model'!U230 -> 0.11853506 | N29: ='Liquidity Model'!V230 -> 0.11189236 | O29: =O28/O14 -> 0.1157589
D31: Free Cash Flow Build
D32: Less: Change in NWC | F32: ='Liquidity Model'!O213 -> -39.691 | G32: ='Liquidity Model'!P213 -> 7.405 | H32: ='Liquidity Model'!Q213 -> 3.922 | I32: ='Liquidity Model'!R213 -> 19.341 | J32: =SUM(F32:I32) -> -9.023 | K32: ='Liquidity Model'!S213 -> 5 | L32: ='Liquidity Model'!T213 -> 5 | M32: ='Liquidity Model'!U213 -> 5 | N32: ='Liquidity Model'!V213 -> 5 | O32: =SUM(K32:N32) -> 20
D33: Less: Capex | F33: ='Liquidity Model'!O214 -> -1.826 | G33: ='Liquidity Model'!P214 -> -2.625 | H33: ='Liquidity Model'!Q214 -> -1.163 | I33: ='Liquidity Model'!R214 -> -1.32 | J33: =SUM(F33:I33) -> -6.934 | K33: ='Liquidity Model'!S214 -> -2.1498576 | L33: ='Liquidity Model'!T214 -> -2.1587071 | M33: ='Liquidity Model'!U214 -> -1.8767332 | N33: ='Liquidity Model'!V214 -> -2.0928115 | O33: =SUM(K33:N33) -> -8.2781095
D34: Unlevered Free Cash Flow | F34: ='Liquidity Model'!O215 -> -18.995 | G34: ='Liquidity Model'!P215 -> 19.028 | H34: ='Liquidity Model'!Q215 -> 16.561 | I34: ='Liquidity Model'!R215 -> 37.393 | J34: =SUM(F34:I34) -> 53.987 | K34: ='Liquidity Model'!S215 -> 18.532937 | L34: ='Liquidity Model'!T215 -> 15.892764 | M34: ='Liquidity Model'!U215 -> 15.865934 | N34: ='Liquidity Model'!V215 -> 16.32067 | O34: =SUM(K34:N34) -> 66.612304
D36: Less: Interest Expense | F36: ='Liquidity Model'!O216 -> -7.893 | G36: ='Liquidity Model'!P216 -> -8.091 | H36: ='Liquidity Model'!Q216 -> -7.815 | I36: ='Liquidity Model'!R216 -> -7.551 | J36: =SUM(F36:I36) -> -31.35 | K36: ='Liquidity Model'!S216 -> -8.8494453 | L36: ='Liquidity Model'!T216 -> -9.3606836 | M36: ='Liquidity Model'!U216 -> -9.0553698 | N36: ='Liquidity Model'!V216 -> -8.8309418 | O36: =SUM(K36:N36) -> -36.096441
D37: Less: Mandatory Amort. | F37: ='Liquidity Model'!O217 -> -1.275 | G37: ='Liquidity Model'!P217 -> -1.275 | H37: ='Liquidity Model'!Q217 -> -1.275 | I37: ='Liquidity Model'!R217 -> -1.275 | J37: =SUM(F37:I37) -> -5.1 | K37: ='Liquidity Model'!S217 -> -1.275 | L37: ='Liquidity Model'!T217 -> -1.275 | M37: ='Liquidity Model'!U217 -> -1.275 | N37: ='Liquidity Model'!V217 -> -1.275 | O37: =SUM(K37:N37) -> -5.1
D38: Plus: New Money from Trx. | F38: ='Liquidity Model'!O218 -> 0 | G38: ='Liquidity Model'!P218 -> 0 | H38: ='Liquidity Model'!Q218 -> 0 | I38: ='Liquidity Model'!R218 -> 0 | J38: =SUM(F38:I38) -> 0 | K38: ='Liquidity Model'!S218 -> 75 | L38: ='Liquidity Model'!T218 -> 0 | M38: ='Liquidity Model'!U218 -> 0 | N38: ='Liquidity Model'!V218 -> 0 | O38: =SUM(K38:N38) -> 75
D39: Levered Free Cash Flows | F39: ='Liquidity Model'!O219 -> -28.163 | G39: ='Liquidity Model'!P219 -> 9.662 | H39: ='Liquidity Model'!Q219 -> 7.471 | I39: ='Liquidity Model'!R219 -> 28.567 | J39: =SUM(F39:I39) -> 17.537 | K39: ='Liquidity Model'!S219 -> 83.408492 | L39: ='Liquidity Model'!T219 -> 5.2570804 | M39: ='Liquidity Model'!U219 -> 5.5355637 | N39: ='Liquidity Model'!V219 -> 6.2147282 | O39: =SUM(K39:N39) -> 100.41586
D41: Liquidity Schedule
D42: Cash | F42: ='Liquidity Model'!O222 -> 12.034 | G42: ='Liquidity Model'!P222 -> 10.3 | H42: ='Liquidity Model'!Q222 -> 5.9 | I42: ='Liquidity Model'!R222 -> 19.624 | J42: =I42 -> 19.624 | K42: ='Liquidity Model'!S222 -> 103.03249 | L42: ='Liquidity Model'!T222 -> 108.28957 | M42: ='Liquidity Model'!U222 -> 113.82514 | N42: ='Liquidity Model'!V222 -> 120.03986 | O42: =N42 -> 120.03986
D43: RFA Availiability | F43: ='Liquidity Model'!O223 -> 5 | G43: ='Liquidity Model'!P223 -> 35.6 | H43: ='Liquidity Model'!Q223 -> 48.8 | I43: ='Liquidity Model'!R223 -> 30 | J43: =I43 -> 30 | K43: ='Liquidity Model'!S223 -> 30 | L43: ='Liquidity Model'!T223 -> 30 | M43: ='Liquidity Model'!U223 -> 30 | N43: ='Liquidity Model'!V223 -> 30 | O43: =N43 -> 30
D44: Revolver Availability | F44: ='Liquidity Model'!O224 -> 125 | G44: ='Liquidity Model'!P224 -> 112.5 | H44: ='Liquidity Model'!Q224 -> 112.5 | I44: ='Liquidity Model'!R224 -> 112.5 | J44: =I44 -> 112.5 | K44: ='Liquidity Model'!S224 -> 112.5 | L44: ='Liquidity Model'!T224 -> 82.5 | M44: ='Liquidity Model'!U224 -> 82.5 | N44: ='Liquidity Model'!V224 -> 82.5 | O44: =N44 -> 82.5
D45: Total Liquidity | F45: ='Liquidity Model'!O225 -> 142.034 | G45: ='Liquidity Model'!P225 -> 158.4 | H45: ='Liquidity Model'!Q225 -> 167.2 | I45: ='Liquidity Model'!R225 -> 162.124 | J45: =SUM(J42:J44) -> 162.124 | K45: ='Liquidity Model'!S225 -> 245.53249 | L45: ='Liquidity Model'!T225 -> 220.78957 | M45: ='Liquidity Model'!U225 -> 226.32514 | N45: ='Liquidity Model'!V225 -> 232.53986 | O45: =SUM(O42:O44) -> 232.53986
D48: Revenue
F49: 1Q'25 | G49: 2Q'25 | H49: 3Q'25 | I49: 4Q'25 | J49: 1Q'26 | K49: 2Q'26 | L49: 3Q'26 | M49: 4Q'26
D51: Live Case | F51: =CHOOSE($H$4,F52,F53,F54) -> 143.283 | G51: =CHOOSE($H$4,G52,G53,G54) -> 145.484 | H51: =CHOOSE($H$4,H52,H53,H54) -> 125.396 | I51: =CHOOSE($H$4,I52,I53,I54) -> 145.357 | J51: =CHOOSE($H$4,J52,J53,J54) -> 123.1461 | K51: =CHOOSE($H$4,K52,K53,K54) -> 123.65301 | L51: =CHOOSE($H$4,L52,L53,L54) -> 107.50125 | M51: =CHOOSE($H$4,M52,M53,M54) -> 119.87844
C52: 1 | D52: Downside Case | F52: =IF($H$4=$C52,F$14,F52) -> 143.283 | G52: =IF($H$4=$C52,G$14,G52) -> 145.484 | H52: =IF($H$4=$C52,H$14,H52) -> 125.396 | I52: =IF($H$4=$C52,I$14,I52) -> 145.357 | J52: =IF($H$4=$C52,K$14,J52) -> 114.8958 | K52: =IF($H$4=$C52,L$14,K52) -> 115.97114 | L52: =IF($H$4=$C52,M$14,L52) -> 100.19918 | M52: =IF($H$4=$C52,N$14,M52) -> 112.57188
C53: 2 | D53: Base Case | F53: =IF($H$4=$C53,F$14,F53) -> 143.283 | G53: =IF($H$4=$C53,G$14,G53) -> 145.484 | H53: =IF($H$4=$C53,H$14,H53) -> 125.396 | I53: =IF($H$4=$C53,I$14,I53) -> 145.357 | J53: =IF($H$4=$C53,K$14,J53) -> 123.1461 | K53: =IF($H$4=$C53,L$14,K53) -> 123.65301 | L53: =IF($H$4=$C53,M$14,L53) -> 107.50125 | M53: =IF($H$4=$C53,N$14,M53) -> 119.87844
C54: 3 | D54: Upside Case | F54: =IF($H$4=$C54,F$14,F54) -> 143.283 | G54: =IF($H$4=$C54,G$14,G54) -> 145.484 | H54: =IF($H$4=$C54,H$14,H54) -> 125.396 | I54: =IF($H$4=$C54,I$14,I54) -> 145.357 | J54: =IF($H$4=$C54,K$14,J54) -> 126.37125 | K54: =IF($H$4=$C54,L$14,K54) -> 131.01112 | L54: =IF($H$4=$C54,M$14,L54) -> 125.396 | M54: =IF($H$4=$C54,N$14,M54) -> 145.357
D56: Adj. EBITDA
F57: 1Q'25 | G57: 2Q'25 | H57: 3Q'25 | I57: 4Q'25 | J57: 1Q'26 | K57: 2Q'26 | L57: 3Q'26 | M57: 4Q'26
D59: Live Case | F59: =CHOOSE($H$4,F60,F61,F62) -> 22.522 | G59: =CHOOSE($H$4,G60,G61,G62) -> 14.248 | H59: =CHOOSE($H$4,H60,H61,H62) -> 13.802 | I59: =CHOOSE($H$4,I60,I61,I62) -> 19.372 | J59: =CHOOSE($H$4,J60,J61,J62) -> 15.682794 | K59: =CHOOSE($H$4,K60,K61,K62) -> 13.051471 | L59: =CHOOSE($H$4,L60,L61,L62) -> 12.742667 | M59: =CHOOSE($H$4,M60,M61,M62) -> 13.413482
C60: 1 | D60: Downside Case | F60: =IF($H$4=$C60,F$28,F60) -> 22.522 | G60: =IF($H$4=$C60,G$28,G60) -> 14.248 | H60: =IF($H$4=$C60,H$28,H60) -> 13.802 | I60: =IF($H$4=$C60,I$28,I60) -> 19.372 | J60: =IF($H$4=$C60,K$28,J60) -> 9.640118 | K60: =IF($H$4=$C60,L$28,K60) -> 7.1609666 | L60: =IF($H$4=$C60,M$28,L60) -> 7.3660982 | M60: =IF($H$4=$C60,N$28,M60) -> 7.7261812
C61: 2 | D61: Base Case | F61: =IF($H$4=$C61,F$28,F61) -> 22.522 | G61: =IF($H$4=$C61,G$28,G61) -> 14.248 | H61: =IF($H$4=$C61,H$28,H61) -> 13.802 | I61: =IF($H$4=$C61,I$28,I61) -> 19.372 | J61: =IF($H$4=$C61,K$28,J61) -> 15.682794 | K61: =IF($H$4=$C61,L$28,K61) -> 13.051471 | L61: =IF($H$4=$C61,M$28,L61) -> 12.742667 | M61: =IF($H$4=$C61,N$28,M61) -> 13.413482
C62: 3 | D62: Upside Case | F62: =IF($H$4=$C62,F$28,F62) -> 22.522 | G62: =IF($H$4=$C62,G$28,G62) -> 14.248 | H62: =IF($H$4=$C62,H$28,H62) -> 13.802 | I62: =IF($H$4=$C62,I$28,I62) -> 19.372 | J62: =IF($H$4=$C62,K$28,J62) -> 17.379661 | K62: =IF($H$4=$C62,L$28,K62) -> 15.758721 | L62: =IF($H$4=$C62,M$28,L62) -> 19.121728 | M62: =IF($H$4=$C62,N$28,M62) -> 20.927392
D64: Liquidity
F65: 1Q'25 | G65: 2Q'25 | H65: 3Q'25 | I65: 4Q'25 | J65: 1Q'26 | K65: 2Q'26 | L65: 3Q'26 | M65: 4Q'26
D67: Live Case | F67: =CHOOSE($H$4,F68,F69,F70) -> 142.034 | G67: =CHOOSE($H$4,G68,G69,G70) -> 158.4 | H67: =CHOOSE($H$4,H68,H69,H70) -> 167.2 | I67: =CHOOSE($H$4,I68,I69,I70) -> 162.124 | J67: =CHOOSE($H$4,J68,J69,J70) -> 172.15123 | K67: =CHOOSE($H$4,K68,K69,K70) -> 149.62655 | L67: =CHOOSE($H$4,L68,L69,L70) -> 157.34334 | M67: =CHOOSE($H$4,M68,M69,M70) -> 165.71193
C68: 1 | D68: Downside Case (Existing Capital Structure) | F68: =IF(AND($H$4=$C68,'Liquidity Model'!$F$14=2),F$45,F68) -> 142.034 | G68: =IF(AND($H$4=$C68,'Liquidity Model'!$F$14=2),G$45,G68) -> 158.4 | H68: =IF(AND($H$4=$C68,'Liquidity Model'!$F$14=2),H$45,H68) -> 167.2 | I68: =IF(AND($H$4=$C68,'Liquidity Model'!$F$14=2),I$45,I68) -> 162.124 | J68: =IF(AND($H$4=$C68,'Liquidity Model'!$F$14=2),K$45,J68) -> 166.25258 | K68: =IF(AND($H$4=$C68,'Liquidity Model'!$F$14=2),L$45,K68) -> 137.97151 | L68: =IF(AND($H$4=$C68,'Liquidity Model'!$F$14=2),M$45,L68) -> 140.43921 | M68: =IF(AND($H$4=$C68,'Liquidity Model'!$F$14=2),N$45,M68) -> 143.24805
C69: 2 | D69: Base Case (Existing Capital Structure) | F69: =IF(AND($H$4=$C69,'Liquidity Model'!$F$14=2),F$45,F69) -> 142.034 | G69: =IF(AND($H$4=$C69,'Liquidity Model'!$F$14=2),G$45,G69) -> 158.4 | H69: =IF(AND($H$4=$C69,'Liquidity Model'!$F$14=2),H$45,H69) -> 167.2 | I69: =IF(AND($H$4=$C69,'Liquidity Model'!$F$14=2),I$45,I69) -> 162.124 | J69: =IF(AND($H$4=$C69,'Liquidity Model'!$F$14=2),K$45,J69) -> 172.15123 | K69: =IF(AND($H$4=$C69,'Liquidity Model'!$F$14=2),L$45,K69) -> 149.62655 | L69: =IF(AND($H$4=$C69,'Liquidity Model'!$F$14=2),M$45,L69) -> 157.34334 | M69: =IF(AND($H$4=$C69,'Liquidity Model'!$F$14=2),N$45,M69) -> 165.71193
C70: 1 | D70: Downside Case | F70: =IF(AND($H$4=$C70,'Liquidity Model'!$F$14=1),F$45,F70) -> 142.034 | G70: =IF(AND($H$4=$C70,'Liquidity Model'!$F$14=1),G$45,G70) -> 158.4 | H70: =IF(AND($H$4=$C70,'Liquidity Model'!$F$14=1),H$45,H70) -> 167.2 | I70: =IF(AND($H$4=$C70,'Liquidity Model'!$F$14=1),I$45,I70) -> 162.124 | J70: =IF(AND($H$4=$C70,'Liquidity Model'!$F$14=1),K$45,J70) -> 239.63385 | K70: =IF(AND($H$4=$C70,'Liquidity Model'!$F$14=1),L$45,K70) -> 209.13453 | L70: =IF(AND($H$4=$C70,'Liquidity Model'!$F$14=1),M$45,L70) -> 209.421 | M70: =IF(AND($H$4=$C70,'Liquidity Model'!$F$14=1),N$45,M70) -> 210.07599
C71: 2 | D71: Base Case | F71: =IF(AND($H$4=$C71,'Liquidity Model'!$F$14=1),F$45,F71) -> 142.034 | G71: =IF(AND($H$4=$C71,'Liquidity Model'!$F$14=1),G$45,G71) -> 158.4 | H71: =IF(AND($H$4=$C71,'Liquidity Model'!$F$14=1),H$45,H71) -> 167.2 | I71: =IF(AND($H$4=$C71,'Liquidity Model'!$F$14=1),I$45,I71) -> 162.124 | J71: =IF(AND($H$4=$C71,'Liquidity Model'!$F$14=1),K$45,J71) -> 245.53249 | K71: =IF(AND($H$4=$C71,'Liquidity Model'!$F$14=1),L$45,K71) -> 220.78957 | L71: =IF(AND($H$4=$C71,'Liquidity Model'!$F$14=1),M$45,L71) -> 226.32514 | M71: =IF(AND($H$4=$C71,'Liquidity Model'!$F$14=1),N$45,M71) -> 232.53986
D72: Liquidity Requirement | F72: 43 | G72: 43 | H72: 43 | I72: 43 | J72: 43 | K72: 43 | L72: 43 | M72: 43

Sheet Amend & Extend
C2: Traeger | H2: DRAFT
C3: Uptier + New Money Transaction Overview | H3: CONFIDENTIAL
C5: Existing Capital Structure
C6: RCF Outstanding | F6: ='Capital Structure'!G14 -> 0
C7: Receivables Financing Agreement Outstanding | F7: ='Capital Structure'!G15 -> 0
C8: 1L Outstanding | F8: ='Capital Structure'!G17 -> 403.325
C9: Cash Balance | F9: ='Capital Structure'!G32 -> 19.624
C10: FY'25 Adj. EBITDA | F10: ='Capital Structure'!G22 -> 69.969
C11: Extended Tranche RCF Capacity | F11: 82.5
C12: Non-Extended Tranche RCF Capacity | F12: 30
C14: Receivables Financing Agreement
C15: Receivables Financing Agreement Balance | F15: =F7 -> 0
C16: Receivables Financing Agreement Paydown | F16: =-F15 -> 0
C18: A&E Fees
C19: 1L TL Interest Margin Fee | F19: 0.005
C20: 1L TL One-Time Amendment Fee | F20: 0
C23: Illustrative Term Loan Value Summary | J23: Near-Term Debt Maturity Profile
F24: Pre-Trx. | G24: Trans. | H24: Post-Trx. | J24: Year | K24: Quarter | L24: Pre Transaction | M24: Post Transaction
F25: Amount | G25: Adj. | H25: Amount | J25: 2026 | K25: 2Q | L25: =$F$12 -> 30 | M25: =$F$12 -> 30
C26: 1L Senior Secured Term Loan | K26: 3Q
C27: Amendment Fee | F27: 0 | G27: =F20*F8 -> 0 | H27: =SUM(F27:G27) -> 0 | K27: 4Q
C28: Annualized Cash Interest(1) | F28: ='Capital Structure'!N17 -> 28.927397 | G28: =F19*F8 -> 2.016625 | H28: =SUM(F28:G28) -> 30.944022 | J28: 2027 | K28: 1Q
C29: Total 1L Interest + Fee | F29: =SUM(F27:F28) -> 28.927397 | G29: =SUM(G27:G28) -> 2.016625 | H29: =SUM(H27:H28) -> 30.944022 | K29: 2Q
K30: 3Q
K31: 4Q | L31: =$F$11 -> 82.5
C32: Cash Interest | F32: ='Capital Structure'!N18 -> 28.927397 | G32: =G28 -> 2.016625 | H32: =SUM(F32:G32) -> 30.944022 | J32: 2028 | K32: 1Q
K33: 2Q | L33: =$F$8 -> 403.325
K34: 3Q
K35: 4Q
J36: 2029 | K36: 1Q
K37: 2Q
K38: 3Q
K39: 4Q
J40: 2030 | K40: 1Q
K41: 2Q
K42: 3Q
K43: 4Q | M43: =$F$11 -> 82.5
J44: 2031 | K44: 1Q
K45: 2Q | M45: =$F$8 -> 403.325
J47: Near-Term Debt Maturity Profile
J48: Year | K48: Quarter | L48: Pre Transaction Term Loan | M48: Post Transaction Term Loan | N48: Pre Transaction RCF Capacity | O48: Post Transaction RCF Capacity | P48: Labels
J49: 2026 | K49: 2Q | L49: =$F$12 -> 30 | P49: =L49 -> 30
K50: 3Q
K51: 4Q
J52: 2027 | K52: 1Q
K53: 2Q
K54: 3Q
K55: 4Q | L55: =$F$11 -> 82.5 | P55: =L55 -> 82.5
J56: 2028 | K56: 1Q
K57: 2Q | L57: =$F$8 -> 403.325 | P57: =L57 -> 403.325
K58: 3Q
K59: 4Q
J60: 2029 | K60: 1Q
K61: 2Q
K62: 3Q
K63: 4Q
J64: 2030 | K64: 1Q
K65: 2Q
K66: 3Q
K67: 4Q | L67: =$F$11 -> 82.5 | P67: =L67 -> 82.5
J68: 2031 | K68: 1Q
K69: 2Q | L69: =$F$8 -> 403.325 | P69: =L69 -> 403.325
F78: Pre-Trx. | G78: Trans. | H78: Post-Trx.
F79: Amount | G79: Adj. | H79: Amount
C81: Receivables Financing Agreement Outstanding | F81: =F7 -> 0 | G81: =F16 -> 0 | H81: =SUM(F81:G81) -> 0
C82: RCF ($112.5mm) | F82: =F6 -> 0 | G82: 0 | H82: =SUM(F82:G82) -> 0
C83: 1L Term Loan | F83: =F8 -> 403.325 | G83: 0 | H83: =SUM(F83:G83) -> 403.325
C84: Total Debt | F84: =SUM(F81:F83) -> 403.325 | G84: =SUM(G81:G83) -> 0 | H84: =SUM(H81:H83) -> 403.325
C85: Total Leverage | F85: =F84/$F$90 -> 5.7643385 | G85: =H85-F85 -> 0 | H85: =H84/$F$90 -> 5.7643385
C87: Less: Cash and Equivalents | F87: =-F98 -> -19.624 | G87: =-G98 -> 0 | H87: =-H98 -> -19.624
C88: Net Debt | F88: =SUM(F87,F84) -> 383.701 | G88: =SUM(G87,G84) -> 0 | H88: =SUM(H87,H84) -> 383.701
C89: Net Leverage | F89: =F88/$F$90 -> 5.4838714 | G89: =H89-F89 -> 0 | H89: =H88/$F$90 -> 5.4838714
C90: Memo: FY'25 Adj. EBITDA | F90: =F10 -> 69.969 | H90: =F90 -> 69.969
C92: Liquidity
C93: Receivables Financing Agreement Capacity | F93: ='Capital Structure'!G29 -> 30 | G93: 0 | H93: =SUM(F93:G93) -> 30
C94: Less: Outstanding | F94: ='Capital Structure'!G30 -> 0 | G94: =-F16 -> 0 | H94: =SUM(F94:G94) -> 0
C95: RCF Capacity | F95: ='Capital Structure'!G27 -> 112.5 | G95: 0 | H95: =SUM(F95:G95) -> 112.5
C96: Less: Outstanding | F96: ='Capital Structure'!G28 -> 0 | G96: 0 | H96: =SUM(F96:G96) -> 0
C97: Credit Facility Availability | F97: =SUM(F93:F96) -> 142.5 | G97: =SUM(G93:G96) -> 0 | H97: =SUM(H93:H96) -> 142.5
C98: Plus: Cash and Equivalents | F98: ='Capital Structure'!G32 -> 19.624 | G98: 0 | H98: =SUM(F98:G98) -> 19.624
C99: Less: Min Liquidity Requirement(1) | F99: ='Capital Structure'!G33 -> -42.5 | G99: 0 | H99: =SUM(F99:G99) -> -42.5
C100: Total Liquidity | F100: =SUM(F97:F99) -> 119.624 | H100: =SUM(H97:H99) -> 119.624

Sheet Uptier + New Money
C2: Traeger | I2: DRAFT
C3: Uptier + New Money Transaction Overview | I3: CONFIDENTIAL
C5: Existing Capital Structure
C6: RCF Outstanding | F6: ='Capital Structure'!G14 -> 0
C7: Receivables Financing Agreement Outstanding | F7: ='Capital Structure'!G15 -> 0
C8: 1L Outstanding | F8: ='Capital Structure'!G17 -> 403.325
C9: Cash Balance | F9: ='Capital Structure'!G32 -> 19.624
C10: Cash to B/S - Post-Transaction | F10: =F18+F15 -> 75
C11: FY'25 Adj. EBITDA | F11: ='Capital Structure'!G22 -> 69.969
C13: Receivables Financing Agreement
C14: Receivables Financing Agreement Balance | F14: =F7 -> 0
C15: Receivables Financing Agreement Paydown | F15: =-MIN(MAX(F18,0),F14) -> 0
C17: New Money First Out 1L Term Loan
C18: New Money First Out 1L Term Loan | F18: 75
C19: Backstop Fee | F19: 0.1
C20: AHG | F20: 0.51
C22: New Second Out 1L Term Loan
C23: 1L TL Outstanding | F23: =F8 -> 403.325 | G23: =F23 -> 403.325
C24: Exchange Rate | F24: 0.9 | G24: 0.1 | H24: <-- Discount Capture
C25: New Second Out 1L Term Loan | F25: =F23*F24 -> 362.9925 | G25: =G23*G24 -> 40.3325
F29: Pre-Trx. | G29: Trans. | H29: Discount | I29: Post-Trx.
F30: Amount | G30: Adj. | H30: Capture | I30: Amount
C32: Receivables Financing Agreement Outstanding | F32: =F7 -> 0 | G32: =F15 -> 0 | H32: 0 | I32: =SUM(F32:H32) -> 0
C33: RCF ($112.5mm) | F33: =F6 -> 0 | G33: 0 | H33: 0 | I33: =SUM(F33:H33) -> 0
C34: New First-Out 1L Term Loan | F34: 0 | G34: =$F$18 -> 75 | H34: 0 | I34: =SUM(F34:H34) -> 75
C35: New Second-Out 1L Term Loan | F35: 0 | G35: =F25+$F$8*$F$20*$F$19 -> 383.56207 | H35: 0 | I35: =SUM(F35:H35) -> 383.56207
C36: 1L Term Loan | F36: =F8 -> 403.325 | G36: =-F25 -> -362.9925 | H36: =-G25 -> -40.3325 | I36: =SUM(F36:H36) -> 0
C37: Total Debt | F37: =SUM(F32:F36) -> 403.325 | G37: =SUM(G32:G36) -> 95.569575 | H37: =SUM(H32:H36) -> -40.3325 | I37: =SUM(I32:I36) -> 458.56207
C38: Total Leverage | F38: =F37/$F$43 -> 5.7643385 | G38: =I38-F38 -> 0.78945069 | H38: 0 | I38: =I37/$F$43 -> 6.5537892
C40: Less: Cash and Equivalents | F40: =-F51 -> -19.624 | G40: =-G51 -> -75 | H40: =-H51 -> 0 | I40: =-I51 -> -94.624
C41: Net Debt | F41: =SUM(F40,F37) -> 383.701 | G41: =SUM(G40,G37) -> 20.569575 | H41: =SUM(H40,H37) -> -40.3325 | I41: =SUM(I40,I37) -> 363.93808
C42: Net Leverage | F42: =F41/$F$43 -> 5.4838714 | G42: =I42-F42 -> -0.28245259 | H42: 0 | I42: =I41/$F$43 -> 5.2014188
C43: Memo: FY'25 Adj. EBITDA | F43: =F11 -> 69.969 | I43: =F43 -> 69.969
C45: Liquidity
C46: Receivables Financing Agreement Capacity | F46: ='Capital Structure'!G29 -> 30 | G46: 0 | H46: 0 | I46: =SUM(F46:G46) -> 30
C47: Less: Outstanding | F47: ='Capital Structure'!G30 -> 0 | G47: =-F15 -> 0 | H47: 0 | I47: =SUM(F47:G47) -> 0 | K47: Sources | O47: Uses
C48: RCF Capacity | F48: ='Capital Structure'!G27 -> 112.5 | G48: 0 | H48: 0 | I48: =SUM(F48:G48) -> 112.5 | K48: New First-Out 1L Term Loan | M48: =$F$18 -> 75 | O48: Pay Down Receivables Fin. Agmt. | Q48: =-F15 -> 0
C49: Less: Outstanding | F49: ='Capital Structure'!G28 -> 0 | G49: 0 | H49: 0 | I49: =SUM(F49:G49) -> 0 | K49: New Second-Out 1L Term Loan | M49: =I35 -> 383.56207 | O49: Extinguish 1L Term Loan | Q49: =F36 -> 403.325
C50: Credit Facility Availability | F50: =SUM(F46:F49) -> 142.5 | G50: =SUM(G46:G49) -> 0 | H50: 0 | I50: =SUM(I46:I49) -> 142.5 | K50: 1L Term Loan Discount Capture | M50: =G25 -> 40.3325 | O50: AHG Premium (2nd-Out TL) | Q50: =F19*F20*F8 -> 20.569575
C51: Plus: Cash and Equivalents | F51: ='Capital Structure'!G32 -> 19.624 | G51: =F10 -> 75 | H51: 0 | I51: =SUM(F51:G51) -> 94.624 | O51: Cash to Balance Sheet | Q51: =F10 -> 75
C52: Less: Min Liquidity Requirement(1) | F52: ='Capital Structure'!G33 -> -42.5 | G52: 0 | H52: 0 | I52: =SUM(F52:G52) -> -42.5 | K52: Total Sources | M52: =SUM(M48:M50) -> 498.89457 | O52: Total Uses | Q52: =M52 -> 498.89457
C53: Total Liquidity | F53: =SUM(F50:F52) -> 119.624 | I53: =SUM(I50:I52) -> 194.624

Sheet Uptier + New Money - Sensitize
C2: Traeger
C3: Implied Recovery
B5: x | C5: Existing Capital Structure | V5: Net Debt / LTM 2Q'25 Adj. EBITDA Sensitivity
C6: RCF Outstanding | D6: ='Capital Structure'!G14 -> 0 | J6: Table 1 - LIVE | M6: Discount Capture Sensitivity | V6: OLD - Don't use | X6: 1L Exchange Price
C7: Receivables Financing Agreement Outstanding | D7: ='Capital Structure'!G15 -> 0 | O7: 1L Exchange Price | W7: =F60 -> 5.2014188 | X7: =Y7-$V$18 -> 0.85 | Y7: =Z7-$V$18 -> 0.875 | Z7: 0.9 | AA7: =Z7+$V$18 -> 0.925 | AB7: =AA7+$V$18 -> 0.95
C8: 1L Outstanding | D8: ='Capital Structure'!G17 -> 403.325 | N8: =D61 -> 19.762925 | O8: =P8-$V$18 -> 0.85 | P8: =Q8-$V$18 -> 0.875 | Q8: 0.9 | R8: =Q8+$V$18 -> 0.925 | S8: =R8+$V$18 -> 0.95 | V8: New Money Amount | W8: 50 | X8: 4.9132019 | Y8: 5.0573104 | Z8: 5.2014188 | AA8: 5.3455273 | AB8: 5.4896358
C9: Cash Balance | D9: ='Capital Structure'!G32 -> 19.624 | M9: AHG Premium | N9: 0 | O9: 60.49875 | P9: 50.415625 | Q9: 40.3325 | R9: 30.249375 | S9: 20.16625 | W9: =W8+$V$20 -> 60 | X9: 4.9132019 | Y9: 5.0573104 | Z9: 5.2014188 | AA9: 5.3455273 | AB9: 5.4896358
C10: Cash to B/S Post-Transaction | D10: =D18+D15 -> 75 | F10: =D38+$D$15 -> 50 | G10: =H38+$D$15 -> 100 | N10: =N9+$V$19 -> 0.02 | O10: 56.384835 | P10: 46.30171 | Q10: 36.218585 | R10: 26.13546 | S10: 16.052335 | W10: =W9+$V$20 -> 70 | X10: 4.9132019 | Y10: 5.0573104 | Z10: 5.2014188 | AA10: 5.3455273 | AB10: 5.4896358
C11: FY'25 Adj. EBITDA | D11: ='Capital Structure'!G22 -> 69.969 | N11: =N10+$V$19 -> 0.04 | O11: 52.27092 | P11: 42.187795 | Q11: 32.10467 | R11: 22.021545 | S11: 11.93842 | W11: =W10+$V$20 -> 80 | X11: 4.9132019 | Y11: 5.0573104 | Z11: 5.2014188 | AA11: 5.3455273 | AB11: 5.4896358
N12: =N11+$V$19 -> 0.06 | O12: 48.157005 | P12: 38.07388 | Q12: 27.990755 | R12: 17.90763 | S12: 7.824505 | W12: =W11+$V$20 -> 90 | X12: 4.9132019 | Y12: 5.0573104 | Z12: 5.2014188 | AA12: 5.3455273 | AB12: 5.4896358
C13: Receivables Financing Agreement | N13: =N12+$V$19 -> 0.08 | O13: 44.04309 | P13: 33.959965 | Q13: 23.87684 | R13: 13.793715 | S13: 3.71059 | W13: =W12+$V$20 -> 100 | X13: 4.9132019 | Y13: 5.0573104 | Z13: 5.2014188 | AA13: 5.3455273 | AB13: 5.4896358
C14: Receivables Financing Agreement Balance | D14: =D7 -> 0 | N14: =N13+$V$19 -> 0.1 | O14: 39.929175 | P14: 29.84605 | Q14: 19.762925 | R14: 9.6798 | S14: -0.403325
C15: Receivables Financing Agreement Paydown | D15: =-MIN(MAX(D18,0),D14) -> 0
J16: Table 1 - Output | M16: Discount Capture Sensitivity
C17: New 1L Term Loan - Structurally Senior | O17: 1L Exchange Price
C18: New 1L Term Loan - Structurally Senior | D18: 75 | N18: 19.766012 | O18: 0.85 | P18: 0.875 | Q18: 0.9 | R18: 0.925 | S18: 0.95 | V18: 0.025 | W18: x-axis increment
M19: AHG Premium | N19: 0 | O19: 60.49875 | P19: 50.415625 | Q19: 40.3325 | R19: 30.249375 | S19: 20.16625 | V19: 0.02 | W19: AHG Premium increment
C20: New Second Out 1L Term Loan | D20: =D18+D24*D29*D30 -> 95.569575 | N20: 0.02 | O20: 56.384835 | P20: 46.30171 | Q20: 36.218585 | R20: 26.13546 | S20: 16.052335 | V20: 10 | W20: AHG Premium increment
N21: 0.04 | O21: 52.27092 | P21: 42.187795 | Q21: 32.10467 | R21: 22.021545 | S21: 11.93842
N22: 0.06 | O22: 48.157005 | P22: 38.07388 | Q22: 27.990755 | R22: 17.90763 | S22: 7.824505
C23: New Second Out 1L Term Loan | N23: 0.08 | O23: 44.04309 | P23: 33.959965 | Q23: 23.87684 | R23: 13.793715 | S23: 3.71059
C24: 1L TL Outstanding | D24: =D8 -> 403.325 | G24: =D24 -> 403.325 | N24: 0.1 | O24: 39.929175 | P24: 29.84605 | Q24: 19.762925 | R24: 9.6798 | S24: -0.403325
C25: % Repurchased | D25: 1
C26: Amount Repurchased | D26: =D24*D25 -> 403.325
C27: Exchange Rate | D27: 0.9 | G27: =1-D27 -> 0.1 | L27: Table 2 | M27: ="Net Debt / "&C11&" Sensitivity" -> Net Debt / FY'25 Adj. EBITDA Sensitivity
C28: New Second-Out 1L Term Loan Pre-Fee | D28: =D26*D27 -> 362.9925 | G28: =G24*G27 -> 40.3325 | H28: <-- Discount Capture | O28: 1L Exchange Price
C29: Backstop Fee | D29: 0.1 | N29: =F60 -> 5.2014188 | O29: =P29-$V$18 -> 0.85 | P29: =Q29-$V$18 -> 0.875 | Q29: 0.9 | R29: =Q29+$V$18 -> 0.925 | S29: =R29+$V$18 -> 0.95
C30: AHG % | D30: 0.51 | M30: AHG Premium | N30: 0 | O30: 4.6192207 | P30: 4.7633291 | Q30: 4.9074376 | R30: 5.051546 | S30: 5.1956545
C31: Backstop Fee | D31: =D24*D30*D29 -> 20.569575 | N31: =N30+$V$19 -> 0.02 | O31: 4.6780169 | P31: 4.8221254 | Q31: 4.9662338 | R31: 5.1103423 | S31: 5.2544508
C32: New Second-Out 1L Term Loan Post-Fee | D32: =D28+D31 -> 383.56207 | G32: =G28*G31 -> 0 | N32: =N31+$V$19 -> 0.04 | O32: 4.7368132 | P32: 4.8809216 | Q32: 5.0250301 | R32: 5.1691385 | S32: 5.313247
N33: =N32+$V$19 -> 0.06 | O33: 4.7956094 | P33: 4.9397179 | Q33: 5.0838263 | R33: 5.2279348 | S33: 5.3720433
N34: =N33+$V$19 -> 0.08 | O34: 4.8544057 | P34: 4.9985141 | Q34: 5.1426226 | R34: 5.2867311 | S34: 5.4308395
B35: x | N35: =N34+$V$19 -> 0.1 | O35: 4.9132019 | P35: 5.0573104 | Q35: 5.2014188 | R35: 5.3455273 | S35: 5.4896358
D38: 50 | F38: 75 | H38: 100
C39: Implied TEV | D39: 400 | E39: =D39+100 -> 500 | F39: 400 | G39: =F39+100 -> 500 | H39: 400 | I39: =H39+100 -> 500
C41: (+) Cash on balance sheet | D41: =$D$9+$D$10 -> 94.624 | E41: =$D$9+$D$10 -> 94.624 | F41: =$D$9+$D$10 -> 94.624 | G41: =$D$9+$D$10 -> 94.624 | H41: =$D$9+$D$10 -> 94.624 | I41: =$D$9+$D$10 -> 94.624
C42: Total distributable proceeds | D42: =D39+D41 -> 494.624 | E42: =E39+E41 -> 594.624 | F42: =F39+F41 -> 494.624 | G42: =G39+G41 -> 594.624 | H42: =H39+H41 -> 494.624 | I42: =I39+I41 -> 594.624
C43: Pre-Transaction Capital Structure
C44: Receivables Financing Agreement | D44: =$D$7 -> 0 | E44: =$D$7 -> 0 | F44: =$D$7 -> 0 | G44: =$D$7 -> 0 | H44: =$D$7 -> 0 | I44: =$D$7 -> 0
C45: RCF ($112.5mm) | D45: =$D$6 -> 0 | E45: =$D$6 -> 0 | F45: =$D$6 -> 0 | G45: =$D$6 -> 0 | H45: =$D$6 -> 0 | I45: =$D$6 -> 0
C46: 1L Term Loan | D46: =$D$8 -> 403.325 | E46: =$D$8 -> 403.325 | F46: =$D$8 -> 403.325 | G46: =$D$8 -> 403.325 | H46: =$D$8 -> 403.325 | I46: =$D$8 -> 403.325
C47: Total Debt | D47: =SUM(D44:D46) -> 403.325 | E47: =SUM(E44:E46) -> 403.325 | F47: =SUM(F44:F46) -> 403.325 | G47: =SUM(G44:G46) -> 403.325 | H47: =SUM(H44:H46) -> 403.325 | I47: =SUM(I44:I46) -> 403.325
C48: Less: Cash | D48: =-$D$9 -> -19.624 | E48: =-$D$9 -> -19.624 | F48: =-$D$9 -> -19.624 | G48: =-$D$9 -> -19.624 | H48: =-$D$9 -> -19.624 | I48: =-$D$9 -> -19.624
C49: Net Debt | D49: =SUM(D47:D48) -> 383.701 | E49: =SUM(E47:E48) -> 383.701 | F49: =SUM(F47:F48) -> 383.701 | G49: =SUM(G47:G48) -> 383.701 | H49: =SUM(H47:H48) -> 383.701 | I49: =SUM(I47:I48) -> 383.701
C50: Net Debt / FY'25 Adj. EBITDA | D50: =D49/$D$11 -> 5.4838714 | E50: =E49/$D$11 -> 5.4838714 | F50: =F49/$D$11 -> 5.4838714 | G50: =G49/$D$11 -> 5.4838714 | H50: =H49/$D$11 -> 5.4838714 | I50: =I49/$D$11 -> 5.4838714
C52: Post-Transaction Capital Structure
C53: Receivables Financing Agreement | D53: =$D$7+$D$15 -> 0 | E53: =$D$7+$D$15 -> 0 | F53: =$D$7+$D$15 -> 0 | G53: =$D$7+$D$15 -> 0 | H53: =$D$7+$D$15 -> 0 | I53: =$D$7+$D$15 -> 0
C54: RCF ($112.5mm) | D54: =D45 -> 0 | E54: =E45 -> 0 | F54: =F45 -> 0 | G54: =G45 -> 0 | H54: =H45 -> 0 | I54: =I45 -> 0
C55: New First-Out 1L Term Loan | D55: =$D$38 -> 50 | E55: =$D$38 -> 50 | F55: =$D$18 -> 75 | G55: =$F$38 -> 75 | H55: =$H$38 -> 100 | I55: =$H$38 -> 100
C56: New Second-Out 1L Term Loan | D56: =$D$32 -> 383.56207 | E56: =$D$32 -> 383.56207 | F56: =$D$32 -> 383.56207 | G56: =$D$32 -> 383.56207 | H56: =$D$32 -> 383.56207 | I56: =$D$32 -> 383.56207
C57: Total Debt | D57: =SUM(D53:D56) -> 433.56207 | E57: =SUM(E53:E56) -> 433.56207 | F57: =SUM(F53:F56) -> 458.56207 | G57: =SUM(G53:G56) -> 458.56207 | H57: =SUM(H53:H56) -> 483.56207 | I57: =SUM(I53:I56) -> 483.56207
C58: Less: Cash | D58: =-$D$9-$F$10 -> -69.624 | E58: =-$D$9-$F$10 -> -69.624 | F58: =-$D$9-$D$10 -> -94.624 | G58: =-$D$9-$D$10 -> -94.624 | H58: =-$D$9-$G$10 -> -119.624 | I58: =-$D$9-$G$10 -> -119.624
C59: Net Debt | D59: =SUM(D57:D58) -> 363.93808 | E59: =SUM(E57:E58) -> 363.93808 | F59: =SUM(F57:F58) -> 363.93808 | G59: =SUM(G57:G58) -> 363.93808 | H59: =SUM(H57:H58) -> 363.93808 | I59: =SUM(I57:I58) -> 363.93808
C60: Net Debt / FY'25 Adj. EBITDA | D60: =D59/$D$11 -> 5.2014188 | E60: =E59/$D$11 -> 5.2014188 | F60: =F59/$D$11 -> 5.2014188 | G60: =G59/$D$11 -> 5.2014188 | H60: =H59/$D$11 -> 5.2014188 | I60: =I59/$D$11 -> 5.2014188
C61: Implied Discount Capture | D61: =D46-D56 -> 19.762925 | E61: =E46-E56 -> 19.762925 | F61: =F46-F56 -> 19.762925 | G61: =G46-G56 -> 19.762925 | H61: =H46-H56 -> 19.762925 | I61: =I46-I56 -> 19.762925
C63: Post-Transaction Recovery ($)
C64: Receivables Financing Agreement | D64: =MIN((D$39-SUM(D$65:D65)),SUM(D54)) -> 0 | E64: =MIN((E$39-SUM(E$65:E65)),SUM(E54)) -> 0 | F64: =MIN((F$39-SUM(F$65:F65)),SUM(F54)) -> 0 | G64: =MIN((G$39-SUM(G$65:G65)),SUM(G54)) -> 0 | H64: =MIN((H$39-SUM(H$65:H65)),SUM(H54)) -> 0 | I64: =MIN((I$39-SUM(I$65:I65)),SUM(I54)) -> 0
C65: RCF ($112.5mm) | D65: =MIN(D54,D$39) -> 0 | E65: =MIN(E54,E$39) -> 0 | F65: =MIN(F54,F$39) -> 0 | G65: =MIN(G54,G$39) -> 0 | H65: =MIN(H54,H$39) -> 0 | I65: =MIN(I54,I$39) -> 0
C66: 1L Term Loan
C67: New First-Out 1L Term Loan | D67: =MIN((D$39-SUM(D$65:D66)),SUM(D55)) -> 50 | E67: =MIN((E$39-SUM(E$65:E66)),SUM(E55)) -> 50 | F67: =MIN((F$39-SUM(F$65:F66)),SUM(F55)) -> 75 | G67: =MIN((G$39-SUM(G$65:G66)),SUM(G55)) -> 75 | H67: =MIN((H$39-SUM(H$65:H66)),SUM(H55)) -> 100 | I67: =MIN((I$39-SUM(I$65:I66)),SUM(I55)) -> 100
C68: New Second-Out 1L Term Loan | D68: =MIN((D$39-SUM(D$65:D67)),SUM(D56)) -> 350 | E68: =MIN((E$39-SUM(E$65:E67)),SUM(E56)) -> 383.56207 | F68: =MIN((F$39-SUM(F$65:F67)),SUM(F56)) -> 325 | G68: =MIN((G$39-SUM(G$65:G67)),SUM(G56)) -> 383.56207 | H68: =MIN((H$39-SUM(H$65:H67)),SUM(H56)) -> 300 | I68: =MIN((I$39-SUM(I$65:I67)),SUM(I56)) -> 383.56207
C69: Total Debt | D69: =SUM(D64:D68) -> 400 | E69: =SUM(E64:E68) -> 433.56207 | F69: =SUM(F64:F68) -> 400 | G69: =SUM(G64:G68) -> 458.56207 | H69: =SUM(H64:H68) -> 400 | I69: =SUM(I64:I68) -> 483.56207
C71: Post-Transaction Recovery (%) / Implied Price ($)
C72: Receivables Financing Agreement | D72: =IF(D53>0,D64/D53*100,0) -> 0 | E72: =IF(E53>0,E64/E53*100,0) -> 0 | F72: =IF(F53>0,F64/F53*100,0) -> 0 | G72: =IF(G53>0,G64/G53*100,0) -> 0 | H72: =IF(H53>0,H64/H53*100,0) -> 0 | I72: =IF(I53>0,I64/I53*100,0) -> 0
C73: RCF ($112.5mm) | D73: =IF(D54>0,D65/D54*100,0) -> 0 | E73: =IF(E54>0,E65/E54*100,0) -> 0 | F73: =IF(F54>0,F65/F54*100,0) -> 0 | G73: =IF(G54>0,G65/G54*100,0) -> 0 | H73: =IF(H54>0,H65/H54*100,0) -> 0 | I73: =IF(I54>0,I65/I54*100,0) -> 0
C74: 1L Term Loan
C75: New First-Out 1L Term Loan | D75: =D67/D55*100 -> 100 | E75: =E67/E55*100 -> 100 | F75: =F67/F55*100 -> 100 | G75: =G67/G55*100 -> 100 | H75: =H67/H55*100 -> 100 | I75: =I67/I55*100 -> 100
C76: New Second-Out 1L Term Loan(1) | D76: =D68/D46*100 -> 86.778652 | E76: =E68/E46*100 -> 95.1 | F76: =F68/F46*100 -> 80.580177 | G76: =G68/G46*100 -> 95.1 | H76: =H68/H46*100 -> 74.381702 | I76: =I68/I46*100 -> 95.1
B77: x | C77: Day 1 AHG Recovery(1) | D77: =D95*100 -> 91.249897 | E77: =E95*100 -> 100 | F77: =F95*100 -> 84.732048 | G77: =G95*100 -> 100 | H77: =H95*100 -> 78.214198 | I77: =I95*100 -> 100
C79: AHG
C80: FO 1L TL
C81: SO 1L TL | D81: =$D$28*$D$30 -> 185.12618 | E81: =$D$28*$D$30 -> 185.12618 | F81: =$D$28*$D$30 -> 185.12618 | G81: =$D$28*$D$30 -> 185.12618 | H81: =$D$28*$D$30 -> 185.12618 | I81: =$D$28*$D$30 -> 185.12618
C82: SO 1L TL Fee | D82: =$D$31 -> 20.569575 | E82: =$D$31 -> 20.569575 | F82: =$D$31 -> 20.569575 | G82: =$D$31 -> 20.569575 | H82: =$D$31 -> 20.569575 | I82: =$D$31 -> 20.569575
C83: SO 1L TL Total | D83: =SUM(D81:D82) -> 205.69575 | E83: =SUM(E81:E82) -> 205.69575 | F83: =SUM(F81:F82) -> 205.69575 | G83: =SUM(G81:G82) -> 205.69575 | H83: =SUM(H81:H82) -> 205.69575 | I83: =SUM(I81:I82) -> 205.69575
C84: AHG Total | D84: =D83+D80 -> 205.69575 | E84: =E83+E80 -> 205.69575 | F84: =F83+F80 -> 205.69575 | G84: =G83+G80 -> 205.69575 | H84: =H83+H80 -> 205.69575 | I84: =I83+I80 -> 205.69575
C86: AHG Ownerishp %
C87: FO 1L TL | D87: =D80/D55 -> 0 | E87: =E80/E55 -> 0 | F87: =F80/F55 -> 0 | G87: =G80/G55 -> 0 | H87: =H80/H55 -> 0 | I87: =I80/I55 -> 0
C88: SO 1L TL | D88: =D83/D56 -> 0.5362776 | E88: =E83/E56 -> 0.5362776 | F88: =F83/F56 -> 0.5362776 | G88: =G83/G56 -> 0.5362776 | H88: =H83/H56 -> 0.5362776 | I88: =I83/I56 -> 0.5362776
C90: AHG Recovery
C91: FO 1L TL | D91: =D67*D87 -> 0 | E91: =E67*E87 -> 0 | F91: =F67*F87 -> 0 | G91: =G67*G87 -> 0 | H91: =H67*H87 -> 0 | I91: =I67*I87 -> 0
C92: SO 1L TL | D92: =D88*D68 -> 187.69716 | E92: =E88*E68 -> 205.69575 | F92: =F88*F68 -> 174.29022 | G92: =G88*G68 -> 205.69575 | H92: =H88*H68 -> 160.88328 | I92: =I88*I68 -> 205.69575
C93: Total | D93: =SUM(D91:D92) -> 187.69716 | E93: =SUM(E91:E92) -> 205.69575 | F93: =SUM(F91:F92) -> 174.29022 | G93: =SUM(G91:G92) -> 205.69575 | H93: =SUM(H91:H92) -> 160.88328 | I93: =SUM(I91:I92) -> 205.69575
C95: AHG Recovery Total | D95: =D93/(D46*$D$30) -> 0.91249897 | E95: =E93/(E46*$D$30) -> 1 | F95: =F93/(F46*$D$30) -> 0.84732048 | G95: =G93/(G46*$D$30) -> 1 | H95: =H93/(H46*$D$30) -> 0.78214198 | I95: =I93/(I46*$D$30) -> 1
B99: x

Sheet Uptier + New Money - Interest
C2: Traeger | R2: DRAFT
C3: Tansaction Interest Calculation | R3: CONFIDENTIAL
C5: Existing Capital Structure | G5: Orig. Rate | H5: Trx Adj. | J5: New Rate
C6: RCF Outstanding | F6: ='Capital Structure'!G14 -> 0 | G6: ='Capital Structure'!H14 -> 350 | H6: 0 | J6: =G6+H6 -> 350
C7: Receivables Financing Agreement Outstanding | F7: ='Capital Structure'!G15 -> 0 | G7: ='Capital Structure'!H15 -> 200 | H7: 0 | J7: =G7+H7 -> 200
C8: 1L Outstanding | F8: ='Capital Structure'!G17 -> 403.325 | G8: ='Capital Structure'!H17 -> 350 | H8: 100 | J8: =G8+H8 -> 450
C9: Cash Balance | F9: ='Capital Structure'!G32 -> 19.624
C10: Cash to B/S - Post-Transaction | F10: =F18+F15 -> 75
C11: FY'25 Adj. EBITDA | F11: ='Capital Structure'!G22 -> 69.969
C13: Receivables Financing Agreement | S13: Cumulative Interest
C14: Receivables Financing Agreement Balance | F14: =F7 -> 0
C15: Receivables Financing Agreement Paydown | F15: =-MIN(MAX(F18,0),F14) -> 0
C17: New Money First Out 1L Term Loan | J17: New Rate
C18: New Money First Out 1L Term Loan | F18: 75 | J18: 500
C19: Backstop Fee | F19: 0.1
C20: AHG | F20: 0.51
C22: New Second Out 1L Term Loan
C23: 1L TL Outstanding | F23: =F8 -> 403.325 | G23: =F23 -> 403.325
C24: Exchange Rate | F24: 0.9 | G24: 0.1 | H24: <-- Discount Capture
C25: New Second-Out 1L Term Loan | F25: =F23*F24 -> 362.9925 | G25: =G23*G24 -> 40.3325
P26: 1 Month SOFR as of 09/10/2025
P27: 0.0437041
F29: Pre-Trx. | G29: Trans. | H29: Post-Trx. | J29: Rate | M29: Maturity | P29: Annual Cash Interest
C30: Capital Structure | F30: Amount | G30: Adj. | H30: Amount | J30: Pre-Trx. | K30: Post-Trx. | M30: Pre-Trx. | N30: Post-Trx. | P30: Pre-Trx. | Q30: Post-Trx.
C32: Receivables Financing Agreement Outstanding | F32: =F7 -> 0 | G32: =F15 -> 0 | H32: =SUM(F32:G32) -> 0 | J32: =G7 -> 200 | K32: =J7 -> 200 | M32: 46605 | N32: 46605 | P32: =F32*((J32/10000)+$P$27) -> 0 | Q32: =H32*((K32/10000)+$P$27) -> 0
C33: RCF ($112.5mm) | F33: =F6 -> 0 | G33: 0 | H33: =SUM(F33:G33) -> 0 | J33: =G6 -> 350 | K33: =J6 -> 350 | M33: 46202 | N33: =EOMONTH(M33,36) -> 47299 | P33: =F33*((J33/10000)+$P$27) -> 0 | Q33: =H33*((K33/10000)+$P$27) -> 0
C34: New First-Out 1L Term Loan | F34: 0 | G34: =$F$18 -> 75 | H34: =SUM(F34:G34) -> 75 | J34: 0 | K34: =J18 -> 500 | M34: 0 | N34: 48028 | P34: =F34*((J34/10000)+$P$27) -> 0 | Q34: =H34*((K34/10000)+$P$27) -> 7.0278075
C35: New Second-Out 1L Term Loan | F35: 0 | G35: =F25+$F$8*$F$20*$F$19 -> 383.56207 | H35: =SUM(F35:G35) -> 383.56207 | J35: 0 | K35: =J8 -> 450 | M35: 0 | N35: 48028 | P35: =F35*((J35/10000)+$P$27) -> 0 | Q35: =H35*((K35/10000)+$P$27) -> 34.023529
C36: 1L Term Loan | F36: =F8 -> 403.325 | G36: =-F25-G25 -> -403.325 | H36: =SUM(F36:G36) -> 0 | J36: =G8 -> 350 | K36: 0 | M36: 46933 | N36: 0 | P36: =F36*((J36/10000)+$P$27) -> 31.743331 | Q36: =H36*((K36/10000)+$P$27) -> 0
C37: Total Debt | F37: =SUM(F32:F36) -> 403.325 | G37: =SUM(G32:G36) -> 55.237075 | H37: =SUM(H32:H36) -> 458.56207 | P37: =SUM(P32:P36) -> 31.743331 | Q37: =SUM(Q32:Q36) -> 41.051336
C39: Less: Cash and Equivalents | F39: =-F9 -> -19.624 | G39: =-F10 -> -75 | H39: =SUM(F39:G39) -> -94.624
C40: Net Debt | F40: =SUM(F39,F37) -> 383.701 | G40: =SUM(G39,G37) -> -19.762925 | H40: =SUM(H39,H37) -> 363.93808
C45: Interest Projections
C47: Quarter Ended | H47: 46112 | I47: =EOMONTH(H47,3) -> 46203 | J47: =EOMONTH(I47,3) -> 46295 | K47: =EOMONTH(J47,3) -> 46387 | L47: =EOMONTH(K47,3) -> 46477 | M47: =EOMONTH(L47,3) -> 46568 | N47: =EOMONTH(M47,3) -> 46660 | O47: =EOMONTH(N47,3) -> 46752 | P47: =EOMONTH(O47,3) -> 46843 | ... AC47: =EOMONTH(AB47,3) -> 48029
C48: Year | H48: =YEAR(H47) -> 2026 | I48: =YEAR(I47) -> 2026 | J48: =YEAR(J47) -> 2026 | K48: =YEAR(K47) -> 2026 | L48: =YEAR(L47) -> 2027 | M48: =YEAR(M47) -> 2027 | N48: =YEAR(N47) -> 2027 | O48: =YEAR(O47) -> 2027 | ... AC48: =YEAR(AC47) -> 2031
C49: Quarter | H49: 1Q'26 | I49: 2Q'26 | J49: 3Q'26 | K49: 4Q'26 | L49: 1Q'27 | M49: 2Q'27 | N49: 3Q'27 | O49: 4Q'27 | P49: 1Q'28 | Q49: 2Q'28 | R49: 3Q'28 | S49: 4Q'28 | T49: 1Q'29 | U49: 2Q'29 | V49: 3Q'29 | W49: 4Q'29 | X49: 1Q'30 | Y49: 2Q'30 | Z49: 3Q'30 | AA49: 4Q'30 | AB49: 1Q'31 | AC49: 2Q'31
C51: SOFR Curve | H51: =_xlfn.XLOOKUP(H47,$C$71:$C$190,$D$71:$D$190,,-1) -> 0.0347 | I51: =_xlfn.XLOOKUP(I47,$C$71:$C$190,$D$71:$D$190,,-1) -> 0.0323 | J51: =_xlfn.XLOOKUP(J47,$C$71:$C$190,$D$71:$D$190,,-1) -> 0.0293 | K51: =_xlfn.XLOOKUP(K47,$C$71:$C$190,$D$71:$D$190,,-1) -> 0.0293 | L51: =_xlfn.XLOOKUP(L47,$C$71:$C$190,$D$71:$D$190,,-1) -> 0.0287 | M51: =_xlfn.XLOOKUP(M47,$C$71:$C$190,$D$71:$D$190,,-1) -> 0.0286 | N51: =_xlfn.XLOOKUP(N47,$C$71:$C$190,$D$71:$D$190,,-1) -> 0.0296 | O51: =_xlfn.XLOOKUP(O47,$C$71:$C$190,$D$71:$D$190,,-1) -> 0.0297 | ... AC51: =_xlfn.XLOOKUP(AC47,$C$71:$C$190,$D$71:$D$190,,-1) -> 0.0351
C53: Pre-Trx.
C54: Receivables Financing Agreement Outstanding | F54: =F32 -> 0 | G54: =J32 -> 200 | H54: =($F54*(($G54/10000)+H$51))/4 -> 0 | I54: =($F54*(($G54/10000)+I$51))/4 -> 0 | J54: =($F54*(($G54/10000)+J$51))/4 -> 0 | K54: =($F54*(($G54/10000)+K$51))/4 -> 0 | L54: =($F54*(($G54/10000)+L$51))/4 -> 0 | M54: =($F54*(($G54/10000)+M$51))/4 -> 0 | N54: =($F54*(($G54/10000)+N$51))/4 -> 0 | O54: =($F54*(($G54/10000)+O$51))/4 -> 0 | ... AC54: =($F54*(($G54/10000)+AC$51))/4 -> 0
C55: RCF ($112.5mm) | F55: =F33 -> 0 | G55: =J33 -> 350 | H55: =($F55*(($G55/10000)+H$51))/4 -> 0 | I55: =($F55*(($G55/10000)+I$51))/4 -> 0 | J55: =($F55*(($G55/10000)+J$51))/4 -> 0 | K55: =($F55*(($G55/10000)+K$51))/4 -> 0 | L55: =($F55*(($G55/10000)+L$51))/4 -> 0 | M55: =($F55*(($G55/10000)+M$51))/4 -> 0 | N55: =($F55*(($G55/10000)+N$51))/4 -> 0 | O55: =($F55*(($G55/10000)+O$51))/4 -> 0 | ... AC55: =($F55*(($G55/10000)+AC$51))/4 -> 0
C56: 1L Term Loan | F56: =F36 -> 403.325 | G56: =J36 -> 350 | H56: =($F56*(($G56/10000)+H$51))/4 -> 7.0279381 | I56: =($F56*(($G56/10000)+I$51))/4 -> 6.7859431 | J56: =($F56*(($G56/10000)+J$51))/4 -> 6.4834494 | K56: =($F56*(($G56/10000)+K$51))/4 -> 6.4834494 | L56: =($F56*(($G56/10000)+L$51))/4 -> 6.4229506 | M56: =($F56*(($G56/10000)+M$51))/4 -> 6.4128675 | N56: =($F56*(($G56/10000)+N$51))/4 -> 6.5136988 | O56: =($F56*(($G56/10000)+O$51))/4 -> 6.5237819 | ... AC56: =($F56*(($G56/10000)+AC$51))/4 -> 7.0682706
C57: Pre-Trx. Cumulative Interest | H57: =SUM(H54:H56) -> 7.0279381 | I57: =H57+SUM(I54:I56) -> 13.813881 | J57: =I57+SUM(J54:J56) -> 20.297331 | K57: =J57+SUM(K54:K56) -> 26.78078 | L57: =K57+SUM(L54:L56) -> 33.203731 | M57: =L57+SUM(M54:M56) -> 39.616598 | N57: =M57+SUM(N54:N56) -> 46.130297 | O57: =N57+SUM(O54:O56) -> 52.654079 | P57: =O57+SUM(P54:P56) -> 59.177861 | ... AC57: =AB57+SUM(AC54:AC56) -> 148.09086
C59: Post-Trx.
C60: Receivables Financing Agreement Outstanding | F60: =H32 -> 0 | G60: =K32 -> 200 | H60: =($F60*(($G60/10000)+H$51))/4 -> 0 | I60: =($F60*(($G60/10000)+I$51))/4 -> 0 | J60: =($F60*(($G60/10000)+J$51))/4 -> 0 | K60: =($F60*(($G60/10000)+K$51))/4 -> 0 | L60: =($F60*(($G60/10000)+L$51))/4 -> 0 | M60: =($F60*(($G60/10000)+M$51))/4 -> 0 | N60: =($F60*(($G60/10000)+N$51))/4 -> 0 | O60: =($F60*(($G60/10000)+O$51))/4 -> 0 | ... AC60: =($F60*(($G60/10000)+AC$51))/4 -> 0
C61: RCF ($112.5mm) | F61: =H33 -> 0 | G61: =K33 -> 350 | H61: =($F61*(($G61/10000)+H$51))/4 -> 0 | I61: =($F61*(($G61/10000)+I$51))/4 -> 0 | J61: =($F61*(($G61/10000)+J$51))/4 -> 0 | K61: =($F61*(($G61/10000)+K$51))/4 -> 0 | L61: =($F61*(($G61/10000)+L$51))/4 -> 0 | M61: =($F61*(($G61/10000)+M$51))/4 -> 0 | N61: =($F61*(($G61/10000)+N$51))/4 -> 0 | O61: =($F61*(($G61/10000)+O$51))/4 -> 0 | ... AC61: =($F61*(($G61/10000)+AC$51))/4 -> 0
C62: New First Out 1L Term Loan | F62: =H34 -> 75 | G62: =K34 -> 500 | H62: =($F62*(($G62/10000)+H$51))/4 -> 1.588125 | I62: =($F62*(($G62/10000)+I$51))/4 -> 1.543125 | J62: =($F62*(($G62/10000)+J$51))/4 -> 1.486875 | K62: =($F62*(($G62/10000)+K$51))/4 -> 1.486875 | L62: =($F62*(($G62/10000)+L$51))/4 -> 1.475625 | M62: =($F62*(($G62/10000)+M$51))/4 -> 1.47375 | N62: =($F62*(($G62/10000)+N$51))/4 -> 1.4925 | O62: =($F62*(($G62/10000)+O$51))/4 -> 1.494375 | ... AC62: =($F62*(($G62/10000)+AC$51))/4 -> 1.595625
C63: New Second Out 1L Term Loan | F63: =H35 -> 383.56207 | G63: =K35 -> 450 | H63: =($F63*(($G63/10000)+H$51))/4 -> 7.6424743 | I63: =($F63*(($G63/10000)+I$51))/4 -> 7.4123371 | J63: =($F63*(($G63/10000)+J$51))/4 -> 7.1246655 | K63: =($F63*(($G63/10000)+K$51))/4 -> 7.1246655 | L63: =($F63*(($G63/10000)+L$51))/4 -> 7.0671312 | M63: =($F63*(($G63/10000)+M$51))/4 -> 7.0575422 | N63: =($F63*(($G63/10000)+N$51))/4 -> 7.1534327 | O63: =($F63*(($G63/10000)+O$51))/4 -> 7.1630218 | ... AC63: =($F63*(($G63/10000)+AC$51))/4 -> 7.6808306
C64: Post-Trx. Cumulative Interest | H64: =SUM(H60:H63) -> 9.2305993 | I64: =H64+SUM(I60:I63) -> 18.186061 | J64: =I64+SUM(J60:J63) -> 26.797602 | K64: =J64+SUM(K60:K63) -> 35.409143 | L64: =K64+SUM(L60:L63) -> 43.951899 | M64: =L64+SUM(M60:M63) -> 52.483191 | N64: =M64+SUM(N60:N63) -> 61.129124 | O64: =N64+SUM(O60:O63) -> 69.78652 | P64: =O64+SUM(P60:P63) -> 78.443917 | ... AC64: =AB64+SUM(AC60:AC63) -> 195.65594
C66: Delta for Chart Output | H66: =H64-H57 -> 2.2026612 | I66: =I64-I57 -> 4.3721802 | J66: =J64-J57 -> 6.5002714 | K66: =K64-K57 -> 8.6283625 | L66: =L64-L57 -> 10.748168 | M66: =M64-M57 -> 12.866593 | N66: =N64-N57 -> 14.998827 | O66: =O64-O57 -> 17.132442 | ... AC66: =AC64-AC57 -> 47.565087
C67: Annual Interest Rate Delta | K67: =-SUM(H54:K56)+SUM(H60:K63) -> 8.6283625 | O67: =-SUM(L54:O56)+SUM(L60:O63) -> 8.5040791 | S67: =-SUM(P54:S56)+SUM(P60:S63) -> 8.5772682 | W67: =-SUM(T54:W56)+SUM(T60:W63) -> 8.6684094 | AA67: =-SUM(X54:AA56)+SUM(X60:AA63) -> 8.770598 | AC67: =-SUM(Z54:AC56)+SUM(Z60:AC63) -> 8.8285969
C68: Average Annual Interest Rate Delta | E68: =AVERAGE(K67,O67,S67,W67,AA67,AC67) -> 8.6628857
C70: Date | D70: 1-Month Forward SOFR Curve
C71: 45910 | D71: 0.0417
C72: 45940 | D72: 0.0402
C73: 45971 | D73: 0.039
C74: 46001 | D74: 0.0373
C75: 46032 | D75: 0.0363
C76: 46063 | D76: 0.0356
C77: 46091 | D77: 0.0347
C78: 46122 | D78: 0.0339
C79: 46152 | D79: 0.0334
C80: 46183 | D80: 0.0323
C81: 46213 | D81: 0.0315
C82: 46244 | D82: 0.0309
... C190: 49531 | D190: 0.0413

Sheet Drop-Down
D3: Traeger | AD3: DRAFT
D4: Drop-Down Transaction | AD4: CONFIDENTIAL
D5: Data as of 1Q25
D7: Inputs | Q7: ($ Millions) | Z7: UnSub Loan Amount
D8: Print Format | H8: 1 | Q8: Illust. Value of Assets Transferred to UnSub | U8: A | V8: =H9 -> 280 | Y8: =V15 -> 0.5 | Z8: 100 | AA8: =Z8+50 -> 150 | AB8: =AA8+50 -> 200 | AC8: =AB8+50 -> 250 | AD8: =AC8+50 -> 300
D9: UnSub Capacity | H9: 280 | Y9: 0.5 | Z9: 0.3030303 | AA9: 0.42253521 | AB9: 0.52631579 | AC9: 0.61728395 | AD9: 0.69767442
D10: 1L Pari Claim | H10: 200 | Q10: Illust. UnSub Loan / I/C Loan Amount | U10: B | V10: 200 | X10: Illust. | Y10: 0.55 | Z10: 0.29850746 | AA10: 0.4137931 | AB10: 0.51282051 | AC10: 0.5988024 | AD10: 0.6741573
D11: Trading Price | H11: 89 | Q11: Illust. I/C Loan Recovery % | V11: 0.6 | X11: I/C | Y11: 0.6 | Z11: 0.29411765 | AA11: 0.40540541 | AB11: 0.5 | AC11: 0.58139535 | AD11: 0.65217391
Q12: Illust. Incremental Collateral Value | U12: C | V12: =V10*V11 -> 120 | X12: Loan | Y12: 0.65 | Z12: 0.28985507 | AA12: 0.39735099 | AB12: 0.48780488 | AC12: 0.56497175 | AD12: 0.63157895
X13: Rcvry. % | Y13: 0.7 | Z13: 0.28571429 | AA13: 0.38961039 | AB13: 0.47619048 | AC13: 0.54945055 | AD13: 0.6122449
Q14: UnSub New Money Collateral Value | U14: A + C = D | V14: =V8+V12 -> 400 | Y14: 0.75 | Z14: 0.28169014 | AA14: 0.38216561 | AB14: 0.46511628 | AC14: 0.53475936 | AD14: 0.59405941
Q15: Implied LTV % | U15: B / D | V15: =V10/V14 -> 0.5
D17: Total TEV Sensitivity | H17: 450 | I17: =H17+50 -> 500 | J17: =I17+50 -> 550 | K17: =J17+50 -> 600 | L17: =K17+50 -> 650 | M17: =L17+50 -> 700 | N17: =M17+50 -> 750
D19: Implied TEVs
D20: Implied RemainCo TEV | H20: =H$17/$K$17*$K20 -> 240 | I20: =I$17/$K$17*$K20 -> 266.66667 | J20: =J$17/$K$17*$K20 -> 293.33333 | K20: =K17-K21 -> 320 | L20: =L$17/$K$17*$K20 -> 346.66667 | M20: =M$17/$K$17*$K20 -> 373.33333 | N20: =N$17/$K$17*$K20 -> 400
D21: Implied UnSub TEV | H21: =H$17/$K$17*$K21 -> 210 | I21: =I$17/$K$17*$K21 -> 233.33333 | J21: =J$17/$K$17*$K21 -> 256.66667 | K21: =H9 -> 280 | L21: =L$17/$K$17*$K21 -> 303.33333 | M21: =M$17/$K$17*$K21 -> 326.66667 | N21: =N$17/$K$17*$K21 -> 350
D23: RemainCo Claims
D24: 1L Term Loan | H24: 403.6 | I24: =H24 -> 403.6 | J24: =I24 -> 403.6 | K24: =I24 -> 403.6 | L24: =K24 -> 403.6 | M24: =L24 -> 403.6 | N24: =M24 -> 403.6
D25: 1L Double Dip to UnSub | H25: =$H$10 -> 200 | I25: =$H$10 -> 200 | J25: =$H$10 -> 200 | K25: =$H$10 -> 200 | L25: =$H$10 -> 200 | M25: =$H$10 -> 200 | N25: =$H$10 -> 200
D27: RemainCo Recovery Waterfall
D28: 1L Term Loan | H28: =H$20*(H24/SUM(H$24:H$25)) -> 160.47714 | I28: =I$20*(I24/SUM(I$24:I$25)) -> 178.30793 | J28: =J$20*(J24/SUM(J$24:J$25)) -> 196.13872 | K28: =K$20*(K24/SUM(K$24:K$25)) -> 213.96952 | L28: =L$20*(L24/SUM(L$24:L$25)) -> 231.80031 | M28: =M$20*(M24/SUM(M$24:M$25)) -> 249.6311 | N28: =N$20*(N24/SUM(N$24:N$25)) -> 267.4619
D29: 1L Double Dip to UnSub | H29: =H$20*(H25/SUM(H$24:H$25)) -> 79.522863 | I29: =I$20*(I25/SUM(I$24:I$25)) -> 88.358736 | J29: =J$20*(J25/SUM(J$24:J$25)) -> 97.19461 | K29: =K$20*(K25/SUM(K$24:K$25)) -> 106.03048 | L29: =L$20*(L25/SUM(L$24:L$25)) -> 114.86636 | M29: =M$20*(M25/SUM(M$24:M$25)) -> 123.70223 | N29: =N$20*(N25/SUM(N$24:N$25)) -> 132.5381
D31: UnSub Collateral Value
D32: UnSub TEV | H32: =H21 -> 210 | I32: =I21 -> 233.33333 | J32: =J21 -> 256.66667 | K32: =K21 -> 280 | L32: =L21 -> 303.33333 | M32: =M21 -> 326.66667 | N32: =N21 -> 350
D33: Double Dip Claim | H33: =H29 -> 79.522863 | I33: =I29 -> 88.358736 | J33: =J29 -> 97.19461 | K33: =K29 -> 106.03048 | L33: =L29 -> 114.86636 | M33: =M29 -> 123.70223 | N33: =N29 -> 132.5381
D34: Total UnSub Collateral Value | H34: =SUM(H32:H33) -> 289.52286 | I34: =SUM(I32:I33) -> 321.69207 | J34: =SUM(J32:J33) -> 353.86128 | K34: =SUM(K32:K33) -> 386.03048 | L34: =SUM(L32:L33) -> 418.19969 | M34: =SUM(M32:M33) -> 450.3689 | N34: =SUM(N32:N33) -> 482.5381
D36: Current Trading Price Implied Recovery
D37: 1L Term Loan | H37: =$H$11/100 -> 0.89 | I37: =$H$11/100 -> 0.89 | J37: =$H$11/100 -> 0.89 | K37: =$H$11/100 -> 0.89 | L37: =$H$11/100 -> 0.89 | M37: =$H$11/100 -> 0.89 | N37: =$H$11/100 -> 0.89
D39: Pro Forma RemainCo Implied Recovery
D40: 1L Term Loan | H40: =H28/H24 -> 0.39761431 | I40: =I28/I24 -> 0.44179368 | J40: =J28/J24 -> 0.48597305 | K40: =K28/K24 -> 0.53015242 | L40: =L28/L24 -> 0.57433179 | M40: =M28/M24 -> 0.61851116 | N40: =N28/N24 -> 0.66269052
D41: 1L Double Dip to UnSub | H41: =H29/H25 -> 0.39761431 | I41: =I29/I25 -> 0.44179368 | J41: =J29/J25 -> 0.48597305 | K41: =K29/K25 -> 0.53015242 | L41: =L29/L25 -> 0.57433179 | M41: =M29/M25 -> 0.61851116 | N41: =N29/N25 -> 0.66269052

Sheet Uptier
D3: Traeger Pellet Grills | W3: DRAFT
D4: Illustrative Uptier Transaction | W4: CONFIDENTIAL
D5: Data as of 1Q'25
D7: Existing Capital Structure
D8: RCF Outstanding | F8: ='Capital Structure'!G14 -> 0
D9: Receivables Financing Arrangement | F9: ='Capital Structure'!G15 -> 0
D10: 1L Term Loan | F10: ='Capital Structure'!G17 -> 403.325
D11: Cash Balance | F11: ='Capital Structure'!G32 -> 19.624
D12: LTM 1Q'25 Adj. EBITDA | F12: ='Capital Structure'!G22 -> 69.969
D14: RCF Paydown
D15: RCF Balance | F15: =F8 -> 0
D16: Cash available to paydown | F16: 0
D17: RCF Paydown | F17: =-MIN(MAX(F20,0),F16) -> 0
D19: New Money First Out 1L Term Loan
D20: New Money First Out 1L Term Loan | F20: 100
D21: Backstop Fee | F21: 0
D22: AHG | F22: 0
D24: New Second Out 1L Term Loan
D25: 1L TL Outstanding | F25: =$F$10 -> 403.325 | G25: =$F$10 -> 403.325 | H25: =$F$10 -> 403.325
D26: % Participation | F26: 0 | G26: =1-F26 -> 1
D27: Exchange Rate | F27: 1 | G27: 0.9 | H27: =F27-G27 -> 0.1
D28: New Second Out 2030 Senior Secured Notes | F28: =MROUND((F25*F26*F27),1) -> 0 | G28: =G25*G26*G27 -> 362.9925 | H28: =(H25*H27) -> 40.3325 | I28: <-- Discount Capture
G31: Pre-Trx. | H31: Trans. | I31: Discount | J31: Post-Trx.
G32: Amount | H32: Adj. | I32: Capture | J32: Amount
D33: Receivables Financing Agreement | G33: =F9 -> 0 | H33: =-G33 -> 0 | I33: 0 | J33: =SUM(G33:I33) -> 0
D34: RCF ($350mm) | G34: =F15 -> 0 | H34: =F17 -> 0 | I34: 0 | J34: 0
D35: New First-Out 1L Term Loan | G35: 0 | H35: =F20 -> 100 | I35: 0 | J35: =SUM(G35:I35) -> 100
D36: New Second-Out 1L Term Loan | G36: 0 | H36: =G28 -> 362.9925 | I36: 0 | J36: =SUM(G36:I36) -> 362.9925 | L36: Sources | R36: Uses
D37: 1L Term Loan | G37: =$F$10 -> 403.325 | H37: =-$G$28 -> -362.9925 | I37: =-$H$28 -> -40.3325 | J37: =MROUND(SUM(G37:I37),1) -> 0 | L37: New First-Out 1L Term Loan | P37: =H35 -> 100 | R37: Extinguish 1L Term Loan | V37: =SUM(G28:H28) -> 403.325
D38: Total Debt | G38: =SUM(G33:G37) -> 403.325 | H38: =SUM(H33:H37) -> 100 | I38: =SUM(I33:I37) -> -40.3325 | J38: =SUM(J33:J37) -> 462.9925 | L38: New Second-Out 1L Term Loan | P38: =-H37 -> 362.9925 | R38: Cash to B/S | V38: =V42-SUM(V37,V39:V41) -> 85
D39: Total Leverage | G39: =G38/$F$12 -> 5.7643385 | H39: =J39-G39 -> 0.85277051 | I39: 0 | J39: =J38/$F$12 -> 6.617109 | L39: 1L Discount Capture | P39: =-I37 -> 40.3325 | R39: Pay down Receivables | V39: =-H33 -> 0
R40: Financing Agreement
D41: Cash and Equivalents | G41: =$F$11 -> 19.624 | H41: =V38 -> 85 | I41: 0 | J41: =SUM(G41:I41) -> 104.624 | R41: Transaction Fees & Expenses | V41: 15
D42: Net Debt | G42: =SUM(-G41,G38) -> 383.701 | H42: =SUM(-H41,H38) -> 15 | I42: =SUM(-I41,I38) -> -40.3325 | J42: =SUM(-J41,J38) -> 358.3685 | L42: Total Sources | P42: =SUM(P37:P39) -> 503.325 | R42: Total Uses | V42: =P42 -> 503.325
D43: Net Leverage | G43: =G42/$F$12 -> 5.4838714 | H43: =J43-G43 -> -0.36205319 | I43: 0 | J43: =J42/$F$12 -> 5.1218182
D44: Memo: LTM 2Q'25 Adj. EBITDA | G44: =$F$12 -> 69.969 | J44: =G44 -> 69.969

Sheet Discount Capture Outputs
D3: Traeger Pellet Grills | O3: DRAFT
D4: Liquidity Model Output | O4: CONFIDENTIAL
D5: Data as of 1Q'25
D7: Debt Market Value
F9: 1L Term Loan due 2028
D11: Face Value | F11: ='Capital Structure'!G17 -> 403.325
D12: Market Value | F12: =F11*('Capital Structure'!M17/100) -> 340.32563 | G12: =F11-F12 -> 62.999365
D14: Discount Capture
D16: Date | E16: TL Pricing | F16: Implied Discount / Premium | G16: =F9 -> 1L Term Loan due 2028
D18: 44372 | E18: 100.25 | F18: =100-E18 -> -0.25 | G18: =IF(((F18/100)*$F$11)<0,0,(F18/100)*$F$11) -> 0
D19: 44375 | E19: 100.25 | F19: =100-E19 -> -0.25 | G19: =IF(((F19/100)*$F$11)<0,0,(F19/100)*$F$11) -> 0
D20: 44376 | E20: 100.25 | F20: =100-E20 -> -0.25 | G20: =IF(((F20/100)*$F$11)<0,0,(F20/100)*$F$11) -> 0
D21: 44377 | E21: 100.38 | F21: =100-E21 -> -0.38 | G21: =IF(((F21/100)*$F$11)<0,0,(F21/100)*$F$11) -> 0
D22: 44378 | E22: 100.27 | F22: =100-E22 -> -0.27 | G22: =IF(((F22/100)*$F$11)<0,0,(F22/100)*$F$11) -> 0
D23: 44379 | E23: 100.29 | F23: =100-E23 -> -0.29 | G23: =IF(((F23/100)*$F$11)<0,0,(F23/100)*$F$11) -> 0
D24: 44382 | E24: 100.29 | F24: =100-E24 -> -0.29 | G24: =IF(((F24/100)*$F$11)<0,0,(F24/100)*$F$11) -> 0
D25: 44383 | E25: 100.29 | F25: =100-E25 -> -0.29 | G25: =IF(((F25/100)*$F$11)<0,0,(F25/100)*$F$11) -> 0
D26: 44384 | E26: 100.28 | F26: =100-E26 -> -0.28 | G26: =IF(((F26/100)*$F$11)<0,0,(F26/100)*$F$11) -> 0
D27: 44385 | E27: 100.27 | F27: =100-E27 -> -0.27 | G27: =IF(((F27/100)*$F$11)<0,0,(F27/100)*$F$11) -> 0
D28: 44386 | E28: 100.28 | F28: =100-E28 -> -0.28 | G28: =IF(((F28/100)*$F$11)<0,0,(F28/100)*$F$11) -> 0
D29: 44389 | E29: 100.27 | F29: =100-E29 -> -0.27 | G29: =IF(((F29/100)*$F$11)<0,0,(F29/100)*$F$11) -> 0
... D1010: 45764 | E1010: 82.97 | F1010: =100-E1010 -> 17.03 | G1010: =IF(((F1010/100)*$F$11)<0,0,(F1010/100)*$F$11) -> 68.686248
D1011: =D1010+1 -> 45765 | E1011: {=IFERROR(INDEX(Pricing!O:O,MATCH('Discount Capture Outputs'!D1011,Pricing!M:M,0),0),'Discount Capture Outputs'!E1010)} -> 82.97 | F1011: =100-E1011 -> 17.03 | G1011: =IF(((F1011/100)*$F$11)<0,0,(F1011/100)*$F$11) -> 68.686248
D1012: =D1011+1 -> 45766 | E1012: {=IFERROR(INDEX(Pricing!O:O,MATCH('Discount Capture Outputs'!D1012,Pricing!M:M,0),0),'Discount Capture Outputs'!E1011)} -> 82.97 | F1012: =100-E1012 -> 17.03 | G1012: =IF(((F1012/100)*$F$11)<0,0,(F1012/100)*$F$11) -> 68.686248
D1013: =D1012+1 -> 45767 | E1013: {=IFERROR(INDEX(Pricing!O:O,MATCH('Discount Capture Outputs'!D1013,Pricing!M:M,0),0),'Discount Capture Outputs'!E1012)} -> 82.97 | F1013: =100-E1013 -> 17.03 | G1013: =IF(((F1013/100)*$F$11)<0,0,(F1013/100)*$F$11) -> 68.686248
D1014: =D1013+1 -> 45768 | E1014: {=IFERROR(INDEX(Pricing!O:O,MATCH('Discount Capture Outputs'!D1014,Pricing!M:M,0),0),'Discount Capture Outputs'!E1013)} -> 82.91 | F1014: =100-E1014 -> 17.09 | G1014: =IF(((F1014/100)*$F$11)<0,0,(F1014/100)*$F$11) -> 68.928243
D1015: =D1014+1 -> 45769 | E1015: {=IFERROR(INDEX(Pricing!O:O,MATCH('Discount Capture Outputs'!D1015,Pricing!M:M,0),0),'Discount Capture Outputs'!E1014)} -> 82.72 | F1015: =100-E1015 -> 17.28 | G1015: =IF(((F1015/100)*$F$11)<0,0,(F1015/100)*$F$11) -> 69.69456
D1016: =D1015+1 -> 45770 | E1016: {=IFERROR(INDEX(Pricing!O:O,MATCH('Discount Capture Outputs'!D1016,Pricing!M:M,0),0),'Discount Capture Outputs'!E1015)} -> 83.13 | F1016: =100-E1016 -> 16.87 | G1016: =IF(((F1016/100)*$F$11)<0,0,(F1016/100)*$F$11) -> 68.040928
D1017: =D1016+1 -> 45771 | E1017: {=IFERROR(INDEX(Pricing!O:O,MATCH('Discount Capture Outputs'!D1017,Pricing!M:M,0),0),'Discount Capture Outputs'!E1016)} -> 83.28 | F1017: =100-E1017 -> 16.72 | G1017: =IF(((F1017/100)*$F$11)<0,0,(F1017/100)*$F$11) -> 67.43594
D1018: =D1017+1 -> 45772 | E1018: {=IFERROR(INDEX(Pricing!O:O,MATCH('Discount Capture Outputs'!D1018,Pricing!M:M,0),0),'Discount Capture Outputs'!E1017)} -> 83.38 | F1018: =100-E1018 -> 16.62 | G1018: =IF(((F1018/100)*$F$11)<0,0,(F1018/100)*$F$11) -> 67.032615
D1019: =D1018+1 -> 45773 | E1019: {=IFERROR(INDEX(Pricing!O:O,MATCH('Discount Capture Outputs'!D1019,Pricing!M:M,0),0),'Discount Capture Outputs'!E1018)} -> 83.38 | F1019: =100-E1019 -> 16.62 | G1019: =IF(((F1019/100)*$F$11)<0,0,(F1019/100)*$F$11) -> 67.032615
D1020: =D1019+1 -> 45774 | E1020: {=IFERROR(INDEX(Pricing!O:O,MATCH('Discount Capture Outputs'!D1020,Pricing!M:M,0),0),'Discount Capture Outputs'!E1019)} -> 83.38 | F1020: =100-E1020 -> 16.62 | G1020: =IF(((F1020/100)*$F$11)<0,0,(F1020/100)*$F$11) -> 67.032615
D1021: =D1020+1 -> 45775 | E1021: {=IFERROR(INDEX(Pricing!O:O,MATCH('Discount Capture Outputs'!D1021,Pricing!M:M,0),0),'Discount Capture Outputs'!E1020)} -> 83.43 | F1021: =100-E1021 -> 16.57 | G1021: =IF(((F1021/100)*$F$11)<0,0,(F1021/100)*$F$11) -> 66.830952
D1022: =D1021+1 -> 45776 | E1022: {=IFERROR(INDEX(Pricing!O:O,MATCH('Discount Capture Outputs'!D1022,Pricing!M:M,0),0),'Discount Capture Outputs'!E1021)} -> 83.47 | F1022: =100-E1022 -> 16.53 | G1022: =IF(((F1022/100)*$F$11)<0,0,(F1022/100)*$F$11) -> 66.669623
... D1065: =D1064+1 -> 45819 | E1065: {=IFERROR(INDEX(Pricing!O:O,MATCH('Discount Capture Outputs'!D1065,Pricing!M:M,0),0),'Discount Capture Outputs'!E1064)} -> 89.1 | F1065: =100-E1065 -> 10.9 | G1065: =IF(((F1065/100)*$F$11)<0,0,(F1065/100)*$F$11) -> 43.962425
D1066: 45820 | E1066: 89.06 | F1066: =100-E1066 -> 10.94 | G1066: =IF(((F1066/100)*$F$11)<0,0,(F1066/100)*$F$11) -> 44.123755
D1067: 45821 | E1067: 89.03 | F1067: =100-E1067 -> 10.97 | G1067: =IF(((F1067/100)*$F$11)<0,0,(F1067/100)*$F$11) -> 44.244752
D1068: 45824 | E1068: 89.07 | F1068: =100-E1068 -> 10.93 | G1068: =IF(((F1068/100)*$F$11)<0,0,(F1068/100)*$F$11) -> 44.083423
D1069: 45825 | E1069: 89.06 | F1069: =100-E1069 -> 10.94 | G1069: =IF(((F1069/100)*$F$11)<0,0,(F1069/100)*$F$11) -> 44.123755
D1070: 45826 | E1070: 89.06 | F1070: =100-E1070 -> 10.94 | G1070: =IF(((F1070/100)*$F$11)<0,0,(F1070/100)*$F$11) -> 44.123755
D1071: 45827 | E1071: 89.06 | F1071: =100-E1071 -> 10.94 | G1071: =IF(((F1071/100)*$F$11)<0,0,(F1071/100)*$F$11) -> 44.123755
D1072: 45828 | E1072: 89.42 | F1072: =100-E1072 -> 10.58 | G1072: =IF(((F1072/100)*$F$11)<0,0,(F1072/100)*$F$11) -> 42.671785
D1073: 45831 | E1073: 89.18 | F1073: =100-E1073 -> 10.82 | G1073: =IF(((F1073/100)*$F$11)<0,0,(F1073/100)*$F$11) -> 43.639765
D1074: 45832 | E1074: 89.19 | F1074: =100-E1074 -> 10.81 | G1074: =IF(((F1074/100)*$F$11)<0,0,(F1074/100)*$F$11) -> 43.599433
D1075: 45833 | E1075: 89.19 | F1075: =100-E1075 -> 10.81 | G1075: =IF(((F1075/100)*$F$11)<0,0,(F1075/100)*$F$11) -> 43.599433
D1076: 45834 | E1076: 89.18 | F1076: =100-E1076 -> 10.82 | G1076: =IF(((F1076/100)*$F$11)<0,0,(F1076/100)*$F$11) -> 43.639765
D1077: 45835 | E1077: 89.82 | F1077: =100-E1077 -> 10.18 | G1077: =IF(((F1077/100)*$F$11)<0,0,(F1077/100)*$F$11) -> 41.058485
... D1256: 46086 | E1256: 92.82 | F1256: =100-E1256 -> 7.18 | G1256: =IF(((F1256/100)*$F$11)<0,0,(F1256/100)*$F$11) -> 28.958735

Sheet Tariff Slide
D3: Traeger Pellet Grills | J3: DRAFT
D4: Industry Data | J4: CONFIDENTIAL
D5: Data as of 1Q'25
D8: Assumptions
D10: Tariffs
D11: Section 232 and 122 Effective Tariff Rate | G11: 0.5
D12: Tariff Pass-Through | G12: 1
D13: Section 301 Tariff? | F13: 0 | G13: 0.2
D14: Total Tariff Rate | G14: =IF($F$13=1,G11+G13,G11) -> 0.5
D16: Unit Economics
D17: COGS as a % of Unit Price - Grills | G17: 0.6
D19: Output
F21: Pre-Tariff | G21: Adj. | H21: Post-Tariff
D22: Traeger
D23: Retailer Pays --> | F23: 1000 | G23: =H23 - F23 -> 300 | H23: =F23+(G25*G12) -> 1300
D24: (-) COGS | F24: =F23*G17 -> 600 | H24: =SUM(F24:G24) -> 600
D25: (-) Tariff | F25: 0 | G25: =H25 - F25 -> 300 | H25: =F24*G14 -> 300
D26: Traeger Gross Profit | F26: =F23-SUM(F24:F25) -> 400 | G26: =G23-SUM(G24:G25) -> 0 | H26: =H23-SUM(H24:H25) -> 400
D27: Margin % | F27: =F26/F23 -> 0.4 | G27: =H27-F27 -> -0.092307692 | H27: =H26/H23 -> 0.30769231
D28: Margin % (No 301 Exemption) | F28: =(IF($F$13=1,F27,F28)) -> 0.4 | G28: =(IF($F$13=1,G27,G28)) -> -0.11830986 | H28: =(IF($F$13=1,H27,H28)) -> 0.28169014
D30: Retailer
D31: Consumer Pays --> | F31: 1250 | G31: =G23*G12 -> 300 | H31: =SUM(F31:G31) -> 1550
D32: (-) COGS | F32: =F23 -> 1000 | G32: =H32 - F32 -> 300 | H32: =H23 -> 1300
D33: Retailer Gross Profit | F33: =F31-F32 -> 250 | G33: =H33 - F33 -> 0 | H33: =H31 - H32 -> 250
D34: Retailer Margin % | F34: =F33/F31 -> 0.2 | G34: =H34-F34 -> -0.038709677 | H34: =H33/H31 -> 0.16129032
D35: Margin % (No 301 Exemption) | F35: =(IF($F$13=1,F34,F35)) -> 0.2 | G35: =(IF($F$13=1,G34,G35)) -> -0.050299401 | H35: =(IF($F$13=1,H34,H35)) -> 0.1497006
D37: Memo: Tariff Rate | F37: =F25 / F23 -> 0 | H37: =G14 -> 0.5
D38: Memo: Consumer Increase | H38: =(H31 - F31) / F31 -> 0.24
D39: Memo: Consumer Increase (No 301 Exemption) | H39: =(IF($F$13=1,H38,H39)) -> 0.336
D41: Sensitivities
D43: Consumer Price
F44: Tariff Pass-Through
E45: =H38 -> 0.24 | F45: 0.5 | G45: =F45+12.5% -> 0.625 | H45: =G45+12.5% -> 0.75 | I45: =H45+12.5% -> 0.875 | J45: =I45+12.5% -> 1
D46: Tariff Rate | E46: 0.25 | F46: 0.03 | G46: 0.046875 | H46: 0.0675 | I46: 0.091875 | J46: 0.12
E47: =E46+25% -> 0.5 | F47: 0.06 | G47: 0.09375 | H47: 0.135 | I47: 0.18375 | J47: 0.24
E48: =E47+25% -> 0.75 | F48: 0.09 | G48: 0.140625 | H48: 0.2025 | I48: 0.275625 | J48: 0.36
E49: =E48+25% -> 1 | F49: 0.12 | G49: 0.1875 | H49: 0.27 | I49: 0.3675 | J49: 0.48
E50: =E49+25% -> 1.25 | F50: 0.15 | G50: 0.234375 | H50: 0.3375 | I50: 0.459375 | J50: 0.6
D52: Traeger Margin
F53: Tariff Pass-Through
E54: =H27 -> 0.30769231 | F54: 0.5 | G54: =F54+12.5% -> 0.625 | H54: =G54+12.5% -> 0.75 | I54: =H54+12.5% -> 0.875 | J54: =I54+12.5% -> 1
D55: Tariff Rate | E55: 0.25 | F55: 0.30232558 | G55: 0.31428571 | H55: 0.3258427 | I55: 0.33701657 | J55: 0.34782609
E56: =E55+25% -> 0.5 | F56: 0.2173913 | G56: 0.24210526 | H56: 0.26530612 | I56: 0.28712871 | J56: 0.30769231
E57: =E56+25% -> 0.75 | F57: 0.14285714 | G57: 0.1804878 | H57: 0.21495327 | I57: 0.24663677 | J57: 0.27586207
E58: =E57+25% -> 1 | F58: 0.076923077 | G58: 0.12727273 | H58: 0.17241379 | I58: 0.21311475 | J58: 0.25
E59: =E58+25% -> 1.25 | F59: 0.018181818 | G59: 0.080851064 | H59: 0.136 | I59: 0.18490566 | J59: 0.22857143
D61: Retailer Margin
F62: Tariff Pass-Through
E63: =H34 -> 0.16129032 | F63: 0.5 | G63: =F63+12.5% -> 0.625 | H63: =G63+12.5% -> 0.75 | I63: =H63+12.5% -> 0.875 | J63: =I63+12.5% -> 1
D64: Tariff Rate | E64: 0.25 | F64: 0.16504854 | G64: 0.1641791 | H64: 0.16627635 | I64: 0.17115054 | J64: 0.17857143
E65: =E64+25% -> 0.5 | F65: 0.13207547 | G65: 0.13142857 | H65: 0.13656388 | I65: 0.1467793 | J65: 0.16129032
E66: =E65+25% -> 0.75 | F66: 0.10091743 | G66: 0.10136986 | H66: 0.11018711 | I66: 0.12591867 | J66: 0.14705882
E67: =E66+25% -> 1 | F67: 0.071428571 | G67: 0.073684211 | H67: 0.086614173 | I67: 0.10786106 | J67: 0.13513514
E68: =E67+25% -> 1.25 | F68: 0.043478261 | G68: 0.048101266 | H68: 0.065420561 | I68: 0.092077088 | J68: 0.125
D70: Product Pricing
D72: Consumer Increase | H72: =H38 -> 0.24 | I72: =H39 -> 0.336
D73: Traeger Woodridge Pro | G73: 999.99 | H73: =$G73*(1+H$72) -> 1239.9876 | I73: =$G73*(1+I$72) -> 1335.9866
D74: Traeger Ironwood | G74: 1799.99 | H74: =$G74*(1+H$72) -> 2231.9876 | I74: =$G74*(1+I$72) -> 2404.7866
D75: Traeger Timberline 1300 | G75: 3999.99 | H75: =$G75*(1+H$72) -> 4959.9876 | I75: =$G75*(1+I$72) -> 5343.9866

Sheet Industry Data
D3: Traeger Pellet Grills | N3: DRAFT
D4: Industry Data | N4: CONFIDENTIAL
D5: Data as of 4Q'25
S7: A | W7: B | AB7: B
E8: Housing Starts | G8: A | S8: FRED Graph Observations | W8: FRED Graph Observations | AB8: FRED Graph Observations
S9: Federal Reserve Economic Data | W9: Federal Reserve Economic Data | AB9: Federal Reserve Economic Data
S10: Link: https://fred.stlouisfed.org | W10: Link: https://fred.stlouisfed.org | AB10: Link: https://fred.stlouisfed.org
S11: Help: https://fredhelp.stlouisfed.org | W11: Help: https://fredhelp.stlouisfed.org | AB11: Help: https://fredhelp.stlouisfed.org
S12: Economic Research Division | W12: Economic Research Division | AB12: Economic Research Division
S13: Federal Reserve Bank of St. Louis | W13: Federal Reserve Bank of St. Louis | AB13: Federal Reserve Bank of St. Louis
BU14: =(M66/J66)^(1/3)-1 -> 0.021359814
S15: HOUST | T15: New Privately-Owned Housing Units Started: Total Units, Thousands of Units, Monthly, Seasonally Adjusted Annual Rate | W15: Disposable Personal Income, Billions of Dollars, Monthly, Seasonally Adjusted Annual Rate | AB15: U.S. Consumer Sentiment Index
S17: Frequency: Monthly | W17: Frequency: Monthly | Y17: % Change from a year ago | AB17: Frequency: Monthly | AD17: Indexed to 100
S18: observation_date | T18: HOUST | W18: observation_date | X18: DSPI | Y18: observation_date | Z18: DSPI_PC1 | AB18: observation_date | AC18: USMCI
S19: 41061 | T19: 757 | W19: 40878 | X19: 12069.5 | Y19: 40909 | Z19: 0.0440136 | AB19: 40940 | AC19: 100
S20: 41091 | T20: 740 | W20: 40909 | X20: 12175.6 | Y20: 40940 | Z20: 0.045446 | AB20: 40969 | AC20: 101.19522
S21: 41122 | T21: 754 | W21: 40940 | X21: 12261.2 | Y21: 40969 | Z21: 0.0489684 | AB21: 41000 | AC21: 101.46082
S22: 41153 | T22: 847 | W22: 40969 | X22: 12319.4 | Y22: 41000 | Z22: 0.0516978 | AB22: 41030 | AC22: 105.31208
S23: 41183 | T23: 915 | W23: 41000 | X23: 12382.9 | Y23: 41030 | Z23: 0.0483163 | AB23: 41061 | AC23: 97.21116
S24: 41214 | T24: 833 | W24: 41030 | X24: 12365.1 | Y24: 41061 | Z24: 0.0425566 | AB24: 41091 | AC24: 96.01594
S25: 41244 | T25: 976 | W25: 41061 | X25: 12344.6 | Y25: 41091 | Z25: 0.0294807 | AB25: 41122 | AC25: 98.67198
E26: Housing Starts | G26: B | S26: 41275 | T26: 888 | W26: 41091 | X26: 12257.1 | Y26: 41122 | Z26: 0.027958 | AB26: 41153 | AC26: 103.98406
S27: 41306 | T27: 962 | W27: 41122 | X27: 12262.1 | Y27: 41153 | Z27: 0.03837 | AB27: 41183 | AC27: 109.69456
S28: 41334 | T28: 1010 | W28: 41153 | X28: 12386.3 | Y28: 41183 | Z28: 0.0476781 | AB28: 41214 | AC28: 109.82736
S29: 41365 | T29: 835 | W29: 41183 | X29: 12507.6 | Y29: 41214 | Z29: 0.0593924 | AB29: 41244 | AC29: 96.81275
S30: 41395 | T30: 930 | W30: 41214 | X30: 12664.4 | Y30: 41244 | Z30: 0.0748747 | AB30: 41275 | AC30: 98.00797
S31: 41426 | T31: 839 | W31: 41244 | X31: 12973.2 | Y31: 41275 | Z31: 0.0051579 | AB31: 41306 | AC31: 103.05445
S32: 41456 | T32: 880 | W32: 41275 | X32: 12238.4 | Y32: 41306 | Z32: -0.0007748 | AB32: 41334 | AC32: 104.38247
S33: 41487 | T33: 917 | W33: 41306 | X33: 12251.7 | Y33: 41334 | Z33: -0.0038395 | AB33: 41365 | AC33: 101.46082
S34: 41518 | T34: 850 | W34: 41334 | X34: 12272.1 | Y34: 41365 | Z34: -0.0067835 | AB34: 41395 | AC34: 112.2178
S35: 41548 | T35: 925 | W35: 41365 | X35: 12298.9 | Y35: 41395 | Z35: 6.47e-05 | AB35: 41426 | AC35: 111.68659
S36: 41579 | T36: 1100 | W36: 41395 | X36: 12365.9 | Y36: 41426 | Z36: 0.0040666 | AB36: 41456 | AC36: 113.01461
S37: 41609 | T37: 1002 | W37: 41426 | X37: 12394.8 | Y37: 41456 | Z37: 0.0114138 | AB37: 41487 | AC37: 109.03054
S38: 41640 | T38: 888 | W38: 41456 | X38: 12397 | Y38: 41487 | Z38: 0.0146631 | AB38: 41518 | AC38: 102.92165
... S43: 41791 | T43: 911 | W43: 41609 | X43: 12551.8 | Y43: 41640 | Z43: 0.0325042 | AB43: 41671 | AC43: 108.36653
E44: US Housing Starts | S44: 41821 | T44: 1085 | W44: 41640 | X44: 12636.2 | Y44: 41671 | Z44: 0.0372846 | AB44: 41699 | AC44: 106.2417
S45: 41852 | T45: 984 | W45: 41671 | X45: 12708.5 | Y45: 41699 | Z45: 0.042894 | AB45: 41730 | AC45: 111.68659
E46: 2018 | F46: 2019 | G46: 2020 | H46: 2021 | I46: 2022 | J46: 2023 | K46: 2024 | L46: 2025 | M46: 2026 | N46: 2027 | O46: 2028 | S46: 41883 | T46: 1023 | W46: 41699 | X46: 12798.5 | Y46: 41730 | Z46: 0.046435 | AB46: 41760 | AC46: 108.76494
E47: 1247 | F47: 1292 | G47: 1394 | H47: 1603 | I47: 1552 | J47: 1421 | K47: 1371 | L47: 1363 | M47: 1345 | N47: 1435 | O47: 1554 | S47: 41913 | T47: 1074 | W47: 41730 | X47: 12870 | Y47: 41760 | Z47: 0.0458276 | AB47: 41791 | AC47: 109.56175
S48: 41944 | T48: 1001 | W48: 41760 | X48: 12932.6 | Y48: 41791 | Z48: 0.0482622 | AB48: 41821 | AC48: 108.63214
S49: 41974 | T49: 1073 | W49: 41791 | X49: 12993 | Y49: 41821 | Z49: 0.0516415 | AB49: 41852 | AC49: 109.56175
S50: 42005 | T50: 1085 | W50: 41821 | X50: 13037.2 | Y50: 41852 | Z50: 0.0523473 | AB50: 41883 | AC50: 112.3506
S51: 42036 | T51: 886 | W51: 41852 | X51: 13093.2 | Y51: 41883 | Z51: 0.0507078 | AB51: 41913 | AC51: 115.40505
S52: 42064 | T52: 960 | W52: 41883 | X52: 13137 | Y52: 41913 | Z52: 0.0583305 | AB52: 41944 | AC52: 117.92829
S53: 42095 | T53: 1190 | W53: 41913 | X53: 13195.9 | Y53: 41944 | Z53: 0.0595015 | AB53: 41974 | AC53: 124.30279
S54: 42125 | T54: 1079 | W54: 41944 | X54: 13255 | Y54: 41974 | Z54: 0.0614972 | AB54: 42005 | AC54: 130.27888
S55: 42156 | T55: 1205 | W55: 41974 | X55: 13323.7 | Y55: 42005 | Z55: 0.0553568 | AB55: 42036 | AC55: 126.69323
S56: 42186 | T56: 1146 | W56: 42005 | X56: 13335.7 | Y56: 42036 | Z56: 0.0550498 | AB56: 42064 | AC56: 123.50598
S57: 42217 | T57: 1130 | W57: 42036 | X57: 13408.1 | Y57: 42064 | Z57: 0.0468258 | AB57: 42095 | AC57: 127.35724
S58: 42248 | T58: 1224 | W58: 42064 | X58: 13397.8 | Y58: 42095 | Z58: 0.0442502 | AB58: 42125 | AC58: 120.45153
S59: 42278 | T59: 1058 | W59: 42095 | X59: 13439.5 | Y59: 42125 | Z59: 0.0434715 | AB59: 42156 | AC59: 127.62284
... S62: 42370 | T62: 1092 | W62: 42186 | X62: 13572.5 | Y62: 42217 | Z62: 0.038921 | AB62: 42248 | AC62: 115.80345
E63: Industry Revenue | S63: 42401 | T63: 1225 | W63: 42217 | X63: 13602.8 | Y63: 42248 | Z63: 0.0367283 | AB63: 42278 | AC63: 119.52191
S64: 42430 | T64: 1111 | W64: 42248 | X64: 13619.5 | Y64: 42278 | Z64: 0.0339272 | AB64: 42309 | AC64: 121.24834
E65: 2019 | F65: 2020 | G65: 2021 | H65: 2022 | I65: 2023 | J65: 2024 | K65: 2025 | L65: 2026 | M65: 2027 | N65: =M65+1 -> 2028 | S65: 42461 | T65: 1163 | W65: 42278 | X65: 13643.6 | Y65: 42309 | Z65: 0.0296945 | AB65: 42339 | AC65: 122.97477
E66: 1753.4 | F66: 1901.2 | G66: 2174.6 | H66: 2099.6 | I66: 2129.3 | J66: 2051.7 | K66: 2082 | L66: 2128.6 | M66: 2186 | N66: 2231.6 | S66: 42491 | T66: 1148 | W66: 42309 | X66: 13648.6 | Y66: 42339 | Z66: 0.028408 | AB66: 42370 | AC66: 122.17795
S67: 42522 | T67: 1203 | W67: 42339 | X67: 13702.2 | Y67: 42370 | Z67: 0.0323568 | AB67: 42401 | AC67: 121.77955
S68: 42552 | T68: 1239 | W68: 42370 | X68: 13767.2 | Y68: 42401 | Z68: 0.0272746 | AB68: 42430 | AC68: 120.84993
S69: 42583 | T69: 1171 | W69: 42401 | X69: 13773.8 | Y69: 42430 | Z69: 0.0304677 | AB69: 42461 | AC69: 118.19389
S70: 42614 | T70: 1068 | W70: 42430 | X70: 13806 | Y70: 42461 | Z70: 0.0285055 | AB70: 42491 | AC70: 125.76361
S71: 42644 | T71: 1313 | W71: 42461 | X71: 13822.6 | Y71: 42491 | Z71: 0.0251875 | AB71: 42522 | AC71: 124.16999
S72: 42675 | T72: 1140 | W72: 42491 | X72: 13834.7 | Y72: 42522 | Z72: 0.0250419 | AB72: 42552 | AC72: 119.52191
S73: 42705 | T73: 1252 | W73: 42522 | X73: 13868.1 | Y73: 42552 | Z73: 0.0259569 | AB73: 42583 | AC73: 119.25631
S74: 42736 | T74: 1190 | W74: 42552 | X74: 13924.8 | Y74: 42583 | Z74: 0.0262961 | AB74: 42614 | AC74: 121.11554
S75: 42767 | T75: 1271 | W75: 42583 | X75: 13960.5 | Y75: 42614 | Z75: 0.0293329 | AB75: 42644 | AC75: 115.80345
S76: 42795 | T76: 1190 | W76: 42614 | X76: 14019 | Y76: 42644 | Z76: 0.0315239 | AB76: 42675 | AC76: 124.56839
S77: 42826 | T77: 1146 | W77: 42644 | X77: 14073.7 | Y77: 42675 | Z77: 0.0342526 | AB77: 42705 | AC77: 130.41169
S78: 42856 | T78: 1157 | W78: 42675 | X78: 14116.1 | Y78: 42705 | Z78: 0.0348776 | AB78: 42736 | AC78: 130.81009
... S80: 42917 | T80: 1206 | W80: 42736 | X80: 14294.2 | Y80: 42767 | Z80: 0.0422977 | AB80: 42795 | AC80: 128.68526
E81: U.S. Grill Unit Share | S81: 42948 | T81: 1159 | W81: 42767 | X81: 14356.4 | Y81: 42795 | Z81: 0.0436404 | AB81: 42826 | AC81: 128.81806
E82: Gas Grills | F82: 0.225 | S82: 42979 | T82: 1181 | W82: 42795 | X82: 14408.5 | Y82: 42826 | Z82: 0.0467495 | AB82: 42856 | AC82: 128.95086
E83: Charcoal Grills | F83: 0.033 | S83: 43009 | T83: 1257 | W83: 42826 | X83: 14468.8 | Y83: 42856 | Z83: 0.0526864 | AB83: 42887 | AC83: 126.16202
E84: Electric Grills | F84: 0.113 | S84: 43040 | T84: 1273 | W84: 42856 | X84: 14563.6 | Y84: 42887 | Z84: 0.0516149 | AB84: 42917 | AC84: 124.03718
E85: Portable Grills | F85: 0.087 | S85: 43070 | T85: 1177 | W85: 42887 | X85: 14583.9 | Y85: 42917 | Z85: 0.0506937 | AB85: 42948 | AC85: 128.55246
S86: 43101 | T86: 1299 | W86: 42917 | X86: 14630.7 | Y86: 42948 | Z86: 0.0516457 | AB86: 42979 | AC86: 126.29482
S87: 43132 | T87: 1277 | W87: 42948 | X87: 14681.5 | Y87: 42979 | Z87: 0.0531493 | AB87: 43009 | AC87: 133.73174
S88: 43160 | T88: 1318 | W88: 42979 | X88: 14764.1 | Y88: 43009 | Z88: 0.0534756 | AB88: 43040 | AC88: 130.81009
S89: 43191 | T89: 1276 | W89: 43009 | X89: 14826.3 | Y89: 43040 | Z89: 0.0534213 | AB89: 43070 | AC89: 127.35724
S90: 43221 | T90: 1357 | W90: 43040 | X90: 14870.2 | Y90: 43070 | Z90: 0.0520941 | AB90: 43101 | AC90: 127.09163
S91: 43252 | T91: 1192 | W91: 43070 | X91: 14918.8 | Y91: 43101 | Z91: 0.053896 | AB91: 43132 | AC91: 132.40372
S92: 43282 | T92: 1208 | W92: 43101 | X92: 15064.6 | Y92: 43132 | Z92: 0.0540247 | AB92: 43160 | AC92: 134.66135
S93: 43313 | T93: 1288 | W93: 43132 | X93: 15132 | Y93: 43160 | Z93: 0.0551133 | AB93: 43191 | AC93: 131.2085
S94: 43344 | T94: 1250 | W94: 43160 | X94: 15202.6 | Y94: 43191 | Z94: 0.0554918 | AB94: 43221 | AC94: 130.14608
S95: 43374 | T95: 1221 | W95: 43191 | X95: 15271.7 | Y95: 43221 | Z95: 0.053977 | AB95: 43252 | AC95: 130.41169
S96: 43405 | T96: 1181 | W96: 43221 | X96: 15349.7 | Y96: 43252 | Z96: 0.0577212 | AB96: 43282 | AC96: 130.01328
S97: 43435 | T97: 1095 | W97: 43252 | X97: 15425.7 | Y97: 43282 | Z97: 0.0600176 | AB97: 43313 | AC97: 127.75564
... S175: 45809 | T175: 1382 | W175: 45627 | X175: 21965.2 | Y175: 45658 | Z175: 0.0390107 | AB175: 45689 | AC175: 85.92297
S176: 45839 | T176: 1420 | W176: 45658 | X176: 22108.9 | Y176: 45689 | Z176: 0.0438061
S177: 45870 | T177: 1291 | W177: 45689 | X177: 22300.5
S178: 45901 | T178: 1328 | W178: 45413 | X178: 20894.3
S179: 45931 | T179: 1272 | W179: 45444 | X179: 20932
S180: 45962 | T180: 1322
S181: 45992 | T181: 1404

Sheet Steel Pricing
D3: Traeger Pellet Grills | Q3: DRAFT
D4: Steel Pricing | Q4: CONFIDENTIAL
D5: Data as of 1Q'25
U6: Daily | V6: Quarterly
T7: Date | U7: Steel Coil Commodity Pricing | V7: Traeger Gross Margin
T8: 45810 | U8: 890
T9: 45807 | U9: 840
T10: 45806 | U10: 842
T11: 45805 | U11: 835
T12: 45804 | U12: 903
T13: 45800 | U13: 903
T14: 45799 | U14: 903
T15: 45798 | U15: 903
T16: 45797 | U16: 893
T17: 45796 | U17: 895
T18: 45793 | U18: 895
T19: 45792 | U19: 900
... T50: 45748 | U50: 895
T51: 45747 | U51: 890 | V51: 0.41497596
C52: 1Q25 | T52: 45744 | U52: 890
T53: 45743 | U53: 890
T54: 45742 | U54: 905
T55: 45741 | U55: 934
T56: 45740 | U56: 934
T57: 45737 | U57: 937
T58: 45736 | U58: 938
T59: 45735 | U59: 937
T60: 45734 | U60: 940
T61: 45733 | U61: 940
T62: 45730 | U62: 939
T63: 45729 | U63: 940
T64: 45728 | U64: 944
... T111: 45659 | U111: 708
T112: 45657 | U112: 709 | V112: 0.40851059
C113: 4Q24 | T113: 45656 | U113: 725
T114: 45653 | U114: 730
T115: 45652 | U115: 720
T116: 45650 | U116: 681
T117: 45649 | U117: 683
T118: 45646 | U118: 679
T119: 45645 | U119: 679
T120: 45644 | U120: 680
T121: 45643 | U121: 675
T122: 45642 | U122: 675
T123: 45639 | U123: 675
T124: 45638 | U124: 675
T125: 45637 | U125: 677
... T175: 45566 | U175: 727
T176: 45565 | U176: 735 | V176: 0.42349857
C177: 3Q24 | T177: 45562 | U177: 734
T178: 45561 | U178: 735
T179: 45560 | U179: 726
T180: 45559 | U180: 704
T181: 45558 | U181: 704
T182: 45555 | U182: 704
T183: 45554 | U183: 705
T184: 45553 | U184: 703
T185: 45552 | U185: 700
T186: 45551 | U186: 698
T187: 45548 | U187: 698
T188: 45547 | U188: 698
T189: 45546 | U189: 700
... T239: 45474 | U239: 674
T240: 45471 | U240: 674 | V240: 0.42932018
C241: 2Q24 | T241: 45470 | U241: 676
T242: 45469 | U242: 675
T243: 45468 | U243: 717
T244: 45467 | U244: 717
T245: 45464 | U245: 721
T246: 45463 | U246: 725
T247: 45461 | U247: 732
T248: 45460 | U248: 735
T249: 45457 | U249: 735
T250: 45456 | U250: 735
T251: 45455 | U251: 733
T252: 45454 | U252: 728
T253: 45453 | U253: 725
... T302: 45383 | U302: 863
T303: 45379 | U303: 860 | V303: 0.43172502
C304: 1Q24 | T304: 45378 | U304: 865
T305: 45377 | U305: 789
T306: 45376 | U306: 789
T307: 45373 | U307: 794
T308: 45372 | U308: 794
T309: 45371 | U309: 794
T310: 45370 | U310: 795
T311: 45369 | U311: 799
T312: 45366 | U312: 792
T313: 45365 | U313: 793
T314: 45364 | U314: 787
T315: 45363 | U315: 800
T316: 45362 | U316: 808
... T363: 45293 | U363: 1127
T364: 45289 | U364: 1135 | V364: 0.36793884
C365: 4Q23 | T365: 45288 | U365: 1149
T366: 45287 | U366: 1146
T367: 45286 | U367: 1078
T368: 45282 | U368: 1074
T369: 45281 | U369: 1074
T370: 45280 | U370: 1074
...

Sheet Pricing
D3: Traeger Pellet Grills | K3: DRAFT
D4: Pricing | K4: CONFIDENTIAL
D5: Data as of 1Q'25
D7: Equity | M7: LTM Pricing | S7: Long Term Equity
N8: Price
M9: Date | N9: RCF Facility | O9: 1L TL | P9: Equity | S9: Date | T9: NYSE: COOK - Price | U9: NYSE: COOK - Volume | W9: Date | X9: RCF Facility | Y9: 1L TL
M10: 45601 | N10: {=IFERROR(INDEX(X:X,MATCH($M10,$W:$W,0),),N9)} -> 91.95 | O10: {=IFERROR(INDEX(Y:Y,MATCH($M10,$W:$W,0),),O9)} -> 95.07 | P10: {=IFERROR(INDEX(T:T,MATCH($M10,$S:$S,0),),P9)} -> 3.17 | Q10: {=IFERROR(INDEX(U:U,MATCH($M10,$S:$S,0),),Q9)} -> 313371 | S10: 44405 | T10: 22 | U10: 13633040 | W10: 44377 | X10: 99.5 | Y10: 100.38
M11: 45602 | N11: {=IFERROR(INDEX(X:X,MATCH($M11,$W:$W,0),),N10)} -> 92.2 | O11: {=IFERROR(INDEX(Y:Y,MATCH($M11,$W:$W,0),),O10)} -> 95.32 | P11: {=IFERROR(INDEX(T:T,MATCH(M11,S:S,0),),P10)} -> 3.27 | Q11: {=IFERROR(INDEX(U:U,MATCH($M11,$S:$S,0),),Q10)} -> 272443 | S11: 44406 | T11: 22.21 | U11: 2828645 | W11: 44852 | X11: 76.02 | Y11: 80.11
M12: 45603 | N12: {=IFERROR(INDEX(X:X,MATCH($M12,$W:$W,0),),N11)} -> 92.22 | O12: {=IFERROR(INDEX(Y:Y,MATCH($M12,$W:$W,0),),O11)} -> 95.35 | P12: {=IFERROR(INDEX(T:T,MATCH(M12,S:S,0),),P11)} -> 3.14 | Q12: {=IFERROR(INDEX(U:U,MATCH($M12,$S:$S,0),),Q11)} -> 230849 | S12: 44409 | T12: 24.2 | U12: 1892916 | W12: 44853 | X12: 76.04 | Y12: 80.13
M13: 45604 | N13: {=IFERROR(INDEX(X:X,MATCH($M13,$W:$W,0),),N12)} -> 92.31 | O13: {=IFERROR(INDEX(Y:Y,MATCH($M13,$W:$W,0),),O12)} -> 95.44 | P13: {=IFERROR(INDEX(T:T,MATCH(M13,S:S,0),),P12)} -> 3.14 | Q13: {=IFERROR(INDEX(U:U,MATCH($M13,$S:$S,0),),Q12)} -> 230849 | S13: 44410 | T13: 27.07 | U13: 1962579 | W13: 44372 | X13: 99.44 | Y13: 100.25
M14: 45607 | N14: {=IFERROR(INDEX(X:X,MATCH($M14,$W:$W,0),),N13)} -> 92.31 | O14: {=IFERROR(INDEX(Y:Y,MATCH($M14,$W:$W,0),),O13)} -> 95.44 | P14: {=IFERROR(INDEX(T:T,MATCH(M14,S:S,0),),P13)} -> 2.97 | Q14: {=IFERROR(INDEX(U:U,MATCH($M14,$S:$S,0),),Q13)} -> 294647 | S14: 44411 | T14: 27.75 | U14: 2689015 | W14: 44378 | X14: 99.43 | Y14: 100.27
M15: 45608 | N15: {=IFERROR(INDEX(X:X,MATCH($M15,$W:$W,0),),N14)} -> 92.16 | O15: {=IFERROR(INDEX(Y:Y,MATCH($M15,$W:$W,0),),O14)} -> 95.29 | P15: {=IFERROR(INDEX(T:T,MATCH(M15,S:S,0),),P14)} -> 2.94 | Q15: {=IFERROR(INDEX(U:U,MATCH($M15,$S:$S,0),),Q14)} -> 243699 | S15: 44412 | T15: 29.4 | U15: 2670300 | W15: 44382 | X15: 99.45 | Y15: 100.29
M16: 45609 | N16: {=IFERROR(INDEX(X:X,MATCH($M16,$W:$W,0),),N15)} -> 92.03 | O16: {=IFERROR(INDEX(Y:Y,MATCH($M16,$W:$W,0),),O15)} -> 95.16 | P16: {=IFERROR(INDEX(T:T,MATCH(M16,S:S,0),),P15)} -> 2.95 | Q16: {=IFERROR(INDEX(U:U,MATCH($M16,$S:$S,0),),Q15)} -> 94064 | S16: 44413 | T16: 29.21 | U16: 635268 | W16: 44375 | X16: 99.43 | Y16: 100.25
M17: 45610 | N17: {=IFERROR(INDEX(X:X,MATCH($M17,$W:$W,0),),N16)} -> 91.96 | O17: {=IFERROR(INDEX(Y:Y,MATCH($M17,$W:$W,0),),O16)} -> 95.09 | P17: {=IFERROR(INDEX(T:T,MATCH(M17,S:S,0),),P16)} -> 2.97 | Q17: {=IFERROR(INDEX(U:U,MATCH($M17,$S:$S,0),),Q16)} -> 110716 | S17: 44416 | T17: 30.79 | U17: 644445 | W17: 44379 | X17: 99.45 | Y17: 100.29
M18: 45611 | N18: {=IFERROR(INDEX(X:X,MATCH($M18,$W:$W,0),),N17)} -> 91.95 | O18: {=IFERROR(INDEX(Y:Y,MATCH($M18,$W:$W,0),),O17)} -> 95.08 | P18: {=IFERROR(INDEX(T:T,MATCH(M18,S:S,0),),P17)} -> 2.97 | Q18: {=IFERROR(INDEX(U:U,MATCH($M18,$S:$S,0),),Q17)} -> 110716 | S18: 44417 | T18: 31.65 | U18: 641109 | W18: 44376 | X18: 99.42 | Y18: 100.25
M19: 45614 | N19: {=IFERROR(INDEX(X:X,MATCH($M19,$W:$W,0),),N18)} -> 91.94 | O19: {=IFERROR(INDEX(Y:Y,MATCH($M19,$W:$W,0),),O18)} -> 95.07 | P19: {=IFERROR(INDEX(T:T,MATCH(M19,S:S,0),),P18)} -> 2.88 | Q19: {=IFERROR(INDEX(U:U,MATCH($M19,$S:$S,0),),Q18)} -> 135448 | S19: 44418 | T19: 29.37 | U19: 998947 | W19: 44383 | X19: 99.45 | Y19: 100.29
M20: 45615 | N20: {=IFERROR(INDEX(X:X,MATCH($M20,$W:$W,0),),N19)} -> 91.9 | O20: {=IFERROR(INDEX(Y:Y,MATCH($M20,$W:$W,0),),O19)} -> 95.03 | P20: {=IFERROR(INDEX(T:T,MATCH(M20,S:S,0),),P19)} -> 2.87 | Q20: {=IFERROR(INDEX(U:U,MATCH($M20,$S:$S,0),),Q19)} -> 102227 | S20: 44419 | T20: 25.8 | U20: 1205749 | W20: 44390 | X20: 99.46 | Y20: 100.28
M21: 45616 | N21: {=IFERROR(INDEX(X:X,MATCH($M21,$W:$W,0),),N20)} -> 91.91 | O21: {=IFERROR(INDEX(Y:Y,MATCH($M21,$W:$W,0),),O20)} -> 95.04 | P21: {=IFERROR(INDEX(T:T,MATCH(M21,S:S,0),),P20)} -> 2.91 | Q21: {=IFERROR(INDEX(U:U,MATCH($M21,$S:$S,0),),Q20)} -> 119634 | S21: 44420 | T21: 26.76 | U21: 363382 | W21: 44384 | X21: 99.46 | Y21: 100.28
D22: Term Loan B | M22: 45617 | N22: {=IFERROR(INDEX(X:X,MATCH($M22,$W:$W,0),),N21)} -> 91.89 | O22: {=IFERROR(INDEX(Y:Y,MATCH($M22,$W:$W,0),),O21)} -> 95.02 | P22: {=IFERROR(INDEX(T:T,MATCH(M22,S:S,0),),P21)} -> 2.95 | Q22: {=IFERROR(INDEX(U:U,MATCH($M22,$S:$S,0),),Q21)} -> 146861 | S22: 44423 | T22: 26.15 | U22: 383187 | W22: 44385 | X22: 99.45 | Y22: 100.27
M23: 45618 | N23: {=IFERROR(INDEX(X:X,MATCH($M23,$W:$W,0),),N22)} -> 91.86 | O23: {=IFERROR(INDEX(Y:Y,MATCH($M23,$W:$W,0),),O22)} -> 94.98 | P23: {=IFERROR(INDEX(T:T,MATCH(M23,S:S,0),),P22)} -> 2.95 | Q23: {=IFERROR(INDEX(U:U,MATCH($M23,$S:$S,0),),Q22)} -> 146861 | S23: 44424 | T23: 25.27 | U23: 771076 | W23: 44391 | X23: 99.46 | Y23: 100.28
M24: 45621 | N24: {=IFERROR(INDEX(X:X,MATCH($M24,$W:$W,0),),N23)} -> 91.77 | O24: {=IFERROR(INDEX(Y:Y,MATCH($M24,$W:$W,0),),O23)} -> 94.9 | P24: {=IFERROR(INDEX(T:T,MATCH(M24,S:S,0),),P23)} -> 3.19 | Q24: {=IFERROR(INDEX(U:U,MATCH($M24,$S:$S,0),),Q23)} -> 248057 | S24: 44425 | T24: 25.35 | U24: 454582 | W24: 44386 | X24: 99.46 | Y24: 100.28
M25: 45622 | N25: {=IFERROR(INDEX(X:X,MATCH($M25,$W:$W,0),),N24)} -> 91.75 | O25: {=IFERROR(INDEX(Y:Y,MATCH($M25,$W:$W,0),),O24)} -> 94.88 | P25: {=IFERROR(INDEX(T:T,MATCH(M25,S:S,0),),P24)} -> 3.23 | Q25: {=IFERROR(INDEX(U:U,MATCH($M25,$S:$S,0),),Q24)} -> 131745 | S25: 44426 | T25: 25.78 | U25: 468848 | W25: 44393 | X25: 99.48 | Y25: 100.3
M26: 45623 | N26: {=IFERROR(INDEX(X:X,MATCH($M26,$W:$W,0),),N25)} -> 91.75 | O26: {=IFERROR(INDEX(Y:Y,MATCH($M26,$W:$W,0),),O25)} -> 94.88 | P26: {=IFERROR(INDEX(T:T,MATCH(M26,S:S,0),),P25)} -> 3.23 | Q26: {=IFERROR(INDEX(U:U,MATCH($M26,$S:$S,0),),Q25)} -> 131745 | S26: 44427 | T26: 25 | U26: 838060 | W26: 44392 | X26: 99.48 | Y26: 100.3
M27: 45624 | N27: {=IFERROR(INDEX(X:X,MATCH($M27,$W:$W,0),),N26)} -> 91.75 | O27: {=IFERROR(INDEX(Y:Y,MATCH($M27,$W:$W,0),),O26)} -> 94.88 | P27: {=IFERROR(INDEX(T:T,MATCH(M27,S:S,0),),P26)} -> 3.21 | Q27: {=IFERROR(INDEX(U:U,MATCH($M27,$S:$S,0),),Q26)} -> 51694 | S27: 44430 | T27: 27.29 | U27: 2179088 | W27: 44396 | X27: 99.38 | Y27: 100.2
M28: 45625 | N28: {=IFERROR(INDEX(X:X,MATCH($M28,$W:$W,0),),N27)} -> 91.76 | O28: {=IFERROR(INDEX(Y:Y,MATCH($M28,$W:$W,0),),O27)} -> 94.87 | P28: {=IFERROR(INDEX(T:T,MATCH(M28,S:S,0),),P27)} -> 3.21 | Q28: {=IFERROR(INDEX(U:U,MATCH($M28,$S:$S,0),),Q27)} -> 51694 | S28: 44431 | T28: 24.72 | U28: 1410955 | W28: 44389 | X28: 99.45 | Y28: 100.27
M29: 45628 | N29: {=IFERROR(INDEX(X:X,MATCH($M29,$W:$W,0),),N28)} -> 91.73 | O29: {=IFERROR(INDEX(Y:Y,MATCH($M29,$W:$W,0),),O28)} -> 94.86 | P29: {=IFERROR(INDEX(T:T,MATCH(M29,S:S,0),),P28)} -> 3.36 | Q29: {=IFERROR(INDEX(U:U,MATCH($M29,$S:$S,0),),Q28)} -> 264857 | S29: 44432 | T29: 24.76 | U29: 588379 | W29: 44397 | X29: 99.47 | Y29: 100.29
M30: 45629 | N30: {=IFERROR(INDEX(X:X,MATCH($M30,$W:$W,0),),N29)} -> 91.74 | O30: {=IFERROR(INDEX(Y:Y,MATCH($M30,$W:$W,0),),O29)} -> 94.87 | P30: {=IFERROR(INDEX(T:T,MATCH(M30,S:S,0),),P29)} -> 3.34 | Q30: {=IFERROR(INDEX(U:U,MATCH($M30,$S:$S,0),),Q29)} -> 197827 | S30: 44433 | T30: 25.53 | U30: 354611 | W30: 44400 | X30: 99.49 | Y30: 100.31
M31: 45630 | N31: {=IFERROR(INDEX(X:X,MATCH($M31,$W:$W,0),),N30)} -> 91.73 | O31: {=IFERROR(INDEX(Y:Y,MATCH($M31,$W:$W,0),),O30)} -> 94.88 | P31: {=IFERROR(INDEX(T:T,MATCH(M31,S:S,0),),P30)} -> 3.09 | Q31: {=IFERROR(INDEX(U:U,MATCH($M31,$S:$S,0),),Q30)} -> 203571 | S31: 44434 | T31: 26.18 | U31: 650738 | W31: 44403 | X31: 99.49 | Y31: 100.31
M32: 45631 | N32: {=IFERROR(INDEX(X:X,MATCH($M32,$W:$W,0),),N31)} -> 91.79 | O32: {=IFERROR(INDEX(Y:Y,MATCH($M32,$W:$W,0),),O31)} -> 94.92 | P32: {=IFERROR(INDEX(T:T,MATCH(M32,S:S,0),),P31)} -> 3.15 | Q32: {=IFERROR(INDEX(U:U,MATCH($M32,$S:$S,0),),Q31)} -> 203400 | S32: 44437 | T32: 25.64 | U32: 613523 | W32: 44398 | X32: 99.47 | Y32: 100.29
M33: 45632 | N33: {=IFERROR(INDEX(X:X,MATCH($M33,$W:$W,0),),N32)} -> 91.86 | O33: {=IFERROR(INDEX(Y:Y,MATCH($M33,$W:$W,0),),O32)} -> 94.99 | P33: {=IFERROR(INDEX(T:T,MATCH(M33,S:S,0),),P32)} -> 3.15 | Q33: {=IFERROR(INDEX(U:U,MATCH($M33,$S:$S,0),),Q32)} -> 203400 | S33: 44438 | T33: 25.14 | U33: 380875 | W33: 44405 | X33: 99.35 | Y33: 100.17
M34: 45635 | N34: {=IFERROR(INDEX(X:X,MATCH($M34,$W:$W,0),),N33)} -> 91.82 | O34: {=IFERROR(INDEX(Y:Y,MATCH($M34,$W:$W,0),),O33)} -> 94.94 | P34: {=IFERROR(INDEX(T:T,MATCH(M34,S:S,0),),P33)} -> 3.08 | Q34: {=IFERROR(INDEX(U:U,MATCH($M34,$S:$S,0),),Q33)} -> 160335 | S34: 44439 | T34: 25.98 | U34: 765013 | W34: 44404 | X34: 99.4 | Y34: 100.22
... M37: 45638 | N37: {=IFERROR(INDEX(X:X,MATCH($M37,$W:$W,0),),N36)} -> 95.18 | O37: {=IFERROR(INDEX(Y:Y,MATCH($M37,$W:$W,0),),O36)} -> 98.3 | P37: {=IFERROR(INDEX(T:T,MATCH(M37,S:S,0),),P36)} -> 3.03 | Q37: {=IFERROR(INDEX(U:U,MATCH($M37,$S:$S,0),),Q36)} -> 117814 | S37: 44445 | T37: 26.08 | U37: 769468 | W37: 44413 | X37: 99.27 | Y37: 100.09
D38: Equity | M38: 45639 | N38: {=IFERROR(INDEX(X:X,MATCH($M38,$W:$W,0),),N37)} -> 95.08 | O38: {=IFERROR(INDEX(Y:Y,MATCH($M38,$W:$W,0),),O37)} -> 98.21 | P38: {=IFERROR(INDEX(T:T,MATCH(M38,S:S,0),),P37)} -> 3.03 | Q38: {=IFERROR(INDEX(U:U,MATCH($M38,$S:$S,0),),Q37)} -> 117814 | S38: 44446 | T38: 25.03 | U38: 799416 | W38: 44410 | X38: 99.35 | Y38: 100.17
M39: 45642 | N39: {=IFERROR(INDEX(X:X,MATCH($M39,$W:$W,0),),N38)} -> 94.97 | O39: {=IFERROR(INDEX(Y:Y,MATCH($M39,$W:$W,0),),O38)} -> 98.1 | P39: {=IFERROR(INDEX(T:T,MATCH(M39,S:S,0),),P38)} -> 3.01 | Q39: {=IFERROR(INDEX(U:U,MATCH($M39,$S:$S,0),),Q38)} -> 119155 | S39: 44447 | T39: 25.56 | U39: 1212306 | W39: 44407 | X39: 99.35 | Y39: 100.17
M40: 45643 | N40: {=IFERROR(INDEX(X:X,MATCH($M40,$W:$W,0),),N39)} -> 95.08 | O40: {=IFERROR(INDEX(Y:Y,MATCH($M40,$W:$W,0),),O39)} -> 98.21 | P40: {=IFERROR(INDEX(T:T,MATCH(M40,S:S,0),),P39)} -> 2.76 | Q40: {=IFERROR(INDEX(U:U,MATCH($M40,$S:$S,0),),Q39)} -> 241144 | S40: 44448 | T40: 24.02 | U40: 2645132 | W40: 44417 | X40: 99.29 | Y40: 100.11
M41: 45644 | N41: {=IFERROR(INDEX(X:X,MATCH($M41,$W:$W,0),),N40)} -> 94.95 | O41: {=IFERROR(INDEX(Y:Y,MATCH($M41,$W:$W,0),),O40)} -> 98.08 | P41: {=IFERROR(INDEX(T:T,MATCH(M41,S:S,0),),P40)} -> 2.56 | Q41: {=IFERROR(INDEX(U:U,MATCH($M41,$S:$S,0),),Q40)} -> 212287 | S41: 44451 | T41: 23.08 | U41: 1084191 | W41: 44414 | X41: 99.27 | Y41: 100.09
M42: 45645 | N42: {=IFERROR(INDEX(X:X,MATCH($M42,$W:$W,0),),N41)} -> 94.89 | O42: {=IFERROR(INDEX(Y:Y,MATCH($M42,$W:$W,0),),O41)} -> 98.01 | P42: {=IFERROR(INDEX(T:T,MATCH(M42,S:S,0),),P41)} -> 2.59 | Q42: {=IFERROR(INDEX(U:U,MATCH($M42,$S:$S,0),),Q41)} -> 343136 | S42: 44452 | T42: 22.13 | U42: 1010019 | W42: 44418 | X42: 99.31 | Y42: 100.13
M43: 45646 | N43: {=IFERROR(INDEX(X:X,MATCH($M43,$W:$W,0),),N42)} -> 94.9 | O43: {=IFERROR(INDEX(Y:Y,MATCH($M43,$W:$W,0),),O42)} -> 98.03 | P43: {=IFERROR(INDEX(T:T,MATCH(M43,S:S,0),),P42)} -> 2.59 | Q43: {=IFERROR(INDEX(U:U,MATCH($M43,$S:$S,0),),Q42)} -> 343136 | S43: 44453 | T43: 22.77 | U43: 1632409 | W43: 44411 | X43: 99.35 | Y43: 100.17
M44: 45649 | N44: {=IFERROR(INDEX(X:X,MATCH($M44,$W:$W,0),),N43)} -> 94.87 | O44: {=IFERROR(INDEX(Y:Y,MATCH($M44,$W:$W,0),),O43)} -> 98 | P44: {=IFERROR(INDEX(T:T,MATCH(M44,S:S,0),),P43)} -> 2.47 | Q44: {=IFERROR(INDEX(U:U,MATCH($M44,$S:$S,0),),Q43)} -> 82291 | S44: 44454 | T44: 23.1 | U44: 1155817 | W44: 44425 | X44: 99.22 | Y44: 100.04
M45: 45650 | N45: {=IFERROR(INDEX(X:X,MATCH($M45,$W:$W,0),),N44)} -> 94.87 | O45: {=IFERROR(INDEX(Y:Y,MATCH($M45,$W:$W,0),),O44)} -> 98 | P45: {=IFERROR(INDEX(T:T,MATCH(M45,S:S,0),),P44)} -> 2.47 | Q45: {=IFERROR(INDEX(U:U,MATCH($M45,$S:$S,0),),Q44)} -> 82291 | S45: 44455 | T45: 21.75 | U45: 4829484 | W45: 44412 | X45: 99.29 | Y45: 100.11
M46: 45651 | N46: {=IFERROR(INDEX(X:X,MATCH($M46,$W:$W,0),),N45)} -> 94.87 | O46: {=IFERROR(INDEX(Y:Y,MATCH($M46,$W:$W,0),),O45)} -> 98 | P46: {=IFERROR(INDEX(T:T,MATCH(M46,S:S,0),),P45)} -> 2.46 | Q46: {=IFERROR(INDEX(U:U,MATCH($M46,$S:$S,0),),Q45)} -> 99974 | S46: 44458 | T46: 21.95 | U46: 806540 | W46: 44420 | X46: 99.34 | Y46: 100.16
M47: 45652 | N47: {=IFERROR(INDEX(X:X,MATCH($M47,$W:$W,0),),N46)} -> 94.87 | O47: {=IFERROR(INDEX(Y:Y,MATCH($M47,$W:$W,0),),O46)} -> 98 | P47: {=IFERROR(INDEX(T:T,MATCH(M47,S:S,0),),P46)} -> 2.4 | Q47: {=IFERROR(INDEX(U:U,MATCH($M47,$S:$S,0),),Q46)} -> 242317 | S47: 44459 | T47: 21.17 | U47: 844450 | W47: 44419 | X47: 99.34 | Y47: 100.16
M48: 45653 | N48: {=IFERROR(INDEX(X:X,MATCH($M48,$W:$W,0),),N47)} -> 94.87 | O48: {=IFERROR(INDEX(Y:Y,MATCH($M48,$W:$W,0),),O47)} -> 98 | P48: {=IFERROR(INDEX(T:T,MATCH(M48,S:S,0),),P47)} -> 2.4 | Q48: {=IFERROR(INDEX(U:U,MATCH($M48,$S:$S,0),),Q47)} -> 242317 | S48: 44460 | T48: 20.64 | U48: 1274400 | W48: 44426 | X48: 99.22 | Y48: 100.04
M49: 45656 | N49: {=IFERROR(INDEX(X:X,MATCH($M49,$W:$W,0),),N48)} -> 94.87 | O49: {=IFERROR(INDEX(Y:Y,MATCH($M49,$W:$W,0),),O48)} -> 98 | P49: {=IFERROR(INDEX(T:T,MATCH(M49,S:S,0),),P48)} -> 2.39 | Q49: {=IFERROR(INDEX(U:U,MATCH($M49,$S:$S,0),),Q48)} -> 188452 | S49: 44461 | T49: 23.09 | U49: 1152100 | W49: 44428 | X49: 99.22 | Y49: 100.04
M50: 45657 | N50: {=IFERROR(INDEX(X:X,MATCH($M50,$W:$W,0),),N49)} -> 94.85 | O50: {=IFERROR(INDEX(Y:Y,MATCH($M50,$W:$W,0),),O49)} -> 97.98 | P50: {=IFERROR(INDEX(T:T,MATCH(M50,S:S,0),),P49)} -> 2.39 | Q50: {=IFERROR(INDEX(U:U,MATCH($M50,$S:$S,0),),Q49)} -> 188452 | S50: 44462 | T50: 22.74 | U50: 1137733 | W50: 44421 | X50: 99.31 | Y50: 100.13
... M229: 45908 | N229: {=IFERROR(INDEX(X:X,MATCH($M229,$W:$W,0),),N228)} -> 88.96 | O229: {=IFERROR(INDEX(Y:Y,MATCH($M229,$W:$W,0),),O228)} -> 92.08 | P229: {=IFERROR(INDEX(T:T,MATCH(M229,S:S,0),),P228)} -> 1.38 | Q229: {=IFERROR(INDEX(U:U,MATCH($M229,$S:$S,0),),Q228)} -> 204840 | S229: 44724 | T229: 4.16 | U229: 1441316 | W229: 44656 | X229: 93.26 | Y229: 96.39
M230: 45909 | O230: {=IFERROR(INDEX(Y:Y,MATCH($M230,$W:$W,0),),O229)} -> 92.63 | P230: {=IFERROR(INDEX(T:T,MATCH(M230,S:S,0),),P229)} -> 1.31 | Q230: {=IFERROR(INDEX(U:U,MATCH($M230,$S:$S,0),),Q229)} -> 1153649 | S230: 44725 | T230: 4.19 | U230: 1127989 | W230: 44658 | X230: 93.17 | Y230: 96.3
M231: 45910 | O231: {=IFERROR(INDEX(Y:Y,MATCH($M231,$W:$W,0),),O230)} -> 92.56 | P231: {=IFERROR(INDEX(T:T,MATCH(M231,S:S,0),),P230)} -> 1.38 | Q231: {=IFERROR(INDEX(U:U,MATCH($M231,$S:$S,0),),Q230)} -> 279690 | S231: 44726 | T231: 4.28 | U231: 739366 | W231: 44664 | X231: 93.19 | Y231: 96.31
M232: 45911 | O232: {=IFERROR(INDEX(Y:Y,MATCH($M232,$W:$W,0),),O231)} -> 92.67 | P232: {=IFERROR(INDEX(T:T,MATCH(M232,S:S,0),),P231)} -> 1.3 | Q232: {=IFERROR(INDEX(U:U,MATCH($M232,$S:$S,0),),Q231)} -> 277457 | S232: 44727 | T232: 4.05 | U232: 2210854 | W232: 44659 | X232: 93.26 | Y232: 96.39
M233: 45912 | O233: {=IFERROR(INDEX(Y:Y,MATCH($M233,$W:$W,0),),O232)} -> 93.2 | P233: {=IFERROR(INDEX(T:T,MATCH(M233,S:S,0),),P232)} -> 1.3 | Q233: {=IFERROR(INDEX(U:U,MATCH($M233,$S:$S,0),),Q232)} -> 277457 | S233: 44728 | T233: 4.14 | U233: 519868 | W233: 44665 | X233: 93.17 | Y233: 96.3
M234: 45915 | O234: {=IFERROR(INDEX(Y:Y,MATCH($M234,$W:$W,0),),O233)} -> 93.21 | P234: {=IFERROR(INDEX(T:T,MATCH(M234,S:S,0),),P233)} -> 1.3 | Q234: {=IFERROR(INDEX(U:U,MATCH($M234,$S:$S,0),),Q233)} -> 277457 | S234: 44697 | T234: 5.97 | U234: 752840 | W234: 44673 | X234: 92.89 | Y234: 96.01
M235: 45916 | O235: {=IFERROR(INDEX(Y:Y,MATCH($M235,$W:$W,0),),O234)} -> 93.26 | P235: {=IFERROR(INDEX(T:T,MATCH(M235,S:S,0),),P234)} -> 1.29 | Q235: {=IFERROR(INDEX(U:U,MATCH($M235,$S:$S,0),),Q234)} -> 364292 | S235: 44732 | T235: 4.07 | U235: 486943 | W235: 44666 | X235: 93.17 | Y235: 96.3
M236: 45917 | O236: {=IFERROR(INDEX(Y:Y,MATCH($M236,$W:$W,0),),O235)} -> 93.33 | P236: {=IFERROR(INDEX(T:T,MATCH(M236,S:S,0),),P235)} -> 1.35 | Q236: {=IFERROR(INDEX(U:U,MATCH($M236,$S:$S,0),),Q235)} -> 330716 | S236: 44733 | T236: 4.23 | U236: 1014088 | W236: 44670 | X236: 93.1 | Y236: 96.16
M237: 45918 | O237: {=IFERROR(INDEX(Y:Y,MATCH($M237,$W:$W,0),),O236)} -> 93.47 | P237: {=IFERROR(INDEX(T:T,MATCH(M237,S:S,0),),P236)} -> 1.3 | Q237: {=IFERROR(INDEX(U:U,MATCH($M237,$S:$S,0),),Q236)} -> 552635 | S237: 44734 | T237: 4.9 | U237: 2857036 | W237: 44676 | X237: 92.86 | Y237: 95.99
M238: 45919 | O238: {=IFERROR(INDEX(Y:Y,MATCH($M238,$W:$W,0),),O237)} -> 93.59 | P238: {=IFERROR(INDEX(T:T,MATCH(M238,S:S,0),),P237)} -> 1.3 | Q238: {=IFERROR(INDEX(U:U,MATCH($M238,$S:$S,0),),Q237)} -> 552635 | S238: 44735 | T238: 5.21 | U238: 1260388 | W238: 44671 | X238: 93.04 | Y238: 96.16
M239: 45922 | O239: {=IFERROR(INDEX(Y:Y,MATCH($M239,$W:$W,0),),O238)} -> 93.68 | P239: {=IFERROR(INDEX(T:T,MATCH(M239,S:S,0),),P238)} -> 1.3 | Q239: {=IFERROR(INDEX(U:U,MATCH($M239,$S:$S,0),),Q238)} -> 483893 | S239: 44738 | T239: 4.56 | U239: 895052 | W239: 44669 | X239: 93.17 | Y239: 96.19
M240: 45923 | O240: {=IFERROR(INDEX(Y:Y,MATCH($M240,$W:$W,0),),O239)} -> 93.8 | P240: {=IFERROR(INDEX(T:T,MATCH(M240,S:S,0),),P239)} -> 1.27 | Q240: {=IFERROR(INDEX(U:U,MATCH($M240,$S:$S,0),),Q239)} -> 182658 | S240: 44739 | T240: 4.62 | U240: 648069 | W240: 44677 | X240: 92.7 | Y240: 95.82
M241: 45924 | O241: {=IFERROR(INDEX(Y:Y,MATCH($M241,$W:$W,0),),O240)} -> 93.89 | P241: {=IFERROR(INDEX(T:T,MATCH(M241,S:S,0),),P240)} -> 1.26 | Q241: {=IFERROR(INDEX(U:U,MATCH($M241,$S:$S,0),),Q240)} -> 214244 | S241: 44740 | T241: 4.5 | U241: 710352 | W241: 44678 | X241: 92.5 | Y241: 95.63
... M268: 45961 | O268: {=IFERROR(INDEX(Y:Y,MATCH($M268,$W:$W,0),),O267)} -> 93.98 | P268: {=IFERROR(INDEX(T:T,MATCH(M268,S:S,0),),P267)} -> 0.92 | Q268: {=IFERROR(INDEX(U:U,MATCH($M268,$S:$S,0),),Q267)} -> 385200 | S268: 44780 | T268: 3.76 | U268: 1594121 | W268: 44721 | X268: 87.45 | Y268: 90.58
G269: =P271/4.25-1 -> -0.79764706 | M269: 45964 | O269: {=IFERROR(INDEX(Y:Y,MATCH($M269,$W:$W,0),),O268)} -> 93.98 | P269: {=IFERROR(INDEX(T:T,MATCH(M269,S:S,0),),P268)} -> 0.91 | Q269: {=IFERROR(INDEX(U:U,MATCH($M269,$S:$S,0),),Q268)} -> 179947 | S269: 44781 | T269: 3.55 | U269: 1297176 | W269: 44714 | X269: 87.85 | Y269: 90.98
M270: 45965 | O270: {=IFERROR(INDEX(Y:Y,MATCH($M270,$W:$W,0),),O269)} -> 93.96 | P270: {=IFERROR(INDEX(T:T,MATCH(M270,S:S,0),),P269)} -> 1.01 | Q270: {=IFERROR(INDEX(U:U,MATCH($M270,$S:$S,0),),Q269)} -> 495982 | S270: 44782 | T270: 4 | U270: 2136543 | W270: 44718 | X270: 87.66 | Y270: 90.79
M271: 45966 | O271: {=IFERROR(INDEX(Y:Y,MATCH($M271,$W:$W,0),),O270)} -> 93.82 | P271: {=IFERROR(INDEX(T:T,MATCH(M271,S:S,0),),P270)} -> 0.86 | Q271: {=IFERROR(INDEX(U:U,MATCH($M271,$S:$S,0),),Q270)} -> 791492 | S271: 44783 | T271: 3.95 | U271: 4018140 | W271: 44722 | X271: 86.38 | Y271: 90.46
M272: 45967 | O272: {=IFERROR(INDEX(Y:Y,MATCH($M272,$W:$W,0),),O271)} -> 94.1 | P272: {=IFERROR(INDEX(T:T,MATCH(M272,S:S,0),),P271)} -> 0.81 | Q272: {=IFERROR(INDEX(U:U,MATCH($M272,$S:$S,0),),Q271)} -> 1384466 | S272: 44784 | T272: 3.63 | U272: 893285 | W272: 44719 | X272: 87.59 | Y272: 90.71
M273: 45968 | O273: {=IFERROR(INDEX(Y:Y,MATCH($M273,$W:$W,0),),O272)} -> 94.11 | P273: {=IFERROR(INDEX(T:T,MATCH(M273,S:S,0),),P272)} -> 0.81 | Q273: {=IFERROR(INDEX(U:U,MATCH($M273,$S:$S,0),),Q272)} -> 1384466 | S273: 44787 | T273: 3.74 | U273: 1097937 | W273: 44715 | X273: 87.77 | Y273: 90.9
M274: 45971 | O274: {=IFERROR(INDEX(Y:Y,MATCH($M274,$W:$W,0),),O273)} -> 94.09 | P274: {=IFERROR(INDEX(T:T,MATCH(M274,S:S,0),),P273)} -> 0.99 | Q274: {=IFERROR(INDEX(U:U,MATCH($M274,$S:$S,0),),Q273)} -> 539365 | S274: 44788 | T274: 3.84 | U274: 2110354 | W274: 44725 | X274: 84.75 | Y274: 88.83
M275: 45972 | O275: {=IFERROR(INDEX(Y:Y,MATCH($M275,$W:$W,0),),O274)} -> 94.09 | P275: {=IFERROR(INDEX(T:T,MATCH(M275,S:S,0),),P274)} -> 0.95 | Q275: {=IFERROR(INDEX(U:U,MATCH($M275,$S:$S,0),),Q274)} -> 195143 | S275: 44789 | T275: 3.5 | U275: 808993 | W275: 44726 | X275: 84.43 | Y275: 88.52
M276: 45973 | O276: {=IFERROR(INDEX(Y:Y,MATCH($M276,$W:$W,0),),O275)} -> 94.15 | P276: {=IFERROR(INDEX(T:T,MATCH(M276,S:S,0),),P275)} -> 0.93 | Q276: {=IFERROR(INDEX(U:U,MATCH($M276,$S:$S,0),),Q275)} -> 243122 | S276: 44790 | T276: 3.64 | U276: 4723556 | W276: 44720 | X276: 87.51 | Y276: 90.64
M277: 45974 | O277: {=IFERROR(INDEX(Y:Y,MATCH($M277,$W:$W,0),),O276)} -> 94.1 | P277: {=IFERROR(INDEX(T:T,MATCH(M277,S:S,0),),P276)} -> 0.91 | Q277: {=IFERROR(INDEX(U:U,MATCH($M277,$S:$S,0),),Q276)} -> 240603 | S277: 44791 | T277: 3.16 | U277: 3073879 | W277: 44728 | X277: 83.66 | Y277: 87.75
M278: 45975 | O278: {=IFERROR(INDEX(Y:Y,MATCH($M278,$W:$W,0),),O277)} -> 94.06 | P278: {=IFERROR(INDEX(T:T,MATCH(M278,S:S,0),),P277)} -> 0.91 | Q278: {=IFERROR(INDEX(U:U,MATCH($M278,$S:$S,0),),Q277)} -> 240603 | S278: 44794 | T278: 3.04 | U278: 1560249 | W278: 44733 | X278: 83.33 | Y278: 87.41
M279: 45978 | O279: {=IFERROR(INDEX(Y:Y,MATCH($M279,$W:$W,0),),O278)} -> 94.06 | P279: {=IFERROR(INDEX(T:T,MATCH(M279,S:S,0),),P278)} -> 0.81 | Q279: {=IFERROR(INDEX(U:U,MATCH($M279,$S:$S,0),),Q278)} -> 232034 | S279: 44795 | T279: 2.97 | U279: 951521 | W279: 44734 | X279: 82.49 | Y279: 86.57
M280: 45979 | O280: {=IFERROR(INDEX(Y:Y,MATCH($M280,$W:$W,0),),O279)} -> 93.98 | P280: {=IFERROR(INDEX(T:T,MATCH(M280,S:S,0),),P279)} -> 0.79 | Q280: {=IFERROR(INDEX(U:U,MATCH($M280,$S:$S,0),),Q279)} -> 176544 | S280: 44796 | T280: 3.07 | U280: 906054 | W280: 44729 | X280: 83.38 | Y280: 87.46
M281: 45980 | O281: {=IFERROR(INDEX(Y:Y,MATCH($M281,$W:$W,0),),O280)} -> 93.96 | P281: {=IFERROR(INDEX(T:T,MATCH(M281,S:S,0),),P280)} -> 0.76 | Q281: {=IFERROR(INDEX(U:U,MATCH($M281,$S:$S,0),),Q280)} -> 197648 | S281: 44797 | T281: 3.12 | U281: 767639 | W281: 44727 | X281: 84.12 | Y281: 88.2
... M357: 46086 | O357: {=IFERROR(INDEX(Y:Y,MATCH($M357,$W:$W,0),),O356)} -> 92.82 | P357: {=IFERROR(INDEX(T:T,MATCH(M357,S:S,0),),P356)} -> 0.83 | Q357: {=IFERROR(INDEX(U:U,MATCH($M357,$S:$S,0),),Q356)} -> 209852 | S357: 44909 | T357: 2.97 | U357: 564548 | W357: 44844 | X357: 75.71 | Y357: 79.79
S358: 44910 | T358: 2.89 | U358: 686920 | W358: 44839 | X358: 75.63 | Y358: 79.72
S359: 44913 | T359: 2.82 | U359: 721635 | W359: 44837 | X359: 75.56 | Y359: 79.64
S360: 44914 | T360: 2.73 | U360: 764341 | W360: 44845 | X360: 75.84 | Y360: 79.92
S361: 44915 | T361: 2.68 | U361: 495900 | W361: 44873 | X361: 77.53 | Y361: 81.61
S362: 44916 | T362: 2.63 | U362: 568581 | W362: 44846 | X362: 75.89 | Y362: 79.98
S363: 44917 | T363: 2.66 | U363: 525105 | W363: 44840 | X363: 75.73 | Y363: 79.81
S364: 44921 | T364: 2.56 | U364: 318515 | W364: 44848 | X364: 75.91 | Y364: 80
S365: 44922 | T365: 2.54 | U365: 528424 | W365: 44874 | X365: 77.54 | Y365: 81.63
S366: 44923 | T366: 2.83 | U366: 578755 | W366: 44851 | X366: 75.97 | Y366: 80.06
S367: 44924 | T367: 2.82 | U367: 898414 | W367: 44847 | X367: 75.91 | Y367: 80
S368: 44928 | T368: 2.62 | U368: 707310 | W368: 44875 | X368: 77.04 | Y368: 81.13
S369: 44929 | T369: 2.77 | U369: 654881 | W369: 44876 | X369: 76.99 | Y369: 81.08
... S885: 45683 | T885: 2.54 | U885: 239883 | W885: 45602 | X885: 92.2 | Y885: 95.32
S886: 45684 | T886: 2.5 | U886: 80727 | W886: 45603 | X886: 92.22 | Y886: 95.35 | AA886: 45603 | AB886: 95.35
S887: 45685 | T887: 2.52 | U887: 114309 | W887: 45604 | X887: 92.31 | Y887: 95.44 | AA887: 45604 | AB887: 95.44
S888: 45686 | T888: 2.52 | U888: 76242 | W888: 45607 | X888: 92.31 | Y888: 95.44 | AA888: 45607 | AB888: 95.44
S889: 45687 | T889: 2.44 | U889: 182800 | W889: 45608 | X889: 92.16 | Y889: 95.29 | AA889: 45608 | AB889: 95.29
S890: 45690 | T890: 2.37 | U890: 296828 | W890: 45609 | X890: 92.03 | Y890: 95.16 | AA890: 45609 | AB890: 95.16
S891: 45691 | T891: 2.37 | U891: 98340 | W891: 45610 | X891: 91.96 | Y891: 95.09 | AA891: 45610 | AB891: 95.09
S892: 45692 | T892: 2.41 | U892: 90557 | W892: 45611 | X892: 91.95 | Y892: 95.08 | AA892: 45611 | AB892: 95.08
S893: 45693 | T893: 2.45 | U893: 63416 | W893: 45614 | X893: 91.94 | Y893: 95.07 | AA893: 45614 | AB893: 95.07
S894: 45694 | T894: 2.38 | U894: 94386 | W894: 45615 | X894: 91.9 | Y894: 95.03 | AA894: 45615 | AB894: 95.03
S895: 45697 | T895: 2.41 | U895: 89242 | W895: 45616 | X895: 91.91 | Y895: 95.04 | AA895: 45616 | AB895: 95.04
S896: 45698 | T896: 2.48 | U896: 109310 | W896: 45617 | X896: 91.89 | Y896: 95.02 | AA896: 45617 | AB896: 95.02
S897: 45699 | T897: 2.45 | U897: 80981 | W897: 45618 | X897: 91.86 | Y897: 94.98 | AA897: 45618 | AB897: 94.98
... S1103: 46005 | T1103: 1.02 | U1103: 435401 | W1103: 45908 | X1103: 88.96 | Y1103: 92.08 | AA1103: 45908 | AB1103: 92.08
S1104: 46006 | T1104: 1.08 | U1104: 495156 | W1104: 45909 | Y1104: 92.63 | AA1104: 45909 | AB1104: 92.63
...

Sheet Holders
D3: Traeger Pellet Grills | G3: DRAFT
D4: Debt Holders | G4: CONFIDENTIAL
D5: Updated 3/13/2026
D7: 1L Term Loan
D8: # | E8: Holder | F8: Amt. ($mm) | G8: %
D9: 1 | E9: PGIM | F9: 49.858945 | G9: =F9/$F$20 -> 0.12361977
D10: 2 | E10: Fidelity | F10: 18.747001 | G10: =F10/$F$20 -> 0.046481128
D11: 3 | E11: Birch Grove Capital | F11: 9.00364 | G11: =F11/$F$20 -> 0.022323536
D12: 4 | E12: CarVal AB | F12: 6.577994 | G12: =F12/$F$20 -> 0.016309413
D13: 5 | E13: MidOcean Partners | F13: 5.998761 | G13: =F13/$F$20 -> 0.014873268
D14: 6 | E14: Crescent Capital Group | F14: 4.979368 | G14: =F14/$F$20 -> 0.012345796
D15: 7 | E15: American Money Management | F15: 4.284899 | G15: =F15/$F$20 -> 0.010623936
D16: 8 | E16: PIMCO | F16: 3.56557 | G16: =F16/$F$20 -> 0.0088404389
D17: 9 | E17: Octagon Credit Investors | F17: 2.973691 | G17: =F17/$F$20 -> 0.0073729399
D18: 10 | E18: Blackstone | F18: 2.898038 | G18: =F18/$F$20 -> 0.0071853666
E19: Other | F19: =SUM(F20-SUM(F9:F18)) -> 294.43709 | G19: =F19 / $F$20 -> 0.7300244
E20: Total | F20: ='Capital Structure'!G17 -> 403.325 | G20: =SUM(G9:G19) -> 1
D22: Equity Holders
D23: # | E23: Holder | F23: Amt. ($mm) | G23: %
D24: 1 | E24: AEA Investors | F24: =G24*$F$35 -> 25.794375 | G24: 0.2442
D25: 2 | E25: Ontario Teachers' Pension Plan Board | F25: =G25*$F$35 -> 19.00249 | G25: 0.1799
D26: 3 | E26: Andrus Jeremy | F26: =G26*$F$35 -> 12.939439 | G26: =10.37%+1.88% -> 0.1225
D27: 4 | E27: Vanguard | F27: =G27*$F$35 -> 2.5456365 | G27: 0.0241
D28: 5 | E28: BlackRock | F28: =G28*$F$35 -> 2.0069333 | G28: 0.019
D29: 6 | E29: Artisan Partners | F29: =G29*$F$35 -> 1.5421698 | G29: 0.0146
D30: 7 | E30: Blosil Dominic | F30: =G30*$F$35 -> 1.1302203 | G30: 0.0107
D31: 8 | E31: First Sabrepoint Capital Management | F31: =G31*$F$35 -> 0.94008982 | G31: 0.0089
D32: 9 | E32: Geode Capital Management | F32: =G32*$F$35 -> 0.80277333 | G32: 0.0076
D33: 10 | E33: Glendon Capital Management | F33: =G33*$F$35 -> 0.78164772 | G33: 0.0074
E34: Other | F34: =G34*$F$35 -> 38.142296 | G34: =G35-SUM(G24:G33) -> 0.3611
E35: Total | F35: ='Capital Structure'!G23 -> 105.62807 | G35: 1

Sheet A&E Timeline
B2: Holiday | D2: Close
J5: March 2026 | R5: April 2026 | Z5: May 2026 | AH5: June 2026
J6: S | K6: M | L6: T | M6: W | N6: T | O6: F | P6: S | R6: S | S6: M | T6: T | U6: W | V6: T | W6: F | X6: S | Z6: S | AA6: M | AB6: T | AC6: W | AD6: T | AE6: F | AF6: S | AH6: S | AI6: M | AJ6: T | AK6: W | AL6: T | AM6: F | AN6: S | AP6: =$D$2 -> Close | AQ6: =$D$9 | AR6: =$D$16 | AS6: =$D$23 | AT6: =$D$30 | AU6: =$D$37 | AV6: =$D$44 | AW6: =$G$2 | AX6: =$G$9 | AY6: =$G$16 | AZ6: =$G$23 | BA6: =$G$30 | BB6: =$G$37 | BC6: =$G$44 -> 0
J7: 46082 | K7: 46083 | L7: 46084 | M7: 46085 | N7: 46086 | O7: 46087 | P7: 46088 | U7: 46113 | V7: 46114 | W7: 46115 | X7: 46116 | AE7: 46143 | AF7: 46144 | AI7: 46174 | AJ7: 46175 | AK7: 46176 | AL7: 46177 | AM7: 46178 | AN7: 46179
J8: 46089 | K8: 46090 | L8: 46091 | M8: 46092 | N8: 46093 | O8: 46094 | P8: 46095 | R8: 46117 | S8: 46118 | T8: 46119 | U8: 46120 | V8: 46121 | W8: 46122 | X8: 46123 | Z8: 46145 | AA8: 46146 | AB8: 46147 | AC8: 46148 | AD8: 46149 | AE8: 46150 | AF8: 46151 | AH8: 46180 | AI8: 46181 | AJ8: 46182 | AK8: 46183 | AL8: 46184 | AM8: 46185 | AN8: 46186
J9: 46096 | K9: 46097 | L9: 46098 | M9: 46099 | N9: 46100 | O9: 46101 | P9: 46102 | R9: 46124 | S9: 46125 | T9: 46126 | U9: 46127 | V9: 46128 | W9: 46129 | X9: 46130 | Z9: 46152 | AA9: 46153 | AB9: 46154 | AC9: 46155 | AD9: 46156 | AE9: 46157 | AF9: 46158 | AH9: 46187 | AI9: 46188 | AJ9: 46189 | AK9: 46190 | AL9: 46191 | AM9: 46192 | AN9: 46193
J10: 46103 | K10: 46104 | L10: 46105 | M10: 46106 | N10: 46107 | O10: 46108 | P10: 46109 | R10: 46131 | S10: 46132 | T10: 46133 | U10: 46134 | V10: 46135 | W10: 46136 | X10: 46137 | Z10: 46159 | AA10: 46160 | AB10: 46161 | AC10: 46162 | AD10: 46163 | AE10: 46164 | AF10: 46165 | AH10: 46194 | AI10: 46195 | AJ10: 46196 | AK10: 46197 | AL10: 46198 | AM10: 46199 | AN10: 46200
J11: 46110 | K11: 46111 | L11: 46112 | R11: 46138 | S11: 46139 | T11: 46140 | U11: 46141 | V11: 46142 | Z11: 46166 | AA11: 46167 | AB11: 46168 | AC11: 46169 | AD11: 46170 | AE11: 46171 | AF11: 46172 | AH11: 46201 | AI11: 46202 | AJ11: 46203
Z12: 46173
