Workbook

Sheet Capital Structure
C3: Xerox Holdings Corporation | D3: Today | E3: =TODAY() | S3: DRAFT
C4: Capital Structure | S4: CONFIDENTIAL
C5: 46203
C6: ($ millions)
D8: Face | E8: Leverage | F8: Interest | G8: Effective | H8: Annual | J8: Credit | K8: Trading | M8: Market | N8: Leverage | Q8: Effective Rate Calculation
C9: Description | D9: Value | E9: (Face) | F9: Rate | G9: Rate | H9: Interest | I9: Maturity | J9: Rating | K9: Price | L9: YTM | M9: Value | N9: (Market) | Q9: SOFR | R9: Spread | S9: Effective
C11: ABL Revolving Credit Facility ($425mm) | D11: 0 | E11: =(D11)/$D$30 | F11: 150 | G11: =S11 | H11: =D11*G11 | I11: 46895 | J11: NA | K11: NA | L11: NA | M11: NA | N11: =E11 | Q11: 0.0387 | R11: 0.015 | S11: =SUM(Q11:R11)
C12: IPCo JV Secured Term Loans ($405mm) | D12: 405 | E12: =(D11+D12)/$D$30 | F12: 812.5 | G12: =S12 | H12: =D12*G12 | I12: 47896 | J12: NA | K12: NA | L12: NA | M12: NA | N12: =E12 | Q12: =Q11 | R12: 0.08125 | S12: =SUM(Q12:R12)
C13: IPCo Class A Units ($45mm) | D13: 45 | E13: =(D11+D12+D13)/$D$30 | F13: NA | G13: NA | H13: NA | I13: NA | J13: NA | K13: NA | L13: NA | M13: NA | N13: =E13
C14: 1L Term Loan B ($705mm) | D14: 705 | E14: =(D11+D12+D13+D14)/$D$30 | F14: 400 | G14: =S14 | H14: =D14*G14 | I14: 47439 | J14: NA | K14: NA | L14: NA | M14: NA | N14: =E14 | Q14: =Q11 | R14: 0.04 | S14: =SUM(Q14:R14)
C15: 1L Senior Secured Notes ($400mm) | D15: 400 | E15: =(D11+D12+D13+D14+D15)/$D$30 | F15: 0.1025 | G15: =F15 | H15: =D15*G15 | I15: 47771 | J15: NA / B | K15: NA | L15: NA | M15: NA | N15: =E15
C16: 2L Senior Secured Notes ($494mm) | D16: 494 | E16: =(D11+D12+D13+D14+D15+D16)/$D$30 | F16: 0.135 | G16: =F16 | H16: =D16*G16 | I16: 47953 | J16: NA / CCC+ | K16: NA | L16: NA | M16: NA | N16: =E16
C17: Total Secured Debt | D17: =SUM(D11:D16) | E17: =D17/$D$30 | H17: =SUM(H11:H16) | N17: =D17/$D$30
C18: Senior Unsecured Notes due 2028 ($556mm) | D18: 556 | E18: =(D11+D12+D13+D14+D15+D16+D18)/$D$30 | F18: 0.055 | G18: =F18 | H18: =D18*G18 | I18: 46980 | J18: NA | K18: 58.6 | L18: NA | M18: =D18*K18/100 | N18: =E18
C19: Senior Unsecured Notes due 2029 ($500mm) | D19: 500 | E19: =(D11+D12+D13+D14+D15+D16+D18+D19)/$D$30 | F19: 0.08875 | G19: =F19 | H19: =D19*G19 | I19: 47452 | J19: NA / CCC | K19: 40.9 | L19: NA | M19: =D19*K19/100 | N19: =E19
C20: Convertible Senior Notes 2030 ($400mm) | D20: 400 | E20: =(D11+D12+D13+D14+D15+D16+D18+D19+D20)/$D$30 | F20: 0.0375 | G20: =F20 | H20: =D20*G20 | I20: 47557 | J20: NA / CCC | K20: NA | L20: NA | M20: NA | N20: =E20
C21: Step-Up Senior Notes due 2030 ($250mm) | D21: 250 | E21: =(D11+D12+D13+D14+D15+D16+D18+D19+D20+D21)/$D$30 | F21: 0.135 | G21: =F21 | H21: =D21*G21 | I21: 47665 | J21: Caa3 / NA | K21: NA | L21: NA | M21: NA | N21: =E21
C22: Xerox Corp. Senior Notes 2035 ($250mm) | D22: 250 | E22: =(D11+D12+D13+D14+D15+D16+D18+D19+D20+D21+D22)/$D$30 | F22: 0.048 | G22: =F22 | H22: =D22*G22 | I22: 49369 | J22: NA / CCC | K22: NA | L22: NA | M22: NA | N22: =E22
C23: Xerox Corp. Senior Notes 2039 ($350mm) | D23: 350 | E23: =(D11+D12+D13+D14+D15+D16+D18+D19+D20+D21+D22+D23)/$D$30 | F23: 0.0675 | G23: =F23 | H23: =D23*G23 | I23: 51119 | J23: NA / CCC | K23: NA | L23: NA | M23: NA | N23: =E23
C24: Total Debt | D24: =SUM(D17:D23) | E24: =D24/$D$30 | H24: =SUM(H17:H23) | N24: =D24/$D$30
C25: Less: Cash & Cash Equivalents | D25: -495 | E25: =D25/$D$30
C26: Net Debt | D26: =SUM(D24:D25) | E26: =D26/$D$30 | H26: =SUM(H24:H25) | N26: =D26/$D$30
C27: Series A Conv. Preferred ($180mm) | D27: 180 | E27: =(D11+D12+D13+D14+D15+D16+D18+D19+D20+D21+D22+D23+D27)/$D$30 | F27: 0.08 | G27: =F27 | H27: =D27*G27 | I27: NA | J27: NA | K27: NA | L27: NA | M27: NA | N27: =E27
C28: Net Debt & Preferred Equity | D28: =SUM(D26:D27) | E28: =D28/$D$30 | H28: =SUM(H26:H27) | N28: =D28/$D$30
C30: Memo: LTM 2Q'26 Adj. EBITDA | D30: 719
C32: ABL Commitments | D32: 425
C33: Less: Borrowing Base Limitation | D33: -37
C34: Less: Outstanding Borrowings | D34: =-D11
C35: Less: Letters of Credit | D35: -112
C36: ABL Availability | D36: =SUM(D32:D35)
C37: Plus: Cash and Equivalents | D37: =-D25
C38: Total Liquidity | D38: =SUM(D36:D37)
C40: Source: 2Q'26 10-Q (filed 6-Aug-26) and 2Q'26 earnings deck. Principal shown; B/S carrying value $4,223m (net of ~$134m OID/fees). Excl. $90m tariff-monetization liability.
C41: Tie-out: 1Q'26 principal $4,581m less 2Q'26 activity ($125m 2026 notes repaid; $93m 2028s and $6m 2Ls repurchased) = ~$4,357m vs. $4,355m shown.
C42: IPCo JV (Feb-26, TPG): $405m TL + $45m Class A Units at XRX Brandco Holdings, secured by contributed IP; company treats both as debt. Units have no stated rate / maturity.
C43: ~$1.3bn of debt funds the finance-receivables book; core debt ~$2.9bn. Mgmt gross / net leverage 5.9x / 5.1x (carrying value).
C44: LTM Adj. EBITDA includes a $105m IEEPA tariff-refund benefit; excl. it EBITDA is $614m (~7.1x gross leverage on principal).
C45: Ratings: Moody's CFR Caa2 / neg. (Mar-26); S&P CCC+ / neg. (16-Jun-26, restored from SD after the below-par 2028 note buyback). Issue ratings Moody's / S&P.
C46: Feb-26 warrants ($8.00 strike, exp. Feb-28) can be exercised by tendering designated notes at par; uptake to date minimal.
C47: Prices: indicative TRACE-based quotes, early Oct-26 (not Bloomberg/Octus). SOFR 3.87% (13-Oct-26). XRX equity ~$3.06 (30-Aug-26).

Sheet Pricing
B3: NA - no pricing source found

Sheet Maturity Schedule
C2: Xerox Holdings Corporation | J2: DRAFT
C3: Maturity Schedule | J3: CONFIDENTIAL
C4: Updated as of 06/30/2026
C5: ($ millions)
D7: Liquidity | E7: 2028 | F7: 2029 | G7: 2030 | H7: 2031 | I7: 2035 | J7: 2039
C8: Cash & Equivalents | D8: ='Capital Structure'!$D$37
C9: ABL Availability | D9: ='Capital Structure'!$D$36
C10: Secured Term Loan | E10: =SUMIFS('Capital Structure'!$D$12:$D$12,'Capital Structure'!$I$12:$I$12,">="&DATE(E$7,1,1),'Capital Structure'!$I$12:$I$12,"<="&DATE(E$7,12,31)) | F10: =SUMIFS('Capital Structure'!$D$12:$D$12,'Capital Structure'!$I$12:$I$12,">="&DATE(F$7,1,1),'Capital Structure'!$I$12:$I$12,"<="&DATE(F$7,12,31)) | G10: =SUMIFS('Capital Structure'!$D$12:$D$12,'Capital Structure'!$I$12:$I$12,">="&DATE(G$7,1,1),'Capital Structure'!$I$12:$I$12,"<="&DATE(G$7,12,31)) | H10: =SUMIFS('Capital Structure'!$D$12:$D$12,'Capital Structure'!$I$12:$I$12,">="&DATE(H$7,1,1),'Capital Structure'!$I$12:$I$12,"<="&DATE(H$7,12,31)) | I10: =SUMIFS('Capital Structure'!$D$12:$D$12,'Capital Structure'!$I$12:$I$12,">="&DATE(I$7,1,1),'Capital Structure'!$I$12:$I$12,"<="&DATE(I$7,12,31)) | J10: =SUMIFS('Capital Structure'!$D$12:$D$12,'Capital Structure'!$I$12:$I$12,">="&DATE(J$7,1,1),'Capital Structure'!$I$12:$I$12,"<="&DATE(J$7,12,31))
C11: 1L Term Loan | E11: =SUMIFS('Capital Structure'!$D$14:$D$14,'Capital Structure'!$I$14:$I$14,">="&DATE(E$7,1,1),'Capital Structure'!$I$14:$I$14,"<="&DATE(E$7,12,31)) | F11: =SUMIFS('Capital Structure'!$D$14:$D$14,'Capital Structure'!$I$14:$I$14,">="&DATE(F$7,1,1),'Capital Structure'!$I$14:$I$14,"<="&DATE(F$7,12,31)) | G11: =SUMIFS('Capital Structure'!$D$14:$D$14,'Capital Structure'!$I$14:$I$14,">="&DATE(G$7,1,1),'Capital Structure'!$I$14:$I$14,"<="&DATE(G$7,12,31)) | H11: =SUMIFS('Capital Structure'!$D$14:$D$14,'Capital Structure'!$I$14:$I$14,">="&DATE(H$7,1,1),'Capital Structure'!$I$14:$I$14,"<="&DATE(H$7,12,31)) | I11: =SUMIFS('Capital Structure'!$D$14:$D$14,'Capital Structure'!$I$14:$I$14,">="&DATE(I$7,1,1),'Capital Structure'!$I$14:$I$14,"<="&DATE(I$7,12,31)) | J11: =SUMIFS('Capital Structure'!$D$14:$D$14,'Capital Structure'!$I$14:$I$14,">="&DATE(J$7,1,1),'Capital Structure'!$I$14:$I$14,"<="&DATE(J$7,12,31))
C12: 1L Notes | E12: =SUMIFS('Capital Structure'!$D$15:$D$15,'Capital Structure'!$I$15:$I$15,">="&DATE(E$7,1,1),'Capital Structure'!$I$15:$I$15,"<="&DATE(E$7,12,31)) | F12: =SUMIFS('Capital Structure'!$D$15:$D$15,'Capital Structure'!$I$15:$I$15,">="&DATE(F$7,1,1),'Capital Structure'!$I$15:$I$15,"<="&DATE(F$7,12,31)) | G12: =SUMIFS('Capital Structure'!$D$15:$D$15,'Capital Structure'!$I$15:$I$15,">="&DATE(G$7,1,1),'Capital Structure'!$I$15:$I$15,"<="&DATE(G$7,12,31)) | H12: =SUMIFS('Capital Structure'!$D$15:$D$15,'Capital Structure'!$I$15:$I$15,">="&DATE(H$7,1,1),'Capital Structure'!$I$15:$I$15,"<="&DATE(H$7,12,31)) | I12: =SUMIFS('Capital Structure'!$D$15:$D$15,'Capital Structure'!$I$15:$I$15,">="&DATE(I$7,1,1),'Capital Structure'!$I$15:$I$15,"<="&DATE(I$7,12,31)) | J12: =SUMIFS('Capital Structure'!$D$15:$D$15,'Capital Structure'!$I$15:$I$15,">="&DATE(J$7,1,1),'Capital Structure'!$I$15:$I$15,"<="&DATE(J$7,12,31))
C13: 2L Notes | E13: =SUMIFS('Capital Structure'!$D$16:$D$16,'Capital Structure'!$I$16:$I$16,">="&DATE(E$7,1,1),'Capital Structure'!$I$16:$I$16,"<="&DATE(E$7,12,31)) | F13: =SUMIFS('Capital Structure'!$D$16:$D$16,'Capital Structure'!$I$16:$I$16,">="&DATE(F$7,1,1),'Capital Structure'!$I$16:$I$16,"<="&DATE(F$7,12,31)) | G13: =SUMIFS('Capital Structure'!$D$16:$D$16,'Capital Structure'!$I$16:$I$16,">="&DATE(G$7,1,1),'Capital Structure'!$I$16:$I$16,"<="&DATE(G$7,12,31)) | H13: =SUMIFS('Capital Structure'!$D$16:$D$16,'Capital Structure'!$I$16:$I$16,">="&DATE(H$7,1,1),'Capital Structure'!$I$16:$I$16,"<="&DATE(H$7,12,31)) | I13: =SUMIFS('Capital Structure'!$D$16:$D$16,'Capital Structure'!$I$16:$I$16,">="&DATE(I$7,1,1),'Capital Structure'!$I$16:$I$16,"<="&DATE(I$7,12,31)) | J13: =SUMIFS('Capital Structure'!$D$16:$D$16,'Capital Structure'!$I$16:$I$16,">="&DATE(J$7,1,1),'Capital Structure'!$I$16:$I$16,"<="&DATE(J$7,12,31))
C14: Senior Unsecured Notes | E14: =SUMIFS('Capital Structure'!$D$18:$D$23,'Capital Structure'!$I$18:$I$23,">="&DATE(E$7,1,1),'Capital Structure'!$I$18:$I$23,"<="&DATE(E$7,12,31)) | F14: =SUMIFS('Capital Structure'!$D$18:$D$23,'Capital Structure'!$I$18:$I$23,">="&DATE(F$7,1,1),'Capital Structure'!$I$18:$I$23,"<="&DATE(F$7,12,31)) | G14: =SUMIFS('Capital Structure'!$D$18:$D$23,'Capital Structure'!$I$18:$I$23,">="&DATE(G$7,1,1),'Capital Structure'!$I$18:$I$23,"<="&DATE(G$7,12,31)) | H14: =SUMIFS('Capital Structure'!$D$18:$D$23,'Capital Structure'!$I$18:$I$23,">="&DATE(H$7,1,1),'Capital Structure'!$I$18:$I$23,"<="&DATE(H$7,12,31)) | I14: =SUMIFS('Capital Structure'!$D$18:$D$23,'Capital Structure'!$I$18:$I$23,">="&DATE(I$7,1,1),'Capital Structure'!$I$18:$I$23,"<="&DATE(I$7,12,31)) | J14: =SUMIFS('Capital Structure'!$D$18:$D$23,'Capital Structure'!$I$18:$I$23,">="&DATE(J$7,1,1),'Capital Structure'!$I$18:$I$23,"<="&DATE(J$7,12,31))
C15: Total | D15: =SUM(D8:D14) | E15: =SUM(E8:E14) | F15: =SUM(F8:F14) | G15: =SUM(G8:G14) | H15: =SUM(H8:H14) | I15: =SUM(I8:I14) | J15: =SUM(J8:J14)
