Workbook

Sheet Cover Page
A1: Return to Cover
C2: Xerox Holdings Corporation (NASDAQ: XRX) – Restructuring Model
C3: All $ in Millions (USD), except Per-Share Values
C6: XEROX HOLDINGS CORPORATION
C7: Credit & Restructuring Analysis
C13: Last Updated | D13: =TODAY() | H13: Data As Of | I13: 2Q'26 (June 30, 2026)
C15: Color Coding | D15: R | E15: G | F15: B | H15: Links (Ctrl + [ to Jump to Sheet)
C16: Formulas | D16: 0 | E16: 0 | F16: 0 | H16: Financial Statements
C17: Hard-Code | D17: 0 | E17: 0 | F17: 255 | H17: ='IS'!A1
C18: Link to Other Sheets | D18: 0 | E18: 128 | F18: 0 | H18: ='IS Out'!A1
C19: Highlight Value (Check) | D19: 255 | E19: 0 | F19: 0 | H19: ='CFS'!A1
H20: ='CFS Out'!A1
C21: Heading 1 | D21: 0 | E21: 32 | F21: 96 | H21: ='BS'!A1
C22: Heading 2 | D22: 128 | E22: 128 | F22: 128 | H22: ='BS Out'!A1
H23: Credit Analysis
C24: Input/Driver | D24: 255 | E24: 242 | F24: 204 | H24: ='NWC'!A1
H25: ='Quarterly NWC'!A1
C26: Sources | H26: ='Capital Structure'!A1
C27: SEC EDGAR – Xerox 10-K & 10-Q Filings | H27: ='Maturity Schedule'!A1
C28: Xerox Investor Relations – Earnings Materials | H28: ='Pricing'!A1
C29: Moody's & S&P Rating Actions | H29: References
C30: TRACE-Based Bond Quotes (Indicative) | H30: ='Sources'!A1
C31: Federal Reserve Bank of New York – SOFR
C32: Note: All Financials Pulled from Xerox 10-Qs & 10-Ks

Sheet Financial Statements >
A1: Financial Statements > | B1: ='Cover Page'!A1

Sheet IS
A1: =D3 | B1: ='Cover Page'!A1
D3: Historical Income Statement
D4: Xerox Holdings Corporation – All values in $ millions (USD), except per-share values. Data as of June 30, 2026 (2Q'26); fiscal year ends December 31.
A5: x | D5: Income Statement | E5: Quarter Ended | AB5: Fiscal Year Ended December 31, | AH5: LTM
E6: 1 | F6: 2 | G6: 3 | H6: 4 | I6: 1 | J6: 2 | K6: 3 | L6: 4 | M6: 1 | N6: 2 | O6: 3 | P6: 4 | Q6: 1 | R6: 2 | S6: 3 | T6: 4 | U6: 1 | V6: 2 | W6: 3 | X6: 4 | Y6: 1 | Z6: 2
E7: 2021 | F7: 2021 | G7: 2021 | H7: 2021 | I7: 2022 | J7: 2022 | K7: 2022 | L7: 2022 | M7: 2023 | N7: 2023 | O7: 2023 | P7: 2023 | Q7: 2024 | R7: 2024 | S7: 2024 | T7: 2024 | U7: 2025 | V7: 2025 | W7: 2025 | X7: 2025 | Y7: 2026 | Z7: 2026 | AB7: 2021 | AC7: 2022 | AD7: 2023 | AE7: 2024 | AF7: 2025
E8: 44286 | F8: 44377 | G8: 44469 | H8: 44561 | I8: 44651 | J8: 44742 | K8: 44834 | L8: 44926 | M8: 45016 | N8: 45107 | O8: 45199 | P8: 45291 | Q8: 45382 | R8: 45473 | S8: 45565 | T8: 45657 | U8: 45747 | V8: 45838 | W8: 45930 | X8: 46022 | Y8: 46112 | Z8: 46203 | AB8: 44561 | AC8: 44926 | AD8: 45291 | AE8: 45657 | AF8: 46022 | AH8: 45838 | AI8: 46203
E9: =E6&"Q'"&RIGHT(E7,2) | F9: =F6&"Q'"&RIGHT(F7,2) | G9: =G6&"Q'"&RIGHT(G7,2) | H9: =H6&"Q'"&RIGHT(H7,2) | I9: =I6&"Q'"&RIGHT(I7,2) | J9: =J6&"Q'"&RIGHT(J7,2) | K9: =K6&"Q'"&RIGHT(K7,2) | L9: =L6&"Q'"&RIGHT(L7,2) | ... Z9: =Z6&"Q'"&RIGHT(Z7,2) | AB9: FY2021 | AC9: FY2022 | AD9: FY2023 | AE9: FY2024 | AF9: FY2025 | AH9: LTM 2Q'25 | AI9: LTM 2Q'26
D11: Sales | E11: 602 | F11: 670 | G11: 657 | H11: =AB11-SUM(E11:G11) | I11: 592 | J11: 667 | K11: 690 | L11: =AC11-SUM(I11:K11) | M11: 659 | N11: 696 | O11: 644 | P11: =AD11-SUM(M11:O11) | Q11: 523 | R11: 611 | S11: 588 | T11: =AE11-SUM(Q11:S11) | U11: 557 | V11: 665 | W11: 993 | X11: =AF11-SUM(U11:W11) | Y11: 920 | Z11: 996 | AB11: 2582 | AC11: 2800 | AD11: 2720 | AE11: 2378 | AF11: 3283 | AH11: =SUM(S11:V11) | AI11: =SUM(W11:Z11)
D12: Services, maintenance, rentals and other | E12: =1053+55 | F12: =1067+56 | G12: =1046+55 | H12: =AB12-SUM(E12:G12) | I12: =1023+53 | J12: =1028+52 | K12: =1010+51 | L12: =AC12-SUM(I12:K12) | M12: =1004+52 | N12: =1009+49 | O12: =962+46 | P12: =AD12-SUM(M12:O12) | Q12: 979 | R12: 967 | S12: 940 | T12: =AE12-SUM(Q12:S12) | U12: 900 | V12: 911 | W12: 968 | X12: =AF12-SUM(U12:W12) | Y12: 926 | Z12: 926 | AB12: =4235+221 | AC12: =4100+207 | AD12: 4166 | AE12: 3843 | AF12: 3739 | AH12: =SUM(S12:V12) | AI12: =SUM(W12:Z12)
D13: Total revenues | E13: =E11+E12 | F13: =F11+F12 | G13: =G11+G12 | H13: =H11+H12 | I13: =I11+I12 | J13: =J11+J12 | K13: =K11+K12 | L13: =L11+L12 | ... Z13: =Z11+Z12 | AB13: =AB11+AB12 | AC13: =AC11+AC12 | AD13: =AD11+AD12 | AE13: =AE11+AE12 | AF13: =AF11+AF12 | AH13: =AH11+AH12 | AI13: =AI11+AI12
D14: Total revenues (reported) | E14: 1710 | F14: 1793 | G14: 1758 | H14: 1777 | I14: 1668 | J14: 1747 | K14: 1751 | L14: 1941 | M14: 1715 | N14: 1754 | O14: 1652 | P14: 1765 | Q14: 1502 | R14: 1578 | S14: 1528 | T14: 1613 | U14: 1457 | V14: 1576 | W14: 1961 | X14: 2028 | Y14: 1846 | Z14: 1922 | AB14: 7038 | AC14: 7107 | AD14: 6886 | AE14: 6221 | AF14: 7022
D15: Check | E15: =E13-E14 | F15: =F13-F14 | G15: =G13-G14 | H15: =H13-H14 | I15: =I13-I14 | J15: =J13-J14 | K15: =K13-K14 | L15: =L13-L14 | ... Z15: =Z13-Z14 | AB15: =AB13-AB14 | AC15: =AC13-AC14 | AD15: =AD13-AD14 | AE15: =AE13-AE14 | AF15: =AF13-AF14
D17: Cost of sales | E17: 420 | F17: 468 | G17: 498 | H17: =AB17-SUM(E17:G17) | I17: 435 | J17: 487 | K17: 508 | L17: =AC17-SUM(I17:K17) | M17: 425 | N17: 452 | O17: 435 | P17: =AD17-SUM(M17:O17) | Q17: 340 | R17: 387 | S17: 390 | T17: =AE17-SUM(Q17:S17) | U17: 382 | V17: 480 | W17: 788 | X17: =AF17-SUM(U17:W17) | Y17: 600 | Z17: 579 | AB17: 1862 | AC17: 2002 | AD17: 1778 | AE17: 1562 | AF17: 2367 | AH17: =SUM(S17:V17) | AI17: =SUM(W17:Z17)
D18: Cost of services, maintenance, rentals and other | E18: =651+28 | F18: =658+28 | G18: =662+29 | H18: =AB18-SUM(E18:G18) | I18: =679+24 | J18: =677+26 | K18: =659+28 | L18: =AC18-SUM(I18:K18) | M18: =665+36 | N18: =671+34 | O18: =651+30 | P18: =AD18-SUM(M18:O18) | Q18: 719 | R18: 671 | S18: 643 | T18: =AE18-SUM(Q18:S18) | U18: 649 | V18: 645 | W18: 728 | X18: =AF18-SUM(U18:W18) | Y18: 697 | Z18: 655 | AB18: =2662+111 | AC18: =2679+108 | AD18: 2794 | AE18: 2699 | AF18: 2754 | AH18: =SUM(S18:V18) | AI18: =SUM(W18:Z18)
D19: Total cost of revenues | E19: =E17+E18 | F19: =F17+F18 | G19: =G17+G18 | H19: =H17+H18 | I19: =I17+I18 | J19: =J17+J18 | K19: =K17+K18 | L19: =L17+L18 | ... Z19: =Z17+Z18 | AB19: =AB17+AB18 | AC19: =AC17+AC18 | AD19: =AD17+AD18 | AE19: =AE17+AE18 | AF19: =AF17+AF18 | AH19: =AH17+AH18 | AI19: =AI17+AI18
D20: Gross profit | E20: =E13-E19 | F20: =F13-F19 | G20: =G13-G19 | H20: =H13-H19 | I20: =I13-I19 | J20: =J13-J19 | K20: =K13-K19 | L20: =L13-L19 | ... Z20: =Z13-Z19 | AB20: =AB13-AB19 | AC20: =AC13-AC19 | AD20: =AD13-AD19 | AE20: =AE13-AE19 | AF20: =AF13-AF19 | AH20: =AH13-AH19 | AI20: =AI13-AI19
D22: Research, development and engineering expenses | E22: 74 | F22: 79 | G22: 82 | H22: =AB22-SUM(E22:G22) | I22: 78 | J22: 84 | K22: 73 | L22: =AC22-SUM(I22:K22) | M22: 64 | N22: 57 | O22: 52 | P22: =AD22-SUM(M22:O22) | Q22: 49 | R22: 50 | S22: 45 | T22: =AE22-SUM(Q22:S22) | U22: 42 | V22: 43 | W22: 74 | X22: =AF22-SUM(U22:W22) | Y22: 64 | Z22: 67 | AB22: 310 | AC22: 304 | AD22: 229 | AE22: 191 | AF22: 230 | AH22: =SUM(S22:V22) | AI22: =SUM(W22:Z22)
D23: Selling, administrative and general expenses | E23: 448 | F23: 434 | G23: 413 | H23: =AB23-SUM(E23:G23) | I23: 455 | J23: 459 | K23: 418 | L23: =AC23-SUM(I23:K23) | M23: 407 | N23: 433 | O23: 416 | P23: =AD23-SUM(M23:O23) | Q23: 397 | R23: 393 | S23: 370 | T23: =AE23-SUM(Q23:S23) | U23: 378 | V23: 368 | W23: 477 | X23: =AF23-SUM(U23:W23) | Y23: 430 | Z23: 432 | AB23: 1718 | AC23: 1760 | AD23: 1696 | AE23: 1537 | AF23: 1654 | AH23: =SUM(S23:V23) | AI23: =SUM(W23:Z23)
D24: Goodwill impairment | E24: 0 | F24: 0 | G24: 0 | H24: =AB24-SUM(E24:G24) | I24: 0 | J24: 0 | K24: 412 | L24: =AC24-SUM(I24:K24) | M24: 0 | N24: 0 | O24: 0 | P24: =AD24-SUM(M24:O24) | Q24: 0 | R24: 0 | S24: 1058 | T24: =AE24-SUM(Q24:S24) | U24: 0 | V24: 0 | W24: 0 | X24: =AF24-SUM(U24:W24) | Y24: 0 | Z24: 0 | AB24: 781 | AC24: 412 | AD24: 0 | AE24: 1058 | AF24: 0 | AH24: =SUM(S24:V24) | AI24: =SUM(W24:Z24)
D25: Restructuring and related costs, net | E25: 17 | F25: 12 | G25: 10 | H25: =AB25-SUM(E25:G25) | I25: 18 | J25: 1 | K25: 22 | L25: =AC25-SUM(I25:K25) | M25: 2 | N25: 23 | O25: 10 | P25: =AD25-SUM(M25:O25) | Q25: 39 | R25: 12 | S25: 56 | T25: =AE25-SUM(Q25:S25) | U25: -1 | V25: 10 | W25: 59 | X25: =AF25-SUM(U25:W25) | Y25: 45 | Z25: 23 | AB25: 38 | AC25: 65 | AD25: 167 | AE25: 112 | AF25: 66 | AH25: =SUM(S25:V25) | AI25: =SUM(W25:Z25)
D26: Amortization of intangible assets | E26: 15 | F26: 14 | G26: 13 | H26: =AB26-SUM(E26:G26) | I26: 11 | J26: 10 | K26: 10 | L26: =AC26-SUM(I26:K26) | M26: 11 | N26: 10 | O26: 12 | P26: =AD26-SUM(M26:O26) | Q26: 10 | R26: 10 | S26: 10 | T26: =AE26-SUM(Q26:S26) | U26: 10 | V26: 10 | W26: 30 | X26: =AF26-SUM(U26:W26) | Y26: 30 | Z26: 30 | AB26: 55 | AC26: 42 | AD26: 43 | AE26: 73 | AF26: 83 | AH26: =SUM(S26:V26) | AI26: =SUM(W26:Z26)
D27: Divestitures | E27: 0 | F27: 0 | G27: 0 | H27: =AB27-SUM(E27:G27) | I27: 0 | J27: 0 | K27: 0 | L27: =AC27-SUM(I27:K27) | M27: 0 | N27: 0 | O27: 0 | P27: =AD27-SUM(M27:O27) | Q27: 54 | R27: -3 | S27: 0 | T27: =AE27-SUM(Q27:S27) | U27: -4 | V27: 0 | W27: 0 | X27: =AF27-SUM(U27:W27) | Y27: 0 | Z27: 0 | AB27: 0 | AC27: 0 | AD27: 0 | AE27: 47 | AF27: -4 | AH27: =SUM(S27:V27) | AI27: =SUM(W27:Z27)
D28: PARC donation | E28: 0 | F28: 0 | G28: 0 | H28: =AB28-SUM(E28:G28) | I28: 0 | J28: 0 | K28: 0 | L28: =AC28-SUM(I28:K28) | M28: 0 | N28: 132 | O28: 0 | P28: =AD28-SUM(M28:O28) | Q28: 0 | R28: 0 | S28: 0 | T28: =AE28-SUM(Q28:S28) | U28: 0 | V28: 0 | W28: 0 | X28: =AF28-SUM(U28:W28) | Y28: 0 | Z28: 0 | AB28: 0 | AC28: 0 | AD28: 132 | AE28: 0 | AF28: 0 | AH28: =SUM(S28:V28) | AI28: =SUM(W28:Z28)
D29: Total operating expenses | E29: =SUM(E22:E28) | F29: =SUM(F22:F28) | G29: =SUM(G22:G28) | H29: =SUM(H22:H28) | I29: =SUM(I22:I28) | J29: =SUM(J22:J28) | K29: =SUM(K22:K28) | L29: =SUM(L22:L28) | ... Z29: =SUM(Z22:Z28) | AB29: =SUM(AB22:AB28) | AC29: =SUM(AC22:AC28) | AD29: =SUM(AD22:AD28) | AE29: =SUM(AE22:AE28) | AF29: =SUM(AF22:AF28) | AH29: =SUM(AH22:AH28) | AI29: =SUM(AI22:AI28)
D30: Operating (loss) income | E30: =E20-E29 | F30: =F20-F29 | G30: =G20-G29 | H30: =H20-H29 | I30: =I20-I29 | J30: =J20-J29 | K30: =K20-K29 | L30: =L20-L29 | ... Z30: =Z20-Z29 | AB30: =AB20-AB29 | AC30: =AC20-AC29 | AD30: =AD20-AD29 | AE30: =AE20-AE29 | AF30: =AF20-AF29 | AH30: =AH20-AH29 | AI30: =AI20-AI29
D32: Non-financing interest expense | E32: =52-28 | F32: =52-28 | G32: =52-29 | H32: =AB32-SUM(E32:G32) | I32: =53-24 | J32: =49-26 | K32: =49-28 | L32: =AC32-SUM(I32:K32) | M32: =50-36 | N32: =46-34 | O32: =44-30 | P32: =AD32-SUM(M32:O32) | Q32: 26 | R32: 31 | S32: 31 | T32: =AE32-SUM(Q32:S32) | U32: 33 | V32: 55 | W32: 80 | X32: =AF32-SUM(U32:W32) | Y32: 84 | Z32: 100 | AB32: =207-111 | AC32: =199-108 | AD32: =198-130 | AE32: 119 | AF32: 248 | AH32: =SUM(S32:V32) | AI32: =SUM(W32:Z32)
D33: Other expenses (income), net | E33: =4-0-24 | F33: =1-1-24 | G33: =-33-1-23 | H33: =AB33-SUM(E33:G33) | I33: =57-1-29 | J33: =8-1-23 | K33: =1-1-21 | L33: =AC33-SUM(I33:K33) | M33: =20-0-14 | N33: =31-1-12 | O33: =-17-1-14 | P33: =AD33-SUM(M33:O33) | Q33: =44-26 | R33: =33-31 | S33: =43-31 | T33: =AE33-SUM(Q33:S33) | U33: 35 | V33: 25 | W33: =105-80 | X33: =AF33-SUM(U33:W33) | Y33: -31 | Z33: 5 | AB33: =-27-(207-111) | AC33: =60-(199-108) | AD33: =75-(198-130) | AE33: =158-119 | AF33: =360-248 | AH33: =SUM(S33:V33) | AI33: =SUM(W33:Z33)
D34: (Loss) income before income taxes | E34: =E30-E32-E33 | F34: =F30-F32-F33 | G34: =G30-G32-G33 | H34: =H30-H32-H33 | I34: =I30-I32-I33 | J34: =J30-J32-J33 | K34: =K30-K32-K33 | L34: =L30-L32-L33 | ... Z34: =Z30-Z32-Z33 | AB34: =AB30-AB32-AB33 | AC34: =AC30-AC32-AC33 | AD34: =AD30-AD32-AD33 | AE34: =AE30-AE32-AE33 | AF34: =AF30-AF32-AF33 | AH34: =AH30-AH32-AH33 | AI34: =AI30-AI32-AI33
D35: Income tax expense (benefit) | E35: 14 | F35: 9 | G35: -4 | H35: =AB35-SUM(E35:G35) | I35: -31 | J35: 1 | K35: 3 | L35: =AC35-SUM(I35:K35) | M35: 14 | N35: -28 | O35: 15 | P35: =AD35-SUM(M35:O35) | Q35: -37 | R35: 7 | S35: 118 | T35: =AE35-SUM(Q35:S35) | U35: 23 | V35: 46 | W35: 460 | X35: =AF35-SUM(U35:W35) | Y35: 32 | Z35: 18 | AB35: -17 | AC35: -3 | AD35: -29 | AE35: 105 | AF35: 541 | AH35: =SUM(S35:V35) | AI35: =SUM(W35:Z35)
D36: Net (loss) income | E36: =E34-E35 | F36: =F34-F35 | G36: =G34-G35 | H36: =H34-H35 | I36: =I34-I35 | J36: =J34-J35 | K36: =K34-K35 | L36: =L34-L35 | ... Z36: =Z34-Z35 | AB36: =AB34-AB35 | AC36: =AC34-AC35 | AD36: =AD34-AD35 | AE36: =AE34-AE35 | AF36: =AF34-AF35 | AH36: =AH34-AH35 | AI36: =AI34-AI35
D37: Less: net (income) loss attributable to noncontrolling interests | E37: 0 | F37: 0 | G37: 1 | H37: =AB37-SUM(E37:G37) | I37: 1 | J37: 1 | K37: -1 | L37: =AC37-SUM(I37:K37) | M37: 0 | N37: -1 | O37: 0 | P37: =AD37-SUM(M37:O37) | Q37: 0 | R37: 0 | S37: 0 | T37: =AE37-SUM(Q37:S37) | U37: 0 | V37: 0 | W37: 0 | X37: =AF37-SUM(U37:W37) | Y37: 0 | Z37: 0 | AB37: 0 | AC37: 0 | AD37: 0 | AE37: 0 | AF37: 0 | AH37: =SUM(S37:V37) | AI37: =SUM(W37:Z37)
D38: Net (loss) income attributable to Xerox Holdings | E38: =E36+E37 | F38: =F36+F37 | G38: =G36+G37 | H38: =H36+H37 | I38: =I36+I37 | J38: =J36+J37 | K38: =K36+K37 | L38: =L36+L37 | ... Z38: =Z36+Z37 | AB38: =AB36+AB37 | AC38: =AC36+AC37 | AD38: =AD36+AD37 | AE38: =AE36+AE37 | AF38: =AF36+AF37 | AH38: =AH36+AH37 | AI38: =AI36+AI37
D39: Net (loss) income attributable to Xerox Holdings (reported) | E39: 39 | F39: 91 | G39: 90 | H39: -675 | I39: -56 | J39: -4 | K39: -383 | L39: 121 | M39: 71 | N39: -61 | O39: 49 | P39: -58 | Q39: -113 | R39: 18 | S39: -1205 | T39: -21 | U39: -90 | V39: -106 | W39: -760 | X39: -73 | Y39: -105 | Z39: 13 | AB39: -455 | AC39: -322 | AD39: 1 | AE39: -1321 | AF39: -1029
D40: Check | E40: =E38-E39 | F40: =F38-F39 | G40: =G38-G39 | H40: =H38-H39 | I40: =I38-I39 | J40: =J38-J39 | K40: =K38-K39 | L40: =L38-L39 | ... Z40: =Z38-Z39 | AB40: =AB38-AB39 | AC40: =AC38-AC39 | AD40: =AD38-AD39 | AE40: =AE38-AE39 | AF40: =AF38-AF39
D41: Less: preferred stock dividends, net | E41: -4 | F41: -3 | G41: -4 | H41: =AB41-SUM(E41:G41) | I41: -4 | J41: -3 | K41: -4 | L41: =AC41-SUM(I41:K41) | M41: -4 | N41: -3 | O41: -4 | P41: =AD41-SUM(M41:O41) | Q41: -4 | R41: -3 | S41: -4 | T41: =AE41-SUM(Q41:S41) | U41: -4 | V41: -3 | W41: -4 | X41: =AF41-SUM(U41:W41) | Y41: -4 | Z41: -3 | AB41: -14 | AC41: -14 | AD41: -14 | AE41: -14 | AF41: -14 | AH41: =SUM(S41:V41) | AI41: =SUM(W41:Z41)
D42: Net (loss) income attributable to common shareholders | E42: =E38+E41 | F42: =F38+F41 | G42: =G38+G41 | H42: =H38+H41 | I42: =I38+I41 | J42: =J38+J41 | K42: =K38+K41 | L42: =L38+L41 | ... Z42: =Z38+Z41 | AB42: =AB38+AB41 | AC42: =AC38+AC41 | AD42: =AD38+AD41 | AE42: =AE38+AE41 | AF42: =AF38+AF41 | AH42: =AH38+AH41 | AI42: =AI38+AI41
D43: Diluted (loss) earnings per share | E43: 0.18 | F43: 0.46 | G43: 0.48 | H43: -3.97 | I43: -0.38 | J43: -0.05 | K43: -2.48 | L43: 0.74 | M43: 0.43 | N43: -0.41 | O43: 0.28 | P43: -0.5 | Q43: -0.94 | R43: 0.11 | S43: -9.71 | T43: -0.2 | U43: -0.75 | V43: -0.87 | W43: -6.01 | X43: -0.6 | Y43: -0.84 | Z43: 0.07 | AB43: -2.56 | AC43: -2.15 | AD43: -0.09 | AE43: -10.75 | AF43: -8.25
D45: Adjusted EBITDA reconciliation (company definition)
D46: Net (loss) income | E46: =E36 | F46: =F36 | G46: =G36 | H46: =H36 | I46: =I36 | J46: =J36 | K46: =K36 | L46: =L36 | ... Z46: =Z36 | AB46: =AB36 | AC46: =AC36 | AD46: =AD36 | AE46: =AE36 | AF46: =AF36 | AH46: =SUM(S46:V46) | AI46: =SUM(W46:Z46)
D47: Non-financing interest expense | E47: =E32 | F47: =F32 | G47: =G32 | H47: =H32 | I47: =I32 | J47: =J32 | K47: =K32 | L47: =L32 | ... Z47: =Z32 | AB47: =AB32 | AC47: =AC32 | AD47: =AD32 | AE47: =AE32 | AF47: =AF32 | AH47: =SUM(S47:V47) | AI47: =SUM(W47:Z47)
D48: Other expenses (income), net | E48: =E33 | F48: =F33 | G48: =G33 | H48: =H33 | I48: =I33 | J48: =J33 | K48: =K33 | L48: =L33 | ... Z48: =Z33 | AB48: =AB33 | AC48: =AC33 | AD48: =AD33 | AE48: =AE33 | AF48: =AF33 | AH48: =SUM(S48:V48) | AI48: =SUM(W48:Z48)
D49: Income tax expense (benefit) | E49: =E35 | F49: =F35 | G49: =G35 | H49: =H35 | I49: =I35 | J49: =J35 | K49: =K35 | L49: =L35 | ... Z49: =Z35 | AB49: =AB35 | AC49: =AC35 | AD49: =AD35 | AE49: =AE35 | AF49: =AF35 | AH49: =SUM(S49:V49) | AI49: =SUM(W49:Z49)
D50: Depreciation and amortization (excl. customer contract costs) | E50: =CFS!F16 | F50: =CFS!G16 | G50: =CFS!H16 | H50: =CFS!I16 | I50: =CFS!J16 | J50: =CFS!K16 | K50: =CFS!L16 | L50: =CFS!M16 | ... Z50: =CFS!AA16 | AB50: =CFS!AC16 | AC50: =CFS!AD16 | AD50: =CFS!AE16 | AE50: =CFS!AF16 | AF50: =CFS!AG16 | AH50: =SUM(S50:V50) | AI50: =SUM(W50:Z50)
D51: Goodwill impairment | E51: =E24 | F51: =F24 | G51: =G24 | H51: =H24 | I51: =I24 | J51: =J24 | K51: =K24 | L51: =L24 | ... Z51: =Z24 | AB51: =AB24 | AC51: =AC24 | AD51: =AD24 | AE51: =AE24 | AF51: =AF24 | AH51: =SUM(S51:V51) | AI51: =SUM(W51:Z51)
D52: EBITDA | E52: =SUM(E46:E51) | F52: =SUM(F46:F51) | G52: =SUM(G46:G51) | H52: =SUM(H46:H51) | I52: =SUM(I46:I51) | J52: =SUM(J46:J51) | K52: =SUM(K46:K51) | L52: =SUM(L46:L51) | ... Z52: =SUM(Z46:Z51) | AB52: =SUM(AB46:AB51) | AC52: =SUM(AC46:AC51) | AD52: =SUM(AD46:AD51) | AE52: =SUM(AE46:AE51) | AF52: =SUM(AF46:AF51) | AH52: =SUM(AH46:AH51) | AI52: =SUM(AI46:AI51)
D54: Stock-based compensation | E54: =CFS!F25 | F54: =CFS!G25 | G54: =CFS!H25 | H54: =CFS!I25 | I54: =CFS!J25 | J54: =CFS!K25 | K54: =CFS!L25 | L54: =CFS!M25 | ... Z54: =CFS!AA25 | AB54: =CFS!AC25 | AC54: =CFS!AD25 | AD54: =CFS!AE25 | AE54: =CFS!AF25 | AF54: =CFS!AG25 | AH54: =SUM(S54:V54) | AI54: =SUM(W54:Z54)
D55: Restructuring and related costs, net | E55: =E25 | F55: =F25 | G55: =G25 | H55: =H25 | I55: =I25 | J55: =J25 | K55: =K25 | L55: =L25 | ... Z55: =Z25 | AB55: =AB25 | AC55: =AC25 | AD55: =AD25 | AE55: =AE25 | AF55: =AF25 | AH55: =SUM(S55:V55) | AI55: =SUM(W55:Z55)
D56: PARC donation | E56: =E28 | F56: =F28 | G56: =G28 | H56: =H28 | I56: =I28 | J56: =J28 | K56: =K28 | L56: =L28 | ... Z56: =Z28 | AB56: =AB28 | AC56: =AC28 | AD56: =AD28 | AE56: =AE28 | AF56: =AF28 | AH56: =SUM(S56:V56) | AI56: =SUM(W56:Z56)
D57: Divestitures | E57: =E27 | F57: =F27 | G57: =G27 | H57: =H27 | I57: =I27 | J57: =J27 | K57: =K27 | L57: =L27 | ... Z57: =Z27 | AB57: =AB27 | AC57: =AC27 | AD57: =AD27 | AE57: =AE27 | AF57: =AF27 | AH57: =SUM(S57:V57) | AI57: =SUM(W57:Z57)
D58: Transformation-related costs | Q58: 0 | R58: 0 | S58: 0 | T58: =AE58-SUM(Q58:S58) | U58: 6 | V58: 3 | W58: 3 | X58: =AF58-SUM(U58:W58) | Y58: 2 | Z58: 2 | AE58: 12 | AF58: 17 | AH58: =SUM(S58:V58) | AI58: =SUM(W58:Z58)
D59: Transaction and related costs, net | Q59: 0 | R59: 0 | S59: 0 | T59: =AE59-SUM(Q59:S59) | U59: 3 | V59: 6 | W59: 23 | X59: =AF59-SUM(U59:W59) | Y59: 4 | Z59: 0 | AE59: 7 | AF59: 34 | AH59: =SUM(S59:V59) | AI59: =SUM(W59:Z59)
D60: Inventory impact, exit of Production Print manufacturing | Q60: 36 | R60: 8 | S60: 0 | T60: =AE60-SUM(Q60:S60) | U60: 7 | V60: 10 | W60: 3 | X60: =AF60-SUM(U60:W60) | Y60: 0 | Z60: 0 | AE60: 51 | AF60: 24 | AH60: =SUM(S60:V60) | AI60: =SUM(W60:Z60)
D61: Lexmark inventory purchase accounting adjustment | U61: 0 | V61: 0 | W61: 102 | X61: =AF61-SUM(U61:W61) | Y61: 0 | Z61: 0 | AF61: 102 | AH61: =SUM(S61:V61) | AI61: =SUM(W61:Z61)
D62: Lexmark settlement of pre-existing employment agreements | U62: 0 | V62: 0 | W62: 24 | X62: =AF62-SUM(U62:W62) | Y62: 0 | Z62: 0 | AF62: 25 | AH62: =SUM(S62:V62) | AI62: =SUM(W62:Z62)
D63: Adjusted EBITDA | E63: =E52+SUM(E54:E62) | F63: =F52+SUM(F54:F62) | G63: =G52+SUM(G54:G62) | H63: =H52+SUM(H54:H62) | I63: =I52+SUM(I54:I62) | J63: =J52+SUM(J54:J62) | K63: =K52+SUM(K54:K62) | L63: =L52+SUM(L54:L62) | ... Z63: =Z52+SUM(Z54:Z62) | AB63: =AB52+SUM(AB54:AB62) | AC63: =AC52+SUM(AC54:AC62) | AD63: =AD52+SUM(AD54:AD62) | AE63: =AE52+SUM(AE54:AE62) | AF63: =AF52+SUM(AF54:AF62) | AH63: =AH52+SUM(AH54:AH62) | AI63: =AI52+SUM(AI54:AI62)
D64: Adjusted EBITDA (company-reported) | Q64: 94 | R64: 151 | S64: 138 | T64: 172 | U64: 84 | V64: 120 | W64: 133 | X64: 175 | Y64: 140 | Z64: 271 | AD64: 651 | AE64: 555 | AF64: 512
D65: Check | Q65: =Q63-Q64 | R65: =R63-R64 | S65: =S63-S64 | T65: =T63-T64 | U65: =U63-U64 | V65: =V63-V64 | W65: =W63-W64 | X65: =X63-X64 | ... Z65: =Z63-Z64 | AD65: =AD63-AD64 | AE65: =AE63-AE64 | AF65: =AF63-AF64
D67: Less: IEEPA tariff refund benefit (in cost of sales) | Z67: -105 | AH67: =SUM(S67:V67) | AI67: =SUM(W67:Z67)
D68: Adjusted EBITDA excl. IEEPA tariff benefit | E68: =E63+E67 | F68: =F63+F67 | G68: =G63+G67 | H68: =H63+H67 | I68: =I63+I67 | J68: =J63+J67 | K68: =K63+K67 | L68: =L63+L67 | ... Z68: =Z63+Z67 | AB68: =AB63+AB67 | AC68: =AC63+AC67 | AD68: =AD63+AD67 | AE68: =AE63+AE67 | AF68: =AF63+AF67 | AH68: =AH63+AH67 | AI68: =AI63+AI67
D70: Memo:
D71: Total revenue growth (YoY) | I71: =I13/E13-1 | J71: =J13/F13-1 | K71: =K13/G13-1 | L71: =L13/H13-1 | M71: =M13/I13-1 | N71: =N13/J13-1 | O71: =O13/K13-1 | P71: =P13/L13-1 | ... Z71: =Z13/V13-1 | AC71: =AC13/AB13-1 | AD71: =AD13/AC13-1 | AE71: =AE13/AD13-1 | AF71: =AF13/AE13-1 | AH71: =SUM(S13:V13)/SUM(O13:R13)-1 | AI71: =AI13/AH13-1
D72: Gross margin % | E72: =E20/E13 | F72: =F20/F13 | G72: =G20/G13 | H72: =H20/H13 | I72: =I20/I13 | J72: =J20/J13 | K72: =K20/K13 | L72: =L20/L13 | ... Z72: =Z20/Z13 | AB72: =AB20/AB13 | AC72: =AC20/AC13 | AD72: =AD20/AD13 | AE72: =AE20/AE13 | AF72: =AF20/AF13 | AH72: =AH20/AH13 | AI72: =AI20/AI13
D73: EBITDA margin % | E73: =E52/E13 | F73: =F52/F13 | G73: =G52/G13 | H73: =H52/H13 | I73: =I52/I13 | J73: =J52/J13 | K73: =K52/K13 | L73: =L52/L13 | ... Z73: =Z52/Z13 | AB73: =AB52/AB13 | AC73: =AC52/AC13 | AD73: =AD52/AD13 | AE73: =AE52/AE13 | AF73: =AF52/AF13 | AH73: =AH52/AH13 | AI73: =AI52/AI13
D74: Adjusted EBITDA margin % | E74: =E63/E13 | F74: =F63/F13 | G74: =G63/G13 | H74: =H63/H13 | I74: =I63/I13 | J74: =J63/J13 | K74: =K63/K13 | L74: =L63/L13 | ... Z74: =Z63/Z13 | AB74: =AB63/AB13 | AC74: =AC63/AC13 | AD74: =AD63/AD13 | AE74: =AE63/AE13 | AF74: =AF63/AF13 | AH74: =AH63/AH13 | AI74: =AI63/AI13
D75: Adjusted EBITDA excl. IEEPA margin % | E75: =E68/E13 | F75: =F68/F13 | G75: =G68/G13 | H75: =H68/H13 | I75: =I68/I13 | J75: =J68/J13 | K75: =K68/K13 | L75: =L68/L13 | ... Z75: =Z68/Z13 | AB75: =AB68/AB13 | AC75: =AC68/AC13 | AD75: =AD68/AD13 | AE75: =AE68/AE13 | AF75: =AF68/AF13 | AH75: =AH68/AH13 | AI75: =AI68/AI13
D77: Notes:
D78: (1) All periods are shown in Xerox's current presentation: Financing revenue and cost of financing are included in Services, maintenance, rentals and other (2025 reclassification); non-financing interest is shown separately from Other expenses, net (2026 reclassification); equity in net income of unconsolidated affiliates is included in Other expenses, net.
D79: (2) Lexmark was acquired July 1, 2025 and is included from 3Q'25 onward. Figures are as reported, not pro forma.
D80: (3) Xerox first reported Adjusted EBITDA for FY2023. Adjusted EBITDA for 2021, 2022 and the 2023 quarters is rebuilt on the company's current definition from filed figures; the FY2023 rebuild ties to the reported $651M.
D81: (4) 2Q'26 includes a $105M pre-tax benefit in cost of sales from recognition of IEEPA tariff receivables, backed out in the row below Adjusted EBITDA.
D82: (5) Q4 figures are derived as full year less 1Q-3Q, except EPS and the reported tie-out rows. 2Q/3Q D&A and stock-based compensation from 2022 onward are derived from year-to-date cash flow statements.

Sheet IS Out
A1: =D3 | B1: ='Cover Page'!A1
D3: Income Statement Summary & Adjusted EBITDA
D4: Xerox Holdings Corporation – All values in $ millions (USD), except per-share values. Data as of June 30, 2026 (2Q'26).
A8: x | D8: Income Statement Summary | E8: Year Ended December 31, | J8: LTM
E9: 2021 | F9: 2022 | G9: 2023 | H9: 2024 | I9: 2025 | J9: LTM 2Q'25 | K9: LTM 2Q'26
D11: Sales | E11: =IS!AB11 | F11: =IS!AC11 | G11: =IS!AD11 | H11: =IS!AE11 | I11: =IS!AF11 | J11: =IS!AH11 | K11: =IS!AI11
D12: Services, maintenance, rentals and other | E12: =IS!AB12 | F12: =IS!AC12 | G12: =IS!AD12 | H12: =IS!AE12 | I12: =IS!AF12 | J12: =IS!AH12 | K12: =IS!AI12
D13: Total revenues | E13: =E11+E12 | F13: =F11+F12 | G13: =G11+G12 | H13: =H11+H12 | I13: =I11+I12 | J13: =J11+J12 | K13: =K11+K12
D14: Cost of revenues | E14: =-IS!AB19 | F14: =-IS!AC19 | G14: =-IS!AD19 | H14: =-IS!AE19 | I14: =-IS!AF19 | J14: =-IS!AH19 | K14: =-IS!AI19
D15: Gross profit | E15: =E13+E14 | F15: =F13+F14 | G15: =G13+G14 | H15: =H13+H14 | I15: =I13+I14 | J15: =J13+J14 | K15: =K13+K14
D16: Research, development and engineering | E16: =-IS!AB22 | F16: =-IS!AC22 | G16: =-IS!AD22 | H16: =-IS!AE22 | I16: =-IS!AF22 | J16: =-IS!AH22 | K16: =-IS!AI22
D17: Selling, administrative and general | E17: =-IS!AB23 | F17: =-IS!AC23 | G17: =-IS!AD23 | H17: =-IS!AE23 | I17: =-IS!AF23 | J17: =-IS!AH23 | K17: =-IS!AI23
D18: Restructuring and related costs, net | E18: =-IS!AB25 | F18: =-IS!AC25 | G18: =-IS!AD25 | H18: =-IS!AE25 | I18: =-IS!AF25 | J18: =-IS!AH25 | K18: =-IS!AI25
D19: Amortization of intangible assets | E19: =-IS!AB26 | F19: =-IS!AC26 | G19: =-IS!AD26 | H19: =-IS!AE26 | I19: =-IS!AF26 | J19: =-IS!AH26 | K19: =-IS!AI26
D20: Divestitures | E20: =-IS!AB27 | F20: =-IS!AC27 | G20: =-IS!AD27 | H20: =-IS!AE27 | I20: =-IS!AF27 | J20: =-IS!AH27 | K20: =-IS!AI27
D21: PARC donation | E21: =-IS!AB28 | F21: =-IS!AC28 | G21: =-IS!AD28 | H21: =-IS!AE28 | I21: =-IS!AF28 | J21: =-IS!AH28 | K21: =-IS!AI28
D22: Depreciation and amortization (add-back) | E22: =IS!AB50 | F22: =IS!AC50 | G22: =IS!AD50 | H22: =IS!AE50 | I22: =IS!AF50 | J22: =IS!AH50 | K22: =IS!AI50
D23: EBITDA | E23: =E15+SUM(E16:E22) | F23: =F15+SUM(F16:F22) | G23: =G15+SUM(G16:G22) | H23: =H15+SUM(H16:H22) | I23: =I15+SUM(I16:I22) | J23: =J15+SUM(J16:J22) | K23: =K15+SUM(K16:K22)
D25: Stock-based compensation | E25: =IS!AB54 | F25: =IS!AC54 | G25: =IS!AD54 | H25: =IS!AE54 | I25: =IS!AF54 | J25: =IS!AH54 | K25: =IS!AI54
D26: Restructuring and related costs, net | E26: =IS!AB25 | F26: =IS!AC25 | G26: =IS!AD25 | H26: =IS!AE25 | I26: =IS!AF25 | J26: =IS!AH25 | K26: =IS!AI25
D27: PARC donation | E27: =IS!AB28 | F27: =IS!AC28 | G27: =IS!AD28 | H27: =IS!AE28 | I27: =IS!AF28 | J27: =IS!AH28 | K27: =IS!AI28
D28: Divestitures | E28: =IS!AB27 | F28: =IS!AC27 | G28: =IS!AD27 | H28: =IS!AE27 | I28: =IS!AF27 | J28: =IS!AH27 | K28: =IS!AI27
D29: Transformation-related costs | E29: =IS!AB58 | F29: =IS!AC58 | G29: =IS!AD58 | H29: =IS!AE58 | I29: =IS!AF58 | J29: =IS!AH58 | K29: =IS!AI58
D30: Transaction and related costs, net | E30: =IS!AB59 | F30: =IS!AC59 | G30: =IS!AD59 | H30: =IS!AE59 | I30: =IS!AF59 | J30: =IS!AH59 | K30: =IS!AI59
D31: Inventory impact, exit of Production Print manufacturing | E31: =IS!AB60 | F31: =IS!AC60 | G31: =IS!AD60 | H31: =IS!AE60 | I31: =IS!AF60 | J31: =IS!AH60 | K31: =IS!AI60
D32: Lexmark inventory purchase accounting adjustment | E32: =IS!AB61 | F32: =IS!AC61 | G32: =IS!AD61 | H32: =IS!AE61 | I32: =IS!AF61 | J32: =IS!AH61 | K32: =IS!AI61
D33: Lexmark settlement of pre-existing employment agreements | E33: =IS!AB62 | F33: =IS!AC62 | G33: =IS!AD62 | H33: =IS!AE62 | I33: =IS!AF62 | J33: =IS!AH62 | K33: =IS!AI62
D34: Adjusted EBITDA | E34: =E23+SUM(E25:E33) | F34: =F23+SUM(F25:F33) | G34: =G23+SUM(G25:G33) | H34: =H23+SUM(H25:H33) | I34: =I23+SUM(I25:I33) | J34: =J23+SUM(J25:J33) | K34: =K23+SUM(K25:K33)
D35: IS Adjusted EBITDA | E35: =IS!AB63 | F35: =IS!AC63 | G35: =IS!AD63 | H35: =IS!AE63 | I35: =IS!AF63 | J35: =IS!AH63 | K35: =IS!AI63
D36: Check | E36: =E34-E35 | F36: =F34-F35 | G36: =G34-G35 | H36: =H34-H35 | I36: =I34-I35 | J36: =J34-J35 | K36: =K34-K35
D38: Less: IEEPA tariff refund benefit | E38: =IS!AB67 | F38: =IS!AC67 | G38: =IS!AD67 | H38: =IS!AE67 | I38: =IS!AF67 | J38: =IS!AH67 | K38: =IS!AI67
D39: Adjusted EBITDA excl. IEEPA tariff benefit | E39: =E34+E38 | F39: =F34+F38 | G39: =G34+G38 | H39: =H34+H38 | I39: =I34+I38 | J39: =J34+J38 | K39: =K34+K38
D41: Memo:
D42: Total revenue growth (YoY) | F42: =F13/E13-1 | G42: =G13/F13-1 | H42: =H13/G13-1 | I42: =I13/H13-1 | J42: =IS!AH71 | K42: =IS!AI71
D43: Gross margin % | E43: =E15/E13 | F43: =F15/F13 | G43: =G15/G13 | H43: =H15/H13 | I43: =I15/I13 | J43: =J15/J13 | K43: =K15/K13
D44: EBITDA margin % | E44: =E23/E13 | F44: =F23/F13 | G44: =G23/G13 | H44: =H23/H13 | I44: =I23/I13 | J44: =J23/J13 | K44: =K23/K13
D45: Adjusted EBITDA margin % | E45: =E34/E13 | F45: =F34/F13 | G45: =G34/G13 | H45: =H34/H13 | I45: =I34/I13 | J45: =J34/J13 | K45: =K34/K13
D46: Adjusted EBITDA excl. IEEPA margin % | E46: =E39/E13 | F46: =F39/F13 | G46: =G39/G13 | H46: =H39/H13 | I46: =I39/I13 | J46: =J39/J13 | K46: =K39/K13
D48: Notes:
D49: (1) Shown in Xerox's current presentation (see IS tab notes).
D50: (2) Lexmark included from 3Q'25 (acquired July 1, 2025); figures as reported, not pro forma.
D51: (3) EBITDA and Adjusted EBITDA follow the company definition. Company-reported Adjusted EBITDA
D52: begins FY2023; FY2021 and FY2022 are rebuilt from filed figures.
D53: (4) LTM 2Q'26 includes the $105M IEEPA tariff refund benefit in 2Q'26 cost of sales.

Sheet CFS
A1: =D3 | B1: ='Cover Page'!A1
D3: Statement of Cash Flows Spread
D4: Xerox Holdings Corporation – All values in $ millions (USD), except per-share values. Data as of June 30, 2026 (2Q'26).
A6: x | D6: Cash Flow Statement | F6: Quarter Ended | AC6: Fiscal Year Ended December 31, | AI6: LTM
F7: 1 | G7: 2 | H7: 3 | I7: 4 | J7: 1 | K7: 2 | L7: 3 | M7: 4 | N7: 1 | O7: 2 | P7: 3 | Q7: 4 | R7: 1 | S7: 2 | T7: 3 | U7: 4 | V7: 1 | W7: 2 | X7: 3 | Y7: 4 | Z7: 1 | AA7: 2
F8: 2021 | G8: 2021 | H8: 2021 | I8: 2021 | J8: 2022 | K8: 2022 | L8: 2022 | M8: 2022 | N8: 2023 | O8: 2023 | P8: 2023 | Q8: 2023 | R8: 2024 | S8: 2024 | T8: 2024 | U8: 2024 | V8: 2025 | W8: 2025 | X8: 2025 | Y8: 2025 | Z8: 2026 | AA8: 2026 | AC8: 2021 | AD8: 2022 | AE8: 2023 | AF8: 2024 | AG8: 2025
F9: 44286 | G9: 44377 | H9: 44469 | I9: 44561 | J9: 44651 | K9: 44742 | L9: 44834 | M9: 44926 | N9: 45016 | O9: 45107 | P9: 45199 | Q9: 45291 | R9: 45382 | S9: 45473 | T9: 45565 | U9: 45657 | V9: 45747 | W9: 45838 | X9: 45930 | Y9: 46022 | Z9: 46112 | AA9: 46203 | AC9: 44561 | AD9: 44926 | AE9: 45291 | AF9: 45657 | AG9: 46022
F11: =F7&"Q'"&RIGHT(F8,2) | G11: =G7&"Q'"&RIGHT(G8,2) | H11: =H7&"Q'"&RIGHT(H8,2) | I11: =I7&"Q'"&RIGHT(I8,2) | J11: =J7&"Q'"&RIGHT(J8,2) | K11: =K7&"Q'"&RIGHT(K8,2) | L11: =L7&"Q'"&RIGHT(L8,2) | M11: =M7&"Q'"&RIGHT(M8,2) | ... AA11: =AA7&"Q'"&RIGHT(AA8,2) | AC11: 2021 | AD11: 2022 | AE11: 2023 | AF11: 2024 | AG11: 2025 | AI11: LTM 2Q'25 | AJ11: LTM 2Q'26
D13: OPERATING ACTIVITIES
D14: Net (loss) income | F14: =IS!E36 | G14: =IS!F36 | H14: =IS!G36 | I14: =IS!H36 | J14: =IS!I36 | K14: =IS!J36 | L14: =IS!K36 | M14: =IS!L36 | ... AA14: =IS!Z36 | AC14: =IS!AB36 | AD14: =IS!AC36 | AE14: =IS!AD36 | AF14: =IS!AE36 | AG14: =IS!AF36 | AI14: =SUM(T14:W14) | AJ14: =SUM(X14:AA14)
D15: Adjustments required to reconcile net (loss) income to cash flows from operating activities:
D16: Depreciation and amortization | F16: 86 | G16: =170-F16 | H16: =249-SUM(F16:G16) | I16: =AC16-SUM(F16:H16) | J16: 72 | K16: =140-J16 | L16: =205-SUM(J16:K16) | M16: =AD16-SUM(J16:L16) | N16: 64 | O16: =126-N16 | P16: =189-SUM(N16:O16) | Q16: =AE16-SUM(N16:P16) | R16: 59 | S16: =118-R16 | T16: =177-SUM(R16:S16) | U16: =AF16-SUM(R16:T16) | V16: 60 | W16: =117-V16 | X16: =224-SUM(V16:W16) | Y16: =AG16-SUM(V16:X16) | Z16: 100 | AA16: =201-Z16 | AC16: 327 | AD16: 270 | AE16: 251 | AF16: 274 | AG16: 331 | AI16: =SUM(T16:W16) | AJ16: =SUM(X16:AA16)
D17: Provisions | F17: 20 | G17: =34-F17 | H17: =38-SUM(F17:G17) | I17: =AC17-SUM(F17:H17) | J17: 19 | K17: =35-J17 | L17: =48-SUM(J17:K17) | M17: =AD17-SUM(J17:L17) | N17: 0 | O17: =21-N17 | P17: =37-SUM(N17:O17) | Q17: =AE17-SUM(N17:P17) | R17: 57 | S17: =79-R17 | T17: =92-SUM(R17:S17) | U17: =AF17-SUM(R17:T17) | V17: 18 | W17: =48-V17 | X17: =67-SUM(V17:W17) | Y17: =AG17-SUM(V17:X17) | Z17: 18 | AA17: =36-Z17 | AC17: 46 | AD17: 65 | AE17: 54 | AF17: 110 | AG17: 85 | AI17: =SUM(T17:W17) | AJ17: =SUM(X17:AA17)
D18: Net (gain) loss on early extinguishment of debt | Z18: -56 | AA18: =-95-Z18 | AI18: =SUM(T18:W18) | AJ18: =SUM(X18:AA18)
D19: Net (gain) loss on sales of businesses and assets | F19: 0 | G19: =-1-F19 | H19: =-40-SUM(F19:G19) | I19: =AC19-SUM(F19:H19) | J19: 0 | K19: =-1-J19 | L19: =-17-SUM(J19:K19) | M19: =AD19-SUM(J19:L19) | N19: 0 | O19: =-2-N19 | P19: =-37-SUM(N19:O19) | Q19: =AE19-SUM(N19:P19) | R19: 0 | S19: =-1-R19 | T19: =-3-SUM(R19:S19) | U19: =AF19-SUM(R19:T19) | V19: -3 | W19: =-5-V19 | X19: =-6-SUM(V19:W19) | Y19: =AG19-SUM(V19:X19) | Z19: 2 | AA19: =2-Z19 | AC19: -40 | AD19: -56 | AE19: -39 | AF19: -8 | AG19: -5 | AI19: =SUM(T19:W19) | AJ19: =SUM(X19:AA19)
D20: Inventory-related purchase accounting adjustment, noncash (Lexmark) | V20: 0 | W20: =0-V20 | X20: =102-SUM(V20:W20) | Y20: =AG20-SUM(V20:X20) | AG20: 102 | AI20: =SUM(T20:W20) | AJ20: =SUM(X20:AA20)
D21: Effective settlement of pre-existing relationship between Lexmark and Xerox | V21: 0 | W21: =0-V21 | X21: =-43-SUM(V21:W21) | Y21: =AG21-SUM(V21:X21) | AG21: -43 | AI21: =SUM(T21:W21) | AJ21: =SUM(X21:AA21)
D22: Divestitures | F22: =IS!E27 | G22: =IS!F27 | H22: =IS!G27 | I22: =IS!H27 | J22: =IS!I27 | K22: =IS!J27 | L22: =IS!K27 | M22: =IS!L27 | ... AA22: =IS!Z27 | AC22: =IS!AB27 | AD22: =IS!AC27 | AE22: =IS!AD27 | AF22: =IS!AE27 | AG22: =IS!AF27 | AI22: =SUM(T22:W22) | AJ22: =SUM(X22:AA22)
D23: PARC donation | F23: =IS!E28 | G23: =IS!F28 | H23: =IS!G28 | I23: =IS!H28 | J23: =IS!I28 | K23: =IS!J28 | L23: =IS!K28 | M23: =IS!L28 | ... AA23: =IS!Z28 | AC23: =IS!AB28 | AD23: =IS!AC28 | AE23: =IS!AD28 | AF23: =IS!AE28 | AG23: =IS!AF28 | AI23: =SUM(T23:W23) | AJ23: =SUM(X23:AA23)
D24: Goodwill impairment | F24: =IS!E24 | G24: =IS!F24 | H24: =IS!G24 | I24: =IS!H24 | J24: =IS!I24 | K24: =IS!J24 | L24: =IS!K24 | M24: =IS!L24 | ... AA24: =IS!Z24 | AC24: =IS!AB24 | AD24: =IS!AC24 | AE24: =IS!AD24 | AF24: =IS!AE24 | AG24: =IS!AF24 | AI24: =SUM(T24:W24) | AJ24: =SUM(X24:AA24)
D25: Stock-based compensation | F25: 16 | G25: =30-F25 | H25: =44-SUM(F25:G25) | I25: =AC25-SUM(F25:H25) | J25: 15 | K25: =50-J25 | L25: =63-SUM(J25:K25) | M25: =AD25-SUM(J25:L25) | N25: 14 | O25: =28-N25 | P25: =40-SUM(N25:O25) | Q25: =AE25-SUM(N25:P25) | R25: 12 | S25: =29-R25 | T25: =38-SUM(R25:S25) | U25: =AF25-SUM(R25:T25) | V25: 12 | W25: =26-V25 | X25: =33-SUM(V25:W25) | Y25: =AG25-SUM(V25:X25) | Z25: 9 | AA25: =18-Z25 | AC25: 54 | AD25: 75 | AE25: 54 | AF25: 52 | AG25: 45 | AI25: =SUM(T25:W25) | AJ25: =SUM(X25:AA25)
D26: Restructuring and asset impairment charges | F26: 21 | G26: =25-F26 | H26: =28-SUM(F26:G26) | I26: =AC26-SUM(F26:H26) | J26: 20 | K26: =22-J26 | L26: =44-SUM(J26:K26) | M26: =AD26-SUM(J26:L26) | N26: 1 | O26: =14-N26 | P26: =25-SUM(N26:O26) | Q26: =AE26-SUM(N26:P26) | R26: 31 | S26: =34-R26 | T26: =80-SUM(R26:S26) | U26: =AF26-SUM(R26:T26) | V26: -1 | W26: =10-V26 | X26: =69-SUM(V26:W26) | Y26: =AG26-SUM(V26:X26) | Z26: 44 | AA26: =65-Z26 | AC26: 27 | AD26: 62 | AE26: 146 | AF26: 87 | AG26: 67 | AI26: =SUM(T26:W26) | AJ26: =SUM(X26:AA26)
D27: Payments for restructurings | F27: -27 | G27: =-49-F27 | H27: =-61-SUM(F27:G27) | I27: =AC27-SUM(F27:H27) | J27: -7 | K27: =-21-J27 | L27: =-38-SUM(J27:K27) | M27: =AD27-SUM(J27:L27) | N27: -6 | O27: =-14-N27 | P27: =-23-SUM(N27:O27) | Q27: =AE27-SUM(N27:P27) | R27: -16 | S27: =-47-R27 | T27: =-58-SUM(R27:S27) | U27: =AF27-SUM(R27:T27) | V27: -18 | W27: =-33-V27 | X27: =-41-SUM(V27:W27) | Y27: =AG27-SUM(V27:X27) | Z27: -21 | AA27: =-40-Z27 | AC27: -72 | AD27: -52 | AE27: -27 | AF27: -78 | AG27: -69 | AI27: =SUM(T27:W27) | AJ27: =SUM(X27:AA27)
D28: Non-service retirement-related costs | F28: 0 | G28: =-2-F28 | H28: =-5-SUM(F28:G28) | I28: =AC28-SUM(F28:H28) | J28: -7 | K28: =-11-J28 | L28: =-18-SUM(J28:K28) | M28: =AD28-SUM(J28:L28) | N28: -1 | O28: =10-N28 | P28: =14-SUM(N28:O28) | Q28: =AE28-SUM(N28:P28) | R28: 23 | S28: =49-R28 | T28: =74-SUM(R28:S28) | U28: =AF28-SUM(R28:T28) | V28: 18 | W28: =37-V28 | X28: =57-SUM(V28:W28) | Y28: =AG28-SUM(V28:X28) | Z28: 21 | AA28: =42-Z28 | AC28: -10 | AD28: -12 | AE28: 19 | AF28: 80 | AG28: 78 | AI28: =SUM(T28:W28) | AJ28: =SUM(X28:AA28)
D29: Contributions to retirement plans | F29: -35 | G29: =-69-F29 | H29: =-102-SUM(F29:G29) | I29: =AC29-SUM(F29:H29) | J29: -38 | K29: =-72-J29 | L29: =-106-SUM(J29:K29) | M29: =AD29-SUM(J29:L29) | N29: -17 | O29: =-32-N29 | P29: =-75-SUM(N29:O29) | Q29: =AE29-SUM(N29:P29) | R29: -31 | S29: =-58-R29 | T29: =-114-SUM(R29:S29) | U29: =AF29-SUM(R29:T29) | V29: -34 | W29: =-67-V29 | X29: =-123-SUM(V29:W29) | Y29: =AG29-SUM(V29:X29) | Z29: -36 | AA29: =-72-Z29 | AC29: -135 | AD29: -124 | AE29: -102 | AF29: -145 | AG29: -161 | AI29: =SUM(T29:W29) | AJ29: =SUM(X29:AA29)
D30: Changes in operating assets and liabilities:
D31: (Increase) decrease in accounts receivable and billed portion of finance receivables | F31: 92 | G31: =37-F31 | H31: =-30-SUM(F31:G31) | I31: =AC31-SUM(F31:H31) | J31: 13 | K31: =-49-J31 | L31: =-48-SUM(J31:K31) | M31: =AD31-SUM(J31:L31) | N31: 39 | O31: =-36-N31 | P31: =-47-SUM(N31:O31) | Q31: =AE31-SUM(N31:P31) | R31: -19 | S31: =-32-R31 | T31: =18-SUM(R31:S31) | U31: =AF31-SUM(R31:T31) | V31: -12 | W31: =-44-V31 | X31: =-41-SUM(V31:W31) | Y31: =AG31-SUM(V31:X31) | Z31: -106 | AA31: =-86-Z31 | AC31: 41 | AD31: -48 | AE31: -5 | AF31: 71 | AG31: -36 | AI31: =SUM(T31:W31) | AJ31: =SUM(X31:AA31)
D32: (Increase) decrease in inventories | F32: -18 | G32: =4-F32 | H32: =10-SUM(F32:G32) | I32: =AC32-SUM(F32:H32) | J32: -31 | K32: =-95-J32 | L32: =-136-SUM(J32:K32) | M32: =AD32-SUM(J32:L32) | N32: -64 | O32: =12-N32 | P32: =50-SUM(N32:O32) | Q32: =AE32-SUM(N32:P32) | R32: -133 | S32: =-148-R32 | T32: =-136-SUM(R32:S32) | U32: =AF32-SUM(R32:T32) | V32: -137 | W32: =-160-V32 | X32: =-123-SUM(V32:W32) | Y32: =AG32-SUM(V32:X32) | Z32: -49 | AA32: =-60-Z32 | AC32: 88 | AD32: -143 | AE32: 123 | AF32: -122 | AG32: -12 | AI32: =SUM(T32:W32) | AJ32: =SUM(X32:AA32)
D33: Increase in equipment on operating leases | F33: -28 | G33: =-63-F33 | H33: =-92-SUM(F33:G33) | I33: =AC33-SUM(F33:H33) | J33: -36 | K33: =-47-J33 | L33: =-74-SUM(J33:K33) | M33: =AD33-SUM(J33:L33) | N33: -40 | O33: =-77-N33 | P33: =-109-SUM(N33:O33) | Q33: =AE33-SUM(N33:P33) | R33: -22 | S33: =-50-R33 | T33: =-78-SUM(R33:S33) | U33: =AF33-SUM(R33:T33) | V33: -30 | W33: =-52-V33 | X33: =-88-SUM(V33:W33) | Y33: =AG33-SUM(V33:X33) | Z33: -32 | AA33: =-67-Z33 | AC33: -129 | AD33: -112 | AE33: -141 | AF33: -107 | AG33: -126 | AI33: =SUM(T33:W33) | AJ33: =SUM(X33:AA33)
D34: Decrease (increase) in finance receivables | F34: 37 | G34: =12-F34 | H34: =33-SUM(F34:G34) | I34: =AC34-SUM(F34:H34) | J34: 41 | K34: =17-J34 | L34: =-10-SUM(J34:K34) | M34: =AD34-SUM(J34:L34) | N34: 160 | O34: =407-N34 | P34: =490-SUM(N34:O34) | Q34: =AE34-SUM(N34:P34) | R34: 210 | S34: =399-R34 | T34: =496-SUM(R34:S34) | U34: =AF34-SUM(R34:T34) | V34: 128 | W34: =212-V34 | X34: =338-SUM(V34:W34) | Y34: =AG34-SUM(V34:X34) | Z34: 66 | AA34: =157-Z34 | AC34: 20 | AD34: -141 | AE34: 614 | AF34: 663 | AG34: 489 | AI34: =SUM(T34:W34) | AJ34: =SUM(X34:AA34)
D35: (Increase) decrease in other current and long-term assets | F35: 18 | G35: =66-F35 | H35: =64-SUM(F35:G35) | I35: =AC35-SUM(F35:H35) | J35: -1 | K35: =35-J35 | L35: =36-SUM(J35:K35) | M35: =AD35-SUM(J35:L35) | N35: 3 | O35: =15-N35 | P35: =-8-SUM(N35:O35) | Q35: =AE35-SUM(N35:P35) | R35: -2 | S35: =14-R35 | T35: =16-SUM(R35:S35) | U35: =AF35-SUM(R35:T35) | V35: -16 | W35: =16-V35 | X35: =4-SUM(V35:W35) | Y35: =AG35-SUM(V35:X35) | Z35: -38 | AA35: =-120-Z35 | AC35: 68 | AD35: 27 | AE35: 16 | AF35: -14 | AG35: 9 | AI35: =SUM(T35:W35) | AJ35: =SUM(X35:AA35)
D36: Increase (decrease) in accounts payable | F36: -31 | G36: =-33-F36 | H36: =74-SUM(F36:G36) | I36: =AC36-SUM(F36:H36) | J36: 111 | K36: =172-J36 | L36: =198-SUM(J36:K36) | M36: =AD36-SUM(J36:L36) | N36: -41 | O36: =-290-N36 | P36: =-290-SUM(N36:O36) | Q36: =AE36-SUM(N36:P36) | R36: 17 | S36: =-88-R36 | T36: =-143-SUM(R36:S36) | U36: =AF36-SUM(R36:T36) | V36: 89 | W36: =25-V36 | X36: =4-SUM(V36:W36) | Y36: =AG36-SUM(V36:X36) | Z36: 58 | AA36: =-30-Z36 | AC36: 118 | AD36: 278 | AE36: -290 | AF36: -48 | AG36: 24 | AI36: =SUM(T36:W36) | AJ36: =SUM(X36:AA36)
D37: Increase (decrease) in accrued compensation | F37: -36 | G37: =-35-F37 | H37: =-56-SUM(F37:G37) | I37: =AC37-SUM(F37:H37) | J37: 22 | K37: =7-J37 | L37: =29-SUM(J37:K37) | M37: =AD37-SUM(J37:L37) | N37: -16 | O37: =-7-N37 | P37: =16-SUM(N37:O37) | Q37: =AE37-SUM(N37:P37) | R37: -86 | S37: =-93-R37 | T37: =-78-SUM(R37:S37) | U37: =AF37-SUM(R37:T37) | V37: -30 | W37: =-51-V37 | X37: =-39-SUM(V37:W37) | Y37: =AG37-SUM(V37:X37) | Z37: -8 | AA37: =18-Z37 | AC37: -95 | AD37: 34 | AE37: 48 | AF37: -78 | AG37: -53 | AI37: =SUM(T37:W37) | AJ37: =SUM(X37:AA37)
D38: Increase (decrease) in other current and long-term liabilities | F38: -35 | G38: =92-F38 | H38: =80-SUM(F38:G38) | I38: =AC38-SUM(F38:H38) | J38: -43 | K38: =-48-J38 | L38: =-73-SUM(J38:K38) | M38: =AD38-SUM(J38:L38) | N38: -128 | O38: =-139-N38 | P38: =-159-SUM(N38:O38) | Q38: =AE38-SUM(N38:P38) | R38: -77 | S38: =-52-R38 | T38: =-83-SUM(R38:S38) | U38: =AF38-SUM(R38:T38) | V38: -48 | W38: =-40-V38 | X38: =58-SUM(V38:W38) | Y38: =AG38-SUM(V38:X38) | Z38: -9 | AA38: =6-Z38 | AC38: 89 | AD38: 9 | AE38: -114 | AF38: -47 | AG38: 33 | AI38: =SUM(T38:W38) | AJ38: =SUM(X38:AA38)
D39: Net change in income tax assets and liabilities (incl. deferred taxes) | F39: 6 | G39: =2-F39 | H39: =-11-SUM(F39:G39) | I39: =AC39-SUM(F39:H39) | J39: -39 | K39: =-76-J39 | L39: =-81-SUM(J39:K39) | M39: =AD39-SUM(J39:L39) | N39: 18 | O39: =-17-N39 | P39: =-24-SUM(N39:O39) | Q39: =AE39-SUM(N39:P39) | R39: -44 | S39: =-64-R39 | T39: =44-SUM(R39:S39) | U39: =AF39-SUM(R39:T39) | V39: -2 | W39: =35-V39 | X39: =479-SUM(V39:W39) | Y39: =AG39-SUM(V39:X39) | Z39: 12 | AA39: =6-Z39 | AC39: =10-89 | AD39: =-27-27 | AE39: =-12-68 | AF39: =-50+90 | AG39: =-26+502 | AI39: =SUM(T39:W39) | AJ39: =SUM(X39:AA39)
D40: Net change in derivative assets and liabilities | F40: 3 | G40: =-2-F40 | H40: =-1-SUM(F40:G40) | I40: =AC40-SUM(F40:H40) | J40: 7 | K40: =-6-J40 | L40: =-10-SUM(J40:K40) | M40: =AD40-SUM(J40:L40) | N40: 13 | O40: =22-N40 | P40: =16-SUM(N40:O40) | Q40: =AE40-SUM(N40:P40) | R40: 6 | S40: =6-R40 | T40: =9-SUM(R40:S40) | U40: =AF40-SUM(R40:T40) | V40: 0 | W40: =-2-V40 | X40: =-1-SUM(V40:W40) | Y40: =AG40-SUM(V40:X40) | AC40: 2 | AD40: -22 | AE40: 13 | AF40: 10 | AG40: -12 | AI40: =SUM(T40:W40) | AJ40: =SUM(X40:AA40)
D41: Other operating, net | F41: -11 | G41: =-17-F41 | H41: =-10-SUM(F41:G41) | I41: =AC41-SUM(F41:H41) | J41: 5 | K41: =-9-J41 | L41: =-7-SUM(J41:K41) | M41: =AD41-SUM(J41:L41) | N41: 8 | O41: =-11-N41 | P41: =0-SUM(N41:O41) | Q41: =AE41-SUM(N41:P41) | R41: -5 | S41: =-7-R41 | T41: =0-SUM(R41:S41) | U41: =AF41-SUM(R41:T41) | V41: 11 | W41: =28-V41 | X41: =46-SUM(V41:W41) | Y41: =AG41-SUM(V41:X41) | Z41: -14 | AA41: =4-Z41 | AC41: -17 | AD41: 13 | AE41: 13 | AF41: -13 | AG41: 35 | AI41: =SUM(T41:W41) | AJ41: =SUM(X41:AA41)
D42: Net cash provided by (used in) operating activities | F42: =SUM(F14:F41) | G42: =SUM(G14:G41) | H42: =SUM(H14:H41) | I42: =SUM(I14:I41) | J42: =SUM(J14:J41) | K42: =SUM(K14:K41) | L42: =SUM(L14:L41) | M42: =SUM(M14:M41) | ... AA42: =SUM(AA14:AA41) | AC42: =SUM(AC14:AC41) | AD42: =SUM(AD14:AD41) | AE42: =SUM(AE14:AE41) | AF42: =SUM(AF14:AF41) | AG42: =SUM(AG14:AG41) | AI42: =SUM(AI14:AI41) | AJ42: =SUM(AJ14:AJ41)
D43: Net cash provided by (used in) operating activities | F43: 117 | G43: =331-117 | H43: =431-331 | I43: =629-431 | J43: 66 | K43: =-19-66 | L43: =-27-(-19) | M43: =159-(-27) | N43: 78 | O43: =173-78 | P43: =297-173 | Q43: =686-297 | R43: -79 | S43: =44-(-79) | T43: =160-44 | U43: =511-160 | V43: -89 | W43: =-100-(-89) | X43: =16-(-100) | Y43: =224-16 | Z43: -144 | AA43: =-107-(-144) | AC43: 629 | AD43: 159 | AE43: 686 | AF43: 511 | AG43: 224 | AI43: =SUM(T43:W43) | AJ43: =SUM(X43:AA43)
D44: Check | F44: =F42-F43 | G44: =G42-G43 | H44: =H42-H43 | I44: =I42-I43 | J44: =J42-J43 | K44: =K42-K43 | L44: =L42-L43 | M44: =M42-M43 | ... AA44: =AA42-AA43 | AC44: =AC42-AC43 | AD44: =AD42-AD43 | AE44: =AE42-AE43 | AF44: =AF42-AF43 | AG44: =AG42-AG43
D46: Memo: Change in NWC | F46: =F31+F32+SUM(F35:F40) | G46: =G31+G32+SUM(G35:G40) | H46: =H31+H32+SUM(H35:H40) | I46: =I31+I32+SUM(I35:I40) | J46: =J31+J32+SUM(J35:J40) | K46: =K31+K32+SUM(K35:K40) | L46: =L31+L32+SUM(L35:L40) | M46: =M31+M32+SUM(M35:M40) | ... AA46: =AA31+AA32+SUM(AA35:AA40) | AC46: =AC31+AC32+SUM(AC35:AC40) | AD46: =AD31+AD32+SUM(AD35:AD40) | AE46: =AE31+AE32+SUM(AE35:AE40) | AF46: =AF31+AF32+SUM(AF35:AF40) | AG46: =AG31+AG32+SUM(AG35:AG40) | AI46: =AI31+AI32+SUM(AI35:AI40) | AJ46: =AJ31+AJ32+SUM(AJ35:AJ40)
D48: INVESTING ACTIVITIES
D49: Cost of additions to land, buildings, equipment and software | F49: -17 | G49: =-33-F49 | H49: =-52-SUM(F49:G49) | I49: =AC49-SUM(F49:H49) | J49: -16 | K49: =-29-J49 | L49: =-39-SUM(J49:K49) | M49: =AD49-SUM(J49:L49) | N49: -8 | O49: =-15-N49 | P49: =-27-SUM(N49:O49) | Q49: =AE49-SUM(N49:P49) | R49: -10 | S49: =-18-R49 | T49: =-27-SUM(R49:S49) | U49: =AF49-SUM(R49:T49) | V49: -20 | W49: =-39-V49 | X49: =-67-SUM(V49:W49) | Y49: =AG49-SUM(V49:X49) | Z49: -21 | AA49: =-47-Z49 | AC49: -68 | AD49: -57 | AE49: -37 | AF49: -44 | AG49: -91 | AI49: =SUM(T49:W49) | AJ49: =SUM(X49:AA49)
D50: Proceeds from sales of businesses and assets | F50: 0 | G50: =1-F50 | H50: =39-SUM(F50:G50) | I50: =AC50-SUM(F50:H50) | J50: 0 | K50: =26-J50 | L50: =49-SUM(J50:K50) | M50: =AD50-SUM(J50:L50) | N50: 1 | O50: =3-N50 | P50: =40-SUM(N50:O50) | Q50: =AE50-SUM(N50:P50) | R50: 4 | S50: =19-R50 | T50: =27-SUM(R50:S50) | U50: =AF50-SUM(R50:T50) | V50: 27 | W50: =30-V50 | X50: =56-SUM(V50:W50) | Y50: =AG50-SUM(V50:X50) | Z50: 2 | AA50: =8-Z50 | AC50: 44 | AD50: 87 | AE50: 43 | AF50: 35 | AG50: 79 | AI50: =SUM(T50:W50) | AJ50: =SUM(X50:AA50)
D51: Acquisitions, net of cash acquired | F51: 0 | G51: =-37-F51 | H51: =-38-SUM(F51:G51) | I51: =AC51-SUM(F51:H51) | J51: -54 | K51: =-52-J51 | L51: =-93-SUM(J51:K51) | M51: =AD51-SUM(J51:L51) | N51: -7 | O51: =-7-N51 | P51: =-7-SUM(N51:O51) | Q51: =AE51-SUM(N51:P51) | R51: 0 | S51: =0-R51 | T51: =0-SUM(R51:S51) | U51: =AF51-SUM(R51:T51) | V51: 1 | W51: =1-V51 | X51: =-674-SUM(V51:W51) | Y51: =AG51-SUM(V51:X51) | Z51: 0 | AA51: =19-Z51 | AC51: -53 | AD51: -93 | AE51: -7 | AF51: -161 | AG51: -674 | AI51: =SUM(T51:W51) | AJ51: =SUM(X51:AA51)
D52: Other investing, net | F52: 0 | G52: =-3-F52 | H52: =-3-SUM(F52:G52) | I52: =AC52-SUM(F52:H52) | J52: -5 | K52: =-7-J52 | L52: =-12-SUM(J52:K52) | M52: =AD52-SUM(J52:L52) | N52: -3 | O52: =-3-N52 | P52: =-3-SUM(N52:O52) | Q52: =AE52-SUM(N52:P52) | R52: -11 | S52: =-20-R52 | T52: =-26-SUM(R52:S52) | U52: =AF52-SUM(R52:T52) | V52: -2 | W52: =-4-V52 | X52: =-9-SUM(V52:W52) | Y52: =AG52-SUM(V52:X52) | Z52: -5 | AA52: =-13-Z52 | AC52: -8 | AD52: -15 | AE52: -4 | AF52: -28 | AG52: -12 | AI52: =SUM(T52:W52) | AJ52: =SUM(X52:AA52)
D53: Net cash provided by (used in) investing activities | F53: =SUM(F49:F52) | G53: =SUM(G49:G52) | H53: =SUM(H49:H52) | I53: =SUM(I49:I52) | J53: =SUM(J49:J52) | K53: =SUM(K49:K52) | L53: =SUM(L49:L52) | M53: =SUM(M49:M52) | ... AA53: =SUM(AA49:AA52) | AC53: =SUM(AC49:AC52) | AD53: =SUM(AD49:AD52) | AE53: =SUM(AE49:AE52) | AF53: =SUM(AF49:AF52) | AG53: =SUM(AG49:AG52) | AI53: =SUM(AI49:AI52) | AJ53: =SUM(AJ49:AJ52)
D54: Net cash provided by (used in) investing activities | F54: -17 | G54: =-72-(-17) | H54: =-54-(-72) | I54: =-85-(-54) | J54: -75 | K54: =-62-(-75) | L54: =-95-(-62) | M54: =-78-(-95) | N54: -17 | O54: =-22-(-17) | P54: =3-(-22) | Q54: =-5-3 | R54: -17 | S54: =-19-(-17) | T54: =-26-(-19) | U54: =-198-(-26) | V54: 6 | W54: =-12-6 | X54: =-694-(-12) | Y54: =-698-(-694) | Z54: -24 | AA54: =-33-(-24) | AC54: -85 | AD54: -78 | AE54: -5 | AF54: -198 | AG54: -698 | AI54: =SUM(T54:W54) | AJ54: =SUM(X54:AA54)
D55: Check | F55: =F53-F54 | G55: =G53-G54 | H55: =H53-H54 | I55: =I53-I54 | J55: =J53-J54 | K55: =K53-K54 | L55: =L53-L54 | M55: =M53-M54 | ... AA55: =AA53-AA54 | AC55: =AC53-AC54 | AD55: =AD53-AD54 | AE55: =AE53-AE54 | AF55: =AF53-AF54 | AG55: =AG53-AG54
D57: FINANCING ACTIVITIES
D58: Net proceeds (payments) on short-term debt | F58: 0 | G58: =0-F58 | H58: =1-SUM(F58:G58) | I58: =AC58-SUM(F58:H58) | J58: 0 | K58: =0-J58 | L58: =0-SUM(J58:K58) | M58: =AD58-SUM(J58:L58) | N58: 0 | O58: =200-N58 | P58: =220-SUM(N58:O58) | Q58: =AE58-SUM(N58:P58) | R58: 0 | S58: =0-R58 | T58: =0-SUM(R58:S58) | U58: =AF58-SUM(R58:T58) | V58: 0 | W58: =0-V58 | X58: =218-SUM(V58:W58) | Y58: =AG58-SUM(V58:X58) | Z58: 0 | AA58: =-125-Z58 | AC58: 0 | AD58: 0 | AE58: 0 | AF58: 0 | AG58: 119 | AI58: =SUM(T58:W58) | AJ58: =SUM(X58:AA58)
D59: Proceeds from issuance of long-term debt | F59: 0 | G59: =0-F59 | H59: =311-SUM(F59:G59) | I59: =AC59-SUM(F59:H59) | J59: 668 | K59: =754-J59 | L59: =754-SUM(J59:K59) | M59: =AD59-SUM(J59:L59) | N59: 0 | O59: =0-N59 | P59: =646-SUM(N59:O59) | Q59: =AE59-SUM(N59:P59) | R59: 905 | S59: =906-R59 | T59: =906-SUM(R59:S59) | U59: =AF59-SUM(R59:T59) | V59: 3 | W59: =889-V59 | X59: =1137-SUM(V59:W59) | Y59: =AG59-SUM(V59:X59) | Z59: 446 | AA59: =446-Z59 | AC59: 311 | AD59: 1194 | AE59: 1396 | AF59: 907 | AG59: 1140 | AI59: =SUM(T59:W59) | AJ59: =SUM(X59:AA59)
D60: Payments on long-term debt | F60: -95 | G60: =-209-F60 | H60: =-445-SUM(F60:G60) | I60: =AC60-SUM(F60:H60) | J60: -646 | K60: =-1133-J60 | L60: =-1259-SUM(J60:K60) | M60: =AD60-SUM(J60:L60) | N60: -452 | O60: =-826-N60 | P60: =-997-SUM(N60:O60) | Q60: =AE60-SUM(N60:P60) | R60: -570 | S60: =-871-R60 | T60: =-913-SUM(R60:S60) | U60: =AF60-SUM(R60:T60) | V60: -107 | W60: =-343-V60 | X60: =-685-SUM(V60:W60) | Y60: =AG60-SUM(V60:X60) | Z60: -191 | AA60: =-251-Z60 | AC60: -519 | AD60: -1723 | AE60: -1874 | AF60: -992 | AG60: -755 | AI60: =SUM(T60:W60) | AJ60: =SUM(X60:AA60)
D61: Tariff receivables monetization | Z61: 0 | AA61: =80-Z61 | AI61: =SUM(T61:W61) | AJ61: =SUM(X61:AA61)
D62: Purchases of capped calls | R62: -23 | S62: =-23-R62 | T62: =-23-SUM(R62:S62) | U62: =AF62-SUM(R62:T62) | V62: 0 | W62: =0-V62 | X62: =0-SUM(V62:W62) | Y62: =AG62-SUM(V62:X62) | AF62: -23 | AG62: 0 | AI62: =SUM(T62:W62) | AJ62: =SUM(X62:AA62)
D63: Dividends | F63: -54 | G63: =-108-F63 | H63: =-157-SUM(F63:G63) | I63: =AC63-SUM(F63:H63) | J63: -46 | K63: =-88-J63 | L63: =-131-SUM(J63:K63) | M63: =AD63-SUM(J63:L63) | N63: -45 | O63: =-88-N63 | P63: =-131-SUM(N63:O63) | Q63: =AE63-SUM(N63:P63) | R63: -37 | S63: =-71-R63 | T63: =-107-SUM(R63:S63) | U63: =AF63-SUM(R63:T63) | V63: -39 | W63: =-58-V63 | X63: =-65-SUM(V63:W63) | Y63: =AG63-SUM(V63:X63) | Z63: -10 | AA63: =-16-Z63 | AC63: -206 | AD63: -174 | AE63: -165 | AF63: -141 | AG63: -71 | AI63: =SUM(T63:W63) | AJ63: =SUM(X63:AA63)
D64: Payments to acquire treasury stock, including fees | F64: -162 | G64: =-413-F64 | H64: =-500-SUM(F64:G64) | I64: =AC64-SUM(F64:H64) | J64: -113 | K64: =-113-J64 | L64: =-113-SUM(J64:K64) | M64: =AD64-SUM(J64:L64) | N64: 0 | O64: =0-N64 | P64: =-544-SUM(N64:O64) | Q64: =AE64-SUM(N64:P64) | R64: -3 | S64: =-3-R64 | T64: =-3-SUM(R64:S64) | U64: =AF64-SUM(R64:T64) | V64: 0 | W64: =0-V64 | X64: =0-SUM(V64:W64) | Y64: =AG64-SUM(V64:X64) | AC64: -888 | AD64: -113 | AE64: -544 | AF64: -8 | AG64: 0 | AI64: =SUM(T64:W64) | AJ64: =SUM(X64:AA64)
D65: Other financing, net | F65: -7 | G65: =-17-F65 | H65: =-3-SUM(F65:G65) | I65: =AC65-SUM(F65:H65) | J65: -12 | K65: =-7-J65 | L65: =-6-SUM(J65:K65) | M65: =AD65-SUM(J65:L65) | N65: -8 | O65: =-11-N65 | P65: =-13-SUM(N65:O65) | Q65: =AE65-SUM(N65:P65) | R65: -11 | S65: =-13-R65 | T65: =-9-SUM(R65:S65) | U65: =AF65-SUM(R65:T65) | V65: -16 | W65: =-29-V65 | X65: =-28-SUM(V65:W65) | Y65: =AG65-SUM(V65:X65) | Z65: -3 | AA65: =-6-Z65 | AC65: -8 | AD65: -6 | AE65: -15 | AF65: -14 | AG65: -29 | AI65: =SUM(T65:W65) | AJ65: =SUM(X65:AA65)
D66: Net cash provided by (used in) financing activities | F66: =SUM(F58:F65) | G66: =SUM(G58:G65) | H66: =SUM(H58:H65) | I66: =SUM(I58:I65) | J66: =SUM(J58:J65) | K66: =SUM(K58:K65) | L66: =SUM(L58:L65) | M66: =SUM(M58:M65) | ... AA66: =SUM(AA58:AA65) | AC66: =SUM(AC58:AC65) | AD66: =SUM(AD58:AD65) | AE66: =SUM(AE58:AE65) | AF66: =SUM(AF58:AF65) | AG66: =SUM(AG58:AG65) | AI66: =SUM(AI58:AI65) | AJ66: =SUM(AJ58:AJ65)
D67: Net cash provided by (used in) financing activities | F67: -318 | G67: =-747-(-318) | H67: =-793-(-747) | I67: =-1310-(-793) | J67: -149 | K67: =-587-(-149) | L67: =-755-(-587) | M67: =-822-(-755) | N67: -505 | O67: =-725-(-505) | P67: =-819-(-725) | Q67: =-1202-(-819) | R67: 261 | S67: =-75-261 | T67: =-149-(-75) | U67: =-271-(-149) | V67: -159 | W67: =459-(-159) | X67: =577-459 | Y67: =404-577 | Z67: 242 | AA67: =128-242 | AC67: -1310 | AD67: -822 | AE67: -1202 | AF67: -271 | AG67: 404 | AI67: =SUM(T67:W67) | AJ67: =SUM(X67:AA67)
D68: Check | F68: =F66-F67 | G68: =G66-G67 | H68: =H66-H67 | I68: =I66-I67 | J68: =J66-J67 | K68: =K66-K67 | L68: =L66-L67 | M68: =M66-M67 | ... AA68: =AA66-AA67 | AC68: =AC66-AC67 | AD68: =AD66-AD67 | AE68: =AE66-AE67 | AF68: =AF66-AF67 | AG68: =AG66-AG67
D70: Effect of exchange rate changes on cash, cash equivalents and restricted cash | F70: -12 | G70: =0-F70 | H70: =-13-SUM(F70:G70) | I70: =AC70-SUM(F70:H70) | J70: 10 | K70: =-14-J70 | L70: =-31-SUM(J70:K70) | M70: =AD70-SUM(J70:L70) | N70: 2 | O70: =4-N70 | P70: =-3-SUM(N70:O70) | Q70: =AE70-SUM(N70:P70) | R70: -10 | S70: =-16-R70 | T70: =-12-SUM(R70:S70) | U70: =AF70-SUM(R70:T70) | V70: 1 | W70: =7-V70 | X70: =5-SUM(V70:W70) | Y70: =AG70-SUM(V70:X70) | Z70: -2 | AA70: =-1-Z70 | AC70: -16 | AD70: -29 | AE70: -1 | AF70: -28 | AG70: 4 | AI70: =SUM(T70:W70) | AJ70: =SUM(X70:AA70)
D71: Net increase (decrease) in cash, cash equivalents and restricted cash | F71: =F42+F53+F66+F70 | G71: =G42+G53+G66+G70 | H71: =H42+H53+H66+H70 | I71: =I42+I53+I66+I70 | J71: =J42+J53+J66+J70 | K71: =K42+K53+K66+K70 | L71: =L42+L53+L66+L70 | M71: =M42+M53+M66+M70 | ... AA71: =AA42+AA53+AA66+AA70 | AC71: =AC42+AC53+AC66+AC70 | AD71: =AD42+AD53+AD66+AD70 | AE71: =AE42+AE53+AE66+AE70 | AF71: =AF42+AF53+AF66+AF70 | AG71: =AG42+AG53+AG66+AG70 | AI71: =AI42+AI53+AI66+AI70 | AJ71: =AJ42+AJ53+AJ66+AJ70
D72: Net increase (decrease) in cash, cash equivalents and restricted cash | F72: -230 | G72: =-488-(-230) | H72: =-429-(-488) | I72: =-782-(-429) | J72: -148 | K72: =-682-(-148) | L72: =-908-(-682) | M72: =-770-(-908) | N72: -442 | O72: =-570-(-442) | P72: =-522-(-570) | Q72: =-522-(-522) | R72: 155 | S72: =-66-155 | T72: =-27-(-66) | U72: =14-(-27) | V72: -241 | W72: =354-(-241) | X72: =-96-354 | Y72: =-66-(-96) | Z72: 72 | AA72: =-13-72 | AC72: -782 | AD72: -770 | AE72: -522 | AF72: 14 | AG72: -66 | AI72: =SUM(T72:W72) | AJ72: =SUM(X72:AA72)
D73: Check | F73: =F71-F72 | G73: =G71-G72 | H73: =H71-H72 | I73: =I71-I72 | J73: =J71-J72 | K73: =K71-K72 | L73: =L71-L72 | M73: =M71-M72 | ... AA73: =AA71-AA72 | AC73: =AC71-AC72 | AD73: =AD71-AD72 | AE73: =AE71-AE72 | AF73: =AF71-AF72 | AG73: =AG71-AG72
D75: Cash, cash equivalents and restricted cash, beginning | F75: 2691 | G75: =F76 | H75: =G76 | I75: =H76 | J75: 1909 | K75: =J76 | L75: =K76 | M75: =L76 | N75: 1139 | O75: =N76 | P75: =O76 | Q75: =P76 | R75: 617 | S75: =R76 | T75: =S76 | U75: =T76 | V75: 631 | W75: =V76 | X75: =W76 | Y75: =X76 | Z75: 565 | AA75: =Z76 | AC75: 2691 | AD75: 1909 | AE75: 1139 | AF75: 617 | AG75: 631 | AI75: =T75 | AJ75: =X75
D76: Cash, cash equivalents and restricted cash, ending | F76: =F71+F75 | G76: =G71+G75 | H76: =H71+H75 | I76: =I71+I75 | J76: =J71+J75 | K76: =K71+K75 | L76: =L71+L75 | M76: =M71+M75 | ... AA76: =AA71+AA75 | AC76: =AC71+AC75 | AD76: =AD71+AD75 | AE76: =AE71+AE75 | AF76: =AF71+AF75 | AG76: =AG71+AG75 | AI76: =AI71+AI75 | AJ76: =AJ71+AJ75
D77: Cash, cash equivalents and restricted cash, ending | F77: 2461 | G77: 2203 | H77: 2262 | I77: 1909 | J77: 1761 | K77: 1227 | L77: 1001 | M77: 1139 | N77: 697 | O77: 569 | P77: 617 | Q77: 617 | R77: 772 | S77: 551 | T77: 590 | U77: 631 | V77: 390 | W77: 985 | X77: 535 | Y77: 565 | Z77: 637 | AA77: 552 | AC77: 1909 | AD77: 1139 | AE77: 617 | AF77: 631 | AG77: 565 | AI77: =W77 | AJ77: =AA77
D78: Check | F78: =F76-F77 | G78: =G76-G77 | H78: =H76-H77 | I78: =I76-I77 | J78: =J76-J77 | K78: =K76-K77 | L78: =L76-L77 | M78: =M76-M77 | ... AA78: =AA76-AA77 | AC78: =AC76-AC77 | AD78: =AD76-AD77 | AE78: =AE76-AE77 | AF78: =AF76-AF77 | AG78: =AG76-AG77
D80: Notes:
D81: (1) 10-Qs report year-to-date cash flows. Discrete quarters: Q1 as reported; Q2 = H1 - Q1; Q3 = 9M - H1; Q4 = FY (10-K) - 9M. Each year uses its own 10-Qs and 10-K so the vintages match.
D82: (2) Deferred taxes appear separately only in the 10-K; they are combined with income tax assets and liabilities so quarters are comparable.
D83: (3) 2021 retirement lines are as originally captioned (defined benefit pension cost and contributions); from 2022 Xerox includes retiree health in these lines.
D84: (4) Lexmark acquired July 1, 2025: cash paid of $674M net of cash acquired sits in acquisitions (3Q'25). Tariff receivables monetization (2Q'26) is classified by Xerox as a financing inflow.
D85: (5) Cash basis is cash, cash equivalents and restricted cash, consistent in every period shown.

Sheet CFS Out
A1: =D3 | B1: ='Cover Page'!A1
D3: Cash Flow Statement Summary
D4: Xerox Holdings Corporation – All values in $ millions (USD), except per-share values. Data as of June 30, 2026 (2Q'26).
A8: x | D8: Cash Flow Statement Summary | E8: Year Ended December 31, | K8: Quarter Ended
E10: 2021 | F10: 2022 | G10: 2023 | H10: 2024 | I10: 2025 | J10: LTM 2Q'26 | K10: 2Q'25 | L10: 2Q'26
D12: Net (loss) income | E12: =SUMIFS(CFS!$F$14:$AJ$14,CFS!$F$11:$AJ$11,E$10) | F12: =SUMIFS(CFS!$F$14:$AJ$14,CFS!$F$11:$AJ$11,F$10) | G12: =SUMIFS(CFS!$F$14:$AJ$14,CFS!$F$11:$AJ$11,G$10) | H12: =SUMIFS(CFS!$F$14:$AJ$14,CFS!$F$11:$AJ$11,H$10) | I12: =SUMIFS(CFS!$F$14:$AJ$14,CFS!$F$11:$AJ$11,I$10) | J12: =SUMIFS(CFS!$F$14:$AJ$14,CFS!$F$11:$AJ$11,J$10) | K12: =SUMIFS(CFS!$F$14:$AJ$14,CFS!$F$11:$AJ$11,K$10) | L12: =SUMIFS(CFS!$F$14:$AJ$14,CFS!$F$11:$AJ$11,L$10)
D13: Depreciation and amortization | E13: =SUMIFS(CFS!$F$16:$AJ$16,CFS!$F$11:$AJ$11,E$10) | F13: =SUMIFS(CFS!$F$16:$AJ$16,CFS!$F$11:$AJ$11,F$10) | G13: =SUMIFS(CFS!$F$16:$AJ$16,CFS!$F$11:$AJ$11,G$10) | H13: =SUMIFS(CFS!$F$16:$AJ$16,CFS!$F$11:$AJ$11,H$10) | I13: =SUMIFS(CFS!$F$16:$AJ$16,CFS!$F$11:$AJ$11,I$10) | J13: =SUMIFS(CFS!$F$16:$AJ$16,CFS!$F$11:$AJ$11,J$10) | K13: =SUMIFS(CFS!$F$16:$AJ$16,CFS!$F$11:$AJ$11,K$10) | L13: =SUMIFS(CFS!$F$16:$AJ$16,CFS!$F$11:$AJ$11,L$10)
D14: Goodwill impairment | E14: =SUMIFS(CFS!$F$24:$AJ$24,CFS!$F$11:$AJ$11,E$10) | F14: =SUMIFS(CFS!$F$24:$AJ$24,CFS!$F$11:$AJ$11,F$10) | G14: =SUMIFS(CFS!$F$24:$AJ$24,CFS!$F$11:$AJ$11,G$10) | H14: =SUMIFS(CFS!$F$24:$AJ$24,CFS!$F$11:$AJ$11,H$10) | I14: =SUMIFS(CFS!$F$24:$AJ$24,CFS!$F$11:$AJ$11,I$10) | J14: =SUMIFS(CFS!$F$24:$AJ$24,CFS!$F$11:$AJ$11,J$10) | K14: =SUMIFS(CFS!$F$24:$AJ$24,CFS!$F$11:$AJ$11,K$10) | L14: =SUMIFS(CFS!$F$24:$AJ$24,CFS!$F$11:$AJ$11,L$10)
D15: Stock-based compensation | E15: =SUMIFS(CFS!$F$25:$AJ$25,CFS!$F$11:$AJ$11,E$10) | F15: =SUMIFS(CFS!$F$25:$AJ$25,CFS!$F$11:$AJ$11,F$10) | G15: =SUMIFS(CFS!$F$25:$AJ$25,CFS!$F$11:$AJ$11,G$10) | H15: =SUMIFS(CFS!$F$25:$AJ$25,CFS!$F$11:$AJ$11,H$10) | I15: =SUMIFS(CFS!$F$25:$AJ$25,CFS!$F$11:$AJ$11,I$10) | J15: =SUMIFS(CFS!$F$25:$AJ$25,CFS!$F$11:$AJ$11,J$10) | K15: =SUMIFS(CFS!$F$25:$AJ$25,CFS!$F$11:$AJ$11,K$10) | L15: =SUMIFS(CFS!$F$25:$AJ$25,CFS!$F$11:$AJ$11,L$10)
D16: Provisions | E16: =SUMIFS(CFS!$F$17:$AJ$17,CFS!$F$11:$AJ$11,E$10) | F16: =SUMIFS(CFS!$F$17:$AJ$17,CFS!$F$11:$AJ$11,F$10) | G16: =SUMIFS(CFS!$F$17:$AJ$17,CFS!$F$11:$AJ$11,G$10) | H16: =SUMIFS(CFS!$F$17:$AJ$17,CFS!$F$11:$AJ$11,H$10) | I16: =SUMIFS(CFS!$F$17:$AJ$17,CFS!$F$11:$AJ$11,I$10) | J16: =SUMIFS(CFS!$F$17:$AJ$17,CFS!$F$11:$AJ$11,J$10) | K16: =SUMIFS(CFS!$F$17:$AJ$17,CFS!$F$11:$AJ$11,K$10) | L16: =SUMIFS(CFS!$F$17:$AJ$17,CFS!$F$11:$AJ$11,L$10)
D17: Restructuring and asset impairment charges | E17: =SUMIFS(CFS!$F$26:$AJ$26,CFS!$F$11:$AJ$11,E$10) | F17: =SUMIFS(CFS!$F$26:$AJ$26,CFS!$F$11:$AJ$11,F$10) | G17: =SUMIFS(CFS!$F$26:$AJ$26,CFS!$F$11:$AJ$11,G$10) | H17: =SUMIFS(CFS!$F$26:$AJ$26,CFS!$F$11:$AJ$11,H$10) | I17: =SUMIFS(CFS!$F$26:$AJ$26,CFS!$F$11:$AJ$11,I$10) | J17: =SUMIFS(CFS!$F$26:$AJ$26,CFS!$F$11:$AJ$11,J$10) | K17: =SUMIFS(CFS!$F$26:$AJ$26,CFS!$F$11:$AJ$11,K$10) | L17: =SUMIFS(CFS!$F$26:$AJ$26,CFS!$F$11:$AJ$11,L$10)
D18: Payments for restructurings | E18: =SUMIFS(CFS!$F$27:$AJ$27,CFS!$F$11:$AJ$11,E$10) | F18: =SUMIFS(CFS!$F$27:$AJ$27,CFS!$F$11:$AJ$11,F$10) | G18: =SUMIFS(CFS!$F$27:$AJ$27,CFS!$F$11:$AJ$11,G$10) | H18: =SUMIFS(CFS!$F$27:$AJ$27,CFS!$F$11:$AJ$11,H$10) | I18: =SUMIFS(CFS!$F$27:$AJ$27,CFS!$F$11:$AJ$11,I$10) | J18: =SUMIFS(CFS!$F$27:$AJ$27,CFS!$F$11:$AJ$11,J$10) | K18: =SUMIFS(CFS!$F$27:$AJ$27,CFS!$F$11:$AJ$11,K$10) | L18: =SUMIFS(CFS!$F$27:$AJ$27,CFS!$F$11:$AJ$11,L$10)
D19: Contributions to retirement plans | E19: =SUMIFS(CFS!$F$29:$AJ$29,CFS!$F$11:$AJ$11,E$10) | F19: =SUMIFS(CFS!$F$29:$AJ$29,CFS!$F$11:$AJ$11,F$10) | G19: =SUMIFS(CFS!$F$29:$AJ$29,CFS!$F$11:$AJ$11,G$10) | H19: =SUMIFS(CFS!$F$29:$AJ$29,CFS!$F$11:$AJ$11,H$10) | I19: =SUMIFS(CFS!$F$29:$AJ$29,CFS!$F$11:$AJ$11,I$10) | J19: =SUMIFS(CFS!$F$29:$AJ$29,CFS!$F$11:$AJ$11,J$10) | K19: =SUMIFS(CFS!$F$29:$AJ$29,CFS!$F$11:$AJ$11,K$10) | L19: =SUMIFS(CFS!$F$29:$AJ$29,CFS!$F$11:$AJ$11,L$10)
D20: Decrease (increase) in finance receivables | E20: =SUMIFS(CFS!$F$34:$AJ$34,CFS!$F$11:$AJ$11,E$10) | F20: =SUMIFS(CFS!$F$34:$AJ$34,CFS!$F$11:$AJ$11,F$10) | G20: =SUMIFS(CFS!$F$34:$AJ$34,CFS!$F$11:$AJ$11,G$10) | H20: =SUMIFS(CFS!$F$34:$AJ$34,CFS!$F$11:$AJ$11,H$10) | I20: =SUMIFS(CFS!$F$34:$AJ$34,CFS!$F$11:$AJ$11,I$10) | J20: =SUMIFS(CFS!$F$34:$AJ$34,CFS!$F$11:$AJ$11,J$10) | K20: =SUMIFS(CFS!$F$34:$AJ$34,CFS!$F$11:$AJ$11,K$10) | L20: =SUMIFS(CFS!$F$34:$AJ$34,CFS!$F$11:$AJ$11,L$10)
D21: Increase in equipment on operating leases | E21: =SUMIFS(CFS!$F$33:$AJ$33,CFS!$F$11:$AJ$11,E$10) | F21: =SUMIFS(CFS!$F$33:$AJ$33,CFS!$F$11:$AJ$11,F$10) | G21: =SUMIFS(CFS!$F$33:$AJ$33,CFS!$F$11:$AJ$11,G$10) | H21: =SUMIFS(CFS!$F$33:$AJ$33,CFS!$F$11:$AJ$11,H$10) | I21: =SUMIFS(CFS!$F$33:$AJ$33,CFS!$F$11:$AJ$11,I$10) | J21: =SUMIFS(CFS!$F$33:$AJ$33,CFS!$F$11:$AJ$11,J$10) | K21: =SUMIFS(CFS!$F$33:$AJ$33,CFS!$F$11:$AJ$11,K$10) | L21: =SUMIFS(CFS!$F$33:$AJ$33,CFS!$F$11:$AJ$11,L$10)
D22: Change in NWC | E22: =SUMIFS(CFS!$F$46:$AJ$46,CFS!$F$11:$AJ$11,E$10) | F22: =SUMIFS(CFS!$F$46:$AJ$46,CFS!$F$11:$AJ$11,F$10) | G22: =SUMIFS(CFS!$F$46:$AJ$46,CFS!$F$11:$AJ$11,G$10) | H22: =SUMIFS(CFS!$F$46:$AJ$46,CFS!$F$11:$AJ$11,H$10) | I22: =SUMIFS(CFS!$F$46:$AJ$46,CFS!$F$11:$AJ$11,I$10) | J22: =SUMIFS(CFS!$F$46:$AJ$46,CFS!$F$11:$AJ$11,J$10) | K22: =SUMIFS(CFS!$F$46:$AJ$46,CFS!$F$11:$AJ$11,K$10) | L22: =SUMIFS(CFS!$F$46:$AJ$46,CFS!$F$11:$AJ$11,L$10)
D23: Other operating activities | E23: =SUM(E24:E31) | F23: =SUM(F24:F31) | G23: =SUM(G24:G31) | H23: =SUM(H24:H31) | I23: =SUM(I24:I31) | J23: =SUM(J24:J31) | K23: =SUM(K24:K31) | L23: =SUM(L24:L31)
D24: Non-service retirement-related costs | E24: =SUMIFS(CFS!$F$28:$AJ$28,CFS!$F$11:$AJ$11,E$10) | F24: =SUMIFS(CFS!$F$28:$AJ$28,CFS!$F$11:$AJ$11,F$10) | G24: =SUMIFS(CFS!$F$28:$AJ$28,CFS!$F$11:$AJ$11,G$10) | H24: =SUMIFS(CFS!$F$28:$AJ$28,CFS!$F$11:$AJ$11,H$10) | I24: =SUMIFS(CFS!$F$28:$AJ$28,CFS!$F$11:$AJ$11,I$10) | J24: =SUMIFS(CFS!$F$28:$AJ$28,CFS!$F$11:$AJ$11,J$10) | K24: =SUMIFS(CFS!$F$28:$AJ$28,CFS!$F$11:$AJ$11,K$10) | L24: =SUMIFS(CFS!$F$28:$AJ$28,CFS!$F$11:$AJ$11,L$10)
D25: Net (gain) loss on sales of businesses and assets | E25: =SUMIFS(CFS!$F$19:$AJ$19,CFS!$F$11:$AJ$11,E$10) | F25: =SUMIFS(CFS!$F$19:$AJ$19,CFS!$F$11:$AJ$11,F$10) | G25: =SUMIFS(CFS!$F$19:$AJ$19,CFS!$F$11:$AJ$11,G$10) | H25: =SUMIFS(CFS!$F$19:$AJ$19,CFS!$F$11:$AJ$11,H$10) | I25: =SUMIFS(CFS!$F$19:$AJ$19,CFS!$F$11:$AJ$11,I$10) | J25: =SUMIFS(CFS!$F$19:$AJ$19,CFS!$F$11:$AJ$11,J$10) | K25: =SUMIFS(CFS!$F$19:$AJ$19,CFS!$F$11:$AJ$11,K$10) | L25: =SUMIFS(CFS!$F$19:$AJ$19,CFS!$F$11:$AJ$11,L$10)
D26: Net (gain) loss on early extinguishment of debt | E26: =SUMIFS(CFS!$F$18:$AJ$18,CFS!$F$11:$AJ$11,E$10) | F26: =SUMIFS(CFS!$F$18:$AJ$18,CFS!$F$11:$AJ$11,F$10) | G26: =SUMIFS(CFS!$F$18:$AJ$18,CFS!$F$11:$AJ$11,G$10) | H26: =SUMIFS(CFS!$F$18:$AJ$18,CFS!$F$11:$AJ$11,H$10) | I26: =SUMIFS(CFS!$F$18:$AJ$18,CFS!$F$11:$AJ$11,I$10) | J26: =SUMIFS(CFS!$F$18:$AJ$18,CFS!$F$11:$AJ$11,J$10) | K26: =SUMIFS(CFS!$F$18:$AJ$18,CFS!$F$11:$AJ$11,K$10) | L26: =SUMIFS(CFS!$F$18:$AJ$18,CFS!$F$11:$AJ$11,L$10)
D27: Lexmark inventory purchase accounting adjustment, noncash | E27: =SUMIFS(CFS!$F$20:$AJ$20,CFS!$F$11:$AJ$11,E$10) | F27: =SUMIFS(CFS!$F$20:$AJ$20,CFS!$F$11:$AJ$11,F$10) | G27: =SUMIFS(CFS!$F$20:$AJ$20,CFS!$F$11:$AJ$11,G$10) | H27: =SUMIFS(CFS!$F$20:$AJ$20,CFS!$F$11:$AJ$11,H$10) | I27: =SUMIFS(CFS!$F$20:$AJ$20,CFS!$F$11:$AJ$11,I$10) | J27: =SUMIFS(CFS!$F$20:$AJ$20,CFS!$F$11:$AJ$11,J$10) | K27: =SUMIFS(CFS!$F$20:$AJ$20,CFS!$F$11:$AJ$11,K$10) | L27: =SUMIFS(CFS!$F$20:$AJ$20,CFS!$F$11:$AJ$11,L$10)
D28: Effective settlement of pre-existing Lexmark relationship | E28: =SUMIFS(CFS!$F$21:$AJ$21,CFS!$F$11:$AJ$11,E$10) | F28: =SUMIFS(CFS!$F$21:$AJ$21,CFS!$F$11:$AJ$11,F$10) | G28: =SUMIFS(CFS!$F$21:$AJ$21,CFS!$F$11:$AJ$11,G$10) | H28: =SUMIFS(CFS!$F$21:$AJ$21,CFS!$F$11:$AJ$11,H$10) | I28: =SUMIFS(CFS!$F$21:$AJ$21,CFS!$F$11:$AJ$11,I$10) | J28: =SUMIFS(CFS!$F$21:$AJ$21,CFS!$F$11:$AJ$11,J$10) | K28: =SUMIFS(CFS!$F$21:$AJ$21,CFS!$F$11:$AJ$11,K$10) | L28: =SUMIFS(CFS!$F$21:$AJ$21,CFS!$F$11:$AJ$11,L$10)
D29: Divestitures | E29: =SUMIFS(CFS!$F$22:$AJ$22,CFS!$F$11:$AJ$11,E$10) | F29: =SUMIFS(CFS!$F$22:$AJ$22,CFS!$F$11:$AJ$11,F$10) | G29: =SUMIFS(CFS!$F$22:$AJ$22,CFS!$F$11:$AJ$11,G$10) | H29: =SUMIFS(CFS!$F$22:$AJ$22,CFS!$F$11:$AJ$11,H$10) | I29: =SUMIFS(CFS!$F$22:$AJ$22,CFS!$F$11:$AJ$11,I$10) | J29: =SUMIFS(CFS!$F$22:$AJ$22,CFS!$F$11:$AJ$11,J$10) | K29: =SUMIFS(CFS!$F$22:$AJ$22,CFS!$F$11:$AJ$11,K$10) | L29: =SUMIFS(CFS!$F$22:$AJ$22,CFS!$F$11:$AJ$11,L$10)
D30: PARC donation | E30: =SUMIFS(CFS!$F$23:$AJ$23,CFS!$F$11:$AJ$11,E$10) | F30: =SUMIFS(CFS!$F$23:$AJ$23,CFS!$F$11:$AJ$11,F$10) | G30: =SUMIFS(CFS!$F$23:$AJ$23,CFS!$F$11:$AJ$11,G$10) | H30: =SUMIFS(CFS!$F$23:$AJ$23,CFS!$F$11:$AJ$11,H$10) | I30: =SUMIFS(CFS!$F$23:$AJ$23,CFS!$F$11:$AJ$11,I$10) | J30: =SUMIFS(CFS!$F$23:$AJ$23,CFS!$F$11:$AJ$11,J$10) | K30: =SUMIFS(CFS!$F$23:$AJ$23,CFS!$F$11:$AJ$11,K$10) | L30: =SUMIFS(CFS!$F$23:$AJ$23,CFS!$F$11:$AJ$11,L$10)
D31: Other operating, net | E31: =SUMIFS(CFS!$F$41:$AJ$41,CFS!$F$11:$AJ$11,E$10) | F31: =SUMIFS(CFS!$F$41:$AJ$41,CFS!$F$11:$AJ$11,F$10) | G31: =SUMIFS(CFS!$F$41:$AJ$41,CFS!$F$11:$AJ$11,G$10) | H31: =SUMIFS(CFS!$F$41:$AJ$41,CFS!$F$11:$AJ$11,H$10) | I31: =SUMIFS(CFS!$F$41:$AJ$41,CFS!$F$11:$AJ$11,I$10) | J31: =SUMIFS(CFS!$F$41:$AJ$41,CFS!$F$11:$AJ$11,J$10) | K31: =SUMIFS(CFS!$F$41:$AJ$41,CFS!$F$11:$AJ$11,K$10) | L31: =SUMIFS(CFS!$F$41:$AJ$41,CFS!$F$11:$AJ$11,L$10)
D32: Cash Flow from Operations | E32: =SUM(E12:E23) | F32: =SUM(F12:F23) | G32: =SUM(G12:G23) | H32: =SUM(H12:H23) | I32: =SUM(I12:I23) | J32: =SUM(J12:J23) | K32: =SUM(K12:K23) | L32: =SUM(L12:L23)
D33: CFO | E33: =SUMIFS(CFS!$F$43:$AJ$43,CFS!$F$11:$AJ$11,E$10) | F33: =SUMIFS(CFS!$F$43:$AJ$43,CFS!$F$11:$AJ$11,F$10) | G33: =SUMIFS(CFS!$F$43:$AJ$43,CFS!$F$11:$AJ$11,G$10) | H33: =SUMIFS(CFS!$F$43:$AJ$43,CFS!$F$11:$AJ$11,H$10) | I33: =SUMIFS(CFS!$F$43:$AJ$43,CFS!$F$11:$AJ$11,I$10) | J33: =SUMIFS(CFS!$F$43:$AJ$43,CFS!$F$11:$AJ$11,J$10) | K33: =SUMIFS(CFS!$F$43:$AJ$43,CFS!$F$11:$AJ$11,K$10) | L33: =SUMIFS(CFS!$F$43:$AJ$43,CFS!$F$11:$AJ$11,L$10)
D34: Check | E34: =E32-E33 | F34: =F32-F33 | G34: =G32-G33 | H34: =H32-H33 | I34: =I32-I33 | J34: =J32-J33 | K34: =K32-K33 | L34: =L32-L33
D36: Capital expenditures | E36: =SUMIFS(CFS!$F$49:$AJ$49,CFS!$F$11:$AJ$11,E$10) | F36: =SUMIFS(CFS!$F$49:$AJ$49,CFS!$F$11:$AJ$11,F$10) | G36: =SUMIFS(CFS!$F$49:$AJ$49,CFS!$F$11:$AJ$11,G$10) | H36: =SUMIFS(CFS!$F$49:$AJ$49,CFS!$F$11:$AJ$11,H$10) | I36: =SUMIFS(CFS!$F$49:$AJ$49,CFS!$F$11:$AJ$11,I$10) | J36: =SUMIFS(CFS!$F$49:$AJ$49,CFS!$F$11:$AJ$11,J$10) | K36: =SUMIFS(CFS!$F$49:$AJ$49,CFS!$F$11:$AJ$11,K$10) | L36: =SUMIFS(CFS!$F$49:$AJ$49,CFS!$F$11:$AJ$11,L$10)
D37: Acquisitions, net of cash acquired | E37: =SUMIFS(CFS!$F$51:$AJ$51,CFS!$F$11:$AJ$11,E$10) | F37: =SUMIFS(CFS!$F$51:$AJ$51,CFS!$F$11:$AJ$11,F$10) | G37: =SUMIFS(CFS!$F$51:$AJ$51,CFS!$F$11:$AJ$11,G$10) | H37: =SUMIFS(CFS!$F$51:$AJ$51,CFS!$F$11:$AJ$11,H$10) | I37: =SUMIFS(CFS!$F$51:$AJ$51,CFS!$F$11:$AJ$11,I$10) | J37: =SUMIFS(CFS!$F$51:$AJ$51,CFS!$F$11:$AJ$11,J$10) | K37: =SUMIFS(CFS!$F$51:$AJ$51,CFS!$F$11:$AJ$11,K$10) | L37: =SUMIFS(CFS!$F$51:$AJ$51,CFS!$F$11:$AJ$11,L$10)
D38: Proceeds from sales of businesses and assets | E38: =SUMIFS(CFS!$F$50:$AJ$50,CFS!$F$11:$AJ$11,E$10) | F38: =SUMIFS(CFS!$F$50:$AJ$50,CFS!$F$11:$AJ$11,F$10) | G38: =SUMIFS(CFS!$F$50:$AJ$50,CFS!$F$11:$AJ$11,G$10) | H38: =SUMIFS(CFS!$F$50:$AJ$50,CFS!$F$11:$AJ$11,H$10) | I38: =SUMIFS(CFS!$F$50:$AJ$50,CFS!$F$11:$AJ$11,I$10) | J38: =SUMIFS(CFS!$F$50:$AJ$50,CFS!$F$11:$AJ$11,J$10) | K38: =SUMIFS(CFS!$F$50:$AJ$50,CFS!$F$11:$AJ$11,K$10) | L38: =SUMIFS(CFS!$F$50:$AJ$50,CFS!$F$11:$AJ$11,L$10)
D39: Other investing activities | E39: =SUM(E40:E40) | F39: =SUM(F40:F40) | G39: =SUM(G40:G40) | H39: =SUM(H40:H40) | I39: =SUM(I40:I40) | J39: =SUM(J40:J40) | K39: =SUM(K40:K40) | L39: =SUM(L40:L40)
D40: Other investing, net | E40: =SUMIFS(CFS!$F$52:$AJ$52,CFS!$F$11:$AJ$11,E$10) | F40: =SUMIFS(CFS!$F$52:$AJ$52,CFS!$F$11:$AJ$11,F$10) | G40: =SUMIFS(CFS!$F$52:$AJ$52,CFS!$F$11:$AJ$11,G$10) | H40: =SUMIFS(CFS!$F$52:$AJ$52,CFS!$F$11:$AJ$11,H$10) | I40: =SUMIFS(CFS!$F$52:$AJ$52,CFS!$F$11:$AJ$11,I$10) | J40: =SUMIFS(CFS!$F$52:$AJ$52,CFS!$F$11:$AJ$11,J$10) | K40: =SUMIFS(CFS!$F$52:$AJ$52,CFS!$F$11:$AJ$11,K$10) | L40: =SUMIFS(CFS!$F$52:$AJ$52,CFS!$F$11:$AJ$11,L$10)
D41: Cash Flow from Investing | E41: =SUM(E36:E39) | F41: =SUM(F36:F39) | G41: =SUM(G36:G39) | H41: =SUM(H36:H39) | I41: =SUM(I36:I39) | J41: =SUM(J36:J39) | K41: =SUM(K36:K39) | L41: =SUM(L36:L39)
D42: CFI | E42: =SUMIFS(CFS!$F$54:$AJ$54,CFS!$F$11:$AJ$11,E$10) | F42: =SUMIFS(CFS!$F$54:$AJ$54,CFS!$F$11:$AJ$11,F$10) | G42: =SUMIFS(CFS!$F$54:$AJ$54,CFS!$F$11:$AJ$11,G$10) | H42: =SUMIFS(CFS!$F$54:$AJ$54,CFS!$F$11:$AJ$11,H$10) | I42: =SUMIFS(CFS!$F$54:$AJ$54,CFS!$F$11:$AJ$11,I$10) | J42: =SUMIFS(CFS!$F$54:$AJ$54,CFS!$F$11:$AJ$11,J$10) | K42: =SUMIFS(CFS!$F$54:$AJ$54,CFS!$F$11:$AJ$11,K$10) | L42: =SUMIFS(CFS!$F$54:$AJ$54,CFS!$F$11:$AJ$11,L$10)
D43: Check | E43: =E41-E42 | F43: =F41-F42 | G43: =G41-G42 | H43: =H41-H42 | I43: =I41-I42 | J43: =J41-J42 | K43: =K41-K42 | L43: =L41-L42
D45: Proceeds from issuance of long-term debt | E45: =SUMIFS(CFS!$F$59:$AJ$59,CFS!$F$11:$AJ$11,E$10) | F45: =SUMIFS(CFS!$F$59:$AJ$59,CFS!$F$11:$AJ$11,F$10) | G45: =SUMIFS(CFS!$F$59:$AJ$59,CFS!$F$11:$AJ$11,G$10) | H45: =SUMIFS(CFS!$F$59:$AJ$59,CFS!$F$11:$AJ$11,H$10) | I45: =SUMIFS(CFS!$F$59:$AJ$59,CFS!$F$11:$AJ$11,I$10) | J45: =SUMIFS(CFS!$F$59:$AJ$59,CFS!$F$11:$AJ$11,J$10) | K45: =SUMIFS(CFS!$F$59:$AJ$59,CFS!$F$11:$AJ$11,K$10) | L45: =SUMIFS(CFS!$F$59:$AJ$59,CFS!$F$11:$AJ$11,L$10)
D46: Payments on long-term debt | E46: =SUMIFS(CFS!$F$60:$AJ$60,CFS!$F$11:$AJ$11,E$10) | F46: =SUMIFS(CFS!$F$60:$AJ$60,CFS!$F$11:$AJ$11,F$10) | G46: =SUMIFS(CFS!$F$60:$AJ$60,CFS!$F$11:$AJ$11,G$10) | H46: =SUMIFS(CFS!$F$60:$AJ$60,CFS!$F$11:$AJ$11,H$10) | I46: =SUMIFS(CFS!$F$60:$AJ$60,CFS!$F$11:$AJ$11,I$10) | J46: =SUMIFS(CFS!$F$60:$AJ$60,CFS!$F$11:$AJ$11,J$10) | K46: =SUMIFS(CFS!$F$60:$AJ$60,CFS!$F$11:$AJ$11,K$10) | L46: =SUMIFS(CFS!$F$60:$AJ$60,CFS!$F$11:$AJ$11,L$10)
D47: Net proceeds (payments) on short-term debt | E47: =SUMIFS(CFS!$F$58:$AJ$58,CFS!$F$11:$AJ$11,E$10) | F47: =SUMIFS(CFS!$F$58:$AJ$58,CFS!$F$11:$AJ$11,F$10) | G47: =SUMIFS(CFS!$F$58:$AJ$58,CFS!$F$11:$AJ$11,G$10) | H47: =SUMIFS(CFS!$F$58:$AJ$58,CFS!$F$11:$AJ$11,H$10) | I47: =SUMIFS(CFS!$F$58:$AJ$58,CFS!$F$11:$AJ$11,I$10) | J47: =SUMIFS(CFS!$F$58:$AJ$58,CFS!$F$11:$AJ$11,J$10) | K47: =SUMIFS(CFS!$F$58:$AJ$58,CFS!$F$11:$AJ$11,K$10) | L47: =SUMIFS(CFS!$F$58:$AJ$58,CFS!$F$11:$AJ$11,L$10)
D48: Dividends | E48: =SUMIFS(CFS!$F$63:$AJ$63,CFS!$F$11:$AJ$11,E$10) | F48: =SUMIFS(CFS!$F$63:$AJ$63,CFS!$F$11:$AJ$11,F$10) | G48: =SUMIFS(CFS!$F$63:$AJ$63,CFS!$F$11:$AJ$11,G$10) | H48: =SUMIFS(CFS!$F$63:$AJ$63,CFS!$F$11:$AJ$11,H$10) | I48: =SUMIFS(CFS!$F$63:$AJ$63,CFS!$F$11:$AJ$11,I$10) | J48: =SUMIFS(CFS!$F$63:$AJ$63,CFS!$F$11:$AJ$11,J$10) | K48: =SUMIFS(CFS!$F$63:$AJ$63,CFS!$F$11:$AJ$11,K$10) | L48: =SUMIFS(CFS!$F$63:$AJ$63,CFS!$F$11:$AJ$11,L$10)
D49: Share repurchases (treasury stock, incl. fees) | E49: =SUMIFS(CFS!$F$64:$AJ$64,CFS!$F$11:$AJ$11,E$10) | F49: =SUMIFS(CFS!$F$64:$AJ$64,CFS!$F$11:$AJ$11,F$10) | G49: =SUMIFS(CFS!$F$64:$AJ$64,CFS!$F$11:$AJ$11,G$10) | H49: =SUMIFS(CFS!$F$64:$AJ$64,CFS!$F$11:$AJ$11,H$10) | I49: =SUMIFS(CFS!$F$64:$AJ$64,CFS!$F$11:$AJ$11,I$10) | J49: =SUMIFS(CFS!$F$64:$AJ$64,CFS!$F$11:$AJ$11,J$10) | K49: =SUMIFS(CFS!$F$64:$AJ$64,CFS!$F$11:$AJ$11,K$10) | L49: =SUMIFS(CFS!$F$64:$AJ$64,CFS!$F$11:$AJ$11,L$10)
D50: Other financing activities | E50: =SUM(E51:E53) | F50: =SUM(F51:F53) | G50: =SUM(G51:G53) | H50: =SUM(H51:H53) | I50: =SUM(I51:I53) | J50: =SUM(J51:J53) | K50: =SUM(K51:K53) | L50: =SUM(L51:L53)
D51: Tariff receivables monetization | E51: =SUMIFS(CFS!$F$61:$AJ$61,CFS!$F$11:$AJ$11,E$10) | F51: =SUMIFS(CFS!$F$61:$AJ$61,CFS!$F$11:$AJ$11,F$10) | G51: =SUMIFS(CFS!$F$61:$AJ$61,CFS!$F$11:$AJ$11,G$10) | H51: =SUMIFS(CFS!$F$61:$AJ$61,CFS!$F$11:$AJ$11,H$10) | I51: =SUMIFS(CFS!$F$61:$AJ$61,CFS!$F$11:$AJ$11,I$10) | J51: =SUMIFS(CFS!$F$61:$AJ$61,CFS!$F$11:$AJ$11,J$10) | K51: =SUMIFS(CFS!$F$61:$AJ$61,CFS!$F$11:$AJ$11,K$10) | L51: =SUMIFS(CFS!$F$61:$AJ$61,CFS!$F$11:$AJ$11,L$10)
D52: Purchases of capped calls | E52: =SUMIFS(CFS!$F$62:$AJ$62,CFS!$F$11:$AJ$11,E$10) | F52: =SUMIFS(CFS!$F$62:$AJ$62,CFS!$F$11:$AJ$11,F$10) | G52: =SUMIFS(CFS!$F$62:$AJ$62,CFS!$F$11:$AJ$11,G$10) | H52: =SUMIFS(CFS!$F$62:$AJ$62,CFS!$F$11:$AJ$11,H$10) | I52: =SUMIFS(CFS!$F$62:$AJ$62,CFS!$F$11:$AJ$11,I$10) | J52: =SUMIFS(CFS!$F$62:$AJ$62,CFS!$F$11:$AJ$11,J$10) | K52: =SUMIFS(CFS!$F$62:$AJ$62,CFS!$F$11:$AJ$11,K$10) | L52: =SUMIFS(CFS!$F$62:$AJ$62,CFS!$F$11:$AJ$11,L$10)
D53: Other financing, net | E53: =SUMIFS(CFS!$F$65:$AJ$65,CFS!$F$11:$AJ$11,E$10) | F53: =SUMIFS(CFS!$F$65:$AJ$65,CFS!$F$11:$AJ$11,F$10) | G53: =SUMIFS(CFS!$F$65:$AJ$65,CFS!$F$11:$AJ$11,G$10) | H53: =SUMIFS(CFS!$F$65:$AJ$65,CFS!$F$11:$AJ$11,H$10) | I53: =SUMIFS(CFS!$F$65:$AJ$65,CFS!$F$11:$AJ$11,I$10) | J53: =SUMIFS(CFS!$F$65:$AJ$65,CFS!$F$11:$AJ$11,J$10) | K53: =SUMIFS(CFS!$F$65:$AJ$65,CFS!$F$11:$AJ$11,K$10) | L53: =SUMIFS(CFS!$F$65:$AJ$65,CFS!$F$11:$AJ$11,L$10)
D54: Cash Flow from Financing | E54: =SUM(E45:E50) | F54: =SUM(F45:F50) | G54: =SUM(G45:G50) | H54: =SUM(H45:H50) | I54: =SUM(I45:I50) | J54: =SUM(J45:J50) | K54: =SUM(K45:K50) | L54: =SUM(L45:L50)
D55: CFF | E55: =SUMIFS(CFS!$F$67:$AJ$67,CFS!$F$11:$AJ$11,E$10) | F55: =SUMIFS(CFS!$F$67:$AJ$67,CFS!$F$11:$AJ$11,F$10) | G55: =SUMIFS(CFS!$F$67:$AJ$67,CFS!$F$11:$AJ$11,G$10) | H55: =SUMIFS(CFS!$F$67:$AJ$67,CFS!$F$11:$AJ$11,H$10) | I55: =SUMIFS(CFS!$F$67:$AJ$67,CFS!$F$11:$AJ$11,I$10) | J55: =SUMIFS(CFS!$F$67:$AJ$67,CFS!$F$11:$AJ$11,J$10) | K55: =SUMIFS(CFS!$F$67:$AJ$67,CFS!$F$11:$AJ$11,K$10) | L55: =SUMIFS(CFS!$F$67:$AJ$67,CFS!$F$11:$AJ$11,L$10)
D56: Check | E56: =E54-E55 | F56: =F54-F55 | G56: =G54-G55 | H56: =H54-H55 | I56: =I54-I55 | J56: =J54-J55 | K56: =K54-K55 | L56: =L54-L55
D58: Effect of foreign currency exchange rates on cash | E58: =SUMIFS(CFS!$F$70:$AJ$70,CFS!$F$11:$AJ$11,E$10) | F58: =SUMIFS(CFS!$F$70:$AJ$70,CFS!$F$11:$AJ$11,F$10) | G58: =SUMIFS(CFS!$F$70:$AJ$70,CFS!$F$11:$AJ$11,G$10) | H58: =SUMIFS(CFS!$F$70:$AJ$70,CFS!$F$11:$AJ$11,H$10) | I58: =SUMIFS(CFS!$F$70:$AJ$70,CFS!$F$11:$AJ$11,I$10) | J58: =SUMIFS(CFS!$F$70:$AJ$70,CFS!$F$11:$AJ$11,J$10) | K58: =SUMIFS(CFS!$F$70:$AJ$70,CFS!$F$11:$AJ$11,K$10) | L58: =SUMIFS(CFS!$F$70:$AJ$70,CFS!$F$11:$AJ$11,L$10)
D59: Net increase (decrease) in cash | E59: =E32+E41+E54+E58 | F59: =F32+F41+F54+F58 | G59: =G32+G41+G54+G58 | H59: =H32+H41+H54+H58 | I59: =I32+I41+I54+I58 | J59: =J32+J41+J54+J58 | K59: =K32+K41+K54+K58 | L59: =L32+L41+L54+L58
D60: Cash at beginning of period | E60: =SUMIFS(CFS!$F$75:$AJ$75,CFS!$F$11:$AJ$11,E$10) | F60: =E61 | G60: =F61 | H60: =G61 | I60: =H61 | J60: =SUMIFS(CFS!$F$75:$AJ$75,CFS!$F$11:$AJ$11,J$10) | K60: =SUMIFS(CFS!$F$75:$AJ$75,CFS!$F$11:$AJ$11,K$10) | L60: =SUMIFS(CFS!$F$75:$AJ$75,CFS!$F$11:$AJ$11,L$10)
D61: Cash at end of period | E61: =SUM(E59:E60) | F61: =SUM(F59:F60) | G61: =SUM(G59:G60) | H61: =SUM(H59:H60) | I61: =SUM(I59:I60) | J61: =SUM(J59:J60) | K61: =SUM(K59:K60) | L61: =SUM(L59:L60)
D63: Free Cash Flow(1) | E63: =E32+E36 | F63: =F32+F36 | G63: =G32+G36 | H63: =H32+H36 | I63: =I32+I36 | J63: =J32+J36 | K63: =K32+K36 | L63: =L32+L36
D66: (1) Free Cash Flow calculated as CFO less capital expenditures (cost of additions to land, buildings, equipment and software); matches Xerox's reported free cash flow definition.
D67: Note: Lexmark acquired July 1, 2025 ($674M net cash paid in 3Q'25 acquisitions).
D68: 2Q'26 includes $80M tariff receivables monetization in financing, which Xerox excludes from operating cash flow.

Sheet BS
A1: =D3 | B1: ='Cover Page'!A1
D3: Balance Sheet Spread
D4: Xerox Holdings Corporation – All values in $ millions (USD), except per-share values. Data as of June 30, 2026 (2Q'26).
A5: x | D5: Balance Sheet | F5: Quarter Ended | AC5: Fiscal Year Ended December 31, | AI5: Variance
F6: 1 | G6: 2 | H6: 3 | I6: 4 | J6: 1 | K6: 2 | L6: 3 | M6: 4 | N6: 1 | O6: 2 | P6: 3 | Q6: 4 | R6: 1 | S6: 2 | T6: 3 | U6: 4 | V6: 1 | W6: 2 | X6: 3 | Y6: 4 | Z6: 1 | AA6: 2
F7: 2021 | G7: 2021 | H7: 2021 | I7: 2021 | J7: 2022 | K7: 2022 | L7: 2022 | M7: 2022 | N7: 2023 | O7: 2023 | P7: 2023 | Q7: 2023 | R7: 2024 | S7: 2024 | T7: 2024 | U7: 2024 | V7: 2025 | W7: 2025 | X7: 2025 | Y7: 2025 | Z7: 2026 | AA7: 2026 | AC7: 2021 | AD7: 2022 | AE7: 2023 | AF7: 2024 | AG7: 2025
F8: 44286 | G8: 44377 | H8: 44469 | I8: 44561 | J8: 44651 | K8: 44742 | L8: 44834 | M8: 44926 | N8: 45016 | O8: 45107 | P8: 45199 | Q8: 45291 | R8: 45382 | S8: 45473 | T8: 45565 | U8: 45657 | V8: 45747 | W8: 45838 | X8: 45930 | Y8: 46022 | Z8: 46112 | AA8: 46203 | AC8: 44561 | AD8: 44926 | AE8: 45291 | AF8: 45657 | AG8: 46022
F10: =F6&"Q'"&RIGHT(F7,2) | G10: =G6&"Q'"&RIGHT(G7,2) | H10: =H6&"Q'"&RIGHT(H7,2) | I10: =I6&"Q'"&RIGHT(I7,2) | J10: =J6&"Q'"&RIGHT(J7,2) | K10: =K6&"Q'"&RIGHT(K7,2) | L10: =L6&"Q'"&RIGHT(L7,2) | M10: =M6&"Q'"&RIGHT(M7,2) | ... AA10: =AA6&"Q'"&RIGHT(AA7,2) | AC10: 2021 | AD10: 2022 | AE10: 2023 | AF10: 2024 | AG10: 2025 | AI10: $ Chg '25 | AJ10: % Chg '25
D12: ASSETS
D13: Cash and cash equivalents | F13: 2379 | G13: 2124 | H13: 2209 | I13: 1840 | J13: 1681 | K13: 1151 | L13: 932 | M13: 1045 | N13: 591 | O13: 477 | P13: 532 | Q13: 519 | R13: 685 | S13: 485 | T13: 521 | U13: 576 | V13: 336 | W13: 449 | X13: 479 | Y13: 512 | Z13: 585 | AA13: 495 | AC13: =I13 | AD13: =M13 | AE13: =Q13 | AF13: =U13 | AG13: =Y13 | AI13: =AG13-AF13 | AJ13: =IFERROR(AI13/ABS(AF13),0)
D14: Accounts receivable, net | F14: 781 | G14: 846 | H14: 891 | I14: 818 | J14: 807 | K14: 852 | L14: 835 | M14: 857 | N14: 818 | O14: 903 | P14: 880 | Q14: 850 | R14: 846 | S14: 847 | T14: 821 | U14: 796 | V14: 819 | W14: 862 | X14: 1196 | Y14: 1122 | Z14: 1218 | AA14: 1185 | AC14: =I14 | AD14: =M14 | AE14: =Q14 | AF14: =U14 | AG14: =Y14 | AI14: =AG14-AF14 | AJ14: =IFERROR(AI14/ABS(AF14),0)
D15: Billed portion of finance receivables, net | F15: 92 | G15: 89 | H15: 100 | I15: 94 | J15: 89 | K15: 83 | L15: 91 | M15: 93 | N15: 94 | O15: 70 | P15: 80 | Q15: 71 | R15: 67 | S15: 70 | T15: 50 | U15: 48 | V15: 43 | W15: 46 | X15: 53 | Y15: 46 | Z15: 43 | AA15: 40 | AC15: =I15 | AD15: =M15 | AE15: =Q15 | AF15: =U15 | AG15: =Y15 | AI15: =AG15-AF15 | AJ15: =IFERROR(AI15/ABS(AF15),0)
D16: Finance receivables, net | F16: 1065 | G16: 1057 | H16: 1039 | I16: 1042 | J16: 1023 | K16: 1019 | L16: 995 | M16: 1061 | N16: 1022 | O16: 940 | P16: 906 | Q16: 842 | R16: 783 | S16: 713 | T16: 664 | U16: 608 | V16: 583 | W16: 584 | X16: 553 | Y16: 510 | Z16: 476 | AA16: 442 | AC16: =I16 | AD16: =M16 | AE16: =Q16 | AF16: =U16 | AG16: =Y16 | AI16: =AG16-AF16 | AJ16: =IFERROR(AI16/ABS(AF16),0)
D17: Inventories | F17: 841 | G17: 815 | H17: 788 | I17: 696 | J17: 732 | K17: 765 | L17: 777 | M17: 797 | N17: 863 | O17: 782 | P17: 728 | Q17: 661 | R17: 736 | S17: 737 | T17: 732 | U17: 695 | V17: 836 | W17: 871 | X17: 1143 | Y17: 1016 | Z17: 1043 | AA17: 1043 | AC17: =I17 | AD17: =M17 | AE17: =Q17 | AF17: =U17 | AG17: =Y17 | AI17: =AG17-AF17 | AJ17: =IFERROR(AI17/ABS(AF17),0)
D18: Other current assets | F18: 262 | G18: 244 | H18: 209 | I18: 211 | J18: 234 | K18: 232 | L18: 265 | M18: 254 | N18: 252 | O18: 218 | P18: 228 | Q18: 234 | R18: 231 | S18: 199 | T18: 223 | U18: 212 | V18: 250 | W18: 731 | X18: 329 | Y18: 362 | Z18: 415 | AA18: 492 | AC18: =I18 | AD18: =M18 | AE18: =Q18 | AF18: =U18 | AG18: =Y18 | AI18: =AG18-AF18 | AJ18: =IFERROR(AI18/ABS(AF18),0)
D19: Total current assets | F19: =SUM(F13:F18) | G19: =SUM(G13:G18) | H19: =SUM(H13:H18) | I19: =SUM(I13:I18) | J19: =SUM(J13:J18) | K19: =SUM(K13:K18) | L19: =SUM(L13:L18) | M19: =SUM(M13:M18) | ... AA19: =SUM(AA13:AA18) | AC19: =SUM(AC13:AC18) | AD19: =SUM(AD13:AD18) | AE19: =SUM(AE13:AE18) | AF19: =SUM(AF13:AF18) | AG19: =SUM(AG13:AG18) | AI19: =AG19-AF19 | AJ19: =IFERROR(AI19/ABS(AF19),0)
D20: Total current assets | F20: 5420 | G20: 5175 | H20: 5236 | I20: 4701 | J20: 4566 | K20: 4102 | L20: 3895 | M20: 4107 | N20: 3640 | O20: 3390 | P20: 3354 | Q20: 3177 | R20: 3348 | S20: 3051 | T20: 3011 | U20: 2935 | V20: 2867 | W20: 3543 | X20: 3753 | Y20: 3568 | Z20: 3780 | AA20: 3697 | AC20: =I20 | AD20: =M20 | AE20: =Q20 | AF20: =U20 | AG20: =Y20
D21: Check | F21: =F19-F20 | G21: =G19-G20 | H21: =H19-H20 | I21: =I19-I20 | J21: =J19-J20 | K21: =K19-K20 | L21: =L19-L20 | M21: =M19-M20 | ... AA21: =AA19-AA20 | AC21: =AC19-AC20 | AD21: =AD19-AD20 | AE21: =AE19-AE20 | AF21: =AF19-AF20 | AG21: =AG19-AG20
D22: Finance receivables due after one year, net | F22: 1920 | G22: 1971 | H22: 1936 | I22: 1934 | J22: 1893 | K22: 1845 | L22: 1814 | M22: 1948 | N22: 1864 | O22: 1697 | P22: 1605 | Q22: 1597 | R22: 1408 | S22: 1277 | T22: 1275 | U22: 1089 | V22: 1013 | W22: 990 | X22: 950 | Y22: 846 | Z22: 797 | AA22: 732 | AC22: =I22 | AD22: =M22 | AE22: =Q22 | AF22: =U22 | AG22: =Y22 | AI22: =AG22-AF22 | AJ22: =IFERROR(AI22/ABS(AF22),0)
D23: Equipment on operating leases, net | F23: 277 | G23: 271 | H23: 254 | I23: 253 | J23: 254 | K23: 226 | L23: 216 | M23: 235 | N23: 250 | O23: 259 | P23: 257 | Q23: 265 | R23: 257 | S23: 253 | T23: 255 | U23: 245 | V23: 248 | W23: 249 | X23: 300 | Y23: 299 | Z23: 292 | AA23: 283 | AC23: =I23 | AD23: =M23 | AE23: =Q23 | AF23: =U23 | AG23: =Y23 | AI23: =AG23-AF23 | AJ23: =IFERROR(AI23/ABS(AF23),0)
D24: Land, buildings and equipment, net | F24: 393 | G24: 372 | H24: 370 | I24: 358 | J24: 350 | K24: 334 | L24: 315 | M24: 320 | N24: 311 | O24: 281 | P24: 273 | Q24: 266 | R24: 245 | S24: 227 | T24: 225 | U24: 251 | V24: 195 | W24: 187 | X24: 427 | Y24: 390 | Z24: 378 | AA24: 378 | AC24: =I24 | AD24: =M24 | AE24: =Q24 | AF24: =U24 | AG24: =Y24 | AI24: =AG24-AF24 | AJ24: =IFERROR(AI24/ABS(AF24),0)
D25: Intangible assets, net | F25: 223 | G25: 230 | H25: 216 | I25: 211 | J25: 240 | K25: 223 | L25: 216 | M25: 208 | N25: 202 | O25: 194 | P25: 183 | Q25: 177 | R25: 165 | S25: 155 | T25: 149 | U25: 236 | V25: 228 | W25: 222 | X25: 954 | Y25: 921 | Z25: 891 | AA25: 857 | AC25: =I25 | AD25: =M25 | AE25: =Q25 | AF25: =U25 | AG25: =Y25 | AI25: =AG25-AF25 | AJ25: =IFERROR(AI25/ABS(AF25),0)
D26: Goodwill, net | F26: 4075 | G26: 4104 | H26: 4066 | I26: 3287 | J26: 3300 | K26: 3217 | L26: 2753 | M26: 2820 | N26: 2850 | O26: 2751 | P26: 2716 | Q26: 2747 | R26: 2720 | S26: 2719 | T26: 1709 | U26: 1937 | V26: 1954 | W26: 1984 | X26: 2182 | Y26: 2222 | Z26: 2201 | AA26: 2234 | AC26: =I26 | AD26: =M26 | AE26: =Q26 | AF26: =U26 | AG26: =Y26 | AI26: =AG26-AF26 | AJ26: =IFERROR(AI26/ABS(AF26),0)
D27: Deferred tax assets | F27: 510 | G27: 491 | H27: 511 | I27: 519 | J27: 528 | K27: 539 | L27: 496 | M27: 582 | N27: 598 | O27: 620 | P27: 701 | Q27: 745 | R27: 749 | S27: 760 | T27: 635 | U27: 615 | V27: 607 | W27: 551 | X27: 101 | Y27: 98 | Z27: 96 | AA27: 86 | AC27: =I27 | AD27: =M27 | AE27: =Q27 | AF27: =U27 | AG27: =Y27 | AI27: =AG27-AF27 | AJ27: =IFERROR(AI27/ABS(AF27),0)
D28: Other long-term assets | F28: 1454 | G28: 1496 | H28: 1492 | I28: 1960 | J28: 1951 | K28: 1784 | L28: 1715 | M28: 1323 | N28: 1331 | O28: 1377 | P28: 1355 | Q28: 1034 | R28: 1052 | S28: 1049 | T28: 1063 | U28: 1057 | V28: 1099 | W28: 1148 | X28: 1401 | Y28: 1479 | Z28: 1467 | AA28: 1457 | AC28: =I28 | AD28: =M28 | AE28: =Q28 | AF28: =U28 | AG28: =Y28 | AI28: =AG28-AF28 | AJ28: =IFERROR(AI28/ABS(AF28),0)
D29: Total assets | F29: =SUM(F22:F28)+F19 | G29: =SUM(G22:G28)+G19 | H29: =SUM(H22:H28)+H19 | I29: =SUM(I22:I28)+I19 | J29: =SUM(J22:J28)+J19 | K29: =SUM(K22:K28)+K19 | L29: =SUM(L22:L28)+L19 | M29: =SUM(M22:M28)+M19 | ... AA29: =SUM(AA22:AA28)+AA19 | AC29: =SUM(AC22:AC28)+AC19 | AD29: =SUM(AD22:AD28)+AD19 | AE29: =SUM(AE22:AE28)+AE19 | AF29: =SUM(AF22:AF28)+AF19 | AG29: =SUM(AG22:AG28)+AG19 | AI29: =AG29-AF29 | AJ29: =IFERROR(AI29/ABS(AF29),0)
D30: Total assets | F30: 14272 | G30: 14110 | H30: 14081 | I30: 13223 | J30: 13082 | K30: 12270 | L30: 11420 | M30: 11543 | N30: 11046 | O30: 10569 | P30: 10444 | Q30: 10008 | R30: 9944 | S30: 9491 | T30: 8322 | U30: 8365 | V30: 8211 | W30: 8874 | X30: 10068 | Y30: 9823 | Z30: 9902 | AA30: 9724 | AC30: =I30 | AD30: =M30 | AE30: =Q30 | AF30: =U30 | AG30: =Y30
D31: Check | F31: =F29-F30 | G31: =G29-G30 | H31: =H29-H30 | I31: =I29-I30 | J31: =J29-J30 | K31: =K29-K30 | L31: =L29-L30 | M31: =M29-M30 | ... AA31: =AA29-AA30 | AC31: =AC29-AC30 | AD31: =AD29-AD30 | AE31: =AE29-AE30 | AF31: =AF29-AF30 | AG31: =AG29-AG30
D33: LIABILITIES AND EQUITY
D34: Current liabilities
D35: Short-term debt and current portion of long-term debt | F35: 678 | G35: 642 | H35: 646 | I35: 650 | J35: 1450 | K35: 1108 | L35: 1070 | M35: 860 | N35: 553 | O35: 891 | P35: 870 | Q35: 567 | R35: 405 | S35: 129 | T35: 519 | U35: 585 | V35: 599 | W35: 458 | X35: 354 | Y35: 231 | Z35: 165 | AA35: 70 | AC35: =I35 | AD35: =M35 | AE35: =Q35 | AF35: =U35 | AG35: =Y35 | AI35: =AG35-AF35 | AJ35: =IFERROR(AI35/ABS(AF35),0)
D36: Financing liability, tariff receivables monetization | F36: 0 | G36: 0 | H36: 0 | I36: 0 | J36: 0 | K36: 0 | L36: 0 | M36: 0 | N36: 0 | O36: 0 | P36: 0 | Q36: 0 | R36: 0 | S36: 0 | T36: 0 | U36: 0 | V36: 0 | W36: 0 | X36: 0 | Y36: 0 | Z36: 0 | AA36: 90 | AC36: =I36 | AD36: =M36 | AE36: =Q36 | AF36: =U36 | AG36: =Y36 | AI36: =AG36-AF36 | AJ36: =IFERROR(AI36/ABS(AF36),0)
D37: Accounts payable | F37: 932 | G37: 935 | H37: 1032 | I37: 1069 | J37: 1183 | K37: 1207 | L37: 1213 | M37: 1331 | N37: 1301 | O37: 1041 | P37: 1031 | Q37: 1044 | R37: 1046 | S37: 936 | T37: 895 | U37: 1023 | V37: 1120 | W37: 1080 | X37: 1481 | Y37: 1498 | Z37: 1548 | AA37: 1456 | AC37: =I37 | AD37: =M37 | AE37: =Q37 | AF37: =U37 | AG37: =Y37 | AI37: =AG37-AF37 | AJ37: =IFERROR(AI37/ABS(AF37),0)
D38: Accrued compensation and benefits costs | F38: 241 | G38: 263 | H38: 262 | I38: 239 | J38: 258 | K38: 233 | L38: 250 | M38: 258 | N38: 243 | O38: 251 | P38: 276 | Q38: 306 | R38: 213 | S38: 205 | T38: 227 | U38: 227 | V38: 199 | W38: 182 | X38: 247 | Y38: 235 | Z38: 223 | AA38: 246 | AC38: =I38 | AD38: =M38 | AE38: =Q38 | AF38: =U38 | AG38: =Y38 | AI38: =AG38-AF38 | AJ38: =IFERROR(AI38/ABS(AF38),0)
D39: Accrued expenses and other current liabilities | F39: 794 | G39: 851 | H39: 844 | I39: 871 | J39: 878 | K39: 867 | L39: 810 | M39: 881 | N39: 782 | O39: 766 | P39: 829 | Q39: 862 | R39: 774 | S39: 776 | T39: 752 | U39: 784 | V39: 721 | W39: 706 | X39: 1317 | Y39: 1258 | Z39: 1266 | AA39: 1264 | AC39: =I39 | AD39: =M39 | AE39: =Q39 | AF39: =U39 | AG39: =Y39 | AI39: =AG39-AF39 | AJ39: =IFERROR(AI39/ABS(AF39),0)
D40: Total current liabilities | F40: =SUM(F35:F39) | G40: =SUM(G35:G39) | H40: =SUM(H35:H39) | I40: =SUM(I35:I39) | J40: =SUM(J35:J39) | K40: =SUM(K35:K39) | L40: =SUM(L35:L39) | M40: =SUM(M35:M39) | ... AA40: =SUM(AA35:AA39) | AC40: =SUM(AC35:AC39) | AD40: =SUM(AD35:AD39) | AE40: =SUM(AE35:AE39) | AF40: =SUM(AF35:AF39) | AG40: =SUM(AG35:AG39) | AI40: =AG40-AF40 | AJ40: =IFERROR(AI40/ABS(AF40),0)
D41: Total current liabilities | F41: 2645 | G41: 2691 | H41: 2784 | I41: 2829 | J41: 3769 | K41: 3415 | L41: 3343 | M41: 3330 | N41: 2879 | O41: 2949 | P41: 3006 | Q41: 2779 | R41: 2438 | S41: 2046 | T41: 2393 | U41: 2619 | V41: 2639 | W41: 2426 | X41: 3399 | Y41: 3222 | Z41: 3202 | AA41: 3126 | AC41: =I41 | AD41: =M41 | AE41: =Q41 | AF41: =U41 | AG41: =Y41
D42: Check | F42: =F40-F41 | G42: =G40-G41 | H42: =H40-H41 | I42: =I40-I41 | J42: =J40-J41 | K42: =K40-K41 | L42: =L40-L41 | M42: =M40-M41 | ... AA42: =AA40-AA41 | AC42: =AC40-AC41 | AD42: =AD40-AD41 | AE42: =AE40-AE41 | AF42: =AF40-AF41 | AG42: =AG40-AG41
D43: Long-term debt | F43: 3674 | G43: 3597 | H43: 3673 | I43: 3596 | J43: 2821 | K43: 2764 | L43: 2676 | M43: 2866 | N43: 2726 | O43: 2225 | P43: 2739 | Q43: 2710 | R43: 3199 | S43: 3174 | T43: 2752 | U43: 2814 | V43: 2699 | W43: 3484 | X43: 4052 | Y43: 4016 | Z43: 4281 | AA43: 4153 | AC43: =I43 | AD43: =M43 | AE43: =Q43 | AF43: =U43 | AG43: =Y43 | AI43: =AG43-AF43 | AJ43: =IFERROR(AI43/ABS(AF43),0)
D44: Pension and other benefit liabilities | F44: 1473 | G44: 1436 | H44: 1381 | I44: 1373 | J44: 1359 | K44: 1310 | L44: 1298 | M44: 1175 | N44: 1168 | O44: 1206 | P44: 1131 | Q44: 1216 | R44: 1183 | S44: 1180 | T44: 1126 | U44: 1088 | V44: 1077 | W44: 1083 | X44: 1150 | Y44: 1068 | Z44: 1037 | AA44: 1027 | AC44: =I44 | AD44: =M44 | AE44: =Q44 | AF44: =U44 | AG44: =Y44 | AI44: =AG44-AF44 | AJ44: =IFERROR(AI44/ABS(AF44),0)
D45: Post-retirement medical benefits | F45: 339 | G45: 340 | H45: 333 | I45: 277 | J45: 247 | K45: 242 | L45: 209 | M45: 184 | N45: 182 | O45: 179 | P45: 175 | Q45: 171 | R45: 167 | S45: 164 | T45: 166 | U45: 154 | V45: 152 | W45: 153 | X45: 168 | Y45: 159 | Z45: 156 | AA45: 148 | AC45: =I45 | AD45: =M45 | AE45: =Q45 | AF45: =U45 | AG45: =Y45 | AI45: =AG45-AF45 | AJ45: =IFERROR(AI45/ABS(AF45),0)
D46: Other long-term liabilities | F46: 498 | G46: 537 | H46: 491 | I46: 481 | J46: 473 | K46: 433 | L46: 416 | M46: 411 | N46: 400 | O46: 394 | P46: 371 | Q46: 360 | R46: 352 | S46: 338 | T46: 354 | U46: 386 | V46: 363 | W46: 377 | X46: 705 | Y46: 685 | Z46: 697 | AA46: 716 | AC46: =I46 | AD46: =M46 | AE46: =Q46 | AF46: =U46 | AG46: =Y46 | AI46: =AG46-AF46 | AJ46: =IFERROR(AI46/ABS(AF46),0)
D47: Total liabilities | F47: =SUM(F43:F46)+F40 | G47: =SUM(G43:G46)+G40 | H47: =SUM(H43:H46)+H40 | I47: =SUM(I43:I46)+I40 | J47: =SUM(J43:J46)+J40 | K47: =SUM(K43:K46)+K40 | L47: =SUM(L43:L46)+L40 | M47: =SUM(M43:M46)+M40 | ... AA47: =SUM(AA43:AA46)+AA40 | AC47: =SUM(AC43:AC46)+AC40 | AD47: =SUM(AD43:AD46)+AD40 | AE47: =SUM(AE43:AE46)+AE40 | AF47: =SUM(AF43:AF46)+AF40 | AG47: =SUM(AG43:AG46)+AG40 | AI47: =AG47-AF47 | AJ47: =IFERROR(AI47/ABS(AF47),0)
D48: Total liabilities | F48: 8629 | G48: 8601 | H48: 8662 | I48: 8556 | J48: 8669 | K48: 8164 | L48: 7942 | M48: 7966 | N48: 7355 | O48: 6953 | P48: 7422 | Q48: 7236 | R48: 7339 | S48: 6902 | T48: 6791 | U48: 7061 | V48: 6930 | W48: 7523 | X48: 9474 | Y48: 9150 | Z48: 9373 | AA48: 9170 | AC48: =I48 | AD48: =M48 | AE48: =Q48 | AF48: =U48 | AG48: =Y48
D49: Check | F49: =F47-F48 | G49: =G47-G48 | H49: =H47-H48 | I49: =I47-I48 | J49: =J47-J48 | K49: =K47-K48 | L49: =L47-L48 | M49: =M47-M48 | ... AA49: =AA47-AA48 | AC49: =AC47-AC48 | AD49: =AD47-AD48 | AE49: =AE47-AE48 | AF49: =AF47-AF48 | AG49: =AG47-AG48
D51: Temporary equity
D52: Noncontrolling interests (temporary equity) | F52: 0 | G52: 0 | H52: 10 | I52: 10 | J52: 10 | K52: 10 | L52: 10 | M52: 10 | N52: 10 | O52: 10 | P52: 10 | Q52: 10 | R52: 10 | S52: 10 | T52: 10 | U52: 10 | V52: 10 | W52: 10 | X52: 10 | Y52: 10 | Z52: 10 | AA52: 10 | AC52: =I52 | AD52: =M52 | AE52: =Q52 | AF52: =U52 | AG52: =Y52 | AI52: =AG52-AF52 | AJ52: =IFERROR(AI52/ABS(AF52),0)
D53: Convertible preferred stock | F53: 214 | G53: 214 | H53: 214 | I53: 214 | J53: 214 | K53: 214 | L53: 214 | M53: 214 | N53: 214 | O53: 214 | P53: 214 | Q53: 214 | R53: 214 | S53: 214 | T53: 214 | U53: 214 | V53: 214 | W53: 214 | X53: 214 | Y53: 214 | Z53: 214 | AA53: 214 | AC53: =I53 | AD53: =M53 | AE53: =Q53 | AF53: =U53 | AG53: =Y53 | AI53: =AG53-AF53 | AJ53: =IFERROR(AI53/ABS(AF53),0)
D54: Shareholders' equity
D55: Common stock | F55: 199 | G55: 189 | H55: 182 | I55: 168 | J55: 156 | K55: 155 | L55: 156 | M55: 156 | N55: 157 | O55: 157 | P55: 157 | Q55: 123 | R55: 124 | S55: 124 | T55: 124 | U55: 124 | V55: 126 | W55: 126 | X55: 128 | Y55: 128 | Z55: 131 | AA55: 131 | AC55: =I55 | AD55: =M55 | AE55: =Q55 | AF55: =U55 | AG55: =Y55 | AI55: =AG55-AF55 | AJ55: =IFERROR(AI55/ABS(AF55),0)
D56: Additional paid-in capital | F56: 2456 | G56: 2214 | H56: 2080 | I56: 1802 | J56: 1560 | K56: 1564 | L56: 1577 | M56: 1588 | N56: 1594 | O56: 1607 | P56: 1619 | Q56: 1114 | R56: 1099 | S56: 1114 | T56: 1123 | U56: 1137 | V56: 1141 | W56: 1154 | X56: 1171 | Y56: 1183 | Z56: 1192 | AA56: 1200 | AC56: =I56 | AD56: =M56 | AE56: =Q56 | AF56: =U56 | AG56: =Y56 | AI56: =AG56-AF56 | AJ56: =IFERROR(AI56/ABS(AF56),0)
D57: Treasury stock, at cost | F57: -162 | G57: -159 | H57: -87 | I57: -177 | J57: -32 | K57: 0 | L57: 0 | M57: 0 | N57: 0 | O57: 0 | P57: -553 | Q57: 0 | R57: 0 | S57: 0 | T57: 0 | U57: 0 | V57: 0 | W57: 0 | X57: 0 | Y57: 0 | Z57: 0 | AA57: 0 | AC57: =I57 | AD57: =M57 | AE57: =Q57 | AF57: =U57 | AG57: =Y57 | AI57: =AG57-AF57 | AJ57: =IFERROR(AI57/ABS(AF57),0)
D58: Retained earnings | F58: 6267 | G58: 6308 | H58: 6348 | I58: 5631 | J58: 5532 | K58: 5484 | L58: 5057 | M58: 5136 | N58: 5162 | O58: 5057 | P58: 5070 | Q58: 4977 | R58: 4828 | S58: 4810 | T58: 3570 | U58: 3514 | V58: 3403 | W58: 3290 | X58: 2523 | Y58: 2444 | Z58: 2320 | AA58: 2326 | AC58: =I58 | AD58: =M58 | AE58: =Q58 | AF58: =U58 | AG58: =Y58 | AI58: =AG58-AF58 | AJ58: =IFERROR(AI58/ABS(AF58),0)
D59: Accumulated other comprehensive loss | F59: -3335 | G59: -3265 | H59: -3335 | I59: -2988 | J59: -3032 | K59: -3330 | L59: -3547 | M59: -3537 | N59: -3454 | O59: -3437 | P59: -3504 | Q59: -3676 | R59: -3673 | S59: -3687 | T59: -3514 | U59: -3699 | V59: -3617 | W59: -3448 | X59: -3457 | Y59: -3311 | Z59: -3344 | AA59: -3334 | AC59: =I59 | AD59: =M59 | AE59: =Q59 | AF59: =U59 | AG59: =Y59 | AI59: =AG59-AF59 | AJ59: =IFERROR(AI59/ABS(AF59),0)
D60: Xerox Holdings shareholders' equity | F60: =SUM(F55:F59) | G60: =SUM(G55:G59) | H60: =SUM(H55:H59) | I60: =SUM(I55:I59) | J60: =SUM(J55:J59) | K60: =SUM(K55:K59) | L60: =SUM(L55:L59) | M60: =SUM(M55:M59) | ... AA60: =SUM(AA55:AA59) | AC60: =SUM(AC55:AC59) | AD60: =SUM(AD55:AD59) | AE60: =SUM(AE55:AE59) | AF60: =SUM(AF55:AF59) | AG60: =SUM(AG55:AG59) | AI60: =AG60-AF60 | AJ60: =IFERROR(AI60/ABS(AF60),0)
D61: Xerox Holdings shareholders' equity | F61: 5425 | G61: 5287 | H61: 5188 | I61: 4436 | J61: 4184 | K61: 3873 | L61: 3243 | M61: 3343 | N61: 3459 | O61: 3384 | P61: 2789 | Q61: 2538 | R61: 2378 | S61: 2361 | T61: 1303 | U61: 1076 | V61: 1053 | W61: 1122 | X61: 365 | Y61: 444 | Z61: 299 | AA61: 323 | AC61: =I61 | AD61: =M61 | AE61: =Q61 | AF61: =U61 | AG61: =Y61
D62: Check | F62: =F60-F61 | G62: =G60-G61 | H62: =H60-H61 | I62: =I60-I61 | J62: =J60-J61 | K62: =K60-K61 | L62: =L60-L61 | M62: =M60-M61 | ... AA62: =AA60-AA61 | AC62: =AC60-AC61 | AD62: =AD60-AD61 | AE62: =AE60-AE61 | AF62: =AF60-AF61 | AG62: =AG60-AG61
D63: Noncontrolling interests | F63: 4 | G63: 8 | H63: 7 | I63: 7 | J63: 5 | K63: 9 | L63: 11 | M63: 10 | N63: 8 | O63: 8 | P63: 9 | Q63: 10 | R63: 3 | S63: 4 | T63: 4 | U63: 4 | V63: 4 | W63: 5 | X63: 5 | Y63: 5 | Z63: 6 | AA63: 7 | AC63: =I63 | AD63: =M63 | AE63: =Q63 | AF63: =U63 | AG63: =Y63 | AI63: =AG63-AF63 | AJ63: =IFERROR(AI63/ABS(AF63),0)
D64: Total equity | F64: =F60+F63 | G64: =G60+G63 | H64: =H60+H63 | I64: =I60+I63 | J64: =J60+J63 | K64: =K60+K63 | L64: =L60+L63 | M64: =M60+M63 | ... AA64: =AA60+AA63 | AC64: =AC60+AC63 | AD64: =AD60+AD63 | AE64: =AE60+AE63 | AF64: =AF60+AF63 | AG64: =AG60+AG63 | AI64: =AG64-AF64 | AJ64: =IFERROR(AI64/ABS(AF64),0)
D65: Total equity | F65: 5429 | G65: 5295 | H65: 5195 | I65: 4443 | J65: 4189 | K65: 3882 | L65: 3254 | M65: 3353 | N65: 3467 | O65: 3392 | P65: 2798 | Q65: 2548 | R65: 2381 | S65: 2365 | T65: 1307 | U65: 1080 | V65: 1057 | W65: 1127 | X65: 370 | Y65: 449 | Z65: 305 | AA65: 330 | AC65: =I65 | AD65: =M65 | AE65: =Q65 | AF65: =U65 | AG65: =Y65
D66: Check | F66: =F64-F65 | G66: =G64-G65 | H66: =H64-H65 | I66: =I64-I65 | J66: =J64-J65 | K66: =K64-K65 | L66: =L64-L65 | M66: =M64-M65 | ... AA66: =AA64-AA65 | AC66: =AC64-AC65 | AD66: =AD64-AD65 | AE66: =AE64-AE65 | AF66: =AF64-AF65 | AG66: =AG64-AG65
D68: Total liabilities and equity | F68: =F47+F52+F53+F64 | G68: =G47+G52+G53+G64 | H68: =H47+H52+H53+H64 | I68: =I47+I52+I53+I64 | J68: =J47+J52+J53+J64 | K68: =K47+K52+K53+K64 | L68: =L47+L52+L53+L64 | M68: =M47+M52+M53+M64 | ... AA68: =AA47+AA52+AA53+AA64 | AC68: =AC47+AC52+AC53+AC64 | AD68: =AD47+AD52+AD53+AD64 | AE68: =AE47+AE52+AE53+AE64 | AF68: =AF47+AF52+AF53+AF64 | AG68: =AG47+AG52+AG53+AG64 | AI68: =AG68-AF68 | AJ68: =IFERROR(AI68/ABS(AF68),0)
D69: Total liabilities and equity | F69: 14272 | G69: 14110 | H69: 14081 | I69: 13223 | J69: 13082 | K69: 12270 | L69: 11420 | M69: 11543 | N69: 11046 | O69: 10569 | P69: 10444 | Q69: 10008 | R69: 9944 | S69: 9491 | T69: 8322 | U69: 8365 | V69: 8211 | W69: 8874 | X69: 10068 | Y69: 9823 | Z69: 9902 | AA69: 9724
D70: Check | F70: =F68-F69 | G70: =G68-G69 | H70: =H68-H69 | I70: =I68-I69 | J70: =J68-J69 | K70: =K68-K69 | L70: =L68-L69 | M70: =M68-M69 | ... AA70: =AA68-AA69
D71: A=L+SE Check | F71: =F29-F68 | G71: =G29-G68 | H71: =H29-H68 | I71: =I29-I68 | J71: =J29-J68 | K71: =K29-K68 | L71: =L29-L68 | M71: =M29-M68 | ... AA71: =AA29-AA68 | AC71: =AC29-AC68 | AD71: =AD29-AD68 | AE71: =AE29-AE68 | AF71: =AF29-AF68 | AG71: =AG29-AG68
D73: MEMO (cross-statement links)
D74: Total debt (short-term + long-term) | F74: =F35+F43 | G74: =G35+G43 | H74: =H35+H43 | I74: =I35+I43 | J74: =J35+J43 | K74: =K35+K43 | L74: =L35+L43 | M74: =M35+M43 | ... AA74: =AA35+AA43 | AC74: =AC35+AC43 | AD74: =AD35+AD43 | AE74: =AE35+AE43 | AF74: =AF35+AF43 | AG74: =AG35+AG43 | AI74: =AG74-AF74 | AJ74: =IFERROR(AI74/ABS(AF74),0)
D75: Net debt (total debt less cash) | F75: =F74-F13 | G75: =G74-G13 | H75: =H74-H13 | I75: =I74-I13 | J75: =J74-J13 | K75: =K74-K13 | L75: =L74-L13 | M75: =M74-M13 | ... AA75: =AA74-AA13 | AC75: =AC74-AC13 | AD75: =AD74-AD13 | AE75: =AE74-AE13 | AF75: =AF74-AF13 | AG75: =AG74-AG13 | AI75: =AG75-AF75 | AJ75: =IFERROR(AI75/ABS(AF75),0)
D76: Cash, cash equivalents and restricted cash (per CFS) | F76: =CFS!F76 | G76: =CFS!G76 | H76: =CFS!H76 | I76: =CFS!I76 | J76: =CFS!J76 | K76: =CFS!K76 | L76: =CFS!L76 | M76: =CFS!M76 | ... AA76: =CFS!AA76 | AC76: =CFS!AC76 | AD76: =CFS!AD76 | AE76: =CFS!AE76 | AF76: =CFS!AF76 | AG76: =CFS!AG76 | AI76: =AG76-AF76 | AJ76: =IFERROR(AI76/ABS(AF76),0)
D77: Restricted cash (CFS cash less BS cash) | F77: =F76-F13 | G77: =G76-G13 | H77: =H76-H13 | I77: =I76-I13 | J77: =J76-J13 | K77: =K76-K13 | L77: =L76-L13 | M77: =M76-M13 | ... AA77: =AA76-AA13 | AC77: =AC76-AC13 | AD77: =AD76-AD13 | AE77: =AE76-AE13 | AF77: =AF76-AF13 | AG77: =AG76-AG13 | AI77: =AG77-AF77 | AJ77: =IFERROR(AI77/ABS(AF77),0)
D78: Total finance receivables (billed + current + long-term) | F78: =F15+F16+F22 | G78: =G15+G16+G22 | H78: =H15+H16+H22 | I78: =I15+I16+I22 | J78: =J15+J16+J22 | K78: =K15+K16+K22 | L78: =L15+L16+L22 | M78: =M15+M16+M22 | ... AA78: =AA15+AA16+AA22 | AC78: =AC15+AC16+AC22 | AD78: =AD15+AD16+AD22 | AE78: =AE15+AE16+AE22 | AF78: =AF15+AF16+AF22 | AG78: =AG15+AG16+AG22 | AI78: =AG78-AF78 | AJ78: =IFERROR(AI78/ABS(AF78),0)
D79: Net working capital (AR + inventories + other CA - AP - accruals) | F79: =F14+F17+F18-F37-F38-F39 | G79: =G14+G17+G18-G37-G38-G39 | H79: =H14+H17+H18-H37-H38-H39 | I79: =I14+I17+I18-I37-I38-I39 | J79: =J14+J17+J18-J37-J38-J39 | K79: =K14+K17+K18-K37-K38-K39 | L79: =L14+L17+L18-L37-L38-L39 | M79: =M14+M17+M18-M37-M38-M39 | ... AA79: =AA14+AA17+AA18-AA37-AA38-AA39 | AC79: =AC14+AC17+AC18-AC37-AC38-AC39 | AD79: =AD14+AD17+AD18-AD37-AD38-AD39 | AE79: =AE14+AE17+AE18-AE37-AE38-AE39 | AF79: =AF14+AF17+AF18-AF37-AF38-AF39 | AG79: =AG14+AG17+AG18-AG37-AG38-AG39 | AI79: =AG79-AF79 | AJ79: =IFERROR(AI79/ABS(AF79),0)
D81: Notes:
D82: (1) Every quarter-end is taken from that period's own 10-Q (or the 10-K for Q4), as originally filed. Annual columns link to each year's Q4.
D83: (2) Lexmark acquired July 1, 2025: step-ups in receivables, inventories, PP&E, intangibles, payables and debt from 3Q'25.
D84: (3) Convertible preferred stock and a small noncontrolling interest are temporary equity, outside Total equity but inside Total liabilities and equity.
D85: (4) Variance columns compare FY2025 with FY2024.

Sheet BS Out
A1: =D3 | B1: ='Cover Page'!A1
D3: Balance Sheet Summary
D4: Xerox Holdings Corporation – All values in $ millions (USD), except per-share values. Data as of June 30, 2026 (2Q'26).
A7: x | D7: Balance Sheet Summary | F7: Year Ended December 31, | J7: Quarter Ended
E9: 2021 | F9: 2022 | G9: 2023 | H9: 2024 | I9: 2025 | J9: 2Q'25 | K9: 2Q'26
D11: Cash and cash equivalents | E11: =SUMIFS(BS!$F$13:$AG$13,BS!$F$10:$AG$10,E$9) | F11: =SUMIFS(BS!$F$13:$AG$13,BS!$F$10:$AG$10,F$9) | G11: =SUMIFS(BS!$F$13:$AG$13,BS!$F$10:$AG$10,G$9) | H11: =SUMIFS(BS!$F$13:$AG$13,BS!$F$10:$AG$10,H$9) | I11: =SUMIFS(BS!$F$13:$AG$13,BS!$F$10:$AG$10,I$9) | J11: =SUMIFS(BS!$F$13:$AG$13,BS!$F$10:$AG$10,J$9) | K11: =SUMIFS(BS!$F$13:$AG$13,BS!$F$10:$AG$10,K$9)
D12: Accounts receivable, net | E12: =SUMIFS(BS!$F$14:$AG$14,BS!$F$10:$AG$10,E$9) | F12: =SUMIFS(BS!$F$14:$AG$14,BS!$F$10:$AG$10,F$9) | G12: =SUMIFS(BS!$F$14:$AG$14,BS!$F$10:$AG$10,G$9) | H12: =SUMIFS(BS!$F$14:$AG$14,BS!$F$10:$AG$10,H$9) | I12: =SUMIFS(BS!$F$14:$AG$14,BS!$F$10:$AG$10,I$9) | J12: =SUMIFS(BS!$F$14:$AG$14,BS!$F$10:$AG$10,J$9) | K12: =SUMIFS(BS!$F$14:$AG$14,BS!$F$10:$AG$10,K$9)
D13: Billed portion of finance receivables, net | E13: =SUMIFS(BS!$F$15:$AG$15,BS!$F$10:$AG$10,E$9) | F13: =SUMIFS(BS!$F$15:$AG$15,BS!$F$10:$AG$10,F$9) | G13: =SUMIFS(BS!$F$15:$AG$15,BS!$F$10:$AG$10,G$9) | H13: =SUMIFS(BS!$F$15:$AG$15,BS!$F$10:$AG$10,H$9) | I13: =SUMIFS(BS!$F$15:$AG$15,BS!$F$10:$AG$10,I$9) | J13: =SUMIFS(BS!$F$15:$AG$15,BS!$F$10:$AG$10,J$9) | K13: =SUMIFS(BS!$F$15:$AG$15,BS!$F$10:$AG$10,K$9)
D14: Finance receivables, net | E14: =SUMIFS(BS!$F$16:$AG$16,BS!$F$10:$AG$10,E$9) | F14: =SUMIFS(BS!$F$16:$AG$16,BS!$F$10:$AG$10,F$9) | G14: =SUMIFS(BS!$F$16:$AG$16,BS!$F$10:$AG$10,G$9) | H14: =SUMIFS(BS!$F$16:$AG$16,BS!$F$10:$AG$10,H$9) | I14: =SUMIFS(BS!$F$16:$AG$16,BS!$F$10:$AG$10,I$9) | J14: =SUMIFS(BS!$F$16:$AG$16,BS!$F$10:$AG$10,J$9) | K14: =SUMIFS(BS!$F$16:$AG$16,BS!$F$10:$AG$10,K$9)
D15: Inventories | E15: =SUMIFS(BS!$F$17:$AG$17,BS!$F$10:$AG$10,E$9) | F15: =SUMIFS(BS!$F$17:$AG$17,BS!$F$10:$AG$10,F$9) | G15: =SUMIFS(BS!$F$17:$AG$17,BS!$F$10:$AG$10,G$9) | H15: =SUMIFS(BS!$F$17:$AG$17,BS!$F$10:$AG$10,H$9) | I15: =SUMIFS(BS!$F$17:$AG$17,BS!$F$10:$AG$10,I$9) | J15: =SUMIFS(BS!$F$17:$AG$17,BS!$F$10:$AG$10,J$9) | K15: =SUMIFS(BS!$F$17:$AG$17,BS!$F$10:$AG$10,K$9)
D16: Other current assets | E16: =SUMIFS(BS!$F$18:$AG$18,BS!$F$10:$AG$10,E$9) | F16: =SUMIFS(BS!$F$18:$AG$18,BS!$F$10:$AG$10,F$9) | G16: =SUMIFS(BS!$F$18:$AG$18,BS!$F$10:$AG$10,G$9) | H16: =SUMIFS(BS!$F$18:$AG$18,BS!$F$10:$AG$10,H$9) | I16: =SUMIFS(BS!$F$18:$AG$18,BS!$F$10:$AG$10,I$9) | J16: =SUMIFS(BS!$F$18:$AG$18,BS!$F$10:$AG$10,J$9) | K16: =SUMIFS(BS!$F$18:$AG$18,BS!$F$10:$AG$10,K$9)
D17: Total current assets | E17: =SUM(E11:E16) | F17: =SUM(F11:F16) | G17: =SUM(G11:G16) | H17: =SUM(H11:H16) | I17: =SUM(I11:I16) | J17: =SUM(J11:J16) | K17: =SUM(K11:K16)
D18: Finance receivables due after one year, net | E18: =SUMIFS(BS!$F$22:$AG$22,BS!$F$10:$AG$10,E$9) | F18: =SUMIFS(BS!$F$22:$AG$22,BS!$F$10:$AG$10,F$9) | G18: =SUMIFS(BS!$F$22:$AG$22,BS!$F$10:$AG$10,G$9) | H18: =SUMIFS(BS!$F$22:$AG$22,BS!$F$10:$AG$10,H$9) | I18: =SUMIFS(BS!$F$22:$AG$22,BS!$F$10:$AG$10,I$9) | J18: =SUMIFS(BS!$F$22:$AG$22,BS!$F$10:$AG$10,J$9) | K18: =SUMIFS(BS!$F$22:$AG$22,BS!$F$10:$AG$10,K$9)
D19: Equipment on operating leases, net | E19: =SUMIFS(BS!$F$23:$AG$23,BS!$F$10:$AG$10,E$9) | F19: =SUMIFS(BS!$F$23:$AG$23,BS!$F$10:$AG$10,F$9) | G19: =SUMIFS(BS!$F$23:$AG$23,BS!$F$10:$AG$10,G$9) | H19: =SUMIFS(BS!$F$23:$AG$23,BS!$F$10:$AG$10,H$9) | I19: =SUMIFS(BS!$F$23:$AG$23,BS!$F$10:$AG$10,I$9) | J19: =SUMIFS(BS!$F$23:$AG$23,BS!$F$10:$AG$10,J$9) | K19: =SUMIFS(BS!$F$23:$AG$23,BS!$F$10:$AG$10,K$9)
D20: Land, buildings and equipment, net | E20: =SUMIFS(BS!$F$24:$AG$24,BS!$F$10:$AG$10,E$9) | F20: =SUMIFS(BS!$F$24:$AG$24,BS!$F$10:$AG$10,F$9) | G20: =SUMIFS(BS!$F$24:$AG$24,BS!$F$10:$AG$10,G$9) | H20: =SUMIFS(BS!$F$24:$AG$24,BS!$F$10:$AG$10,H$9) | I20: =SUMIFS(BS!$F$24:$AG$24,BS!$F$10:$AG$10,I$9) | J20: =SUMIFS(BS!$F$24:$AG$24,BS!$F$10:$AG$10,J$9) | K20: =SUMIFS(BS!$F$24:$AG$24,BS!$F$10:$AG$10,K$9)
D21: Intangible assets, net | E21: =SUMIFS(BS!$F$25:$AG$25,BS!$F$10:$AG$10,E$9) | F21: =SUMIFS(BS!$F$25:$AG$25,BS!$F$10:$AG$10,F$9) | G21: =SUMIFS(BS!$F$25:$AG$25,BS!$F$10:$AG$10,G$9) | H21: =SUMIFS(BS!$F$25:$AG$25,BS!$F$10:$AG$10,H$9) | I21: =SUMIFS(BS!$F$25:$AG$25,BS!$F$10:$AG$10,I$9) | J21: =SUMIFS(BS!$F$25:$AG$25,BS!$F$10:$AG$10,J$9) | K21: =SUMIFS(BS!$F$25:$AG$25,BS!$F$10:$AG$10,K$9)
D22: Goodwill, net | E22: =SUMIFS(BS!$F$26:$AG$26,BS!$F$10:$AG$10,E$9) | F22: =SUMIFS(BS!$F$26:$AG$26,BS!$F$10:$AG$10,F$9) | G22: =SUMIFS(BS!$F$26:$AG$26,BS!$F$10:$AG$10,G$9) | H22: =SUMIFS(BS!$F$26:$AG$26,BS!$F$10:$AG$10,H$9) | I22: =SUMIFS(BS!$F$26:$AG$26,BS!$F$10:$AG$10,I$9) | J22: =SUMIFS(BS!$F$26:$AG$26,BS!$F$10:$AG$10,J$9) | K22: =SUMIFS(BS!$F$26:$AG$26,BS!$F$10:$AG$10,K$9)
D23: Deferred tax assets | E23: =SUMIFS(BS!$F$27:$AG$27,BS!$F$10:$AG$10,E$9) | F23: =SUMIFS(BS!$F$27:$AG$27,BS!$F$10:$AG$10,F$9) | G23: =SUMIFS(BS!$F$27:$AG$27,BS!$F$10:$AG$10,G$9) | H23: =SUMIFS(BS!$F$27:$AG$27,BS!$F$10:$AG$10,H$9) | I23: =SUMIFS(BS!$F$27:$AG$27,BS!$F$10:$AG$10,I$9) | J23: =SUMIFS(BS!$F$27:$AG$27,BS!$F$10:$AG$10,J$9) | K23: =SUMIFS(BS!$F$27:$AG$27,BS!$F$10:$AG$10,K$9)
D24: Other long-term assets | E24: =SUMIFS(BS!$F$28:$AG$28,BS!$F$10:$AG$10,E$9) | F24: =SUMIFS(BS!$F$28:$AG$28,BS!$F$10:$AG$10,F$9) | G24: =SUMIFS(BS!$F$28:$AG$28,BS!$F$10:$AG$10,G$9) | H24: =SUMIFS(BS!$F$28:$AG$28,BS!$F$10:$AG$10,H$9) | I24: =SUMIFS(BS!$F$28:$AG$28,BS!$F$10:$AG$10,I$9) | J24: =SUMIFS(BS!$F$28:$AG$28,BS!$F$10:$AG$10,J$9) | K24: =SUMIFS(BS!$F$28:$AG$28,BS!$F$10:$AG$10,K$9)
D25: Total assets | E25: =E17+SUM(E18:E24) | F25: =F17+SUM(F18:F24) | G25: =G17+SUM(G18:G24) | H25: =H17+SUM(H18:H24) | I25: =I17+SUM(I18:I24) | J25: =J17+SUM(J18:J24) | K25: =K17+SUM(K18:K24)
D27: Short-term debt and current portion of long-term debt | E27: =SUMIFS(BS!$F$35:$AG$35,BS!$F$10:$AG$10,E$9) | F27: =SUMIFS(BS!$F$35:$AG$35,BS!$F$10:$AG$10,F$9) | G27: =SUMIFS(BS!$F$35:$AG$35,BS!$F$10:$AG$10,G$9) | H27: =SUMIFS(BS!$F$35:$AG$35,BS!$F$10:$AG$10,H$9) | I27: =SUMIFS(BS!$F$35:$AG$35,BS!$F$10:$AG$10,I$9) | J27: =SUMIFS(BS!$F$35:$AG$35,BS!$F$10:$AG$10,J$9) | K27: =SUMIFS(BS!$F$35:$AG$35,BS!$F$10:$AG$10,K$9)
D28: Financing liability, tariff receivables monetization | E28: =SUMIFS(BS!$F$36:$AG$36,BS!$F$10:$AG$10,E$9) | F28: =SUMIFS(BS!$F$36:$AG$36,BS!$F$10:$AG$10,F$9) | G28: =SUMIFS(BS!$F$36:$AG$36,BS!$F$10:$AG$10,G$9) | H28: =SUMIFS(BS!$F$36:$AG$36,BS!$F$10:$AG$10,H$9) | I28: =SUMIFS(BS!$F$36:$AG$36,BS!$F$10:$AG$10,I$9) | J28: =SUMIFS(BS!$F$36:$AG$36,BS!$F$10:$AG$10,J$9) | K28: =SUMIFS(BS!$F$36:$AG$36,BS!$F$10:$AG$10,K$9)
D29: Accounts payable | E29: =SUMIFS(BS!$F$37:$AG$37,BS!$F$10:$AG$10,E$9) | F29: =SUMIFS(BS!$F$37:$AG$37,BS!$F$10:$AG$10,F$9) | G29: =SUMIFS(BS!$F$37:$AG$37,BS!$F$10:$AG$10,G$9) | H29: =SUMIFS(BS!$F$37:$AG$37,BS!$F$10:$AG$10,H$9) | I29: =SUMIFS(BS!$F$37:$AG$37,BS!$F$10:$AG$10,I$9) | J29: =SUMIFS(BS!$F$37:$AG$37,BS!$F$10:$AG$10,J$9) | K29: =SUMIFS(BS!$F$37:$AG$37,BS!$F$10:$AG$10,K$9)
D30: Accrued compensation and benefits costs | E30: =SUMIFS(BS!$F$38:$AG$38,BS!$F$10:$AG$10,E$9) | F30: =SUMIFS(BS!$F$38:$AG$38,BS!$F$10:$AG$10,F$9) | G30: =SUMIFS(BS!$F$38:$AG$38,BS!$F$10:$AG$10,G$9) | H30: =SUMIFS(BS!$F$38:$AG$38,BS!$F$10:$AG$10,H$9) | I30: =SUMIFS(BS!$F$38:$AG$38,BS!$F$10:$AG$10,I$9) | J30: =SUMIFS(BS!$F$38:$AG$38,BS!$F$10:$AG$10,J$9) | K30: =SUMIFS(BS!$F$38:$AG$38,BS!$F$10:$AG$10,K$9)
D31: Accrued expenses and other current liabilities | E31: =SUMIFS(BS!$F$39:$AG$39,BS!$F$10:$AG$10,E$9) | F31: =SUMIFS(BS!$F$39:$AG$39,BS!$F$10:$AG$10,F$9) | G31: =SUMIFS(BS!$F$39:$AG$39,BS!$F$10:$AG$10,G$9) | H31: =SUMIFS(BS!$F$39:$AG$39,BS!$F$10:$AG$10,H$9) | I31: =SUMIFS(BS!$F$39:$AG$39,BS!$F$10:$AG$10,I$9) | J31: =SUMIFS(BS!$F$39:$AG$39,BS!$F$10:$AG$10,J$9) | K31: =SUMIFS(BS!$F$39:$AG$39,BS!$F$10:$AG$10,K$9)
D32: Total current liabilities | E32: =SUM(E27:E31) | F32: =SUM(F27:F31) | G32: =SUM(G27:G31) | H32: =SUM(H27:H31) | I32: =SUM(I27:I31) | J32: =SUM(J27:J31) | K32: =SUM(K27:K31)
D33: Long-term debt | E33: =SUMIFS(BS!$F$43:$AG$43,BS!$F$10:$AG$10,E$9) | F33: =SUMIFS(BS!$F$43:$AG$43,BS!$F$10:$AG$10,F$9) | G33: =SUMIFS(BS!$F$43:$AG$43,BS!$F$10:$AG$10,G$9) | H33: =SUMIFS(BS!$F$43:$AG$43,BS!$F$10:$AG$10,H$9) | I33: =SUMIFS(BS!$F$43:$AG$43,BS!$F$10:$AG$10,I$9) | J33: =SUMIFS(BS!$F$43:$AG$43,BS!$F$10:$AG$10,J$9) | K33: =SUMIFS(BS!$F$43:$AG$43,BS!$F$10:$AG$10,K$9)
D34: Pension and other benefit liabilities | E34: =SUMIFS(BS!$F$44:$AG$44,BS!$F$10:$AG$10,E$9) | F34: =SUMIFS(BS!$F$44:$AG$44,BS!$F$10:$AG$10,F$9) | G34: =SUMIFS(BS!$F$44:$AG$44,BS!$F$10:$AG$10,G$9) | H34: =SUMIFS(BS!$F$44:$AG$44,BS!$F$10:$AG$10,H$9) | I34: =SUMIFS(BS!$F$44:$AG$44,BS!$F$10:$AG$10,I$9) | J34: =SUMIFS(BS!$F$44:$AG$44,BS!$F$10:$AG$10,J$9) | K34: =SUMIFS(BS!$F$44:$AG$44,BS!$F$10:$AG$10,K$9)
D35: Post-retirement medical benefits | E35: =SUMIFS(BS!$F$45:$AG$45,BS!$F$10:$AG$10,E$9) | F35: =SUMIFS(BS!$F$45:$AG$45,BS!$F$10:$AG$10,F$9) | G35: =SUMIFS(BS!$F$45:$AG$45,BS!$F$10:$AG$10,G$9) | H35: =SUMIFS(BS!$F$45:$AG$45,BS!$F$10:$AG$10,H$9) | I35: =SUMIFS(BS!$F$45:$AG$45,BS!$F$10:$AG$10,I$9) | J35: =SUMIFS(BS!$F$45:$AG$45,BS!$F$10:$AG$10,J$9) | K35: =SUMIFS(BS!$F$45:$AG$45,BS!$F$10:$AG$10,K$9)
D36: Other long-term liabilities | E36: =SUMIFS(BS!$F$46:$AG$46,BS!$F$10:$AG$10,E$9) | F36: =SUMIFS(BS!$F$46:$AG$46,BS!$F$10:$AG$10,F$9) | G36: =SUMIFS(BS!$F$46:$AG$46,BS!$F$10:$AG$10,G$9) | H36: =SUMIFS(BS!$F$46:$AG$46,BS!$F$10:$AG$10,H$9) | I36: =SUMIFS(BS!$F$46:$AG$46,BS!$F$10:$AG$10,I$9) | J36: =SUMIFS(BS!$F$46:$AG$46,BS!$F$10:$AG$10,J$9) | K36: =SUMIFS(BS!$F$46:$AG$46,BS!$F$10:$AG$10,K$9)
D37: Total liabilities | E37: =E32+SUM(E33:E36) | F37: =F32+SUM(F33:F36) | G37: =G32+SUM(G33:G36) | H37: =H32+SUM(H33:H36) | I37: =I32+SUM(I33:I36) | J37: =J32+SUM(J33:J36) | K37: =K32+SUM(K33:K36)
D39: Noncontrolling interests (temporary equity) | E39: =SUMIFS(BS!$F$52:$AG$52,BS!$F$10:$AG$10,E$9) | F39: =SUMIFS(BS!$F$52:$AG$52,BS!$F$10:$AG$10,F$9) | G39: =SUMIFS(BS!$F$52:$AG$52,BS!$F$10:$AG$10,G$9) | H39: =SUMIFS(BS!$F$52:$AG$52,BS!$F$10:$AG$10,H$9) | I39: =SUMIFS(BS!$F$52:$AG$52,BS!$F$10:$AG$10,I$9) | J39: =SUMIFS(BS!$F$52:$AG$52,BS!$F$10:$AG$10,J$9) | K39: =SUMIFS(BS!$F$52:$AG$52,BS!$F$10:$AG$10,K$9)
D40: Convertible preferred stock | E40: =SUMIFS(BS!$F$53:$AG$53,BS!$F$10:$AG$10,E$9) | F40: =SUMIFS(BS!$F$53:$AG$53,BS!$F$10:$AG$10,F$9) | G40: =SUMIFS(BS!$F$53:$AG$53,BS!$F$10:$AG$10,G$9) | H40: =SUMIFS(BS!$F$53:$AG$53,BS!$F$10:$AG$10,H$9) | I40: =SUMIFS(BS!$F$53:$AG$53,BS!$F$10:$AG$10,I$9) | J40: =SUMIFS(BS!$F$53:$AG$53,BS!$F$10:$AG$10,J$9) | K40: =SUMIFS(BS!$F$53:$AG$53,BS!$F$10:$AG$10,K$9)
D41: Common stock | E41: =SUMIFS(BS!$F$55:$AG$55,BS!$F$10:$AG$10,E$9) | F41: =SUMIFS(BS!$F$55:$AG$55,BS!$F$10:$AG$10,F$9) | G41: =SUMIFS(BS!$F$55:$AG$55,BS!$F$10:$AG$10,G$9) | H41: =SUMIFS(BS!$F$55:$AG$55,BS!$F$10:$AG$10,H$9) | I41: =SUMIFS(BS!$F$55:$AG$55,BS!$F$10:$AG$10,I$9) | J41: =SUMIFS(BS!$F$55:$AG$55,BS!$F$10:$AG$10,J$9) | K41: =SUMIFS(BS!$F$55:$AG$55,BS!$F$10:$AG$10,K$9)
D42: Additional paid-in capital | E42: =SUMIFS(BS!$F$56:$AG$56,BS!$F$10:$AG$10,E$9) | F42: =SUMIFS(BS!$F$56:$AG$56,BS!$F$10:$AG$10,F$9) | G42: =SUMIFS(BS!$F$56:$AG$56,BS!$F$10:$AG$10,G$9) | H42: =SUMIFS(BS!$F$56:$AG$56,BS!$F$10:$AG$10,H$9) | I42: =SUMIFS(BS!$F$56:$AG$56,BS!$F$10:$AG$10,I$9) | J42: =SUMIFS(BS!$F$56:$AG$56,BS!$F$10:$AG$10,J$9) | K42: =SUMIFS(BS!$F$56:$AG$56,BS!$F$10:$AG$10,K$9)
D43: Treasury stock, at cost | E43: =SUMIFS(BS!$F$57:$AG$57,BS!$F$10:$AG$10,E$9) | F43: =SUMIFS(BS!$F$57:$AG$57,BS!$F$10:$AG$10,F$9) | G43: =SUMIFS(BS!$F$57:$AG$57,BS!$F$10:$AG$10,G$9) | H43: =SUMIFS(BS!$F$57:$AG$57,BS!$F$10:$AG$10,H$9) | I43: =SUMIFS(BS!$F$57:$AG$57,BS!$F$10:$AG$10,I$9) | J43: =SUMIFS(BS!$F$57:$AG$57,BS!$F$10:$AG$10,J$9) | K43: =SUMIFS(BS!$F$57:$AG$57,BS!$F$10:$AG$10,K$9)
D44: Retained earnings | E44: =SUMIFS(BS!$F$58:$AG$58,BS!$F$10:$AG$10,E$9) | F44: =SUMIFS(BS!$F$58:$AG$58,BS!$F$10:$AG$10,F$9) | G44: =SUMIFS(BS!$F$58:$AG$58,BS!$F$10:$AG$10,G$9) | H44: =SUMIFS(BS!$F$58:$AG$58,BS!$F$10:$AG$10,H$9) | I44: =SUMIFS(BS!$F$58:$AG$58,BS!$F$10:$AG$10,I$9) | J44: =SUMIFS(BS!$F$58:$AG$58,BS!$F$10:$AG$10,J$9) | K44: =SUMIFS(BS!$F$58:$AG$58,BS!$F$10:$AG$10,K$9)
D45: Accumulated other comprehensive loss | E45: =SUMIFS(BS!$F$59:$AG$59,BS!$F$10:$AG$10,E$9) | F45: =SUMIFS(BS!$F$59:$AG$59,BS!$F$10:$AG$10,F$9) | G45: =SUMIFS(BS!$F$59:$AG$59,BS!$F$10:$AG$10,G$9) | H45: =SUMIFS(BS!$F$59:$AG$59,BS!$F$10:$AG$10,H$9) | I45: =SUMIFS(BS!$F$59:$AG$59,BS!$F$10:$AG$10,I$9) | J45: =SUMIFS(BS!$F$59:$AG$59,BS!$F$10:$AG$10,J$9) | K45: =SUMIFS(BS!$F$59:$AG$59,BS!$F$10:$AG$10,K$9)
D46: Xerox Holdings shareholders' equity | E46: =SUM(E41:E45) | F46: =SUM(F41:F45) | G46: =SUM(G41:G45) | H46: =SUM(H41:H45) | I46: =SUM(I41:I45) | J46: =SUM(J41:J45) | K46: =SUM(K41:K45)
D47: Noncontrolling interests | E47: =SUMIFS(BS!$F$63:$AG$63,BS!$F$10:$AG$10,E$9) | F47: =SUMIFS(BS!$F$63:$AG$63,BS!$F$10:$AG$10,F$9) | G47: =SUMIFS(BS!$F$63:$AG$63,BS!$F$10:$AG$10,G$9) | H47: =SUMIFS(BS!$F$63:$AG$63,BS!$F$10:$AG$10,H$9) | I47: =SUMIFS(BS!$F$63:$AG$63,BS!$F$10:$AG$10,I$9) | J47: =SUMIFS(BS!$F$63:$AG$63,BS!$F$10:$AG$10,J$9) | K47: =SUMIFS(BS!$F$63:$AG$63,BS!$F$10:$AG$10,K$9)
D48: Total equity | E48: =E46+E47 | F48: =F46+F47 | G48: =G46+G47 | H48: =H46+H47 | I48: =I46+I47 | J48: =J46+J47 | K48: =K46+K47
D50: Total liabilities and equity | E50: =E37+E39+E40+E48 | F50: =F37+F39+F40+F48 | G50: =G37+G39+G40+G48 | H50: =H37+H39+H40+H48 | I50: =I37+I39+I40+I48 | J50: =J37+J39+J40+J48 | K50: =K37+K39+K40+K48
D51: Check | E51: =E50-E25 | F51: =F50-F25 | G51: =G50-G25 | H51: =H50-H25 | I51: =I50-I25 | J51: =J50-J25 | K51: =K50-K25
D53: Memo: Leverage
D54: Adj. EBITDA (LTM) | E54: =IS!AB63 | F54: =IS!AC63 | G54: =IS!AD63 | H54: =IS!AE63 | I54: =IS!AF63 | J54: =IS!AH63 | K54: =IS!AI63
D55: Adj. EBITDA excl. IEEPA tariff benefit (LTM) | E55: =IS!AB68 | F55: =IS!AC68 | G55: =IS!AD68 | H55: =IS!AE68 | I55: =IS!AF68 | J55: =IS!AH68 | K55: =IS!AI68
D56: Gross leverage | E56: =IFERROR((E27+E33)/E54,"n/a") | F56: =IFERROR((F27+F33)/F54,"n/a") | G56: =IFERROR((G27+G33)/G54,"n/a") | H56: =IFERROR((H27+H33)/H54,"n/a") | I56: =IFERROR((I27+I33)/I54,"n/a") | J56: =IFERROR((J27+J33)/J54,"n/a") | K56: =IFERROR((K27+K33)/K54,"n/a")
D57: Net leverage | E57: =IFERROR(((E27+E33)-E11)/E54,"n/a") | F57: =IFERROR(((F27+F33)-F11)/F54,"n/a") | G57: =IFERROR(((G27+G33)-G11)/G54,"n/a") | H57: =IFERROR(((H27+H33)-H11)/H54,"n/a") | I57: =IFERROR(((I27+I33)-I11)/I54,"n/a") | J57: =IFERROR(((J27+J33)-J11)/J54,"n/a") | K57: =IFERROR(((K27+K33)-K11)/K54,"n/a")
D58: Gross leverage excl. IEEPA | E58: =IFERROR((E27+E33)/E55,"n/a") | F58: =IFERROR((F27+F33)/F55,"n/a") | G58: =IFERROR((G27+G33)/G55,"n/a") | H58: =IFERROR((H27+H33)/H55,"n/a") | I58: =IFERROR((I27+I33)/I55,"n/a") | J58: =IFERROR((J27+J33)/J55,"n/a") | K58: =IFERROR((K27+K33)/K55,"n/a")
D59: Net leverage excl. IEEPA | E59: =IFERROR(((E27+E33)-E11)/E55,"n/a") | F59: =IFERROR(((F27+F33)-F11)/F55,"n/a") | G59: =IFERROR(((G27+G33)-G11)/G55,"n/a") | H59: =IFERROR(((H27+H33)-H11)/H55,"n/a") | I59: =IFERROR(((I27+I33)-I11)/I55,"n/a") | J59: =IFERROR(((J27+J33)-J11)/J55,"n/a") | K59: =IFERROR(((K27+K33)-K11)/K55,"n/a")
D61: Note: Lexmark acquired July 1, 2025. Leverage uses balance sheet debt (excludes the tariff monetization financing liability).

Sheet Credit Analysis >
A1: Credit Analysis > | B1: ='Cover Page'!A1

Sheet NWC
A1: =C3 | B1: ='Cover Page'!A1
C3: Net Working Capital Analysis
C4: Xerox Holdings Corporation – All values in $ millions (USD), except per-share values. Data as of June 30, 2026 (2Q'26). | I4: Print Toggle | K4: 1
A8: x | C8: Net Working Capital | G8: Year Ended | N8: Change in NWC | R8: Year Ended
F10: 2021 | G10: =F10+1 | H10: =G10+1 | I10: =H10+1 | J10: =I10+1 | K10: 1Q'26 | L10: 2Q'26 | Q10: 2021 | R10: =Q10+1 | S10: =R10+1 | T10: =S10+1 | U10: =T10+1
C11: Accounts receivable, net | F11: =SUMIFS(BS!14:14,BS!$10:$10,NWC!F$10) | G11: =SUMIFS(BS!14:14,BS!$10:$10,NWC!G$10) | H11: =SUMIFS(BS!14:14,BS!$10:$10,NWC!H$10) | I11: =SUMIFS(BS!14:14,BS!$10:$10,NWC!I$10) | J11: =SUMIFS(BS!14:14,BS!$10:$10,NWC!J$10) | K11: =SUMIFS(BS!14:14,BS!$10:$10,NWC!K$10) | L11: =SUMIFS(BS!14:14,BS!$10:$10,NWC!L$10) | N11: =C11 | R11: =G11-F11 | S11: =H11-G11 | T11: =I11-H11 | U11: =J11-I11
C12: Billed finance receivables | F12: =SUMIFS(BS!15:15,BS!$10:$10,NWC!F$10) | G12: =SUMIFS(BS!15:15,BS!$10:$10,NWC!G$10) | H12: =SUMIFS(BS!15:15,BS!$10:$10,NWC!H$10) | I12: =SUMIFS(BS!15:15,BS!$10:$10,NWC!I$10) | J12: =SUMIFS(BS!15:15,BS!$10:$10,NWC!J$10) | K12: =SUMIFS(BS!15:15,BS!$10:$10,NWC!K$10) | L12: =SUMIFS(BS!15:15,BS!$10:$10,NWC!L$10) | N12: =C12 | R12: =G12-F12 | S12: =H12-G12 | T12: =I12-H12 | U12: =J12-I12
C13: Inventories | F13: =SUMIFS(BS!17:17,BS!$10:$10,NWC!F$10) | G13: =SUMIFS(BS!17:17,BS!$10:$10,NWC!G$10) | H13: =SUMIFS(BS!17:17,BS!$10:$10,NWC!H$10) | I13: =SUMIFS(BS!17:17,BS!$10:$10,NWC!I$10) | J13: =SUMIFS(BS!17:17,BS!$10:$10,NWC!J$10) | K13: =SUMIFS(BS!17:17,BS!$10:$10,NWC!K$10) | L13: =SUMIFS(BS!17:17,BS!$10:$10,NWC!L$10) | N13: =C13 | R13: =G13-F13 | S13: =H13-G13 | T13: =I13-H13 | U13: =J13-I13
C14: Other current assets | F14: =SUMIFS(BS!18:18,BS!$10:$10,NWC!F$10) | G14: =SUMIFS(BS!18:18,BS!$10:$10,NWC!G$10) | H14: =SUMIFS(BS!18:18,BS!$10:$10,NWC!H$10) | I14: =SUMIFS(BS!18:18,BS!$10:$10,NWC!I$10) | J14: =SUMIFS(BS!18:18,BS!$10:$10,NWC!J$10) | K14: =SUMIFS(BS!18:18,BS!$10:$10,NWC!K$10) | L14: =SUMIFS(BS!18:18,BS!$10:$10,NWC!L$10) | N14: =C14 | R14: =G14-F14 | S14: =H14-G14 | T14: =I14-H14 | U14: =J14-I14
C15: Accounts payable | F15: =-SUMIFS(BS!37:37,BS!$10:$10,NWC!F$10) | G15: =-SUMIFS(BS!37:37,BS!$10:$10,NWC!G$10) | H15: =-SUMIFS(BS!37:37,BS!$10:$10,NWC!H$10) | I15: =-SUMIFS(BS!37:37,BS!$10:$10,NWC!I$10) | J15: =-SUMIFS(BS!37:37,BS!$10:$10,NWC!J$10) | K15: =-SUMIFS(BS!37:37,BS!$10:$10,NWC!K$10) | L15: =-SUMIFS(BS!37:37,BS!$10:$10,NWC!L$10) | N15: =C15 | R15: =G15-F15 | S15: =H15-G15 | T15: =I15-H15 | U15: =J15-I15
C16: Accrued compensation & benefits | F16: =-SUMIFS(BS!38:38,BS!$10:$10,NWC!F$10) | G16: =-SUMIFS(BS!38:38,BS!$10:$10,NWC!G$10) | H16: =-SUMIFS(BS!38:38,BS!$10:$10,NWC!H$10) | I16: =-SUMIFS(BS!38:38,BS!$10:$10,NWC!I$10) | J16: =-SUMIFS(BS!38:38,BS!$10:$10,NWC!J$10) | K16: =-SUMIFS(BS!38:38,BS!$10:$10,NWC!K$10) | L16: =-SUMIFS(BS!38:38,BS!$10:$10,NWC!L$10) | N16: =C16 | R16: =G16-F16 | S16: =H16-G16 | T16: =I16-H16 | U16: =J16-I16
C17: Accrued exp. & other CL | F17: =-SUMIFS(BS!39:39,BS!$10:$10,NWC!F$10) | G17: =-SUMIFS(BS!39:39,BS!$10:$10,NWC!G$10) | H17: =-SUMIFS(BS!39:39,BS!$10:$10,NWC!H$10) | I17: =-SUMIFS(BS!39:39,BS!$10:$10,NWC!I$10) | J17: =-SUMIFS(BS!39:39,BS!$10:$10,NWC!J$10) | K17: =-SUMIFS(BS!39:39,BS!$10:$10,NWC!K$10) | L17: =-SUMIFS(BS!39:39,BS!$10:$10,NWC!L$10) | N17: =C17 | R17: =G17-F17 | S17: =H17-G17 | T17: =I17-H17 | U17: =J17-I17
C18: Total NWC | F18: =SUM(F11:F17) | G18: =SUM(G11:G17) | H18: =SUM(H11:H17) | I18: =SUM(I11:I17) | J18: =SUM(J11:J17) | K18: =SUM(K11:K17) | L18: =SUM(L11:L17) | N18: Change in NWC | R18: =SUM(R11:R17) | S18: =SUM(S11:S17) | T18: =SUM(T11:T17) | U18: =SUM(U11:U17)
C20: Change in NWC(1) | F20: =Q18 | G20: =R18 | H20: =S18 | I20: =T18 | J20: =U18 | K20: =K18-J18 | L20: =L18-K18 | N20: Check | R20: =SUMIFS('Quarterly NWC'!44:44,'Quarterly NWC'!$28:$28,NWC!R$10)+R18 | S20: =SUMIFS('Quarterly NWC'!44:44,'Quarterly NWC'!$28:$28,NWC!S$10)+S18 | T20: =SUMIFS('Quarterly NWC'!44:44,'Quarterly NWC'!$28:$28,NWC!T$10)+T18 | U20: =SUMIFS('Quarterly NWC'!44:44,'Quarterly NWC'!$28:$28,NWC!U$10)+U18
C22: Memo:
C23: DSO | F23: =F11/F26*F28 | G23: =G11/G26*G28 | H23: =H11/H26*H28 | I23: =I11/I26*I28 | J23: =J11/J26*J28 | K23: =K11/K26*K28 | L23: =L11/L26*L28
C24: DPO | F24: =-F15/F27*F28 | G24: =-G15/G27*G28 | H24: =-H15/H27*H28 | I24: =-I15/I27*I28 | J24: =-J15/J27*J28 | K24: =-K15/K27*K28 | L24: =-L15/L27*L28
C26: Revenue | F26: =SUMIFS(IS!13:13,IS!$9:$9,"FY"&NWC!F$10) | G26: =SUMIFS(IS!13:13,IS!$9:$9,"FY"&NWC!G$10) | H26: =SUMIFS(IS!13:13,IS!$9:$9,"FY"&NWC!H$10) | I26: =SUMIFS(IS!13:13,IS!$9:$9,"FY"&NWC!I$10) | J26: =SUMIFS(IS!13:13,IS!$9:$9,"FY"&NWC!J$10) | K26: =SUMIFS(IS!13:13,IS!$9:$9,NWC!K$10) | L26: =SUMIFS(IS!13:13,IS!$9:$9,NWC!L$10)
C27: COGS | F27: =SUMIFS(IS!19:19,IS!$9:$9,"FY"&NWC!F$10) | G27: =SUMIFS(IS!19:19,IS!$9:$9,"FY"&NWC!G$10) | H27: =SUMIFS(IS!19:19,IS!$9:$9,"FY"&NWC!H$10) | I27: =SUMIFS(IS!19:19,IS!$9:$9,"FY"&NWC!I$10) | J27: =SUMIFS(IS!19:19,IS!$9:$9,"FY"&NWC!J$10) | K27: =SUMIFS(IS!19:19,IS!$9:$9,NWC!K$10) | L27: =SUMIFS(IS!19:19,IS!$9:$9,NWC!L$10)
C28: Days | F28: 365 | G28: 365 | H28: 365 | I28: 366 | J28: 365 | K28: 91 | L28: 91
C30: (1) Change in NWC reflects year-over-year movement; a NWC build (use of cash) is a negative change.
C31: (2) Operating WC only: excludes cash, short-term debt, the tariff-receivables financing liability and current finance receivables (lease book, funded by ~$1.3bn of financing debt).
C32: (3) Billed portion of finance receivables included as trade-like receivables. Quarterly DSO/DPO use 91 days on quarterly revenue / cost of revenues.
C34: Change in Net Working Capital by Year
C35: Stacked drivers and the net change ($mm); a NWC build is a use of cash

Sheet Quarterly NWC
A1: =D3 | B1: ='Cover Page'!A1
D3: Quarterly Net Working Capital
D4: Xerox Holdings Corporation – All values in $ millions (USD), except per-share values. Data as of June 30, 2026 (2Q'26).
A8: x | D8: Quarterly | E8: 2021 | I8: 2022 | M8: 2023 | Q8: 2024 | U8: 2025 | Y8: 2026
E10: 1Q'21 | F10: 2Q'21 | G10: 3Q'21 | H10: 4Q'21 | I10: 1Q'22 | J10: 2Q'22 | K10: 3Q'22 | L10: 4Q'22 | M10: 1Q'23 | N10: 2Q'23 | O10: 3Q'23 | P10: 4Q'23 | Q10: 1Q'24 | R10: 2Q'24 | S10: 3Q'24 | T10: 4Q'24 | U10: 1Q'25 | V10: 2Q'25 | W10: 3Q'25 | X10: 4Q'25 | Y10: 1Q'26 | Z10: 2Q'26
D12: Current Assets
D13: Accounts receivable, net | E13: =SUMIFS(BS!14:14,BS!$10:$10,'Quarterly NWC'!E$10) | F13: =SUMIFS(BS!14:14,BS!$10:$10,'Quarterly NWC'!F$10) | G13: =SUMIFS(BS!14:14,BS!$10:$10,'Quarterly NWC'!G$10) | H13: =SUMIFS(BS!14:14,BS!$10:$10,'Quarterly NWC'!H$10) | I13: =SUMIFS(BS!14:14,BS!$10:$10,'Quarterly NWC'!I$10) | J13: =SUMIFS(BS!14:14,BS!$10:$10,'Quarterly NWC'!J$10) | K13: =SUMIFS(BS!14:14,BS!$10:$10,'Quarterly NWC'!K$10) | L13: =SUMIFS(BS!14:14,BS!$10:$10,'Quarterly NWC'!L$10) | ... Z13: =SUMIFS(BS!14:14,BS!$10:$10,'Quarterly NWC'!Z$10)
D14: Billed finance receivables | E14: =SUMIFS(BS!15:15,BS!$10:$10,'Quarterly NWC'!E$10) | F14: =SUMIFS(BS!15:15,BS!$10:$10,'Quarterly NWC'!F$10) | G14: =SUMIFS(BS!15:15,BS!$10:$10,'Quarterly NWC'!G$10) | H14: =SUMIFS(BS!15:15,BS!$10:$10,'Quarterly NWC'!H$10) | I14: =SUMIFS(BS!15:15,BS!$10:$10,'Quarterly NWC'!I$10) | J14: =SUMIFS(BS!15:15,BS!$10:$10,'Quarterly NWC'!J$10) | K14: =SUMIFS(BS!15:15,BS!$10:$10,'Quarterly NWC'!K$10) | L14: =SUMIFS(BS!15:15,BS!$10:$10,'Quarterly NWC'!L$10) | ... Z14: =SUMIFS(BS!15:15,BS!$10:$10,'Quarterly NWC'!Z$10)
D15: Inventories | E15: =SUMIFS(BS!17:17,BS!$10:$10,'Quarterly NWC'!E$10) | F15: =SUMIFS(BS!17:17,BS!$10:$10,'Quarterly NWC'!F$10) | G15: =SUMIFS(BS!17:17,BS!$10:$10,'Quarterly NWC'!G$10) | H15: =SUMIFS(BS!17:17,BS!$10:$10,'Quarterly NWC'!H$10) | I15: =SUMIFS(BS!17:17,BS!$10:$10,'Quarterly NWC'!I$10) | J15: =SUMIFS(BS!17:17,BS!$10:$10,'Quarterly NWC'!J$10) | K15: =SUMIFS(BS!17:17,BS!$10:$10,'Quarterly NWC'!K$10) | L15: =SUMIFS(BS!17:17,BS!$10:$10,'Quarterly NWC'!L$10) | ... Z15: =SUMIFS(BS!17:17,BS!$10:$10,'Quarterly NWC'!Z$10)
D16: Other current assets | E16: =SUMIFS(BS!18:18,BS!$10:$10,'Quarterly NWC'!E$10) | F16: =SUMIFS(BS!18:18,BS!$10:$10,'Quarterly NWC'!F$10) | G16: =SUMIFS(BS!18:18,BS!$10:$10,'Quarterly NWC'!G$10) | H16: =SUMIFS(BS!18:18,BS!$10:$10,'Quarterly NWC'!H$10) | I16: =SUMIFS(BS!18:18,BS!$10:$10,'Quarterly NWC'!I$10) | J16: =SUMIFS(BS!18:18,BS!$10:$10,'Quarterly NWC'!J$10) | K16: =SUMIFS(BS!18:18,BS!$10:$10,'Quarterly NWC'!K$10) | L16: =SUMIFS(BS!18:18,BS!$10:$10,'Quarterly NWC'!L$10) | ... Z16: =SUMIFS(BS!18:18,BS!$10:$10,'Quarterly NWC'!Z$10)
D17: Total Current Assets | E17: =SUM(E13:E16) | F17: =SUM(F13:F16) | G17: =SUM(G13:G16) | H17: =SUM(H13:H16) | I17: =SUM(I13:I16) | J17: =SUM(J13:J16) | K17: =SUM(K13:K16) | L17: =SUM(L13:L16) | ... Z17: =SUM(Z13:Z16)
D19: Current Liabilities
D20: Accounts payable | E20: =SUMIFS(BS!37:37,BS!$10:$10,'Quarterly NWC'!E$10) | F20: =SUMIFS(BS!37:37,BS!$10:$10,'Quarterly NWC'!F$10) | G20: =SUMIFS(BS!37:37,BS!$10:$10,'Quarterly NWC'!G$10) | H20: =SUMIFS(BS!37:37,BS!$10:$10,'Quarterly NWC'!H$10) | I20: =SUMIFS(BS!37:37,BS!$10:$10,'Quarterly NWC'!I$10) | J20: =SUMIFS(BS!37:37,BS!$10:$10,'Quarterly NWC'!J$10) | K20: =SUMIFS(BS!37:37,BS!$10:$10,'Quarterly NWC'!K$10) | L20: =SUMIFS(BS!37:37,BS!$10:$10,'Quarterly NWC'!L$10) | ... Z20: =SUMIFS(BS!37:37,BS!$10:$10,'Quarterly NWC'!Z$10)
D21: Accrued compensation & benefits | E21: =SUMIFS(BS!38:38,BS!$10:$10,'Quarterly NWC'!E$10) | F21: =SUMIFS(BS!38:38,BS!$10:$10,'Quarterly NWC'!F$10) | G21: =SUMIFS(BS!38:38,BS!$10:$10,'Quarterly NWC'!G$10) | H21: =SUMIFS(BS!38:38,BS!$10:$10,'Quarterly NWC'!H$10) | I21: =SUMIFS(BS!38:38,BS!$10:$10,'Quarterly NWC'!I$10) | J21: =SUMIFS(BS!38:38,BS!$10:$10,'Quarterly NWC'!J$10) | K21: =SUMIFS(BS!38:38,BS!$10:$10,'Quarterly NWC'!K$10) | L21: =SUMIFS(BS!38:38,BS!$10:$10,'Quarterly NWC'!L$10) | ... Z21: =SUMIFS(BS!38:38,BS!$10:$10,'Quarterly NWC'!Z$10)
D22: Accrued exp. & other CL | E22: =SUMIFS(BS!39:39,BS!$10:$10,'Quarterly NWC'!E$10) | F22: =SUMIFS(BS!39:39,BS!$10:$10,'Quarterly NWC'!F$10) | G22: =SUMIFS(BS!39:39,BS!$10:$10,'Quarterly NWC'!G$10) | H22: =SUMIFS(BS!39:39,BS!$10:$10,'Quarterly NWC'!H$10) | I22: =SUMIFS(BS!39:39,BS!$10:$10,'Quarterly NWC'!I$10) | J22: =SUMIFS(BS!39:39,BS!$10:$10,'Quarterly NWC'!J$10) | K22: =SUMIFS(BS!39:39,BS!$10:$10,'Quarterly NWC'!K$10) | L22: =SUMIFS(BS!39:39,BS!$10:$10,'Quarterly NWC'!L$10) | ... Z22: =SUMIFS(BS!39:39,BS!$10:$10,'Quarterly NWC'!Z$10)
D23: Total Current Liabilities | E23: =SUM(E20:E22) | F23: =SUM(F20:F22) | G23: =SUM(G20:G22) | H23: =SUM(H20:H22) | I23: =SUM(I20:I22) | J23: =SUM(J20:J22) | K23: =SUM(K20:K22) | L23: =SUM(L20:L22) | ... Z23: =SUM(Z20:Z22)
D25: NWC | E25: =E17-E23 | F25: =F17-F23 | G25: =G17-G23 | H25: =H17-H23 | I25: =I17-I23 | J25: =J17-J23 | K25: =K17-K23 | L25: =L17-L23 | ... Z25: =Z17-Z23
D26: Change in NWC | F26: =E25-F25 | G26: =F25-G25 | H26: =G25-H25 | I26: =H25-I25 | J26: =I25-J25 | K26: =J25-K25 | L26: =K25-L25 | M26: =L25-M25 | ... Z26: =Y25-Z25
A27: x | D27: Annual
E28: 2021 | F28: =E28+1 | G28: =F28+1 | H28: =G28+1 | I28: =H28+1
D30: Current Assets
D31: Accounts receivable, net | E31: =SUMIFS(BS!14:14,BS!$10:$10,'Quarterly NWC'!E$28) | F31: =SUMIFS(BS!14:14,BS!$10:$10,'Quarterly NWC'!F$28) | G31: =SUMIFS(BS!14:14,BS!$10:$10,'Quarterly NWC'!G$28) | H31: =SUMIFS(BS!14:14,BS!$10:$10,'Quarterly NWC'!H$28) | I31: =SUMIFS(BS!14:14,BS!$10:$10,'Quarterly NWC'!I$28)
D32: Billed finance receivables | E32: =SUMIFS(BS!15:15,BS!$10:$10,'Quarterly NWC'!E$28) | F32: =SUMIFS(BS!15:15,BS!$10:$10,'Quarterly NWC'!F$28) | G32: =SUMIFS(BS!15:15,BS!$10:$10,'Quarterly NWC'!G$28) | H32: =SUMIFS(BS!15:15,BS!$10:$10,'Quarterly NWC'!H$28) | I32: =SUMIFS(BS!15:15,BS!$10:$10,'Quarterly NWC'!I$28)
D33: Inventories | E33: =SUMIFS(BS!17:17,BS!$10:$10,'Quarterly NWC'!E$28) | F33: =SUMIFS(BS!17:17,BS!$10:$10,'Quarterly NWC'!F$28) | G33: =SUMIFS(BS!17:17,BS!$10:$10,'Quarterly NWC'!G$28) | H33: =SUMIFS(BS!17:17,BS!$10:$10,'Quarterly NWC'!H$28) | I33: =SUMIFS(BS!17:17,BS!$10:$10,'Quarterly NWC'!I$28)
D34: Other current assets | E34: =SUMIFS(BS!18:18,BS!$10:$10,'Quarterly NWC'!E$28) | F34: =SUMIFS(BS!18:18,BS!$10:$10,'Quarterly NWC'!F$28) | G34: =SUMIFS(BS!18:18,BS!$10:$10,'Quarterly NWC'!G$28) | H34: =SUMIFS(BS!18:18,BS!$10:$10,'Quarterly NWC'!H$28) | I34: =SUMIFS(BS!18:18,BS!$10:$10,'Quarterly NWC'!I$28)
D35: Total Current Assets | E35: =SUM(E31:E34) | F35: =SUM(F31:F34) | G35: =SUM(G31:G34) | H35: =SUM(H31:H34) | I35: =SUM(I31:I34)
D37: Current Liabilities
D38: Accounts payable | E38: =SUMIFS(BS!37:37,BS!$10:$10,'Quarterly NWC'!E$28) | F38: =SUMIFS(BS!37:37,BS!$10:$10,'Quarterly NWC'!F$28) | G38: =SUMIFS(BS!37:37,BS!$10:$10,'Quarterly NWC'!G$28) | H38: =SUMIFS(BS!37:37,BS!$10:$10,'Quarterly NWC'!H$28) | I38: =SUMIFS(BS!37:37,BS!$10:$10,'Quarterly NWC'!I$28)
D39: Accrued compensation & benefits | E39: =SUMIFS(BS!38:38,BS!$10:$10,'Quarterly NWC'!E$28) | F39: =SUMIFS(BS!38:38,BS!$10:$10,'Quarterly NWC'!F$28) | G39: =SUMIFS(BS!38:38,BS!$10:$10,'Quarterly NWC'!G$28) | H39: =SUMIFS(BS!38:38,BS!$10:$10,'Quarterly NWC'!H$28) | I39: =SUMIFS(BS!38:38,BS!$10:$10,'Quarterly NWC'!I$28)
D40: Accrued exp. & other CL | E40: =SUMIFS(BS!39:39,BS!$10:$10,'Quarterly NWC'!E$28) | F40: =SUMIFS(BS!39:39,BS!$10:$10,'Quarterly NWC'!F$28) | G40: =SUMIFS(BS!39:39,BS!$10:$10,'Quarterly NWC'!G$28) | H40: =SUMIFS(BS!39:39,BS!$10:$10,'Quarterly NWC'!H$28) | I40: =SUMIFS(BS!39:39,BS!$10:$10,'Quarterly NWC'!I$28)
D41: Total Current Liabilities | E41: =SUM(E38:E40) | F41: =SUM(F38:F40) | G41: =SUM(G38:G40) | H41: =SUM(H38:H40) | I41: =SUM(I38:I40)
D43: NWC | E43: =E35-E41 | F43: =F35-F41 | G43: =G35-G41 | H43: =H35-H41 | I43: =I35-I41
D44: Change in NWC | F44: =E43-F43 | G44: =F43-G43 | H44: =G43-H43 | I44: =H43-I43
D46: Change in NWC = prior period less current; ties to the NWC tab Check (annual).

Sheet Capital Structure
A1: =C3 | B1: ='Cover Page'!A1
C3: Capital Structure | D3: Today | E3: =TODAY()
C4: Xerox Holdings Corporation – All values in $ millions (USD). Capital structure as of June 30, 2026.
A7: x | C7: Capital Structure
D8: Face | E8: Leverage | F8: Interest | G8: Effective | H8: Annual | J8: Credit | K8: Trading | M8: Market | N8: Leverage | Q8: Effective Rate Calculation
C9: Description | D9: Value | E9: (Face) | F9: Rate | G9: Rate | H9: Interest | I9: Maturity | J9: Rating | K9: Price | L9: YTM | M9: Value | N9: (Market) | Q9: SOFR | R9: Spread | S9: Effective
C11: ABL Revolving Credit Facility ($425mm) | D11: 0 | E11: =(D11)/$D$30 | F11: 150 | G11: =S11 | H11: =D11*G11 | I11: 46895 | J11: NA | K11: NA | L11: NA | M11: NA | N11: =E11 | Q11: 0.0387 | R11: 0.015 | S11: =SUM(Q11:R11)
C12: IPCo JV Secured Term Loans ($405mm) | D12: 405 | E12: =(D11+D12)/$D$30 | F12: 812.5 | G12: =S12 | H12: =D12*G12 | I12: 47896 | J12: NA | K12: NA | L12: NA | M12: NA | N12: =E12 | Q12: =Q11 | R12: 0.08125 | S12: =SUM(Q12:R12)
C13: IPCo Class A Units ($45mm) | D13: 45 | E13: =(D11+D12+D13)/$D$30 | F13: NA | G13: NA | H13: NA | I13: NA | J13: NA | K13: NA | L13: NA | M13: NA | N13: =E13
C14: 1L Term Loan B ($705mm) | D14: 705 | E14: =(D11+D12+D13+D14)/$D$30 | F14: 400 | G14: =S14 | H14: =D14*G14 | I14: 47439 | J14: NA | K14: NA | L14: NA | M14: NA | N14: =E14 | Q14: =Q11 | R14: 0.04 | S14: =SUM(Q14:R14)
C15: 1L Senior Secured Notes ($400mm) | D15: 400 | E15: =(D11+D12+D13+D14+D15)/$D$30 | F15: 0.1025 | G15: =F15 | H15: =D15*G15 | I15: 47771 | J15: NA / B | K15: NA | L15: NA | M15: NA | N15: =E15
C16: 2L Senior Secured Notes ($494mm) | D16: 494 | E16: =(D11+D12+D13+D14+D15+D16)/$D$30 | F16: 0.135 | G16: =F16 | H16: =D16*G16 | I16: 47953 | J16: NA / CCC+ | K16: NA | L16: NA | M16: NA | N16: =E16
C17: Total Secured Debt | D17: =SUM(D11:D16) | E17: =D17/$D$30 | H17: =SUM(H11:H16) | N17: =D17/$D$30
C18: Senior Unsecured Notes due 2028 ($556mm) | D18: 556 | E18: =(D11+D12+D13+D14+D15+D16+D18)/$D$30 | F18: 0.055 | G18: =F18 | H18: =D18*G18 | I18: 46980 | J18: NA | K18: 58.6 | L18: NA | M18: =D18*K18/100 | N18: =E18
C19: Senior Unsecured Notes due 2029 ($500mm) | D19: 500 | E19: =(D11+D12+D13+D14+D15+D16+D18+D19)/$D$30 | F19: 0.08875 | G19: =F19 | H19: =D19*G19 | I19: 47452 | J19: NA / CCC | K19: 40.9 | L19: NA | M19: =D19*K19/100 | N19: =E19
C20: Convertible Senior Notes 2030 ($400mm) | D20: 400 | E20: =(D11+D12+D13+D14+D15+D16+D18+D19+D20)/$D$30 | F20: 0.0375 | G20: =F20 | H20: =D20*G20 | I20: 47557 | J20: NA / CCC | K20: NA | L20: NA | M20: NA | N20: =E20
C21: Step-Up Senior Notes due 2030 ($250mm) | D21: 250 | E21: =(D11+D12+D13+D14+D15+D16+D18+D19+D20+D21)/$D$30 | F21: 0.135 | G21: =F21 | H21: =D21*G21 | I21: 47665 | J21: Caa3 / NA | K21: NA | L21: NA | M21: NA | N21: =E21
C22: Xerox Corp. Senior Notes 2035 ($250mm) | D22: 250 | E22: =(D11+D12+D13+D14+D15+D16+D18+D19+D20+D21+D22)/$D$30 | F22: 0.048 | G22: =F22 | H22: =D22*G22 | I22: 49369 | J22: NA / CCC | K22: NA | L22: NA | M22: NA | N22: =E22
C23: Xerox Corp. Senior Notes 2039 ($350mm) | D23: 350 | E23: =(D11+D12+D13+D14+D15+D16+D18+D19+D20+D21+D22+D23)/$D$30 | F23: 0.0675 | G23: =F23 | H23: =D23*G23 | I23: 51119 | J23: NA / CCC | K23: NA | L23: NA | M23: NA | N23: =E23
C24: Total Debt | D24: =SUM(D17:D23) | E24: =D24/$D$30 | H24: =SUM(H17:H23) | N24: =D24/$D$30
C25: Less: Cash & Cash Equivalents | D25: =-BS!AA13 | E25: =D25/$D$30
C26: Net Debt | D26: =SUM(D24:D25) | E26: =D26/$D$30 | H26: =SUM(H24:H25) | N26: =D26/$D$30
C27: Series A Conv. Preferred ($180mm) | D27: 180 | E27: =(D11+D12+D13+D14+D15+D16+D18+D19+D20+D21+D22+D23+D27)/$D$30 | F27: 0.08 | G27: =F27 | H27: =D27*G27 | I27: NA | J27: NA | K27: NA | L27: NA | M27: NA | N27: =E27
C28: Net Debt & Preferred Equity | D28: =SUM(D26:D27) | E28: =D28/$D$30 | H28: =SUM(H26:H27) | N28: =D28/$D$30
C30: Memo: LTM 2Q'26 Adj. EBITDA | D30: =IS!AI63
C32: ABL Commitments | D32: 425
C33: Less: Borrowing Base Limitation | D33: -37
C34: Less: Outstanding Borrowings | D34: =-D11
C35: Less: Letters of Credit | D35: -112
C36: ABL Availability | D36: =SUM(D32:D35)
C37: Plus: Cash and Equivalents | D37: =-D25
C38: Total Liquidity | D38: =SUM(D36:D37)
C40: Source: 2Q'26 10-Q (filed 6-Aug-26) and 2Q'26 earnings deck. Principal shown; B/S carrying value $4,223m (net of ~$134m OID/fees). Excl. $90m tariff-monetization liability.
C41: Tie-out: 1Q'26 principal $4,581m less 2Q'26 activity ($125m 2026 notes repaid; $93m 2028s and $6m 2Ls repurchased) = ~$4,357m vs. $4,355m shown.
C42: IPCo JV (Feb-26, TPG): $405m TL + $45m Class A Units at XRX Brandco Holdings, secured by contributed IP; company treats both as debt. Units have no stated rate / maturity.
C43: ~$1.3bn of debt funds the finance-receivables book; core debt ~$2.9bn. Mgmt gross / net leverage 5.9x / 5.1x (carrying value).
C44: LTM Adj. EBITDA includes a $105m IEEPA tariff-refund benefit; excl. it EBITDA is $614m (~7.1x gross leverage on principal).
C45: Ratings: Moody's CFR Caa2 / neg. (Mar-26); S&P CCC+ / neg. (16-Jun-26, restored from SD after the below-par 2028 note buyback). Issue ratings Moody's / S&P.
C46: Feb-26 warrants ($8.00 strike, exp. Feb-28) can be exercised by tendering designated notes at par; uptake to date minimal.
C47: Prices: indicative TRACE-based quotes, early Oct-26 (not Bloomberg/Octus). SOFR 3.87% (13-Oct-26). XRX equity ~$3.06 (30-Aug-26).

Sheet Maturity Schedule
A1: =C2 | B1: ='Cover Page'!A1
C2: Debt Maturity Schedule
C3: Xerox Holdings Corporation – All values in $ millions (USD). As of June 30, 2026.
A6: x | C6: Debt Maturity Profile
D7: Liquidity | E7: 2028 | F7: 2029 | G7: 2030 | H7: 2031 | I7: 2035 | J7: 2039
C8: Cash & Equivalents | D8: ='Capital Structure'!$D$37
C9: ABL Availability | D9: ='Capital Structure'!$D$36
C10: Secured Term Loan | E10: =SUMIFS('Capital Structure'!$D$12:$D$12,'Capital Structure'!$I$12:$I$12,">="&DATE(E$7,1,1),'Capital Structure'!$I$12:$I$12,"<="&DATE(E$7,12,31)) | F10: =SUMIFS('Capital Structure'!$D$12:$D$12,'Capital Structure'!$I$12:$I$12,">="&DATE(F$7,1,1),'Capital Structure'!$I$12:$I$12,"<="&DATE(F$7,12,31)) | G10: =SUMIFS('Capital Structure'!$D$12:$D$12,'Capital Structure'!$I$12:$I$12,">="&DATE(G$7,1,1),'Capital Structure'!$I$12:$I$12,"<="&DATE(G$7,12,31)) | H10: =SUMIFS('Capital Structure'!$D$12:$D$12,'Capital Structure'!$I$12:$I$12,">="&DATE(H$7,1,1),'Capital Structure'!$I$12:$I$12,"<="&DATE(H$7,12,31)) | I10: =SUMIFS('Capital Structure'!$D$12:$D$12,'Capital Structure'!$I$12:$I$12,">="&DATE(I$7,1,1),'Capital Structure'!$I$12:$I$12,"<="&DATE(I$7,12,31)) | J10: =SUMIFS('Capital Structure'!$D$12:$D$12,'Capital Structure'!$I$12:$I$12,">="&DATE(J$7,1,1),'Capital Structure'!$I$12:$I$12,"<="&DATE(J$7,12,31))
C11: 1L Term Loan | E11: =SUMIFS('Capital Structure'!$D$14:$D$14,'Capital Structure'!$I$14:$I$14,">="&DATE(E$7,1,1),'Capital Structure'!$I$14:$I$14,"<="&DATE(E$7,12,31)) | F11: =SUMIFS('Capital Structure'!$D$14:$D$14,'Capital Structure'!$I$14:$I$14,">="&DATE(F$7,1,1),'Capital Structure'!$I$14:$I$14,"<="&DATE(F$7,12,31)) | G11: =SUMIFS('Capital Structure'!$D$14:$D$14,'Capital Structure'!$I$14:$I$14,">="&DATE(G$7,1,1),'Capital Structure'!$I$14:$I$14,"<="&DATE(G$7,12,31)) | H11: =SUMIFS('Capital Structure'!$D$14:$D$14,'Capital Structure'!$I$14:$I$14,">="&DATE(H$7,1,1),'Capital Structure'!$I$14:$I$14,"<="&DATE(H$7,12,31)) | I11: =SUMIFS('Capital Structure'!$D$14:$D$14,'Capital Structure'!$I$14:$I$14,">="&DATE(I$7,1,1),'Capital Structure'!$I$14:$I$14,"<="&DATE(I$7,12,31)) | J11: =SUMIFS('Capital Structure'!$D$14:$D$14,'Capital Structure'!$I$14:$I$14,">="&DATE(J$7,1,1),'Capital Structure'!$I$14:$I$14,"<="&DATE(J$7,12,31))
C12: 1L Notes | E12: =SUMIFS('Capital Structure'!$D$15:$D$15,'Capital Structure'!$I$15:$I$15,">="&DATE(E$7,1,1),'Capital Structure'!$I$15:$I$15,"<="&DATE(E$7,12,31)) | F12: =SUMIFS('Capital Structure'!$D$15:$D$15,'Capital Structure'!$I$15:$I$15,">="&DATE(F$7,1,1),'Capital Structure'!$I$15:$I$15,"<="&DATE(F$7,12,31)) | G12: =SUMIFS('Capital Structure'!$D$15:$D$15,'Capital Structure'!$I$15:$I$15,">="&DATE(G$7,1,1),'Capital Structure'!$I$15:$I$15,"<="&DATE(G$7,12,31)) | H12: =SUMIFS('Capital Structure'!$D$15:$D$15,'Capital Structure'!$I$15:$I$15,">="&DATE(H$7,1,1),'Capital Structure'!$I$15:$I$15,"<="&DATE(H$7,12,31)) | I12: =SUMIFS('Capital Structure'!$D$15:$D$15,'Capital Structure'!$I$15:$I$15,">="&DATE(I$7,1,1),'Capital Structure'!$I$15:$I$15,"<="&DATE(I$7,12,31)) | J12: =SUMIFS('Capital Structure'!$D$15:$D$15,'Capital Structure'!$I$15:$I$15,">="&DATE(J$7,1,1),'Capital Structure'!$I$15:$I$15,"<="&DATE(J$7,12,31))
C13: 2L Notes | E13: =SUMIFS('Capital Structure'!$D$16:$D$16,'Capital Structure'!$I$16:$I$16,">="&DATE(E$7,1,1),'Capital Structure'!$I$16:$I$16,"<="&DATE(E$7,12,31)) | F13: =SUMIFS('Capital Structure'!$D$16:$D$16,'Capital Structure'!$I$16:$I$16,">="&DATE(F$7,1,1),'Capital Structure'!$I$16:$I$16,"<="&DATE(F$7,12,31)) | G13: =SUMIFS('Capital Structure'!$D$16:$D$16,'Capital Structure'!$I$16:$I$16,">="&DATE(G$7,1,1),'Capital Structure'!$I$16:$I$16,"<="&DATE(G$7,12,31)) | H13: =SUMIFS('Capital Structure'!$D$16:$D$16,'Capital Structure'!$I$16:$I$16,">="&DATE(H$7,1,1),'Capital Structure'!$I$16:$I$16,"<="&DATE(H$7,12,31)) | I13: =SUMIFS('Capital Structure'!$D$16:$D$16,'Capital Structure'!$I$16:$I$16,">="&DATE(I$7,1,1),'Capital Structure'!$I$16:$I$16,"<="&DATE(I$7,12,31)) | J13: =SUMIFS('Capital Structure'!$D$16:$D$16,'Capital Structure'!$I$16:$I$16,">="&DATE(J$7,1,1),'Capital Structure'!$I$16:$I$16,"<="&DATE(J$7,12,31))
C14: Senior Unsecured Notes | E14: =SUMIFS('Capital Structure'!$D$18:$D$23,'Capital Structure'!$I$18:$I$23,">="&DATE(E$7,1,1),'Capital Structure'!$I$18:$I$23,"<="&DATE(E$7,12,31)) | F14: =SUMIFS('Capital Structure'!$D$18:$D$23,'Capital Structure'!$I$18:$I$23,">="&DATE(F$7,1,1),'Capital Structure'!$I$18:$I$23,"<="&DATE(F$7,12,31)) | G14: =SUMIFS('Capital Structure'!$D$18:$D$23,'Capital Structure'!$I$18:$I$23,">="&DATE(G$7,1,1),'Capital Structure'!$I$18:$I$23,"<="&DATE(G$7,12,31)) | H14: =SUMIFS('Capital Structure'!$D$18:$D$23,'Capital Structure'!$I$18:$I$23,">="&DATE(H$7,1,1),'Capital Structure'!$I$18:$I$23,"<="&DATE(H$7,12,31)) | I14: =SUMIFS('Capital Structure'!$D$18:$D$23,'Capital Structure'!$I$18:$I$23,">="&DATE(I$7,1,1),'Capital Structure'!$I$18:$I$23,"<="&DATE(I$7,12,31)) | J14: =SUMIFS('Capital Structure'!$D$18:$D$23,'Capital Structure'!$I$18:$I$23,">="&DATE(J$7,1,1),'Capital Structure'!$I$18:$I$23,"<="&DATE(J$7,12,31))
C15: Total | D15: =SUM(D8:D14) | E15: =SUM(E8:E14) | F15: =SUM(F8:F14) | G15: =SUM(G8:G14) | H15: =SUM(H8:H14) | I15: =SUM(I8:I14) | J15: =SUM(J8:J14)

Sheet Pricing
A1: =B2 | B1: ='Cover Page'!A1
B2: Debt & Equity Pricing
B3: NA - pricing pending (analyst to supply daily price CSV; run pricing_chart.py)

Sheet References >
A1: References > | B1: ='Cover Page'!A1

Sheet Sources
A1: =B2 | B1: ='Cover Page'!A1
B2: Sources
B3: Every figure traces to an original SEC filing or Xerox IR document. Quotes are kept under 15 words.
A4: x | B4: Source Documents
B5: Period(s) supplied | C5: Form | D5: Filed / Period end | E5: Accession no. | F5: URL | G5: Statement / page | H5: Quote (<15 words) | I5: Notes (differencing / sign / scale / restatement) | J5: Tabs fed
B6: 1Q'21 (three-month YTD) | C6: 10-Q | D6: Filed 2021-04-30; period end 2021-03-31 | E6: 0001770450-21-000025 | F6: https://www.sec.gov/Archives/edgar/data/1770450/000177045021000025/xrx-20210331.htm | G6: Condensed Consolidated Statements of Cash Flows (XBRL R6.htm); Statements of Income (Loss); Balance Sheets (XBRL R4/R5.htm) | H6: Net cash ... operating activities ... 117 | I6: Q1 as reported. $ millions. Retirement lines as originally captioned (pension only). | J6: IS, CFS, BS
B7: 2Q'21 (six-month YTD) | C7: 10-Q | D7: Filed 2021-08-04; period end 2021-06-30 | E7: 0001770450-21-000036 | F7: https://www.sec.gov/Archives/edgar/data/1770450/000177045021000036/xrx-20210630.htm | G7: Condensed Consolidated Statements of Cash Flows (XBRL R6.htm); Statements of Income (Loss); Balance Sheets (XBRL R4/R5.htm) | H7: Net cash ... operating activities ... 331 | I7: Q2 = H1 YTD - Q1. $ millions. Retirement lines as originally captioned (pension only). | J7: IS, CFS, BS
B8: 3Q'21 (nine-month YTD) | C8: 10-Q | D8: Filed 2021-11-03; period end 2021-09-30 | E8: 0001770450-21-000050 | F8: https://www.sec.gov/Archives/edgar/data/1770450/000177045021000050/xrx-20210930.htm | G8: Condensed Consolidated Statements of Cash Flows (XBRL R6.htm); Statements of Income (Loss); Balance Sheets (XBRL R4/R5.htm) | H8: Net cash ... operating activities ... 431 | I8: Q3 = 9M YTD - H1. $ millions. Retirement lines as originally captioned (pension only). | J8: IS, CFS, BS
B9: FY2021 annual column; 4Q'21 plug | C9: 10-K | D9: Filed 2022-02-23; period end 2021-12-31 | E9: 0001770450-22-000010 | F9: https://www.sec.gov/Archives/edgar/data/1770450/000177045022000010/xrx-20211231.htm | G9: Condensed Consolidated Statements of Cash Flows (XBRL R7.htm); Statements of Income (Loss); Balance Sheets (XBRL R4/R5.htm) | H9: Net cash ... operating activities ... 629 | I9: FY figures hardcoded; 4Q'21 = FY - 9M. $ millions. Deferred taxes combined with tax assets/liabilities. | J9: IS, CFS, BS
B10: 1Q'22 (three-month YTD) | C10: 10-Q | D10: Filed 2022-05-03; period end 2022-03-31 | E10: 0001770450-22-000020 | F10: https://www.sec.gov/Archives/edgar/data/1770450/000177045022000020/xrx-20220331.htm | G10: Condensed Consolidated Statements of Cash Flows (XBRL R6.htm); Statements of Income (Loss); Balance Sheets (XBRL R4/R5.htm) | H10: Net cash ... operating activities ... 66 | I10: Q1 as reported. $ millions. | J10: IS, CFS, BS
B11: 2Q'22 (six-month YTD) | C11: 10-Q | D11: Filed 2022-08-03; period end 2022-06-30 | E11: 0001770450-22-000030 | F11: https://www.sec.gov/Archives/edgar/data/1770450/000177045022000030/xrx-20220630.htm | G11: Condensed Consolidated Statements of Cash Flows (XBRL R6.htm); Statements of Income (Loss); Balance Sheets (XBRL R4/R5.htm) | H11: Net cash ... operating activities ... -19 | I11: Q2 = H1 YTD - Q1. $ millions. | J11: IS, CFS, BS
B12: 3Q'22 (nine-month YTD) | C12: 10-Q | D12: Filed 2022-11-02; period end 2022-09-30 | E12: 0001770450-22-000041 | F12: https://www.sec.gov/Archives/edgar/data/1770450/000177045022000041/xrx-20220930.htm | G12: Condensed Consolidated Statements of Cash Flows (XBRL R6.htm); Statements of Income (Loss); Balance Sheets (XBRL R4/R5.htm) | H12: Net cash ... operating activities ... -27 | I12: Q3 = 9M YTD - H1. $ millions. | J12: IS, CFS, BS
B13: FY2022 annual column; 4Q'22 plug | C13: 10-K | D13: Filed 2023-02-23; period end 2022-12-31 | E13: 0001770450-23-000011 | F13: https://www.sec.gov/Archives/edgar/data/1770450/000177045023000011/xrx-20221231.htm | G13: Condensed Consolidated Statements of Cash Flows (XBRL R7.htm); Statements of Income (Loss); Balance Sheets (XBRL R4/R5.htm) | H13: Net cash ... operating activities ... 159 | I13: FY figures hardcoded; 4Q'22 = FY - 9M. $ millions. Deferred taxes combined with tax assets/liabilities. | J13: IS, CFS, BS
B14: 1Q'23 (three-month YTD) | C14: 10-Q | D14: Filed 2023-05-01; period end 2023-03-31 | E14: 0001770450-23-000032 | F14: https://www.sec.gov/Archives/edgar/data/1770450/000177045023000032/xrx-20230331.htm | G14: Condensed Consolidated Statements of Cash Flows (XBRL R6.htm); Statements of Income (Loss); Balance Sheets (XBRL R4/R5.htm) | H14: Net cash ... operating activities ... 78 | I14: Q1 as reported. $ millions. | J14: IS, CFS, BS
B15: 2Q'23 (six-month YTD) | C15: 10-Q | D15: Filed 2023-08-02; period end 2023-06-30 | E15: 0001770450-23-000042 | F15: https://www.sec.gov/Archives/edgar/data/1770450/000177045023000042/xrx-20230630.htm | G15: Condensed Consolidated Statements of Cash Flows (XBRL R6.htm); Statements of Income (Loss); Balance Sheets (XBRL R4/R5.htm) | H15: Net cash ... operating activities ... 173 | I15: Q2 = H1 YTD - Q1. $ millions. | J15: IS, CFS, BS
B16: 3Q'23 (nine-month YTD) | C16: 10-Q | D16: Filed 2023-10-30; period end 2023-09-30 | E16: 0001770450-23-000050 | F16: https://www.sec.gov/Archives/edgar/data/1770450/000177045023000050/xrx-20230930.htm | G16: Condensed Consolidated Statements of Cash Flows (XBRL R6.htm); Statements of Income (Loss); Balance Sheets (XBRL R4/R5.htm) | H16: Net cash ... operating activities ... 297 | I16: Q3 = 9M YTD - H1. $ millions. | J16: IS, CFS, BS
... B27: 2Q'26 (six-month YTD) | C27: 10-Q | D27: Filed 2026-08-06; period end 2026-06-30 | E27: 0001770450-26-000040 | F27: https://www.sec.gov/Archives/edgar/data/1770450/000177045026000040/xrx-20260630.htm | G27: Condensed Consolidated Statements of Cash Flows (XBRL R6.htm); Statements of Income (Loss); Balance Sheets (XBRL R4/R5.htm) | H27: Net cash ... operating activities ... -107 | I27: Q2 = H1 YTD - Q1. $ millions. | J27: IS, CFS, BS
B28: 4Q EPS and 4Q tie-out rows, FY2021 to FY2025 | C28: 8-K Ex. 99.1 | D28: Filed 2022-01-25, 2023-01-26, 2024-01-25, 2025-01-28, 2026-01-29 | E28: See uploaded files | F28: EDGAR 8-K filings (CIK 1770450) | G28: Condensed Consolidated Statements of Income (Loss) | I28: Q4 reported revenue, net income and diluted EPS | J28: IS
B29: Adj. EBITDA FY2023, 1Q'24 to 4Q'24 | C29: Earnings slides | D29: Xerox IR, 2025-07-31 | E29: n/a | F29: investors.xerox.com | G29: Adjusted EBITDA and Margin Reconciliation | I29: Company-reported Adjusted EBITDA and special items | J29: IS
B30: Adj. EBITDA FY2024, FY2025, 1Q'25 to 2Q'26 | C30: Earnings slides | D30: Xerox IR, 2026-07-30 | E30: n/a | F30: investors.xerox.com | G30: Adjusted EBITDA and Margin Reconciliation | I30: Includes $105M IEEPA benefit in 2Q'26 | J30: IS
A32: x | B32: Capital Structure / Maturity Schedule tabs (built 16 Oct 2026 via HL cap-structure skill)
B33: 2Q'26 debt stack, ABL, cash | C33: 10-Q | D33: Filed 2026-08-06; period end 2026-06-30 | E33: 0001770450-26-000040 | F33: https://www.sec.gov/Archives/edgar/data/1770450/000177045026000040/xrx-20260630.htm | G33: Note - Debt; Liquidity; Balance Sheet | H33: ABL lender commitments of $425 | I33: ABL undrawn; availability $388 before ~$112 LCs (6-Aug-26) | J33: Capital Structure
B34: 1Q'26 JV financing, principal, 2028 buyback | C34: 10-Q | D34: Filed 2026-05-07; period end 2026-03-31 | E34: 0001770450-26-000030 | F34: https://www.sec.gov/Archives/edgar/data/1770450/000177045026000030/xrx-20260331.htm | G34: Note - Debt; VIE (IPCo) | H34: Term SOFR, floor 3.000%, plus margin 8.125% | I34: $405 TL + $45 Class A Units = $450 indebtedness | J34: Capital Structure
B35: Tranche principal at 2Q'26 | C35: Earnings slides | D35: Xerox IR, 2026-07-30 | E35: n/a | F35: https://investors.xerox.com/static-files/b7e7fa5f-f76d-4673-ba78-520392c48dc3 | G35: Debt / maturity profile | I35: TLB $705; 2028 notes $556; unsecured total $2,308 | J35: Capital Structure
B36: TLB terms, legacy notes | C36: 10-K | D36: Filed 2026-03-17; period end 2025-12-31 | E36: 0001770450-26-000009 | F36: https://www.sec.gov/Archives/edgar/data/1770450/000177045026000009/xrx-20251231.htm | G36: Note - Debt | I36: TLB S+400, 0.50% floor, due 17-Nov-29 | J36: Capital Structure
B37: Ratings | C37: Press | D37: Moody's Mar-2026; S&P 11/16-Jun-2026 | E37: n/a | F37: https://www.action-intell.com/2026/06/18/sp-restores-xerox-credit-rating-to-ccc-while-maintaining-negative-outlook/ | G37: Rating actions | I37: Moody's Caa2 CFR; S&P CCC+ issuer | J37: Capital Structure
B38: Bond prices (indicative) | C38: TRACE quotes | D38: Oct 5-7, 2026 | E38: n/a | F38: https://sqxbonds.com/bonds/US98421MAC01 | G38: 2028 / 2029 notes | I38: Third-party quotes; refresh on Bloomberg | J38: Capital Structure
B39: SOFR | C39: Market data | D39: 2026-10-13 | E39: n/a | F39: https://www.sofrrate.com/sofr-rate/2026-10 | G39: SOFR table | I39: 3.87%; confirm vs NY Fed | J39: Capital Structure
