Workbook
Name Active_Case: '[1]Cover Page'!$E$13
Name Circ: '[1]Cover Page'!$E$14
Name Days: '[1]Cover Page'!$E$19
Name Divest: '[1]Cover Page'!$E$18
Name Exit: '[1]Cover Page'!$E$20
Name Exit_Case: '[1]Cover Page'!$E$15

Sheet Cover Page
A1: Return to Cover
C2: Xerox Holdings Corporation (NASDAQ: XRX) – Restructuring Model
C3: All $ in Millions (USD), except Per-Share Values
C8: Credit & Restructuring Analysis
C10: Last Updated | F10: =TODAY() | H10: Data As Of | J10: 2Q'26 (June 30, 2026)
C12: Color Coding | D12: R | E12: G | F12: B | H12: Links (Ctrl + [ to Jump to Sheet)
C13: Formulas | D13: 0 | E13: 0 | F13: 0 | H13: Financial Statements
C14: Hard-Code | D14: 0 | E14: 0 | F14: 255 | H14: ='Income Statement'!A1
C15: Link to Other Sheets | D15: 0 | E15: 128 | F15: 0 | H15: ='Income Statement Output'!A1
C16: Highlight Value (Check) | D16: 255 | E16: 0 | F16: 0 | H16: ='Cash Flow Statement'!A1
H17: ='Cash Flow Statement Output'!A1
C18: Heading 1 | D18: 0 | E18: 32 | F18: 96 | H18: ='Balance Sheet'!A1
C19: Heading 2 | D19: 128 | E19: 128 | F19: 128 | H19: ='Balance Sheet Output'!A1
H20: Credit Analysis
C21: Input/Driver | D21: 255 | E21: 242 | F21: 204 | H21: ='NWC'!A1
H22: ='Quarterly NWC'!A1
C23: Sources | H23: ='Capital Structure'!A1
C24: SEC EDGAR – Xerox 10-K & 10-Q Filings | H24: ='Maturity Schedule'!A1
C25: Xerox Investor Relations – Earnings Materials
C26: Moody's & S&P Rating Actions | H26: Analysis
C27: TRACE-Based Bond Quotes (Indicative) | H27: ='Precedent Transactions'!A1
C28: Federal Reserve Bank of New York – SOFR | H28: ='$XRX Comparable Companies'!A1
C29: Note: All Financials Pulled from Xerox 10-Qs & 10-Ks | H29: ='$XRX Revenue Build'!A1
H30: ='$XRX DCF Operating Assumptions'!A1
C31: Active Case (DCF / Revenue Build) | F31: Base | H31: ='$XRX DCF'!A1
H32: ='Liquidity Analysis'!A1
H34: Stock Performance & Valuation
H35: ='$XRX Stock Performance'!A1
H36: ='$FRSH Valuation FF'!A1
H37: ='Charts'!A1

Sheet Financial Statement Inputs >
A1: Financial Statements > | B1: ='Cover Page'!A1

Sheet Income Statement
A1: =C3 | B1: ='Cover Page'!A1
C3: Historical Income Statement | AH3: Xerox Holding Corporation
C4: All values in $ millions (USD), except per-share values
A6: x | B6: x | C6: Income Statement | D6: Quarter Ended | AA6: Fiscal Year Ended December 31, | AG6: LTM
D7: 1Q'21 | E7: 2Q'21 | F7: 3Q'21 | G7: 4Q'21 | H7: 1Q'22 | I7: 2Q'22 | J7: 3Q'22 | K7: 4Q'22 | L7: 1Q'23 | M7: 2Q'23 | N7: 3Q'23 | O7: 4Q'23 | P7: 1Q'24 | Q7: 2Q'24 | R7: 3Q'24 | S7: 4Q'24 | T7: 1Q'25 | U7: 2Q'25 | V7: 3Q'25 | W7: 4Q'25 | X7: 1Q'26 | Y7: 2Q'26 | AA7: FY2021 | AB7: FY2022 | AC7: FY2023 | AD7: FY2024 | AE7: FY2025 | AG7: LTM 2Q'25 | AH7: LTM 2Q'26
C9: Revenues:
C10: Sales | D10: 602 | E10: 670 | F10: 657 | G10: =AA10-SUM(D10:F10) | H10: 592 | I10: 667 | J10: 690 | K10: =AB10-SUM(H10:J10) | L10: 659 | M10: 696 | N10: 644 | O10: =AC10-SUM(L10:N10) | P10: 523 | Q10: 611 | R10: 588 | S10: =AD10-SUM(P10:R10) | T10: 557 | U10: 665 | V10: 993 | W10: =AE10-SUM(T10:V10) | X10: 920 | Y10: 996 | AA10: 2582 | AB10: 2800 | AC10: 2720 | AD10: 2378 | AE10: 3283 | AG10: =SUM(R10:U10) | AH10: =SUM(V10:Y10)
C11: Services, maintenance, rentals and other | D11: =1053+55 | E11: =1067+56 | F11: =1046+55 | G11: =AA11-SUM(D11:F11) | H11: =1023+53 | I11: =1028+52 | J11: =1010+51 | K11: =AB11-SUM(H11:J11) | L11: =1004+52 | M11: =1009+49 | N11: =962+46 | O11: =AC11-SUM(L11:N11) | P11: 979 | Q11: 967 | R11: 940 | S11: =AD11-SUM(P11:R11) | T11: 900 | U11: 911 | V11: 968 | W11: =AE11-SUM(T11:V11) | X11: 926 | Y11: 926 | AA11: =4235+221 | AB11: =4100+207 | AC11: 4166 | AD11: 3843 | AE11: 3739 | AG11: =SUM(R11:U11) | AH11: =SUM(V11:Y11)
C12: Total revenues | D12: =D10+D11 | E12: =E10+E11 | F12: =F10+F11 | G12: =G10+G11 | H12: =H10+H11 | I12: =I10+I11 | J12: =J10+J11 | K12: =K10+K11 | ... Y12: =Y10+Y11 | AA12: =AA10+AA11 | AB12: =AB10+AB11 | AC12: =AC10+AC11 | AD12: =AD10+AD11 | AE12: =AE10+AE11 | AG12: =AG10+AG11 | AH12: =AH10+AH11
C14: Expenses:
C15: Cost of sales | D15: 420 | E15: 468 | F15: 498 | G15: =AA15-SUM(D15:F15) | H15: 435 | I15: 487 | J15: 508 | K15: =AB15-SUM(H15:J15) | L15: 425 | M15: 452 | N15: 435 | O15: =AC15-SUM(L15:N15) | P15: 340 | Q15: 387 | R15: 390 | S15: =AD15-SUM(P15:R15) | T15: 382 | U15: 480 | V15: 788 | W15: =AE15-SUM(T15:V15) | X15: 600 | Y15: 579 | AA15: 1862 | AB15: 2002 | AC15: 1778 | AD15: 1562 | AE15: 2367 | AG15: =SUM(R15:U15) | AH15: =SUM(V15:Y15)
C16: Cost of services, maintenance, rentals and other | D16: =651+28 | E16: =658+28 | F16: =662+29 | G16: =AA16-SUM(D16:F16) | H16: =679+24 | I16: =677+26 | J16: =659+28 | K16: =AB16-SUM(H16:J16) | L16: =665+36 | M16: =671+34 | N16: =651+30 | O16: =AC16-SUM(L16:N16) | P16: 719 | Q16: 671 | R16: 643 | S16: =AD16-SUM(P16:R16) | T16: 649 | U16: 645 | V16: 728 | W16: =AE16-SUM(T16:V16) | X16: 697 | Y16: 655 | AA16: =2662+111 | AB16: =2679+108 | AC16: 2794 | AD16: 2699 | AE16: 2754 | AG16: =SUM(R16:U16) | AH16: =SUM(V16:Y16)
C17: Total cost of revenues | D17: =D15+D16 | E17: =E15+E16 | F17: =F15+F16 | G17: =G15+G16 | H17: =H15+H16 | I17: =I15+I16 | J17: =J15+J16 | K17: =K15+K16 | ... Y17: =Y15+Y16 | AA17: =AA15+AA16 | AB17: =AB15+AB16 | AC17: =AC15+AC16 | AD17: =AD15+AD16 | AE17: =AE15+AE16 | AG17: =AG15+AG16 | AH17: =AH15+AH16
C18: Gross profit | D18: =D12-D17 | E18: =E12-E17 | F18: =F12-F17 | G18: =G12-G17 | H18: =H12-H17 | I18: =I12-I17 | J18: =J12-J17 | K18: =K12-K17 | ... Y18: =Y12-Y17 | AA18: =AA12-AA17 | AB18: =AB12-AB17 | AC18: =AC12-AC17 | AD18: =AD12-AD17 | AE18: =AE12-AE17 | AG18: =AG12-AG17 | AH18: =AH12-AH17
C19: Research, development and engineering expenses | D19: 74 | E19: 79 | F19: 82 | G19: =AA19-SUM(D19:F19) | H19: 78 | I19: 84 | J19: 73 | K19: =AB19-SUM(H19:J19) | L19: 64 | M19: 57 | N19: 52 | O19: =AC19-SUM(L19:N19) | P19: 49 | Q19: 50 | R19: 45 | S19: =AD19-SUM(P19:R19) | T19: 42 | U19: 43 | V19: 74 | W19: =AE19-SUM(T19:V19) | X19: 64 | Y19: 67 | AA19: 310 | AB19: 304 | AC19: 229 | AD19: 191 | AE19: 230 | AG19: =SUM(R19:U19) | AH19: =SUM(V19:Y19)
C20: Selling, administrative and general expenses | D20: 448 | E20: 434 | F20: 413 | G20: =AA20-SUM(D20:F20) | H20: 455 | I20: 459 | J20: 418 | K20: =AB20-SUM(H20:J20) | L20: 407 | M20: 433 | N20: 416 | O20: =AC20-SUM(L20:N20) | P20: 397 | Q20: 393 | R20: 370 | S20: =AD20-SUM(P20:R20) | T20: 378 | U20: 368 | V20: 477 | W20: =AE20-SUM(T20:V20) | X20: 430 | Y20: 432 | AA20: 1718 | AB20: 1760 | AC20: 1696 | AD20: 1537 | AE20: 1654 | AG20: =SUM(R20:U20) | AH20: =SUM(V20:Y20)
C21: Goodwill impairment | D21: 0 | E21: 0 | F21: 0 | G21: =AA21-SUM(D21:F21) | H21: 0 | I21: 0 | J21: 412 | K21: =AB21-SUM(H21:J21) | L21: 0 | M21: 0 | N21: 0 | O21: =AC21-SUM(L21:N21) | P21: 0 | Q21: 0 | R21: 1058 | S21: =AD21-SUM(P21:R21) | T21: 0 | U21: 0 | V21: 0 | W21: =AE21-SUM(T21:V21) | X21: 0 | Y21: 0 | AA21: 781 | AB21: 412 | AC21: 0 | AD21: 1058 | AE21: 0 | AG21: =SUM(R21:U21) | AH21: =SUM(V21:Y21)
C22: Restructuring and related costs, net | D22: 17 | E22: 12 | F22: 10 | G22: =AA22-SUM(D22:F22) | H22: 18 | I22: 1 | J22: 22 | K22: =AB22-SUM(H22:J22) | L22: 2 | M22: 23 | N22: 10 | O22: =AC22-SUM(L22:N22) | P22: 39 | Q22: 12 | R22: 56 | S22: =AD22-SUM(P22:R22) | T22: -1 | U22: 10 | V22: 59 | W22: =AE22-SUM(T22:V22) | X22: 45 | Y22: 23 | AA22: 38 | AB22: 65 | AC22: 167 | AD22: 112 | AE22: 66 | AG22: =SUM(R22:U22) | AH22: =SUM(V22:Y22)
C23: Amortization of intangible assets | D23: 15 | E23: 14 | F23: 13 | G23: =AA23-SUM(D23:F23) | H23: 11 | I23: 10 | J23: 10 | K23: =AB23-SUM(H23:J23) | L23: 11 | M23: 10 | N23: 12 | O23: =AC23-SUM(L23:N23) | P23: 10 | Q23: 10 | R23: 10 | S23: =AD23-SUM(P23:R23) | T23: 10 | U23: 10 | V23: 30 | W23: =AE23-SUM(T23:V23) | X23: 30 | Y23: 30 | AA23: 55 | AB23: 42 | AC23: 43 | AD23: 73 | AE23: 83 | AG23: =SUM(R23:U23) | AH23: =SUM(V23:Y23)
C24: Divestitures | D24: 0 | E24: 0 | F24: 0 | G24: =AA24-SUM(D24:F24) | H24: 0 | I24: 0 | J24: 0 | K24: =AB24-SUM(H24:J24) | L24: 0 | M24: 0 | N24: 0 | O24: =AC24-SUM(L24:N24) | P24: 54 | Q24: -3 | R24: 0 | S24: =AD24-SUM(P24:R24) | T24: -4 | U24: 0 | V24: 0 | W24: =AE24-SUM(T24:V24) | X24: 0 | Y24: 0 | AA24: 0 | AB24: 0 | AC24: 0 | AD24: 47 | AE24: -4 | AG24: =SUM(R24:U24) | AH24: =SUM(V24:Y24)
C25: PARC donation | D25: 0 | E25: 0 | F25: 0 | G25: =AA25-SUM(D25:F25) | H25: 0 | I25: 0 | J25: 0 | K25: =AB25-SUM(H25:J25) | L25: 0 | M25: 132 | N25: 0 | O25: =AC25-SUM(L25:N25) | P25: 0 | Q25: 0 | R25: 0 | S25: =AD25-SUM(P25:R25) | T25: 0 | U25: 0 | V25: 0 | W25: =AE25-SUM(T25:V25) | X25: 0 | Y25: 0 | AA25: 0 | AB25: 0 | AC25: 132 | AD25: 0 | AE25: 0 | AG25: =SUM(R25:U25) | AH25: =SUM(V25:Y25)
C26: Total operating expenses | D26: =SUM(D19:D25) | E26: =SUM(E19:E25) | F26: =SUM(F19:F25) | G26: =SUM(G19:G25) | H26: =SUM(H19:H25) | I26: =SUM(I19:I25) | J26: =SUM(J19:J25) | K26: =SUM(K19:K25) | ... Y26: =SUM(Y19:Y25) | AA26: =SUM(AA19:AA25) | AB26: =SUM(AB19:AB25) | AC26: =SUM(AC19:AC25) | AD26: =SUM(AD19:AD25) | AE26: =SUM(AE19:AE25) | AG26: =SUM(AG19:AG25) | AH26: =SUM(AH19:AH25)
C27: Operating (loss) income | D27: =D18-D26 | E27: =E18-E26 | F27: =F18-F26 | G27: =G18-G26 | H27: =H18-H26 | I27: =I18-I26 | J27: =J18-J26 | K27: =K18-K26 | ... Y27: =Y18-Y26 | AA27: =AA18-AA26 | AB27: =AB18-AB26 | AC27: =AC18-AC26 | AD27: =AD18-AD26 | AE27: =AE18-AE26 | AG27: =AG18-AG26 | AH27: =AH18-AH26
C28: Non-financing interest expense | D28: =52-28 | E28: =52-28 | F28: =52-29 | G28: =AA28-SUM(D28:F28) | H28: =53-24 | I28: =49-26 | J28: =49-28 | K28: =AB28-SUM(H28:J28) | L28: =50-36 | M28: =46-34 | N28: =44-30 | O28: =AC28-SUM(L28:N28) | P28: 26 | Q28: 31 | R28: 31 | S28: =AD28-SUM(P28:R28) | T28: 33 | U28: 55 | V28: 80 | W28: =AE28-SUM(T28:V28) | X28: 84 | Y28: 100 | AA28: =207-111 | AB28: =199-108 | AC28: =198-130 | AD28: 119 | AE28: 248 | AG28: =SUM(R28:U28) | AH28: =SUM(V28:Y28)
C29: Other expenses (income), net | D29: =4-0-24 | E29: =1-1-24 | F29: =-33-1-23 | G29: =AA29-SUM(D29:F29) | H29: =57-1-29 | I29: =8-1-23 | J29: =1-1-21 | K29: =AB29-SUM(H29:J29) | L29: =20-0-14 | M29: =31-1-12 | N29: =-17-1-14 | O29: =AC29-SUM(L29:N29) | P29: =44-26 | Q29: =33-31 | R29: =43-31 | S29: =AD29-SUM(P29:R29) | T29: 35 | U29: 25 | V29: =105-80 | W29: =AE29-SUM(T29:V29) | X29: -31 | Y29: 5 | AA29: =-27-(207-111) | AB29: =60-(199-108) | AC29: =75-(198-130) | AD29: =158-119 | AE29: =360-248 | AG29: =SUM(R29:U29) | AH29: =SUM(V29:Y29)
C30: Income (loss) before income taxes | D30: =D27-D28-D29 | E30: =E27-E28-E29 | F30: =F27-F28-F29 | G30: =G27-G28-G29 | H30: =H27-H28-H29 | I30: =I27-I28-I29 | J30: =J27-J28-J29 | K30: =K27-K28-K29 | ... Y30: =Y27-Y28-Y29 | AA30: =AA27-AA28-AA29 | AB30: =AB27-AB28-AB29 | AC30: =AC27-AC28-AC29 | AD30: =AD27-AD28-AD29 | AE30: =AE27-AE28-AE29 | AG30: =AG27-AG28-AG29 | AH30: =AH27-AH28-AH29
C31: Income tax expense (benefit) | D31: 14 | E31: 9 | F31: -4 | G31: =AA31-SUM(D31:F31) | H31: -31 | I31: 1 | J31: 3 | K31: =AB31-SUM(H31:J31) | L31: 14 | M31: -28 | N31: 15 | O31: =AC31-SUM(L31:N31) | P31: -37 | Q31: 7 | R31: 118 | S31: =AD31-SUM(P31:R31) | T31: 23 | U31: 46 | V31: 460 | W31: =AE31-SUM(T31:V31) | X31: 32 | Y31: 18 | AA31: -17 | AB31: -3 | AC31: -29 | AD31: 105 | AE31: 541 | AG31: =SUM(R31:U31) | AH31: =SUM(V31:Y31)
C32: Net Income (loss) | D32: =D30-D31 | E32: =E30-E31 | F32: =F30-F31 | G32: =G30-G31 | H32: =H30-H31 | I32: =I30-I31 | J32: =J30-J31 | K32: =K30-K31 | ... Y32: =Y30-Y31 | AA32: =AA30-AA31 | AB32: =AB30-AB31 | AC32: =AC30-AC31 | AD32: =AD30-AD31 | AE32: =AE30-AE31 | AG32: =AG30-AG31 | AH32: =AH30-AH31
C33: Less: net (income) loss attributable to noncontrolling interests | D33: 0 | E33: 0 | F33: 1 | G33: =AA33-SUM(D33:F33) | H33: 1 | I33: 1 | J33: -1 | K33: =AB33-SUM(H33:J33) | L33: 0 | M33: -1 | N33: 0 | O33: =AC33-SUM(L33:N33) | P33: 0 | Q33: 0 | R33: 0 | S33: =AD33-SUM(P33:R33) | T33: 0 | U33: 0 | V33: 0 | W33: =AE33-SUM(T33:V33) | X33: 0 | Y33: 0 | AA33: 0 | AB33: 0 | AC33: 0 | AD33: 0 | AE33: 0 | AG33: =SUM(R33:U33) | AH33: =SUM(V33:Y33)
B34: x | C34: Net (loss) income attributable to Xerox Holdings | D34: =D32+D33 | E34: =E32+E33 | F34: =F32+F33 | G34: =G32+G33 | H34: =H32+H33 | I34: =I32+I33 | J34: =J32+J33 | K34: =K32+K33 | ... Y34: =Y32+Y33 | AA34: =AA32+AA33 | AB34: =AB32+AB33 | AC34: =AC32+AC33 | AD34: =AD32+AD33 | AE34: =AE32+AE33 | AG34: =AG32+AG33 | AH34: =AH32+AH33
B38: x | C38: Adjusted EBITDA Build | D38: Quarter Ended | AA38: Fiscal Year Ended December 31, | AG38: LTM
C39: Net (loss) income | D39: =D32 | E39: =E32 | F39: =F32 | G39: =G32 | H39: =H32 | I39: =I32 | J39: =J32 | K39: =K32 | ... Y39: =Y32 | AA39: =AA32 | AB39: =AB32 | AC39: =AC32 | AD39: =AD32 | AE39: =AE32 | AG39: =SUM(R39:U39) | AH39: =SUM(V39:Y39)
C40: Non-financing interest expense | D40: =D28 | E40: =E28 | F40: =F28 | G40: =G28 | H40: =H28 | I40: =I28 | J40: =J28 | K40: =K28 | ... Y40: =Y28 | AA40: =AA28 | AB40: =AB28 | AC40: =AC28 | AD40: =AD28 | AE40: =AE28 | AG40: =SUM(R40:U40) | AH40: =SUM(V40:Y40)
C41: Other expenses (income), net | D41: =D29 | E41: =E29 | F41: =F29 | G41: =G29 | H41: =H29 | I41: =I29 | J41: =J29 | K41: =K29 | ... Y41: =Y29 | AA41: =AA29 | AB41: =AB29 | AC41: =AC29 | AD41: =AD29 | AE41: =AE29 | AG41: =SUM(R41:U41) | AH41: =SUM(V41:Y41)
C42: Income tax expense (benefit) | D42: =D31 | E42: =E31 | F42: =F31 | G42: =G31 | H42: =H31 | I42: =I31 | J42: =J31 | K42: =K31 | ... Y42: =Y31 | AA42: =AA31 | AB42: =AB31 | AC42: =AC31 | AD42: =AD31 | AE42: =AE31 | AG42: =SUM(R42:U42) | AH42: =SUM(V42:Y42)
C43: Depreciation and amortization (excl. customer contract costs) | D43: ='Cash Flow Statement'!E16 | E43: ='Cash Flow Statement'!F16 | F43: ='Cash Flow Statement'!G16 | G43: ='Cash Flow Statement'!H16 | H43: ='Cash Flow Statement'!I16 | I43: ='Cash Flow Statement'!J16 | J43: ='Cash Flow Statement'!K16 | K43: ='Cash Flow Statement'!L16 | ... Y43: ='Cash Flow Statement'!Z16 | AA43: ='Cash Flow Statement'!AB16 | AB43: ='Cash Flow Statement'!AC16 | AC43: ='Cash Flow Statement'!AD16 | AD43: ='Cash Flow Statement'!AE16 | AE43: ='Cash Flow Statement'!AF16 | AG43: =SUM(R43:U43) | AH43: =SUM(V43:Y43)
C44: Goodwill impairment | D44: =D21 | E44: =E21 | F44: =F21 | G44: =G21 | H44: =H21 | I44: =I21 | J44: =J21 | K44: =K21 | ... Y44: =Y21 | AA44: =AA21 | AB44: =AB21 | AC44: =AC21 | AD44: =AD21 | AE44: =AE21 | AG44: =SUM(R44:U44) | AH44: =SUM(V44:Y44)
C45: EBITDA | D45: =SUM(D39:D44) | E45: =SUM(E39:E44) | F45: =SUM(F39:F44) | G45: =SUM(G39:G44) | H45: =SUM(H39:H44) | I45: =SUM(I39:I44) | J45: =SUM(J39:J44) | K45: =SUM(K39:K44) | ... Y45: =SUM(Y39:Y44) | AA45: =SUM(AA39:AA44) | AB45: =SUM(AB39:AB44) | AC45: =SUM(AC39:AC44) | AD45: =SUM(AD39:AD44) | AE45: =SUM(AE39:AE44) | AG45: =SUM(AG39:AG44) | AH45: =SUM(AH39:AH44)
C46: Stock-based compensation | D46: ='Cash Flow Statement'!E25 | E46: ='Cash Flow Statement'!F25 | F46: ='Cash Flow Statement'!G25 | G46: ='Cash Flow Statement'!H25 | H46: ='Cash Flow Statement'!I25 | I46: ='Cash Flow Statement'!J25 | J46: ='Cash Flow Statement'!K25 | K46: ='Cash Flow Statement'!L25 | ... Y46: ='Cash Flow Statement'!Z25 | AA46: ='Cash Flow Statement'!AB25 | AB46: ='Cash Flow Statement'!AC25 | AC46: ='Cash Flow Statement'!AD25 | AD46: ='Cash Flow Statement'!AE25 | AE46: ='Cash Flow Statement'!AF25 | AG46: =SUM(R46:U46) | AH46: =SUM(V46:Y46)
C47: Restructuring and related costs, net | D47: =D22 | E47: =E22 | F47: =F22 | G47: =G22 | H47: =H22 | I47: =I22 | J47: =J22 | K47: =K22 | ... Y47: =Y22 | AA47: =AA22 | AB47: =AB22 | AC47: =AC22 | AD47: =AD22 | AE47: =AE22 | AG47: =SUM(R47:U47) | AH47: =SUM(V47:Y47)
C48: PARC donation | D48: =D25 | E48: =E25 | F48: =F25 | G48: =G25 | H48: =H25 | I48: =I25 | J48: =J25 | K48: =K25 | ... Y48: =Y25 | AA48: =AA25 | AB48: =AB25 | AC48: =AC25 | AD48: =AD25 | AE48: =AE25 | AG48: =SUM(R48:U48) | AH48: =SUM(V48:Y48)
C49: Divestitures | D49: =D24 | E49: =E24 | F49: =F24 | G49: =G24 | H49: =H24 | I49: =I24 | J49: =J24 | K49: =K24 | ... Y49: =Y24 | AA49: =AA24 | AB49: =AB24 | AC49: =AC24 | AD49: =AD24 | AE49: =AE24 | AG49: =SUM(R49:U49) | AH49: =SUM(V49:Y49)
C50: Transformation-related costs | D50: 0 | E50: 0 | F50: 0 | G50: 0 | H50: 0 | I50: 0 | J50: 0 | K50: 0 | L50: 0 | M50: 0 | N50: 0 | O50: 0 | P50: 0 | Q50: 0 | R50: 0 | S50: =AD50-SUM(P50:R50) | T50: 6 | U50: 3 | V50: 3 | W50: =AE50-SUM(T50:V50) | X50: 2 | Y50: 2 | AA50: =AA25 | AB50: =AB25 | AC50: 0 | AD50: 12 | AE50: 17 | AG50: =SUM(R50:U50) | AH50: =SUM(V50:Y50)
C51: Transaction and related costs, net | D51: 0 | E51: 0 | F51: 0 | G51: 0 | H51: 0 | I51: 0 | J51: 0 | K51: 0 | L51: 0 | M51: 0 | N51: 0 | O51: 0 | P51: 0 | Q51: 0 | R51: 0 | S51: =AD51-SUM(P51:R51) | T51: 3 | U51: 6 | V51: 23 | W51: =AE51-SUM(T51:V51) | X51: 4 | Y51: 0 | AA51: 0 | AB51: 0 | AC51: 0 | AD51: 7 | AE51: 34 | AG51: =SUM(R51:U51) | AH51: =SUM(V51:Y51)
C52: Inventory impact, exit of Production Print manufacturing | D52: 0 | E52: 0 | F52: 0 | G52: 0 | H52: 0 | I52: 0 | J52: 0 | K52: 0 | L52: 0 | M52: 0 | N52: 0 | O52: 0 | P52: 36 | Q52: 8 | R52: 0 | S52: =AD52-SUM(P52:R52) | T52: 7 | U52: 10 | V52: 3 | W52: =AE52-SUM(T52:V52) | X52: 0 | Y52: 0 | AA52: 0 | AB52: 0 | AC52: 0 | AD52: 51 | AE52: 24 | AG52: =SUM(R52:U52) | AH52: =SUM(V52:Y52)
C53: Lexmark inventory purchase accounting adjustment | D53: 0 | E53: 0 | F53: 0 | G53: 0 | H53: 0 | I53: 0 | J53: 0 | K53: 0 | L53: 0 | M53: 0 | N53: 0 | O53: 0 | P53: 0 | Q53: 0 | R53: 0 | S53: 0 | T53: 0 | U53: 0 | V53: 102 | W53: =AE53-SUM(T53:V53) | X53: 0 | Y53: 0 | AA53: 0 | AB53: 0 | AC53: 0 | AD53: 0 | AE53: 102 | AG53: =SUM(R53:U53) | AH53: =SUM(V53:Y53)
C54: Lexmark settlement of pre-existing employment agreements | D54: 0 | E54: 0 | F54: 0 | G54: 0 | H54: 0 | I54: 0 | J54: 0 | K54: 0 | L54: 0 | M54: 0 | N54: 0 | O54: 0 | P54: 0 | Q54: 0 | R54: 0 | S54: 0 | T54: 0 | U54: 0 | V54: 24 | W54: =AE54-SUM(T54:V54) | X54: 0 | Y54: 0 | AA54: 0 | AB54: 0 | AC54: 0 | AD54: 0 | AE54: 25 | AG54: =SUM(R54:U54) | AH54: =SUM(V54:Y54)
C55: Adjusted EBITDA | D55: =D45+SUM(D46:D54) | E55: =E45+SUM(E46:E54) | F55: =F45+SUM(F46:F54) | G55: =G45+SUM(G46:G54) | H55: =H45+SUM(H46:H54) | I55: =I45+SUM(I46:I54) | J55: =J45+SUM(J46:J54) | K55: =K45+SUM(K46:K54) | ... Y55: =Y45+SUM(Y46:Y54) | AA55: =AA45+SUM(AA46:AA54) | AB55: =AB45+SUM(AB46:AB54) | AC55: =AC45+SUM(AC46:AC54) | AD55: =AD45+SUM(AD46:AD54) | AE55: =AE45+SUM(AE46:AE54) | AG55: =AG45+SUM(AG46:AG54) | AH55: =AH45+SUM(AH46:AH54)
C56: Less: IEEPA tariff refund benefit (in cost of sales) | D56: 0 | E56: 0 | F56: 0 | G56: 0 | H56: 0 | I56: 0 | J56: 0 | K56: 0 | L56: 0 | M56: 0 | N56: 0 | O56: 0 | P56: 0 | Q56: 0 | R56: 0 | S56: 0 | T56: 0 | U56: 0 | V56: 0 | W56: 0 | X56: 0 | Y56: -105 | AA56: 0 | AB56: 0 | AC56: 0 | AD56: 0 | AE56: 0 | AG56: =SUM(R56:U56) | AH56: =SUM(V56:Y56)
B57: x | C57: Adjusted EBITDA excl. IEEPA tariff benefit | D57: =D55+D56 | E57: =E55+E56 | F57: =F55+F56 | G57: =G55+G56 | H57: =H55+H56 | I57: =I55+I56 | J57: =J55+J56 | K57: =K55+K56 | ... Y57: =Y55+Y56 | AA57: =AA55+AA56 | AB57: =AB55+AB56 | AC57: =AC55+AC56 | AD57: =AD55+AD56 | AE57: =AE55+AE56 | AG57: =AG55+AG56 | AH57: =AH55+AH56
C59: Memo:
C60: Total revenue growth (YoY) | D60: n.a. | E60: n.a. | F60: n.a. | G60: n.a. | H60: =H12/D12-1 | I60: =I12/E12-1 | J60: =J12/F12-1 | K60: =K12/G12-1 | L60: =L12/H12-1 | M60: =M12/I12-1 | N60: =N12/J12-1 | O60: =O12/K12-1 | ... Y60: =Y12/U12-1 | AB60: =AB12/AA12-1 | AC60: =AC12/AB12-1 | AD60: =AD12/AC12-1 | AE60: =AE12/AD12-1 | AG60: =SUM(R12:U12)/SUM(N12:Q12)-1 | AH60: =AH12/AG12-1
C61: Gross margin % | D61: =D18/D12 | E61: =E18/E12 | F61: =F18/F12 | G61: =G18/G12 | H61: =H18/H12 | I61: =I18/I12 | J61: =J18/J12 | K61: =K18/K12 | ... Y61: =Y18/Y12 | AA61: =AA18/AA12 | AB61: =AB18/AB12 | AC61: =AC18/AC12 | AD61: =AD18/AD12 | AE61: =AE18/AE12 | AG61: =AG18/AG12 | AH61: =AH18/AH12
C62: EBITDA margin % | D62: =D45/D12 | E62: =E45/E12 | F62: =F45/F12 | G62: =G45/G12 | H62: =H45/H12 | I62: =I45/I12 | J62: =J45/J12 | K62: =K45/K12 | ... Y62: =Y45/Y12 | AA62: =AA45/AA12 | AB62: =AB45/AB12 | AC62: =AC45/AC12 | AD62: =AD45/AD12 | AE62: =AE45/AE12 | AG62: =AG45/AG12 | AH62: =AH45/AH12
C63: Adjusted EBITDA margin % | D63: =D55/D12 | E63: =E55/E12 | F63: =F55/F12 | G63: =G55/G12 | H63: =H55/H12 | I63: =I55/I12 | J63: =J55/J12 | K63: =K55/K12 | ... Y63: =Y55/Y12 | AA63: =AA55/AA12 | AB63: =AB55/AB12 | AC63: =AC55/AC12 | AD63: =AD55/AD12 | AE63: =AE55/AE12 | AG63: =AG55/AG12 | AH63: =AH55/AH12
A64: x | B64: x | C64: Adjusted EBITDA excl. IEEPA margin % | D64: =D57/D12 | E64: =E57/E12 | F64: =F57/F12 | G64: =G57/G12 | H64: =H57/H12 | I64: =I57/I12 | J64: =J57/J12 | K64: =K57/K12 | ... Y64: =Y57/Y12 | AA64: =AA57/AA12 | AB64: =AB57/AB12 | AC64: =AC57/AC12 | AD64: =AD57/AD12 | AE64: =AE57/AE12 | AG64: =AG57/AG12 | AH64: =AH57/AH12
A65: End

Sheet Balance Sheet
A1: =C3 | B1: ='Cover Page'!A1
C3: Balance Sheet | AI3: Xerox Holdings Corporation
C4: All values in $ millions (USD)
E6: 1 | F6: 2 | G6: 3 | H6: 4 | I6: 1 | J6: 2 | K6: 3 | L6: 4 | M6: 1 | N6: 2 | O6: 3 | P6: 4 | Q6: 1 | R6: 2 | S6: 3 | T6: 4 | U6: 1 | V6: 2 | W6: 3 | X6: 4 | Y6: 1 | Z6: 2
E7: 2021 | F7: 2021 | G7: 2021 | H7: 2021 | I7: 2022 | J7: 2022 | K7: 2022 | L7: 2022 | M7: 2023 | N7: 2023 | O7: 2023 | P7: 2023 | Q7: 2024 | R7: 2024 | S7: 2024 | T7: 2024 | U7: 2025 | V7: 2025 | W7: 2025 | X7: 2025 | Y7: 2026 | Z7: 2026 | AB7: 2021 | AC7: 2022 | AD7: 2023 | AE7: 2024 | AF7: 2025
E8: 44286 | F8: 44377 | G8: 44469 | H8: 44561 | I8: 44651 | J8: 44742 | K8: 44834 | L8: 44926 | M8: 45016 | N8: 45107 | O8: 45199 | P8: 45291 | Q8: 45382 | R8: 45473 | S8: 45565 | T8: 45657 | U8: 45747 | V8: 45838 | W8: 45930 | X8: 46022 | Y8: 46112 | Z8: 46203 | AB8: 44561 | AC8: 44926 | AD8: 45291 | AE8: 45657 | AF8: 46022
A9: x | B9: x | C9: Balance Sheet | E9: Quarter Ended | AB9: Fiscal Year Ended December 31, | AH9: LTM
E10: =E6&"Q'"&RIGHT(E7,2) | F10: =F6&"Q'"&RIGHT(F7,2) | G10: =G6&"Q'"&RIGHT(G7,2) | H10: =H6&"Q'"&RIGHT(H7,2) | I10: =I6&"Q'"&RIGHT(I7,2) | J10: =J6&"Q'"&RIGHT(J7,2) | K10: =K6&"Q'"&RIGHT(K7,2) | L10: =L6&"Q'"&RIGHT(L7,2) | ... Z10: =Z6&"Q'"&RIGHT(Z7,2) | AB10: 2021 | AC10: 2022 | AD10: 2023 | AE10: 2024 | AF10: 2025 | AH10: $ Chg '25 | AI10: % Chg '25
C12: Assets:
C13: Cash and cash equivalents | E13: 2379 | F13: 2124 | G13: 2209 | H13: 1840 | I13: 1681 | J13: 1151 | K13: 932 | L13: 1045 | M13: 591 | N13: 477 | O13: 532 | P13: 519 | Q13: 685 | R13: 485 | S13: 521 | T13: 576 | U13: 336 | V13: 449 | W13: 479 | X13: 512 | Y13: 585 | Z13: 495 | AB13: =H13 | AC13: =L13 | AD13: =P13 | AE13: =T13 | AF13: =X13 | AH13: =AF13-AE13 | AI13: =IFERROR(AH13/ABS(AE13),0)
C14: Accounts receivable, net | E14: 781 | F14: 846 | G14: 891 | H14: 818 | I14: 807 | J14: 852 | K14: 835 | L14: 857 | M14: 818 | N14: 903 | O14: 880 | P14: 850 | Q14: 846 | R14: 847 | S14: 821 | T14: 796 | U14: 819 | V14: 862 | W14: 1196 | X14: 1122 | Y14: 1218 | Z14: 1185 | AB14: =H14 | AC14: =L14 | AD14: =P14 | AE14: =T14 | AF14: =X14 | AH14: =AF14-AE14 | AI14: =IFERROR(AH14/ABS(AE14),0)
C15: Billed portion of finance receivables, net | E15: 92 | F15: 89 | G15: 100 | H15: 94 | I15: 89 | J15: 83 | K15: 91 | L15: 93 | M15: 94 | N15: 70 | O15: 80 | P15: 71 | Q15: 67 | R15: 70 | S15: 50 | T15: 48 | U15: 43 | V15: 46 | W15: 53 | X15: 46 | Y15: 43 | Z15: 40 | AB15: =H15 | AC15: =L15 | AD15: =P15 | AE15: =T15 | AF15: =X15 | AH15: =AF15-AE15 | AI15: =IFERROR(AH15/ABS(AE15),0)
C16: Finance receivables, net | E16: 1065 | F16: 1057 | G16: 1039 | H16: 1042 | I16: 1023 | J16: 1019 | K16: 995 | L16: 1061 | M16: 1022 | N16: 940 | O16: 906 | P16: 842 | Q16: 783 | R16: 713 | S16: 664 | T16: 608 | U16: 583 | V16: 584 | W16: 553 | X16: 510 | Y16: 476 | Z16: 442 | AB16: =H16 | AC16: =L16 | AD16: =P16 | AE16: =T16 | AF16: =X16 | AH16: =AF16-AE16 | AI16: =IFERROR(AH16/ABS(AE16),0)
C17: Inventories | E17: 841 | F17: 815 | G17: 788 | H17: 696 | I17: 732 | J17: 765 | K17: 777 | L17: 797 | M17: 863 | N17: 782 | O17: 728 | P17: 661 | Q17: 736 | R17: 737 | S17: 732 | T17: 695 | U17: 836 | V17: 871 | W17: 1143 | X17: 1016 | Y17: 1043 | Z17: 1043 | AB17: =H17 | AC17: =L17 | AD17: =P17 | AE17: =T17 | AF17: =X17 | AH17: =AF17-AE17 | AI17: =IFERROR(AH17/ABS(AE17),0)
C18: Other current assets | E18: 262 | F18: 244 | G18: 209 | H18: 211 | I18: 234 | J18: 232 | K18: 265 | L18: 254 | M18: 252 | N18: 218 | O18: 228 | P18: 234 | Q18: 231 | R18: 199 | S18: 223 | T18: 212 | U18: 250 | V18: 731 | W18: 329 | X18: 362 | Y18: 415 | Z18: 492 | AB18: =H18 | AC18: =L18 | AD18: =P18 | AE18: =T18 | AF18: =X18 | AH18: =AF18-AE18 | AI18: =IFERROR(AH18/ABS(AE18),0)
C19: Total current assets | E19: =SUM(E13:E18) | F19: =SUM(F13:F18) | G19: =SUM(G13:G18) | H19: =SUM(H13:H18) | I19: =SUM(I13:I18) | J19: =SUM(J13:J18) | K19: =SUM(K13:K18) | L19: =SUM(L13:L18) | ... Z19: =SUM(Z13:Z18) | AB19: =SUM(AB13:AB18) | AC19: =SUM(AC13:AC18) | AD19: =SUM(AD13:AD18) | AE19: =SUM(AE13:AE18) | AF19: =SUM(AF13:AF18) | AH19: =AF19-AE19 | AI19: =IFERROR(AH19/ABS(AE19),0)
C20: Total current assets | E20: 5420 | F20: 5175 | G20: 5236 | H20: 4701 | I20: 4566 | J20: 4102 | K20: 3895 | L20: 4107 | M20: 3640 | N20: 3390 | O20: 3354 | P20: 3177 | Q20: 3348 | R20: 3051 | S20: 3011 | T20: 2935 | U20: 2867 | V20: 3543 | W20: 3753 | X20: 3568 | Y20: 3780 | Z20: 3697 | AB20: =H20 | AC20: =L20 | AD20: =P20 | AE20: =T20 | AF20: =X20
C21: Check | E21: =E19-E20 | F21: =F19-F20 | G21: =G19-G20 | H21: =H19-H20 | I21: =I19-I20 | J21: =J19-J20 | K21: =K19-K20 | L21: =L19-L20 | ... Z21: =Z19-Z20 | AB21: =AB19-AB20 | AC21: =AC19-AC20 | AD21: =AD19-AD20 | AE21: =AE19-AE20 | AF21: =AF19-AF20
C22: Finance receivables due after one year, net | E22: 1920 | F22: 1971 | G22: 1936 | H22: 1934 | I22: 1893 | J22: 1845 | K22: 1814 | L22: 1948 | M22: 1864 | N22: 1697 | O22: 1605 | P22: 1597 | Q22: 1408 | R22: 1277 | S22: 1275 | T22: 1089 | U22: 1013 | V22: 990 | W22: 950 | X22: 846 | Y22: 797 | Z22: 732 | AB22: =H22 | AC22: =L22 | AD22: =P22 | AE22: =T22 | AF22: =X22 | AH22: =AF22-AE22 | AI22: =IFERROR(AH22/ABS(AE22),0)
C23: Equipment on operating leases, net | E23: 277 | F23: 271 | G23: 254 | H23: 253 | I23: 254 | J23: 226 | K23: 216 | L23: 235 | M23: 250 | N23: 259 | O23: 257 | P23: 265 | Q23: 257 | R23: 253 | S23: 255 | T23: 245 | U23: 248 | V23: 249 | W23: 300 | X23: 299 | Y23: 292 | Z23: 283 | AB23: =H23 | AC23: =L23 | AD23: =P23 | AE23: =T23 | AF23: =X23 | AH23: =AF23-AE23 | AI23: =IFERROR(AH23/ABS(AE23),0)
C24: Land, buildings and equipment, net | E24: 393 | F24: 372 | G24: 370 | H24: 358 | I24: 350 | J24: 334 | K24: 315 | L24: 320 | M24: 311 | N24: 281 | O24: 273 | P24: 266 | Q24: 245 | R24: 227 | S24: 225 | T24: 251 | U24: 195 | V24: 187 | W24: 427 | X24: 390 | Y24: 378 | Z24: 378 | AB24: =H24 | AC24: =L24 | AD24: =P24 | AE24: =T24 | AF24: =X24 | AH24: =AF24-AE24 | AI24: =IFERROR(AH24/ABS(AE24),0)
C25: Intangible assets, net | E25: 223 | F25: 230 | G25: 216 | H25: 211 | I25: 240 | J25: 223 | K25: 216 | L25: 208 | M25: 202 | N25: 194 | O25: 183 | P25: 177 | Q25: 165 | R25: 155 | S25: 149 | T25: 236 | U25: 228 | V25: 222 | W25: 954 | X25: 921 | Y25: 891 | Z25: 857 | AB25: =H25 | AC25: =L25 | AD25: =P25 | AE25: =T25 | AF25: =X25 | AH25: =AF25-AE25 | AI25: =IFERROR(AH25/ABS(AE25),0)
C26: Goodwill, net | E26: 4075 | F26: 4104 | G26: 4066 | H26: 3287 | I26: 3300 | J26: 3217 | K26: 2753 | L26: 2820 | M26: 2850 | N26: 2751 | O26: 2716 | P26: 2747 | Q26: 2720 | R26: 2719 | S26: 1709 | T26: 1937 | U26: 1954 | V26: 1984 | W26: 2182 | X26: 2222 | Y26: 2201 | Z26: 2234 | AB26: =H26 | AC26: =L26 | AD26: =P26 | AE26: =T26 | AF26: =X26 | AH26: =AF26-AE26 | AI26: =IFERROR(AH26/ABS(AE26),0)
C27: Deferred tax assets | E27: 510 | F27: 491 | G27: 511 | H27: 519 | I27: 528 | J27: 539 | K27: 496 | L27: 582 | M27: 598 | N27: 620 | O27: 701 | P27: 745 | Q27: 749 | R27: 760 | S27: 635 | T27: 615 | U27: 607 | V27: 551 | W27: 101 | X27: 98 | Y27: 96 | Z27: 86 | AB27: =H27 | AC27: =L27 | AD27: =P27 | AE27: =T27 | AF27: =X27 | AH27: =AF27-AE27 | AI27: =IFERROR(AH27/ABS(AE27),0)
C28: Other long-term assets | E28: 1454 | F28: 1496 | G28: 1492 | H28: 1960 | I28: 1951 | J28: 1784 | K28: 1715 | L28: 1323 | M28: 1331 | N28: 1377 | O28: 1355 | P28: 1034 | Q28: 1052 | R28: 1049 | S28: 1063 | T28: 1057 | U28: 1099 | V28: 1148 | W28: 1401 | X28: 1479 | Y28: 1467 | Z28: 1457 | AB28: =H28 | AC28: =L28 | AD28: =P28 | AE28: =T28 | AF28: =X28 | AH28: =AF28-AE28 | AI28: =IFERROR(AH28/ABS(AE28),0)
C29: Total assets | E29: =SUM(E22:E28)+E19 | F29: =SUM(F22:F28)+F19 | G29: =SUM(G22:G28)+G19 | H29: =SUM(H22:H28)+H19 | I29: =SUM(I22:I28)+I19 | J29: =SUM(J22:J28)+J19 | K29: =SUM(K22:K28)+K19 | L29: =SUM(L22:L28)+L19 | ... Z29: =SUM(Z22:Z28)+Z19 | AB29: =SUM(AB22:AB28)+AB19 | AC29: =SUM(AC22:AC28)+AC19 | AD29: =SUM(AD22:AD28)+AD19 | AE29: =SUM(AE22:AE28)+AE19 | AF29: =SUM(AF22:AF28)+AF19 | AH29: =AF29-AE29 | AI29: =IFERROR(AH29/ABS(AE29),0)
C30: Total assets | E30: 14272 | F30: 14110 | G30: 14081 | H30: 13223 | I30: 13082 | J30: 12270 | K30: 11420 | L30: 11543 | M30: 11046 | N30: 10569 | O30: 10444 | P30: 10008 | Q30: 9944 | R30: 9491 | S30: 8322 | T30: 8365 | U30: 8211 | V30: 8874 | W30: 10068 | X30: 9823 | Y30: 9902 | Z30: 9724 | AB30: =H30 | AC30: =L30 | AD30: =P30 | AE30: =T30 | AF30: =X30
C31: Check | E31: =E29-E30 | F31: =F29-F30 | G31: =G29-G30 | H31: =H29-H30 | I31: =I29-I30 | J31: =J29-J30 | K31: =K29-K30 | L31: =L29-L30 | ... Z31: =Z29-Z30 | AB31: =AB29-AB30 | AC31: =AC29-AC30 | AD31: =AD29-AD30 | AE31: =AE29-AE30 | AF31: =AF29-AF30
C33: Liabilities and Equity:
C34: Current liabilities:
C35: Short-term debt and current portion of long-term debt | E35: 678 | F35: 642 | G35: 646 | H35: 650 | I35: 1450 | J35: 1108 | K35: 1070 | L35: 860 | M35: 553 | N35: 891 | O35: 870 | P35: 567 | Q35: 405 | R35: 129 | S35: 519 | T35: 585 | U35: 599 | V35: 458 | W35: 354 | X35: 231 | Y35: 165 | Z35: 70 | AB35: =H35 | AC35: =L35 | AD35: =P35 | AE35: =T35 | AF35: =X35 | AH35: =AF35-AE35 | AI35: =IFERROR(AH35/ABS(AE35),0)
C36: Financing liability, tariff receivables monetization | E36: 0 | F36: 0 | G36: 0 | H36: 0 | I36: 0 | J36: 0 | K36: 0 | L36: 0 | M36: 0 | N36: 0 | O36: 0 | P36: 0 | Q36: 0 | R36: 0 | S36: 0 | T36: 0 | U36: 0 | V36: 0 | W36: 0 | X36: 0 | Y36: 0 | Z36: 90 | AB36: =H36 | AC36: =L36 | AD36: =P36 | AE36: =T36 | AF36: =X36 | AH36: =AF36-AE36 | AI36: =IFERROR(AH36/ABS(AE36),0)
C37: Accounts payable | E37: 932 | F37: 935 | G37: 1032 | H37: 1069 | I37: 1183 | J37: 1207 | K37: 1213 | L37: 1331 | M37: 1301 | N37: 1041 | O37: 1031 | P37: 1044 | Q37: 1046 | R37: 936 | S37: 895 | T37: 1023 | U37: 1120 | V37: 1080 | W37: 1481 | X37: 1498 | Y37: 1548 | Z37: 1456 | AB37: =H37 | AC37: =L37 | AD37: =P37 | AE37: =T37 | AF37: =X37 | AH37: =AF37-AE37 | AI37: =IFERROR(AH37/ABS(AE37),0)
C38: Accrued compensation and benefits costs | E38: 241 | F38: 263 | G38: 262 | H38: 239 | I38: 258 | J38: 233 | K38: 250 | L38: 258 | M38: 243 | N38: 251 | O38: 276 | P38: 306 | Q38: 213 | R38: 205 | S38: 227 | T38: 227 | U38: 199 | V38: 182 | W38: 247 | X38: 235 | Y38: 223 | Z38: 246 | AB38: =H38 | AC38: =L38 | AD38: =P38 | AE38: =T38 | AF38: =X38 | AH38: =AF38-AE38 | AI38: =IFERROR(AH38/ABS(AE38),0)
C39: Accrued expenses and other current liabilities | E39: 794 | F39: 851 | G39: 844 | H39: 871 | I39: 878 | J39: 867 | K39: 810 | L39: 881 | M39: 782 | N39: 766 | O39: 829 | P39: 862 | Q39: 774 | R39: 776 | S39: 752 | T39: 784 | U39: 721 | V39: 706 | W39: 1317 | X39: 1258 | Y39: 1266 | Z39: 1264 | AB39: =H39 | AC39: =L39 | AD39: =P39 | AE39: =T39 | AF39: =X39 | AH39: =AF39-AE39 | AI39: =IFERROR(AH39/ABS(AE39),0)
C40: Total current liabilities | E40: =SUM(E35:E39) | F40: =SUM(F35:F39) | G40: =SUM(G35:G39) | H40: =SUM(H35:H39) | I40: =SUM(I35:I39) | J40: =SUM(J35:J39) | K40: =SUM(K35:K39) | L40: =SUM(L35:L39) | ... Z40: =SUM(Z35:Z39) | AB40: =SUM(AB35:AB39) | AC40: =SUM(AC35:AC39) | AD40: =SUM(AD35:AD39) | AE40: =SUM(AE35:AE39) | AF40: =SUM(AF35:AF39) | AH40: =AF40-AE40 | AI40: =IFERROR(AH40/ABS(AE40),0)
C41: Total current liabilities | E41: 2645 | F41: 2691 | G41: 2784 | H41: 2829 | I41: 3769 | J41: 3415 | K41: 3343 | L41: 3330 | M41: 2879 | N41: 2949 | O41: 3006 | P41: 2779 | Q41: 2438 | R41: 2046 | S41: 2393 | T41: 2619 | U41: 2639 | V41: 2426 | W41: 3399 | X41: 3222 | Y41: 3202 | Z41: 3126 | AB41: =H41 | AC41: =L41 | AD41: =P41 | AE41: =T41 | AF41: =X41
C42: Check | E42: =E40-E41 | F42: =F40-F41 | G42: =G40-G41 | H42: =H40-H41 | I42: =I40-I41 | J42: =J40-J41 | K42: =K40-K41 | L42: =L40-L41 | ... Z42: =Z40-Z41 | AB42: =AB40-AB41 | AC42: =AC40-AC41 | AD42: =AD40-AD41 | AE42: =AE40-AE41 | AF42: =AF40-AF41
C43: Long-term debt | E43: 3674 | F43: 3597 | G43: 3673 | H43: 3596 | I43: 2821 | J43: 2764 | K43: 2676 | L43: 2866 | M43: 2726 | N43: 2225 | O43: 2739 | P43: 2710 | Q43: 3199 | R43: 3174 | S43: 2752 | T43: 2814 | U43: 2699 | V43: 3484 | W43: 4052 | X43: 4016 | Y43: 4281 | Z43: 4153 | AB43: =H43 | AC43: =L43 | AD43: =P43 | AE43: =T43 | AF43: =X43 | AH43: =AF43-AE43 | AI43: =IFERROR(AH43/ABS(AE43),0)
C44: Pension and other benefit liabilities | E44: 1473 | F44: 1436 | G44: 1381 | H44: 1373 | I44: 1359 | J44: 1310 | K44: 1298 | L44: 1175 | M44: 1168 | N44: 1206 | O44: 1131 | P44: 1216 | Q44: 1183 | R44: 1180 | S44: 1126 | T44: 1088 | U44: 1077 | V44: 1083 | W44: 1150 | X44: 1068 | Y44: 1037 | Z44: 1027 | AB44: =H44 | AC44: =L44 | AD44: =P44 | AE44: =T44 | AF44: =X44 | AH44: =AF44-AE44 | AI44: =IFERROR(AH44/ABS(AE44),0)
C45: Post-retirement medical benefits | E45: 339 | F45: 340 | G45: 333 | H45: 277 | I45: 247 | J45: 242 | K45: 209 | L45: 184 | M45: 182 | N45: 179 | O45: 175 | P45: 171 | Q45: 167 | R45: 164 | S45: 166 | T45: 154 | U45: 152 | V45: 153 | W45: 168 | X45: 159 | Y45: 156 | Z45: 148 | AB45: =H45 | AC45: =L45 | AD45: =P45 | AE45: =T45 | AF45: =X45 | AH45: =AF45-AE45 | AI45: =IFERROR(AH45/ABS(AE45),0)
C46: Other long-term liabilities | E46: 498 | F46: 537 | G46: 491 | H46: 481 | I46: 473 | J46: 433 | K46: 416 | L46: 411 | M46: 400 | N46: 394 | O46: 371 | P46: 360 | Q46: 352 | R46: 338 | S46: 354 | T46: 386 | U46: 363 | V46: 377 | W46: 705 | X46: 685 | Y46: 697 | Z46: 716 | AB46: =H46 | AC46: =L46 | AD46: =P46 | AE46: =T46 | AF46: =X46 | AH46: =AF46-AE46 | AI46: =IFERROR(AH46/ABS(AE46),0)
C47: Total liabilities | E47: =SUM(E43:E46)+E40 | F47: =SUM(F43:F46)+F40 | G47: =SUM(G43:G46)+G40 | H47: =SUM(H43:H46)+H40 | I47: =SUM(I43:I46)+I40 | J47: =SUM(J43:J46)+J40 | K47: =SUM(K43:K46)+K40 | L47: =SUM(L43:L46)+L40 | ... Z47: =SUM(Z43:Z46)+Z40 | AB47: =SUM(AB43:AB46)+AB40 | AC47: =SUM(AC43:AC46)+AC40 | AD47: =SUM(AD43:AD46)+AD40 | AE47: =SUM(AE43:AE46)+AE40 | AF47: =SUM(AF43:AF46)+AF40 | AH47: =AF47-AE47 | AI47: =IFERROR(AH47/ABS(AE47),0)
C48: Total liabilities | E48: 8629 | F48: 8601 | G48: 8662 | H48: 8556 | I48: 8669 | J48: 8164 | K48: 7942 | L48: 7966 | M48: 7355 | N48: 6953 | O48: 7422 | P48: 7236 | Q48: 7339 | R48: 6902 | S48: 6791 | T48: 7061 | U48: 6930 | V48: 7523 | W48: 9474 | X48: 9150 | Y48: 9373 | Z48: 9170 | AB48: =H48 | AC48: =L48 | AD48: =P48 | AE48: =T48 | AF48: =X48
C49: Check | E49: =E47-E48 | F49: =F47-F48 | G49: =G47-G48 | H49: =H47-H48 | I49: =I47-I48 | J49: =J47-J48 | K49: =K47-K48 | L49: =L47-L48 | ... Z49: =Z47-Z48 | AB49: =AB47-AB48 | AC49: =AC47-AC48 | AD49: =AD47-AD48 | AE49: =AE47-AE48 | AF49: =AF47-AF48
C51: Temporary equity:
C52: Noncontrolling interests (temporary equity) | E52: 0 | F52: 0 | G52: 10 | H52: 10 | I52: 10 | J52: 10 | K52: 10 | L52: 10 | M52: 10 | N52: 10 | O52: 10 | P52: 10 | Q52: 10 | R52: 10 | S52: 10 | T52: 10 | U52: 10 | V52: 10 | W52: 10 | X52: 10 | Y52: 10 | Z52: 10 | AB52: =H52 | AC52: =L52 | AD52: =P52 | AE52: =T52 | AF52: =X52 | AH52: =AF52-AE52 | AI52: =IFERROR(AH52/ABS(AE52),0)
C53: Convertible preferred stock | E53: 214 | F53: 214 | G53: 214 | H53: 214 | I53: 214 | J53: 214 | K53: 214 | L53: 214 | M53: 214 | N53: 214 | O53: 214 | P53: 214 | Q53: 214 | R53: 214 | S53: 214 | T53: 214 | U53: 214 | V53: 214 | W53: 214 | X53: 214 | Y53: 214 | Z53: 214 | AB53: =H53 | AC53: =L53 | AD53: =P53 | AE53: =T53 | AF53: =X53 | AH53: =AF53-AE53 | AI53: =IFERROR(AH53/ABS(AE53),0)
C54: Shareholders' equity:
C55: Common stock | E55: 199 | F55: 189 | G55: 182 | H55: 168 | I55: 156 | J55: 155 | K55: 156 | L55: 156 | M55: 157 | N55: 157 | O55: 157 | P55: 123 | Q55: 124 | R55: 124 | S55: 124 | T55: 124 | U55: 126 | V55: 126 | W55: 128 | X55: 128 | Y55: 131 | Z55: 131 | AB55: =H55 | AC55: =L55 | AD55: =P55 | AE55: =T55 | AF55: =X55 | AH55: =AF55-AE55 | AI55: =IFERROR(AH55/ABS(AE55),0)
C56: Additional paid-in capital | E56: 2456 | F56: 2214 | G56: 2080 | H56: 1802 | I56: 1560 | J56: 1564 | K56: 1577 | L56: 1588 | M56: 1594 | N56: 1607 | O56: 1619 | P56: 1114 | Q56: 1099 | R56: 1114 | S56: 1123 | T56: 1137 | U56: 1141 | V56: 1154 | W56: 1171 | X56: 1183 | Y56: 1192 | Z56: 1200 | AB56: =H56 | AC56: =L56 | AD56: =P56 | AE56: =T56 | AF56: =X56 | AH56: =AF56-AE56 | AI56: =IFERROR(AH56/ABS(AE56),0)
C57: Treasury stock, at cost | E57: -162 | F57: -159 | G57: -87 | H57: -177 | I57: -32 | J57: 0 | K57: 0 | L57: 0 | M57: 0 | N57: 0 | O57: -553 | P57: 0 | Q57: 0 | R57: 0 | S57: 0 | T57: 0 | U57: 0 | V57: 0 | W57: 0 | X57: 0 | Y57: 0 | Z57: 0 | AB57: =H57 | AC57: =L57 | AD57: =P57 | AE57: =T57 | AF57: =X57 | AH57: =AF57-AE57 | AI57: =IFERROR(AH57/ABS(AE57),0)
C58: Retained earnings | E58: 6267 | F58: 6308 | G58: 6348 | H58: 5631 | I58: 5532 | J58: 5484 | K58: 5057 | L58: 5136 | M58: 5162 | N58: 5057 | O58: 5070 | P58: 4977 | Q58: 4828 | R58: 4810 | S58: 3570 | T58: 3514 | U58: 3403 | V58: 3290 | W58: 2523 | X58: 2444 | Y58: 2320 | Z58: 2326 | AB58: =H58 | AC58: =L58 | AD58: =P58 | AE58: =T58 | AF58: =X58 | AH58: =AF58-AE58 | AI58: =IFERROR(AH58/ABS(AE58),0)
C59: Accumulated other comprehensive loss | E59: -3335 | F59: -3265 | G59: -3335 | H59: -2988 | I59: -3032 | J59: -3330 | K59: -3547 | L59: -3537 | M59: -3454 | N59: -3437 | O59: -3504 | P59: -3676 | Q59: -3673 | R59: -3687 | S59: -3514 | T59: -3699 | U59: -3617 | V59: -3448 | W59: -3457 | X59: -3311 | Y59: -3344 | Z59: -3334 | AB59: =H59 | AC59: =L59 | AD59: =P59 | AE59: =T59 | AF59: =X59 | AH59: =AF59-AE59 | AI59: =IFERROR(AH59/ABS(AE59),0)
C60: Xerox Holdings shareholders' equity | E60: =SUM(E55:E59) | F60: =SUM(F55:F59) | G60: =SUM(G55:G59) | H60: =SUM(H55:H59) | I60: =SUM(I55:I59) | J60: =SUM(J55:J59) | K60: =SUM(K55:K59) | L60: =SUM(L55:L59) | ... Z60: =SUM(Z55:Z59) | AB60: =SUM(AB55:AB59) | AC60: =SUM(AC55:AC59) | AD60: =SUM(AD55:AD59) | AE60: =SUM(AE55:AE59) | AF60: =SUM(AF55:AF59) | AH60: =AF60-AE60 | AI60: =IFERROR(AH60/ABS(AE60),0)
C61: Xerox Holdings shareholders' equity | E61: 5425 | F61: 5287 | G61: 5188 | H61: 4436 | I61: 4184 | J61: 3873 | K61: 3243 | L61: 3343 | M61: 3459 | N61: 3384 | O61: 2789 | P61: 2538 | Q61: 2378 | R61: 2361 | S61: 1303 | T61: 1076 | U61: 1053 | V61: 1122 | W61: 365 | X61: 444 | Y61: 299 | Z61: 323 | AB61: =H61 | AC61: =L61 | AD61: =P61 | AE61: =T61 | AF61: =X61
C62: Check | E62: =E60-E61 | F62: =F60-F61 | G62: =G60-G61 | H62: =H60-H61 | I62: =I60-I61 | J62: =J60-J61 | K62: =K60-K61 | L62: =L60-L61 | ... Z62: =Z60-Z61 | AB62: =AB60-AB61 | AC62: =AC60-AC61 | AD62: =AD60-AD61 | AE62: =AE60-AE61 | AF62: =AF60-AF61
C63: Noncontrolling interests | E63: 4 | F63: 8 | G63: 7 | H63: 7 | I63: 5 | J63: 9 | K63: 11 | L63: 10 | M63: 8 | N63: 8 | O63: 9 | P63: 10 | Q63: 3 | R63: 4 | S63: 4 | T63: 4 | U63: 4 | V63: 5 | W63: 5 | X63: 5 | Y63: 6 | Z63: 7 | AB63: =H63 | AC63: =L63 | AD63: =P63 | AE63: =T63 | AF63: =X63 | AH63: =AF63-AE63 | AI63: =IFERROR(AH63/ABS(AE63),0)
C64: Total equity | E64: =E60+E63 | F64: =F60+F63 | G64: =G60+G63 | H64: =H60+H63 | I64: =I60+I63 | J64: =J60+J63 | K64: =K60+K63 | L64: =L60+L63 | ... Z64: =Z60+Z63 | AB64: =AB60+AB63 | AC64: =AC60+AC63 | AD64: =AD60+AD63 | AE64: =AE60+AE63 | AF64: =AF60+AF63 | AH64: =AF64-AE64 | AI64: =IFERROR(AH64/ABS(AE64),0)
C65: Total equity | E65: 5429 | F65: 5295 | G65: 5195 | H65: 4443 | I65: 4189 | J65: 3882 | K65: 3254 | L65: 3353 | M65: 3467 | N65: 3392 | O65: 2798 | P65: 2548 | Q65: 2381 | R65: 2365 | S65: 1307 | T65: 1080 | U65: 1057 | V65: 1127 | W65: 370 | X65: 449 | Y65: 305 | Z65: 330 | AB65: =H65 | AC65: =L65 | AD65: =P65 | AE65: =T65 | AF65: =X65
C66: Check | E66: =E64-E65 | F66: =F64-F65 | G66: =G64-G65 | H66: =H64-H65 | I66: =I64-I65 | J66: =J64-J65 | K66: =K64-K65 | L66: =L64-L65 | ... Z66: =Z64-Z65 | AB66: =AB64-AB65 | AC66: =AC64-AC65 | AD66: =AD64-AD65 | AE66: =AE64-AE65 | AF66: =AF64-AF65
C67: Total liabilities and equity | E67: =E47+E52+E53+E64 | F67: =F47+F52+F53+F64 | G67: =G47+G52+G53+G64 | H67: =H47+H52+H53+H64 | I67: =I47+I52+I53+I64 | J67: =J47+J52+J53+J64 | K67: =K47+K52+K53+K64 | L67: =L47+L52+L53+L64 | ... Z67: =Z47+Z52+Z53+Z64 | AB67: =AB47+AB52+AB53+AB64 | AC67: =AC47+AC52+AC53+AC64 | AD67: =AD47+AD52+AD53+AD64 | AE67: =AE47+AE52+AE53+AE64 | AF67: =AF47+AF52+AF53+AF64 | AH67: =AF67-AE67 | AI67: =IFERROR(AH67/ABS(AE67),0)
C68: Total liabilities and equity | E68: 14272 | F68: 14110 | G68: 14081 | H68: 13223 | I68: 13082 | J68: 12270 | K68: 11420 | L68: 11543 | M68: 11046 | N68: 10569 | O68: 10444 | P68: 10008 | Q68: 9944 | R68: 9491 | S68: 8322 | T68: 8365 | U68: 8211 | V68: 8874 | W68: 10068 | X68: 9823 | Y68: 9902 | Z68: 9724
C69: Check | E69: =E67-E68 | F69: =F67-F68 | G69: =G67-G68 | H69: =H67-H68 | I69: =I67-I68 | J69: =J67-J68 | K69: =K67-K68 | L69: =L67-L68 | ... Z69: =Z67-Z68
C70: A=L+SE Check | E70: =E29-E67 | F70: =F29-F67 | G70: =G29-G67 | H70: =H29-H67 | I70: =I29-I67 | J70: =J29-J67 | K70: =K29-K67 | L70: =L29-L67 | ... Z70: =Z29-Z67 | AB70: =AB29-AB67 | AC70: =AC29-AC67 | AD70: =AD29-AD67 | AE70: =AE29-AE67 | AF70: =AF29-AF67
C73: Memo
C74: Total debt | E74: =E35+E43 | F74: =F35+F43 | G74: =G35+G43 | H74: =H35+H43 | I74: =I35+I43 | J74: =J35+J43 | K74: =K35+K43 | L74: =L35+L43 | ... Z74: =Z35+Z43 | AB74: =AB35+AB43 | AC74: =AC35+AC43 | AD74: =AD35+AD43 | AE74: =AE35+AE43 | AF74: =AF35+AF43 | AH74: =AF74-AE74 | AI74: =IFERROR(AH74/ABS(AE74),0)
C75: Net debt | E75: =E74-E13 | F75: =F74-F13 | G75: =G74-G13 | H75: =H74-H13 | I75: =I74-I13 | J75: =J74-J13 | K75: =K74-K13 | L75: =L74-L13 | ... Z75: =Z74-Z13 | AB75: =AB74-AB13 | AC75: =AC74-AC13 | AD75: =AD74-AD13 | AE75: =AE74-AE13 | AF75: =AF74-AF13 | AH75: =AF75-AE75 | AI75: =IFERROR(AH75/ABS(AE75),0)
C76: Cash, cash equivalents and restricted cash | E76: ='Cash Flow Statement'!E74 | F76: ='Cash Flow Statement'!F74 | G76: ='Cash Flow Statement'!G74 | H76: ='Cash Flow Statement'!H74 | I76: ='Cash Flow Statement'!I74 | J76: ='Cash Flow Statement'!J74 | K76: ='Cash Flow Statement'!K74 | L76: ='Cash Flow Statement'!L74 | ... Z76: ='Cash Flow Statement'!Z74 | AB76: ='Cash Flow Statement'!AB74 | AC76: ='Cash Flow Statement'!AC74 | AD76: ='Cash Flow Statement'!AD74 | AE76: ='Cash Flow Statement'!AE74 | AF76: ='Cash Flow Statement'!AF74 | AH76: =AF76-AE76 | AI76: =IFERROR(AH76/ABS(AE76),0)
C77: Restricted cash | E77: =E76-E13 | F77: =F76-F13 | G77: =G76-G13 | H77: =H76-H13 | I77: =I76-I13 | J77: =J76-J13 | K77: =K76-K13 | L77: =L76-L13 | ... Z77: =Z76-Z13 | AB77: =AB76-AB13 | AC77: =AC76-AC13 | AD77: =AD76-AD13 | AE77: =AE76-AE13 | AF77: =AF76-AF13 | AH77: =AF77-AE77 | AI77: =IFERROR(AH77/ABS(AE77),0)
C78: Total finance receivables | E78: =E15+E16+E22 | F78: =F15+F16+F22 | G78: =G15+G16+G22 | H78: =H15+H16+H22 | I78: =I15+I16+I22 | J78: =J15+J16+J22 | K78: =K15+K16+K22 | L78: =L15+L16+L22 | ... Z78: =Z15+Z16+Z22 | AB78: =AB15+AB16+AB22 | AC78: =AC15+AC16+AC22 | AD78: =AD15+AD16+AD22 | AE78: =AE15+AE16+AE22 | AF78: =AF15+AF16+AF22 | AH78: =AF78-AE78 | AI78: =IFERROR(AH78/ABS(AE78),0)
A79: x | B79: x | C79: Net working capital | E79: =E14+E17+E18-E37-E38-E39 | F79: =F14+F17+F18-F37-F38-F39 | G79: =G14+G17+G18-G37-G38-G39 | H79: =H14+H17+H18-H37-H38-H39 | I79: =I14+I17+I18-I37-I38-I39 | J79: =J14+J17+J18-J37-J38-J39 | K79: =K14+K17+K18-K37-K38-K39 | L79: =L14+L17+L18-L37-L38-L39 | ... Z79: =Z14+Z17+Z18-Z37-Z38-Z39 | AB79: =AB14+AB17+AB18-AB37-AB38-AB39 | AC79: =AC14+AC17+AC18-AC37-AC38-AC39 | AD79: =AD14+AD17+AD18-AD37-AD38-AD39 | AE79: =AE14+AE17+AE18-AE37-AE38-AE39 | AF79: =AF14+AF17+AF18-AF37-AF38-AF39 | AH79: =AF79-AE79 | AI79: =IFERROR(AH79/ABS(AE79),0)
A80: End

Sheet Cash Flow Statement
A1: =C3 | B1: ='Cover Page'!A1
C3: Statement of Cash Flows | AI3: Xerox Holdings Corporation
C4: All values in $ millions (USD)
E7: 1 | F7: 2 | G7: 3 | H7: 4 | I7: 1 | J7: 2 | K7: 3 | L7: 4 | M7: 1 | N7: 2 | O7: 3 | P7: 4 | Q7: 1 | R7: 2 | S7: 3 | T7: 4 | U7: 1 | V7: 2 | W7: 3 | X7: 4 | Y7: 1 | Z7: 2
E8: 2021 | F8: 2021 | G8: 2021 | H8: 2021 | I8: 2022 | J8: 2022 | K8: 2022 | L8: 2022 | M8: 2023 | N8: 2023 | O8: 2023 | P8: 2023 | Q8: 2024 | R8: 2024 | S8: 2024 | T8: 2024 | U8: 2025 | V8: 2025 | W8: 2025 | X8: 2025 | Y8: 2026 | Z8: 2026 | AB8: 2021 | AC8: 2022 | AD8: 2023 | AE8: 2024 | AF8: 2025
E9: 44286 | F9: 44377 | G9: 44469 | H9: 44561 | I9: 44651 | J9: 44742 | K9: 44834 | L9: 44926 | M9: 45016 | N9: 45107 | O9: 45199 | P9: 45291 | Q9: 45382 | R9: 45473 | S9: 45565 | T9: 45657 | U9: 45747 | V9: 45838 | W9: 45930 | X9: 46022 | Y9: 46112 | Z9: 46203 | AB9: 44561 | AC9: 44926 | AD9: 45291 | AE9: 45657 | AF9: 46022
A10: x | B10: x | C10: Cash Flow Statement | E10: Quarter Ended | AB10: Fiscal Year Ended December 31, | AH10: LTM
E11: =E7&"Q'"&RIGHT(E8,2) | F11: =F7&"Q'"&RIGHT(F8,2) | G11: =G7&"Q'"&RIGHT(G8,2) | H11: =H7&"Q'"&RIGHT(H8,2) | I11: =I7&"Q'"&RIGHT(I8,2) | J11: =J7&"Q'"&RIGHT(J8,2) | K11: =K7&"Q'"&RIGHT(K8,2) | L11: =L7&"Q'"&RIGHT(L8,2) | ... Z11: =Z7&"Q'"&RIGHT(Z8,2) | AB11: 2021 | AC11: 2022 | AD11: 2023 | AE11: 2024 | AF11: 2025 | AH11: LTM 2Q'25 | AI11: LTM 2Q'26
C13: Operating Activities:
C14: Net (loss) income | E14: ='Income Statement'!D32 | F14: ='Income Statement'!E32 | G14: ='Income Statement'!F32 | H14: ='Income Statement'!G32 | I14: ='Income Statement'!H32 | J14: ='Income Statement'!I32 | K14: ='Income Statement'!J32 | L14: ='Income Statement'!K32 | ... Z14: ='Income Statement'!Y32 | AB14: ='Income Statement'!AA32 | AC14: ='Income Statement'!AB32 | AD14: ='Income Statement'!AC32 | AE14: ='Income Statement'!AD32 | AF14: ='Income Statement'!AE32 | AH14: =SUM(S14:V14) | AI14: =SUM(W14:Z14)
C15: Adjustments required to reconcile net (loss) income to cash flows from operating activities:
C16: Depreciation and amortization | E16: 86 | F16: =170-E16 | G16: =249-SUM(E16:F16) | H16: =AB16-SUM(E16:G16) | I16: 72 | J16: =140-I16 | K16: =205-SUM(I16:J16) | L16: =AC16-SUM(I16:K16) | M16: 64 | N16: =126-M16 | O16: =189-SUM(M16:N16) | P16: =AD16-SUM(M16:O16) | Q16: 59 | R16: =118-Q16 | S16: =177-SUM(Q16:R16) | T16: =AE16-SUM(Q16:S16) | U16: 60 | V16: =117-U16 | W16: =224-SUM(U16:V16) | X16: =AF16-SUM(U16:W16) | Y16: 100 | Z16: =201-Y16 | AB16: 327 | AC16: 270 | AD16: 251 | AE16: 274 | AF16: 331 | AH16: =SUM(S16:V16) | AI16: =SUM(W16:Z16)
C17: Provisions | E17: 20 | F17: =34-E17 | G17: =38-SUM(E17:F17) | H17: =AB17-SUM(E17:G17) | I17: 19 | J17: =35-I17 | K17: =48-SUM(I17:J17) | L17: =AC17-SUM(I17:K17) | M17: 0 | N17: =21-M17 | O17: =37-SUM(M17:N17) | P17: =AD17-SUM(M17:O17) | Q17: 57 | R17: =79-Q17 | S17: =92-SUM(Q17:R17) | T17: =AE17-SUM(Q17:S17) | U17: 18 | V17: =48-U17 | W17: =67-SUM(U17:V17) | X17: =AF17-SUM(U17:W17) | Y17: 18 | Z17: =36-Y17 | AB17: 46 | AC17: 65 | AD17: 54 | AE17: 110 | AF17: 85 | AH17: =SUM(S17:V17) | AI17: =SUM(W17:Z17)
C18: Net (gain) loss on early extinguishment of debt | Y18: -56 | Z18: =-95-Y18 | AH18: =SUM(S18:V18) | AI18: =SUM(W18:Z18)
C19: Net (gain) loss on sales of businesses and assets | E19: 0 | F19: =-1-E19 | G19: =-40-SUM(E19:F19) | H19: =AB19-SUM(E19:G19) | I19: 0 | J19: =-1-I19 | K19: =-17-SUM(I19:J19) | L19: =AC19-SUM(I19:K19) | M19: 0 | N19: =-2-M19 | O19: =-37-SUM(M19:N19) | P19: =AD19-SUM(M19:O19) | Q19: 0 | R19: =-1-Q19 | S19: =-3-SUM(Q19:R19) | T19: =AE19-SUM(Q19:S19) | U19: -3 | V19: =-5-U19 | W19: =-6-SUM(U19:V19) | X19: =AF19-SUM(U19:W19) | Y19: 2 | Z19: =2-Y19 | AB19: -40 | AC19: -56 | AD19: -39 | AE19: -8 | AF19: -5 | AH19: =SUM(S19:V19) | AI19: =SUM(W19:Z19)
C20: Inventory-related purchase accounting adjustment, noncash (Lexmark) | U20: 0 | V20: =0-U20 | W20: =102-SUM(U20:V20) | X20: =AF20-SUM(U20:W20) | AF20: 102 | AH20: =SUM(S20:V20) | AI20: =SUM(W20:Z20)
C21: Effective settlement of pre-existing relationship between Lexmark and Xerox | U21: 0 | V21: =0-U21 | W21: =-43-SUM(U21:V21) | X21: =AF21-SUM(U21:W21) | AF21: -43 | AH21: =SUM(S21:V21) | AI21: =SUM(W21:Z21)
C22: Divestitures | E22: ='Income Statement'!D24 | F22: ='Income Statement'!E24 | G22: ='Income Statement'!F24 | H22: ='Income Statement'!G24 | I22: ='Income Statement'!H24 | J22: ='Income Statement'!I24 | K22: ='Income Statement'!J24 | L22: ='Income Statement'!K24 | ... Z22: ='Income Statement'!Y24 | AB22: ='Income Statement'!AA24 | AC22: ='Income Statement'!AB24 | AD22: ='Income Statement'!AC24 | AE22: ='Income Statement'!AD24 | AF22: ='Income Statement'!AE24 | AH22: =SUM(S22:V22) | AI22: =SUM(W22:Z22)
C23: PARC donation | E23: ='Income Statement'!D25 | F23: ='Income Statement'!E25 | G23: ='Income Statement'!F25 | H23: ='Income Statement'!G25 | I23: ='Income Statement'!H25 | J23: ='Income Statement'!I25 | K23: ='Income Statement'!J25 | L23: ='Income Statement'!K25 | ... Z23: ='Income Statement'!Y25 | AB23: ='Income Statement'!AA25 | AC23: ='Income Statement'!AB25 | AD23: ='Income Statement'!AC25 | AE23: ='Income Statement'!AD25 | AF23: ='Income Statement'!AE25 | AH23: =SUM(S23:V23) | AI23: =SUM(W23:Z23)
C24: Goodwill impairment | E24: ='Income Statement'!D21 | F24: ='Income Statement'!E21 | G24: ='Income Statement'!F21 | H24: ='Income Statement'!G21 | I24: ='Income Statement'!H21 | J24: ='Income Statement'!I21 | K24: ='Income Statement'!J21 | L24: ='Income Statement'!K21 | ... Z24: ='Income Statement'!Y21 | AB24: ='Income Statement'!AA21 | AC24: ='Income Statement'!AB21 | AD24: ='Income Statement'!AC21 | AE24: ='Income Statement'!AD21 | AF24: ='Income Statement'!AE21 | AH24: =SUM(S24:V24) | AI24: =SUM(W24:Z24)
C25: Stock-based compensation | E25: 16 | F25: =30-E25 | G25: =44-SUM(E25:F25) | H25: =AB25-SUM(E25:G25) | I25: 15 | J25: =50-I25 | K25: =63-SUM(I25:J25) | L25: =AC25-SUM(I25:K25) | M25: 14 | N25: =28-M25 | O25: =40-SUM(M25:N25) | P25: =AD25-SUM(M25:O25) | Q25: 12 | R25: =29-Q25 | S25: =38-SUM(Q25:R25) | T25: =AE25-SUM(Q25:S25) | U25: 12 | V25: =26-U25 | W25: =33-SUM(U25:V25) | X25: =AF25-SUM(U25:W25) | Y25: 9 | Z25: =18-Y25 | AB25: 54 | AC25: 75 | AD25: 54 | AE25: 52 | AF25: 45 | AH25: =SUM(S25:V25) | AI25: =SUM(W25:Z25)
C26: Restructuring and asset impairment charges | E26: 21 | F26: =25-E26 | G26: =28-SUM(E26:F26) | H26: =AB26-SUM(E26:G26) | I26: 20 | J26: =22-I26 | K26: =44-SUM(I26:J26) | L26: =AC26-SUM(I26:K26) | M26: 1 | N26: =14-M26 | O26: =25-SUM(M26:N26) | P26: =AD26-SUM(M26:O26) | Q26: 31 | R26: =34-Q26 | S26: =80-SUM(Q26:R26) | T26: =AE26-SUM(Q26:S26) | U26: -1 | V26: =10-U26 | W26: =69-SUM(U26:V26) | X26: =AF26-SUM(U26:W26) | Y26: 44 | Z26: =65-Y26 | AB26: 27 | AC26: 62 | AD26: 146 | AE26: 87 | AF26: 67 | AH26: =SUM(S26:V26) | AI26: =SUM(W26:Z26)
C27: Payments for restructurings | E27: -27 | F27: =-49-E27 | G27: =-61-SUM(E27:F27) | H27: =AB27-SUM(E27:G27) | I27: -7 | J27: =-21-I27 | K27: =-38-SUM(I27:J27) | L27: =AC27-SUM(I27:K27) | M27: -6 | N27: =-14-M27 | O27: =-23-SUM(M27:N27) | P27: =AD27-SUM(M27:O27) | Q27: -16 | R27: =-47-Q27 | S27: =-58-SUM(Q27:R27) | T27: =AE27-SUM(Q27:S27) | U27: -18 | V27: =-33-U27 | W27: =-41-SUM(U27:V27) | X27: =AF27-SUM(U27:W27) | Y27: -21 | Z27: =-40-Y27 | AB27: -72 | AC27: -52 | AD27: -27 | AE27: -78 | AF27: -69 | AH27: =SUM(S27:V27) | AI27: =SUM(W27:Z27)
C28: Non-service retirement-related costs | E28: 0 | F28: =-2-E28 | G28: =-5-SUM(E28:F28) | H28: =AB28-SUM(E28:G28) | I28: -7 | J28: =-11-I28 | K28: =-18-SUM(I28:J28) | L28: =AC28-SUM(I28:K28) | M28: -1 | N28: =10-M28 | O28: =14-SUM(M28:N28) | P28: =AD28-SUM(M28:O28) | Q28: 23 | R28: =49-Q28 | S28: =74-SUM(Q28:R28) | T28: =AE28-SUM(Q28:S28) | U28: 18 | V28: =37-U28 | W28: =57-SUM(U28:V28) | X28: =AF28-SUM(U28:W28) | Y28: 21 | Z28: =42-Y28 | AB28: -10 | AC28: -12 | AD28: 19 | AE28: 80 | AF28: 78 | AH28: =SUM(S28:V28) | AI28: =SUM(W28:Z28)
C29: Contributions to retirement plans | E29: -35 | F29: =-69-E29 | G29: =-102-SUM(E29:F29) | H29: =AB29-SUM(E29:G29) | I29: -38 | J29: =-72-I29 | K29: =-106-SUM(I29:J29) | L29: =AC29-SUM(I29:K29) | M29: -17 | N29: =-32-M29 | O29: =-75-SUM(M29:N29) | P29: =AD29-SUM(M29:O29) | Q29: -31 | R29: =-58-Q29 | S29: =-114-SUM(Q29:R29) | T29: =AE29-SUM(Q29:S29) | U29: -34 | V29: =-67-U29 | W29: =-123-SUM(U29:V29) | X29: =AF29-SUM(U29:W29) | Y29: -36 | Z29: =-72-Y29 | AB29: -135 | AC29: -124 | AD29: -102 | AE29: -145 | AF29: -161 | AH29: =SUM(S29:V29) | AI29: =SUM(W29:Z29)
C30: Changes in operating assets and liabilities:
C31: (Increase) decrease in accounts receivable and billed portion of finance receivables | E31: 92 | F31: =37-E31 | G31: =-30-SUM(E31:F31) | H31: =AB31-SUM(E31:G31) | I31: 13 | J31: =-49-I31 | K31: =-48-SUM(I31:J31) | L31: =AC31-SUM(I31:K31) | M31: 39 | N31: =-36-M31 | O31: =-47-SUM(M31:N31) | P31: =AD31-SUM(M31:O31) | Q31: -19 | R31: =-32-Q31 | S31: =18-SUM(Q31:R31) | T31: =AE31-SUM(Q31:S31) | U31: -12 | V31: =-44-U31 | W31: =-41-SUM(U31:V31) | X31: =AF31-SUM(U31:W31) | Y31: -106 | Z31: =-86-Y31 | AB31: 41 | AC31: -48 | AD31: -5 | AE31: 71 | AF31: -36 | AH31: =SUM(S31:V31) | AI31: =SUM(W31:Z31)
C32: (Increase) decrease in inventories | E32: -18 | F32: =4-E32 | G32: =10-SUM(E32:F32) | H32: =AB32-SUM(E32:G32) | I32: -31 | J32: =-95-I32 | K32: =-136-SUM(I32:J32) | L32: =AC32-SUM(I32:K32) | M32: -64 | N32: =12-M32 | O32: =50-SUM(M32:N32) | P32: =AD32-SUM(M32:O32) | Q32: -133 | R32: =-148-Q32 | S32: =-136-SUM(Q32:R32) | T32: =AE32-SUM(Q32:S32) | U32: -137 | V32: =-160-U32 | W32: =-123-SUM(U32:V32) | X32: =AF32-SUM(U32:W32) | Y32: -49 | Z32: =-60-Y32 | AB32: 88 | AC32: -143 | AD32: 123 | AE32: -122 | AF32: -12 | AH32: =SUM(S32:V32) | AI32: =SUM(W32:Z32)
C33: Increase in equipment on operating leases | E33: -28 | F33: =-63-E33 | G33: =-92-SUM(E33:F33) | H33: =AB33-SUM(E33:G33) | I33: -36 | J33: =-47-I33 | K33: =-74-SUM(I33:J33) | L33: =AC33-SUM(I33:K33) | M33: -40 | N33: =-77-M33 | O33: =-109-SUM(M33:N33) | P33: =AD33-SUM(M33:O33) | Q33: -22 | R33: =-50-Q33 | S33: =-78-SUM(Q33:R33) | T33: =AE33-SUM(Q33:S33) | U33: -30 | V33: =-52-U33 | W33: =-88-SUM(U33:V33) | X33: =AF33-SUM(U33:W33) | Y33: -32 | Z33: =-67-Y33 | AB33: -129 | AC33: -112 | AD33: -141 | AE33: -107 | AF33: -126 | AH33: =SUM(S33:V33) | AI33: =SUM(W33:Z33)
C34: Decrease (increase) in finance receivables | E34: 37 | F34: =12-E34 | G34: =33-SUM(E34:F34) | H34: =AB34-SUM(E34:G34) | I34: 41 | J34: =17-I34 | K34: =-10-SUM(I34:J34) | L34: =AC34-SUM(I34:K34) | M34: 160 | N34: =407-M34 | O34: =490-SUM(M34:N34) | P34: =AD34-SUM(M34:O34) | Q34: 210 | R34: =399-Q34 | S34: =496-SUM(Q34:R34) | T34: =AE34-SUM(Q34:S34) | U34: 128 | V34: =212-U34 | W34: =338-SUM(U34:V34) | X34: =AF34-SUM(U34:W34) | Y34: 66 | Z34: =157-Y34 | AB34: 20 | AC34: -141 | AD34: 614 | AE34: 663 | AF34: 489 | AH34: =SUM(S34:V34) | AI34: =SUM(W34:Z34)
C35: (Increase) decrease in other current and long-term assets | E35: 18 | F35: =66-E35 | G35: =64-SUM(E35:F35) | H35: =AB35-SUM(E35:G35) | I35: -1 | J35: =35-I35 | K35: =36-SUM(I35:J35) | L35: =AC35-SUM(I35:K35) | M35: 3 | N35: =15-M35 | O35: =-8-SUM(M35:N35) | P35: =AD35-SUM(M35:O35) | Q35: -2 | R35: =14-Q35 | S35: =16-SUM(Q35:R35) | T35: =AE35-SUM(Q35:S35) | U35: -16 | V35: =16-U35 | W35: =4-SUM(U35:V35) | X35: =AF35-SUM(U35:W35) | Y35: -38 | Z35: =-120-Y35 | AB35: 68 | AC35: 27 | AD35: 16 | AE35: -14 | AF35: 9 | AH35: =SUM(S35:V35) | AI35: =SUM(W35:Z35)
C36: Increase (decrease) in accounts payable | E36: -31 | F36: =-33-E36 | G36: =74-SUM(E36:F36) | H36: =AB36-SUM(E36:G36) | I36: 111 | J36: =172-I36 | K36: =198-SUM(I36:J36) | L36: =AC36-SUM(I36:K36) | M36: -41 | N36: =-290-M36 | O36: =-290-SUM(M36:N36) | P36: =AD36-SUM(M36:O36) | Q36: 17 | R36: =-88-Q36 | S36: =-143-SUM(Q36:R36) | T36: =AE36-SUM(Q36:S36) | U36: 89 | V36: =25-U36 | W36: =4-SUM(U36:V36) | X36: =AF36-SUM(U36:W36) | Y36: 58 | Z36: =-30-Y36 | AB36: 118 | AC36: 278 | AD36: -290 | AE36: -48 | AF36: 24 | AH36: =SUM(S36:V36) | AI36: =SUM(W36:Z36)
C37: Increase (decrease) in accrued compensation | E37: -36 | F37: =-35-E37 | G37: =-56-SUM(E37:F37) | H37: =AB37-SUM(E37:G37) | I37: 22 | J37: =7-I37 | K37: =29-SUM(I37:J37) | L37: =AC37-SUM(I37:K37) | M37: -16 | N37: =-7-M37 | O37: =16-SUM(M37:N37) | P37: =AD37-SUM(M37:O37) | Q37: -86 | R37: =-93-Q37 | S37: =-78-SUM(Q37:R37) | T37: =AE37-SUM(Q37:S37) | U37: -30 | V37: =-51-U37 | W37: =-39-SUM(U37:V37) | X37: =AF37-SUM(U37:W37) | Y37: -8 | Z37: =18-Y37 | AB37: -95 | AC37: 34 | AD37: 48 | AE37: -78 | AF37: -53 | AH37: =SUM(S37:V37) | AI37: =SUM(W37:Z37)
C38: Increase (decrease) in other current and long-term liabilities | E38: -35 | F38: =92-E38 | G38: =80-SUM(E38:F38) | H38: =AB38-SUM(E38:G38) | I38: -43 | J38: =-48-I38 | K38: =-73-SUM(I38:J38) | L38: =AC38-SUM(I38:K38) | M38: -128 | N38: =-139-M38 | O38: =-159-SUM(M38:N38) | P38: =AD38-SUM(M38:O38) | Q38: -77 | R38: =-52-Q38 | S38: =-83-SUM(Q38:R38) | T38: =AE38-SUM(Q38:S38) | U38: -48 | V38: =-40-U38 | W38: =58-SUM(U38:V38) | X38: =AF38-SUM(U38:W38) | Y38: -9 | Z38: =6-Y38 | AB38: 89 | AC38: 9 | AD38: -114 | AE38: -47 | AF38: 33 | AH38: =SUM(S38:V38) | AI38: =SUM(W38:Z38)
C39: Net change in income tax assets and liabilities (incl. deferred taxes) | E39: 6 | F39: =2-E39 | G39: =-11-SUM(E39:F39) | H39: =AB39-SUM(E39:G39) | I39: -39 | J39: =-76-I39 | K39: =-81-SUM(I39:J39) | L39: =AC39-SUM(I39:K39) | M39: 18 | N39: =-17-M39 | O39: =-24-SUM(M39:N39) | P39: =AD39-SUM(M39:O39) | Q39: -44 | R39: =-64-Q39 | S39: =44-SUM(Q39:R39) | T39: =AE39-SUM(Q39:S39) | U39: -2 | V39: =35-U39 | W39: =479-SUM(U39:V39) | X39: =AF39-SUM(U39:W39) | Y39: 12 | Z39: =6-Y39 | AB39: =10-89 | AC39: =-27-27 | AD39: =-12-68 | AE39: =-50+90 | AF39: =-26+502 | AH39: =SUM(S39:V39) | AI39: =SUM(W39:Z39)
C40: Net change in derivative assets and liabilities | E40: 3 | F40: =-2-E40 | G40: =-1-SUM(E40:F40) | H40: =AB40-SUM(E40:G40) | I40: 7 | J40: =-6-I40 | K40: =-10-SUM(I40:J40) | L40: =AC40-SUM(I40:K40) | M40: 13 | N40: =22-M40 | O40: =16-SUM(M40:N40) | P40: =AD40-SUM(M40:O40) | Q40: 6 | R40: =6-Q40 | S40: =9-SUM(Q40:R40) | T40: =AE40-SUM(Q40:S40) | U40: 0 | V40: =-2-U40 | W40: =-1-SUM(U40:V40) | X40: =AF40-SUM(U40:W40) | AB40: 2 | AC40: -22 | AD40: 13 | AE40: 10 | AF40: -12 | AH40: =SUM(S40:V40) | AI40: =SUM(W40:Z40)
C41: Other operating, net | E41: -11 | F41: =-17-E41 | G41: =-10-SUM(E41:F41) | H41: =AB41-SUM(E41:G41) | I41: 5 | J41: =-9-I41 | K41: =-7-SUM(I41:J41) | L41: =AC41-SUM(I41:K41) | M41: 8 | N41: =-11-M41 | O41: =0-SUM(M41:N41) | P41: =AD41-SUM(M41:O41) | Q41: -5 | R41: =-7-Q41 | S41: =0-SUM(Q41:R41) | T41: =AE41-SUM(Q41:S41) | U41: 11 | V41: =28-U41 | W41: =46-SUM(U41:V41) | X41: =AF41-SUM(U41:W41) | Y41: -14 | Z41: =4-Y41 | AB41: -17 | AC41: 13 | AD41: 13 | AE41: -13 | AF41: 35 | AH41: =SUM(S41:V41) | AI41: =SUM(W41:Z41)
C42: Net cash provided by (used in) operating activities | E42: =SUM(E14:E41) | F42: =SUM(F14:F41) | G42: =SUM(G14:G41) | H42: =SUM(H14:H41) | I42: =SUM(I14:I41) | J42: =SUM(J14:J41) | K42: =SUM(K14:K41) | L42: =SUM(L14:L41) | ... Z42: =SUM(Z14:Z41) | AB42: =SUM(AB14:AB41) | AC42: =SUM(AC14:AC41) | AD42: =SUM(AD14:AD41) | AE42: =SUM(AE14:AE41) | AF42: =SUM(AF14:AF41) | AH42: =SUM(AH14:AH41) | AI42: =SUM(AI14:AI41)
C43: Net cash provided by (used in) operating activities | E43: 117 | F43: =331-117 | G43: =431-331 | H43: =629-431 | I43: 66 | J43: =-19-66 | K43: =-27-(-19) | L43: =159-(-27) | M43: 78 | N43: =173-78 | O43: =297-173 | P43: =686-297 | Q43: -79 | R43: =44-(-79) | S43: =160-44 | T43: =511-160 | U43: -89 | V43: =-100-(-89) | W43: =16-(-100) | X43: =224-16 | Y43: -144 | Z43: =-107-(-144) | AB43: 629 | AC43: 159 | AD43: 686 | AE43: 511 | AF43: 224 | AH43: =SUM(S43:V43) | AI43: =SUM(W43:Z43)
C44: Check | E44: =E42-E43 | F44: =F42-F43 | G44: =G42-G43 | H44: =H42-H43 | I44: =I42-I43 | J44: =J42-J43 | K44: =K42-K43 | L44: =L42-L43 | ... Z44: =Z42-Z43 | AB44: =AB42-AB43 | AC44: =AC42-AC43 | AD44: =AD42-AD43 | AE44: =AE42-AE43 | AF44: =AF42-AF43
C46: Memo: Change in NWC | E46: =E31+E32+SUM(E35:E40) | F46: =F31+F32+SUM(F35:F40) | G46: =G31+G32+SUM(G35:G40) | H46: =H31+H32+SUM(H35:H40) | I46: =I31+I32+SUM(I35:I40) | J46: =J31+J32+SUM(J35:J40) | K46: =K31+K32+SUM(K35:K40) | L46: =L31+L32+SUM(L35:L40) | ... Z46: =Z31+Z32+SUM(Z35:Z40) | AB46: =AB31+AB32+SUM(AB35:AB40) | AC46: =AC31+AC32+SUM(AC35:AC40) | AD46: =AD31+AD32+SUM(AD35:AD40) | AE46: =AE31+AE32+SUM(AE35:AE40) | AF46: =AF31+AF32+SUM(AF35:AF40) | AH46: =AH31+AH32+SUM(AH35:AH40) | AI46: =AI31+AI32+SUM(AI35:AI40)
C48: Investing Activities:
C49: Cost of additions to land, buildings, equipment and software | E49: -17 | F49: =-33-E49 | G49: =-52-SUM(E49:F49) | H49: =AB49-SUM(E49:G49) | I49: -16 | J49: =-29-I49 | K49: =-39-SUM(I49:J49) | L49: =AC49-SUM(I49:K49) | M49: -8 | N49: =-15-M49 | O49: =-27-SUM(M49:N49) | P49: =AD49-SUM(M49:O49) | Q49: -10 | R49: =-18-Q49 | S49: =-27-SUM(Q49:R49) | T49: =AE49-SUM(Q49:S49) | U49: -20 | V49: =-39-U49 | W49: =-67-SUM(U49:V49) | X49: =AF49-SUM(U49:W49) | Y49: -21 | Z49: =-47-Y49 | AB49: -68 | AC49: -57 | AD49: -37 | AE49: -44 | AF49: -91 | AH49: =SUM(S49:V49) | AI49: =SUM(W49:Z49)
C50: Proceeds from sales of businesses and assets | E50: 0 | F50: =1-E50 | G50: =39-SUM(E50:F50) | H50: =AB50-SUM(E50:G50) | I50: 0 | J50: =26-I50 | K50: =49-SUM(I50:J50) | L50: =AC50-SUM(I50:K50) | M50: 1 | N50: =3-M50 | O50: =40-SUM(M50:N50) | P50: =AD50-SUM(M50:O50) | Q50: 4 | R50: =19-Q50 | S50: =27-SUM(Q50:R50) | T50: =AE50-SUM(Q50:S50) | U50: 27 | V50: =30-U50 | W50: =56-SUM(U50:V50) | X50: =AF50-SUM(U50:W50) | Y50: 2 | Z50: =8-Y50 | AB50: 44 | AC50: 87 | AD50: 43 | AE50: 35 | AF50: 79 | AH50: =SUM(S50:V50) | AI50: =SUM(W50:Z50)
C51: Acquisitions, net of cash acquired | E51: 0 | F51: =-37-E51 | G51: =-38-SUM(E51:F51) | H51: =AB51-SUM(E51:G51) | I51: -54 | J51: =-52-I51 | K51: =-93-SUM(I51:J51) | L51: =AC51-SUM(I51:K51) | M51: -7 | N51: =-7-M51 | O51: =-7-SUM(M51:N51) | P51: =AD51-SUM(M51:O51) | Q51: 0 | R51: =0-Q51 | S51: =0-SUM(Q51:R51) | T51: =AE51-SUM(Q51:S51) | U51: 1 | V51: =1-U51 | W51: =-674-SUM(U51:V51) | X51: =AF51-SUM(U51:W51) | Y51: 0 | Z51: =19-Y51 | AB51: -53 | AC51: -93 | AD51: -7 | AE51: -161 | AF51: -674 | AH51: =SUM(S51:V51) | AI51: =SUM(W51:Z51)
C52: Other investing, net | E52: 0 | F52: =-3-E52 | G52: =-3-SUM(E52:F52) | H52: =AB52-SUM(E52:G52) | I52: -5 | J52: =-7-I52 | K52: =-12-SUM(I52:J52) | L52: =AC52-SUM(I52:K52) | M52: -3 | N52: =-3-M52 | O52: =-3-SUM(M52:N52) | P52: =AD52-SUM(M52:O52) | Q52: -11 | R52: =-20-Q52 | S52: =-26-SUM(Q52:R52) | T52: =AE52-SUM(Q52:S52) | U52: -2 | V52: =-4-U52 | W52: =-9-SUM(U52:V52) | X52: =AF52-SUM(U52:W52) | Y52: -5 | Z52: =-13-Y52 | AB52: -8 | AC52: -15 | AD52: -4 | AE52: -28 | AF52: -12 | AH52: =SUM(S52:V52) | AI52: =SUM(W52:Z52)
C53: Net cash provided by (used in) investing activities | E53: =SUM(E49:E52) | F53: =SUM(F49:F52) | G53: =SUM(G49:G52) | H53: =SUM(H49:H52) | I53: =SUM(I49:I52) | J53: =SUM(J49:J52) | K53: =SUM(K49:K52) | L53: =SUM(L49:L52) | ... Z53: =SUM(Z49:Z52) | AB53: =SUM(AB49:AB52) | AC53: =SUM(AC49:AC52) | AD53: =SUM(AD49:AD52) | AE53: =SUM(AE49:AE52) | AF53: =SUM(AF49:AF52) | AH53: =SUM(AH49:AH52) | AI53: =SUM(AI49:AI52)
C54: Net cash provided by (used in) investing activities | E54: -17 | F54: =-72-(-17) | G54: =-54-(-72) | H54: =-85-(-54) | I54: -75 | J54: =-62-(-75) | K54: =-95-(-62) | L54: =-78-(-95) | M54: -17 | N54: =-22-(-17) | O54: =3-(-22) | P54: =-5-3 | Q54: -17 | R54: =-19-(-17) | S54: =-26-(-19) | T54: =-198-(-26) | U54: 6 | V54: =-12-6 | W54: =-694-(-12) | X54: =-698-(-694) | Y54: -24 | Z54: =-33-(-24) | AB54: -85 | AC54: -78 | AD54: -5 | AE54: -198 | AF54: -698 | AH54: =SUM(S54:V54) | AI54: =SUM(W54:Z54)
C55: Check | E55: =E53-E54 | F55: =F53-F54 | G55: =G53-G54 | H55: =H53-H54 | I55: =I53-I54 | J55: =J53-J54 | K55: =K53-K54 | L55: =L53-L54 | ... Z55: =Z53-Z54 | AB55: =AB53-AB54 | AC55: =AC53-AC54 | AD55: =AD53-AD54 | AE55: =AE53-AE54 | AF55: =AF53-AF54
C57: Financing Activities:
C58: Net proceeds (payments) on short-term debt | E58: 0 | F58: =0-E58 | G58: =1-SUM(E58:F58) | H58: =AB58-SUM(E58:G58) | I58: 0 | J58: =0-I58 | K58: =0-SUM(I58:J58) | L58: =AC58-SUM(I58:K58) | M58: 0 | N58: =200-M58 | O58: =220-SUM(M58:N58) | P58: =AD58-SUM(M58:O58) | Q58: 0 | R58: =0-Q58 | S58: =0-SUM(Q58:R58) | T58: =AE58-SUM(Q58:S58) | U58: 0 | V58: =0-U58 | W58: =218-SUM(U58:V58) | X58: =AF58-SUM(U58:W58) | Y58: 0 | Z58: =-125-Y58 | AB58: 0 | AC58: 0 | AD58: 0 | AE58: 0 | AF58: 119 | AH58: =SUM(S58:V58) | AI58: =SUM(W58:Z58)
C59: Proceeds from issuance of long-term debt | E59: 0 | F59: =0-E59 | G59: =311-SUM(E59:F59) | H59: =AB59-SUM(E59:G59) | I59: 668 | J59: =754-I59 | K59: =754-SUM(I59:J59) | L59: =AC59-SUM(I59:K59) | M59: 0 | N59: =0-M59 | O59: =646-SUM(M59:N59) | P59: =AD59-SUM(M59:O59) | Q59: 905 | R59: =906-Q59 | S59: =906-SUM(Q59:R59) | T59: =AE59-SUM(Q59:S59) | U59: 3 | V59: =889-U59 | W59: =1137-SUM(U59:V59) | X59: =AF59-SUM(U59:W59) | Y59: 446 | Z59: =446-Y59 | AB59: 311 | AC59: 1194 | AD59: 1396 | AE59: 907 | AF59: 1140 | AH59: =SUM(S59:V59) | AI59: =SUM(W59:Z59)
C60: Payments on long-term debt | E60: -95 | F60: =-209-E60 | G60: =-445-SUM(E60:F60) | H60: =AB60-SUM(E60:G60) | I60: -646 | J60: =-1133-I60 | K60: =-1259-SUM(I60:J60) | L60: =AC60-SUM(I60:K60) | M60: -452 | N60: =-826-M60 | O60: =-997-SUM(M60:N60) | P60: =AD60-SUM(M60:O60) | Q60: -570 | R60: =-871-Q60 | S60: =-913-SUM(Q60:R60) | T60: =AE60-SUM(Q60:S60) | U60: -107 | V60: =-343-U60 | W60: =-685-SUM(U60:V60) | X60: =AF60-SUM(U60:W60) | Y60: -191 | Z60: =-251-Y60 | AB60: -519 | AC60: -1723 | AD60: -1874 | AE60: -992 | AF60: -755 | AH60: =SUM(S60:V60) | AI60: =SUM(W60:Z60)
C61: Tariff receivables monetization | Y61: 0 | Z61: =80-Y61 | AH61: =SUM(S61:V61) | AI61: =SUM(W61:Z61)
C62: Purchases of capped calls | Q62: -23 | R62: =-23-Q62 | S62: =-23-SUM(Q62:R62) | T62: =AE62-SUM(Q62:S62) | U62: 0 | V62: =0-U62 | W62: =0-SUM(U62:V62) | X62: =AF62-SUM(U62:W62) | AE62: -23 | AF62: 0 | AH62: =SUM(S62:V62) | AI62: =SUM(W62:Z62)
C63: Dividends | E63: -54 | F63: =-108-E63 | G63: =-157-SUM(E63:F63) | H63: =AB63-SUM(E63:G63) | I63: -46 | J63: =-88-I63 | K63: =-131-SUM(I63:J63) | L63: =AC63-SUM(I63:K63) | M63: -45 | N63: =-88-M63 | O63: =-131-SUM(M63:N63) | P63: =AD63-SUM(M63:O63) | Q63: -37 | R63: =-71-Q63 | S63: =-107-SUM(Q63:R63) | T63: =AE63-SUM(Q63:S63) | U63: -39 | V63: =-58-U63 | W63: =-65-SUM(U63:V63) | X63: =AF63-SUM(U63:W63) | Y63: -10 | Z63: =-16-Y63 | AB63: -206 | AC63: -174 | AD63: -165 | AE63: -141 | AF63: -71 | AH63: =SUM(S63:V63) | AI63: =SUM(W63:Z63)
C64: Payments to acquire treasury stock, including fees | E64: -162 | F64: =-413-E64 | G64: =-500-SUM(E64:F64) | H64: =AB64-SUM(E64:G64) | I64: -113 | J64: =-113-I64 | K64: =-113-SUM(I64:J64) | L64: =AC64-SUM(I64:K64) | M64: 0 | N64: =0-M64 | O64: =-544-SUM(M64:N64) | P64: =AD64-SUM(M64:O64) | Q64: -3 | R64: =-3-Q64 | S64: =-3-SUM(Q64:R64) | T64: =AE64-SUM(Q64:S64) | U64: 0 | V64: =0-U64 | W64: =0-SUM(U64:V64) | X64: =AF64-SUM(U64:W64) | AB64: -888 | AC64: -113 | AD64: -544 | AE64: -8 | AF64: 0 | AH64: =SUM(S64:V64) | AI64: =SUM(W64:Z64)
C65: Other financing, net | E65: -7 | F65: =-17-E65 | G65: =-3-SUM(E65:F65) | H65: =AB65-SUM(E65:G65) | I65: -12 | J65: =-7-I65 | K65: =-6-SUM(I65:J65) | L65: =AC65-SUM(I65:K65) | M65: -8 | N65: =-11-M65 | O65: =-13-SUM(M65:N65) | P65: =AD65-SUM(M65:O65) | Q65: -11 | R65: =-13-Q65 | S65: =-9-SUM(Q65:R65) | T65: =AE65-SUM(Q65:S65) | U65: -16 | V65: =-29-U65 | W65: =-28-SUM(U65:V65) | X65: =AF65-SUM(U65:W65) | Y65: -3 | Z65: =-6-Y65 | AB65: -8 | AC65: -6 | AD65: -15 | AE65: -14 | AF65: -29 | AH65: =SUM(S65:V65) | AI65: =SUM(W65:Z65)
C66: Net cash provided by (used in) financing activities | E66: =SUM(E58:E65) | F66: =SUM(F58:F65) | G66: =SUM(G58:G65) | H66: =SUM(H58:H65) | I66: =SUM(I58:I65) | J66: =SUM(J58:J65) | K66: =SUM(K58:K65) | L66: =SUM(L58:L65) | ... Z66: =SUM(Z58:Z65) | AB66: =SUM(AB58:AB65) | AC66: =SUM(AC58:AC65) | AD66: =SUM(AD58:AD65) | AE66: =SUM(AE58:AE65) | AF66: =SUM(AF58:AF65) | AH66: =SUM(AH58:AH65) | AI66: =SUM(AI58:AI65)
C67: Net cash provided by (used in) financing activities | E67: -318 | F67: =-747-(-318) | G67: =-793-(-747) | H67: =-1310-(-793) | I67: -149 | J67: =-587-(-149) | K67: =-755-(-587) | L67: =-822-(-755) | M67: -505 | N67: =-725-(-505) | O67: =-819-(-725) | P67: =-1202-(-819) | Q67: 261 | R67: =-75-261 | S67: =-149-(-75) | T67: =-271-(-149) | U67: -159 | V67: =459-(-159) | W67: =577-459 | X67: =404-577 | Y67: 242 | Z67: =128-242 | AB67: -1310 | AC67: -822 | AD67: -1202 | AE67: -271 | AF67: 404 | AH67: =SUM(S67:V67) | AI67: =SUM(W67:Z67)
C68: Check | E68: =E66-E67 | F68: =F66-F67 | G68: =G66-G67 | H68: =H66-H67 | I68: =I66-I67 | J68: =J66-J67 | K68: =K66-K67 | L68: =L66-L67 | ... Z68: =Z66-Z67 | AB68: =AB66-AB67 | AC68: =AC66-AC67 | AD68: =AD66-AD67 | AE68: =AE66-AE67 | AF68: =AF66-AF67
C69: Effect of exchange rate changes on cash, cash equivalents and restricted cash | E69: -12 | F69: =0-E69 | G69: =-13-SUM(E69:F69) | H69: =AB69-SUM(E69:G69) | I69: 10 | J69: =-14-I69 | K69: =-31-SUM(I69:J69) | L69: =AC69-SUM(I69:K69) | M69: 2 | N69: =4-M69 | O69: =-3-SUM(M69:N69) | P69: =AD69-SUM(M69:O69) | Q69: -10 | R69: =-16-Q69 | S69: =-12-SUM(Q69:R69) | T69: =AE69-SUM(Q69:S69) | U69: 1 | V69: =7-U69 | W69: =5-SUM(U69:V69) | X69: =AF69-SUM(U69:W69) | Y69: -2 | Z69: =-1-Y69 | AB69: -16 | AC69: -29 | AD69: -1 | AE69: -28 | AF69: 4 | AH69: =SUM(S69:V69) | AI69: =SUM(W69:Z69)
C70: Net increase (decrease) in cash, cash equivalents and restricted cash | E70: =E42+E53+E66+E69 | F70: =F42+F53+F66+F69 | G70: =G42+G53+G66+G69 | H70: =H42+H53+H66+H69 | I70: =I42+I53+I66+I69 | J70: =J42+J53+J66+J69 | K70: =K42+K53+K66+K69 | L70: =L42+L53+L66+L69 | ... Z70: =Z42+Z53+Z66+Z69 | AB70: =AB42+AB53+AB66+AB69 | AC70: =AC42+AC53+AC66+AC69 | AD70: =AD42+AD53+AD66+AD69 | AE70: =AE42+AE53+AE66+AE69 | AF70: =AF42+AF53+AF66+AF69 | AH70: =AH42+AH53+AH66+AH69 | AI70: =AI42+AI53+AI66+AI69
C71: Net increase (decrease) in cash, cash equivalents and restricted cash | E71: -230 | F71: =-488-(-230) | G71: =-429-(-488) | H71: =-782-(-429) | I71: -148 | J71: =-682-(-148) | K71: =-908-(-682) | L71: =-770-(-908) | M71: -442 | N71: =-570-(-442) | O71: =-522-(-570) | P71: =-522-(-522) | Q71: 155 | R71: =-66-155 | S71: =-27-(-66) | T71: =14-(-27) | U71: -241 | V71: =354-(-241) | W71: =-96-354 | X71: =-66-(-96) | Y71: 72 | Z71: =-13-72 | AB71: -782 | AC71: -770 | AD71: -522 | AE71: 14 | AF71: -66 | AH71: =SUM(S71:V71) | AI71: =SUM(W71:Z71)
C72: Check | E72: =E70-E71 | F72: =F70-F71 | G72: =G70-G71 | H72: =H70-H71 | I72: =I70-I71 | J72: =J70-J71 | K72: =K70-K71 | L72: =L70-L71 | ... Z72: =Z70-Z71 | AB72: =AB70-AB71 | AC72: =AC70-AC71 | AD72: =AD70-AD71 | AE72: =AE70-AE71 | AF72: =AF70-AF71
C73: Cash, cash equivalents and restricted cash, beginning | E73: 2691 | F73: =E74 | G73: =F74 | H73: =G74 | I73: 1909 | J73: =I74 | K73: =J74 | L73: =K74 | M73: 1139 | N73: =M74 | O73: =N74 | P73: =O74 | Q73: 617 | R73: =Q74 | S73: =R74 | T73: =S74 | U73: 631 | V73: =U74 | W73: =V74 | X73: =W74 | Y73: 565 | Z73: =Y74 | AB73: 2691 | AC73: 1909 | AD73: 1139 | AE73: 617 | AF73: 631 | AH73: =S73 | AI73: =W73
A74: x | B74: x | C74: Cash, cash equivalents and restricted cash, ending | E74: =E70+E73 | F74: =F70+F73 | G74: =G70+G73 | H74: =H70+H73 | I74: =I70+I73 | J74: =J70+J73 | K74: =K70+K73 | L74: =L70+L73 | ... Z74: =Z70+Z73 | AB74: =AB70+AB73 | AC74: =AC70+AC73 | AD74: =AD70+AD73 | AE74: =AE70+AE73 | AF74: =AF70+AF73 | AH74: =AH70+AH73 | AI74: =AI70+AI73
A75: End | C75: Cash, cash equivalents and restricted cash, ending | E75: 2461 | F75: 2203 | G75: 2262 | H75: 1909 | I75: 1761 | J75: 1227 | K75: 1001 | L75: 1139 | M75: 697 | N75: 569 | O75: 617 | P75: 617 | Q75: 772 | R75: 551 | S75: 590 | T75: 631 | U75: 390 | V75: 985 | W75: 535 | X75: 565 | Y75: 637 | Z75: 552 | AB75: 1909 | AC75: 1139 | AD75: 617 | AE75: 631 | AF75: 565 | AH75: =V75 | AI75: =Z75
C76: Check | E76: =E74-E75 | F76: =F74-F75 | G76: =G74-G75 | H76: =H74-H75 | I76: =I74-I75 | J76: =J74-J75 | K76: =K74-K75 | L76: =L74-L75 | ... Z76: =Z74-Z75 | AB76: =AB74-AB75 | AC76: =AC74-AC75 | AD76: =AD74-AD75 | AE76: =AE74-AE75 | AF76: =AF74-AF75
A77: End

Sheet Financial Statement Outputs >
A1: Financial Statements > | B1: ='Cover Page'!A1

Sheet Income Statement Output
A1: =C3 | B1: ='Cover Page'!A1
C3: Income Statement Summary | J3: Xerox Holdings Corporation
C4: All values in $ millions (USD)
A8: x | B8: x | C8: Income Statement Summary | D8: Fiscal Year Ended | I8: LTM
D9: 2021 | E9: 2022 | F9: 2023 | G9: 2024 | H9: 2025 | I9: LTM 2Q'25 | J9: LTM 2Q'26
C11: Sales | D11: ='Income Statement'!AA10 | E11: ='Income Statement'!AB10 | F11: ='Income Statement'!AC10 | G11: ='Income Statement'!AD10 | H11: ='Income Statement'!AE10 | I11: ='Income Statement'!AG10 | J11: ='Income Statement'!AH10
C12: Services, maintenance, rentals and other | D12: ='Income Statement'!AA11 | E12: ='Income Statement'!AB11 | F12: ='Income Statement'!AC11 | G12: ='Income Statement'!AD11 | H12: ='Income Statement'!AE11 | I12: ='Income Statement'!AG11 | J12: ='Income Statement'!AH11
C13: Total revenues | D13: =D11+D12 | E13: =E11+E12 | F13: =F11+F12 | G13: =G11+G12 | H13: =H11+H12 | I13: =I11+I12 | J13: =J11+J12
C14: Cost of revenues | D14: =-'Income Statement'!AA17 | E14: =-'Income Statement'!AB17 | F14: =-'Income Statement'!AC17 | G14: =-'Income Statement'!AD17 | H14: =-'Income Statement'!AE17 | I14: =-'Income Statement'!AG17 | J14: =-'Income Statement'!AH17
C15: Gross profit | D15: =D13+D14 | E15: =E13+E14 | F15: =F13+F14 | G15: =G13+G14 | H15: =H13+H14 | I15: =I13+I14 | J15: =J13+J14
C16: Research, development and engineering | D16: =-'Income Statement'!AA19 | E16: =-'Income Statement'!AB19 | F16: =-'Income Statement'!AC19 | G16: =-'Income Statement'!AD19 | H16: =-'Income Statement'!AE19 | I16: =-'Income Statement'!AG19 | J16: =-'Income Statement'!AH19
C17: Selling, administrative and general | D17: =-'Income Statement'!AA20 | E17: =-'Income Statement'!AB20 | F17: =-'Income Statement'!AC20 | G17: =-'Income Statement'!AD20 | H17: =-'Income Statement'!AE20 | I17: =-'Income Statement'!AG20 | J17: =-'Income Statement'!AH20
C18: Restructuring and related costs, net | D18: =-'Income Statement'!AA22 | E18: =-'Income Statement'!AB22 | F18: =-'Income Statement'!AC22 | G18: =-'Income Statement'!AD22 | H18: =-'Income Statement'!AE22 | I18: =-'Income Statement'!AG22 | J18: =-'Income Statement'!AH22
C19: Amortization of intangible assets | D19: =-'Income Statement'!AA23 | E19: =-'Income Statement'!AB23 | F19: =-'Income Statement'!AC23 | G19: =-'Income Statement'!AD23 | H19: =-'Income Statement'!AE23 | I19: =-'Income Statement'!AG23 | J19: =-'Income Statement'!AH23
C20: Divestitures | D20: =-'Income Statement'!AA24 | E20: =-'Income Statement'!AB24 | F20: =-'Income Statement'!AC24 | G20: =-'Income Statement'!AD24 | H20: =-'Income Statement'!AE24 | I20: =-'Income Statement'!AG24 | J20: =-'Income Statement'!AH24
C21: PARC donation | D21: =-'Income Statement'!AA25 | E21: =-'Income Statement'!AB25 | F21: =-'Income Statement'!AC25 | G21: =-'Income Statement'!AD25 | H21: =-'Income Statement'!AE25 | I21: =-'Income Statement'!AG25 | J21: =-'Income Statement'!AH25
C22: Depreciation and amortization (add-back) | D22: ='Income Statement'!AA43 | E22: ='Income Statement'!AB43 | F22: ='Income Statement'!AC43 | G22: ='Income Statement'!AD43 | H22: ='Income Statement'!AE43 | I22: ='Income Statement'!AG43 | J22: ='Income Statement'!AH43
C23: EBITDA | D23: =D15+SUM(D16:D22) | E23: =E15+SUM(E16:E22) | F23: =F15+SUM(F16:F22) | G23: =G15+SUM(G16:G22) | H23: =H15+SUM(H16:H22) | I23: =I15+SUM(I16:I22) | J23: =J15+SUM(J16:J22)
C24: Stock-based compensation | D24: ='Income Statement'!AA46 | E24: ='Income Statement'!AB46 | F24: ='Income Statement'!AC46 | G24: ='Income Statement'!AD46 | H24: ='Income Statement'!AE46 | I24: ='Income Statement'!AG46 | J24: ='Income Statement'!AH46
C25: Restructuring and related costs, net | D25: ='Income Statement'!AA22 | E25: ='Income Statement'!AB22 | F25: ='Income Statement'!AC22 | G25: ='Income Statement'!AD22 | H25: ='Income Statement'!AE22 | I25: ='Income Statement'!AG22 | J25: ='Income Statement'!AH22
C26: PARC donation | D26: ='Income Statement'!AA25 | E26: ='Income Statement'!AB25 | F26: ='Income Statement'!AC25 | G26: ='Income Statement'!AD25 | H26: ='Income Statement'!AE25 | I26: ='Income Statement'!AG25 | J26: ='Income Statement'!AH25
C27: Divestitures | D27: ='Income Statement'!AA24 | E27: ='Income Statement'!AB24 | F27: ='Income Statement'!AC24 | G27: ='Income Statement'!AD24 | H27: ='Income Statement'!AE24 | I27: ='Income Statement'!AG24 | J27: ='Income Statement'!AH24
C28: Transformation-related costs | D28: ='Income Statement'!AA50 | E28: ='Income Statement'!AB50 | F28: ='Income Statement'!AC50 | G28: ='Income Statement'!AD50 | H28: ='Income Statement'!AE50 | I28: ='Income Statement'!AG50 | J28: ='Income Statement'!AH50
C29: Transaction and related costs, net | D29: ='Income Statement'!AA51 | E29: ='Income Statement'!AB51 | F29: ='Income Statement'!AC51 | G29: ='Income Statement'!AD51 | H29: ='Income Statement'!AE51 | I29: ='Income Statement'!AG51 | J29: ='Income Statement'!AH51
C30: Inventory impact, exit of Production Print manufacturing | D30: ='Income Statement'!AA52 | E30: ='Income Statement'!AB52 | F30: ='Income Statement'!AC52 | G30: ='Income Statement'!AD52 | H30: ='Income Statement'!AE52 | I30: ='Income Statement'!AG52 | J30: ='Income Statement'!AH52
C31: Lexmark inventory purchase accounting adjustment | D31: ='Income Statement'!AA53 | E31: ='Income Statement'!AB53 | F31: ='Income Statement'!AC53 | G31: ='Income Statement'!AD53 | H31: ='Income Statement'!AE53 | I31: ='Income Statement'!AG53 | J31: ='Income Statement'!AH53
C32: Lexmark settlement of pre-existing employment agreements | D32: ='Income Statement'!AA54 | E32: ='Income Statement'!AB54 | F32: ='Income Statement'!AC54 | G32: ='Income Statement'!AD54 | H32: ='Income Statement'!AE54 | I32: ='Income Statement'!AG54 | J32: ='Income Statement'!AH54
C33: Adjusted EBITDA | D33: =D23+SUM(D24:D32) | E33: =E23+SUM(E24:E32) | F33: =F23+SUM(F24:F32) | G33: =G23+SUM(G24:G32) | H33: =H23+SUM(H24:H32) | I33: =I23+SUM(I24:I32) | J33: =J23+SUM(J24:J32)
C34: IS Adjusted EBITDA | D34: ='Income Statement'!AA55 | E34: ='Income Statement'!AB55 | F34: ='Income Statement'!AC55 | G34: ='Income Statement'!AD55 | H34: ='Income Statement'!AE55 | I34: ='Income Statement'!AG55 | J34: ='Income Statement'!AH55
C35: Check | D35: =D33-D34 | E35: =E33-E34 | F35: =F33-F34 | G35: =G33-G34 | H35: =H33-H34 | I35: =I33-I34 | J35: =J33-J34
C36: Less: IEEPA tariff refund benefit | D36: ='Income Statement'!AA56 | E36: ='Income Statement'!AB56 | F36: ='Income Statement'!AC56 | G36: ='Income Statement'!AD56 | H36: ='Income Statement'!AE56 | I36: ='Income Statement'!AG56 | J36: ='Income Statement'!AH56
B37: x | C37: Adjusted EBITDA excl. IEEPA tariff benefit | D37: =D33+D36 | E37: =E33+E36 | F37: =F33+F36 | G37: =G33+G36 | H37: =H33+H36 | I37: =I33+I36 | J37: =J33+J36
C39: Memo:
C40: Total revenue growth (YoY) | E40: =E13/D13-1 | F40: =F13/E13-1 | G40: =G13/F13-1 | H40: =H13/G13-1 | I40: ='Income Statement'!AG60 | J40: ='Income Statement'!AH60
C41: Gross margin % | D41: =D15/D13 | E41: =E15/E13 | F41: =F15/F13 | G41: =G15/G13 | H41: =H15/H13 | I41: =I15/I13 | J41: =J15/J13
C42: EBITDA margin % | D42: =D23/D13 | E42: =E23/E13 | F42: =F23/F13 | G42: =G23/G13 | H42: =H23/H13 | I42: =I23/I13 | J42: =J23/J13
C43: Adjusted EBITDA margin % | D43: =D33/D13 | E43: =E33/E13 | F43: =F33/F13 | G43: =G33/G13 | H43: =H33/H13 | I43: =I33/I13 | J43: =J33/J13
A44: x | B44: x | C44: Adjusted EBITDA excl. IEEPA margin % | D44: =D37/D13 | E44: =E37/E13 | F44: =F37/F13 | G44: =G37/G13 | H44: =H37/H13 | I44: =I37/I13 | J44: =J37/J13
A45: End

Sheet Balance Sheet Output
A1: =C3 | B1: ='Cover Page'!A1
C3: Balance Sheet Summary | J3: Xerox Holdings Corporation
C4: All values in $ millions (USD)
A7: x | B7: x | C7: Balance Sheet Summary | D7: Fiscal Year Ended December 31, | E7: Fiscal Year | I7: Quarter Ended
D9: 2021 | E9: 2022 | F9: 2023 | G9: 2024 | H9: 2025 | I9: 2Q'25 | J9: 2Q'26
C11: Cash and cash equivalents | D11: =SUMIFS('Balance Sheet'!$E$13:$AF$13,'Balance Sheet'!$E$10:$AF$10,D$9) | E11: =SUMIFS('Balance Sheet'!$E$13:$AF$13,'Balance Sheet'!$E$10:$AF$10,E$9) | F11: =SUMIFS('Balance Sheet'!$E$13:$AF$13,'Balance Sheet'!$E$10:$AF$10,F$9) | G11: =SUMIFS('Balance Sheet'!$E$13:$AF$13,'Balance Sheet'!$E$10:$AF$10,G$9) | H11: =SUMIFS('Balance Sheet'!$E$13:$AF$13,'Balance Sheet'!$E$10:$AF$10,H$9) | I11: =SUMIFS('Balance Sheet'!$E$13:$AF$13,'Balance Sheet'!$E$10:$AF$10,I$9) | J11: =SUMIFS('Balance Sheet'!$E$13:$AF$13,'Balance Sheet'!$E$10:$AF$10,J$9)
C12: Accounts receivable, net | D12: =SUMIFS('Balance Sheet'!$E$14:$AF$14,'Balance Sheet'!$E$10:$AF$10,D$9) | E12: =SUMIFS('Balance Sheet'!$E$14:$AF$14,'Balance Sheet'!$E$10:$AF$10,E$9) | F12: =SUMIFS('Balance Sheet'!$E$14:$AF$14,'Balance Sheet'!$E$10:$AF$10,F$9) | G12: =SUMIFS('Balance Sheet'!$E$14:$AF$14,'Balance Sheet'!$E$10:$AF$10,G$9) | H12: =SUMIFS('Balance Sheet'!$E$14:$AF$14,'Balance Sheet'!$E$10:$AF$10,H$9) | I12: =SUMIFS('Balance Sheet'!$E$14:$AF$14,'Balance Sheet'!$E$10:$AF$10,I$9) | J12: =SUMIFS('Balance Sheet'!$E$14:$AF$14,'Balance Sheet'!$E$10:$AF$10,J$9)
C13: Billed portion of finance receivables, net | D13: =SUMIFS('Balance Sheet'!$E$15:$AF$15,'Balance Sheet'!$E$10:$AF$10,D$9) | E13: =SUMIFS('Balance Sheet'!$E$15:$AF$15,'Balance Sheet'!$E$10:$AF$10,E$9) | F13: =SUMIFS('Balance Sheet'!$E$15:$AF$15,'Balance Sheet'!$E$10:$AF$10,F$9) | G13: =SUMIFS('Balance Sheet'!$E$15:$AF$15,'Balance Sheet'!$E$10:$AF$10,G$9) | H13: =SUMIFS('Balance Sheet'!$E$15:$AF$15,'Balance Sheet'!$E$10:$AF$10,H$9) | I13: =SUMIFS('Balance Sheet'!$E$15:$AF$15,'Balance Sheet'!$E$10:$AF$10,I$9) | J13: =SUMIFS('Balance Sheet'!$E$15:$AF$15,'Balance Sheet'!$E$10:$AF$10,J$9)
C14: Finance receivables, net | D14: =SUMIFS('Balance Sheet'!$E$16:$AF$16,'Balance Sheet'!$E$10:$AF$10,D$9) | E14: =SUMIFS('Balance Sheet'!$E$16:$AF$16,'Balance Sheet'!$E$10:$AF$10,E$9) | F14: =SUMIFS('Balance Sheet'!$E$16:$AF$16,'Balance Sheet'!$E$10:$AF$10,F$9) | G14: =SUMIFS('Balance Sheet'!$E$16:$AF$16,'Balance Sheet'!$E$10:$AF$10,G$9) | H14: =SUMIFS('Balance Sheet'!$E$16:$AF$16,'Balance Sheet'!$E$10:$AF$10,H$9) | I14: =SUMIFS('Balance Sheet'!$E$16:$AF$16,'Balance Sheet'!$E$10:$AF$10,I$9) | J14: =SUMIFS('Balance Sheet'!$E$16:$AF$16,'Balance Sheet'!$E$10:$AF$10,J$9)
C15: Inventories | D15: =SUMIFS('Balance Sheet'!$E$17:$AF$17,'Balance Sheet'!$E$10:$AF$10,D$9) | E15: =SUMIFS('Balance Sheet'!$E$17:$AF$17,'Balance Sheet'!$E$10:$AF$10,E$9) | F15: =SUMIFS('Balance Sheet'!$E$17:$AF$17,'Balance Sheet'!$E$10:$AF$10,F$9) | G15: =SUMIFS('Balance Sheet'!$E$17:$AF$17,'Balance Sheet'!$E$10:$AF$10,G$9) | H15: =SUMIFS('Balance Sheet'!$E$17:$AF$17,'Balance Sheet'!$E$10:$AF$10,H$9) | I15: =SUMIFS('Balance Sheet'!$E$17:$AF$17,'Balance Sheet'!$E$10:$AF$10,I$9) | J15: =SUMIFS('Balance Sheet'!$E$17:$AF$17,'Balance Sheet'!$E$10:$AF$10,J$9)
C16: Other current assets | D16: =SUMIFS('Balance Sheet'!$E$18:$AF$18,'Balance Sheet'!$E$10:$AF$10,D$9) | E16: =SUMIFS('Balance Sheet'!$E$18:$AF$18,'Balance Sheet'!$E$10:$AF$10,E$9) | F16: =SUMIFS('Balance Sheet'!$E$18:$AF$18,'Balance Sheet'!$E$10:$AF$10,F$9) | G16: =SUMIFS('Balance Sheet'!$E$18:$AF$18,'Balance Sheet'!$E$10:$AF$10,G$9) | H16: =SUMIFS('Balance Sheet'!$E$18:$AF$18,'Balance Sheet'!$E$10:$AF$10,H$9) | I16: =SUMIFS('Balance Sheet'!$E$18:$AF$18,'Balance Sheet'!$E$10:$AF$10,I$9) | J16: =SUMIFS('Balance Sheet'!$E$18:$AF$18,'Balance Sheet'!$E$10:$AF$10,J$9)
C17: Total current assets | D17: =SUM(D11:D16) | E17: =SUM(E11:E16) | F17: =SUM(F11:F16) | G17: =SUM(G11:G16) | H17: =SUM(H11:H16) | I17: =SUM(I11:I16) | J17: =SUM(J11:J16)
C18: Finance receivables due after one year, net | D18: =SUMIFS('Balance Sheet'!$E$22:$AF$22,'Balance Sheet'!$E$10:$AF$10,D$9) | E18: =SUMIFS('Balance Sheet'!$E$22:$AF$22,'Balance Sheet'!$E$10:$AF$10,E$9) | F18: =SUMIFS('Balance Sheet'!$E$22:$AF$22,'Balance Sheet'!$E$10:$AF$10,F$9) | G18: =SUMIFS('Balance Sheet'!$E$22:$AF$22,'Balance Sheet'!$E$10:$AF$10,G$9) | H18: =SUMIFS('Balance Sheet'!$E$22:$AF$22,'Balance Sheet'!$E$10:$AF$10,H$9) | I18: =SUMIFS('Balance Sheet'!$E$22:$AF$22,'Balance Sheet'!$E$10:$AF$10,I$9) | J18: =SUMIFS('Balance Sheet'!$E$22:$AF$22,'Balance Sheet'!$E$10:$AF$10,J$9)
C19: Equipment on operating leases, net | D19: =SUMIFS('Balance Sheet'!$E$23:$AF$23,'Balance Sheet'!$E$10:$AF$10,D$9) | E19: =SUMIFS('Balance Sheet'!$E$23:$AF$23,'Balance Sheet'!$E$10:$AF$10,E$9) | F19: =SUMIFS('Balance Sheet'!$E$23:$AF$23,'Balance Sheet'!$E$10:$AF$10,F$9) | G19: =SUMIFS('Balance Sheet'!$E$23:$AF$23,'Balance Sheet'!$E$10:$AF$10,G$9) | H19: =SUMIFS('Balance Sheet'!$E$23:$AF$23,'Balance Sheet'!$E$10:$AF$10,H$9) | I19: =SUMIFS('Balance Sheet'!$E$23:$AF$23,'Balance Sheet'!$E$10:$AF$10,I$9) | J19: =SUMIFS('Balance Sheet'!$E$23:$AF$23,'Balance Sheet'!$E$10:$AF$10,J$9)
C20: Land, buildings and equipment, net | D20: =SUMIFS('Balance Sheet'!$E$24:$AF$24,'Balance Sheet'!$E$10:$AF$10,D$9) | E20: =SUMIFS('Balance Sheet'!$E$24:$AF$24,'Balance Sheet'!$E$10:$AF$10,E$9) | F20: =SUMIFS('Balance Sheet'!$E$24:$AF$24,'Balance Sheet'!$E$10:$AF$10,F$9) | G20: =SUMIFS('Balance Sheet'!$E$24:$AF$24,'Balance Sheet'!$E$10:$AF$10,G$9) | H20: =SUMIFS('Balance Sheet'!$E$24:$AF$24,'Balance Sheet'!$E$10:$AF$10,H$9) | I20: =SUMIFS('Balance Sheet'!$E$24:$AF$24,'Balance Sheet'!$E$10:$AF$10,I$9) | J20: =SUMIFS('Balance Sheet'!$E$24:$AF$24,'Balance Sheet'!$E$10:$AF$10,J$9)
C21: Intangible assets, net | D21: =SUMIFS('Balance Sheet'!$E$25:$AF$25,'Balance Sheet'!$E$10:$AF$10,D$9) | E21: =SUMIFS('Balance Sheet'!$E$25:$AF$25,'Balance Sheet'!$E$10:$AF$10,E$9) | F21: =SUMIFS('Balance Sheet'!$E$25:$AF$25,'Balance Sheet'!$E$10:$AF$10,F$9) | G21: =SUMIFS('Balance Sheet'!$E$25:$AF$25,'Balance Sheet'!$E$10:$AF$10,G$9) | H21: =SUMIFS('Balance Sheet'!$E$25:$AF$25,'Balance Sheet'!$E$10:$AF$10,H$9) | I21: =SUMIFS('Balance Sheet'!$E$25:$AF$25,'Balance Sheet'!$E$10:$AF$10,I$9) | J21: =SUMIFS('Balance Sheet'!$E$25:$AF$25,'Balance Sheet'!$E$10:$AF$10,J$9)
C22: Goodwill, net | D22: =SUMIFS('Balance Sheet'!$E$26:$AF$26,'Balance Sheet'!$E$10:$AF$10,D$9) | E22: =SUMIFS('Balance Sheet'!$E$26:$AF$26,'Balance Sheet'!$E$10:$AF$10,E$9) | F22: =SUMIFS('Balance Sheet'!$E$26:$AF$26,'Balance Sheet'!$E$10:$AF$10,F$9) | G22: =SUMIFS('Balance Sheet'!$E$26:$AF$26,'Balance Sheet'!$E$10:$AF$10,G$9) | H22: =SUMIFS('Balance Sheet'!$E$26:$AF$26,'Balance Sheet'!$E$10:$AF$10,H$9) | I22: =SUMIFS('Balance Sheet'!$E$26:$AF$26,'Balance Sheet'!$E$10:$AF$10,I$9) | J22: =SUMIFS('Balance Sheet'!$E$26:$AF$26,'Balance Sheet'!$E$10:$AF$10,J$9)
C23: Deferred tax assets | D23: =SUMIFS('Balance Sheet'!$E$27:$AF$27,'Balance Sheet'!$E$10:$AF$10,D$9) | E23: =SUMIFS('Balance Sheet'!$E$27:$AF$27,'Balance Sheet'!$E$10:$AF$10,E$9) | F23: =SUMIFS('Balance Sheet'!$E$27:$AF$27,'Balance Sheet'!$E$10:$AF$10,F$9) | G23: =SUMIFS('Balance Sheet'!$E$27:$AF$27,'Balance Sheet'!$E$10:$AF$10,G$9) | H23: =SUMIFS('Balance Sheet'!$E$27:$AF$27,'Balance Sheet'!$E$10:$AF$10,H$9) | I23: =SUMIFS('Balance Sheet'!$E$27:$AF$27,'Balance Sheet'!$E$10:$AF$10,I$9) | J23: =SUMIFS('Balance Sheet'!$E$27:$AF$27,'Balance Sheet'!$E$10:$AF$10,J$9)
C24: Other long-term assets | D24: =SUMIFS('Balance Sheet'!$E$28:$AF$28,'Balance Sheet'!$E$10:$AF$10,D$9) | E24: =SUMIFS('Balance Sheet'!$E$28:$AF$28,'Balance Sheet'!$E$10:$AF$10,E$9) | F24: =SUMIFS('Balance Sheet'!$E$28:$AF$28,'Balance Sheet'!$E$10:$AF$10,F$9) | G24: =SUMIFS('Balance Sheet'!$E$28:$AF$28,'Balance Sheet'!$E$10:$AF$10,G$9) | H24: =SUMIFS('Balance Sheet'!$E$28:$AF$28,'Balance Sheet'!$E$10:$AF$10,H$9) | I24: =SUMIFS('Balance Sheet'!$E$28:$AF$28,'Balance Sheet'!$E$10:$AF$10,I$9) | J24: =SUMIFS('Balance Sheet'!$E$28:$AF$28,'Balance Sheet'!$E$10:$AF$10,J$9)
C25: Total assets | D25: =D17+SUM(D18:D24) | E25: =E17+SUM(E18:E24) | F25: =F17+SUM(F18:F24) | G25: =G17+SUM(G18:G24) | H25: =H17+SUM(H18:H24) | I25: =I17+SUM(I18:I24) | J25: =J17+SUM(J18:J24)
C27: Short-term debt and current portion of long-term debt | D27: =SUMIFS('Balance Sheet'!$E$35:$AF$35,'Balance Sheet'!$E$10:$AF$10,D$9) | E27: =SUMIFS('Balance Sheet'!$E$35:$AF$35,'Balance Sheet'!$E$10:$AF$10,E$9) | F27: =SUMIFS('Balance Sheet'!$E$35:$AF$35,'Balance Sheet'!$E$10:$AF$10,F$9) | G27: =SUMIFS('Balance Sheet'!$E$35:$AF$35,'Balance Sheet'!$E$10:$AF$10,G$9) | H27: =SUMIFS('Balance Sheet'!$E$35:$AF$35,'Balance Sheet'!$E$10:$AF$10,H$9) | I27: =SUMIFS('Balance Sheet'!$E$35:$AF$35,'Balance Sheet'!$E$10:$AF$10,I$9) | J27: =SUMIFS('Balance Sheet'!$E$35:$AF$35,'Balance Sheet'!$E$10:$AF$10,J$9)
C28: Financing liability, tariff receivables monetization | D28: =SUMIFS('Balance Sheet'!$E$36:$AF$36,'Balance Sheet'!$E$10:$AF$10,D$9) | E28: =SUMIFS('Balance Sheet'!$E$36:$AF$36,'Balance Sheet'!$E$10:$AF$10,E$9) | F28: =SUMIFS('Balance Sheet'!$E$36:$AF$36,'Balance Sheet'!$E$10:$AF$10,F$9) | G28: =SUMIFS('Balance Sheet'!$E$36:$AF$36,'Balance Sheet'!$E$10:$AF$10,G$9) | H28: =SUMIFS('Balance Sheet'!$E$36:$AF$36,'Balance Sheet'!$E$10:$AF$10,H$9) | I28: =SUMIFS('Balance Sheet'!$E$36:$AF$36,'Balance Sheet'!$E$10:$AF$10,I$9) | J28: =SUMIFS('Balance Sheet'!$E$36:$AF$36,'Balance Sheet'!$E$10:$AF$10,J$9)
C29: Accounts payable | D29: =SUMIFS('Balance Sheet'!$E$37:$AF$37,'Balance Sheet'!$E$10:$AF$10,D$9) | E29: =SUMIFS('Balance Sheet'!$E$37:$AF$37,'Balance Sheet'!$E$10:$AF$10,E$9) | F29: =SUMIFS('Balance Sheet'!$E$37:$AF$37,'Balance Sheet'!$E$10:$AF$10,F$9) | G29: =SUMIFS('Balance Sheet'!$E$37:$AF$37,'Balance Sheet'!$E$10:$AF$10,G$9) | H29: =SUMIFS('Balance Sheet'!$E$37:$AF$37,'Balance Sheet'!$E$10:$AF$10,H$9) | I29: =SUMIFS('Balance Sheet'!$E$37:$AF$37,'Balance Sheet'!$E$10:$AF$10,I$9) | J29: =SUMIFS('Balance Sheet'!$E$37:$AF$37,'Balance Sheet'!$E$10:$AF$10,J$9)
C30: Accrued compensation and benefits costs | D30: =SUMIFS('Balance Sheet'!$E$38:$AF$38,'Balance Sheet'!$E$10:$AF$10,D$9) | E30: =SUMIFS('Balance Sheet'!$E$38:$AF$38,'Balance Sheet'!$E$10:$AF$10,E$9) | F30: =SUMIFS('Balance Sheet'!$E$38:$AF$38,'Balance Sheet'!$E$10:$AF$10,F$9) | G30: =SUMIFS('Balance Sheet'!$E$38:$AF$38,'Balance Sheet'!$E$10:$AF$10,G$9) | H30: =SUMIFS('Balance Sheet'!$E$38:$AF$38,'Balance Sheet'!$E$10:$AF$10,H$9) | I30: =SUMIFS('Balance Sheet'!$E$38:$AF$38,'Balance Sheet'!$E$10:$AF$10,I$9) | J30: =SUMIFS('Balance Sheet'!$E$38:$AF$38,'Balance Sheet'!$E$10:$AF$10,J$9)
C31: Accrued expenses and other current liabilities | D31: =SUMIFS('Balance Sheet'!$E$39:$AF$39,'Balance Sheet'!$E$10:$AF$10,D$9) | E31: =SUMIFS('Balance Sheet'!$E$39:$AF$39,'Balance Sheet'!$E$10:$AF$10,E$9) | F31: =SUMIFS('Balance Sheet'!$E$39:$AF$39,'Balance Sheet'!$E$10:$AF$10,F$9) | G31: =SUMIFS('Balance Sheet'!$E$39:$AF$39,'Balance Sheet'!$E$10:$AF$10,G$9) | H31: =SUMIFS('Balance Sheet'!$E$39:$AF$39,'Balance Sheet'!$E$10:$AF$10,H$9) | I31: =SUMIFS('Balance Sheet'!$E$39:$AF$39,'Balance Sheet'!$E$10:$AF$10,I$9) | J31: =SUMIFS('Balance Sheet'!$E$39:$AF$39,'Balance Sheet'!$E$10:$AF$10,J$9)
C32: Total current liabilities | D32: =SUM(D27:D31) | E32: =SUM(E27:E31) | F32: =SUM(F27:F31) | G32: =SUM(G27:G31) | H32: =SUM(H27:H31) | I32: =SUM(I27:I31) | J32: =SUM(J27:J31)
C33: Long-term debt | D33: =SUMIFS('Balance Sheet'!$E$43:$AF$43,'Balance Sheet'!$E$10:$AF$10,D$9) | E33: =SUMIFS('Balance Sheet'!$E$43:$AF$43,'Balance Sheet'!$E$10:$AF$10,E$9) | F33: =SUMIFS('Balance Sheet'!$E$43:$AF$43,'Balance Sheet'!$E$10:$AF$10,F$9) | G33: =SUMIFS('Balance Sheet'!$E$43:$AF$43,'Balance Sheet'!$E$10:$AF$10,G$9) | H33: =SUMIFS('Balance Sheet'!$E$43:$AF$43,'Balance Sheet'!$E$10:$AF$10,H$9) | I33: =SUMIFS('Balance Sheet'!$E$43:$AF$43,'Balance Sheet'!$E$10:$AF$10,I$9) | J33: =SUMIFS('Balance Sheet'!$E$43:$AF$43,'Balance Sheet'!$E$10:$AF$10,J$9)
C34: Pension and other benefit liabilities | D34: =SUMIFS('Balance Sheet'!$E$44:$AF$44,'Balance Sheet'!$E$10:$AF$10,D$9) | E34: =SUMIFS('Balance Sheet'!$E$44:$AF$44,'Balance Sheet'!$E$10:$AF$10,E$9) | F34: =SUMIFS('Balance Sheet'!$E$44:$AF$44,'Balance Sheet'!$E$10:$AF$10,F$9) | G34: =SUMIFS('Balance Sheet'!$E$44:$AF$44,'Balance Sheet'!$E$10:$AF$10,G$9) | H34: =SUMIFS('Balance Sheet'!$E$44:$AF$44,'Balance Sheet'!$E$10:$AF$10,H$9) | I34: =SUMIFS('Balance Sheet'!$E$44:$AF$44,'Balance Sheet'!$E$10:$AF$10,I$9) | J34: =SUMIFS('Balance Sheet'!$E$44:$AF$44,'Balance Sheet'!$E$10:$AF$10,J$9)
C35: Post-retirement medical benefits | D35: =SUMIFS('Balance Sheet'!$E$45:$AF$45,'Balance Sheet'!$E$10:$AF$10,D$9) | E35: =SUMIFS('Balance Sheet'!$E$45:$AF$45,'Balance Sheet'!$E$10:$AF$10,E$9) | F35: =SUMIFS('Balance Sheet'!$E$45:$AF$45,'Balance Sheet'!$E$10:$AF$10,F$9) | G35: =SUMIFS('Balance Sheet'!$E$45:$AF$45,'Balance Sheet'!$E$10:$AF$10,G$9) | H35: =SUMIFS('Balance Sheet'!$E$45:$AF$45,'Balance Sheet'!$E$10:$AF$10,H$9) | I35: =SUMIFS('Balance Sheet'!$E$45:$AF$45,'Balance Sheet'!$E$10:$AF$10,I$9) | J35: =SUMIFS('Balance Sheet'!$E$45:$AF$45,'Balance Sheet'!$E$10:$AF$10,J$9)
C36: Other long-term liabilities | D36: =SUMIFS('Balance Sheet'!$E$46:$AF$46,'Balance Sheet'!$E$10:$AF$10,D$9) | E36: =SUMIFS('Balance Sheet'!$E$46:$AF$46,'Balance Sheet'!$E$10:$AF$10,E$9) | F36: =SUMIFS('Balance Sheet'!$E$46:$AF$46,'Balance Sheet'!$E$10:$AF$10,F$9) | G36: =SUMIFS('Balance Sheet'!$E$46:$AF$46,'Balance Sheet'!$E$10:$AF$10,G$9) | H36: =SUMIFS('Balance Sheet'!$E$46:$AF$46,'Balance Sheet'!$E$10:$AF$10,H$9) | I36: =SUMIFS('Balance Sheet'!$E$46:$AF$46,'Balance Sheet'!$E$10:$AF$10,I$9) | J36: =SUMIFS('Balance Sheet'!$E$46:$AF$46,'Balance Sheet'!$E$10:$AF$10,J$9)
C37: Total liabilities | D37: =D32+SUM(D33:D36) | E37: =E32+SUM(E33:E36) | F37: =F32+SUM(F33:F36) | G37: =G32+SUM(G33:G36) | H37: =H32+SUM(H33:H36) | I37: =I32+SUM(I33:I36) | J37: =J32+SUM(J33:J36)
C39: Noncontrolling interests (temporary equity) | D39: =SUMIFS('Balance Sheet'!$E$52:$AF$52,'Balance Sheet'!$E$10:$AF$10,D$9) | E39: =SUMIFS('Balance Sheet'!$E$52:$AF$52,'Balance Sheet'!$E$10:$AF$10,E$9) | F39: =SUMIFS('Balance Sheet'!$E$52:$AF$52,'Balance Sheet'!$E$10:$AF$10,F$9) | G39: =SUMIFS('Balance Sheet'!$E$52:$AF$52,'Balance Sheet'!$E$10:$AF$10,G$9) | H39: =SUMIFS('Balance Sheet'!$E$52:$AF$52,'Balance Sheet'!$E$10:$AF$10,H$9) | I39: =SUMIFS('Balance Sheet'!$E$52:$AF$52,'Balance Sheet'!$E$10:$AF$10,I$9) | J39: =SUMIFS('Balance Sheet'!$E$52:$AF$52,'Balance Sheet'!$E$10:$AF$10,J$9)
C40: Convertible preferred stock | D40: =SUMIFS('Balance Sheet'!$E$53:$AF$53,'Balance Sheet'!$E$10:$AF$10,D$9) | E40: =SUMIFS('Balance Sheet'!$E$53:$AF$53,'Balance Sheet'!$E$10:$AF$10,E$9) | F40: =SUMIFS('Balance Sheet'!$E$53:$AF$53,'Balance Sheet'!$E$10:$AF$10,F$9) | G40: =SUMIFS('Balance Sheet'!$E$53:$AF$53,'Balance Sheet'!$E$10:$AF$10,G$9) | H40: =SUMIFS('Balance Sheet'!$E$53:$AF$53,'Balance Sheet'!$E$10:$AF$10,H$9) | I40: =SUMIFS('Balance Sheet'!$E$53:$AF$53,'Balance Sheet'!$E$10:$AF$10,I$9) | J40: =SUMIFS('Balance Sheet'!$E$53:$AF$53,'Balance Sheet'!$E$10:$AF$10,J$9)
C41: Common stock | D41: =SUMIFS('Balance Sheet'!$E$55:$AF$55,'Balance Sheet'!$E$10:$AF$10,D$9) | E41: =SUMIFS('Balance Sheet'!$E$55:$AF$55,'Balance Sheet'!$E$10:$AF$10,E$9) | F41: =SUMIFS('Balance Sheet'!$E$55:$AF$55,'Balance Sheet'!$E$10:$AF$10,F$9) | G41: =SUMIFS('Balance Sheet'!$E$55:$AF$55,'Balance Sheet'!$E$10:$AF$10,G$9) | H41: =SUMIFS('Balance Sheet'!$E$55:$AF$55,'Balance Sheet'!$E$10:$AF$10,H$9) | I41: =SUMIFS('Balance Sheet'!$E$55:$AF$55,'Balance Sheet'!$E$10:$AF$10,I$9) | J41: =SUMIFS('Balance Sheet'!$E$55:$AF$55,'Balance Sheet'!$E$10:$AF$10,J$9)
C42: Additional paid-in capital | D42: =SUMIFS('Balance Sheet'!$E$56:$AF$56,'Balance Sheet'!$E$10:$AF$10,D$9) | E42: =SUMIFS('Balance Sheet'!$E$56:$AF$56,'Balance Sheet'!$E$10:$AF$10,E$9) | F42: =SUMIFS('Balance Sheet'!$E$56:$AF$56,'Balance Sheet'!$E$10:$AF$10,F$9) | G42: =SUMIFS('Balance Sheet'!$E$56:$AF$56,'Balance Sheet'!$E$10:$AF$10,G$9) | H42: =SUMIFS('Balance Sheet'!$E$56:$AF$56,'Balance Sheet'!$E$10:$AF$10,H$9) | I42: =SUMIFS('Balance Sheet'!$E$56:$AF$56,'Balance Sheet'!$E$10:$AF$10,I$9) | J42: =SUMIFS('Balance Sheet'!$E$56:$AF$56,'Balance Sheet'!$E$10:$AF$10,J$9)
C43: Treasury stock, at cost | D43: =SUMIFS('Balance Sheet'!$E$57:$AF$57,'Balance Sheet'!$E$10:$AF$10,D$9) | E43: =SUMIFS('Balance Sheet'!$E$57:$AF$57,'Balance Sheet'!$E$10:$AF$10,E$9) | F43: =SUMIFS('Balance Sheet'!$E$57:$AF$57,'Balance Sheet'!$E$10:$AF$10,F$9) | G43: =SUMIFS('Balance Sheet'!$E$57:$AF$57,'Balance Sheet'!$E$10:$AF$10,G$9) | H43: =SUMIFS('Balance Sheet'!$E$57:$AF$57,'Balance Sheet'!$E$10:$AF$10,H$9) | I43: =SUMIFS('Balance Sheet'!$E$57:$AF$57,'Balance Sheet'!$E$10:$AF$10,I$9) | J43: =SUMIFS('Balance Sheet'!$E$57:$AF$57,'Balance Sheet'!$E$10:$AF$10,J$9)
C44: Retained earnings | D44: =SUMIFS('Balance Sheet'!$E$58:$AF$58,'Balance Sheet'!$E$10:$AF$10,D$9) | E44: =SUMIFS('Balance Sheet'!$E$58:$AF$58,'Balance Sheet'!$E$10:$AF$10,E$9) | F44: =SUMIFS('Balance Sheet'!$E$58:$AF$58,'Balance Sheet'!$E$10:$AF$10,F$9) | G44: =SUMIFS('Balance Sheet'!$E$58:$AF$58,'Balance Sheet'!$E$10:$AF$10,G$9) | H44: =SUMIFS('Balance Sheet'!$E$58:$AF$58,'Balance Sheet'!$E$10:$AF$10,H$9) | I44: =SUMIFS('Balance Sheet'!$E$58:$AF$58,'Balance Sheet'!$E$10:$AF$10,I$9) | J44: =SUMIFS('Balance Sheet'!$E$58:$AF$58,'Balance Sheet'!$E$10:$AF$10,J$9)
C45: Accumulated other comprehensive loss | D45: =SUMIFS('Balance Sheet'!$E$59:$AF$59,'Balance Sheet'!$E$10:$AF$10,D$9) | E45: =SUMIFS('Balance Sheet'!$E$59:$AF$59,'Balance Sheet'!$E$10:$AF$10,E$9) | F45: =SUMIFS('Balance Sheet'!$E$59:$AF$59,'Balance Sheet'!$E$10:$AF$10,F$9) | G45: =SUMIFS('Balance Sheet'!$E$59:$AF$59,'Balance Sheet'!$E$10:$AF$10,G$9) | H45: =SUMIFS('Balance Sheet'!$E$59:$AF$59,'Balance Sheet'!$E$10:$AF$10,H$9) | I45: =SUMIFS('Balance Sheet'!$E$59:$AF$59,'Balance Sheet'!$E$10:$AF$10,I$9) | J45: =SUMIFS('Balance Sheet'!$E$59:$AF$59,'Balance Sheet'!$E$10:$AF$10,J$9)
C46: Xerox Holdings shareholders' equity | D46: =SUM(D41:D45) | E46: =SUM(E41:E45) | F46: =SUM(F41:F45) | G46: =SUM(G41:G45) | H46: =SUM(H41:H45) | I46: =SUM(I41:I45) | J46: =SUM(J41:J45)
C47: Noncontrolling interests | D47: =SUMIFS('Balance Sheet'!$E$63:$AF$63,'Balance Sheet'!$E$10:$AF$10,D$9) | E47: =SUMIFS('Balance Sheet'!$E$63:$AF$63,'Balance Sheet'!$E$10:$AF$10,E$9) | F47: =SUMIFS('Balance Sheet'!$E$63:$AF$63,'Balance Sheet'!$E$10:$AF$10,F$9) | G47: =SUMIFS('Balance Sheet'!$E$63:$AF$63,'Balance Sheet'!$E$10:$AF$10,G$9) | H47: =SUMIFS('Balance Sheet'!$E$63:$AF$63,'Balance Sheet'!$E$10:$AF$10,H$9) | I47: =SUMIFS('Balance Sheet'!$E$63:$AF$63,'Balance Sheet'!$E$10:$AF$10,I$9) | J47: =SUMIFS('Balance Sheet'!$E$63:$AF$63,'Balance Sheet'!$E$10:$AF$10,J$9)
C48: Total equity | D48: =D46+D47 | E48: =E46+E47 | F48: =F46+F47 | G48: =G46+G47 | H48: =H46+H47 | I48: =I46+I47 | J48: =J46+J47
C49: Total liabilities and equity | D49: =D37+D39+D40+D48 | E49: =E37+E39+E40+E48 | F49: =F37+F39+F40+F48 | G49: =G37+G39+G40+G48 | H49: =H37+H39+H40+H48 | I49: =I37+I39+I40+I48 | J49: =J37+J39+J40+J48
C50: Check | D50: =D49-D25 | E50: =E49-E25 | F50: =F49-F25 | G50: =G49-G25 | H50: =H49-H25 | I50: =I49-I25 | J50: =J49-J25
C53: Memo: Leverage
C54: Adj. EBITDA (LTM) | D54: ='Income Statement'!AA55 | E54: ='Income Statement'!AB55 | F54: ='Income Statement'!AC55 | G54: ='Income Statement'!AD55 | H54: ='Income Statement'!AE55 | I54: ='Income Statement'!AG55 | J54: ='Income Statement'!AH55
C55: Adj. EBITDA excl. IEEPA tariff benefit (LTM) | D55: ='Income Statement'!AA57 | E55: ='Income Statement'!AB57 | F55: ='Income Statement'!AC57 | G55: ='Income Statement'!AD57 | H55: ='Income Statement'!AE57 | I55: ='Income Statement'!AG57 | J55: ='Income Statement'!AH57
C56: Gross leverage | D56: =IFERROR((D27+D33)/D54,"n/a") | E56: =IFERROR((E27+E33)/E54,"n/a") | F56: =IFERROR((F27+F33)/F54,"n/a") | G56: =IFERROR((G27+G33)/G54,"n/a") | H56: =IFERROR((H27+H33)/H54,"n/a") | I56: =IFERROR((I27+I33)/I54,"n/a") | J56: =IFERROR((J27+J33)/J54,"n/a")
C57: Net leverage | D57: =IFERROR(((D27+D33)-D11)/D54,"n/a") | E57: =IFERROR(((E27+E33)-E11)/E54,"n/a") | F57: =IFERROR(((F27+F33)-F11)/F54,"n/a") | G57: =IFERROR(((G27+G33)-G11)/G54,"n/a") | H57: =IFERROR(((H27+H33)-H11)/H54,"n/a") | I57: =IFERROR(((I27+I33)-I11)/I54,"n/a") | J57: =IFERROR(((J27+J33)-J11)/J54,"n/a")
C58: Gross leverage excl. IEEPA | D58: =IFERROR((D27+D33)/D55,"n/a") | E58: =IFERROR((E27+E33)/E55,"n/a") | F58: =IFERROR((F27+F33)/F55,"n/a") | G58: =IFERROR((G27+G33)/G55,"n/a") | H58: =IFERROR((H27+H33)/H55,"n/a") | I58: =IFERROR((I27+I33)/I55,"n/a") | J58: =IFERROR((J27+J33)/J55,"n/a")
A59: x | B59: x | C59: Net leverage excl. IEEPA | D59: =IFERROR(((D27+D33)-D11)/D55,"n/a") | E59: =IFERROR(((E27+E33)-E11)/E55,"n/a") | F59: =IFERROR(((F27+F33)-F11)/F55,"n/a") | G59: =IFERROR(((G27+G33)-G11)/G55,"n/a") | H59: =IFERROR(((H27+H33)-H11)/H55,"n/a") | I59: =IFERROR(((I27+I33)-I11)/I55,"n/a") | J59: =IFERROR(((J27+J33)-J11)/J55,"n/a")
A60: End

Sheet Cash Flow Statement Output
A1: =C3 | B1: ='Cover Page'!A1
C3: Cash Flow Statement Summary | K3: Xerox Holdings Corporation
C4: All values in $ millions (USD)
A8: x | B8: x | C8: Cash Flow Statement Summary | D8: Fiscal Year | I8: LTM | J8: Quarter Ended
D10: 2021 | E10: 2022 | F10: 2023 | G10: 2024 | H10: 2025 | I10: LTM 2Q'26 | J10: 2Q'25 | K10: 2Q'26
C12: Net (loss) income | D12: =SUMIFS('Cash Flow Statement'!$E$14:$AI$14,'Cash Flow Statement'!$E$11:$AI$11,D$10) | E12: =SUMIFS('Cash Flow Statement'!$E$14:$AI$14,'Cash Flow Statement'!$E$11:$AI$11,E$10) | F12: =SUMIFS('Cash Flow Statement'!$E$14:$AI$14,'Cash Flow Statement'!$E$11:$AI$11,F$10) | G12: =SUMIFS('Cash Flow Statement'!$E$14:$AI$14,'Cash Flow Statement'!$E$11:$AI$11,G$10) | H12: =SUMIFS('Cash Flow Statement'!$E$14:$AI$14,'Cash Flow Statement'!$E$11:$AI$11,H$10) | I12: =SUMIFS('Cash Flow Statement'!$E$14:$AI$14,'Cash Flow Statement'!$E$11:$AI$11,I$10) | J12: =SUMIFS('Cash Flow Statement'!$E$14:$AI$14,'Cash Flow Statement'!$E$11:$AI$11,J$10) | K12: =SUMIFS('Cash Flow Statement'!$E$14:$AI$14,'Cash Flow Statement'!$E$11:$AI$11,K$10)
C13: Depreciation and amortization | D13: =SUMIFS('Cash Flow Statement'!$E$16:$AI$16,'Cash Flow Statement'!$E$11:$AI$11,D$10) | E13: =SUMIFS('Cash Flow Statement'!$E$16:$AI$16,'Cash Flow Statement'!$E$11:$AI$11,E$10) | F13: =SUMIFS('Cash Flow Statement'!$E$16:$AI$16,'Cash Flow Statement'!$E$11:$AI$11,F$10) | G13: =SUMIFS('Cash Flow Statement'!$E$16:$AI$16,'Cash Flow Statement'!$E$11:$AI$11,G$10) | H13: =SUMIFS('Cash Flow Statement'!$E$16:$AI$16,'Cash Flow Statement'!$E$11:$AI$11,H$10) | I13: =SUMIFS('Cash Flow Statement'!$E$16:$AI$16,'Cash Flow Statement'!$E$11:$AI$11,I$10) | J13: =SUMIFS('Cash Flow Statement'!$E$16:$AI$16,'Cash Flow Statement'!$E$11:$AI$11,J$10) | K13: =SUMIFS('Cash Flow Statement'!$E$16:$AI$16,'Cash Flow Statement'!$E$11:$AI$11,K$10)
C14: Goodwill impairment | D14: =SUMIFS('Cash Flow Statement'!$E$24:$AI$24,'Cash Flow Statement'!$E$11:$AI$11,D$10) | E14: =SUMIFS('Cash Flow Statement'!$E$24:$AI$24,'Cash Flow Statement'!$E$11:$AI$11,E$10) | F14: =SUMIFS('Cash Flow Statement'!$E$24:$AI$24,'Cash Flow Statement'!$E$11:$AI$11,F$10) | G14: =SUMIFS('Cash Flow Statement'!$E$24:$AI$24,'Cash Flow Statement'!$E$11:$AI$11,G$10) | H14: =SUMIFS('Cash Flow Statement'!$E$24:$AI$24,'Cash Flow Statement'!$E$11:$AI$11,H$10) | I14: =SUMIFS('Cash Flow Statement'!$E$24:$AI$24,'Cash Flow Statement'!$E$11:$AI$11,I$10) | J14: =SUMIFS('Cash Flow Statement'!$E$24:$AI$24,'Cash Flow Statement'!$E$11:$AI$11,J$10) | K14: =SUMIFS('Cash Flow Statement'!$E$24:$AI$24,'Cash Flow Statement'!$E$11:$AI$11,K$10)
C15: Stock-based compensation | D15: =SUMIFS('Cash Flow Statement'!$E$25:$AI$25,'Cash Flow Statement'!$E$11:$AI$11,D$10) | E15: =SUMIFS('Cash Flow Statement'!$E$25:$AI$25,'Cash Flow Statement'!$E$11:$AI$11,E$10) | F15: =SUMIFS('Cash Flow Statement'!$E$25:$AI$25,'Cash Flow Statement'!$E$11:$AI$11,F$10) | G15: =SUMIFS('Cash Flow Statement'!$E$25:$AI$25,'Cash Flow Statement'!$E$11:$AI$11,G$10) | H15: =SUMIFS('Cash Flow Statement'!$E$25:$AI$25,'Cash Flow Statement'!$E$11:$AI$11,H$10) | I15: =SUMIFS('Cash Flow Statement'!$E$25:$AI$25,'Cash Flow Statement'!$E$11:$AI$11,I$10) | J15: =SUMIFS('Cash Flow Statement'!$E$25:$AI$25,'Cash Flow Statement'!$E$11:$AI$11,J$10) | K15: =SUMIFS('Cash Flow Statement'!$E$25:$AI$25,'Cash Flow Statement'!$E$11:$AI$11,K$10)
C16: Provisions | D16: =SUMIFS('Cash Flow Statement'!$E$17:$AI$17,'Cash Flow Statement'!$E$11:$AI$11,D$10) | E16: =SUMIFS('Cash Flow Statement'!$E$17:$AI$17,'Cash Flow Statement'!$E$11:$AI$11,E$10) | F16: =SUMIFS('Cash Flow Statement'!$E$17:$AI$17,'Cash Flow Statement'!$E$11:$AI$11,F$10) | G16: =SUMIFS('Cash Flow Statement'!$E$17:$AI$17,'Cash Flow Statement'!$E$11:$AI$11,G$10) | H16: =SUMIFS('Cash Flow Statement'!$E$17:$AI$17,'Cash Flow Statement'!$E$11:$AI$11,H$10) | I16: =SUMIFS('Cash Flow Statement'!$E$17:$AI$17,'Cash Flow Statement'!$E$11:$AI$11,I$10) | J16: =SUMIFS('Cash Flow Statement'!$E$17:$AI$17,'Cash Flow Statement'!$E$11:$AI$11,J$10) | K16: =SUMIFS('Cash Flow Statement'!$E$17:$AI$17,'Cash Flow Statement'!$E$11:$AI$11,K$10)
C17: Restructuring and asset impairment charges | D17: =SUMIFS('Cash Flow Statement'!$E$26:$AI$26,'Cash Flow Statement'!$E$11:$AI$11,D$10) | E17: =SUMIFS('Cash Flow Statement'!$E$26:$AI$26,'Cash Flow Statement'!$E$11:$AI$11,E$10) | F17: =SUMIFS('Cash Flow Statement'!$E$26:$AI$26,'Cash Flow Statement'!$E$11:$AI$11,F$10) | G17: =SUMIFS('Cash Flow Statement'!$E$26:$AI$26,'Cash Flow Statement'!$E$11:$AI$11,G$10) | H17: =SUMIFS('Cash Flow Statement'!$E$26:$AI$26,'Cash Flow Statement'!$E$11:$AI$11,H$10) | I17: =SUMIFS('Cash Flow Statement'!$E$26:$AI$26,'Cash Flow Statement'!$E$11:$AI$11,I$10) | J17: =SUMIFS('Cash Flow Statement'!$E$26:$AI$26,'Cash Flow Statement'!$E$11:$AI$11,J$10) | K17: =SUMIFS('Cash Flow Statement'!$E$26:$AI$26,'Cash Flow Statement'!$E$11:$AI$11,K$10)
C18: Payments for restructurings | D18: =SUMIFS('Cash Flow Statement'!$E$27:$AI$27,'Cash Flow Statement'!$E$11:$AI$11,D$10) | E18: =SUMIFS('Cash Flow Statement'!$E$27:$AI$27,'Cash Flow Statement'!$E$11:$AI$11,E$10) | F18: =SUMIFS('Cash Flow Statement'!$E$27:$AI$27,'Cash Flow Statement'!$E$11:$AI$11,F$10) | G18: =SUMIFS('Cash Flow Statement'!$E$27:$AI$27,'Cash Flow Statement'!$E$11:$AI$11,G$10) | H18: =SUMIFS('Cash Flow Statement'!$E$27:$AI$27,'Cash Flow Statement'!$E$11:$AI$11,H$10) | I18: =SUMIFS('Cash Flow Statement'!$E$27:$AI$27,'Cash Flow Statement'!$E$11:$AI$11,I$10) | J18: =SUMIFS('Cash Flow Statement'!$E$27:$AI$27,'Cash Flow Statement'!$E$11:$AI$11,J$10) | K18: =SUMIFS('Cash Flow Statement'!$E$27:$AI$27,'Cash Flow Statement'!$E$11:$AI$11,K$10)
C19: Contributions to retirement plans | D19: =SUMIFS('Cash Flow Statement'!$E$29:$AI$29,'Cash Flow Statement'!$E$11:$AI$11,D$10) | E19: =SUMIFS('Cash Flow Statement'!$E$29:$AI$29,'Cash Flow Statement'!$E$11:$AI$11,E$10) | F19: =SUMIFS('Cash Flow Statement'!$E$29:$AI$29,'Cash Flow Statement'!$E$11:$AI$11,F$10) | G19: =SUMIFS('Cash Flow Statement'!$E$29:$AI$29,'Cash Flow Statement'!$E$11:$AI$11,G$10) | H19: =SUMIFS('Cash Flow Statement'!$E$29:$AI$29,'Cash Flow Statement'!$E$11:$AI$11,H$10) | I19: =SUMIFS('Cash Flow Statement'!$E$29:$AI$29,'Cash Flow Statement'!$E$11:$AI$11,I$10) | J19: =SUMIFS('Cash Flow Statement'!$E$29:$AI$29,'Cash Flow Statement'!$E$11:$AI$11,J$10) | K19: =SUMIFS('Cash Flow Statement'!$E$29:$AI$29,'Cash Flow Statement'!$E$11:$AI$11,K$10)
C20: Decrease (increase) in finance receivables | D20: =SUMIFS('Cash Flow Statement'!$E$34:$AI$34,'Cash Flow Statement'!$E$11:$AI$11,D$10) | E20: =SUMIFS('Cash Flow Statement'!$E$34:$AI$34,'Cash Flow Statement'!$E$11:$AI$11,E$10) | F20: =SUMIFS('Cash Flow Statement'!$E$34:$AI$34,'Cash Flow Statement'!$E$11:$AI$11,F$10) | G20: =SUMIFS('Cash Flow Statement'!$E$34:$AI$34,'Cash Flow Statement'!$E$11:$AI$11,G$10) | H20: =SUMIFS('Cash Flow Statement'!$E$34:$AI$34,'Cash Flow Statement'!$E$11:$AI$11,H$10) | I20: =SUMIFS('Cash Flow Statement'!$E$34:$AI$34,'Cash Flow Statement'!$E$11:$AI$11,I$10) | J20: =SUMIFS('Cash Flow Statement'!$E$34:$AI$34,'Cash Flow Statement'!$E$11:$AI$11,J$10) | K20: =SUMIFS('Cash Flow Statement'!$E$34:$AI$34,'Cash Flow Statement'!$E$11:$AI$11,K$10)
C21: Increase in equipment on operating leases | D21: =SUMIFS('Cash Flow Statement'!$E$33:$AI$33,'Cash Flow Statement'!$E$11:$AI$11,D$10) | E21: =SUMIFS('Cash Flow Statement'!$E$33:$AI$33,'Cash Flow Statement'!$E$11:$AI$11,E$10) | F21: =SUMIFS('Cash Flow Statement'!$E$33:$AI$33,'Cash Flow Statement'!$E$11:$AI$11,F$10) | G21: =SUMIFS('Cash Flow Statement'!$E$33:$AI$33,'Cash Flow Statement'!$E$11:$AI$11,G$10) | H21: =SUMIFS('Cash Flow Statement'!$E$33:$AI$33,'Cash Flow Statement'!$E$11:$AI$11,H$10) | I21: =SUMIFS('Cash Flow Statement'!$E$33:$AI$33,'Cash Flow Statement'!$E$11:$AI$11,I$10) | J21: =SUMIFS('Cash Flow Statement'!$E$33:$AI$33,'Cash Flow Statement'!$E$11:$AI$11,J$10) | K21: =SUMIFS('Cash Flow Statement'!$E$33:$AI$33,'Cash Flow Statement'!$E$11:$AI$11,K$10)
C22: Change in NWC | D22: =SUMIFS('Cash Flow Statement'!$E$46:$AI$46,'Cash Flow Statement'!$E$11:$AI$11,D$10) | E22: =SUMIFS('Cash Flow Statement'!$E$46:$AI$46,'Cash Flow Statement'!$E$11:$AI$11,E$10) | F22: =SUMIFS('Cash Flow Statement'!$E$46:$AI$46,'Cash Flow Statement'!$E$11:$AI$11,F$10) | G22: =SUMIFS('Cash Flow Statement'!$E$46:$AI$46,'Cash Flow Statement'!$E$11:$AI$11,G$10) | H22: =SUMIFS('Cash Flow Statement'!$E$46:$AI$46,'Cash Flow Statement'!$E$11:$AI$11,H$10) | I22: =SUMIFS('Cash Flow Statement'!$E$46:$AI$46,'Cash Flow Statement'!$E$11:$AI$11,I$10) | J22: =SUMIFS('Cash Flow Statement'!$E$46:$AI$46,'Cash Flow Statement'!$E$11:$AI$11,J$10) | K22: =SUMIFS('Cash Flow Statement'!$E$46:$AI$46,'Cash Flow Statement'!$E$11:$AI$11,K$10)
C23: Other operating activities | D23: =SUM(D24:D31) | E23: =SUM(E24:E31) | F23: =SUM(F24:F31) | G23: =SUM(G24:G31) | H23: =SUM(H24:H31) | I23: =SUM(I24:I31) | J23: =SUM(J24:J31) | K23: =SUM(K24:K31)
C24: Non-service retirement-related costs | D24: =SUMIFS('Cash Flow Statement'!$E$28:$AI$28,'Cash Flow Statement'!$E$11:$AI$11,D$10) | E24: =SUMIFS('Cash Flow Statement'!$E$28:$AI$28,'Cash Flow Statement'!$E$11:$AI$11,E$10) | F24: =SUMIFS('Cash Flow Statement'!$E$28:$AI$28,'Cash Flow Statement'!$E$11:$AI$11,F$10) | G24: =SUMIFS('Cash Flow Statement'!$E$28:$AI$28,'Cash Flow Statement'!$E$11:$AI$11,G$10) | H24: =SUMIFS('Cash Flow Statement'!$E$28:$AI$28,'Cash Flow Statement'!$E$11:$AI$11,H$10) | I24: =SUMIFS('Cash Flow Statement'!$E$28:$AI$28,'Cash Flow Statement'!$E$11:$AI$11,I$10) | J24: =SUMIFS('Cash Flow Statement'!$E$28:$AI$28,'Cash Flow Statement'!$E$11:$AI$11,J$10) | K24: =SUMIFS('Cash Flow Statement'!$E$28:$AI$28,'Cash Flow Statement'!$E$11:$AI$11,K$10)
C25: Net (gain) loss on sales of businesses and assets | D25: =SUMIFS('Cash Flow Statement'!$E$19:$AI$19,'Cash Flow Statement'!$E$11:$AI$11,D$10) | E25: =SUMIFS('Cash Flow Statement'!$E$19:$AI$19,'Cash Flow Statement'!$E$11:$AI$11,E$10) | F25: =SUMIFS('Cash Flow Statement'!$E$19:$AI$19,'Cash Flow Statement'!$E$11:$AI$11,F$10) | G25: =SUMIFS('Cash Flow Statement'!$E$19:$AI$19,'Cash Flow Statement'!$E$11:$AI$11,G$10) | H25: =SUMIFS('Cash Flow Statement'!$E$19:$AI$19,'Cash Flow Statement'!$E$11:$AI$11,H$10) | I25: =SUMIFS('Cash Flow Statement'!$E$19:$AI$19,'Cash Flow Statement'!$E$11:$AI$11,I$10) | J25: =SUMIFS('Cash Flow Statement'!$E$19:$AI$19,'Cash Flow Statement'!$E$11:$AI$11,J$10) | K25: =SUMIFS('Cash Flow Statement'!$E$19:$AI$19,'Cash Flow Statement'!$E$11:$AI$11,K$10)
C26: Net (gain) loss on early extinguishment of debt | D26: =SUMIFS('Cash Flow Statement'!$E$18:$AI$18,'Cash Flow Statement'!$E$11:$AI$11,D$10) | E26: =SUMIFS('Cash Flow Statement'!$E$18:$AI$18,'Cash Flow Statement'!$E$11:$AI$11,E$10) | F26: =SUMIFS('Cash Flow Statement'!$E$18:$AI$18,'Cash Flow Statement'!$E$11:$AI$11,F$10) | G26: =SUMIFS('Cash Flow Statement'!$E$18:$AI$18,'Cash Flow Statement'!$E$11:$AI$11,G$10) | H26: =SUMIFS('Cash Flow Statement'!$E$18:$AI$18,'Cash Flow Statement'!$E$11:$AI$11,H$10) | I26: =SUMIFS('Cash Flow Statement'!$E$18:$AI$18,'Cash Flow Statement'!$E$11:$AI$11,I$10) | J26: =SUMIFS('Cash Flow Statement'!$E$18:$AI$18,'Cash Flow Statement'!$E$11:$AI$11,J$10) | K26: =SUMIFS('Cash Flow Statement'!$E$18:$AI$18,'Cash Flow Statement'!$E$11:$AI$11,K$10)
C27: Lexmark inventory purchase accounting adjustment, noncash | D27: =SUMIFS('Cash Flow Statement'!$E$20:$AI$20,'Cash Flow Statement'!$E$11:$AI$11,D$10) | E27: =SUMIFS('Cash Flow Statement'!$E$20:$AI$20,'Cash Flow Statement'!$E$11:$AI$11,E$10) | F27: =SUMIFS('Cash Flow Statement'!$E$20:$AI$20,'Cash Flow Statement'!$E$11:$AI$11,F$10) | G27: =SUMIFS('Cash Flow Statement'!$E$20:$AI$20,'Cash Flow Statement'!$E$11:$AI$11,G$10) | H27: =SUMIFS('Cash Flow Statement'!$E$20:$AI$20,'Cash Flow Statement'!$E$11:$AI$11,H$10) | I27: =SUMIFS('Cash Flow Statement'!$E$20:$AI$20,'Cash Flow Statement'!$E$11:$AI$11,I$10) | J27: =SUMIFS('Cash Flow Statement'!$E$20:$AI$20,'Cash Flow Statement'!$E$11:$AI$11,J$10) | K27: =SUMIFS('Cash Flow Statement'!$E$20:$AI$20,'Cash Flow Statement'!$E$11:$AI$11,K$10)
C28: Effective settlement of pre-existing Lexmark relationship | D28: =SUMIFS('Cash Flow Statement'!$E$21:$AI$21,'Cash Flow Statement'!$E$11:$AI$11,D$10) | E28: =SUMIFS('Cash Flow Statement'!$E$21:$AI$21,'Cash Flow Statement'!$E$11:$AI$11,E$10) | F28: =SUMIFS('Cash Flow Statement'!$E$21:$AI$21,'Cash Flow Statement'!$E$11:$AI$11,F$10) | G28: =SUMIFS('Cash Flow Statement'!$E$21:$AI$21,'Cash Flow Statement'!$E$11:$AI$11,G$10) | H28: =SUMIFS('Cash Flow Statement'!$E$21:$AI$21,'Cash Flow Statement'!$E$11:$AI$11,H$10) | I28: =SUMIFS('Cash Flow Statement'!$E$21:$AI$21,'Cash Flow Statement'!$E$11:$AI$11,I$10) | J28: =SUMIFS('Cash Flow Statement'!$E$21:$AI$21,'Cash Flow Statement'!$E$11:$AI$11,J$10) | K28: =SUMIFS('Cash Flow Statement'!$E$21:$AI$21,'Cash Flow Statement'!$E$11:$AI$11,K$10)
C29: Divestitures | D29: =SUMIFS('Cash Flow Statement'!$E$22:$AI$22,'Cash Flow Statement'!$E$11:$AI$11,D$10) | E29: =SUMIFS('Cash Flow Statement'!$E$22:$AI$22,'Cash Flow Statement'!$E$11:$AI$11,E$10) | F29: =SUMIFS('Cash Flow Statement'!$E$22:$AI$22,'Cash Flow Statement'!$E$11:$AI$11,F$10) | G29: =SUMIFS('Cash Flow Statement'!$E$22:$AI$22,'Cash Flow Statement'!$E$11:$AI$11,G$10) | H29: =SUMIFS('Cash Flow Statement'!$E$22:$AI$22,'Cash Flow Statement'!$E$11:$AI$11,H$10) | I29: =SUMIFS('Cash Flow Statement'!$E$22:$AI$22,'Cash Flow Statement'!$E$11:$AI$11,I$10) | J29: =SUMIFS('Cash Flow Statement'!$E$22:$AI$22,'Cash Flow Statement'!$E$11:$AI$11,J$10) | K29: =SUMIFS('Cash Flow Statement'!$E$22:$AI$22,'Cash Flow Statement'!$E$11:$AI$11,K$10)
C30: PARC donation | D30: =SUMIFS('Cash Flow Statement'!$E$23:$AI$23,'Cash Flow Statement'!$E$11:$AI$11,D$10) | E30: =SUMIFS('Cash Flow Statement'!$E$23:$AI$23,'Cash Flow Statement'!$E$11:$AI$11,E$10) | F30: =SUMIFS('Cash Flow Statement'!$E$23:$AI$23,'Cash Flow Statement'!$E$11:$AI$11,F$10) | G30: =SUMIFS('Cash Flow Statement'!$E$23:$AI$23,'Cash Flow Statement'!$E$11:$AI$11,G$10) | H30: =SUMIFS('Cash Flow Statement'!$E$23:$AI$23,'Cash Flow Statement'!$E$11:$AI$11,H$10) | I30: =SUMIFS('Cash Flow Statement'!$E$23:$AI$23,'Cash Flow Statement'!$E$11:$AI$11,I$10) | J30: =SUMIFS('Cash Flow Statement'!$E$23:$AI$23,'Cash Flow Statement'!$E$11:$AI$11,J$10) | K30: =SUMIFS('Cash Flow Statement'!$E$23:$AI$23,'Cash Flow Statement'!$E$11:$AI$11,K$10)
C31: Other operating, net | D31: =SUMIFS('Cash Flow Statement'!$E$41:$AI$41,'Cash Flow Statement'!$E$11:$AI$11,D$10) | E31: =SUMIFS('Cash Flow Statement'!$E$41:$AI$41,'Cash Flow Statement'!$E$11:$AI$11,E$10) | F31: =SUMIFS('Cash Flow Statement'!$E$41:$AI$41,'Cash Flow Statement'!$E$11:$AI$11,F$10) | G31: =SUMIFS('Cash Flow Statement'!$E$41:$AI$41,'Cash Flow Statement'!$E$11:$AI$11,G$10) | H31: =SUMIFS('Cash Flow Statement'!$E$41:$AI$41,'Cash Flow Statement'!$E$11:$AI$11,H$10) | I31: =SUMIFS('Cash Flow Statement'!$E$41:$AI$41,'Cash Flow Statement'!$E$11:$AI$11,I$10) | J31: =SUMIFS('Cash Flow Statement'!$E$41:$AI$41,'Cash Flow Statement'!$E$11:$AI$11,J$10) | K31: =SUMIFS('Cash Flow Statement'!$E$41:$AI$41,'Cash Flow Statement'!$E$11:$AI$11,K$10)
C32: Cash Flow from Operations | D32: =SUM(D12:D23) | E32: =SUM(E12:E23) | F32: =SUM(F12:F23) | G32: =SUM(G12:G23) | H32: =SUM(H12:H23) | I32: =SUM(I12:I23) | J32: =SUM(J12:J23) | K32: =SUM(K12:K23)
C33: CFO | D33: =SUMIFS('Cash Flow Statement'!$E$43:$AI$43,'Cash Flow Statement'!$E$11:$AI$11,D$10) | E33: =SUMIFS('Cash Flow Statement'!$E$43:$AI$43,'Cash Flow Statement'!$E$11:$AI$11,E$10) | F33: =SUMIFS('Cash Flow Statement'!$E$43:$AI$43,'Cash Flow Statement'!$E$11:$AI$11,F$10) | G33: =SUMIFS('Cash Flow Statement'!$E$43:$AI$43,'Cash Flow Statement'!$E$11:$AI$11,G$10) | H33: =SUMIFS('Cash Flow Statement'!$E$43:$AI$43,'Cash Flow Statement'!$E$11:$AI$11,H$10) | I33: =SUMIFS('Cash Flow Statement'!$E$43:$AI$43,'Cash Flow Statement'!$E$11:$AI$11,I$10) | J33: =SUMIFS('Cash Flow Statement'!$E$43:$AI$43,'Cash Flow Statement'!$E$11:$AI$11,J$10) | K33: =SUMIFS('Cash Flow Statement'!$E$43:$AI$43,'Cash Flow Statement'!$E$11:$AI$11,K$10)
C34: Check | D34: =D32-D33 | E34: =E32-E33 | F34: =F32-F33 | G34: =G32-G33 | H34: =H32-H33 | I34: =I32-I33 | J34: =J32-J33 | K34: =K32-K33
C36: Capital expenditures | D36: =SUMIFS('Cash Flow Statement'!$E$49:$AI$49,'Cash Flow Statement'!$E$11:$AI$11,D$10) | E36: =SUMIFS('Cash Flow Statement'!$E$49:$AI$49,'Cash Flow Statement'!$E$11:$AI$11,E$10) | F36: =SUMIFS('Cash Flow Statement'!$E$49:$AI$49,'Cash Flow Statement'!$E$11:$AI$11,F$10) | G36: =SUMIFS('Cash Flow Statement'!$E$49:$AI$49,'Cash Flow Statement'!$E$11:$AI$11,G$10) | H36: =SUMIFS('Cash Flow Statement'!$E$49:$AI$49,'Cash Flow Statement'!$E$11:$AI$11,H$10) | I36: =SUMIFS('Cash Flow Statement'!$E$49:$AI$49,'Cash Flow Statement'!$E$11:$AI$11,I$10) | J36: =SUMIFS('Cash Flow Statement'!$E$49:$AI$49,'Cash Flow Statement'!$E$11:$AI$11,J$10) | K36: =SUMIFS('Cash Flow Statement'!$E$49:$AI$49,'Cash Flow Statement'!$E$11:$AI$11,K$10)
C37: Acquisitions, net of cash acquired | D37: =SUMIFS('Cash Flow Statement'!$E$51:$AI$51,'Cash Flow Statement'!$E$11:$AI$11,D$10) | E37: =SUMIFS('Cash Flow Statement'!$E$51:$AI$51,'Cash Flow Statement'!$E$11:$AI$11,E$10) | F37: =SUMIFS('Cash Flow Statement'!$E$51:$AI$51,'Cash Flow Statement'!$E$11:$AI$11,F$10) | G37: =SUMIFS('Cash Flow Statement'!$E$51:$AI$51,'Cash Flow Statement'!$E$11:$AI$11,G$10) | H37: =SUMIFS('Cash Flow Statement'!$E$51:$AI$51,'Cash Flow Statement'!$E$11:$AI$11,H$10) | I37: =SUMIFS('Cash Flow Statement'!$E$51:$AI$51,'Cash Flow Statement'!$E$11:$AI$11,I$10) | J37: =SUMIFS('Cash Flow Statement'!$E$51:$AI$51,'Cash Flow Statement'!$E$11:$AI$11,J$10) | K37: =SUMIFS('Cash Flow Statement'!$E$51:$AI$51,'Cash Flow Statement'!$E$11:$AI$11,K$10)
C38: Proceeds from sales of businesses and assets | D38: =SUMIFS('Cash Flow Statement'!$E$50:$AI$50,'Cash Flow Statement'!$E$11:$AI$11,D$10) | E38: =SUMIFS('Cash Flow Statement'!$E$50:$AI$50,'Cash Flow Statement'!$E$11:$AI$11,E$10) | F38: =SUMIFS('Cash Flow Statement'!$E$50:$AI$50,'Cash Flow Statement'!$E$11:$AI$11,F$10) | G38: =SUMIFS('Cash Flow Statement'!$E$50:$AI$50,'Cash Flow Statement'!$E$11:$AI$11,G$10) | H38: =SUMIFS('Cash Flow Statement'!$E$50:$AI$50,'Cash Flow Statement'!$E$11:$AI$11,H$10) | I38: =SUMIFS('Cash Flow Statement'!$E$50:$AI$50,'Cash Flow Statement'!$E$11:$AI$11,I$10) | J38: =SUMIFS('Cash Flow Statement'!$E$50:$AI$50,'Cash Flow Statement'!$E$11:$AI$11,J$10) | K38: =SUMIFS('Cash Flow Statement'!$E$50:$AI$50,'Cash Flow Statement'!$E$11:$AI$11,K$10)
C39: Other investing activities | D39: =SUM(D40:D40) | E39: =SUM(E40:E40) | F39: =SUM(F40:F40) | G39: =SUM(G40:G40) | H39: =SUM(H40:H40) | I39: =SUM(I40:I40) | J39: =SUM(J40:J40) | K39: =SUM(K40:K40)
C40: Other investing, net | D40: =SUMIFS('Cash Flow Statement'!$E$52:$AI$52,'Cash Flow Statement'!$E$11:$AI$11,D$10) | E40: =SUMIFS('Cash Flow Statement'!$E$52:$AI$52,'Cash Flow Statement'!$E$11:$AI$11,E$10) | F40: =SUMIFS('Cash Flow Statement'!$E$52:$AI$52,'Cash Flow Statement'!$E$11:$AI$11,F$10) | G40: =SUMIFS('Cash Flow Statement'!$E$52:$AI$52,'Cash Flow Statement'!$E$11:$AI$11,G$10) | H40: =SUMIFS('Cash Flow Statement'!$E$52:$AI$52,'Cash Flow Statement'!$E$11:$AI$11,H$10) | I40: =SUMIFS('Cash Flow Statement'!$E$52:$AI$52,'Cash Flow Statement'!$E$11:$AI$11,I$10) | J40: =SUMIFS('Cash Flow Statement'!$E$52:$AI$52,'Cash Flow Statement'!$E$11:$AI$11,J$10) | K40: =SUMIFS('Cash Flow Statement'!$E$52:$AI$52,'Cash Flow Statement'!$E$11:$AI$11,K$10)
C41: Cash Flow from Investing | D41: =SUM(D36:D39) | E41: =SUM(E36:E39) | F41: =SUM(F36:F39) | G41: =SUM(G36:G39) | H41: =SUM(H36:H39) | I41: =SUM(I36:I39) | J41: =SUM(J36:J39) | K41: =SUM(K36:K39)
C42: CFI | D42: =SUMIFS('Cash Flow Statement'!$E$54:$AI$54,'Cash Flow Statement'!$E$11:$AI$11,D$10) | E42: =SUMIFS('Cash Flow Statement'!$E$54:$AI$54,'Cash Flow Statement'!$E$11:$AI$11,E$10) | F42: =SUMIFS('Cash Flow Statement'!$E$54:$AI$54,'Cash Flow Statement'!$E$11:$AI$11,F$10) | G42: =SUMIFS('Cash Flow Statement'!$E$54:$AI$54,'Cash Flow Statement'!$E$11:$AI$11,G$10) | H42: =SUMIFS('Cash Flow Statement'!$E$54:$AI$54,'Cash Flow Statement'!$E$11:$AI$11,H$10) | I42: =SUMIFS('Cash Flow Statement'!$E$54:$AI$54,'Cash Flow Statement'!$E$11:$AI$11,I$10) | J42: =SUMIFS('Cash Flow Statement'!$E$54:$AI$54,'Cash Flow Statement'!$E$11:$AI$11,J$10) | K42: =SUMIFS('Cash Flow Statement'!$E$54:$AI$54,'Cash Flow Statement'!$E$11:$AI$11,K$10)
C43: Check | D43: =D41-D42 | E43: =E41-E42 | F43: =F41-F42 | G43: =G41-G42 | H43: =H41-H42 | I43: =I41-I42 | J43: =J41-J42 | K43: =K41-K42
C45: Proceeds from issuance of long-term debt | D45: =SUMIFS('Cash Flow Statement'!$E$59:$AI$59,'Cash Flow Statement'!$E$11:$AI$11,D$10) | E45: =SUMIFS('Cash Flow Statement'!$E$59:$AI$59,'Cash Flow Statement'!$E$11:$AI$11,E$10) | F45: =SUMIFS('Cash Flow Statement'!$E$59:$AI$59,'Cash Flow Statement'!$E$11:$AI$11,F$10) | G45: =SUMIFS('Cash Flow Statement'!$E$59:$AI$59,'Cash Flow Statement'!$E$11:$AI$11,G$10) | H45: =SUMIFS('Cash Flow Statement'!$E$59:$AI$59,'Cash Flow Statement'!$E$11:$AI$11,H$10) | I45: =SUMIFS('Cash Flow Statement'!$E$59:$AI$59,'Cash Flow Statement'!$E$11:$AI$11,I$10) | J45: =SUMIFS('Cash Flow Statement'!$E$59:$AI$59,'Cash Flow Statement'!$E$11:$AI$11,J$10) | K45: =SUMIFS('Cash Flow Statement'!$E$59:$AI$59,'Cash Flow Statement'!$E$11:$AI$11,K$10)
C46: Payments on long-term debt | D46: =SUMIFS('Cash Flow Statement'!$E$60:$AI$60,'Cash Flow Statement'!$E$11:$AI$11,D$10) | E46: =SUMIFS('Cash Flow Statement'!$E$60:$AI$60,'Cash Flow Statement'!$E$11:$AI$11,E$10) | F46: =SUMIFS('Cash Flow Statement'!$E$60:$AI$60,'Cash Flow Statement'!$E$11:$AI$11,F$10) | G46: =SUMIFS('Cash Flow Statement'!$E$60:$AI$60,'Cash Flow Statement'!$E$11:$AI$11,G$10) | H46: =SUMIFS('Cash Flow Statement'!$E$60:$AI$60,'Cash Flow Statement'!$E$11:$AI$11,H$10) | I46: =SUMIFS('Cash Flow Statement'!$E$60:$AI$60,'Cash Flow Statement'!$E$11:$AI$11,I$10) | J46: =SUMIFS('Cash Flow Statement'!$E$60:$AI$60,'Cash Flow Statement'!$E$11:$AI$11,J$10) | K46: =SUMIFS('Cash Flow Statement'!$E$60:$AI$60,'Cash Flow Statement'!$E$11:$AI$11,K$10)
C47: Net proceeds (payments) on short-term debt | D47: =SUMIFS('Cash Flow Statement'!$E$58:$AI$58,'Cash Flow Statement'!$E$11:$AI$11,D$10) | E47: =SUMIFS('Cash Flow Statement'!$E$58:$AI$58,'Cash Flow Statement'!$E$11:$AI$11,E$10) | F47: =SUMIFS('Cash Flow Statement'!$E$58:$AI$58,'Cash Flow Statement'!$E$11:$AI$11,F$10) | G47: =SUMIFS('Cash Flow Statement'!$E$58:$AI$58,'Cash Flow Statement'!$E$11:$AI$11,G$10) | H47: =SUMIFS('Cash Flow Statement'!$E$58:$AI$58,'Cash Flow Statement'!$E$11:$AI$11,H$10) | I47: =SUMIFS('Cash Flow Statement'!$E$58:$AI$58,'Cash Flow Statement'!$E$11:$AI$11,I$10) | J47: =SUMIFS('Cash Flow Statement'!$E$58:$AI$58,'Cash Flow Statement'!$E$11:$AI$11,J$10) | K47: =SUMIFS('Cash Flow Statement'!$E$58:$AI$58,'Cash Flow Statement'!$E$11:$AI$11,K$10)
C48: Dividends | D48: =SUMIFS('Cash Flow Statement'!$E$63:$AI$63,'Cash Flow Statement'!$E$11:$AI$11,D$10) | E48: =SUMIFS('Cash Flow Statement'!$E$63:$AI$63,'Cash Flow Statement'!$E$11:$AI$11,E$10) | F48: =SUMIFS('Cash Flow Statement'!$E$63:$AI$63,'Cash Flow Statement'!$E$11:$AI$11,F$10) | G48: =SUMIFS('Cash Flow Statement'!$E$63:$AI$63,'Cash Flow Statement'!$E$11:$AI$11,G$10) | H48: =SUMIFS('Cash Flow Statement'!$E$63:$AI$63,'Cash Flow Statement'!$E$11:$AI$11,H$10) | I48: =SUMIFS('Cash Flow Statement'!$E$63:$AI$63,'Cash Flow Statement'!$E$11:$AI$11,I$10) | J48: =SUMIFS('Cash Flow Statement'!$E$63:$AI$63,'Cash Flow Statement'!$E$11:$AI$11,J$10) | K48: =SUMIFS('Cash Flow Statement'!$E$63:$AI$63,'Cash Flow Statement'!$E$11:$AI$11,K$10)
C49: Share repurchases (treasury stock, incl. fees) | D49: =SUMIFS('Cash Flow Statement'!$E$64:$AI$64,'Cash Flow Statement'!$E$11:$AI$11,D$10) | E49: =SUMIFS('Cash Flow Statement'!$E$64:$AI$64,'Cash Flow Statement'!$E$11:$AI$11,E$10) | F49: =SUMIFS('Cash Flow Statement'!$E$64:$AI$64,'Cash Flow Statement'!$E$11:$AI$11,F$10) | G49: =SUMIFS('Cash Flow Statement'!$E$64:$AI$64,'Cash Flow Statement'!$E$11:$AI$11,G$10) | H49: =SUMIFS('Cash Flow Statement'!$E$64:$AI$64,'Cash Flow Statement'!$E$11:$AI$11,H$10) | I49: =SUMIFS('Cash Flow Statement'!$E$64:$AI$64,'Cash Flow Statement'!$E$11:$AI$11,I$10) | J49: =SUMIFS('Cash Flow Statement'!$E$64:$AI$64,'Cash Flow Statement'!$E$11:$AI$11,J$10) | K49: =SUMIFS('Cash Flow Statement'!$E$64:$AI$64,'Cash Flow Statement'!$E$11:$AI$11,K$10)
C50: Other financing activities | D50: =SUM(D51:D53) | E50: =SUM(E51:E53) | F50: =SUM(F51:F53) | G50: =SUM(G51:G53) | H50: =SUM(H51:H53) | I50: =SUM(I51:I53) | J50: =SUM(J51:J53) | K50: =SUM(K51:K53)
C51: Tariff receivables monetization | D51: =SUMIFS('Cash Flow Statement'!$E$61:$AI$61,'Cash Flow Statement'!$E$11:$AI$11,D$10) | E51: =SUMIFS('Cash Flow Statement'!$E$61:$AI$61,'Cash Flow Statement'!$E$11:$AI$11,E$10) | F51: =SUMIFS('Cash Flow Statement'!$E$61:$AI$61,'Cash Flow Statement'!$E$11:$AI$11,F$10) | G51: =SUMIFS('Cash Flow Statement'!$E$61:$AI$61,'Cash Flow Statement'!$E$11:$AI$11,G$10) | H51: =SUMIFS('Cash Flow Statement'!$E$61:$AI$61,'Cash Flow Statement'!$E$11:$AI$11,H$10) | I51: =SUMIFS('Cash Flow Statement'!$E$61:$AI$61,'Cash Flow Statement'!$E$11:$AI$11,I$10) | J51: =SUMIFS('Cash Flow Statement'!$E$61:$AI$61,'Cash Flow Statement'!$E$11:$AI$11,J$10) | K51: =SUMIFS('Cash Flow Statement'!$E$61:$AI$61,'Cash Flow Statement'!$E$11:$AI$11,K$10)
C52: Purchases of capped calls | D52: =SUMIFS('Cash Flow Statement'!$E$62:$AI$62,'Cash Flow Statement'!$E$11:$AI$11,D$10) | E52: =SUMIFS('Cash Flow Statement'!$E$62:$AI$62,'Cash Flow Statement'!$E$11:$AI$11,E$10) | F52: =SUMIFS('Cash Flow Statement'!$E$62:$AI$62,'Cash Flow Statement'!$E$11:$AI$11,F$10) | G52: =SUMIFS('Cash Flow Statement'!$E$62:$AI$62,'Cash Flow Statement'!$E$11:$AI$11,G$10) | H52: =SUMIFS('Cash Flow Statement'!$E$62:$AI$62,'Cash Flow Statement'!$E$11:$AI$11,H$10) | I52: =SUMIFS('Cash Flow Statement'!$E$62:$AI$62,'Cash Flow Statement'!$E$11:$AI$11,I$10) | J52: =SUMIFS('Cash Flow Statement'!$E$62:$AI$62,'Cash Flow Statement'!$E$11:$AI$11,J$10) | K52: =SUMIFS('Cash Flow Statement'!$E$62:$AI$62,'Cash Flow Statement'!$E$11:$AI$11,K$10)
C53: Other financing, net | D53: =SUMIFS('Cash Flow Statement'!$E$65:$AI$65,'Cash Flow Statement'!$E$11:$AI$11,D$10) | E53: =SUMIFS('Cash Flow Statement'!$E$65:$AI$65,'Cash Flow Statement'!$E$11:$AI$11,E$10) | F53: =SUMIFS('Cash Flow Statement'!$E$65:$AI$65,'Cash Flow Statement'!$E$11:$AI$11,F$10) | G53: =SUMIFS('Cash Flow Statement'!$E$65:$AI$65,'Cash Flow Statement'!$E$11:$AI$11,G$10) | H53: =SUMIFS('Cash Flow Statement'!$E$65:$AI$65,'Cash Flow Statement'!$E$11:$AI$11,H$10) | I53: =SUMIFS('Cash Flow Statement'!$E$65:$AI$65,'Cash Flow Statement'!$E$11:$AI$11,I$10) | J53: =SUMIFS('Cash Flow Statement'!$E$65:$AI$65,'Cash Flow Statement'!$E$11:$AI$11,J$10) | K53: =SUMIFS('Cash Flow Statement'!$E$65:$AI$65,'Cash Flow Statement'!$E$11:$AI$11,K$10)
C54: Cash Flow from Financing | D54: =SUM(D45:D50) | E54: =SUM(E45:E50) | F54: =SUM(F45:F50) | G54: =SUM(G45:G50) | H54: =SUM(H45:H50) | I54: =SUM(I45:I50) | J54: =SUM(J45:J50) | K54: =SUM(K45:K50)
C55: CFF | D55: =SUMIFS('Cash Flow Statement'!$E$67:$AI$67,'Cash Flow Statement'!$E$11:$AI$11,D$10) | E55: =SUMIFS('Cash Flow Statement'!$E$67:$AI$67,'Cash Flow Statement'!$E$11:$AI$11,E$10) | F55: =SUMIFS('Cash Flow Statement'!$E$67:$AI$67,'Cash Flow Statement'!$E$11:$AI$11,F$10) | G55: =SUMIFS('Cash Flow Statement'!$E$67:$AI$67,'Cash Flow Statement'!$E$11:$AI$11,G$10) | H55: =SUMIFS('Cash Flow Statement'!$E$67:$AI$67,'Cash Flow Statement'!$E$11:$AI$11,H$10) | I55: =SUMIFS('Cash Flow Statement'!$E$67:$AI$67,'Cash Flow Statement'!$E$11:$AI$11,I$10) | J55: =SUMIFS('Cash Flow Statement'!$E$67:$AI$67,'Cash Flow Statement'!$E$11:$AI$11,J$10) | K55: =SUMIFS('Cash Flow Statement'!$E$67:$AI$67,'Cash Flow Statement'!$E$11:$AI$11,K$10)
C56: Check | D56: =D54-D55 | E56: =E54-E55 | F56: =F54-F55 | G56: =G54-G55 | H56: =H54-H55 | I56: =I54-I55 | J56: =J54-J55 | K56: =K54-K55
C57: Effect of foreign currency exchange rates on cash | D57: =SUMIFS('Cash Flow Statement'!$E$69:$AI$69,'Cash Flow Statement'!$E$11:$AI$11,D$10) | E57: =SUMIFS('Cash Flow Statement'!$E$69:$AI$69,'Cash Flow Statement'!$E$11:$AI$11,E$10) | F57: =SUMIFS('Cash Flow Statement'!$E$69:$AI$69,'Cash Flow Statement'!$E$11:$AI$11,F$10) | G57: =SUMIFS('Cash Flow Statement'!$E$69:$AI$69,'Cash Flow Statement'!$E$11:$AI$11,G$10) | H57: =SUMIFS('Cash Flow Statement'!$E$69:$AI$69,'Cash Flow Statement'!$E$11:$AI$11,H$10) | I57: =SUMIFS('Cash Flow Statement'!$E$69:$AI$69,'Cash Flow Statement'!$E$11:$AI$11,I$10) | J57: =SUMIFS('Cash Flow Statement'!$E$69:$AI$69,'Cash Flow Statement'!$E$11:$AI$11,J$10) | K57: =SUMIFS('Cash Flow Statement'!$E$69:$AI$69,'Cash Flow Statement'!$E$11:$AI$11,K$10)
C58: Net increase (decrease) in cash | D58: =D32+D41+D54+D57 | E58: =E32+E41+E54+E57 | F58: =F32+F41+F54+F57 | G58: =G32+G41+G54+G57 | H58: =H32+H41+H54+H57 | I58: =I32+I41+I54+I57 | J58: =J32+J41+J54+J57 | K58: =K32+K41+K54+K57
C59: Cash at beginning of period | D59: =SUMIFS('Cash Flow Statement'!$E$73:$AI$73,'Cash Flow Statement'!$E$11:$AI$11,D$10) | E59: =D60 | F59: =E60 | G59: =F60 | H59: =G60 | I59: =SUMIFS('Cash Flow Statement'!$E$73:$AI$73,'Cash Flow Statement'!$E$11:$AI$11,I$10) | J59: =SUMIFS('Cash Flow Statement'!$E$73:$AI$73,'Cash Flow Statement'!$E$11:$AI$11,J$10) | K59: =SUMIFS('Cash Flow Statement'!$E$73:$AI$73,'Cash Flow Statement'!$E$11:$AI$11,K$10)
C60: Cash at end of period | D60: =SUM(D58:D59) | E60: =SUM(E58:E59) | F60: =SUM(F58:F59) | G60: =SUM(G58:G59) | H60: =SUM(H58:H59) | I60: =SUM(I58:I59) | J60: =SUM(J58:J59) | K60: =SUM(K58:K59)
A62: x | B62: x | C62: Memo: Free Cash Flow | D62: =D32+D36 | E62: =E32+E36 | F62: =F32+F36 | G62: =G32+G36 | H62: =H32+H36 | I62: =I32+I36 | J62: =J32+J36 | K62: =K32+K36
A63: End

Sheet Credit Analysis >
A1: Credit Analysis > | B1: ='Cover Page'!A1

Sheet NWC
A1: =C3 | B1: ='Cover Page'!A1
C3: Net Working Capital Analysis | U3: Xerox Holdings Corporation
C4: All values in $ millions (USD)
A8: x | B8: x | C8: Net Working Capital | F8: Fiscal Year | K8: Quarter Ended | N8: Change in NWC | Q8: Fiscal Year
F10: 2021 | G10: =F10+1 | H10: =G10+1 | I10: =H10+1 | J10: =I10+1 | K10: 1Q'26 | L10: 2Q'26 | Q10: 2021 | R10: =Q10+1 | S10: =R10+1 | T10: =S10+1 | U10: =T10+1
C11: Accounts receivable, net | F11: =SUMIFS('Balance Sheet'!14:14,'Balance Sheet'!$10:$10,NWC!F$10) | G11: =SUMIFS('Balance Sheet'!14:14,'Balance Sheet'!$10:$10,NWC!G$10) | H11: =SUMIFS('Balance Sheet'!14:14,'Balance Sheet'!$10:$10,NWC!H$10) | I11: =SUMIFS('Balance Sheet'!14:14,'Balance Sheet'!$10:$10,NWC!I$10) | J11: =SUMIFS('Balance Sheet'!14:14,'Balance Sheet'!$10:$10,NWC!J$10) | K11: =SUMIFS('Balance Sheet'!14:14,'Balance Sheet'!$10:$10,NWC!K$10) | L11: =SUMIFS('Balance Sheet'!14:14,'Balance Sheet'!$10:$10,NWC!L$10) | N11: =C11 | R11: =G11-F11 | S11: =H11-G11 | T11: =I11-H11 | U11: =J11-I11
C12: Billed finance receivables | F12: =SUMIFS('Balance Sheet'!15:15,'Balance Sheet'!$10:$10,NWC!F$10) | G12: =SUMIFS('Balance Sheet'!15:15,'Balance Sheet'!$10:$10,NWC!G$10) | H12: =SUMIFS('Balance Sheet'!15:15,'Balance Sheet'!$10:$10,NWC!H$10) | I12: =SUMIFS('Balance Sheet'!15:15,'Balance Sheet'!$10:$10,NWC!I$10) | J12: =SUMIFS('Balance Sheet'!15:15,'Balance Sheet'!$10:$10,NWC!J$10) | K12: =SUMIFS('Balance Sheet'!15:15,'Balance Sheet'!$10:$10,NWC!K$10) | L12: =SUMIFS('Balance Sheet'!15:15,'Balance Sheet'!$10:$10,NWC!L$10) | N12: =C12 | R12: =G12-F12 | S12: =H12-G12 | T12: =I12-H12 | U12: =J12-I12
C13: Inventories | F13: =SUMIFS('Balance Sheet'!17:17,'Balance Sheet'!$10:$10,NWC!F$10) | G13: =SUMIFS('Balance Sheet'!17:17,'Balance Sheet'!$10:$10,NWC!G$10) | H13: =SUMIFS('Balance Sheet'!17:17,'Balance Sheet'!$10:$10,NWC!H$10) | I13: =SUMIFS('Balance Sheet'!17:17,'Balance Sheet'!$10:$10,NWC!I$10) | J13: =SUMIFS('Balance Sheet'!17:17,'Balance Sheet'!$10:$10,NWC!J$10) | K13: =SUMIFS('Balance Sheet'!17:17,'Balance Sheet'!$10:$10,NWC!K$10) | L13: =SUMIFS('Balance Sheet'!17:17,'Balance Sheet'!$10:$10,NWC!L$10) | N13: =C13 | R13: =G13-F13 | S13: =H13-G13 | T13: =I13-H13 | U13: =J13-I13
C14: Other current assets | F14: =SUMIFS('Balance Sheet'!18:18,'Balance Sheet'!$10:$10,NWC!F$10) | G14: =SUMIFS('Balance Sheet'!18:18,'Balance Sheet'!$10:$10,NWC!G$10) | H14: =SUMIFS('Balance Sheet'!18:18,'Balance Sheet'!$10:$10,NWC!H$10) | I14: =SUMIFS('Balance Sheet'!18:18,'Balance Sheet'!$10:$10,NWC!I$10) | J14: =SUMIFS('Balance Sheet'!18:18,'Balance Sheet'!$10:$10,NWC!J$10) | K14: =SUMIFS('Balance Sheet'!18:18,'Balance Sheet'!$10:$10,NWC!K$10) | L14: =SUMIFS('Balance Sheet'!18:18,'Balance Sheet'!$10:$10,NWC!L$10) | N14: =C14 | R14: =G14-F14 | S14: =H14-G14 | T14: =I14-H14 | U14: =J14-I14
C15: Accounts payable | F15: =-SUMIFS('Balance Sheet'!37:37,'Balance Sheet'!$10:$10,NWC!F$10) | G15: =-SUMIFS('Balance Sheet'!37:37,'Balance Sheet'!$10:$10,NWC!G$10) | H15: =-SUMIFS('Balance Sheet'!37:37,'Balance Sheet'!$10:$10,NWC!H$10) | I15: =-SUMIFS('Balance Sheet'!37:37,'Balance Sheet'!$10:$10,NWC!I$10) | J15: =-SUMIFS('Balance Sheet'!37:37,'Balance Sheet'!$10:$10,NWC!J$10) | K15: =-SUMIFS('Balance Sheet'!37:37,'Balance Sheet'!$10:$10,NWC!K$10) | L15: =-SUMIFS('Balance Sheet'!37:37,'Balance Sheet'!$10:$10,NWC!L$10) | N15: =C15 | R15: =G15-F15 | S15: =H15-G15 | T15: =I15-H15 | U15: =J15-I15
C16: Accrued compensation & benefits | F16: =-SUMIFS('Balance Sheet'!38:38,'Balance Sheet'!$10:$10,NWC!F$10) | G16: =-SUMIFS('Balance Sheet'!38:38,'Balance Sheet'!$10:$10,NWC!G$10) | H16: =-SUMIFS('Balance Sheet'!38:38,'Balance Sheet'!$10:$10,NWC!H$10) | I16: =-SUMIFS('Balance Sheet'!38:38,'Balance Sheet'!$10:$10,NWC!I$10) | J16: =-SUMIFS('Balance Sheet'!38:38,'Balance Sheet'!$10:$10,NWC!J$10) | K16: =-SUMIFS('Balance Sheet'!38:38,'Balance Sheet'!$10:$10,NWC!K$10) | L16: =-SUMIFS('Balance Sheet'!38:38,'Balance Sheet'!$10:$10,NWC!L$10) | N16: =C16 | R16: =G16-F16 | S16: =H16-G16 | T16: =I16-H16 | U16: =J16-I16
C17: Accrued exp. & other CL | F17: =-SUMIFS('Balance Sheet'!39:39,'Balance Sheet'!$10:$10,NWC!F$10) | G17: =-SUMIFS('Balance Sheet'!39:39,'Balance Sheet'!$10:$10,NWC!G$10) | H17: =-SUMIFS('Balance Sheet'!39:39,'Balance Sheet'!$10:$10,NWC!H$10) | I17: =-SUMIFS('Balance Sheet'!39:39,'Balance Sheet'!$10:$10,NWC!I$10) | J17: =-SUMIFS('Balance Sheet'!39:39,'Balance Sheet'!$10:$10,NWC!J$10) | K17: =-SUMIFS('Balance Sheet'!39:39,'Balance Sheet'!$10:$10,NWC!K$10) | L17: =-SUMIFS('Balance Sheet'!39:39,'Balance Sheet'!$10:$10,NWC!L$10) | N17: =C17 | R17: =G17-F17 | S17: =H17-G17 | T17: =I17-H17 | U17: =J17-I17
C18: Total NWC | F18: =SUM(F11:F17) | G18: =SUM(G11:G17) | H18: =SUM(H11:H17) | I18: =SUM(I11:I17) | J18: =SUM(J11:J17) | K18: =SUM(K11:K17) | L18: =SUM(L11:L17) | N18: Change in NWC | R18: =SUM(R11:R17) | S18: =SUM(S11:S17) | T18: =SUM(T11:T17) | U18: =SUM(U11:U17)
C20: Change in NWC | F20: =Q18 | G20: =R18 | H20: =S18 | I20: =T18 | J20: =U18 | K20: =K18-J18 | L20: =L18-K18 | N20: Check | R20: =SUMIFS('Quarterly NWC'!47:47,'Quarterly NWC'!$31:$31,NWC!R$10)+R18 | S20: =SUMIFS('Quarterly NWC'!47:47,'Quarterly NWC'!$31:$31,NWC!S$10)+S18 | T20: =SUMIFS('Quarterly NWC'!47:47,'Quarterly NWC'!$31:$31,NWC!T$10)+T18 | U20: =SUMIFS('Quarterly NWC'!47:47,'Quarterly NWC'!$31:$31,NWC!U$10)+U18
C22: Memo:
C23: DSO | F23: =F11/F26*F28 | G23: =G11/G26*G28 | H23: =H11/H26*H28 | I23: =I11/I26*I28 | J23: =J11/J26*J28 | K23: =K11/K26*K28 | L23: =L11/L26*L28
C24: DPO | F24: =-F15/F27*F28 | G24: =-G15/G27*G28 | H24: =-H15/H27*H28 | I24: =-I15/I27*I28 | J24: =-J15/J27*J28 | K24: =-K15/K27*K28 | L24: =-L15/L27*L28
C26: Revenue | F26: =SUMIFS('Income Statement'!12:12,'Income Statement'!$7:$7,"FY"&NWC!F$10) | G26: =SUMIFS('Income Statement'!12:12,'Income Statement'!$7:$7,"FY"&NWC!G$10) | H26: =SUMIFS('Income Statement'!12:12,'Income Statement'!$7:$7,"FY"&NWC!H$10) | I26: =SUMIFS('Income Statement'!12:12,'Income Statement'!$7:$7,"FY"&NWC!I$10) | J26: =SUMIFS('Income Statement'!12:12,'Income Statement'!$7:$7,"FY"&NWC!J$10) | K26: =SUMIFS('Income Statement'!12:12,'Income Statement'!$7:$7,NWC!K$10) | L26: =SUMIFS('Income Statement'!12:12,'Income Statement'!$7:$7,NWC!L$10)
C27: COGS | F27: =SUMIFS('Income Statement'!17:17,'Income Statement'!$7:$7,"FY"&NWC!F$10) | G27: =SUMIFS('Income Statement'!17:17,'Income Statement'!$7:$7,"FY"&NWC!G$10) | H27: =SUMIFS('Income Statement'!17:17,'Income Statement'!$7:$7,"FY"&NWC!H$10) | I27: =SUMIFS('Income Statement'!17:17,'Income Statement'!$7:$7,"FY"&NWC!I$10) | J27: =SUMIFS('Income Statement'!17:17,'Income Statement'!$7:$7,"FY"&NWC!J$10) | K27: =SUMIFS('Income Statement'!17:17,'Income Statement'!$7:$7,NWC!K$10) | L27: =SUMIFS('Income Statement'!17:17,'Income Statement'!$7:$7,NWC!L$10)
C28: Days | F28: 365 | G28: 365 | H28: 365 | I28: 366 | J28: 365 | K28: 91 | L28: 91
B32: x | C32: Change in Net Working Capital by Year
C33: Stacked drivers and the net change ($mm); a NWC build is a use of cash
A53: x | B53: x
A54: End

Sheet Quarterly NWC
A1: =C3 | B1: ='Cover Page'!A1
C3: Quarterly Net Working Capital | Y3: Xerox Holdings Corporation
C4: All values in $ millions (USD)
A8: x | B8: x | C8: Quarterly NWC | D8: Quarter Ended
D10: 1Q'21 | E10: 2Q'21 | F10: 3Q'21 | G10: 4Q'21 | H10: 1Q'22 | I10: 2Q'22 | J10: 3Q'22 | K10: 4Q'22 | L10: 1Q'23 | M10: 2Q'23 | N10: 3Q'23 | O10: 4Q'23 | P10: 1Q'24 | Q10: 2Q'24 | R10: 3Q'24 | S10: 4Q'24 | T10: 1Q'25 | U10: 2Q'25 | V10: 3Q'25 | W10: 4Q'25 | X10: 1Q'26 | Y10: 2Q'26
C12: Current Assets:
C13: Accounts receivable, net | D13: =SUMIFS('Balance Sheet'!14:14,'Balance Sheet'!$10:$10,'Quarterly NWC'!D$10) | E13: =SUMIFS('Balance Sheet'!14:14,'Balance Sheet'!$10:$10,'Quarterly NWC'!E$10) | F13: =SUMIFS('Balance Sheet'!14:14,'Balance Sheet'!$10:$10,'Quarterly NWC'!F$10) | G13: =SUMIFS('Balance Sheet'!14:14,'Balance Sheet'!$10:$10,'Quarterly NWC'!G$10) | H13: =SUMIFS('Balance Sheet'!14:14,'Balance Sheet'!$10:$10,'Quarterly NWC'!H$10) | I13: =SUMIFS('Balance Sheet'!14:14,'Balance Sheet'!$10:$10,'Quarterly NWC'!I$10) | J13: =SUMIFS('Balance Sheet'!14:14,'Balance Sheet'!$10:$10,'Quarterly NWC'!J$10) | K13: =SUMIFS('Balance Sheet'!14:14,'Balance Sheet'!$10:$10,'Quarterly NWC'!K$10) | ... Y13: =SUMIFS('Balance Sheet'!14:14,'Balance Sheet'!$10:$10,'Quarterly NWC'!Y$10)
C14: Billed finance receivables | D14: =SUMIFS('Balance Sheet'!15:15,'Balance Sheet'!$10:$10,'Quarterly NWC'!D$10) | E14: =SUMIFS('Balance Sheet'!15:15,'Balance Sheet'!$10:$10,'Quarterly NWC'!E$10) | F14: =SUMIFS('Balance Sheet'!15:15,'Balance Sheet'!$10:$10,'Quarterly NWC'!F$10) | G14: =SUMIFS('Balance Sheet'!15:15,'Balance Sheet'!$10:$10,'Quarterly NWC'!G$10) | H14: =SUMIFS('Balance Sheet'!15:15,'Balance Sheet'!$10:$10,'Quarterly NWC'!H$10) | I14: =SUMIFS('Balance Sheet'!15:15,'Balance Sheet'!$10:$10,'Quarterly NWC'!I$10) | J14: =SUMIFS('Balance Sheet'!15:15,'Balance Sheet'!$10:$10,'Quarterly NWC'!J$10) | K14: =SUMIFS('Balance Sheet'!15:15,'Balance Sheet'!$10:$10,'Quarterly NWC'!K$10) | ... Y14: =SUMIFS('Balance Sheet'!15:15,'Balance Sheet'!$10:$10,'Quarterly NWC'!Y$10)
C15: Inventories | D15: =SUMIFS('Balance Sheet'!17:17,'Balance Sheet'!$10:$10,'Quarterly NWC'!D$10) | E15: =SUMIFS('Balance Sheet'!17:17,'Balance Sheet'!$10:$10,'Quarterly NWC'!E$10) | F15: =SUMIFS('Balance Sheet'!17:17,'Balance Sheet'!$10:$10,'Quarterly NWC'!F$10) | G15: =SUMIFS('Balance Sheet'!17:17,'Balance Sheet'!$10:$10,'Quarterly NWC'!G$10) | H15: =SUMIFS('Balance Sheet'!17:17,'Balance Sheet'!$10:$10,'Quarterly NWC'!H$10) | I15: =SUMIFS('Balance Sheet'!17:17,'Balance Sheet'!$10:$10,'Quarterly NWC'!I$10) | J15: =SUMIFS('Balance Sheet'!17:17,'Balance Sheet'!$10:$10,'Quarterly NWC'!J$10) | K15: =SUMIFS('Balance Sheet'!17:17,'Balance Sheet'!$10:$10,'Quarterly NWC'!K$10) | ... Y15: =SUMIFS('Balance Sheet'!17:17,'Balance Sheet'!$10:$10,'Quarterly NWC'!Y$10)
C16: Other current assets | D16: =SUMIFS('Balance Sheet'!18:18,'Balance Sheet'!$10:$10,'Quarterly NWC'!D$10) | E16: =SUMIFS('Balance Sheet'!18:18,'Balance Sheet'!$10:$10,'Quarterly NWC'!E$10) | F16: =SUMIFS('Balance Sheet'!18:18,'Balance Sheet'!$10:$10,'Quarterly NWC'!F$10) | G16: =SUMIFS('Balance Sheet'!18:18,'Balance Sheet'!$10:$10,'Quarterly NWC'!G$10) | H16: =SUMIFS('Balance Sheet'!18:18,'Balance Sheet'!$10:$10,'Quarterly NWC'!H$10) | I16: =SUMIFS('Balance Sheet'!18:18,'Balance Sheet'!$10:$10,'Quarterly NWC'!I$10) | J16: =SUMIFS('Balance Sheet'!18:18,'Balance Sheet'!$10:$10,'Quarterly NWC'!J$10) | K16: =SUMIFS('Balance Sheet'!18:18,'Balance Sheet'!$10:$10,'Quarterly NWC'!K$10) | ... Y16: =SUMIFS('Balance Sheet'!18:18,'Balance Sheet'!$10:$10,'Quarterly NWC'!Y$10)
C17: Total Current Assets | D17: =SUM(D13:D16) | E17: =SUM(E13:E16) | F17: =SUM(F13:F16) | G17: =SUM(G13:G16) | H17: =SUM(H13:H16) | I17: =SUM(I13:I16) | J17: =SUM(J13:J16) | K17: =SUM(K13:K16) | ... Y17: =SUM(Y13:Y16)
C19: Current Liabilities:
C20: Accounts payable | D20: =SUMIFS('Balance Sheet'!37:37,'Balance Sheet'!$10:$10,'Quarterly NWC'!D$10) | E20: =SUMIFS('Balance Sheet'!37:37,'Balance Sheet'!$10:$10,'Quarterly NWC'!E$10) | F20: =SUMIFS('Balance Sheet'!37:37,'Balance Sheet'!$10:$10,'Quarterly NWC'!F$10) | G20: =SUMIFS('Balance Sheet'!37:37,'Balance Sheet'!$10:$10,'Quarterly NWC'!G$10) | H20: =SUMIFS('Balance Sheet'!37:37,'Balance Sheet'!$10:$10,'Quarterly NWC'!H$10) | I20: =SUMIFS('Balance Sheet'!37:37,'Balance Sheet'!$10:$10,'Quarterly NWC'!I$10) | J20: =SUMIFS('Balance Sheet'!37:37,'Balance Sheet'!$10:$10,'Quarterly NWC'!J$10) | K20: =SUMIFS('Balance Sheet'!37:37,'Balance Sheet'!$10:$10,'Quarterly NWC'!K$10) | ... Y20: =SUMIFS('Balance Sheet'!37:37,'Balance Sheet'!$10:$10,'Quarterly NWC'!Y$10)
C21: Accrued compensation & benefits | D21: =SUMIFS('Balance Sheet'!38:38,'Balance Sheet'!$10:$10,'Quarterly NWC'!D$10) | E21: =SUMIFS('Balance Sheet'!38:38,'Balance Sheet'!$10:$10,'Quarterly NWC'!E$10) | F21: =SUMIFS('Balance Sheet'!38:38,'Balance Sheet'!$10:$10,'Quarterly NWC'!F$10) | G21: =SUMIFS('Balance Sheet'!38:38,'Balance Sheet'!$10:$10,'Quarterly NWC'!G$10) | H21: =SUMIFS('Balance Sheet'!38:38,'Balance Sheet'!$10:$10,'Quarterly NWC'!H$10) | I21: =SUMIFS('Balance Sheet'!38:38,'Balance Sheet'!$10:$10,'Quarterly NWC'!I$10) | J21: =SUMIFS('Balance Sheet'!38:38,'Balance Sheet'!$10:$10,'Quarterly NWC'!J$10) | K21: =SUMIFS('Balance Sheet'!38:38,'Balance Sheet'!$10:$10,'Quarterly NWC'!K$10) | ... Y21: =SUMIFS('Balance Sheet'!38:38,'Balance Sheet'!$10:$10,'Quarterly NWC'!Y$10)
C22: Accrued exp. & other CL | D22: =SUMIFS('Balance Sheet'!39:39,'Balance Sheet'!$10:$10,'Quarterly NWC'!D$10) | E22: =SUMIFS('Balance Sheet'!39:39,'Balance Sheet'!$10:$10,'Quarterly NWC'!E$10) | F22: =SUMIFS('Balance Sheet'!39:39,'Balance Sheet'!$10:$10,'Quarterly NWC'!F$10) | G22: =SUMIFS('Balance Sheet'!39:39,'Balance Sheet'!$10:$10,'Quarterly NWC'!G$10) | H22: =SUMIFS('Balance Sheet'!39:39,'Balance Sheet'!$10:$10,'Quarterly NWC'!H$10) | I22: =SUMIFS('Balance Sheet'!39:39,'Balance Sheet'!$10:$10,'Quarterly NWC'!I$10) | J22: =SUMIFS('Balance Sheet'!39:39,'Balance Sheet'!$10:$10,'Quarterly NWC'!J$10) | K22: =SUMIFS('Balance Sheet'!39:39,'Balance Sheet'!$10:$10,'Quarterly NWC'!K$10) | ... Y22: =SUMIFS('Balance Sheet'!39:39,'Balance Sheet'!$10:$10,'Quarterly NWC'!Y$10)
C23: Total Current Liabilities | D23: =SUM(D20:D22) | E23: =SUM(E20:E22) | F23: =SUM(F20:F22) | G23: =SUM(G20:G22) | H23: =SUM(H20:H22) | I23: =SUM(I20:I22) | J23: =SUM(J20:J22) | K23: =SUM(K20:K22) | ... Y23: =SUM(Y20:Y22)
C25: NWC | D25: =D17-D23 | E25: =E17-E23 | F25: =F17-F23 | G25: =G17-G23 | H25: =H17-H23 | I25: =I17-I23 | J25: =J17-J23 | K25: =K17-K23 | ... Y25: =Y17-Y23
B26: x | C26: Change in NWC | E26: =D25-E25 | F26: =E25-F25 | G26: =F25-G25 | H26: =G25-H25 | I26: =H25-I25 | J26: =I25-J25 | K26: =J25-K25 | L26: =K25-L25 | ... Y26: =X25-Y25
B30: x | C30: Annual NWC | D30: Fiscal Year
D31: 2021 | E31: =D31+1 | F31: =E31+1 | G31: =F31+1 | H31: =G31+1
C33: Current Assets:
C34: Accounts receivable, net | D34: =SUMIFS('Balance Sheet'!14:14,'Balance Sheet'!$10:$10,'Quarterly NWC'!D$31) | E34: =SUMIFS('Balance Sheet'!14:14,'Balance Sheet'!$10:$10,'Quarterly NWC'!E$31) | F34: =SUMIFS('Balance Sheet'!14:14,'Balance Sheet'!$10:$10,'Quarterly NWC'!F$31) | G34: =SUMIFS('Balance Sheet'!14:14,'Balance Sheet'!$10:$10,'Quarterly NWC'!G$31) | H34: =SUMIFS('Balance Sheet'!14:14,'Balance Sheet'!$10:$10,'Quarterly NWC'!H$31)
C35: Billed finance receivables | D35: =SUMIFS('Balance Sheet'!15:15,'Balance Sheet'!$10:$10,'Quarterly NWC'!D$31) | E35: =SUMIFS('Balance Sheet'!15:15,'Balance Sheet'!$10:$10,'Quarterly NWC'!E$31) | F35: =SUMIFS('Balance Sheet'!15:15,'Balance Sheet'!$10:$10,'Quarterly NWC'!F$31) | G35: =SUMIFS('Balance Sheet'!15:15,'Balance Sheet'!$10:$10,'Quarterly NWC'!G$31) | H35: =SUMIFS('Balance Sheet'!15:15,'Balance Sheet'!$10:$10,'Quarterly NWC'!H$31)
C36: Inventories | D36: =SUMIFS('Balance Sheet'!17:17,'Balance Sheet'!$10:$10,'Quarterly NWC'!D$31) | E36: =SUMIFS('Balance Sheet'!17:17,'Balance Sheet'!$10:$10,'Quarterly NWC'!E$31) | F36: =SUMIFS('Balance Sheet'!17:17,'Balance Sheet'!$10:$10,'Quarterly NWC'!F$31) | G36: =SUMIFS('Balance Sheet'!17:17,'Balance Sheet'!$10:$10,'Quarterly NWC'!G$31) | H36: =SUMIFS('Balance Sheet'!17:17,'Balance Sheet'!$10:$10,'Quarterly NWC'!H$31)
C37: Other current assets | D37: =SUMIFS('Balance Sheet'!18:18,'Balance Sheet'!$10:$10,'Quarterly NWC'!D$31) | E37: =SUMIFS('Balance Sheet'!18:18,'Balance Sheet'!$10:$10,'Quarterly NWC'!E$31) | F37: =SUMIFS('Balance Sheet'!18:18,'Balance Sheet'!$10:$10,'Quarterly NWC'!F$31) | G37: =SUMIFS('Balance Sheet'!18:18,'Balance Sheet'!$10:$10,'Quarterly NWC'!G$31) | H37: =SUMIFS('Balance Sheet'!18:18,'Balance Sheet'!$10:$10,'Quarterly NWC'!H$31)
C38: Total Current Assets | D38: =SUM(D34:D37) | E38: =SUM(E34:E37) | F38: =SUM(F34:F37) | G38: =SUM(G34:G37) | H38: =SUM(H34:H37)
C40: Current Liabilities:
C41: Accounts payable | D41: =SUMIFS('Balance Sheet'!37:37,'Balance Sheet'!$10:$10,'Quarterly NWC'!D$31) | E41: =SUMIFS('Balance Sheet'!37:37,'Balance Sheet'!$10:$10,'Quarterly NWC'!E$31) | F41: =SUMIFS('Balance Sheet'!37:37,'Balance Sheet'!$10:$10,'Quarterly NWC'!F$31) | G41: =SUMIFS('Balance Sheet'!37:37,'Balance Sheet'!$10:$10,'Quarterly NWC'!G$31) | H41: =SUMIFS('Balance Sheet'!37:37,'Balance Sheet'!$10:$10,'Quarterly NWC'!H$31)
C42: Accrued compensation & benefits | D42: =SUMIFS('Balance Sheet'!38:38,'Balance Sheet'!$10:$10,'Quarterly NWC'!D$31) | E42: =SUMIFS('Balance Sheet'!38:38,'Balance Sheet'!$10:$10,'Quarterly NWC'!E$31) | F42: =SUMIFS('Balance Sheet'!38:38,'Balance Sheet'!$10:$10,'Quarterly NWC'!F$31) | G42: =SUMIFS('Balance Sheet'!38:38,'Balance Sheet'!$10:$10,'Quarterly NWC'!G$31) | H42: =SUMIFS('Balance Sheet'!38:38,'Balance Sheet'!$10:$10,'Quarterly NWC'!H$31)
C43: Accrued exp. & other CL | D43: =SUMIFS('Balance Sheet'!39:39,'Balance Sheet'!$10:$10,'Quarterly NWC'!D$31) | E43: =SUMIFS('Balance Sheet'!39:39,'Balance Sheet'!$10:$10,'Quarterly NWC'!E$31) | F43: =SUMIFS('Balance Sheet'!39:39,'Balance Sheet'!$10:$10,'Quarterly NWC'!F$31) | G43: =SUMIFS('Balance Sheet'!39:39,'Balance Sheet'!$10:$10,'Quarterly NWC'!G$31) | H43: =SUMIFS('Balance Sheet'!39:39,'Balance Sheet'!$10:$10,'Quarterly NWC'!H$31)
C44: Total Current Liabilities | D44: =SUM(D41:D43) | E44: =SUM(E41:E43) | F44: =SUM(F41:F43) | G44: =SUM(G41:G43) | H44: =SUM(H41:H43)
C46: NWC | D46: =D38-D44 | E46: =E38-E44 | F46: =F38-F44 | G46: =G38-G44 | H46: =H38-H44
A47: x | B47: x | C47: Change in NWC | E47: =D46-E46 | F47: =E46-F46 | G47: =F46-G46 | H47: =G46-H46
A48: End

Sheet Capital Structure
A1: =C3 | B1: ='Cover Page'!A1
C3: Capital Structure | R3: Xerox Holdings Corporation
C4: All values in $ millions (USD), as of June 30, 2026
A7: x | B7: x | C7: Capital Structure
D8: Face | E8: Leverage | F8: Interest | G8: Effective | H8: Annual | J8: Credit | K8: Trading | M8: Market | N8: Leverage | P8: Effective Rate Calculation
C9: Description | D9: Value | E9: (Face) | F9: Rate | G9: Rate | H9: Interest | I9: Maturity | J9: Rating | K9: Price | L9: YTM | M9: Value | N9: (Market) | P9: SOFR | Q9: Spread | R9: Effective
C11: ABL Revolving Credit Facility ($425mm) | D11: 0 | E11: =(D11)/$D$30 | F11: 150 | G11: =R11 | H11: =D11*G11 | I11: 46895 | J11: NA | K11: NA | L11: NA | M11: NA | N11: =E11 | P11: 0.0387 | Q11: 0.015 | R11: =SUM(P11:Q11)
C12: IPCo JV Secured Term Loans ($405mm) | D12: 405 | E12: =(D11+D12)/$D$30 | F12: 812.5 | G12: =R12 | H12: =D12*G12 | I12: 47896 | J12: NA | K12: NA | L12: NA | M12: NA | N12: =E12 | P12: =P11 | Q12: 0.08125 | R12: =SUM(P12:Q12)
C13: IPCo Class A Units ($45mm) | D13: 45 | E13: =(D11+D12+D13)/$D$30 | F13: NA | G13: NA | H13: NA | I13: NA | J13: NA | K13: NA | L13: NA | M13: NA | N13: =E13
C14: 1L Term Loan B ($705mm) | D14: 705 | E14: =(D11+D12+D13+D14)/$D$30 | F14: 400 | G14: =R14 | H14: =D14*G14 | I14: 47439 | J14: NA | K14: NA | L14: NA | M14: NA | N14: =E14 | P14: =P11 | Q14: 0.04 | R14: =SUM(P14:Q14)
C15: 1L Senior Secured Notes ($400mm) | D15: 400 | E15: =(D11+D12+D13+D14+D15)/$D$30 | F15: 0.1025 | G15: =F15 | H15: =D15*G15 | I15: 47771 | J15: NA / B | K15: NA | L15: NA | M15: NA | N15: =E15
C16: 2L Senior Secured Notes ($494mm) | D16: 494 | E16: =(D11+D12+D13+D14+D15+D16)/$D$30 | F16: 0.135 | G16: =F16 | H16: =D16*G16 | I16: 47953 | J16: NA / CCC+ | K16: NA | L16: NA | M16: NA | N16: =E16
C17: Total Secured Debt | D17: =SUM(D11:D16) | E17: =D17/$D$30 | F17: 0 | G17: 0 | H17: =SUM(H11:H16) | I17: 0 | J17: 0 | K17: 0 | L17: 0 | N17: =D17/$D$30
C18: Senior Unsecured Notes due 2028 ($556mm) | D18: 556 | E18: =(D11+D12+D13+D14+D15+D16+D18)/$D$30 | F18: 0.055 | G18: =F18 | H18: =D18*G18 | I18: 46980 | J18: NA | K18: 58.6 | L18: NA | M18: =D18*K18/100 | N18: =E18
C19: Senior Unsecured Notes due 2029 ($500mm) | D19: 500 | E19: =(D11+D12+D13+D14+D15+D16+D18+D19)/$D$30 | F19: 0.08875 | G19: =F19 | H19: =D19*G19 | I19: 47452 | J19: NA / CCC | K19: 40.9 | L19: NA | M19: =D19*K19/100 | N19: =E19
C20: Convertible Senior Notes 2030 ($400mm) | D20: 400 | E20: =(D11+D12+D13+D14+D15+D16+D18+D19+D20)/$D$30 | F20: 0.0375 | G20: =F20 | H20: =D20*G20 | I20: 47557 | J20: NA / CCC | K20: NA | L20: NA | M20: NA | N20: =E20
C21: Step-Up Senior Notes due 2030 ($250mm) | D21: 250 | E21: =(D11+D12+D13+D14+D15+D16+D18+D19+D20+D21)/$D$30 | F21: 0.135 | G21: =F21 | H21: =D21*G21 | I21: 47665 | J21: Caa3 / NA | K21: NA | L21: NA | M21: NA | N21: =E21
C22: Xerox Corp. Senior Notes 2035 ($250mm) | D22: 250 | E22: =(D11+D12+D13+D14+D15+D16+D18+D19+D20+D21+D22)/$D$30 | F22: 0.048 | G22: =F22 | H22: =D22*G22 | I22: 49369 | J22: NA / CCC | K22: NA | L22: NA | M22: NA | N22: =E22
C23: Xerox Corp. Senior Notes 2039 ($350mm) | D23: 350 | E23: =(D11+D12+D13+D14+D15+D16+D18+D19+D20+D21+D22+D23)/$D$30 | F23: 0.0675 | G23: =F23 | H23: =D23*G23 | I23: 51119 | J23: NA / CCC | K23: NA | L23: NA | M23: NA | N23: =E23
C24: Total Debt | D24: =SUM(D17:D23) | E24: =D24/$D$30 | F24: 0 | G24: 0 | H24: =SUM(H17:H23) | I24: 0 | J24: 0 | K24: 0 | L24: 0 | N24: =D24/$D$30
C25: Less: Cash & Cash Equivalents | D25: =-'Balance Sheet'!Z13 | E25: =D25/$D$30 | F25: 0 | G25: 0 | H25: 0 | I25: 0 | J25: 0 | K25: 0 | L25: 0 | M25: 0 | N25: 0
C26: Net Debt | D26: =SUM(D24:D25) | E26: =D26/$D$30 | F26: 0 | G26: 0 | H26: =SUM(H24:H25) | I26: 0 | J26: 0 | K26: 0 | L26: 0 | N26: =D26/$D$30
C27: Series A Conv. Preferred ($180mm) | D27: 180 | E27: =(D11+D12+D13+D14+D15+D16+D18+D19+D20+D21+D22+D23+D27)/$D$30 | F27: 0.08 | G27: =F27 | H27: =D27*G27 | I27: NA | J27: NA | K27: NA | L27: NA | M27: NA | N27: =E27
C28: Net Debt & Preferred Equity | D28: =SUM(D26:D27) | E28: =D28/$D$30 | F28: 0 | G28: 0 | H28: =SUM(H26:H27) | I28: 0 | J28: 0 | K28: 0 | L28: 0 | N28: =D28/$D$30
C30: Memo: LTM 2Q'26 Adj. EBITDA | D30: ='Income Statement'!AH55
C32: Liquidity Walk
C33: ABL Commitments | D33: 425
C34: Less: Borrowing Base Limitation | D34: -37
C35: Less: Outstanding Borrowings | D35: =-D11
C36: Less: Letters of Credit | D36: -112
C37: ABL Availability | D37: =SUM(D33:D36)
C38: Plus: Cash and Equivalents | D38: =-D25
A39: x | B39: x | C39: Total Liquidity | D39: =SUM(D37:D38)
A40: End

Sheet Maturity Schedule
A1: =C3 | B1: ='Cover Page'!A1
C3: Debt Maturity Schedule | J3: Xerox Holdings Corporation
C4: All values in $ millions (USD), as of June 30, 2026
A7: x | B7: x | C7: Debt Maturity Profile
D8: Liquidity | E8: 2028 | F8: 2029 | G8: 2030 | H8: 2031 | I8: 2035 | J8: 2039
C9: Cash & Equivalents | D9: ='Capital Structure'!$D$38
C10: ABL Availability | D10: ='Capital Structure'!$D$37
C11: Secured Term Loan | E11: =SUMIFS('Capital Structure'!$D$12:$D$12,'Capital Structure'!$I$12:$I$12,">="&DATE(E$8,1,1),'Capital Structure'!$I$12:$I$12,"<="&DATE(E$8,12,31)) | F11: =SUMIFS('Capital Structure'!$D$12:$D$12,'Capital Structure'!$I$12:$I$12,">="&DATE(F$8,1,1),'Capital Structure'!$I$12:$I$12,"<="&DATE(F$8,12,31)) | G11: =SUMIFS('Capital Structure'!$D$12:$D$12,'Capital Structure'!$I$12:$I$12,">="&DATE(G$8,1,1),'Capital Structure'!$I$12:$I$12,"<="&DATE(G$8,12,31)) | H11: =SUMIFS('Capital Structure'!$D$12:$D$12,'Capital Structure'!$I$12:$I$12,">="&DATE(H$8,1,1),'Capital Structure'!$I$12:$I$12,"<="&DATE(H$8,12,31)) | I11: =SUMIFS('Capital Structure'!$D$12:$D$12,'Capital Structure'!$I$12:$I$12,">="&DATE(I$8,1,1),'Capital Structure'!$I$12:$I$12,"<="&DATE(I$8,12,31)) | J11: =SUMIFS('Capital Structure'!$D$12:$D$12,'Capital Structure'!$I$12:$I$12,">="&DATE(J$8,1,1),'Capital Structure'!$I$12:$I$12,"<="&DATE(J$8,12,31))
C12: 1L Term Loan | E12: =SUMIFS('Capital Structure'!$D$14:$D$14,'Capital Structure'!$I$14:$I$14,">="&DATE(E$8,1,1),'Capital Structure'!$I$14:$I$14,"<="&DATE(E$8,12,31)) | F12: =SUMIFS('Capital Structure'!$D$14:$D$14,'Capital Structure'!$I$14:$I$14,">="&DATE(F$8,1,1),'Capital Structure'!$I$14:$I$14,"<="&DATE(F$8,12,31)) | G12: =SUMIFS('Capital Structure'!$D$14:$D$14,'Capital Structure'!$I$14:$I$14,">="&DATE(G$8,1,1),'Capital Structure'!$I$14:$I$14,"<="&DATE(G$8,12,31)) | H12: =SUMIFS('Capital Structure'!$D$14:$D$14,'Capital Structure'!$I$14:$I$14,">="&DATE(H$8,1,1),'Capital Structure'!$I$14:$I$14,"<="&DATE(H$8,12,31)) | I12: =SUMIFS('Capital Structure'!$D$14:$D$14,'Capital Structure'!$I$14:$I$14,">="&DATE(I$8,1,1),'Capital Structure'!$I$14:$I$14,"<="&DATE(I$8,12,31)) | J12: =SUMIFS('Capital Structure'!$D$14:$D$14,'Capital Structure'!$I$14:$I$14,">="&DATE(J$8,1,1),'Capital Structure'!$I$14:$I$14,"<="&DATE(J$8,12,31))
C13: 1L Notes | E13: =SUMIFS('Capital Structure'!$D$15:$D$15,'Capital Structure'!$I$15:$I$15,">="&DATE(E$8,1,1),'Capital Structure'!$I$15:$I$15,"<="&DATE(E$8,12,31)) | F13: =SUMIFS('Capital Structure'!$D$15:$D$15,'Capital Structure'!$I$15:$I$15,">="&DATE(F$8,1,1),'Capital Structure'!$I$15:$I$15,"<="&DATE(F$8,12,31)) | G13: =SUMIFS('Capital Structure'!$D$15:$D$15,'Capital Structure'!$I$15:$I$15,">="&DATE(G$8,1,1),'Capital Structure'!$I$15:$I$15,"<="&DATE(G$8,12,31)) | H13: =SUMIFS('Capital Structure'!$D$15:$D$15,'Capital Structure'!$I$15:$I$15,">="&DATE(H$8,1,1),'Capital Structure'!$I$15:$I$15,"<="&DATE(H$8,12,31)) | I13: =SUMIFS('Capital Structure'!$D$15:$D$15,'Capital Structure'!$I$15:$I$15,">="&DATE(I$8,1,1),'Capital Structure'!$I$15:$I$15,"<="&DATE(I$8,12,31)) | J13: =SUMIFS('Capital Structure'!$D$15:$D$15,'Capital Structure'!$I$15:$I$15,">="&DATE(J$8,1,1),'Capital Structure'!$I$15:$I$15,"<="&DATE(J$8,12,31))
C14: 2L Notes | E14: =SUMIFS('Capital Structure'!$D$16:$D$16,'Capital Structure'!$I$16:$I$16,">="&DATE(E$8,1,1),'Capital Structure'!$I$16:$I$16,"<="&DATE(E$8,12,31)) | F14: =SUMIFS('Capital Structure'!$D$16:$D$16,'Capital Structure'!$I$16:$I$16,">="&DATE(F$8,1,1),'Capital Structure'!$I$16:$I$16,"<="&DATE(F$8,12,31)) | G14: =SUMIFS('Capital Structure'!$D$16:$D$16,'Capital Structure'!$I$16:$I$16,">="&DATE(G$8,1,1),'Capital Structure'!$I$16:$I$16,"<="&DATE(G$8,12,31)) | H14: =SUMIFS('Capital Structure'!$D$16:$D$16,'Capital Structure'!$I$16:$I$16,">="&DATE(H$8,1,1),'Capital Structure'!$I$16:$I$16,"<="&DATE(H$8,12,31)) | I14: =SUMIFS('Capital Structure'!$D$16:$D$16,'Capital Structure'!$I$16:$I$16,">="&DATE(I$8,1,1),'Capital Structure'!$I$16:$I$16,"<="&DATE(I$8,12,31)) | J14: =SUMIFS('Capital Structure'!$D$16:$D$16,'Capital Structure'!$I$16:$I$16,">="&DATE(J$8,1,1),'Capital Structure'!$I$16:$I$16,"<="&DATE(J$8,12,31))
C15: Senior Unsecured Notes | E15: =SUMIFS('Capital Structure'!$D$18:$D$23,'Capital Structure'!$I$18:$I$23,">="&DATE(E$8,1,1),'Capital Structure'!$I$18:$I$23,"<="&DATE(E$8,12,31)) | F15: =SUMIFS('Capital Structure'!$D$18:$D$23,'Capital Structure'!$I$18:$I$23,">="&DATE(F$8,1,1),'Capital Structure'!$I$18:$I$23,"<="&DATE(F$8,12,31)) | G15: =SUMIFS('Capital Structure'!$D$18:$D$23,'Capital Structure'!$I$18:$I$23,">="&DATE(G$8,1,1),'Capital Structure'!$I$18:$I$23,"<="&DATE(G$8,12,31)) | H15: =SUMIFS('Capital Structure'!$D$18:$D$23,'Capital Structure'!$I$18:$I$23,">="&DATE(H$8,1,1),'Capital Structure'!$I$18:$I$23,"<="&DATE(H$8,12,31)) | I15: =SUMIFS('Capital Structure'!$D$18:$D$23,'Capital Structure'!$I$18:$I$23,">="&DATE(I$8,1,1),'Capital Structure'!$I$18:$I$23,"<="&DATE(I$8,12,31)) | J15: =SUMIFS('Capital Structure'!$D$18:$D$23,'Capital Structure'!$I$18:$I$23,">="&DATE(J$8,1,1),'Capital Structure'!$I$18:$I$23,"<="&DATE(J$8,12,31))
C16: Total | D16: =SUM(D9:D15) | E16: =SUM(E9:E15) | F16: =SUM(F9:F15) | G16: =SUM(G9:G15) | H16: =SUM(H9:H15) | I16: =SUM(I9:I15) | J16: =SUM(J9:J15)
A35: x | B35: x
A36: End

Sheet Analysis >
A1: Analysis > | B1: ='Cover Page'!A1

Sheet Precedent Transactions
A1: =C2 | B1: ='Cover Page'!A1
C2: Precedent Transactions Analysis | M2: Xerox Holdings Corporation
C3: All Values in Millions ($USD), Except Per-Share Values
C5: M&A Precedent Transactions - Print & Document Technology
A7: x | B7: x | C7: Date | D7: Target | F7: Acquirer | G7: Segment | I7: EV ($mm) | J7: EV/Revenue | L7: EV/EBITDA | M7: Premium
C8: 45649 | D8: Lexmark International | F8: Xerox Holdings | G8: A4 print / imaging OEM | I8: 1500 | J8: 0.68368277 | L8: 4.7169811 | M8: NA
C9: 45531 | D9: ARC Document Solutions | F9: TechPrint Holdings (mgmt.) | G9: Document / print services | I9: NA | J9: NA | L9: NA | M9: 0.288
C10: 43774 | D10: Fuji Xerox (25% stake) | F10: FUJIFILM Holdings | G10: Office print / document services | I10: n.m. | J10: n.m. | L10: n.m. | M10: n.m.
C11: 43570 | D11: Electronics for Imaging | F11: Siris Capital | G11: Print controllers / industrial inkjet | I11: 1700 | J11: 1.6748768 | L11: 15.2 | M11: 0.26
C12: 42625 | D12: Samsung printer business | F12: HP Inc. | G12: A3/A4 laser printing | I12: 1050 | J12: 0.58333333 | L12: NA | M12: NA
C13: 42479 | D13: Lexmark International | F13: Apex Technology / PAG Asia Capital | G13: Print / imaging OEM | I13: 3600 | J13: 1 | L13: 9 | M13: 0.3
B15: x | C15: Company | F15: LTM Revenue | G15: LTM Adj. EBITDA | I15: Excl. IEEPA | J15: Total Debt | L15: ND + Pref. | M15: Shares (mm)
C16: Xerox Holdings Corporation | F16: ='Income Statement Output'!J13 | G16: ='Income Statement Output'!J33 | I16: ='Income Statement Output'!J37 | J16: ='Capital Structure'!D24 | L16: ='Capital Structure'!D28 | M16: ='$XRX Comparable Companies'!G20
C18: Min | J18: =MIN(J8:J13) | L18: =MIN(L8:L13) | M18: =MIN(M8:M13)
C19: Q1 | J19: =_xlfn.QUARTILE.INC(J8:J13,1) | L19: =_xlfn.QUARTILE.INC(L8:L13,1) | M19: =_xlfn.QUARTILE.INC(M8:M13,1)
C20: Median | J20: =MEDIAN(J8:J13) | L20: =MEDIAN(L8:L13) | M20: =MEDIAN(M8:M13)
C21: Q3 | J21: =_xlfn.QUARTILE.INC(J8:J13,3) | L21: =_xlfn.QUARTILE.INC(L8:L13,3) | M21: =_xlfn.QUARTILE.INC(M8:M13,3)
C22: Max | J22: =MAX(J8:J13) | L22: =MAX(L8:L13) | M22: =MAX(M8:M13)
C24: Low | H24: Q1 | J24: =_xlfn.XLOOKUP($H24,$C$18:$C$22,J$18:J$22) | L24: =_xlfn.XLOOKUP($H24,$C$18:$C$22,L$18:L$22) | M24: =_xlfn.XLOOKUP($H24,$C$18:$C$22,M$18:M$22)
C25: High | H25: Median | J25: =_xlfn.XLOOKUP($H25,$C$18:$C$22,J$18:J$22) | L25: =_xlfn.XLOOKUP($H25,$C$18:$C$22,L$18:L$22) | M25: =_xlfn.XLOOKUP($H25,$C$18:$C$22,M$18:M$22)
C27: Enterprise Value - Low | J27: =J24*$F$16 | L27: =L24*$I$16 | M27: N/A
C28: Enterprise Value - High | J28: =J25*$F$16 | L28: =L25*$I$16 | M28: N/A
C30: Implied EV / Total Debt (Coverage) - Low | J30: =J27/$J$16 | L30: =L27/$J$16 | M30: N/A
C31: Implied EV / Total Debt (Coverage) - High | J31: =J28/$J$16 | L31: =L28/$J$16 | M31: N/A
C33: Equity Value (after Net Debt & Pref.) - Low | J33: =J27-$L$16 | L33: =L27-$L$16 | M33: N/A
C34: Equity Value (after Net Debt & Pref.) - High | J34: =J28-$L$16 | L34: =L28-$L$16 | M34: N/A
C36: Price per Share - Low | J36: =J33/$M$16 | L36: =L33/$M$16 | M36: N/A
C37: Price per Share - High | J37: =J34/$M$16 | L37: =L34/$M$16 | M37: N/A
C39: Implied Upside / (Downside) to Current Price - Low | J39: =(J36-'$XRX Comparable Companies'!$F$20)/'$XRX Comparable Companies'!$F$20 | L39: =(L36-'$XRX Comparable Companies'!$F$20)/'$XRX Comparable Companies'!$F$20 | M39: N/A
B40: x | C40: Implied Upside / (Downside) to Current Price - High | J40: =(J37-'$XRX Comparable Companies'!$F$20)/'$XRX Comparable Companies'!$F$20 | L40: =(L37-'$XRX Comparable Companies'!$F$20)/'$XRX Comparable Companies'!$F$20 | M40: N/A
C44: Precedent Restructurings & Liability Management Transactions - Comparable Credits
B46: x | C46: Date | D46: Company | F46: Transaction Type | G46: Debt ($mm) | H46: Key Terms / Outcome
C47: 46070 | D47: Xerox Holdings | F47: IP drop-down JV financing (LME) | G47: 450 | H47: TPG funded $405mm 5-yr term loans + $45mm Class A Units at XRX Brandco (IPCo), secured by contributed IP; ad hoc group of Holdings lenders organized.
C48: 46184 | D48: Xerox Holdings | F48: Below-par open-market repurchases | G48: 194 | H48: ~$194mm 2028 notes bought for ~$99mm (~51% of par) in 1H26; S&P cut to SD then restored CCC+ (16-Jun-26).
C49: 45719 | D49: Exela Technologies (DocuData) | F49: Prearranged Chapter 11 | G49: 1315 | H49: ~$1.25bn secured notes converted to equity; $245mm exit facility; plan effective 29-Jul-25.
C50: 45512 | D50: Pitney Bowes (Global Ecommerce) | F50: Subsidiary sale + Ch. 11 liquidation | G50: NA | H50: Sold control of GEC to Hilco, which liquidated it in Ch. 11; one-time cost capped at ~$150mm; removed ~$136mm annual losses.
C51: 45363 | D51: Rackspace Technology | F51: Non-pro-rata uptier exchange (LME) | G51: 1920 | H51: $1,589mm TL + $331mm notes exchanged into first-lien second-out debt; $275mm new-money super-priority FLFO; >$375mm net debt cut.
C52: 45078 | D52: Diebold Nixdorf | F52: Prepackaged Ch. 11 + Dutch WHOA | G52: 2700 | H52: ~$2.7bn funded debt restructured; 1L claims equitized into 98% of new equity; $1.25bn DIP rolled into exit TL; old equity cancelled. Effective 11-Aug-23.
C53: 43934 | D53: LSC Communications | F53: Ch. 11 / 363 sale (credit bid) | G53: NA | H53: Sold substantially all assets to Atlas Holdings and the secured creditor group for cash plus a credit bid of the TL and secured notes; buyer assumed the pension plan.
A54: x | B54: x | C54: 40927 | D54: Eastman Kodak | F54: Chapter 11 | G54: NA | H54: Emerged 3-Sep-13; 2L notes and unsecured notes cancelled - 2L holders took most of the new equity via a $406mm rights offering; GUCs ~4-5c; new $695mm TLs + $200mm ABL.
A55: End

Sheet $XRX Comparable Companies
A1: =C2 | B1: ='Cover Page'!A1
C2: $XRX Comparable Companies Analysis | AD2: Xerox Holdings Corporation
C3: All Values in Millions ($USD), Except Per-Share Values
A5: x | B5: x | C5: Company Name | M5: Beta | O5: EBITDA | Q5: EBIT | S5: Revenue | U5: FCF | W5: EV/EBITDA | Y5: EV/EBIT | AA5: EV/Revenue | AC5: EV/FCF
E6: Ticker | F6: Share Price | G6: Shares OS | H6: Market Cap | I6: Enterprise Value | J6: Total Debt | K6: Cash & ST Inv. | L6: Tax Rate | M6: Levered | N6: Unlevered | O6: LTM | P6: NTM | Q6: LTM | R6: NTM | S6: LTM | T6: NTM | U6: LTM | V6: NTM | W6: LTM | X6: NTM | Y6: LTM | Z6: NTM | AA6: LTM | AB6: NTM | AC6: LTM | AD6: NTM
C7: {=_xll.FDS($E7,"FG_COMPANY_NAME")} | E7: HPQ | F7: {=_xll.FDS($E7,"FG_PRICE(0)")} | G7: {=_xll.FDS($E7,"FREF_SHARES_COMPANY(0,,,,0,""LEGACY"")")} | H7: =IF(AND(ISNUMBER(F7),ISNUMBER(G7)),F7*G7,"NA") | I7: {=_xll.FDS($E7,"FG_ENT_VALUE(0)")} | J7: {=_xll.FDSR(E7,"FF_DEBT(ANN_R,0)")} | K7: {=_xll.FDS(E7,"FF_CASH_ST(ANN_R,0)")} | L7: =IFERROR(_xlfn.AGGREGATE(12,6,I50:L50),$L$64) | M7: =IF(ISNUMBER(I72),I72,"NA") | N7: =IF(AND(ISNUMBER(M7),ISNUMBER(L7),ISNUMBER(J7),ISNUMBER(H7)),IF(H7>0,M7/(1+(1-L7)*(J7/H7)),"NM"),"NA") | O7: {=_xll.FDS($E7,"FF_EBITDA_OPER(LTM_R,0)")} | P7: {=_xll.FDS($E7,"FE_ESTIMATE(EBITDA,MEAN,NTM4_ROLL,,NOW,,,'')")} | Q7: {=_xll.FDS(E7,"FF_EBIT_OPER(LTM_R,0)")} | R7: {=_xll.FDS(E7,"FE_ESTIMATE(EBIT,MEAN,NTM4_ROLL,,NOW,,,'')")} | S7: {=_xll.FDS(E7,"FF_SALES(LTM_R,0)")} | T7: {=_xll.FDS(E7,"FE_ESTIMATE(SALES,MEAN,NTM4_ROLL,,NOW,,,'')")} | U7: {=_xll.FDS(E7,"FF_FREE_CF(ANN_R_FCF,0)")} | V7: {=_xll.FDS(E7,"FE_ESTIMATE(FCF,MEAN,NTM4_ROLL,,NOW,,,'')")} | W7: =IF(AND(ISNUMBER($I7),ISNUMBER(O7)),IF(O7>0,$I7/O7,"NM"),"NA") | X7: =IF(AND(ISNUMBER($I7),ISNUMBER(P7)),IF(P7>0,$I7/P7,"NM"),"NA") | Y7: =IF(AND(ISNUMBER($I7),ISNUMBER(Q7)),IF(Q7>0,$I7/Q7,"NM"),"NA") | Z7: =IF(AND(ISNUMBER($I7),ISNUMBER(R7)),IF(R7>0,$I7/R7,"NM"),"NA") | AA7: =IF(AND(ISNUMBER($I7),ISNUMBER(S7)),IF(S7>0,$I7/S7,"NM"),"NA") | AB7: =IF(AND(ISNUMBER($I7),ISNUMBER(T7)),IF(T7>0,$I7/T7,"NM"),"NA") | AC7: =IF(AND(ISNUMBER($I7),ISNUMBER(U7)),IF(U7>0,$I7/U7,"NM"),"NA") | AD7: =IF(AND(ISNUMBER($I7),ISNUMBER(V7)),IF(V7>0,$I7/V7,"NM"),"NA")
C8: {=_xll.FDS($E8,"FG_COMPANY_NAME")} | E8: 7751-JP | F8: {=_xll.FDS($E8,"FG_PRICE(0)")} | G8: {=_xll.FDS($E8,"FREF_SHARES_COMPANY(0,,,,0,""LEGACY"")")} | H8: =IF(AND(ISNUMBER(F8),ISNUMBER(G8)),F8*G8,"NA") | I8: {=_xll.FDS($E8,"FG_ENT_VALUE(0)")} | J8: {=_xll.FDSR(E8,"FF_DEBT(ANN_R,0)")} | K8: {=_xll.FDS(E8,"FF_CASH_ST(ANN_R,0)")} | L8: =IFERROR(_xlfn.AGGREGATE(12,6,I51:L51),$L$64) | M8: =IF(ISNUMBER(I73),I73,"NA") | N8: =IF(AND(ISNUMBER(M8),ISNUMBER(L8),ISNUMBER(J8),ISNUMBER(H8)),IF(H8>0,M8/(1+(1-L8)*(J8/H8)),"NM"),"NA") | O8: {=_xll.FDS($E8,"FF_EBITDA_OPER(LTM_R,0)")} | P8: {=_xll.FDS($E8,"FE_ESTIMATE(EBITDA,MEAN,NTM4_ROLL,,NOW,,,'')")} | Q8: {=_xll.FDS(E8,"FF_EBIT_OPER(LTM_R,0)")} | R8: {=_xll.FDS(E8,"FE_ESTIMATE(EBIT,MEAN,NTM4_ROLL,,NOW,,,'')")} | S8: {=_xll.FDS(E8,"FF_SALES(LTM_R,0)")} | T8: {=_xll.FDS(E8,"FE_ESTIMATE(SALES,MEAN,NTM4_ROLL,,NOW,,,'')")} | U8: {=_xll.FDS(E8,"FF_FREE_CF(ANN_R_FCF,0)")} | V8: {=_xll.FDS(E8,"FE_ESTIMATE(FCF,MEAN,NTM4_ROLL,,NOW,,,'')")} | W8: =IF(AND(ISNUMBER($I8),ISNUMBER(O8)),IF(O8>0,$I8/O8,"NM"),"NA") | X8: =IF(AND(ISNUMBER($I8),ISNUMBER(P8)),IF(P8>0,$I8/P8,"NM"),"NA") | Y8: =IF(AND(ISNUMBER($I8),ISNUMBER(Q8)),IF(Q8>0,$I8/Q8,"NM"),"NA") | Z8: =IF(AND(ISNUMBER($I8),ISNUMBER(R8)),IF(R8>0,$I8/R8,"NM"),"NA") | AA8: =IF(AND(ISNUMBER($I8),ISNUMBER(S8)),IF(S8>0,$I8/S8,"NM"),"NA") | AB8: =IF(AND(ISNUMBER($I8),ISNUMBER(T8)),IF(T8>0,$I8/T8,"NM"),"NA") | AC8: =IF(AND(ISNUMBER($I8),ISNUMBER(U8)),IF(U8>0,$I8/U8,"NM"),"NA") | AD8: =IF(AND(ISNUMBER($I8),ISNUMBER(V8)),IF(V8>0,$I8/V8,"NM"),"NA")
C9: {=_xll.FDS($E9,"FG_COMPANY_NAME")} | E9: 7752-JP | F9: {=_xll.FDS($E9,"FG_PRICE(0)")} | G9: {=_xll.FDS($E9,"FREF_SHARES_COMPANY(0,,,,0,""LEGACY"")")} | H9: =IF(AND(ISNUMBER(F9),ISNUMBER(G9)),F9*G9,"NA") | I9: {=_xll.FDS($E9,"FG_ENT_VALUE(0)")} | J9: {=_xll.FDSR(E9,"FF_DEBT(ANN_R,0)")} | K9: {=_xll.FDS(E9,"FF_CASH_ST(ANN_R,0)")} | L9: =IFERROR(_xlfn.AGGREGATE(12,6,I52:L52),$L$64) | M9: =IF(ISNUMBER(I74),I74,"NA") | N9: =IF(AND(ISNUMBER(M9),ISNUMBER(L9),ISNUMBER(J9),ISNUMBER(H9)),IF(H9>0,M9/(1+(1-L9)*(J9/H9)),"NM"),"NA") | O9: {=_xll.FDS($E9,"FF_EBITDA_OPER(LTM_R,0)")} | P9: {=_xll.FDS($E9,"FE_ESTIMATE(EBITDA,MEAN,NTM4_ROLL,,NOW,,,'')")} | Q9: {=_xll.FDS(E9,"FF_EBIT_OPER(LTM_R,0)")} | R9: {=_xll.FDS(E9,"FE_ESTIMATE(EBIT,MEAN,NTM4_ROLL,,NOW,,,'')")} | S9: {=_xll.FDS(E9,"FF_SALES(LTM_R,0)")} | T9: {=_xll.FDS(E9,"FE_ESTIMATE(SALES,MEAN,NTM4_ROLL,,NOW,,,'')")} | U9: {=_xll.FDS(E9,"FF_FREE_CF(ANN_R_FCF,0)")} | V9: {=_xll.FDS(E9,"FE_ESTIMATE(FCF,MEAN,NTM4_ROLL,,NOW,,,'')")} | W9: =IF(AND(ISNUMBER($I9),ISNUMBER(O9)),IF(O9>0,$I9/O9,"NM"),"NA") | X9: =IF(AND(ISNUMBER($I9),ISNUMBER(P9)),IF(P9>0,$I9/P9,"NM"),"NA") | Y9: =IF(AND(ISNUMBER($I9),ISNUMBER(Q9)),IF(Q9>0,$I9/Q9,"NM"),"NA") | Z9: =IF(AND(ISNUMBER($I9),ISNUMBER(R9)),IF(R9>0,$I9/R9,"NM"),"NA") | AA9: =IF(AND(ISNUMBER($I9),ISNUMBER(S9)),IF(S9>0,$I9/S9,"NM"),"NA") | AB9: =IF(AND(ISNUMBER($I9),ISNUMBER(T9)),IF(T9>0,$I9/T9,"NM"),"NA") | AC9: =IF(AND(ISNUMBER($I9),ISNUMBER(U9)),IF(U9>0,$I9/U9,"NM"),"NA") | AD9: =IF(AND(ISNUMBER($I9),ISNUMBER(V9)),IF(V9>0,$I9/V9,"NM"),"NA")
C10: {=_xll.FDS($E10,"FG_COMPANY_NAME")} | E10: 4902-JP | F10: {=_xll.FDS($E10,"FG_PRICE(0)")} | G10: {=_xll.FDS($E10,"FREF_SHARES_COMPANY(0,,,,0,""LEGACY"")")} | H10: =IF(AND(ISNUMBER(F10),ISNUMBER(G10)),F10*G10,"NA") | I10: {=_xll.FDS($E10,"FG_ENT_VALUE(0)")} | J10: {=_xll.FDSR(E10,"FF_DEBT(ANN_R,0)")} | K10: {=_xll.FDS(E10,"FF_CASH_ST(ANN_R,0)")} | L10: =IFERROR(_xlfn.AGGREGATE(12,6,I53:L53),$L$64) | M10: =IF(ISNUMBER(I75),I75,"NA") | N10: =IF(AND(ISNUMBER(M10),ISNUMBER(L10),ISNUMBER(J10),ISNUMBER(H10)),IF(H10>0,M10/(1+(1-L10)*(J10/H10)),"NM"),"NA") | O10: {=_xll.FDS($E10,"FF_EBITDA_OPER(LTM_R,0)")} | P10: {=_xll.FDS($E10,"FE_ESTIMATE(EBITDA,MEAN,NTM4_ROLL,,NOW,,,'')")} | Q10: {=_xll.FDS(E10,"FF_EBIT_OPER(LTM_R,0)")} | R10: {=_xll.FDS(E10,"FE_ESTIMATE(EBIT,MEAN,NTM4_ROLL,,NOW,,,'')")} | S10: {=_xll.FDS(E10,"FF_SALES(LTM_R,0)")} | T10: {=_xll.FDS(E10,"FE_ESTIMATE(SALES,MEAN,NTM4_ROLL,,NOW,,,'')")} | U10: {=_xll.FDS(E10,"FF_FREE_CF(ANN_R_FCF,0)")} | V10: {=_xll.FDS(E10,"FE_ESTIMATE(FCF,MEAN,NTM4_ROLL,,NOW,,,'')")} | W10: =IF(AND(ISNUMBER($I10),ISNUMBER(O10)),IF(O10>0,$I10/O10,"NM"),"NA") | X10: =IF(AND(ISNUMBER($I10),ISNUMBER(P10)),IF(P10>0,$I10/P10,"NM"),"NA") | Y10: =IF(AND(ISNUMBER($I10),ISNUMBER(Q10)),IF(Q10>0,$I10/Q10,"NM"),"NA") | Z10: =IF(AND(ISNUMBER($I10),ISNUMBER(R10)),IF(R10>0,$I10/R10,"NM"),"NA") | AA10: =IF(AND(ISNUMBER($I10),ISNUMBER(S10)),IF(S10>0,$I10/S10,"NM"),"NA") | AB10: =IF(AND(ISNUMBER($I10),ISNUMBER(T10)),IF(T10>0,$I10/T10,"NM"),"NA") | AC10: =IF(AND(ISNUMBER($I10),ISNUMBER(U10)),IF(U10>0,$I10/U10,"NM"),"NA") | AD10: =IF(AND(ISNUMBER($I10),ISNUMBER(V10)),IF(V10>0,$I10/V10,"NM"),"NA")
C11: {=_xll.FDS($E11,"FG_COMPANY_NAME")} | E11: 6588-JP | F11: {=_xll.FDS($E11,"FG_PRICE(0)")} | G11: {=_xll.FDS($E11,"FREF_SHARES_COMPANY(0,,,,0,""LEGACY"")")} | H11: =IF(AND(ISNUMBER(F11),ISNUMBER(G11)),F11*G11,"NA") | I11: {=_xll.FDS($E11,"FG_ENT_VALUE(0)")} | J11: {=_xll.FDSR(E11,"FF_DEBT(ANN_R,0)")} | K11: {=_xll.FDS(E11,"FF_CASH_ST(ANN_R,0)")} | L11: =IFERROR(_xlfn.AGGREGATE(12,6,I54:L54),$L$64) | M11: =IF(ISNUMBER(I76),I76,"NA") | N11: =IF(AND(ISNUMBER(M11),ISNUMBER(L11),ISNUMBER(J11),ISNUMBER(H11)),IF(H11>0,M11/(1+(1-L11)*(J11/H11)),"NM"),"NA") | O11: {=_xll.FDS($E11,"FF_EBITDA_OPER(LTM_R,0)")} | P11: {=_xll.FDS($E11,"FE_ESTIMATE(EBITDA,MEAN,NTM4_ROLL,,NOW,,,'')")} | Q11: {=_xll.FDS(E11,"FF_EBIT_OPER(LTM_R,0)")} | R11: {=_xll.FDS(E11,"FE_ESTIMATE(EBIT,MEAN,NTM4_ROLL,,NOW,,,'')")} | S11: {=_xll.FDS(E11,"FF_SALES(LTM_R,0)")} | T11: {=_xll.FDS(E11,"FE_ESTIMATE(SALES,MEAN,NTM4_ROLL,,NOW,,,'')")} | U11: {=_xll.FDS(E11,"FF_FREE_CF(ANN_R_FCF,0)")} | V11: {=_xll.FDS(E11,"FE_ESTIMATE(FCF,MEAN,NTM4_ROLL,,NOW,,,'')")} | W11: =IF(AND(ISNUMBER($I11),ISNUMBER(O11)),IF(O11>0,$I11/O11,"NM"),"NA") | X11: =IF(AND(ISNUMBER($I11),ISNUMBER(P11)),IF(P11>0,$I11/P11,"NM"),"NA") | Y11: =IF(AND(ISNUMBER($I11),ISNUMBER(Q11)),IF(Q11>0,$I11/Q11,"NM"),"NA") | Z11: =IF(AND(ISNUMBER($I11),ISNUMBER(R11)),IF(R11>0,$I11/R11,"NM"),"NA") | AA11: =IF(AND(ISNUMBER($I11),ISNUMBER(S11)),IF(S11>0,$I11/S11,"NM"),"NA") | AB11: =IF(AND(ISNUMBER($I11),ISNUMBER(T11)),IF(T11>0,$I11/T11,"NM"),"NA") | AC11: =IF(AND(ISNUMBER($I11),ISNUMBER(U11)),IF(U11>0,$I11/U11,"NM"),"NA") | AD11: =IF(AND(ISNUMBER($I11),ISNUMBER(V11)),IF(V11>0,$I11/V11,"NM"),"NA")
C12: {=_xll.FDS($E12,"FG_COMPANY_NAME")} | E12: 6448-JP | F12: {=_xll.FDS($E12,"FG_PRICE(0)")} | G12: {=_xll.FDS($E12,"FREF_SHARES_COMPANY(0,,,,0,""LEGACY"")")} | H12: =IF(AND(ISNUMBER(F12),ISNUMBER(G12)),F12*G12,"NA") | I12: {=_xll.FDS($E12,"FG_ENT_VALUE(0)")} | J12: {=_xll.FDSR(E12,"FF_DEBT(ANN_R,0)")} | K12: {=_xll.FDS(E12,"FF_CASH_ST(ANN_R,0)")} | L12: =IFERROR(_xlfn.AGGREGATE(12,6,I55:L55),$L$64) | M12: =IF(ISNUMBER(I77),I77,"NA") | N12: =IF(AND(ISNUMBER(M12),ISNUMBER(L12),ISNUMBER(J12),ISNUMBER(H12)),IF(H12>0,M12/(1+(1-L12)*(J12/H12)),"NM"),"NA") | O12: {=_xll.FDS($E12,"FF_EBITDA_OPER(LTM_R,0)")} | P12: {=_xll.FDS($E12,"FE_ESTIMATE(EBITDA,MEAN,NTM4_ROLL,,NOW,,,'')")} | Q12: {=_xll.FDS(E12,"FF_EBIT_OPER(LTM_R,0)")} | R12: {=_xll.FDS(E12,"FE_ESTIMATE(EBIT,MEAN,NTM4_ROLL,,NOW,,,'')")} | S12: {=_xll.FDS(E12,"FF_SALES(LTM_R,0)")} | T12: {=_xll.FDS(E12,"FE_ESTIMATE(SALES,MEAN,NTM4_ROLL,,NOW,,,'')")} | U12: {=_xll.FDS(E12,"FF_FREE_CF(ANN_R_FCF,0)")} | V12: {=_xll.FDS(E12,"FE_ESTIMATE(FCF,MEAN,NTM4_ROLL,,NOW,,,'')")} | W12: =IF(AND(ISNUMBER($I12),ISNUMBER(O12)),IF(O12>0,$I12/O12,"NM"),"NA") | X12: =IF(AND(ISNUMBER($I12),ISNUMBER(P12)),IF(P12>0,$I12/P12,"NM"),"NA") | Y12: =IF(AND(ISNUMBER($I12),ISNUMBER(Q12)),IF(Q12>0,$I12/Q12,"NM"),"NA") | Z12: =IF(AND(ISNUMBER($I12),ISNUMBER(R12)),IF(R12>0,$I12/R12,"NM"),"NA") | AA12: =IF(AND(ISNUMBER($I12),ISNUMBER(S12)),IF(S12>0,$I12/S12,"NM"),"NA") | AB12: =IF(AND(ISNUMBER($I12),ISNUMBER(T12)),IF(T12>0,$I12/T12,"NM"),"NA") | AC12: =IF(AND(ISNUMBER($I12),ISNUMBER(U12)),IF(U12>0,$I12/U12,"NM"),"NA") | AD12: =IF(AND(ISNUMBER($I12),ISNUMBER(V12)),IF(V12>0,$I12/V12,"NM"),"NA")
C13: {=_xll.FDS($E13,"FG_COMPANY_NAME")} | E13: 6724-JP | F13: {=_xll.FDS($E13,"FG_PRICE(0)")} | G13: {=_xll.FDS($E13,"FREF_SHARES_COMPANY(0,,,,0,""LEGACY"")")} | H13: =IF(AND(ISNUMBER(F13),ISNUMBER(G13)),F13*G13,"NA") | I13: {=_xll.FDS($E13,"FG_ENT_VALUE(0)")} | J13: {=_xll.FDSR(E13,"FF_DEBT(ANN_R,0)")} | K13: {=_xll.FDS(E13,"FF_CASH_ST(ANN_R,0)")} | L13: =IFERROR(_xlfn.AGGREGATE(12,6,I56:L56),$L$64) | M13: =IF(ISNUMBER(I78),I78,"NA") | N13: =IF(AND(ISNUMBER(M13),ISNUMBER(L13),ISNUMBER(J13),ISNUMBER(H13)),IF(H13>0,M13/(1+(1-L13)*(J13/H13)),"NM"),"NA") | O13: {=_xll.FDS($E13,"FF_EBITDA_OPER(LTM_R,0)")} | P13: {=_xll.FDS($E13,"FE_ESTIMATE(EBITDA,MEAN,NTM4_ROLL,,NOW,,,'')")} | Q13: {=_xll.FDS(E13,"FF_EBIT_OPER(LTM_R,0)")} | R13: {=_xll.FDS(E13,"FE_ESTIMATE(EBIT,MEAN,NTM4_ROLL,,NOW,,,'')")} | S13: {=_xll.FDS(E13,"FF_SALES(LTM_R,0)")} | T13: {=_xll.FDS(E13,"FE_ESTIMATE(SALES,MEAN,NTM4_ROLL,,NOW,,,'')")} | U13: {=_xll.FDS(E13,"FF_FREE_CF(ANN_R_FCF,0)")} | V13: {=_xll.FDS(E13,"FE_ESTIMATE(FCF,MEAN,NTM4_ROLL,,NOW,,,'')")} | W13: =IF(AND(ISNUMBER($I13),ISNUMBER(O13)),IF(O13>0,$I13/O13,"NM"),"NA") | X13: =IF(AND(ISNUMBER($I13),ISNUMBER(P13)),IF(P13>0,$I13/P13,"NM"),"NA") | Y13: =IF(AND(ISNUMBER($I13),ISNUMBER(Q13)),IF(Q13>0,$I13/Q13,"NM"),"NA") | Z13: =IF(AND(ISNUMBER($I13),ISNUMBER(R13)),IF(R13>0,$I13/R13,"NM"),"NA") | AA13: =IF(AND(ISNUMBER($I13),ISNUMBER(S13)),IF(S13>0,$I13/S13,"NM"),"NA") | AB13: =IF(AND(ISNUMBER($I13),ISNUMBER(T13)),IF(T13>0,$I13/T13,"NM"),"NA") | AC13: =IF(AND(ISNUMBER($I13),ISNUMBER(U13)),IF(U13>0,$I13/U13,"NM"),"NA") | AD13: =IF(AND(ISNUMBER($I13),ISNUMBER(V13)),IF(V13>0,$I13/V13,"NM"),"NA")
C14: {=_xll.FDS($E14,"FG_COMPANY_NAME")} | E14: PBI | F14: {=_xll.FDS($E14,"FG_PRICE(0)")} | G14: {=_xll.FDS($E14,"FREF_SHARES_COMPANY(0,,,,0,""LEGACY"")")} | H14: =IF(AND(ISNUMBER(F14),ISNUMBER(G14)),F14*G14,"NA") | I14: {=_xll.FDS($E14,"FG_ENT_VALUE(0)")} | J14: {=_xll.FDSR(E14,"FF_DEBT(ANN_R,0)")} | K14: {=_xll.FDS(E14,"FF_CASH_ST(ANN_R,0)")} | L14: =IFERROR(_xlfn.AGGREGATE(12,6,I57:L57),$L$64) | M14: =IF(ISNUMBER(I79),I79,"NA") | N14: =IF(AND(ISNUMBER(M14),ISNUMBER(L14),ISNUMBER(J14),ISNUMBER(H14)),IF(H14>0,M14/(1+(1-L14)*(J14/H14)),"NM"),"NA") | O14: {=_xll.FDS($E14,"FF_EBITDA_OPER(LTM_R,0)")} | P14: {=_xll.FDS($E14,"FE_ESTIMATE(EBITDA,MEAN,NTM4_ROLL,,NOW,,,'')")} | Q14: {=_xll.FDS(E14,"FF_EBIT_OPER(LTM_R,0)")} | R14: {=_xll.FDS(E14,"FE_ESTIMATE(EBIT,MEAN,NTM4_ROLL,,NOW,,,'')")} | S14: {=_xll.FDS(E14,"FF_SALES(LTM_R,0)")} | T14: {=_xll.FDS(E14,"FE_ESTIMATE(SALES,MEAN,NTM4_ROLL,,NOW,,,'')")} | U14: {=_xll.FDS(E14,"FF_FREE_CF(ANN_R_FCF,0)")} | V14: {=_xll.FDS(E14,"FE_ESTIMATE(FCF,MEAN,NTM4_ROLL,,NOW,,,'')")} | W14: =IF(AND(ISNUMBER($I14),ISNUMBER(O14)),IF(O14>0,$I14/O14,"NM"),"NA") | X14: =IF(AND(ISNUMBER($I14),ISNUMBER(P14)),IF(P14>0,$I14/P14,"NM"),"NA") | Y14: =IF(AND(ISNUMBER($I14),ISNUMBER(Q14)),IF(Q14>0,$I14/Q14,"NM"),"NA") | Z14: =IF(AND(ISNUMBER($I14),ISNUMBER(R14)),IF(R14>0,$I14/R14,"NM"),"NA") | AA14: =IF(AND(ISNUMBER($I14),ISNUMBER(S14)),IF(S14>0,$I14/S14,"NM"),"NA") | AB14: =IF(AND(ISNUMBER($I14),ISNUMBER(T14)),IF(T14>0,$I14/T14,"NM"),"NA") | AC14: =IF(AND(ISNUMBER($I14),ISNUMBER(U14)),IF(U14>0,$I14/U14,"NM"),"NA") | AD14: =IF(AND(ISNUMBER($I14),ISNUMBER(V14)),IF(V14>0,$I14/V14,"NM"),"NA")
C15: {=_xll.FDS($E15,"FG_COMPANY_NAME")} | E15: DBD | F15: {=_xll.FDS($E15,"FG_PRICE(0)")} | G15: {=_xll.FDS($E15,"FREF_SHARES_COMPANY(0,,,,0,""LEGACY"")")} | H15: =IF(AND(ISNUMBER(F15),ISNUMBER(G15)),F15*G15,"NA") | I15: {=_xll.FDS($E15,"FG_ENT_VALUE(0)")} | J15: {=_xll.FDSR(E15,"FF_DEBT(ANN_R,0)")} | K15: {=_xll.FDS(E15,"FF_CASH_ST(ANN_R,0)")} | L15: =IFERROR(_xlfn.AGGREGATE(12,6,I58:L58),$L$64) | M15: =IF(ISNUMBER(I80),I80,"NA") | N15: =IF(AND(ISNUMBER(M15),ISNUMBER(L15),ISNUMBER(J15),ISNUMBER(H15)),IF(H15>0,M15/(1+(1-L15)*(J15/H15)),"NM"),"NA") | O15: {=_xll.FDS($E15,"FF_EBITDA_OPER(LTM_R,0)")} | P15: {=_xll.FDS($E15,"FE_ESTIMATE(EBITDA,MEAN,NTM4_ROLL,,NOW,,,'')")} | Q15: {=_xll.FDS(E15,"FF_EBIT_OPER(LTM_R,0)")} | R15: {=_xll.FDS(E15,"FE_ESTIMATE(EBIT,MEAN,NTM4_ROLL,,NOW,,,'')")} | S15: {=_xll.FDS(E15,"FF_SALES(LTM_R,0)")} | T15: {=_xll.FDS(E15,"FE_ESTIMATE(SALES,MEAN,NTM4_ROLL,,NOW,,,'')")} | U15: {=_xll.FDS(E15,"FF_FREE_CF(ANN_R_FCF,0)")} | V15: {=_xll.FDS(E15,"FE_ESTIMATE(FCF,MEAN,NTM4_ROLL,,NOW,,,'')")} | W15: =IF(AND(ISNUMBER($I15),ISNUMBER(O15)),IF(O15>0,$I15/O15,"NM"),"NA") | X15: =IF(AND(ISNUMBER($I15),ISNUMBER(P15)),IF(P15>0,$I15/P15,"NM"),"NA") | Y15: =IF(AND(ISNUMBER($I15),ISNUMBER(Q15)),IF(Q15>0,$I15/Q15,"NM"),"NA") | Z15: =IF(AND(ISNUMBER($I15),ISNUMBER(R15)),IF(R15>0,$I15/R15,"NM"),"NA") | AA15: =IF(AND(ISNUMBER($I15),ISNUMBER(S15)),IF(S15>0,$I15/S15,"NM"),"NA") | AB15: =IF(AND(ISNUMBER($I15),ISNUMBER(T15)),IF(T15>0,$I15/T15,"NM"),"NA") | AC15: =IF(AND(ISNUMBER($I15),ISNUMBER(U15)),IF(U15>0,$I15/U15,"NM"),"NA") | AD15: =IF(AND(ISNUMBER($I15),ISNUMBER(V15)),IF(V15>0,$I15/V15,"NM"),"NA")
C16: {=_xll.FDS($E16,"FG_COMPANY_NAME")} | E16: KODK | F16: {=_xll.FDS($E16,"FG_PRICE(0)")} | G16: {=_xll.FDS($E16,"FREF_SHARES_COMPANY(0,,,,0,""LEGACY"")")} | H16: =IF(AND(ISNUMBER(F16),ISNUMBER(G16)),F16*G16,"NA") | I16: {=_xll.FDS($E16,"FG_ENT_VALUE(0)")} | J16: {=_xll.FDSR(E16,"FF_DEBT(ANN_R,0)")} | K16: {=_xll.FDS(E16,"FF_CASH_ST(ANN_R,0)")} | L16: =IFERROR(_xlfn.AGGREGATE(12,6,I59:L59),$L$64) | M16: =IF(ISNUMBER(I81),I81,"NA") | N16: =IF(AND(ISNUMBER(M16),ISNUMBER(L16),ISNUMBER(J16),ISNUMBER(H16)),IF(H16>0,M16/(1+(1-L16)*(J16/H16)),"NM"),"NA") | O16: {=_xll.FDS($E16,"FF_EBITDA_OPER(LTM_R,0)")} | P16: {=_xll.FDS($E16,"FE_ESTIMATE(EBITDA,MEAN,NTM4_ROLL,,NOW,,,'')")} | Q16: {=_xll.FDS(E16,"FF_EBIT_OPER(LTM_R,0)")} | R16: {=_xll.FDS(E16,"FE_ESTIMATE(EBIT,MEAN,NTM4_ROLL,,NOW,,,'')")} | S16: {=_xll.FDS(E16,"FF_SALES(LTM_R,0)")} | T16: {=_xll.FDS(E16,"FE_ESTIMATE(SALES,MEAN,NTM4_ROLL,,NOW,,,'')")} | U16: {=_xll.FDS(E16,"FF_FREE_CF(ANN_R_FCF,0)")} | V16: {=_xll.FDS(E16,"FE_ESTIMATE(FCF,MEAN,NTM4_ROLL,,NOW,,,'')")} | W16: =IF(AND(ISNUMBER($I16),ISNUMBER(O16)),IF(O16>0,$I16/O16,"NM"),"NA") | X16: =IF(AND(ISNUMBER($I16),ISNUMBER(P16)),IF(P16>0,$I16/P16,"NM"),"NA") | Y16: =IF(AND(ISNUMBER($I16),ISNUMBER(Q16)),IF(Q16>0,$I16/Q16,"NM"),"NA") | Z16: =IF(AND(ISNUMBER($I16),ISNUMBER(R16)),IF(R16>0,$I16/R16,"NM"),"NA") | AA16: =IF(AND(ISNUMBER($I16),ISNUMBER(S16)),IF(S16>0,$I16/S16,"NM"),"NA") | AB16: =IF(AND(ISNUMBER($I16),ISNUMBER(T16)),IF(T16>0,$I16/T16,"NM"),"NA") | AC16: =IF(AND(ISNUMBER($I16),ISNUMBER(U16)),IF(U16>0,$I16/U16,"NM"),"NA") | AD16: =IF(AND(ISNUMBER($I16),ISNUMBER(V16)),IF(V16>0,$I16/V16,"NM"),"NA")
C17: {=_xll.FDS($E17,"FG_COMPANY_NAME")} | E17: CNDT | F17: {=_xll.FDS($E17,"FG_PRICE(0)")} | G17: {=_xll.FDS($E17,"FREF_SHARES_COMPANY(0,,,,0,""LEGACY"")")} | H17: =IF(AND(ISNUMBER(F17),ISNUMBER(G17)),F17*G17,"NA") | I17: {=_xll.FDS($E17,"FG_ENT_VALUE(0)")} | J17: {=_xll.FDSR(E17,"FF_DEBT(ANN_R,0)")} | K17: {=_xll.FDS(E17,"FF_CASH_ST(ANN_R,0)")} | L17: =IFERROR(_xlfn.AGGREGATE(12,6,I60:L60),$L$64) | M17: =IF(ISNUMBER(I82),I82,"NA") | N17: =IF(AND(ISNUMBER(M17),ISNUMBER(L17),ISNUMBER(J17),ISNUMBER(H17)),IF(H17>0,M17/(1+(1-L17)*(J17/H17)),"NM"),"NA") | O17: {=_xll.FDS($E17,"FF_EBITDA_OPER(LTM_R,0)")} | P17: {=_xll.FDS($E17,"FE_ESTIMATE(EBITDA,MEAN,NTM4_ROLL,,NOW,,,'')")} | Q17: {=_xll.FDS(E17,"FF_EBIT_OPER(LTM_R,0)")} | R17: {=_xll.FDS(E17,"FE_ESTIMATE(EBIT,MEAN,NTM4_ROLL,,NOW,,,'')")} | S17: {=_xll.FDS(E17,"FF_SALES(LTM_R,0)")} | T17: {=_xll.FDS(E17,"FE_ESTIMATE(SALES,MEAN,NTM4_ROLL,,NOW,,,'')")} | U17: {=_xll.FDS(E17,"FF_FREE_CF(ANN_R_FCF,0)")} | V17: {=_xll.FDS(E17,"FE_ESTIMATE(FCF,MEAN,NTM4_ROLL,,NOW,,,'')")} | W17: =IF(AND(ISNUMBER($I17),ISNUMBER(O17)),IF(O17>0,$I17/O17,"NM"),"NA") | X17: =IF(AND(ISNUMBER($I17),ISNUMBER(P17)),IF(P17>0,$I17/P17,"NM"),"NA") | Y17: =IF(AND(ISNUMBER($I17),ISNUMBER(Q17)),IF(Q17>0,$I17/Q17,"NM"),"NA") | Z17: =IF(AND(ISNUMBER($I17),ISNUMBER(R17)),IF(R17>0,$I17/R17,"NM"),"NA") | AA17: =IF(AND(ISNUMBER($I17),ISNUMBER(S17)),IF(S17>0,$I17/S17,"NM"),"NA") | AB17: =IF(AND(ISNUMBER($I17),ISNUMBER(T17)),IF(T17>0,$I17/T17,"NM"),"NA") | AC17: =IF(AND(ISNUMBER($I17),ISNUMBER(U17)),IF(U17>0,$I17/U17,"NM"),"NA") | AD17: =IF(AND(ISNUMBER($I17),ISNUMBER(V17)),IF(V17>0,$I17/V17,"NM"),"NA")
C18: {=_xll.FDS($E18,"FG_COMPANY_NAME")} | E18: QDT-FR | F18: {=_xll.FDS($E18,"FG_PRICE(0)")} | G18: {=_xll.FDS($E18,"FREF_SHARES_COMPANY(0,,,,0,""LEGACY"")")} | H18: =IF(AND(ISNUMBER(F18),ISNUMBER(G18)),F18*G18,"NA") | I18: {=_xll.FDS($E18,"FG_ENT_VALUE(0)")} | J18: {=_xll.FDSR(E18,"FF_DEBT(ANN_R,0)")} | K18: {=_xll.FDS(E18,"FF_CASH_ST(ANN_R,0)")} | L18: =IFERROR(_xlfn.AGGREGATE(12,6,I61:L61),$L$64) | M18: =IF(ISNUMBER(I83),I83,"NA") | N18: =IF(AND(ISNUMBER(M18),ISNUMBER(L18),ISNUMBER(J18),ISNUMBER(H18)),IF(H18>0,M18/(1+(1-L18)*(J18/H18)),"NM"),"NA") | O18: {=_xll.FDS($E18,"FF_EBITDA_OPER(LTM_R,0)")} | P18: {=_xll.FDS($E18,"FE_ESTIMATE(EBITDA,MEAN,NTM4_ROLL,,NOW,,,'')")} | Q18: {=_xll.FDS(E18,"FF_EBIT_OPER(LTM_R,0)")} | R18: {=_xll.FDS(E18,"FE_ESTIMATE(EBIT,MEAN,NTM4_ROLL,,NOW,,,'')")} | S18: {=_xll.FDS(E18,"FF_SALES(LTM_R,0)")} | T18: {=_xll.FDS(E18,"FE_ESTIMATE(SALES,MEAN,NTM4_ROLL,,NOW,,,'')")} | U18: {=_xll.FDS(E18,"FF_FREE_CF(ANN_R_FCF,0)")} | V18: {=_xll.FDS(E18,"FE_ESTIMATE(FCF,MEAN,NTM4_ROLL,,NOW,,,'')")} | W18: =IF(AND(ISNUMBER($I18),ISNUMBER(O18)),IF(O18>0,$I18/O18,"NM"),"NA") | X18: =IF(AND(ISNUMBER($I18),ISNUMBER(P18)),IF(P18>0,$I18/P18,"NM"),"NA") | Y18: =IF(AND(ISNUMBER($I18),ISNUMBER(Q18)),IF(Q18>0,$I18/Q18,"NM"),"NA") | Z18: =IF(AND(ISNUMBER($I18),ISNUMBER(R18)),IF(R18>0,$I18/R18,"NM"),"NA") | AA18: =IF(AND(ISNUMBER($I18),ISNUMBER(S18)),IF(S18>0,$I18/S18,"NM"),"NA") | AB18: =IF(AND(ISNUMBER($I18),ISNUMBER(T18)),IF(T18>0,$I18/T18,"NM"),"NA") | AC18: =IF(AND(ISNUMBER($I18),ISNUMBER(U18)),IF(U18>0,$I18/U18,"NM"),"NA") | AD18: =IF(AND(ISNUMBER($I18),ISNUMBER(V18)),IF(V18>0,$I18/V18,"NM"),"NA")
C20: {=_xll.FDS($E20,"FG_COMPANY_NAME")} | E20: XRX | F20: {=_xll.FDS($E20,"FG_PRICE(0)")} | G20: {=_xll.FDS($E20,"FREF_SHARES_COMPANY(0,,,,0,""LEGACY"")")} | H20: =IF(AND(ISNUMBER(F20),ISNUMBER(G20)),F20*G20,"NA") | I20: {=_xll.FDS($E20,"FG_ENT_VALUE(0)")} | J20: {=_xll.FDSR(E20,"FF_DEBT(ANN_R,0)")} | K20: {=_xll.FDS(E20,"FF_CASH_ST(ANN_R,0)")} | L20: =$L$66 | M20: =IF(ISNUMBER(I85),I85,"NA") | N20: N/A | O20: {=_xll.FDS($E20,"FF_EBITDA_OPER(LTM_R,0)")} | P20: {=_xll.FDS($E20,"FE_ESTIMATE(EBITDA,MEAN,NTM4_ROLL,,NOW,,,'')")} | Q20: {=_xll.FDS(E20,"FF_EBIT_OPER(LTM_R,0)")} | R20: {=_xll.FDS(E20,"FE_ESTIMATE(EBIT,MEAN,NTM4_ROLL,,NOW,,,'')")} | S20: {=_xll.FDS(E20,"FF_SALES(LTM_R,0)")} | T20: {=_xll.FDS(E20,"FE_ESTIMATE(SALES,MEAN,NTM4_ROLL,,NOW,,,'')")} | U20: {=_xll.FDS(E20,"FF_FREE_CF(ANN_R_FCF,0)")} | V20: {=_xll.FDS(E20,"FE_ESTIMATE(FCF,MEAN,NTM4_ROLL,,NOW,,,'')")} | W20: =IF(AND(ISNUMBER($I20),ISNUMBER(O20)),IF(O20>0,$I20/O20,"NM"),"NA") | X20: =IF(AND(ISNUMBER($I20),ISNUMBER(P20)),IF(P20>0,$I20/P20,"NM"),"NA") | Y20: =IF(AND(ISNUMBER($I20),ISNUMBER(Q20)),IF(Q20>0,$I20/Q20,"NM"),"NA") | Z20: =IF(AND(ISNUMBER($I20),ISNUMBER(R20)),IF(R20>0,$I20/R20,"NM"),"NA") | AA20: =IF(AND(ISNUMBER($I20),ISNUMBER(S20)),IF(S20>0,$I20/S20,"NM"),"NA") | AB20: =IF(AND(ISNUMBER($I20),ISNUMBER(T20)),IF(T20>0,$I20/T20,"NM"),"NA") | AC20: =IF(AND(ISNUMBER($I20),ISNUMBER(U20)),IF(U20>0,$I20/U20,"NM"),"NA") | AD20: =IF(AND(ISNUMBER($I20),ISNUMBER(V20)),IF(V20>0,$I20/V20,"NM"),"NA")
C22: Min | H22: =IF(COUNT(H7:H18)=0,"NM",_xlfn.AGGREGATE(5,6,H7:H18)) | I22: =IF(COUNT(I7:I18)=0,"NM",_xlfn.AGGREGATE(5,6,I7:I18)) | J22: =IF(COUNT(J7:J18)=0,"NM",_xlfn.AGGREGATE(5,6,J7:J18)) | K22: =IF(COUNT(K7:K18)=0,"NM",_xlfn.AGGREGATE(5,6,K7:K18)) | L22: =IF(COUNT(L7:L18)=0,"NM",_xlfn.AGGREGATE(5,6,L7:L18)) | M22: =IF(COUNT(M7:M18)=0,"NM",_xlfn.AGGREGATE(5,6,M7:M18)) | N22: =IF(COUNT(N7:N18)=0,"NM",_xlfn.AGGREGATE(5,6,N7:N18)) | O22: =IF(COUNT(O7:O18)=0,"NM",_xlfn.AGGREGATE(5,6,O7:O18)) | ... AD22: =IF(COUNT(AD7:AD18)=0,"NM",_xlfn.AGGREGATE(5,6,AD7:AD18))
C23: Q1 | H23: =IF(COUNT(H7:H18)=0,"NM",_xlfn.AGGREGATE(17,6,H7:H18,1)) | I23: =IF(COUNT(I7:I18)=0,"NM",_xlfn.AGGREGATE(17,6,I7:I18,1)) | J23: =IF(COUNT(J7:J18)=0,"NM",_xlfn.AGGREGATE(17,6,J7:J18,1)) | K23: =IF(COUNT(K7:K18)=0,"NM",_xlfn.AGGREGATE(17,6,K7:K18,1)) | L23: =IF(COUNT(L7:L18)=0,"NM",_xlfn.AGGREGATE(17,6,L7:L18,1)) | M23: =IF(COUNT(M7:M18)=0,"NM",_xlfn.AGGREGATE(17,6,M7:M18,1)) | N23: =IF(COUNT(N7:N18)=0,"NM",_xlfn.AGGREGATE(17,6,N7:N18,1)) | O23: =IF(COUNT(O7:O18)=0,"NM",_xlfn.AGGREGATE(17,6,O7:O18,1)) | ... AD23: =IF(COUNT(AD7:AD18)=0,"NM",_xlfn.AGGREGATE(17,6,AD7:AD18,1))
C24: Median | H24: =IF(COUNT(H7:H18)=0,"NM",_xlfn.AGGREGATE(12,6,H7:H18)) | I24: =IF(COUNT(I7:I18)=0,"NM",_xlfn.AGGREGATE(12,6,I7:I18)) | J24: =IF(COUNT(J7:J18)=0,"NM",_xlfn.AGGREGATE(12,6,J7:J18)) | K24: =IF(COUNT(K7:K18)=0,"NM",_xlfn.AGGREGATE(12,6,K7:K18)) | L24: =IF(COUNT(L7:L18)=0,"NM",_xlfn.AGGREGATE(12,6,L7:L18)) | M24: =IF(COUNT(M7:M18)=0,"NM",_xlfn.AGGREGATE(12,6,M7:M18)) | N24: =IF(COUNT(N7:N18)=0,"NM",_xlfn.AGGREGATE(12,6,N7:N18)) | O24: =IF(COUNT(O7:O18)=0,"NM",_xlfn.AGGREGATE(12,6,O7:O18)) | ... AD24: =IF(COUNT(AD7:AD18)=0,"NM",_xlfn.AGGREGATE(12,6,AD7:AD18))
C25: Mean | H25: =IF(COUNT(H7:H18)=0,"NM",_xlfn.AGGREGATE(1,6,H7:H18)) | I25: =IF(COUNT(I7:I18)=0,"NM",_xlfn.AGGREGATE(1,6,I7:I18)) | J25: =IF(COUNT(J7:J18)=0,"NM",_xlfn.AGGREGATE(1,6,J7:J18)) | K25: =IF(COUNT(K7:K18)=0,"NM",_xlfn.AGGREGATE(1,6,K7:K18)) | L25: =IF(COUNT(L7:L18)=0,"NM",_xlfn.AGGREGATE(1,6,L7:L18)) | M25: =IF(COUNT(M7:M18)=0,"NM",_xlfn.AGGREGATE(1,6,M7:M18)) | N25: =IF(COUNT(N7:N18)=0,"NM",_xlfn.AGGREGATE(1,6,N7:N18)) | O25: =IF(COUNT(O7:O18)=0,"NM",_xlfn.AGGREGATE(1,6,O7:O18)) | ... AD25: =IF(COUNT(AD7:AD18)=0,"NM",_xlfn.AGGREGATE(1,6,AD7:AD18))
C26: Q3 | H26: =IF(COUNT(H7:H18)=0,"NM",_xlfn.AGGREGATE(17,6,H7:H18,3)) | I26: =IF(COUNT(I7:I18)=0,"NM",_xlfn.AGGREGATE(17,6,I7:I18,3)) | J26: =IF(COUNT(J7:J18)=0,"NM",_xlfn.AGGREGATE(17,6,J7:J18,3)) | K26: =IF(COUNT(K7:K18)=0,"NM",_xlfn.AGGREGATE(17,6,K7:K18,3)) | L26: =IF(COUNT(L7:L18)=0,"NM",_xlfn.AGGREGATE(17,6,L7:L18,3)) | M26: =IF(COUNT(M7:M18)=0,"NM",_xlfn.AGGREGATE(17,6,M7:M18,3)) | N26: =IF(COUNT(N7:N18)=0,"NM",_xlfn.AGGREGATE(17,6,N7:N18,3)) | O26: =IF(COUNT(O7:O18)=0,"NM",_xlfn.AGGREGATE(17,6,O7:O18,3)) | ... AD26: =IF(COUNT(AD7:AD18)=0,"NM",_xlfn.AGGREGATE(17,6,AD7:AD18,3))
C27: Max | H27: =IF(COUNT(H7:H18)=0,"NM",_xlfn.AGGREGATE(4,6,H7:H18)) | I27: =IF(COUNT(I7:I18)=0,"NM",_xlfn.AGGREGATE(4,6,I7:I18)) | J27: =IF(COUNT(J7:J18)=0,"NM",_xlfn.AGGREGATE(4,6,J7:J18)) | K27: =IF(COUNT(K7:K18)=0,"NM",_xlfn.AGGREGATE(4,6,K7:K18)) | L27: =IF(COUNT(L7:L18)=0,"NM",_xlfn.AGGREGATE(4,6,L7:L18)) | M27: =IF(COUNT(M7:M18)=0,"NM",_xlfn.AGGREGATE(4,6,M7:M18)) | N27: =IF(COUNT(N7:N18)=0,"NM",_xlfn.AGGREGATE(4,6,N7:N18)) | O27: =IF(COUNT(O7:O18)=0,"NM",_xlfn.AGGREGATE(4,6,O7:O18)) | ... AD27: =IF(COUNT(AD7:AD18)=0,"NM",_xlfn.AGGREGATE(4,6,AD7:AD18))
C29: Implied Multiple - Low | V29: Q1 | W29: =IFERROR(_xlfn.XLOOKUP($V$29,$C$22:$C$27,W22:W27),"NM") | X29: =IFERROR(_xlfn.XLOOKUP($V$29,$C$22:$C$27,X22:X27),"NM") | Y29: =IFERROR(_xlfn.XLOOKUP($V$29,$C$22:$C$27,Y22:Y27),"NM") | Z29: =IFERROR(_xlfn.XLOOKUP($V$29,$C$22:$C$27,Z22:Z27),"NM") | AA29: =IFERROR(_xlfn.XLOOKUP($V$29,$C$22:$C$27,AA22:AA27),"NM") | AB29: =IFERROR(_xlfn.XLOOKUP($V$29,$C$22:$C$27,AB22:AB27),"NM") | AC29: =IFERROR(_xlfn.XLOOKUP($V$29,$C$22:$C$27,AC22:AC27),"NM") | AD29: =IFERROR(_xlfn.XLOOKUP($V$29,$C$22:$C$27,AD22:AD27),"NM")
C30: Implied Multiple - High | V30: Median | W30: =IFERROR(_xlfn.XLOOKUP($V$30,$C$22:$C$27,W22:W27),"NM") | X30: =IFERROR(_xlfn.XLOOKUP($V$30,$C$22:$C$27,X22:X27),"NM") | Y30: =IFERROR(_xlfn.XLOOKUP($V$30,$C$22:$C$27,Y22:Y27),"NM") | Z30: =IFERROR(_xlfn.XLOOKUP($V$30,$C$22:$C$27,Z22:Z27),"NM") | AA30: =IFERROR(_xlfn.XLOOKUP($V$30,$C$22:$C$27,AA22:AA27),"NM") | AB30: =IFERROR(_xlfn.XLOOKUP($V$30,$C$22:$C$27,AB22:AB27),"NM") | AC30: =IFERROR(_xlfn.XLOOKUP($V$30,$C$22:$C$27,AC22:AC27),"NM") | AD30: =IFERROR(_xlfn.XLOOKUP($V$30,$C$22:$C$27,AD22:AD27),"NM")
C32: Enterprise Value - Low | W32: =IFERROR(W29*O$20,"NM") | X32: =IFERROR(X29*P$20,"NM") | Y32: =IFERROR(Y29*Q$20,"NM") | Z32: =IFERROR(Z29*R$20,"NM") | AA32: =IFERROR(AA29*S$20,"NM") | AB32: =IFERROR(AB29*T$20,"NM") | AC32: =IFERROR(AC29*U$20,"NM") | AD32: =IFERROR(AD29*V$20,"NM")
C33: Enterprise Value - High | W33: =IFERROR(W30*O$20,"NM") | X33: =IFERROR(X30*P$20,"NM") | Y33: =IFERROR(Y30*Q$20,"NM") | Z33: =IFERROR(Z30*R$20,"NM") | AA33: =IFERROR(AA30*S$20,"NM") | AB33: =IFERROR(AB30*T$20,"NM") | AC33: =IFERROR(AC30*U$20,"NM") | AD33: =IFERROR(AD30*V$20,"NM")
C35: Equity Value - Low | W35: =IFERROR(W32-$J$20+$K$20,"NM") | X35: =IFERROR(X32-$J$20+$K$20,"NM") | Y35: =IFERROR(Y32-$J$20+$K$20,"NM") | Z35: =IFERROR(Z32-$J$20+$K$20,"NM") | AA35: =IFERROR(AA32-$J$20+$K$20,"NM") | AB35: =IFERROR(AB32-$J$20+$K$20,"NM") | AC35: =IFERROR(AC32-$J$20+$K$20,"NM") | AD35: =IFERROR(AD32-$J$20+$K$20,"NM")
C36: Equity Value - High | W36: =IFERROR(W33-$J$20+$K$20,"NM") | X36: =IFERROR(X33-$J$20+$K$20,"NM") | Y36: =IFERROR(Y33-$J$20+$K$20,"NM") | Z36: =IFERROR(Z33-$J$20+$K$20,"NM") | AA36: =IFERROR(AA33-$J$20+$K$20,"NM") | AB36: =IFERROR(AB33-$J$20+$K$20,"NM") | AC36: =IFERROR(AC33-$J$20+$K$20,"NM") | AD36: =IFERROR(AD33-$J$20+$K$20,"NM")
C38: Implied Price per Share - Low | W38: =IFERROR(W35/$G$20,"NM") | X38: =IFERROR(X35/$G$20,"NM") | Y38: =IFERROR(Y35/$G$20,"NM") | Z38: =IFERROR(Z35/$G$20,"NM") | AA38: =IFERROR(AA35/$G$20,"NM") | AB38: =IFERROR(AB35/$G$20,"NM") | AC38: =IFERROR(AC35/$G$20,"NM") | AD38: =IFERROR(AD35/$G$20,"NM")
C39: Implied Price per Share - High | W39: =IFERROR(W36/$G$20,"NM") | X39: =IFERROR(X36/$G$20,"NM") | Y39: =IFERROR(Y36/$G$20,"NM") | Z39: =IFERROR(Z36/$G$20,"NM") | AA39: =IFERROR(AA36/$G$20,"NM") | AB39: =IFERROR(AB36/$G$20,"NM") | AC39: =IFERROR(AC36/$G$20,"NM") | AD39: =IFERROR(AD36/$G$20,"NM")
C41: Implied Upside (Downside) - Low | W41: =IFERROR((W38-$F$20)/$F$20,"NM") | X41: =IFERROR((X38-$F$20)/$F$20,"NM") | Y41: =IFERROR((Y38-$F$20)/$F$20,"NM") | Z41: =IFERROR((Z38-$F$20)/$F$20,"NM") | AA41: =IFERROR((AA38-$F$20)/$F$20,"NM") | AB41: =IFERROR((AB38-$F$20)/$F$20,"NM") | AC41: =IFERROR((AC38-$F$20)/$F$20,"NM") | AD41: =IFERROR((AD38-$F$20)/$F$20,"NM")
C42: Implied Upside (Downside) - High | W42: =IFERROR((W39-$F$20)/$F$20,"NM") | X42: =IFERROR((X39-$F$20)/$F$20,"NM") | Y42: =IFERROR((Y39-$F$20)/$F$20,"NM") | Z42: =IFERROR((Z39-$F$20)/$F$20,"NM") | AA42: =IFERROR((AA39-$F$20)/$F$20,"NM") | AB42: =IFERROR((AB39-$F$20)/$F$20,"NM") | AC42: =IFERROR((AC39-$F$20)/$F$20,"NM") | AD42: =IFERROR((AD39-$F$20)/$F$20,"NM")
B43: x
C44: Note: Japanese comps report in JPY - size columns (price, market cap, EV, debt, cash, EBITDA $) are local currency, multiples are currency-neutral. Equity value deducts total debt only; Xerox's $180mm Series A preferred is not netted here (see Precedent Transactions tab).
B48: x | C48: Tax Calculation
C49: Ticker | F49: 2020 | G49: 2021 | H49: 2022 | I49: 2023 | J49: 2024 | K49: 2025 | L49: Latest Quarter
C50: =E7 | F50: {=_xll.FDSR($C50,"FF_INC_TAX(ANN_R,01/01/2020,12/31/2020)")/_xll.FDSR($C50,"FF_PTX_INC(ANN_R,01/01/2020,12/31/2020)")} | G50: {=_xll.FDSR($C50,"FF_INC_TAX(ANN_R,01/01/2021,12/31/2021)")/_xll.FDSR($C50,"FF_PTX_INC(ANN_R,01/01/2021,12/31/2021)")} | H50: {=_xll.FDSR($C50,"FF_INC_TAX(ANN_R,01/01/2022,12/31/2022)")/_xll.FDSR($C50,"FF_PTX_INC(ANN_R,01/01/2022,12/31/2022)")} | I50: {=_xll.FDSR($C50,"FF_INC_TAX(ANN_R,01/01/2023,12/31/2023)")/_xll.FDSR($C50,"FF_PTX_INC(ANN_R,01/01/2023,12/31/2023)")} | J50: {=_xll.FDSR($C50,"FF_INC_TAX(ANN_R,01/01/2024,12/31/2024)")/_xll.FDSR($C50,"FF_PTX_INC(ANN_R,01/01/2024,12/31/2024)")} | K50: {=_xll.FDSR($C50,"FF_INC_TAX(ANN_R,01/01/2025,12/31/2025)")/_xll.FDSR($C50,"FF_PTX_INC(ANN_R,01/01/2025,12/31/2025)")} | L50: {=_xll.FDSR($C50,"FF_INC_TAX(QTR_R,0)")/_xll.FDSR($C50,"FF_PTX_INC(QTR_R,0)")}
C51: =E8 | F51: {=_xll.FDSR($C51,"FF_INC_TAX(ANN_R,01/01/2020,12/31/2020)")/_xll.FDSR($C51,"FF_PTX_INC(ANN_R,01/01/2020,12/31/2020)")} | G51: {=_xll.FDSR($C51,"FF_INC_TAX(ANN_R,01/01/2021,12/31/2021)")/_xll.FDSR($C51,"FF_PTX_INC(ANN_R,01/01/2021,12/31/2021)")} | H51: {=_xll.FDSR($C51,"FF_INC_TAX(ANN_R,01/01/2022,12/31/2022)")/_xll.FDSR($C51,"FF_PTX_INC(ANN_R,01/01/2022,12/31/2022)")} | I51: {=_xll.FDSR($C51,"FF_INC_TAX(ANN_R,01/01/2023,12/31/2023)")/_xll.FDSR($C51,"FF_PTX_INC(ANN_R,01/01/2023,12/31/2023)")} | J51: {=_xll.FDSR($C51,"FF_INC_TAX(ANN_R,01/01/2024,12/31/2024)")/_xll.FDSR($C51,"FF_PTX_INC(ANN_R,01/01/2024,12/31/2024)")} | K51: {=_xll.FDSR($C51,"FF_INC_TAX(ANN_R,01/01/2025,12/31/2025)")/_xll.FDSR($C51,"FF_PTX_INC(ANN_R,01/01/2025,12/31/2025)")} | L51: {=_xll.FDSR($C51,"FF_INC_TAX(QTR_R,0)")/_xll.FDSR($C51,"FF_PTX_INC(QTR_R,0)")}
C52: =E9 | F52: {=_xll.FDSR($C52,"FF_INC_TAX(ANN_R,01/01/2020,12/31/2020)")/_xll.FDSR($C52,"FF_PTX_INC(ANN_R,01/01/2020,12/31/2020)")} | G52: {=_xll.FDSR($C52,"FF_INC_TAX(ANN_R,01/01/2021,12/31/2021)")/_xll.FDSR($C52,"FF_PTX_INC(ANN_R,01/01/2021,12/31/2021)")} | H52: {=_xll.FDSR($C52,"FF_INC_TAX(ANN_R,01/01/2022,12/31/2022)")/_xll.FDSR($C52,"FF_PTX_INC(ANN_R,01/01/2022,12/31/2022)")} | I52: {=_xll.FDSR($C52,"FF_INC_TAX(ANN_R,01/01/2023,12/31/2023)")/_xll.FDSR($C52,"FF_PTX_INC(ANN_R,01/01/2023,12/31/2023)")} | J52: {=_xll.FDSR($C52,"FF_INC_TAX(ANN_R,01/01/2024,12/31/2024)")/_xll.FDSR($C52,"FF_PTX_INC(ANN_R,01/01/2024,12/31/2024)")} | K52: {=_xll.FDSR($C52,"FF_INC_TAX(ANN_R,01/01/2025,12/31/2025)")/_xll.FDSR($C52,"FF_PTX_INC(ANN_R,01/01/2025,12/31/2025)")} | L52: {=_xll.FDSR($C52,"FF_INC_TAX(QTR_R,0)")/_xll.FDSR($C52,"FF_PTX_INC(QTR_R,0)")}
C53: =E10 | F53: {=_xll.FDSR($C53,"FF_INC_TAX(ANN_R,01/01/2020,12/31/2020)")/_xll.FDSR($C53,"FF_PTX_INC(ANN_R,01/01/2020,12/31/2020)")} | G53: {=_xll.FDSR($C53,"FF_INC_TAX(ANN_R,01/01/2021,12/31/2021)")/_xll.FDSR($C53,"FF_PTX_INC(ANN_R,01/01/2021,12/31/2021)")} | H53: {=_xll.FDSR($C53,"FF_INC_TAX(ANN_R,01/01/2022,12/31/2022)")/_xll.FDSR($C53,"FF_PTX_INC(ANN_R,01/01/2022,12/31/2022)")} | I53: {=_xll.FDSR($C53,"FF_INC_TAX(ANN_R,01/01/2023,12/31/2023)")/_xll.FDSR($C53,"FF_PTX_INC(ANN_R,01/01/2023,12/31/2023)")} | J53: {=_xll.FDSR($C53,"FF_INC_TAX(ANN_R,01/01/2024,12/31/2024)")/_xll.FDSR($C53,"FF_PTX_INC(ANN_R,01/01/2024,12/31/2024)")} | K53: {=_xll.FDSR($C53,"FF_INC_TAX(ANN_R,01/01/2025,12/31/2025)")/_xll.FDSR($C53,"FF_PTX_INC(ANN_R,01/01/2025,12/31/2025)")} | L53: {=_xll.FDSR($C53,"FF_INC_TAX(QTR_R,0)")/_xll.FDSR($C53,"FF_PTX_INC(QTR_R,0)")}
C54: =E11 | F54: {=_xll.FDSR($C54,"FF_INC_TAX(ANN_R,01/01/2020,12/31/2020)")/_xll.FDSR($C54,"FF_PTX_INC(ANN_R,01/01/2020,12/31/2020)")} | G54: {=_xll.FDSR($C54,"FF_INC_TAX(ANN_R,01/01/2021,12/31/2021)")/_xll.FDSR($C54,"FF_PTX_INC(ANN_R,01/01/2021,12/31/2021)")} | H54: {=_xll.FDSR($C54,"FF_INC_TAX(ANN_R,01/01/2022,12/31/2022)")/_xll.FDSR($C54,"FF_PTX_INC(ANN_R,01/01/2022,12/31/2022)")} | I54: {=_xll.FDSR($C54,"FF_INC_TAX(ANN_R,01/01/2023,12/31/2023)")/_xll.FDSR($C54,"FF_PTX_INC(ANN_R,01/01/2023,12/31/2023)")} | J54: {=_xll.FDSR($C54,"FF_INC_TAX(ANN_R,01/01/2024,12/31/2024)")/_xll.FDSR($C54,"FF_PTX_INC(ANN_R,01/01/2024,12/31/2024)")} | K54: {=_xll.FDSR($C54,"FF_INC_TAX(ANN_R,01/01/2025,12/31/2025)")/_xll.FDSR($C54,"FF_PTX_INC(ANN_R,01/01/2025,12/31/2025)")} | L54: {=_xll.FDSR($C54,"FF_INC_TAX(QTR_R,0)")/_xll.FDSR($C54,"FF_PTX_INC(QTR_R,0)")}
C55: =E12 | F55: {=_xll.FDSR($C55,"FF_INC_TAX(ANN_R,01/01/2020,12/31/2020)")/_xll.FDSR($C55,"FF_PTX_INC(ANN_R,01/01/2020,12/31/2020)")} | G55: {=_xll.FDSR($C55,"FF_INC_TAX(ANN_R,01/01/2021,12/31/2021)")/_xll.FDSR($C55,"FF_PTX_INC(ANN_R,01/01/2021,12/31/2021)")} | H55: {=_xll.FDSR($C55,"FF_INC_TAX(ANN_R,01/01/2022,12/31/2022)")/_xll.FDSR($C55,"FF_PTX_INC(ANN_R,01/01/2022,12/31/2022)")} | I55: {=_xll.FDSR($C55,"FF_INC_TAX(ANN_R,01/01/2023,12/31/2023)")/_xll.FDSR($C55,"FF_PTX_INC(ANN_R,01/01/2023,12/31/2023)")} | J55: {=_xll.FDSR($C55,"FF_INC_TAX(ANN_R,01/01/2024,12/31/2024)")/_xll.FDSR($C55,"FF_PTX_INC(ANN_R,01/01/2024,12/31/2024)")} | K55: {=_xll.FDSR($C55,"FF_INC_TAX(ANN_R,01/01/2025,12/31/2025)")/_xll.FDSR($C55,"FF_PTX_INC(ANN_R,01/01/2025,12/31/2025)")} | L55: {=_xll.FDSR($C55,"FF_INC_TAX(QTR_R,0)")/_xll.FDSR($C55,"FF_PTX_INC(QTR_R,0)")}
C56: =E13 | F56: {=_xll.FDSR($C56,"FF_INC_TAX(ANN_R,01/01/2020,12/31/2020)")/_xll.FDSR($C56,"FF_PTX_INC(ANN_R,01/01/2020,12/31/2020)")} | G56: {=_xll.FDSR($C56,"FF_INC_TAX(ANN_R,01/01/2021,12/31/2021)")/_xll.FDSR($C56,"FF_PTX_INC(ANN_R,01/01/2021,12/31/2021)")} | H56: {=_xll.FDSR($C56,"FF_INC_TAX(ANN_R,01/01/2022,12/31/2022)")/_xll.FDSR($C56,"FF_PTX_INC(ANN_R,01/01/2022,12/31/2022)")} | I56: {=_xll.FDSR($C56,"FF_INC_TAX(ANN_R,01/01/2023,12/31/2023)")/_xll.FDSR($C56,"FF_PTX_INC(ANN_R,01/01/2023,12/31/2023)")} | J56: {=_xll.FDSR($C56,"FF_INC_TAX(ANN_R,01/01/2024,12/31/2024)")/_xll.FDSR($C56,"FF_PTX_INC(ANN_R,01/01/2024,12/31/2024)")} | K56: {=_xll.FDSR($C56,"FF_INC_TAX(ANN_R,01/01/2025,12/31/2025)")/_xll.FDSR($C56,"FF_PTX_INC(ANN_R,01/01/2025,12/31/2025)")} | L56: {=_xll.FDSR($C56,"FF_INC_TAX(QTR_R,0)")/_xll.FDSR($C56,"FF_PTX_INC(QTR_R,0)")}
C57: =E14 | F57: {=_xll.FDSR($C57,"FF_INC_TAX(ANN_R,01/01/2020,12/31/2020)")/_xll.FDSR($C57,"FF_PTX_INC(ANN_R,01/01/2020,12/31/2020)")} | G57: {=_xll.FDSR($C57,"FF_INC_TAX(ANN_R,01/01/2021,12/31/2021)")/_xll.FDSR($C57,"FF_PTX_INC(ANN_R,01/01/2021,12/31/2021)")} | H57: {=_xll.FDSR($C57,"FF_INC_TAX(ANN_R,01/01/2022,12/31/2022)")/_xll.FDSR($C57,"FF_PTX_INC(ANN_R,01/01/2022,12/31/2022)")} | I57: {=_xll.FDSR($C57,"FF_INC_TAX(ANN_R,01/01/2023,12/31/2023)")/_xll.FDSR($C57,"FF_PTX_INC(ANN_R,01/01/2023,12/31/2023)")} | J57: {=_xll.FDSR($C57,"FF_INC_TAX(ANN_R,01/01/2024,12/31/2024)")/_xll.FDSR($C57,"FF_PTX_INC(ANN_R,01/01/2024,12/31/2024)")} | K57: {=_xll.FDSR($C57,"FF_INC_TAX(ANN_R,01/01/2025,12/31/2025)")/_xll.FDSR($C57,"FF_PTX_INC(ANN_R,01/01/2025,12/31/2025)")} | L57: {=_xll.FDSR($C57,"FF_INC_TAX(QTR_R,0)")/_xll.FDSR($C57,"FF_PTX_INC(QTR_R,0)")}
